Workbook
Name A_D: INDEX(#REF!,MATCH(#REF!,#REF!,0))
Name AA: INDEX(#REF!,MATCH(#REF!,#REF!,0))
Name AB: INDEX(#REF!,MATCH(#REF!,#REF!,0))
Name AC: INDEX(#REF!,MATCH(#REF!,#REF!,0))
Name AE: INDEX(#REF!,MATCH(#REF!,#REF!,0))
Name AF: INDEX(#REF!,MATCH(#REF!,#REF!,0))
Name AG: INDEX(#REF!,MATCH(#REF!,#REF!,0))
Name AH: INDEX(#REF!,MATCH(#REF!,#REF!,0))
Name AI: INDEX(#REF!,MATCH(#REF!,#REF!,0))
Name AJ: INDEX(#REF!,MATCH(#REF!,#REF!,0))
Name AK: INDEX(#REF!,MATCH(#REF!,#REF!,0))
Name AL: INDEX(#REF!,MATCH(#REF!,#REF!,0))
Name AM: INDEX(#REF!,MATCH(#REF!,#REF!,0))
Name BA: INDEX(#REF!,MATCH(#REF!,#REF!,0))
Name BB: INDEX(#REF!,MATCH(#REF!,#REF!,0))
Name BC: INDEX(#REF!,MATCH(#REF!,#REF!,0))
Name BD: INDEX(#REF!,MATCH(#REF!,#REF!,0))
Name BE: INDEX(#REF!,MATCH(#REF!,#REF!,0))
Name BF: INDEX(#REF!,MATCH(#REF!,#REF!,0))
Name BG: INDEX(#REF!,MATCH(#REF!,#REF!,0))
Name BH: INDEX(#REF!,MATCH(#REF!,#REF!,0))
Name BI: INDEX(#REF!,MATCH(#REF!,#REF!,0))
Name BJ: INDEX(#REF!,MATCH(#REF!,#REF!,0))
Name BK: INDEX(#REF!,MATCH(#REF!,#REF!,0))
Name BL: INDEX(#REF!,MATCH(#REF!,#REF!,0))
Name BM: INDEX(#REF!,MATCH(#REF!,#REF!,0))
Name CA: INDEX(#REF!,MATCH(#REF!,#REF!,0))
Name CB: INDEX(#REF!,MATCH(#REF!,#REF!,0))
Name CC: INDEX(#REF!,MATCH(#REF!,#REF!,0))
Name CD: INDEX(#REF!,MATCH(#REF!,#REF!,0))
Name CE: INDEX(#REF!,MATCH(#REF!,#REF!,0))
Name CF: INDEX(#REF!,MATCH(#REF!,#REF!,0))
Name CG: INDEX(#REF!,MATCH(#REF!,#REF!,0))
Name CH: INDEX(#REF!,MATCH(#REF!,#REF!,0))
Name CI: INDEX(#REF!,MATCH(#REF!,#REF!,0))
Name CJ: INDEX(#REF!,MATCH(#REF!,#REF!,0))
Name CK: INDEX(#REF!,MATCH(#REF!,#REF!,0))
Name CL: INDEX(#REF!,MATCH(#REF!,#REF!,0))
Name CM: INDEX(#REF!,MATCH(#REF!,#REF!,0))
Name D_D: INDEX(#REF!,MATCH(#REF!,#REF!,0))
Name DA: INDEX(#REF!,MATCH(#REF!,#REF!,0))
Name DB: INDEX(#REF!,MATCH(#REF!,#REF!,0))
Name DC: INDEX(#REF!,MATCH(#REF!,#REF!,0))
Name DE: INDEX(#REF!,MATCH(#REF!,#REF!,0))
Name DF: INDEX(#REF!,MATCH(#REF!,#REF!,0))
Name DG: INDEX(#REF!,MATCH(#REF!,#REF!,0))
Name DH: INDEX(#REF!,MATCH(#REF!,#REF!,0))
Name DI: INDEX(#REF!,MATCH(#REF!,#REF!,0))
Name DJ: INDEX(#REF!,MATCH(#REF!,#REF!,0))
Name DK: INDEX(#REF!,MATCH(#REF!,#REF!,0))
Name DL: INDEX(#REF!,MATCH(#REF!,#REF!,0))
Name DM: INDEX(#REF!,MATCH(#REF!,#REF!,0))
Name DPR: #REF!&#REF!&#REF!&#REF!&#REF!&#REF!&#REF!&#REF!&#REF!&#REF!
Name EA: INDEX(#REF!,MATCH(#REF!,#REF!,0))
Name EB: INDEX(#REF!,MATCH(#REF!,#REF!,0))
Name EC: INDEX(#REF!,MATCH(#REF!,#REF!,0))
Name ED: INDEX(#REF!,MATCH(#REF!,#REF!,0))
Name EE: INDEX(#REF!,MATCH(#REF!,#REF!,0))
Name EF: INDEX(#REF!,MATCH(#REF!,#REF!,0))
Name EG: INDEX(#REF!,MATCH(#REF!,#REF!,0))

Sheet 400kV Summery
C3: TB-507 | D3: DAILY PROGRESS REPORT | M3: =NOW()-1 -> 46113.496
A4: CONTRACTUAL START DATE: | C4: 45632 | D4: 400kV D/C Fatehgarh IV (Section-2)PS - Bhinmal (PG) Transmission Line
A5: CONTRACTUAL FINISH DATE: | C5: 46178
A6: REPORTING DATE | D6: Client Name : RAJASTHAN IV A POWER TRANSMISSION LTD
A7: TOTAL DAYS | D7: NOA Ref No(Supply): RIVA/LOA-KEC(SUP)/AUG 24/405
A8: COMP. DAYS | D8: NOA Ref No(Service): RIVA/LOA-KEC(SER)/AUG 24/406
A9: Progress Summary | M9: =M3 -> 46113.496
A10: Sl No. | B10: Activity | C10: LOA Quantity | D10: Estimated Line Quantity | E10: Cumm. Progress till Last Month | F10: Plan For MAR'25 | G10: Progress in MAR'25 | H10: WIP | I10: Today's Progress | J10: Cumulative progress till date | K10: Balance | L10: ="Gangs working "&CHAR(10)&TEXT(M3,"mmm-yy") -> Gangs working Apr-26 | M10: Remarks
A11: A.i | B11: Route Alignment (Kms) | C11: 184 | D11: 188.503 | J11: 188.503 | K11: =D11-J11 -> 0 | M11: In the Scope of Rajasthan IV A Power Transmission Ltd
A12: ii | B12: Detailed Survey (Kms) | C12: 184 | D12: 188.678 | E12: 188.678 | G12: =D12-E12 -> 0 | J12: 188.678 | K12: =D12-J12 -> 0
A13: iii | B13: Check Survey (Kms) | C13: 184 | D13: 188.678 | E13: 188.678 | J13: 188.678 | K13: =D13-J13 -> 0 | L13: 1 | M13: 172 KM Approved
A14: B. | B14: Soil Investigation (Nos) | C14: 73 | D14: 73 | E14: 73 | J14: 73 | K14: 0
A15: C. | B15: Foundation (Nos) | C15: 508 | D15: 513 | E15: 276 | F15: 0 | G15: 0 | H15: 2 | I15: 0 | J15: =SUM(E15+G15) -> 276 | K15: =D15-J15 -> 237 | L15: 2 | M15: 47/2 1Pit RCC Done, 2 Pit RCC WIP ROW Since 28.09.25
A16: D. | B16: Earthing (Nos) | C16: 508 | D16: 513 | E16: 260 | F16: 0 | G16: 0 | I16: 0 | J16: =SUM(E16+G16) -> 260 | K16: =D16-J16 -> 253
A17: E. | B17: Tower Erection (Nos) | C17: 508 | D17: 513 | E17: 188 | F17: 0 | G17: 0 | H17: 0 | I17: 0 | J17: =SUM(E17+G17) -> 188 | K17: =D17-J17 -> 325 | L17: 0
A18: F. | B18: Tack Welding (Nos) | C18: 508 | D18: 513 | E18: 61 | G18: 2 | H18: 1 | I18: 2 | J18: =SUM(E18+G18) -> 63 | K18: =D18-J18 -> 450 | L18: 1
A19: G. | B19: Stringing (Kms) | K19: =D19-J19 -> 0
A20: i | B20: Paying Out (Kms) | C20: 184 | D20: 188.678 | E20: 8.999 | F20: 0 | G20: 0 | J20: =E20+G20 -> 8.999 | K20: =D20-J20 -> 179.679 | M20: 1
A21: ii | B21: Final Sag (Kms) | C21: 184 | D21: 188.678 | E21: 7.339 | F21: 0 | G21: 0 | J21: =E21+G21 -> 7.339 | K21: =D21-J21 -> 181.339
A22: I. | B22: OPGW Stringing (Kms) | C22: 184 | D22: 188.678 | E22: 0 | J22: =E22+G22 -> 0 | K22: =D22-J22 -> 188.678
K23: =D23-J23 -> 0
A24: Sl No. | B24: Crossing Span | C24: Type | D24: Description | G24: Proposal Status | J24: Remarks
A25: A | B25: Power Line Crossings
A26: 1 | B26: AP2/1 - AP3 | C26: 400KV D/C Fatehgarh III Fatehgarh IV T/L | D26: Apraava Energy PVT. LTD. | E26: 10.07.2025 | F26: Subject to Approval of CS | G26: Survey Report Submitted to Apraava Engg,
A27: 2 | B27: AP4 - AP5 | C27: 220 KV S/C PSS To FS IV Ampin CKT-1. | D27: RRVPNL | E27: 10.07.2025 | F27: Subject to Approval of CS | G27: Survey Report Submitted to Apraava Engg,
A28: 3 | B28: AP5D - AP5E | C28: 132 KV S/C Sheo to Undoo Line. | D28: RRVPNL | E28: 10.07.2025 | F28: Subject to Approval of CS | G28: Survey Report Submitted to Apraava Engg,
A29: 4 | B29: AP25 - 26 | C29: 400kV D/C Rajwest to Jodhpur TL & Rajwest to Pancpadra | D29: RRVPNL | E29: 07.07.2025 | F29: Crossing Proposal Hardcopy submitted to Apraava | G29: Proposal Submitted to Apraava
A30: 5 | B30: A 27- A 27A | C30: 220kV S/C BALOTARA TO GIRAL T/ Lin | D30: RRVPNL | F30: Submitted on 24.05.25 | G30: AE will forward proposal for NOC to Chief Zonal by 10.10.2025
A31: 6 | B31: AP50-AP51 | C31: 220kV S/C BALOTARA TO BARMER T/ Line | D31: RRVPNL | F31: Submitted on 24.05.25
A32: 7 | B32: AP58-AP59 | C32: 132kV S/C BALOTARA TO BARMER T/ Line | D32: RRVPNL | F32: Submitted on 24.05.25
A33: 8 | B33: AP111-AP112 | C33: 132kV S/C KHOOKHA TO JIWANA T/ Line | D33: RRVPNL | F33: Submitted on 24.05.25 | G33: NOC/Approval Given on 28.08.2025
A34: 9 | B34: AP144-AP145 | C34: 132kV S/C BHINMAL TO DASPUR T/ Line | D34: RRVPNL | F34: Submitted on 24.05.25
A35: 10 | B35: AP152-AP153 | C35: 220kV D/C SAYLA TO BHINMAL,PGCIL (RRVPNL) T/ Line | D35: RRVPNL | F35: Submitted on 24.05.25
A36: 11 | B36: AP154-AP155 | C36: 400kV D/C BARMER-II TO BHINMAL T/ Line | D36: RRVPNL | E36: 07.07.2025 | F36: Crossing Proposal Hardcopy under submission | G36: Proposal submited by KEC.
A37: B | B37: River Crossing
A38: 1 | B38: AP 94 TO AP 95 | C38: LUNI River | D38: River Crossing
A39: 2 | B39: 133/0 TO 133/4 | C39: SUKRI River | D39: River Crossing
A40: 3 | B40: 137/0 TO138/0 | C40: BANDI RIVER | D40: River Crossing
A41: C | B41: Railway Crossings
A42: 1 | B42: AP 46 TO AP 47 | C42: Rly | D42: Barmer-Jodhpur Single Track | G42: Partial payment done on 25th Sep. Further proceedings of approval are under process.
A43: =A42+1 -> 2 | B43: AP 150 AP 151 | C43: Rly | D43: Jalore-Bhinmal Single Track
A44: D. | B44: Road Crossing
A45: 1 | B45: AP 53-AP-54 | C45: Baytu (Balotra Road) -Chava (Barmer Road) | D45: PWD | F45: NOC pending
A46: 2 | B46: AP 71 - 71/1 | C46: Barmer-Sindhari | D46: PWD
A47: 3 | B47: AP 92- AP 93 | C47: Sindhari-Gudamalani | D47: PWD | E47: NOC/Approved on21.08.2025
A48: 4 | B48: 130/1 - AP 131 | C48: Bagoda-Sayla | D48: PWD
A49: 5 | B49: AP 147/9 - AP 148 | C49: Siyawat/Daspa- Bhinmal | D49: PWD
A50: 6 | B50: AP 04 - AP 05 | C50: Re-Route | F50: Detail survey submitted by KEC.
A51: E. | B51: Oil Pipe Crossing
A52: 1 | B52: 29/0-29/1 | D52: VEDANTA CAIRN OIL & GAS PIPE LINE RAJASTHAN | G52: NOC/APPROVAL 26.09.2025
A53: =A52+1 -> 2 | B53: 36A/0-37/0 | D53: MANGALA CRUDE OIL PIPE LINE (HPCL-RAJASTHAN REFINERY LIMITED) RAJASTHAN | G53: Demand letter expected by 15.10.2025
A54: =A53+1 -> 3 | B54: 99B/0-99C/0 | D54: HRRL CONNECTIVITY GAS PIPE LINE(GSPL INDIA GASNE LIMITED BALOTRA ) RAJASTHAN | G54: DD submitted and other documents to be submitted as per GSPL requirement
A55: =A54+1 -> 4 | B55: 102/1-102/2 | D55: ARAB MIX CRUDE OIL PIPE LINE(HPCL RAJASTHAN REFINERY LIMITED PACHADRA,BALOTRA ) RAJASTHAN | G55: Documents to be submitted as per HRRL requirement
A56: =A55+1 -> 5 | B56: 134/0-134A/0 | D56: BARMER- PALANPUR PRTROLEUM PIPE LINE (HINDUSTAN PERTOLEUM CORP.LTD) RAJASTHAN | G56: Demand letter expected by 15.10.2025
A57: 6 | B57: 149/0-149A/0 | D57: MUNDRA- BATHINDA CRUDE OIL PIPE LINE (HPCL-Mittal Pipelines Limited) RAJASTHAN | G57: Draft agreement copy submitted for HMEL review

Sheet Check Survey 
A1: NAME OF PROJECT : FARHEGARH IV-BHINMAL 400KV D/C TRANSMISSION LINE
A2: Client : RAJASTHAN IV A POWER TRANSMISSION LTD.
A3: CONTRACTOR : KEC INTERNATIONAL LIMITED
A4: 400 KV CHECK SURVEY
A5: SL No | B5: Section | C5: Section Length | D5: Submission Date | E5: Approval Date | F5: Remarks
A6: 1 | B6: AP 51- AP 54 | C6: 2.653 | D6: 45684 | E6: 45691 | F6: Approved
A7: =A6+1 -> 2 | B7: AP 54- AP 60 | C7: 5.31 | F7: Approved
A8: =A7+1 -> 3 | B8: AP 60- AP 75 | C8: 19.672 | D8: 15.02.2025 , 24-02-2025 25-02-2025 | E8: 45713 | F8: Approved | G8: Required Change
A9: =A8+1 -> 4 | B9: AP 75- AP 92 | C9: 20.273 | D9: 45657 | E9: 45691 | F9: Approved
A10: =A9+1 -> 5 | B10: AP 92- AP 96 | C10: 3.084 | D10: 15-02-25 & 21-02-2025 | E10: 45712 | F10: Approved
A11: =A10+1 -> 6 | B11: AP 96- AP 97 | C11: 1.063 | D11: 45713 | E11: 45715 | F11: Approved
A12: =A11+1 -> 7 | B12: AP 97- AP 98B | C12: 2.09 | D12: 45713 | F12: Approved
A13: =A12+1 -> 8 | B13: AP 98B- 99A/0 | C13: 3.893 | D13: 45713 | F13: Approved
A14: =A13+1 -> 9 | B14: AP99A/0-AP 107 | C14: 6.971 | D14: 45713 | F14: Approved
A15: =A14+1 -> 10 | B15: AP 107- AP 121 | C15: 9.495 | D15: 45721 | E15: 45722 | F15: Approved
A16: =A15+1 -> 11 | B16: AP 121- AP 131 | C16: 8.697 | D16: 12-03-2025 & ReSubmission 4-04-2025 | F16: Submitted | G16: Resubmitted
A17: =A16+1 -> 12 | B17: AP 131- AP 133 | C17: 3.084 | F17: Submitted
A18: =A17+1 -> 13 | B18: AP 133- AP 134 | C18: 3.963 | F18: Submitted
A19: =A18+1 -> 14 | B19: AP 134- AP 135 | C19: 1.656 | F19: Submitted
A20: =A19+1 -> 15 | B20: AP 135- AP 136 | C20: 1.635 | F20: Submitted
A21: =A20+1 -> 16 | B21: AP 136 - AP 139 | C21: 2.221 | F21: Submitted
A22: =A21+1 -> 17 | B22: AP 139 - AP 147 | C22: 10.724 | D22: 26-03-2025 Resubmission 4-04-2025 &28-04-25 | F22: Submitted | G22: Resubmitted
A23: =A22+1 -> 18 | B23: AP 147/0 - AP 148 | C23: 3.666 | D23: 26-03-2025 Resubmission 4-04-2025 & 28-04-25 | F23: Submitted | G23: Resubmitted
A24: =A23+1 -> 19 | B24: AP148/0 - AP 149B | C24: 4.88 | F24: Submitted
A25: =A24+1 -> 20 | B25: AP 150 to Bhinmal GTY | C25: 2.474 | D25: 45765 | F25: Submitted
A26: =A25+1 -> 21 | B26: AP 50- AP 51 | C26: 0.275 | D26: 45752 | F26: Submitted
A27: =A26+1 -> 22 | B27: AP 47- AP 50 | C27: 2.008 | D27: 45752 | F27: Submitted
A28: =A27+1 -> 23 | B28: AP 46- AP 47 | C28: 0.223 | D28: 45752 | F28: Submitted
A29: =A28+1 -> 24 | B29: AP 42- AP 43 | C29: 2.731 | D29: 45752 | F29: Submitted
A30: =A29+1 -> 25 | B30: AP 45- AP 46 | C30: 1.717 | D30: 45752 | F30: Submitted
A31: =A30+1 -> 26 | B31: AP 43- AP 45 | C31: 1.068 | D31: 45752 | F31: Submitted
A32: =A31+1 -> 27 | B32: AP 40- AP 42 | C32: 2.873 | D32: 45752 | F32: Submitted
A34: =A32+1 -> 28 | B34: AP 10- AP 21 | C34: 19.57 | D34: 16-04-2025 & 16.05.2025 | F34: Re Submitted
A35: =A34+1 -> 29 | B35: 21/0-24/0 | C35: 2.618 | D35: 45781 | F35: Complete
A36: =A35+1 -> 30 | B36: 24/0-40/0 | C36: 18.193 | D36: 45805 | F36: Complete
B39: AS on date | C39: =SUM(C6:C36) -> 168.78
B43: Submission of Check Survey
A44: SL. No. | B44: Section | C44: Date of submission | D44: Section Length in kms | E44: Letter Reference Number | F44: Date of Approval | G44: Section Length in kms
A45: 1 | B45: AP75 To AP92 | C45: 45657 | D45: 20.273 | E45: KEC/FBTL/RPTL/TB507/008A | F45: 45691 | G45: 20.273 | H45: JMC -01
A46: =A45+1 -> 2 | B46: AP51 To AP60 | C46: 45684 | D46: 7.962 | E46: KEC/FBTL/RPTL/TB507/0014 | F46: 45691 | G46: 7.962 | H46: JMC -01
A47: =A46+1 -> 3 | B47: AP92 To AP96 | C47: 45709 | D47: 3.084 | E47: KEC/FBTL/RPTL/TB507/0025 & 0029 | F47: 45712 | G47: 3.084 | H47: JMC -02
A48: =A47+1 -> 4 | B48: AP60 To AP75 | C48: 45703 | D48: 19.672 | E48: KEC/FBTL/RPTL/TB507/0025 , 0030 & 0033 | F48: 45713 | G48: 19.672 | H48: JMC -02
A49: =A48+1 -> 5 | B49: AP96 To AP107 | C49: 45713 | D49: 14.017 | E49: KEC/FBTL/RPTL/TB507/0032 | F49: 45715 | G49: 14.017 | H49: JMC -02
A50: =A49+1 -> 6 | B50: AP107 To AP121 | C50: 45721 | D50: 9.495 | E50: KEC/FBTL/RPTL/TB507/0036 | F50: 45722 | G50: 9.495 | H50: JMC -03
A51: =A50+1 -> 7 | B51: AP121 To AP131 | C51: 45751 | D51: 8.697 | E51: KEC/FBTL/RPTL/TB507/0043 ,0050,0061 | F51: 45763 | G51: 8.697 | H51: JMC -04
A52: =A51+1 -> 8 | B52: AP139 To AP148 | C52: 45742 | D52: 14.39 | E52: KEC/FBTL/RPTL/TB507/0049 | F52: 45763 | G52: 14.39 | H52: JMC -04
A53: =A52+1 -> 9 | B53: AP40 To AP51 | C53: 45752 | D53: 10.894 | E53: KEC/FBTL/RPTL/TB507/0064
A54: =A53+1 -> 10 | B54: AP10 To AP21 | C54: 06-04-2025 & 16.05.2025 | D54: 19.57 | E54: KEC/FBTL/RPTL/TB507/79
A55: =A54+1 -> 11 | B55: AP150 To Bhinmal GTY | C55: 45765 | D55: 2.474 | E55: KEC/FBTL/RPTL/TB507/0068
A56: =A55+1 -> 12 | B56: AP131-AP 133 | C56: 45787 | D56: 3.084 | E56: KEC/FBTL/RPTL/TB507/0077
A57: =A56+1 -> 13 | B57: AP136-AP 139 | C57: 45787 | D57: 2.22 | E57: KEC/FBTL/RPTL/TB507/0077
A58: =A57+1 -> 14 | B58: AP 133-AP 135 | C58: 45802 | D58: 5.619 | E58: Resubmitted on dated 25/05/2025
A59: =A58+1 -> 15 | B59: AP 99-AP 100 | C59: 45794 | D59: 3.95 | E59: KEC/FBTL/RPTL/TB507/82 | F59: 45810
A60: =A59+1 -> 16 | B60: AP 135-AP 136 | C60: 45802 | D60: 1.635 | E60: KEC/FBTL/RPTL/TB507/0077 on 10/05/25
A61: =A60+1 -> 17 | B61: AP 148-AP 149B | C61: 45802 | D61: 4.88
A63: Total | D63: =SUM(D45:D61) -> 151.916 | G63: =SUM(G45:G62) -> 97.59
A66: Check Survey
A67: Sr. no | B67: Action by | C67: Section AP To AP | D67: Section length | E67: Approved by Client | F67: Pending by Client | G67: Remarks | H67: JMC
A68: 1 | B68: KEC | C68: S/S Gantry To AP-5/0 | D68: 1.609 | G68: Approved on 17.2.26
A69: 2 | B69: KEC | C69: AP 5 to AP 5B | D69: 3.619 | E69: yes | F69: Yes | G69: Approved
A70: 3 | B70: KEC | C70: AP 5B To AP 7/0 | D70: 5.374 | G70: Approved
A71: 4 | B71: KEC | C71: AP-7/0 To AP-10/0 | D71: 8.716 | G71: Approved on 25-07-2025
A72: =A71+1 -> 5 | C72: AP-10/0 To AP-21/0 | D72: 19.572 | E72: YES | G72: Approved on 16-06-2025 | H72: JMC -04
A73: =A72+1 -> 6 | B73: Apraava | C73: AP-21/0 To AP-24/0 | D73: 2.616 | E73: YES | G73: Approved on 23-07-2025
A74: =A73+1 -> 7 | B74: KEC | C74: AP-24/0 To AP-27/0 | D74: 1.428 | E74: YES | G74: Approved on 5-09-2025
A75: =A74+1 -> 8 | B75: KEC | C75: AP-27/0 To AP-40/0 | D75: 16.76 | G75: Approved on 23-07-2025
A76: =A75+1 -> 9 | C76: AP-40/0 To AP-45/0 | D76: 6.659 | E76: Yes | G76: Approved on 18-06-2025 | H76: JMC -04
A77: =A76+1 -> 10 | B77: KEC | C77: AP-45/0 To AP-48/0 | D77: 3.187 | E77: YES | G77: Approved on 18-06-2025
A78: =A77+1 -> 11 | C78: AP 48/0 to AP 51/0, | D78: 1.051 | E78: Yes | G78: Approved on 18-06-2025 | H78: JMC -04
A79: =A78+1 -> 12 | C79: AP-51/0 To AP-60/0 | D79: 7.962 | E79: Yes | G79: Approved | H79: JMC -01
A80: =A79+1 -> 13 | C80: AP-60/0 To AP-75/0 | D80: 19.567 | E80: Yes | G80: Approved | H80: JMC -04
A81: =A80+1 -> 14 | C81: AP-75/0 To AP-92/0 | D81: 20.274 | E81: Yes | G81: Approved | H81: JMC -01
A82: =A81+1 -> 15 | C82: AP-92/0 To AP-96/0 | D82: 3.084 | E82: Yes | G82: Approved | H82: JMC -02
A83: =A82+1 -> 16 | C83: AP-96/0 To AP-107/0 | D83: 14.119 | E83: Yes | G83: Approved | H83: JMC -02
A84: =A83+1 -> 17 | C84: AP-107/0 To AP-121/0 | D84: 9.495 | E84: Yes | G84: Approved | H84: JMC -03
A85: =A84+1 -> 18 | C85: AP-121/0 To AP-131/0 | D85: 8.693 | E85: Yes | G85: Approved | H85: JMC -04
A86: =A85+1 -> 19 | B86: KEC | C86: AP-131/0 To AP-139/0 | D86: 12.659 | E86: Yes | G86: Approved on 20-06-2025 | H86: JMC -04
A87: =A86+1 -> 20 | B87: KEC | C87: AP-139/0 To AP-148/0 | D87: 14.392 | E87: Yes | G87: Approved | H87: JMC -04
A88: =A87+1 -> 21 | B88: KEC | C88: AP-148/0 To AP-153/0 | D88: 6.321 | E88: Yes | G88: Approved | H88: JMC -04
A89: =A88+1 -> 22 | B89: Apraava | C89: AP-153/0 To AP-154/0 | D89: 0.732 | E89: Yes | G89: Approved on 5-09-2025
A90: =A89+1 -> 23 | B90: KEC | C90: AP-154/0 To AP-155/0 | D90: 0.218 | E90: Yes | G90: Approved on 5-09-2025
A91: =A90+1 -> 24 | B91: Apraava | C91: AP-155/0 To S/S Gantry | D91: 0.571 | E91: Yes | G91: Approved on 5-09-2025
C92: TOTAL | D92: =SUM(D68:D91) -> 188.678
A94: TOTAL | E94: =D92 -> 188.678
A95: Check Survey Submitted | E95: 188.678
A96: Check Survey Approved | E96: 188.678
A97: Balance for Approval by Client | E97: =E94-E95 -> 0
A98: Check Survey Approval Pending | E98: =E95-E96 -> 0 | F98: 13.1
A101: Sr. no | B101: Section AP To AP | C101: Section length | D101: Check Survey | E101: Details Survey | F101: Remarks
A102: 1 | B102: S/S Gantry To AP-7/0 | C102: 10.369 | D102: YES | E102: YES | F102: Details Survey Completed. Profile & Tower Schedule Submitted with Apraava Engg.
A103: =A102+1 -> 2 | B103: AP-7/0 To AP-10/0 | C103: 8.713 | D103: YES | F103: Approved
A104: =A103+1 -> 3 | B104: AP-10/0 To AP-21/0 | C104: 19.57 | D104: YES | F104: Approved
A105: =A104+1 -> 4 | B105: AP-21/0 To AP-24/0 | C105: 2.618 | D105: YES | F105: Approved
A106: =A105+1 -> 5 | B106: AP-24/0 To AP-27/0 | C106: 1.44 | D106: YES | F106: Check Survey Completed. Profile & Tower Schedule Submitted with Apraava Engg.
A107: =A106+1 -> 6 | B107: AP-27/0 To AP-40/0 | C107: 16.759 | D107: YES | F107: Approved
A108: =A107+1 -> 7 | B108: AP-40/0 To AP-45/0 | C108: 6.672 | D108: YES | F108: Approved
A109: =A108+1 -> 8 | B109: AP-45/0 To AP-48/0 | C109: 3.172 | D109: YES | E109: YES | F109: Details Survey Completed. Profile & Tower Schedule Submitted with Apraava Engg.
A110: =A109+1 -> 9 | B110: AP 48/0 to AP 51/0, | C110: 1.05 | D110: Yes | F110: Approved
A111: =A110+1 -> 10 | B111: AP-51/0 To AP-60/0 | C111: 7.962 | D111: Yes | F111: Approved
A112: =A111+1 -> 11 | B112: AP-60/0 To AP-75/0 | C112: 19.567 | D112: Yes | F112: Approved
...

Sheet Check Survey Status
A1: NAME OF PROJECT : FARHEGARH IV-BHINMAL 400KV D/C TRANSMISSION LINE
A2: Client : RAJASTHAN IV A POWER TRANSMISSION LTD.
A3: CONTRACTOR : KEC INTERNATIONAL LIMITED
A4: 400 KV CHECK SURVEY
A5: SL No | B5: Section | C5: Section Length | D5: Submission Date | E5: Approval Date | F5: Remarks
A6: 1 | B6: AP 51- AP 54 | C6: 2.653 | D6: 45684 | E6: 45691 | F6: Approved
A7: =A6+1 -> 2 | B7: AP 54- AP 60 | C7: 5.31 | F7: Approved
A8: =A7+1 -> 3 | B8: AP 60- AP 75 | C8: 19.672 | D8: 15.02.2025 , 24-02-2025 25-02-2025 | E8: 45713 | F8: Approved | G8: Required Change
A9: =A8+1 -> 4 | B9: AP 75- AP 92 | C9: 20.273 | D9: 45657 | E9: 45691 | F9: Approved
A10: =A9+1 -> 5 | B10: AP 92- AP 96 | C10: 3.084 | D10: 15-02-25 & 21-02-2025 | E10: 45712 | F10: Approved
A11: =A10+1 -> 6 | B11: AP 96- AP 97 | C11: 1.063 | D11: 45713 | E11: 45715 | F11: Approved
A12: =A11+1 -> 7 | B12: AP 97- AP 98B | C12: 2.09 | D12: 45713 | F12: Approved
A13: =A12+1 -> 8 | B13: AP 98B- 99A/0 | C13: 3.893 | D13: 45713 | F13: Approved
A14: =A13+1 -> 9 | B14: AP99A/0-AP 107 | C14: 6.971 | D14: 45713 | F14: Approved
A15: =A14+1 -> 10 | B15: AP 107- AP 121 | C15: 9.495 | D15: 45721 | E15: 45722 | F15: Approved
A16: =A15+1 -> 11 | B16: AP 121- AP 131 | C16: 8.697 | D16: 12-03-2025 & ReSubmission 4-04-2025 | F16: Submitted | G16: Resubmitted
A17: =A16+1 -> 12 | B17: AP 131- AP 133 | C17: 3.084 | F17: Submitted
A18: =A17+1 -> 13 | B18: AP 133- AP 134 | C18: 3.963 | F18: Submitted
A19: =A18+1 -> 14 | B19: AP 134- AP 135 | C19: 1.656 | F19: Submitted
A20: =A19+1 -> 15 | B20: AP 135- AP 136 | C20: 1.635 | F20: Submitted
A21: =A20+1 -> 16 | B21: AP 136 - AP 139 | C21: 2.221 | F21: Submitted
A22: =A21+1 -> 17 | B22: AP 139 - AP 147 | C22: 10.724 | D22: 26-03-2025 Resubmission 4-04-2025 &28-04-25 | F22: Submitted | G22: Resubmitted
A23: =A22+1 -> 18 | B23: AP 147/0 - AP 148 | C23: 3.666 | D23: 26-03-2025 Resubmission 4-04-2025 & 28-04-25 | F23: Submitted | G23: Resubmitted
A24: =A23+1 -> 19 | B24: AP148/0 - AP 149B | C24: 4.88 | F24: Submitted
A25: =A24+1 -> 20 | B25: AP 150 to Bhinmal GTY | C25: 2.474 | D25: 45765 | F25: Submitted
A26: =A25+1 -> 21 | B26: AP 50- AP 51 | C26: 0.275 | D26: 45752 | F26: Submitted
A27: =A26+1 -> 22 | B27: AP 47- AP 50 | C27: 2.008 | D27: 45752 | F27: Submitted
A28: =A27+1 -> 23 | B28: AP 46- AP 47 | C28: 0.223 | D28: 45752 | F28: Submitted
A29: =A28+1 -> 24 | B29: AP 42- AP 43 | C29: 2.731 | D29: 45752 | F29: Submitted
A30: =A29+1 -> 25 | B30: AP 45- AP 46 | C30: 1.717 | D30: 45752 | F30: Submitted
A31: =A30+1 -> 26 | B31: AP 43- AP 45 | C31: 1.068 | D31: 45752 | F31: Submitted
A32: =A31+1 -> 27 | B32: AP 40- AP 42 | C32: 2.873 | D32: 45752 | F32: Submitted
A34: =A32+1 -> 28 | B34: AP 10- AP 21 | C34: 19.57 | D34: 16-04-2025 & 16.05.2025 | F34: Re Submitted
A35: =A34+1 -> 29 | B35: 21/0-24/0 | C35: 2.618 | D35: 45781 | F35: Complete
A36: =A35+1 -> 30 | B36: 24/0-40/0 | C36: 18.193 | D36: 45805 | F36: Complete
B39: AS on date | C39: =SUM(C6:C36) -> 168.78
B43: Submission of Check Survey
A44: SL. No. | B44: Section | C44: Date of submission | D44: Section Length in kms | E44: Letter Reference Number | F44: Date of Approval | G44: Section Length in kms
A45: 1 | B45: AP75 To AP92 | C45: 45657 | D45: 20.273 | E45: KEC/FBTL/RPTL/TB507/008A | F45: 45691 | G45: 20.273
A46: =A45+1 -> 2 | B46: AP51 To AP60 | C46: 45684 | D46: 7.962 | E46: KEC/FBTL/RPTL/TB507/0014 | F46: 45691 | G46: 7.962
A47: =A46+1 -> 3 | B47: AP92 To AP96 | C47: 45709 | D47: 3.084 | E47: KEC/FBTL/RPTL/TB507/0025 & 0029 | F47: 45712 | G47: 3.084
A48: =A47+1 -> 4 | B48: AP60 To AP75 | C48: 45703 | D48: 19.672 | E48: KEC/FBTL/RPTL/TB507/0025 , 0030 & 0033 | F48: 45713 | G48: 19.672
A49: =A48+1 -> 5 | B49: AP96 To AP107 | C49: 45713 | D49: 14.017 | E49: KEC/FBTL/RPTL/TB507/0032 | F49: 45715 | G49: 14.017
A50: =A49+1 -> 6 | B50: AP107 To AP121 | C50: 45721 | D50: 9.495 | E50: KEC/FBTL/RPTL/TB507/0036 | F50: 45722 | G50: 9.495
A51: =A50+1 -> 7 | B51: AP121 To AP131 | C51: 45751 | D51: 8.697 | E51: KEC/FBTL/RPTL/TB507/0043 ,0050,0061 | F51: 45732 | G51: 8.697
A52: =A51+1 -> 8 | B52: AP139 To AP148 | C52: 45742 | D52: 14.39 | E52: KEC/FBTL/RPTL/TB507/0049 | F52: 45732 | G52: 14.39
A53: =A52+1 -> 9 | B53: AP40 To AP51 | C53: 45752 | D53: 10.894 | E53: KEC/FBTL/RPTL/TB507/0064
A54: =A53+1 -> 10 | B54: AP10 To AP21 | C54: 06-04-2025 & 16.05.2025 | D54: 19.57 | E54: KEC/FBTL/RPTL/TB507/79
A55: =A54+1 -> 11 | B55: AP150 To Bhinmal GTY | C55: 45765 | D55: 2.474 | E55: KEC/FBTL/RPTL/TB507/0068
A56: =A55+1 -> 12 | B56: AP131-AP 133 | C56: 45787 | D56: 3.084 | E56: KEC/FBTL/RPTL/TB507/0077
A57: =A56+1 -> 13 | B57: AP136-AP 139 | C57: 45787 | D57: 2.22 | E57: KEC/FBTL/RPTL/TB507/0077
A58: =A57+1 -> 14 | B58: AP 133-AP 135 | C58: 45802 | D58: 5.619 | E58: Resubmitted on dated 25/05/2025
A59: =A58+1 -> 15 | B59: AP 99-AP 100 | C59: 45794 | D59: 3.95 | E59: KEC/FBTL/RPTL/TB507/82 | F59: 45810
A60: =A59+1 -> 16 | B60: AP 135-AP 136 | C60: 45802 | D60: 1.635 | E60: KEC/FBTL/RPTL/TB507/0077 on 10/05/25
A61: =A60+1 -> 17 | B61: AP 148-AP 149B | C61: 45802 | D61: 4.88
A63: Total | D63: =SUM(D45:D61) -> 151.916 | G63: =SUM(G45:G62) -> 97.59
C66: Check Survey
A67: Sr. no | B67: Action by | C67: Section AP To AP | D67: Section length | E67: Approved by Client | F67: Pending by Client | G67: Remarks
A68: 1 | B68: KEC | C68: S/S Gantry To AP-7/0 | D68: 10.373 | G68: Details Survey Completed. Profile Preperation in process with KEC Engg.
A69: =A68+1 -> 2 | B69: KEC | C69: AP-7/0 To AP-10/0 | D69: 8.719 | G69: Submitted on 3.07.2025,
A70: =A69+1 -> 3 | C70: AP-10/0 To AP-21/0 | D70: 19.57 | E70: YES | G70: Approved
A71: =A70+1 -> 4 | B71: Apraava | C71: AP-21/0 To AP-24/0 | D71: 2.618 | F71: YES | G71: Hard Copy Submitted on 24-06-2025
A72: =A71+1 -> 5 | B72: KEC | C72: AP-24/0 To AP-40/0 | D72: 18.193 | G72: Submited on 30.06.2025
A73: =A72+1 -> 6 | C73: AP-40/0 To AP-45/0 | D73: 6.659 | E73: Yes | G73: Approved on 18-06-2025
A74: =A73+1 -> 7 | B74: KEC | C74: AP-45/0 To AP-48/0 | D74: 3.17 | G74: Profile Preperation in process with KEC Engg.
A75: =A74+1 -> 8 | C75: AP 48/0 to AP 51/0, | D75: 1.05 | E75: Yes | G75: Approved on 18-06-2025
A76: =A75+1 -> 9 | C76: AP-51/0 To AP-60/0 | D76: 7.962 | E76: Yes | G76: Approved
A77: =A76+1 -> 10 | C77: AP-60/0 To AP-75/0 | D77: 19.567 | E77: Yes | G77: Approved
A78: =A77+1 -> 11 | C78: AP-75/0 To AP-92/0 | D78: 20.273 | E78: Yes | G78: Approved
A79: =A78+1 -> 12 | C79: AP-92/0 To AP-96/0 | D79: 3.084 | E79: Yes | G79: Approved
A80: =A79+1 -> 13 | C80: AP-96/0 To AP-107/0 | D80: 14.119 | E80: Yes | G80: Approved
A81: =A80+1 -> 14 | C81: AP-107/0 To AP-121/0 | D81: 9.495 | E81: Yes | G81: Approved
A82: =A81+1 -> 15 | C82: AP-121/0 To AP-131/0 | D82: 8.694 | E82: Yes | G82: Approved
A83: =A82+1 -> 16 | B83: KEC | C83: AP-131/0 To AP-139/0 | D83: 12.559 | E83: Yes | G83: Approved
A84: =A83+1 -> 17 | B84: KEC | C84: AP-139/0 To AP-148/0 | D84: 14.391 | E84: Yes | G84: Approved
A85: =A84+1 -> 18 | B85: KEC | C85: AP-148/0 To AP-153/0 | D85: 6.321 | E85: Yes | G85: Approved
A86: 19 | B86: Apraava | C86: AP-153/0 To AP-154/0 | D86: 0.389 | F86: Yes
A87: 20 | B87: KEC | C87: AP-154/0 To AP-155/0 | D87: 0.22 | G87: Underneath crossing proposal under process with KEC Engg.
A88: 21 | B88: Apraava | C88: AP-155/0 To S/S Gantry | D88: 0.57 | F88: Yes | G88: Submitted on 16.04.2025,
C89: TOTAL | D89: =SUM(D68:D88) -> 187.996
E91: 2.618 | F91: AP 21 to AP 24
A92: TOTAL | E92: =D89 -> 187.996
A93: Check Survey Submitted | E93: =E92-E96 -> 156.04
A94: Check Survey Approved | E94: =E93-E95 -> 152.463
A95: Balance for Approval by Client | E95: 3.577
A96: Check Survey report to be Submitted | E96: 31.956
B98: Check Survey
B99: Sr.no | C99: Section AP To AP | D99: Section length | E99: Approved | F99: Resposnibility | G99: Remarks
B100: 1 | C100: AP-1/0 To AP-10/0 | D100: 18.116 | F100: M/s Kec | G100: Rerouting confirmation given on 12.06.2025 to carry out detail survey, When will be the survey started
B101: 2 | C101: AP-10/0 To AP-21/0 | D101: 19.57 | F101: M/s Apraava | G101: Will be approved by 17.06.2025
B102: 3 | C102: AP-21/0 To AP-40/0 | D102: 20.811 | F102: M/s Kec | G102: From AP 21 to AP 24 and AP 27 to AP 40 has to be submitted. From AP 24 to AP 27 Underneath data has also to be submitted. When it will be submitted
B103: 4 | C103: AP-40/0 To AP 45 and AP 48 to AP 51/0 | D103: 10.894 | F103: M/s Apraava | G103: From AP 40 to AP 45, AP 48 to AP 51 will be approved by 17.06.2025
C104: AP 45 to AP 48 | F104: M/s Kec | G104: Railway crossing detail survey profile, Tower Schedule yet not provided, When will we get this.
B105: 5 | C105: AP-51/0 To AP-60/0 | D105: 7.962 | E105: 45691
B106: 6 | C106: AP-60/0 To AP-75/0 | D106: 19.567 | E106: 45713
B107: 7 | C107: AP-75/0 To AP-92/0 | D107: 20.273 | E107: 45691
B108: 8 | C108: AP-92/0 To AP-96/0 | D108: 3.084 | E108: 45712
B109: 9 | C109: AP-96/0 To AP-107/0 | D109: 14.017 | E109: 45715
B110: 10 | C110: AP-107/0 To AP-121/0 | D110: 9.495 | E110: 45722
B111: 11 | C111: AP-121/0 To AP-131/0 | D111: 8.694 | E111: 45763
...

Sheet Check Survey
A1: NAME OF PROJECT : FARHEGARH IV-BHINMAL 400KV D/C TRANSMISSION LINE
A2: Client : RAJASTHAN IV A POWER TRANSMISSION LTD.
A3: CONTRACTOR : KEC INTERNATIONAL LIMITED
A4: 400 KV CHECK SURVEY
A5: SL No | B5: Section | C5: Section Length | D5: Submission Date | E5: Approval Date | F5: Remarks
A6: 1 | B6: AP 51- AP 54 | C6: 2.653 | D6: 45684 | E6: 45691 | F6: Approved
A7: =A6+1 -> 2 | B7: AP 54- AP 60 | C7: 5.31 | F7: Approved
A8: =A7+1 -> 3 | B8: AP 60- AP 75 | C8: 19.672 | D8: 15.02.2025 , 24-02-2025 25-02-2025 | E8: 45713 | F8: Approved | G8: Required Change | H8: Approved | I8: =G63 -> 97.59
A9: =A8+1 -> 4 | B9: AP 75- AP 92 | C9: 20.273 | D9: 45657 | E9: 45691 | F9: Approved
A10: =A9+1 -> 5 | B10: AP 92- AP 96 | C10: 3.084 | D10: 15-02-25 & 21-02-2025 | E10: 45712 | F10: Approved | H10: Submitted | I10: =D63 -> 151.916
A11: =A10+1 -> 6 | B11: AP 96- AP 97 | C11: 1.063 | D11: 45713 | E11: 45715 | F11: Approved
A12: =A11+1 -> 7 | B12: AP 97- AP 98B | C12: 2.09 | D12: 45713 | F12: Approved
A13: =A12+1 -> 8 | B13: AP 98B- 99A/0 | C13: 3.893 | D13: 45713 | F13: Approved
A14: =A13+1 -> 9 | B14: AP99A/0-AP 107 | C14: 6.971 | D14: 45713 | F14: Approved
A15: =A14+1 -> 10 | B15: AP 107- AP 121 | C15: 9.495 | D15: 45721 | E15: 45722 | F15: Approved
A16: =A15+1 -> 11 | B16: AP 121- AP 131 | C16: 8.697 | D16: 12-03-2025 & ReSubmission 4-04-2025 | F16: Submitted | G16: Resubmitted
A17: =A16+1 -> 12 | B17: AP 131- AP 133 | C17: 3.084 | F17: Submitted
A18: =A17+1 -> 13 | B18: AP 133- AP 134 | C18: 3.963 | F18: Submitted
A19: =A18+1 -> 14 | B19: AP 134- AP 135 | C19: 1.656 | F19: Submitted
A20: =A19+1 -> 15 | B20: AP 135- AP 136 | C20: 1.635 | F20: Submitted
A21: =A20+1 -> 16 | B21: AP 136 - AP 139 | C21: 2.221 | F21: Submitted
A22: =A21+1 -> 17 | B22: AP 139 - AP 147 | C22: 10.724 | D22: 26-03-2025 Resubmission 4-04-2025 &28-04-25 | F22: Submitted | G22: Resubmitted
A23: =A22+1 -> 18 | B23: AP 147/0 - AP 148 | C23: 3.666 | D23: 26-03-2025 Resubmission 4-04-2025 & 28-04-25 | F23: Submitted | G23: Resubmitted | M23: Blance | N23: =187.176-M11 -> 187.176
A24: =A23+1 -> 19 | B24: AP148/0 - AP 149B | C24: 4.88 | F24: Submitted
A25: =A24+1 -> 20 | B25: AP 150 to Bhinmal GTY | C25: 2.474 | D25: 45765 | F25: Submitted
A26: =A25+1 -> 21 | B26: AP 50- AP 51 | C26: 0.275 | D26: 45752 | F26: Submitted
A27: =A26+1 -> 22 | B27: AP 47- AP 50 | C27: 2.008 | D27: 45752 | F27: Submitted
A28: =A27+1 -> 23 | B28: AP 46- AP 47 | C28: 0.223 | D28: 45752 | F28: Submitted
A29: =A28+1 -> 24 | B29: AP 42- AP 43 | C29: 2.731 | D29: 45752 | F29: Submitted
A30: =A29+1 -> 25 | B30: AP 45- AP 46 | C30: 1.717 | D30: 45752 | F30: Submitted
A31: =A30+1 -> 26 | B31: AP 43- AP 45 | C31: 1.068 | D31: 45752 | F31: Submitted
A32: =A31+1 -> 27 | B32: AP 40- AP 42 | C32: 2.873 | D32: 45752 | F32: Submitted
A34: =A32+1 -> 28 | B34: AP 10- AP 21 | C34: 19.57 | D34: 16-04-2025 & 16.05.2025 | F34: Re Submitted
A35: =A34+1 -> 29 | B35: 21/0-24/0 | C35: 2.618 | D35: 45781 | F35: Complete
A36: =A35+1 -> 30 | B36: 24/0-40/0 | C36: 18.193 | D36: 45805 | F36: Complete | I36: =155.849-130.528 -> 25.321
B39: AS on date | C39: =SUM(C6:C36) -> 168.78
B43: Submission of Check Survey
A44: SL. No. | B44: Section | C44: Date of submission | D44: Section Length in kms | E44: Letter Reference Number | F44: Date of Approval | G44: Section Length in kms | H44: Approved By | I44: Remarks
A45: 1 | B45: AP75 To AP92 | C45: 45657 | D45: 20.273 | E45: KEC/FBTL/RPTL/TB507/008A | F45: 45691 | G45: 20.273 | H45: Gundewadi Mallappa
A46: =A45+1 -> 2 | B46: AP51 To AP60 | C46: 45684 | D46: 7.962 | E46: KEC/FBTL/RPTL/TB507/0014 | F46: 45691 | G46: 7.962 | H46: Gundewadi Mallappa
A47: =A46+1 -> 3 | B47: AP92 To AP96 | C47: 45709 | D47: 3.084 | E47: KEC/FBTL/RPTL/TB507/0025 & 0029 | F47: 45712 | G47: 3.084 | H47: Gundewadi Mallappa | I47: Resubmission on dated 21/02/2025
A48: =A47+1 -> 4 | B48: AP60 To AP75 | C48: 45703 | D48: 19.672 | E48: KEC/FBTL/RPTL/TB507/0025 , 0030 & 0033 | F48: 45713 | G48: 19.672 | H48: Gundewadi Mallappa | I48: Resubmission on dated 24/02/2025 & 25/02/2025
A49: =A48+1 -> 5 | B49: AP96 To AP107 | C49: 45713 | D49: 14.017 | E49: KEC/FBTL/RPTL/TB507/0032 | F49: 45715 | G49: 14.017 | H49: Gundewadi Mallappa
A50: =A49+1 -> 6 | B50: AP107 To AP121 | C50: 45721 | D50: 9.495 | E50: KEC/FBTL/RPTL/TB507/0036 | F50: 45722 | G50: 9.495 | H50: Gundewadi Mallappa
A51: =A50+1 -> 7 | B51: AP121 To AP131 | C51: 45751 | D51: 8.697 | E51: KEC/FBTL/RPTL/TB507/0043 ,0050,0061 | F51: 45732 | G51: 8.697 | H51: Gundewadi Mallappa | I51: Resubmission on dated 04/04/2025
A52: =A51+1 -> 8 | B52: AP139 To AP148 | C52: 45742 | D52: 14.39 | E52: KEC/FBTL/RPTL/TB507/0049 | F52: 45732 | G52: 14.39 | H52: Gundewadi Mallappa | I52: Resubmission on dated 04/04/2025
A53: =A52+1 -> 9 | B53: AP40 To AP51 | C53: 45752 | D53: 10.894 | E53: KEC/FBTL/RPTL/TB507/0064
A54: =A53+1 -> 10 | B54: AP10 To AP21 | C54: 06-04-2025 & 16.05.2025 | D54: 19.57 | E54: KEC/FBTL/RPTL/TB507/79 | I54: Resubmission on dated 16/05/2025
A55: =A54+1 -> 11 | B55: AP150 To Bhinmal GTY | C55: 45765 | D55: 2.474 | E55: KEC/FBTL/RPTL/TB507/0068
A56: =A55+1 -> 12 | B56: AP131-AP 133 | C56: 45787 | D56: 3.084 | E56: KEC/FBTL/RPTL/TB507/0077 | I56: Resubmission on dated 10/05/2025
A57: =A56+1 -> 13 | B57: AP136-AP 139 | C57: 45787 | D57: 2.22 | E57: KEC/FBTL/RPTL/TB507/0077 | I57: Resubmission on dated 10/05/2025
A58: =A57+1 -> 14 | B58: AP 133-AP 135 | C58: 45802 | D58: 5.619 | E58: Resubmitted on dated 25/05/2025 | I58: Resubmission on dated 25/05/2025
A59: =A58+1 -> 15 | B59: AP 99-AP 100 | C59: 45794 | D59: 3.95 | E59: KEC/FBTL/RPTL/TB507/82 | F59: 45810 | I59: Resubmission on dated 16/05/2025
A60: =A59+1 -> 16 | B60: AP 135-AP 136 | C60: 45802 | D60: 1.635 | E60: KEC/FBTL/RPTL/TB507/0077 on 10/05/25 | I60: Resubmission on dated 25/05/2025
A61: =A60+1 -> 17 | B61: AP 148-AP 149B | C61: 45802 | D61: 4.88 | I61: Resubmission on dated 25/05/2025
I62: Resubmission on dated 25/05/2025
A63: Total | D63: =SUM(D45:D61) -> 151.916 | G63: =SUM(G45:G62) -> 97.59
C66: Check Survey
A67: Action by | B67: Sr.no | C67: Section AP To AP | D67: Section length | E67: Approved by Client | F67: Pending by Client | G67: Remarks | H67: Apraava Comments
A68: Apraava | B68: 1 | C68: AP-1/0 To AP-7/0 | D68: 9.4 | G68: Details Survey Completed | H68: Discussion and coordination with Statcraft are ongoing. Awaiting their response
B69: =B68+1 -> 2 | C69: AP-7/0 To AP-10/0 | D69: 9.096 | G69: Check Survry Completed
A70: KEC | B70: =B69+1 -> 3 | C70: AP-10/0 To AP-21/0 | D70: 19.57 | F70: YES | G70: Approved | H70: KEC was to submit a proposal avoiding the shifting of the 11 kV line; their response is still awaited. The rest of the profile is acceptable—awaiting a hard-signed copy along with revised tower schdule from the KEC team for official release
B71: =B70+1 -> 4 | C71: AP-21/0 To AP-24/0 | D71: 2.618 | G71: Hard Copy Submitted on 24-06-2025
A72: KEC | B72: =B71+1 -> 5 | C72: AP-24/0 To AP-40/0 | D72: 18.193 | F72: 45784 | G72: AP 27 to AP 40(16.753Km) CS completed and Profile Under Process in KEC Engg, GTY position finalization at AP 24 to AP 27(1.440 KM) | H72: Check Survey for two oil/gas pipeline crossings is awaited, and the re-survey for the 400kV line crossing between AP25 to AP26 (underneath crossing) is pending from KEC.
A73: KEC | B73: =B72+1 -> 6 | C73: AP-40/0 To AP-45/0 | D73: 6.659 | G73: Approved on 18-06-2025
A74: KEC | B74: =B73+1 -> 7 | C74: AP-45/0 To AP-48/0 | D74: 3.17 | G74: Hold due to Railway crossing angle 870 to 900 | H74: Re-survey for the railway crossing between AP46 and AP47, due to alignment change from 86° to 90°, is pending from KEC.
A75: KEC | B75: =B74+1 -> 8 | C75: AP 48/0 to AP 51/0, | D75: 1.05 | F75: 45752 | G75: Approved on 18-06-2025
A76: KEC | B76: =B75+1 -> 9 | C76: AP-51/0 To AP-60/0 | D76: 7.962 | E76: 45691 | G76: Approved | H76: Tower schedule has been approved; however, the profile as per the approved check survey is still awaited from KEC
B77: =B76+1 -> 10 | C77: AP-60/0 To AP-75/0 | D77: 19.567 | E77: 45713 | G77: Approved
B78: =B77+1 -> 11 | C78: AP-75/0 To AP-92/0 | D78: 20.273 | E78: 45691 | G78: Approved
B79: =B78+1 -> 12 | C79: AP-92/0 To AP-96/0 | D79: 3.084 | E79: 45712 | G79: Approved
B80: =B79+1 -> 13 | C80: AP-96/0 To AP-107/0 | D80: 14.119 | E80: 45715 | G80: Approved
B81: =B80+1 -> 14 | C81: AP-107/0 To AP-121/0 | D81: 9.495 | E81: 45722 | G81: Approved
B82: =B81+1 -> 15 | C82: AP-121/0 To AP-131/0 | D82: 8.694 | E82: 45763 | G82: Approved
A83: KEC | B83: =B82+1 -> 16 | C83: AP-131/0 To AP-139/0 | D83: 12.559 | F83: YES | G83: Approved | H83: Location of AP132 has been changed due to the presence of a house within the corridor; revised check survey and profile are awaited from KEC."
A84: KEC | B84: =B83+1 -> 17 | C84: AP-139/0 To AP-148/0 | D84: 14.391 | E84: 45763 | G84: Approved | H84: Tower schedule has been approved; however, the profile as per the approved check survey is still awaited from KEC
A85: KEC | B85: =B84+1 -> 18 | C85: AP-148/0 To AP-150/0 | D85: 5.268 | F85: 45800 | G85: Approved | H85: Hard signed profile & Tower schudle copies are awaited from KEC to offical realse.
A86: KEC | B86: =B85+1 -> 19 | C86: AP-150/0 To AP-157/0 | D86: 2.474 | E86: 45765 | G86: Approval pending from Engg Team | H86: Re-survey for the 400kV line crossing between AP154 to AP155 (underneath crossing) is pending from KEC.
D87: =SUM(D68:D86) -> 187.642
D89: CS Submitted | E89: =187.176-(18.496+2.618) -> 166.062
E90: 2.618 | F90: AP 21 to AP 24
D91: TOTAL | E91: =D87 -> 187.642
D92: Approved | E92: =D70+D73+SUM(D75:D86) -> 145.165
D93: Balance | E93: =E91-E92 -> 42.477
B95: Check Survey
B96: Sr.no | C96: Section AP To AP | D96: Section length | E96: Approved | F96: Resposnibility | G96: Remarks
B97: 1 | C97: AP-1/0 To AP-10/0 | D97: 18.116 | F97: M/s Kec | G97: Rerouting confirmation given on 12.06.2025 to carry out detail survey, When will be the survey started
B98: 2 | C98: AP-10/0 To AP-21/0 | D98: 19.57 | F98: M/s Apraava | G98: Will be approved by 17.06.2025
B99: 3 | C99: AP-21/0 To AP-40/0 | D99: 20.811 | F99: M/s Kec | G99: From AP 21 to AP 24 and AP 27 to AP 40 has to be submitted. From AP 24 to AP 27 Underneath data has also to be submitted. When it will be submitted
B100: 4 | C100: AP-40/0 To AP 45 and AP 48 to AP 51/0 | D100: 10.894 | F100: M/s Apraava | G100: From AP 40 to AP 45, AP 48 to AP 51 will be approved by 17.06.2025
C101: AP 45 to AP 48 | F101: M/s Kec | G101: Railway crossing detail survey profile, Tower Schedule yet not provided, When will we get this.
B102: 5 | C102: AP-51/0 To AP-60/0 | D102: 7.962 | E102: 45691
B103: 6 | C103: AP-60/0 To AP-75/0 | D103: 19.567 | E103: 45713
B104: 7 | C104: AP-75/0 To AP-92/0 | D104: 20.273 | E104: 45691
B105: 8 | C105: AP-92/0 To AP-96/0 | D105: 3.084 | E105: 45712
B106: 9 | C106: AP-96/0 To AP-107/0 | D106: 14.017 | E106: 45715
B107: 10 | C107: AP-107/0 To AP-121/0 | D107: 9.495 | E107: 45722
B108: 11 | C108: AP-121/0 To AP-131/0 | D108: 8.694 | E108: 45763
B109: 12 | C109: AP-131/0 To AP-133/0 | D109: 3.084 | F109: M/s Kec | G109: Yet not submitted
B110: 13 | C110: AP-133/0 To AP-135/0 | D110: 5.619 | F110: M/s Kec | G110: Yet not submitted
...

Sheet Sheet8
A1: S No. | B1: MOM as on 11/6/25 | C1: Timeline | D1: Responsibility | E1: Status as on 19/6/25
A2: 1 | B2: 400kv Detail Survey from AP 01 to AP 10
A3: a | B3: Apraava will give clearance for further proceeding of Detail Survey | C3: 45821 | D3: M/S Apraava | E3: Clearance provided for Detail Survey
A4: b | B4: Completion of Detail Survey | C4: 45833 | D4: M/S KEC | E4: Detail Survey work under progress
A5: c | B5: Detail Survey of 765 kV is submitted by KEC, observation raised by Apraava, KEC has to re-submitted according to observation | C5: 45824 | D5: M/S KEC | E5: Reobservation mail by Engg. Team on dt. 19.06.25
A6: 2 | B6: Check Survey
A7: a | B7: 50 km will be approved | C7: 45820 | D7: M/S Apraava & KEC | E7: 33 km Approved & 15 km submitted by KEC
A8: b | B8: Pending Section of 21 km will be approved | C8: 45828 | D8: M/S Apraava & KEC | E8: Under Progress
A9: c | B9: Check Survey of 765kV is to be submitted by KEC | C9: 46198 | D9: M/S KEC | E9: Detail Survey work under progress
A10: 3 | B10: Statutory Approvals
A11: a | B11: 02 No NH Proposal Submission | C11: 45838 | D11: M/S KEC | E11: Under Progress
A12: b | B12: 02 No Railway Proposal Submission | C12: 45838 | D12: M/S KEC | E12: Under Progress
A13: c | B13: 02 Nos PLC Proposal of 400 kV Underneath has to Submit | C13: ASAP | D13: M/S KEC | E13: Under Progress
A14: d | B14: Statutory Approvals tracker to be maintain for monitoring current status of NOC | C14: N/A | D14: M/S Apraava & KEC | E14: Under Progress
A15: e | B15: 04 Submission of SH Proposal to SH Authority | C15: 45828 | D15: M/S Apraava | E15: Under Progress
A16: f | B16: 03 Submission of Oil Proposal to Oil Authority | C16: 45828 | D16: M/s Apraava | E16: Under Progress
A17: 4 | B17: Deployment of surveyor, supervisors, engineers & section in charge to be expedite in Bhinmal Section | C17: 45820 | D17: M/S KEC | E17: Under Progress
A18: 5 | B18: KEC committed 43 nos. foundation for this month & accordingly Apraava will provide ROW clearance | C18: 45838 | D18: M/S Apraava & KEC | E18: Till date 13 foundations completed, 10 are in WIP and 30 work fronts are available
A19: 6 | B19: Manpower in each foundation gang need to be strengthen with at least 8-10 manpower/gang | C19: ASAP | D19: M/S KEC | E19: Under Progress
A20: 7 | B20: Apraava asked to increase 4 more foundation gangs to expedite foundation work (currently 7 gangs are available with insufficient manpower | C20: ASAP | D20: M/S KEC | E20: 9 Gangs are available (insufficient manpower in 4 gangs)
A21: 8 | B21: 40 Nos Departmental Manpower availability at site | C21: 45838 | D21: M/S KEC | E21: -
A22: 9 | B22: Quality Constraints
A23: a | B23: Information regarding supply of cement with prior & proper documentation | C23: N/A | D23: M/S KEC | E23: -
A24: b | B24: Material availability at site from approved source | C24: - | D24: M/S KEC | E24: -
A25: c | B25: Approval of use of Curing compound in foundation work need to be expedite after jointly discussion of both team | C25: ASAP | D25: M/S Apraava & KEC | E25: Cubes taken after applying curing compound & further process is u/p
A26: d | B26: CTM Machine at store need be installed on priority for cube testing | C26: 45821 | D26: M/S KEC | E26: Under Progress
A27: 10 | B27: Erection team to be deployed and erection to be start | C27: 45826 | D27: M/S KEC | E27: Erection to be start by Monday, 23/6/25
A28: 11 | B28: July month foundation & erection plan to be shared by KEC | C28: 45824 | D28: M/S KEC | E28: July month plan to be shared within 2-3 days by KEC
A29: 12 | B29: Supply of conductor to be start in September month | C29: 45930 | D29: M/S Apraava | E29: Planned for September month
A30: 13 | B30: Total 121 nos. of DA type of tower supplied to store & 2nd lot of 74 nos. towers (approx. 1500 MT) supply, consisting of DC & DD type towers are scheduled for next month | C30: 45848 | D30: M/S KEC | E30: DA type towers are supplied

Sheet Sheet2
C2: 400kV D/C Fatehgarh IV (Section-2)PS - Bhinmal (PG) Transmission Line
C4: Sl No | D4: Section AP To AP | E4: Section length | F4: Remarks
C5: 1 | D5: AP-21/0 To AP-24/0 | E5: 2.618
C6: =C5+1 -> 2 | D6: AP-24/0 To AP-27/0 | E6: 1.428
C7: =C6+1 -> 3 | D7: AP-27/0 To AP-40/0 | E7: 16.76
C8: =C7+1 -> 4 | D8: AP-45/0 To AP-48/0 | E8: 3.187
C9: =C8+1 -> 5 | D9: AP-153/0 To AP-154/0 | E9: 0.732
C10: =C9+1 -> 6 | D10: AP-154/0 To AP-155/0 | E10: 0.218
C11: =C10+1 -> 7 | D11: AP-155/0 To S/S Gantry | E11: 0.571
D12: TOTAL | E12: =SUM(E5:E11) -> 25.514
C14: 765kV D/C Fatehgarh IV (Section-2)PS - Bhinmal (PG) Transmission Line
C16: Sl No | D16: Section AP To AP | E16: Section length | F16: Route Allignment,Detail Survey,Check survey
D17: LI | E17: =7584/1000 -> 7.584
D18: LO | E18: =6951/1000 -> 6.951
D19: TOTAL | E19: =SUM(E17:E18) -> 14.535

Sheet Project Details
A1: Project Code | B1: Project Name | C1: Client Name | D1: LOA Start Date | E1: LOA End Date | F1: Planning Engineer | G1: PCH | H1: Regional Manager | I1: Project Manger | J1: Section Incharge | K1: Supervisor/Engineer
A2: TB 507 | B2: 400kV D/C Fatehgarh IV (Section-2)PS - Bhinmal (PG) Transmission Line | C2: RAJASTHAN IV A POWER TRANSMISSION LTD | D2: 45632 | E2: 46178 | F2: Amartya sarkar | G2: Sanjay Kr Gupta | I2: ALOK SINHA | J2: ALOK JANA VARUN TYAGI

Sheet Sheet1
B1: FOUNDATION STATUS | J1: =SUBTOTAL(3,J5:J24) -> 18
B2: SL. No. | C2: Location Number | D2: Span | E2: Tower Type | F2: RC | G2: Foundation type
H3: Starting date | I3: Completion Date | J3: Agency | K3: Remark | L3: Remarks
B4: 1 | C4: 83/1 | D4: 83/1 | E4: DA+3 | G4: Sandy | H4: 45665 | I4: 45674 | J4: Mahadeep Company | K4: 45674 | L4: Complete
B5: =B4+1 -> 2 | C5: 81/4 | D5: 81/4 | E5: DA+0 | G5: Sandy | H5: 45675 | I5: ROW | J5: Mahadeep Company | K5: ROW LOC HOLD | L5: Row Since 20-01-2025, Gang Domobilized
B6: =B5+1 -> 3 | C6: 75/7 | D6: 75/7 | E6: DA+0 | G6: Sandy | H6: 45675 | I6: 45684 | J6: AR PATEL | L6: RCC Complete
B7: =B6+1 -> 4 | C7: 75/6 | E7: DA+0 | G7: Sandy | H7: 45685 | I7: 45690 | J7: AR PATEL | L7: RCC Complete, Backfilling Done
B8: =B7+1 -> 5 | C8: 75/5 | E8: DA+0 | G8: Sandy | H8: 45685 | I8: 45693 | J8: AR PATEL | L8: RCC Complete.
B9: =B8+1 -> 6 | C9: 75/4 | E9: DA+0 | G9: Sandy | H9: 45686 | I9: 45693 | J9: Om Constraction | L9: RCC Complete, Backfilling Done
B10: =B9+1 -> 7 | C10: 75/3 | E10: DA+3 | G10: Sandy | H10: 45691 | I10: 45698 | J10: Om Constraction | L10: RCC Complete.
B11: =B10+1 -> 8 | C11: 75/1 | E11: DA+0 | G11: Sandy | H11: 45697 | I11: 45705 | J11: Om Constraction | L11: RCC Complete.
B12: =B11+1 -> 9 | C12: 75/2 | E12: DA+0 | G12: Sandy | H12: 45700 | I12: 45706 | J12: Om Constraction | L12: RCC Complete.
B13: =B12+1 -> 10 | C13: 77/1 | E13: DA+0 | G13: Sandy | H13: 45691 | I13: 45699 | J13: Anjaana Construction | L13: RCC Complete.
B14: =B13+1 -> 11 | C14: 77/2 | E14: DA+3 | G14: Sandy | H14: 45691 | I14: 45697 | J14: AR PATEL | L14: RCC Complete, Backfilling Done
B15: =B14+1 -> 12 | C15: 77/3 | E15: DA+0 | G15: Sandy | H15: 45696 | I15: 45702 | J15: AR PATEL | L15: RCC Complete.
B16: =B15+1 -> 13 | C16: 77/4 | E16: DA+3 | G16: Sandy | H16: 42046 | I16: 45705 | J16: Anjaana Construction | L16: RCC Complete.
B17: =B16+1 -> 14 | C17: 77/5 | E17: DA+6 | G17: Sandy | H17: 45701 | J17: AR PATEL | L17: Pit B,C RCC Done & Pit A,D Frustrum RCC done.
B18: =B17+1 -> 15 | C18: 86/2 | E18: DA+0 | G18: Sandy | H18: 45698 | J18: Kalpana Enterprises | L18: Pit A , Pit B RCC Done , Pit C -Stub setting.
B19: =B18+1 -> 16 | C19: 66/1 | E19: DA+9 | G19: Sandy | H19: 45705 | J19: Siyag Construction | L19: Excavation WIP, ROW,Material Shifting WIP
B20: =B19+1 -> 17 | C20: 73/3 | E20: DA+9 | G20: Sandy | H20: 45705 | J20: Om Constraction | L20: Excavation WIP, ROW, Material Shifting WIP
B21: =B20+1 -> 18 | C21: 79/1 | E21: DA+9 | G21: Sandy | H21: 45705 | J21: Anjana Construction | L21: Excavation WIP, ROW, Material Shifting WIP
B22: =B21+1 -> 19 | C22: 95A/1 | E22: DA+0 | G22: Sandy | J22: Gurukripa Enterprises | L22: Pit Marking Done
B23: =B22+1 -> 20 | C23: 80/1
B24: =B23+1 -> 21 | C24: 85/1
B25: =B24+1 -> 22 | C25: 73/2
B26: =B25+1 -> 23 | C26: 66/2
B27: =B26+1 -> 24 | C27: 66/3
B28: =B27+1 -> 25 | C28: 86/1
B29: =B28+1 -> 26 | C29: 76/1

Sheet VC 51-96
B1: TB-507 400 KV (Twin) D/C Fatehgarh IV - Bhinmal Transmission Line
A2: DPR and VISUAL CHART
A4: DPR- | D4: District | F4: No.Of Towers | G4: Length | H4: Foundation | K4: Earthing | L4: Tower Erection | O4: Stringing
H5: Com | I5: WIP | J5: Bal | K5: Com | L5: Com | M5: WIP | N5: Bal | O5: Com | P5: WIP | Q5: Bal
F6: 163 | G6: 50.886 | H6: 16 | I6: 5 | J6: =F6-H6-I6 -> 142 | K6: 10 | N6: =F6-L6 -> 163 | Q6: =G6-O6 -> 50.886
C8: =A8+1 -> 1 | E8: =C8+1 -> 2 | G8: =E8+1 -> 3 | I8: =G8+1 -> 4 | K8: =I8+1 -> 5 | M8: =K8+1 -> 6 | O8: =M8+1 -> 7 | Q8: =O8+1 -> 8 | S8: =Q8+1 -> 9
D10: 465.03 | F10: 375.98 | H10: 414.86 | J10: 381.02 | L10: 353.63 | N10: 351.4 | P10: 433.26 | R10: 396.56 | T10: 408.11 | U10: =B10+F10+H10+J10+L10+D10+N10+P10+R10+T10 -> 3579.85
C13: AP51 | E13: 51/1 | G13: 51/2 | I13: 51/3 | K13: AP52 | M13: 52/1 | O13: AP53 | Q13: AP54 | S13: 54/1
C14: DD+18 | E14: DA+03 | G14: DA+00 | I14: DA+03 | K14: DB+0 | M14: DA+06 | O14: DD+0 | Q14: DC+00 | S14: DA+03
K15: RC | M15: RC
B17: =S8+1 -> 10 | D17: =B17+1 -> 11 | F17: =D17+1 -> 12 | H17: =F17+1 -> 13 | J17: =H17+1 -> 14 | L17: =J17+1 -> 15 | N17: =L17+1 -> 16 | P17: =N17+1 -> 17 | R17: =P17+1 -> 18 | T17: =R17+1 -> 19
C19: 425.22 | E19: 420.54 | G19: 340.56 | I19: 336.52 | K19: 375.99 | M19: 303.41 | O19: 448.76 | Q19: 393.09 | S19: 407.8 | U19: 206.06 | V19: =C19+G19+I19+K19+M19+E19+O19+Q19+S19+U19 -> 3657.95
B22: 54/2 | D22: 54/3 | F22: AP55 | H22: AP56 | J22: 56/1 | L22: 56/2 | N22: 56/3 | P22: 56/4 | R22: 56/5 | T22: AP57
B23: DA+06 | D23: DA+03 | F23: DD+18 | H23: DB+09 | J23: DB+9 | L23: DA+0 | N23: DB+9 | P23: DA+6 | R23: DA+6 | T23: DB+09
B24: Benching &RC | D24: RC | F24: RC | H24: Benching &RC | L24: Benching Required | R24: Benching &RC | T24: Benching &RC
B26: =T17+1 -> 20 | D26: =B26+1 -> 21 | F26: =D26+1 -> 22 | H26: =F26+1 -> 23 | J26: =H26+1 -> 24 | L26: =J26+1 -> 25 | N26: =L26+1 -> 26 | P26: =N26+1 -> 27 | R26: =P26+1 -> 28 | T26: =R26+1 -> 29
C28: 417.38 | E28: 304.56 | G28: 408.66 | I28: 434.89 | K28: 408.17 | M28: 398.59 | O28: 446.37 | Q28: 297.58 | S28: 240.47 | U28: 312.69 | V28: =C28+G28+I28+K28+M28+E28+O28+Q28+S28+U28 -> 3669.36
B31: AP58 | D31: AP59 | F31: 59/1 | H31: AP60 | J31: 60/1 | L31: 60/2 | N31: 60/3 | P31: AP61 | R31: 61/1 | T31: AP62
B32: DB+09 | D32: DC+09 | F32: DA+0 | H32: DD+00 | J32: DA+9 | L32: DA+0 | N32: DA+9 | P32: DC+00 | R32: DA+9 | T32: DB+00
F33: Benching | N33: RC
B35: =T26+1 -> 30 | D35: =B35+1 -> 31 | F35: =D35+1 -> 32 | H35: =F35+1 -> 33 | J35: =H35+1 -> 34 | L35: =J35+1 -> 35 | N35: =L35+1 -> 36 | P35: =N35+1 -> 37 | R35: =P35+1 -> 38 | T35: =R35+1 -> 39
C37: 347.88 | E37: 379.25 | G37: 398.7 | I37: 439.06 | K37: 381.53 | M37: 379.71 | O37: 426.3 | Q37: 387.14 | U37: 423.77 | V37: =C37+G37+I37+K37+M37+E37+#REF!+O37+Q37+#REF! -> #REF!
B40: 62/1 | D40: 62/2 | F40: 62/3 | H40: 62/4 | J40: 62/5 | L40: AP63 | N40: 63/1 | P40: AP64 | R40: 64/1 | T40: 64/2
B41: DA+0 | D41: DA+0 | F41: DA+09 | H41: DA+06 | J41: DA+06 | L41: DC+00 | N41: DA+0 | P41: DC+09 | R41: DA+9 | T41: DA+9
B42: RC | F42: RC | P42: Benching &RC | T42: RC
B43: =T35+1 -> 40 | D43: =B43+1 -> 41 | F43: =D43+1 -> 42 | H43: =F43+1 -> 43 | J43: =H43+1 -> 44 | L43: =J43+1 -> 45 | N43: =L43+1 -> 46 | P43: =N43+1 -> 47 | R43: =P43+1 -> 48 | T43: =R43+1 -> 49
C45: 407.9 | E45: 426.63 | G45: 392.27 | I45: 431.96 | K45: 426.02 | M45: 405.36 | O45: 411.93 | Q45: 423.77 | S45: 407.9 | U45: 426.63
B46: F | D46: WIP | R46: F | T46: F
B48: 64/3 | D48: 64/4 | F48: 64/5 | H48: 64/6 | J48: 64/7 | L48: 65/0 | N48: 65/1 | P48: 66/0 | R48: 66/1 | T48: 66/2
B49: DA+9 | D49: DA+9 | F49: DA+9 | H49: DA+3 | J49: DA+3 | L49: DD+0 | N49: DB+09 | P49: DD+0 | R49: DA+9 | T49: DA+0 | V49: =#REF!+I77+K77+M77+O77+G77+Q77+S77+#REF!+#REF! -> #REF!
P50: RC
B51: =T43+1 -> 50 | D51: =B51+1 -> 51 | F51: =D51+1 -> 52 | H51: =F51+1 -> 53 | J51: =H51+1 -> 54 | L51: =J51+1 -> 55 | N51: =L51+1 -> 56 | P51: =N51+1 -> 57 | R51: =P51+1 -> 58 | T51: =R51+1 -> 59
C53: 392.27 | E53: 431.96 | G53: 426.02 | I53: 405.36 | K53: 411.93 | M53: 350.33 | O53: 378.3 | Q53: 416.82 | S53: 371.85
B54: WIP
B56: 66/3 | D56: 66/4 | F56: 67/0 | H56: 67/1 | J56: 67/2 | L56: AP68 | N56: AP69 | P56: 69/1 | R56: 69/2 | T56: 69/3
B57: DA+3 | D57: DA+9 | F57: DC+6 | H57: DA+6 | J57: DB+0 | L57: DB+09 | N57: DD+3 | P57: DA+6 | R57: DA+0 | T57: DA+00
F58: RC | R58: Benching | T58: RC | V58: =A85+I77+K77+M77+O77+G77+Q77+S77+#REF!+C77 -> #REF!
B59: =T51+1 -> 60 | D59: =B59+1 -> 61 | F59: =D59+1 -> 62 | H59: =F59+1 -> 63 | J59: =H59+1 -> 64 | L59: =J59+1 -> 65 | N59: =L59+1 -> 66 | P59: =N59+1 -> 67 | R59: =P59+1 -> 68 | T59: =R59+1 -> 69
C61: 392.27 | E61: 431.96 | G61: 426.02 | I61: 405.36 | K61: 411.93 | M61: 350.33 | O61: 378.3 | Q61: 416.82 | S61: 371.85
T62: F
B64: AP71 | D64: 71/1 | F64: 71/2 | H64: 71/3 | J64: AP72 | L64: 72/1 | N64: 72/2 | P64: AP73 | R64: 73/1 | T64: 73/2
B65: DB+00 | D65: DA+09 | F65: DA+00 | H65: DA+00 | J65: DD+00 | L65: DA+03 | N65: DA+03 | P65: DB+00 | R65: DA+00 | T65: DA+09
H66: RC | J66: Benching &RC | L66: RC | R66: Benching & RC | T66: CLEAR | V66: =A93+I85+K85+M85+O85+G85+Q85+S85+U85+C85 -> 3994.99
B67: =T59+1 -> 70 | D67: =B67+1 -> 71 | F67: =D67+1 -> 72 | H67: =F67+1 -> 73 | J67: =H67+1 -> 74 | L67: =J67+1 -> 75 | N67: =L67+1 -> 76 | P67: =N67+1 -> 77 | R67: =P67+1 -> 78 | T67: =R67+1 -> 79
C69: 385.17 | E69: 345.19 | G69: 332.38 | I69: 393.62 | K69: 387.95 | M69: 340.35 | O69: 393.12 | Q69: 328.54 | S69: 398.52
B70: F | F70: F | J70: F | L70: F | N70: F | P70: F | R70: F | T70: F
B71: Er | J71: Er | L71: Er | N71: Er | T71: Er
B72: 73/3 | D72: AP74 | F72: 74/1 | H72: AP75 | J72: 75/1 | L72: 75/2 | N72: 75/3 | P72: 75/4 | R72: 75/5 | T72: 75/6
B73: DA+09 | D73: DB+09 | F73: DA+0 | H73: DC+0 | J73: DA+00 | L73: DA+0 | N73: DA+3 | P73: DA+0 | R73: DA+0 | T73: DA+0
B74: CLEAR | H74: Benching | J74: Benching | L74: Benching &RC
B75: =T67+1 -> 80 | D75: =B75+1 -> 81 | F75: =D75+1 -> 82 | H75: =F75+1 -> 83 | J75: =H75+1 -> 84 | L75: =J75+1 -> 85 | N75: =L75+1 -> 86 | P75: =N75+1 -> 87 | R75: =P75+1 -> 88 | T75: =R75+1 -> 89
G77: 388.46 | I77: 380.96 | K77: 374.03 | M77: 351.96 | O77: 395.64 | Q77: 414.76 | S77: 401.93
B78: F | F78: F | J78: F | L78: F | N78: F | P78: F | R78: F
B79: Er | J79: Er | P79: Er | R79: Er
B80: 75/7 | D80: AP76 | F80: 76/1 | H80: 77/0 | J80: 77/1 | L80: 77/2 | N80: 77/3 | P80: 77/4 | R80: 77/5 | T80: AP78
B81: DA+0 | D81: DC+00 | F81: DA+06 | H81: DB+00 | J81: DA+00 | L81: DA+03 | N81: DA+00 | P81: DA+03 | R81: DA+06 | T81: DC+00
F82: Clear | L82: Benching
B83: =T75+1 -> 90 | D83: =B83+1 -> 91 | F83: =D83+1 -> 92 | H83: =F83+1 -> 93 | J83: =H83+1 -> 94 | L83: =J83+1 -> 95 | N83: =L83+1 -> 96 | P83: =N83+1 -> 97 | R83: =P83+1 -> 98 | T83: =R83+1 -> 99
C85: 385.54 | G85: 351.18 | I85: 441.06 | K85: 387.5 | M85: 372.63 | O85: 415.3 | Q85: 424.58 | S85: 391.7 | U85: 410.47
F86: F | L86: F
F87: Er
B88: 78/1 | D88: AP79 | F88: 79/1 | H88: 79/2 | J88: AP80 | L88: 80/1 | N88: AP81 | P88: 81/1 | R88: 81/2 | T88: 81/3
B89: DA+03 | D89: DD+00 | F89: DA+09 | H89: DA+00 | J89: DB+03 | L89: DA+9 | N89: DB+09 | P89: DA+00 | R89: DA+03 | T89: DA+00
F90: Clear | H90: RC,Benching | L90: Benching | P90: Benching &RC
B91: =T83+1 -> 100 | D91: =B91+1 -> 101 | F91: =D91+1 -> 102 | H91: =F91+1 -> 103 | J91: =H91+1 -> 104 | L91: =J91+1 -> 105 | N91: =L91+1 -> 106 | P91: =N91+1 -> 107 | R91: =P91+1 -> 108 | T91: =R91+1 -> 109
V92: =G110+K110+M110+O110+Q110+I110+S110+#REF!+C110+#REF! -> #REF!
A93: 415.03 | C93: 416.87 | G93: 426.47 | I93: 396.98 | K93: 429.38 | M93: 403.83 | O93: 384.63 | Q93: 380.68 | S93: 354.53
B94: ROW | N94: F
B95: U/P
B96: 81/4 | D96: 81/5 | F96: AP82 | H96: 82/1 | J96: 82/2 | L96: AP83 | N96: 83/1 | P96: AP84 | R96: AP85 | T96: 85/1
B97: DA+00 | D97: DA+06 | F97: DB+03 | H97: DA+00 | J97: DA+03 | L97: DC+00 | N97: DA+03 | P97: DC+06 | R97: DC+00 | T97: DA+00
H98: RC | T98: CLEAR
B99: =T91+1 -> 110 | D99: =B99+1 -> 111 | F99: =D99+1 -> 112 | H99: =F99+1 -> 113 | J99: =H99+1 -> 114 | L99: =J99+1 -> 115 | N99: =L99+1 -> 116 | P99: =N99+1 -> 117 | R99: =P99+1 -> 118 | T99: =R99+1 -> 119
V100: =G117+K117+O117+Q117+S117+I117+U117+Q125+C117+U100 -> 3121.94
C101: 395.01 | D101: =#REF!+I93+K93+M93+O93+G93+Q93+S93+#REF!+C93 -> #REF! | G101: 380.77 | I101: 411.81 | K101: 432.08 | M101: 256.87 | O101: 412.4 | Q101: 382.17 | S101: 452.74
F102: F
B104: AP86 | D104: 86/1 | F104: 86/2 | H104: AP87 | J104: 87/1 | L104: 87/2 | N104: AP88 | P104: AP89 | R104: 89/1 | T104: AP90
B105: DD+00 | D105: DA+06 | F105: DA+00 | H105: DC+00 | J105: DA+03 | L105: DA+09 | N105: DC+00 | P105: DC+00 | R105: DA+09 | T105: DC+00
B106: CLEAR | D106: CLEAR | F106: CLEAR
B108: =T99+1 -> 120 | D108: =B108+1 -> 121 | F108: =D108+1 -> 122 | H108: =F108+1 -> 123 | J108: =H108+1 -> 124 | L108: =J108+1 -> 125 | N108: =L108+1 -> 126 | P108: =N108+1 -> 127 | R108: =P108+1 -> 128 | T108: =R108+1 -> 129
V109: =G101+K101+M101+O101+Q101+I101+S101+#REF!+C101+U109 -> #REF!
C110: 430.39 | G110: 378.62 | I110: 350.22 | K110: 357.91 | M110: 237.48 | O110: 440.03 | Q110: 504 | S110: 430.57
B113: 90/1 | D113: AP91 | F113: 91/1 | H113: 91/2 | J113: 91/3 | L113: AP92 | N113: AP93 | P113: AP94 | R113: AP95 | T113: 95/1
B114: DA+09 | D114: DD+00 | F114: DA+00 | H114: DA+00 | J114: DA+00 | L114: DC+00 | N114: DC+00 | P114: DB+06 | R114: DB+06 | T114: DB+00
B115: =T108+1 -> 130 | D115: =B115+1 -> 131 | F115: =D115+1 -> 132 | H115: =F115+1 -> 133 | J115: =H115+1 -> 134 | L115: =J115+1 -> 135 | N115: =L115+1 -> 136 | P115: =N115+1 -> 137 | R115: =P115+1 -> 138 | T115: =R115+1 -> 139 | V115: 130
C117: 354.92 | G117: 419.38 | I117: 406.18 | K117: 427.47 | O117: 416.77 | Q117: 378.13 | S117: 358.57 | U117: 360.52
F118: F | J118: F
B120: 95/2 | D120: 95A/0 | F120: 95A/1 | H120: AP96 | J120: 96/1 | L120: 96/2 | N120: AP97 | P120: 97/1 | R120: AP98 | T120: AP98/1 | V120: 98A/0
B121: DA+09 | D121: DB+0 | F121: DA+00 | H121: DC+00 | J121: DA+00 | L121: DA+00 | N121: DC+00 | P121: DA+03 | R121: DC+00 | T121: DA+00 | V121: DC+00
P122: RC
B123: =V115+1 -> 131 | D123: =B123+1 -> 132 | F123: =D123+1 -> 133 | H123: =F123+1 -> 134 | J123: =H123+1 -> 135 | L123: =J123+1 -> 136 | N123: =L123+1 -> 137 | P123: =N123+1 -> 138 | R123: =P123+1 -> 139 | T123: =R123+1 -> 140 | V123: =T123+1 -> 141
B128: 98A/1 | D128: 98B/0 | F128: 98B/1 | H128: 98B/2 | J128: 99/0 | L128: 99/1 | N128: 99/2 | P128: 99/3 | R128: 99/4 | T128: 99/5 | V128: 99/6
B129: DA+00 | D129: DD+00 | F129: DA+00 | H129: DCT+00 | J129: DC+0 | L129: DA+06 | N129: DA+00 | P129: DA+00 | R129: DA+06 | T129: DA+03 | V129: DA+03
F130: RC | P130: RC
B132: =V123+1 -> 142 | D132: =B132+1 -> 143 | F132: =D132+1 -> 144 | H132: =F132+1 -> 145 | J132: =H132+1 -> 146 | L132: =J132+1 -> 147 | N132: =L132+1 -> 148 | P132: =N132+1 -> 149 | R132: =P132+1 -> 150 | T132: =R132+1 -> 151 | V132: =T132+1 -> 152
B137: AP99A | D137: 99A/1 | F137: 99A/2 | H137: AP100 | J137: 100/1 | L137: AP101 | N137: AP102 | P137: 102/1 | R137: 102/2 | T137: AP103 | V137: 103/1
B138: DB+00 | D138: DA+00 | F138: DA+00 | H138: DC+00 | J138: DA+6 | L138: DD+06 | N138: DD+3 | P138: DA+00 | R138: DA+00 | T138: DC+0 | V138: DA+6
B141: =V132+1 -> 153 | D141: =B141+1 -> 154 | F141: =D141+1 -> 155 | H141: =F141+1 -> 156 | J141: =H141+1 -> 157 | L141: =J141+1 -> 158 | N141: =L141+1 -> 159 | P141: =N141+1 -> 160 | R141: =P141+1 -> 161 | T141: =R141+1 -> 162 | V141: =T141+1 -> 163
B146: AP104 | D146: AP104A | F146: AP104B | H146: 104B/1 | J146: 104B/2 | L146: AP105 | N146: 105/1 | P146: AP106 | R146: AP107
B147: DB+9 | D147: DC+9 | F147: DB+9 | H147: DA+0 | J147: DA+0 | L147: DD+0 | N147: DA+3 | P147: DC+6 | R147: DD+3
...

Sheet VC
C2: TB-507 400 KV (Twin) D/C Fatehgarh IV - Bhinmal Transmission Line
C3: DPR and VISUAL CHART
C5: DPR- | F5: District | H5: No.Of Towers | I5: Length | J5: Foundation | M5: Earthing | N5: Tower Erection | Q5: Stringing
J6: Com | K6: WIP | L6: Bal | M6: Com | N6: Com | O6: WIP | P6: Bal | Q6: Com | R6: WIP | S6: Bal
H7: 495 | I7: 187.175 | J7: 9 | K7: 5 | L7: =H7-J7-K7 -> 481 | M7: 3 | P7: =H7-N7 -> 495 | S7: =I7-Q7 -> 187.175
I8: r
C9: 1 | E9: =C9+1 -> 2 | G9: =E9+1 -> 3 | I9: =G9+1 -> 4 | K9: =I9+1 -> 5 | M9: =K9+1 -> 6 | O9: =M9+1 -> 7 | Q9: =O9+1 -> 8 | S9: =Q9+1 -> 9 | U9: =S9+1 -> 10
D11: 97.4 | F11: 139.42 | H11: 484.04 | J11: 398 | L11: 443.16 | N11: 399.53 | P11: 402.87 | R11: 437.15 | T11: 381.84 | V11: 416.91 | W11: =D11+H11+J11+L11+N11+F11+P11+R11+T11+V11 -> 3600.32 | X11: FDN | Y11: TE | Z11: Earthing | AA11: Stringing | AC11: Tack Welding | AE11: =SUM(D11:V11) -> 3600.32
A12: 1 | X12: =COUNTIF(C12:U12,"F") -> 0 | Y12: =COUNTIF(C11:U11,"E") -> 0 | Z12: =COUNTIF(C13:V13,"Er") -> 0 | AB12: COM
X13: =COUNTIF(C13:U13,"U/P") -> 0 | Y13: 0 | Z13: 0 | AB13: WIP
C14: GE | E14: AP1 | G14: AP2 | I14: AP3 | K14: 03/1 | M14: 3/2 | O14: 3/3 | Q14: 3/4 | S14: 3/5 | U14: 3/6 | X14: =COUNTIF(C12:U12,"ROW") -> 0 | Y14: 0 | Z14: 0 | AB14: ROW
E15: DD+03 | G15: DD+9 | I15: DC+9 | K15: DA+9 | M15: DA+0 | O15: DA+3 | Q15: DA+6 | S15: DA+3 | U15: DA+00
C17: =U9+1 -> 11 | E17: =C17+1 -> 12 | G17: =E17+1 -> 13 | I17: =G17+1 -> 14 | K17: =I17+1 -> 15 | M17: =K17+1 -> 16 | O17: =M17+1 -> 17 | Q17: =O17+1 -> 18 | S17: =Q17+1 -> 19 | U17: =S17+1 -> 20
D19: 428.12 | F19: 249.58 | H19: 454.54 | J19: 377.83 | L19: 447.64 | N19: 396.44 | P19: 445.93 | R19: 156.98 | T19: 409.67 | V19: 382.38 | W19: =D19+H19+J19+L19+N19+F19+P19+R19+T19+V19 -> 3749.11 | AE19: =SUM(D19:V19) -> 3749.11
A20: =A12+1 -> 2 | X20: =COUNTIF(C20:U20,"F") -> 0 | Y20: =COUNTIF(C19:U19,"E") -> 0 | Z20: =COUNTIF(C21:V21,"Er") -> 0 | AB20: COM
X21: =COUNTIF(C21:U21,"U/P") -> 0 | Y21: 0 | Z21: 0 | AB21: WIP
C22: 3/7 | E22: 3/8 | G22: AP4 | I22: 4/1 | K22: AP5 | M22: 5/1 | O22: 5/2 | Q22: AP6 | S22: AP7 | U22: 7/1 | X22: =COUNTIF(C20:U20,"ROW") -> 0 | Y22: 0 | Z22: 0 | AB22: ROW
C23: DA+03 | E23: DD+03 RC | G23: DD+03 | I23: DA+09 | K23: DC+3 | M23: DA+06 | O23: DA+03 | Q23: DD+09 | S23: DD+09 | U23: DA+00
C25: =U17+1 -> 21 | E25: =C25+1 -> 22 | G25: =E25+1 -> 23 | I25: =G25+1 -> 24 | K25: =I25+1 -> 25 | M25: =K25+1 -> 26 | O25: =M25+1 -> 27 | Q25: =O25+1 -> 28 | S25: =Q25+1 -> 29 | U25: =S25+1 -> 30
D27: 353.89 | F27: 385.21 | H27: 367.67 | J27: 378.32 | L27: 392.49 | N27: 399.24 | P27: 390.93 | R27: 412.07 | T27: 421.95 | V27: 391.87 | W27: =D27+H27+J27+L27+N27+F27+P27+R27+T27+V27 -> 3893.64 | AE27: =SUM(D27:V27) -> 3893.64
A28: =A20+1 -> 3 | X28: =COUNTIF(C28:U28,"F") -> 0 | Y28: =COUNTIF(C27:U27,"E") -> 0 | Z28: =COUNTIF(C29:V29,"Er") -> 0 | AB28: COM
X29: =COUNTIF(C29:U29,"U/P") -> 0 | Y29: 0 | Z29: 0 | AB29: WIP
C30: 7/2 | E30: 7/3 | G30: 7/4 | I30: 7/5 | K30: 7/6 | M30: '7/7 | O30: AP8 | Q30: 08/01 | S30: 08/2 | U30: 08/3 | X30: =COUNTIF(C28:U28,"ROW") -> 0 | Y30: 0 | Z30: 0 | AB30: ROW
C31: DA+00 | E31: DA+00 | G31: DA+00 | I31: DA+00 | K31: DA+00 | M31: DA+00 | O31: DB+00 | Q31: DA+06 | S31: DA+00 | U31: DA+00
C33: =U25+1 -> 31 | E33: =C33+1 -> 32 | G33: =E33+1 -> 33 | I33: =G33+1 -> 34 | K33: =I33+1 -> 35 | M33: =K33+1 -> 36 | O33: =M33+1 -> 37 | Q33: =O33+1 -> 38 | S33: =Q33+1 -> 39 | U33: =S33+1 -> 40
D35: 406.65 | F35: 383.31 | H35: 402.96 | J35: 433.9 | L35: 328.55 | N35: 331.44 | P35: 358.83 | R35: 358.55 | T35: 429.37 | V35: 354.9 | W35: =D35+H35+J35+L35+N35+F35+P35+R35+T35+V35 -> 3788.46 | AE35: =SUM(D35:V35) -> 3788.46
A36: =A28+1 -> 4 | X36: =COUNTIF(C36:U36,"F") -> 0 | Y36: =COUNTIF(C35:U35,"E") -> 0 | Z36: =COUNTIF(C37:V37,"Er") -> 0 | AB36: COM
X37: =COUNTIF(C37:U37,"U/P") -> 0 | Y37: 0 | Z37: 0 | AB37: WIP
C38: 08/4 | E38: 08/5 | G38: 08/6 | I38: 08/7 | K38: AP9 | M38: 09/01 | O38: 09/02 | Q38: 09/03 | S38: 09/04 | U38: 09/05 | X38: =COUNTIF(C36:U36,"ROW") -> 0 | Y38: 0 | Z38: 0 | AB38: ROW
C39: DA+03 | E39: DA+00 | G39: DA+06 | I39: DA+06 | K39: DB+00 | M39: DA+00 | O39: DA+00 | Q39: DA+00 | S39: DA+00 | U39: DA+00
C41: =U33+1 -> 41 | E41: =C41+1 -> 42 | G41: =E41+1 -> 43 | I41: =G41+1 -> 44 | K41: =I41+1 -> 45 | M41: =K41+1 -> 46 | O41: =M41+1 -> 47 | Q41: =O41+1 -> 48 | S41: =Q41+1 -> 49 | U41: =S41+1 -> 50
D43: 340.94 | F43: 405.66 | H43: 409.41 | J43: 378.36 | L43: 322.47 | N43: 386.39 | P43: 386.19 | R43: 406.2 | T43: 351.15 | V43: 380.59 | W43: =D43+H43+J43+L43+N43+F43+P43+R43+T43+V43 -> 3767.36 | AE43: =SUM(D43:V43) -> 3767.36
A44: =A36+1 -> 5 | X44: =COUNTIF(C44:U44,"F") -> 0 | Y44: =COUNTIF(C43:U43,"E") -> 0 | Z44: =COUNTIF(C45:V45,"Er") -> 0 | AB44: COM
X45: =COUNTIF(C45:U45,"U/P") -> 0 | Y45: 0 | Z45: 0 | AB45: WIP
C46: 09/06 | E46: AP10 | G46: 10/01 | I46: 10/02 | K46: 10/03 | M46: 10/04 | O46: 10/05 | Q46: 10/06 | S46: 10/07 | U46: 10/08 | X46: =COUNTIF(C44:U44,"ROW") -> 0 | Y46: 0 | Z46: 0 | AB46: ROW
C47: DA+00 | E47: DC+9 | G47: DA+09 | I47: DA+00 | K47: DA+00 | M47: DA+00 | O47: DA+00 | Q47: DA+00 | S47: DA+00 | U47: DA+00
C49: =U41+1 -> 51 | E49: =C49+1 -> 52 | G49: =E49+1 -> 53 | I49: =G49+1 -> 54 | K49: =I49+1 -> 55 | M49: =K49+1 -> 56 | O49: =M49+1 -> 57 | Q49: =O49+1 -> 58 | S49: =Q49+1 -> 59 | U49: =S49+1 -> 60
D51: 380.02 | F51: 393.7 | H51: 390.68 | J51: 349.16 | L51: 416.01 | N51: 400.75 | P51: 406.84 | R51: 404.76 | T51: 311.74 | V51: 389.98 | W51: =D51+H51+J51+L51+N51+F51+P51+R51+T51+V51 -> 3843.64 | AE51: =SUM(D51:V51) -> 3843.64
A52: =A44+1 -> 6 | X52: =COUNTIF(C52:U52,"F") -> 0 | Y52: =COUNTIF(C51:U51,"E") -> 0 | Z52: =COUNTIF(C53:V53,"Er") -> 0 | AB52: COM
X53: =COUNTIF(C53:U53,"U/P") -> 0 | Y53: 0 | Z53: 0 | AB53: WIP
C54: 10/09 | E54: AP11 | G54: 11/01 | I54: AP12 | K54: 12/01 | M54: 12/02 | O54: 12/03 | Q54: 12/04 | S54: 12/05 | U54: 12/06 | X54: =COUNTIF(C52:U52,"ROW") -> 0 | Y54: 0 | Z54: 0 | AB54: ROW
C55: DA+00 | E55: DC+00 | G55: DA+03 | I55: DD+00 | K55: DA+03 | M55: DA+03 | O55: DA+00 | Q55: DA+03 | S55: DA+00 | U55: DA+00
C57: =U49+1 -> 61 | E57: =C57+1 -> 62 | G57: =E57+1 -> 63 | I57: =G57+1 -> 64 | K57: =I57+1 -> 65 | M57: =K57+1 -> 66 | O57: =M57+1 -> 67 | Q57: =O57+1 -> 68 | S57: =Q57+1 -> 69 | U57: =S57+1 -> 70
D59: 384.15 | F59: 350.96 | H59: 437.11 | J59: 406.67 | L59: 421.42 | N59: 421.75 | P59: 380.8 | R59: 438.78 | T59: 426.5 | V59: 375.59 | W59: =N59+R59+T59+V59+D68+P59+F68+H68+J68+L68 -> 4066.13 | AE59: =SUM(D59:V59) -> 4043.73
A60: =A52+1 -> 7 | X60: =COUNTIF(C60:U60,"F") -> 0 | Y60: =COUNTIF(C59:U59,"E") -> 0 | Z60: =COUNTIF(C61:V61,"Er") -> 0 | AB60: COM
X61: =COUNTIF(C61:U61,"U/P") -> 0 | Y61: 0 | Z61: 0 | AB61: WIP
C62: 12/07 | E62: 12/08 | G62: AP13 | I62: 13/01 | K62: 13/02 | M62: 13/03 | O62: 13/04 | Q62: AP14 | S62: AP15 | U62: 15/01 | X62: =COUNTIF(C60:U60,"ROW") -> 0 | Y62: 0 | Z62: 0 | AB62: ROW
C63: DA+00 | E63: DA+00 | G63: DC+00 | I63: DA+09 | K63: DA+00 | M63: DA+06 | O63: DA+03 | Q63: DB+09 | S63: DC+06 | U63: DA+03
O65: Paddy
C66: =U57+1 -> 71 | E66: =C66+1 -> 72 | G66: =E66+1 -> 73 | I66: =G66+1 -> 74 | K66: =I66+1 -> 75 | M66: =K66+1 -> 76 | O66: =M66+1 -> 77 | Q66: =O66+1 -> 78 | S66: =Q66+1 -> 79 | U66: =S66+1 -> 80
D68: 413.56 | F68: 407.62 | H68: 397.38 | J68: 408.9 | L68: 395.25 | N68: 384.81 | P68: 388.05 | R68: 362.31 | T68: 359.92 | V68: 386.31 | W68: =#REF!+R68+T68+V68+N68+P68+#REF!+#REF!+#REF!+#REF! -> #REF! | AE68: =SUM(D68:V68) -> 3904.11
A69: =A60+1 -> 8 | X69: =COUNTIF(C69:U69,"F") -> 0 | Y69: =COUNTIF(C68:U68,"E") -> 0 | Z69: =COUNTIF(C70:V70,"Er") -> 0 | AB69: COM
X70: =COUNTIF(C70:U70,"U/P") -> 0 | Y70: 0 | Z70: 0 | AB70: WIP
C71: 15/02 | E71: 15/03 | G71: AP16 | I71: 16/01 | K71: 16/02 | M71: 16/03 | O71: 16/04 | Q71: 16/05 | S71: 16/06 | U71: 16/07 | X71: =COUNTIF(C69:U69,"ROW") -> 0 | Y71: 0 | Z71: 0 | AB71: ROW
C72: DA+03 | E72: DA+06 | G72: DC+00 | I72: DA+03 | K72: DA+09 | M72: DA+00 | O72: DA+00 | Q72: DA+00 | S72: DA+00 | U72: DA+00
M74: Paddy
C75: =U66+1 -> 81 | E75: =C75+1 -> 82 | G75: =E75+1 -> 83 | I75: =G75+1 -> 84 | K75: =I75+1 -> 85 | M75: =K75+1 -> 86 | O75: =M75+1 -> 87 | Q75: =O75+1 -> 88 | S75: =Q75+1 -> 89 | U75: =S75+1 -> 90
D77: 319.93 | F77: 342.16 | H77: 384.83 | J77: 365.71 | L77: 394.61 | N77: 315.81 | P77: 419.79 | R77: 418.97 | T77: 420.65 | V77: 422.09 | W77: =D77+H77+J77+L77+N77+F77+P77+R77+T77+V77 -> 3804.55 | AE77: =SUM(D77:V77) -> 3804.55
A78: =A69+1 -> 9 | X78: =COUNTIF(C78:U78,"F") -> 0 | Y78: =COUNTIF(C77:U77,"E") -> 0 | Z78: =COUNTIF(C79:V79,"Er") -> 0 | AB78: COM
X79: =COUNTIF(C79:U79,"U/P") -> 0 | Y79: 0 | Z79: 0 | AB79: WIP
C80: 16/08 | E80: AP17 | G80: 17/01 | I80: 17/02 | K80: 17/03 | M80: AP18 | O80: AP19 | Q80: AP20 | S80: 20/01 | U80: 20/02 | X80: =COUNTIF(C78:U78,"ROW") -> 0 | Y80: 0 | Z80: 0 | AB80: ROW
C81: DA+00 | E81: DB+0 | G81: DA+00 | I81: DA+00 | K81: DA+03 | M81: DB+00 | O81: DB+06 | Q81: DB+09 | S81: DA+03 | U81: DA+00
M83: Paddy | S83: Paddy
C84: =U75+1 -> 91 | E84: =C84+1 -> 92 | G84: =E84+1 -> 93 | I84: =G84+1 -> 94 | K84: =I84+1 -> 95 | M84: =K84+1 -> 96 | O84: =M84+1 -> 97 | Q84: =O84+1 -> 98 | S84: =Q84+1 -> 99 | U84: =S84+1 -> 100
D86: 420.49 | F86: 459.09 | H86: 386.28 | J86: 273.16 | L86: 313.62 | N86: 361.38 | P86: 308.79 | R86: 332.52 | T86: 269.07 | V86: 357.59 | W86: =D86+H86+J86+L86+N86+F86+P86+R86+T86+V86 -> 3481.99 | AE86: =SUM(D86:V86) -> 3481.99
A87: =A78+1 -> 10 | X87: =COUNTIF(C87:U87,"F") -> 0 | Y87: =COUNTIF(C86:U86,"E") -> 0 | Z87: =COUNTIF(C88:V88,"Er") -> 0 | AB87: COM
X88: =COUNTIF(C88:U88,"U/P") -> 0 | Y88: 0 | Z88: 0 | AB88: WIP
C89: 20/03 | E89: 20/04 | G89: 20/05 | I89: AP21 | K89: 21/01 | M89: 21/02 | O89: 21/03 | Q89: AP22 | S89: 22/01 | U89: 22/02 | X89: =COUNTIF(C87:U87,"ROW") -> 0 | Y89: 0 | Z89: 0 | AB89: ROW
C90: DA+06 | E90: DB+00 | G90: DA+09 | I90: DC+09 | K90: DA+03 | M90: DA+06 | O90: DA+00 | Q90: DC+09 | S90: DA+03 | U90: DA+06
O92: Paddy | U92: Paddy
C93: =U84+1 -> 101 | E93: =C93+1 -> 102 | G93: =E93+1 -> 103 | I93: =G93+1 -> 104 | K93: =I93+1 -> 105 | M93: =K93+1 -> 106 | O93: =M93+1 -> 107 | Q93: =O93+1 -> 108 | S93: =Q93+1 -> 109 | U93: =S93+1 -> 110
D95: 201.38 | F95: 218.35 | H95: 439.11 | J95: 365.6 | L95: 424.47 | N95: 412.73 | P95: 401.93 | R95: 379.06 | T95: 404.19 | V95: 441.06 | W95: =D95+H95+J95+L95+N95+F95+P95+R95+T95+V95 -> 3687.88 | AE95: =SUM(D95:V95) -> 3687.88
A96: =A87+1 -> 11 | X96: =COUNTIF(C96:U96,"F") -> 0 | Y96: =COUNTIF(C95:U95,"E") -> 0 | Z96: =COUNTIF(C97:V97,"Er") -> 0 | AB96: COM
X97: =COUNTIF(C97:U97,"U/P") -> 0 | Y97: 0 | Z97: 0 | AB97: WIP
C98: AP23 | E98: AP24 | G98: AP25 | I98: 25/01 | K98: AP26 | M98: 26/01 | O98: 26/02 | Q98: 26/03 | S98: 26/04 | U98: 26/05 | X98: =COUNTIF(C96:U96,"ROW") -> 0 | Y98: 0 | Z98: 0 | AB98: ROW
C99: DD+18 | E99: DD+25 | G99: DD+06 | I99: DA+09 | K99: DC+09 | M99: DA+09 | O99: DA+06 | Q99: DA+03 | S99: DA+06 | U99: DA+03
E101: Paddy
C102: =U93+1 -> 111 | E102: =C102+1 -> 112 | G102: =E102+1 -> 113 | I102: =G102+1 -> 114 | K102: =I102+1 -> 115 | M102: =K102+1 -> 116 | O102: =M102+1 -> 117 | Q102: =O102+1 -> 118 | S102: =Q102+1 -> 119 | U102: =S102+1 -> 120
D104: 404.77 | F104: 386.79 | H104: 382.59 | J104: 460.27 | L104: 369.05 | N104: 447.91 | P104: 371.72 | R104: 373.16 | T104: 423.96 | V104: 381.03 | W104: =D104+H104+J104+L104+N104+F104+P104+R104+T104+V104 -> 4001.25 | AE104: =SUM(D104:V104) -> 4001.25
A105: =A96+1 -> 12 | X105: =COUNTIF(C105:U105,"F") -> 0 | Y105: =COUNTIF(C104:U104,"E") -> 0 | Z105: =COUNTIF(C106:V106,"Er") -> 0 | AB105: COM
X106: =COUNTIF(C106:U106,"U/P") -> 0 | Y106: 0 | Z106: 0 | AB106: WIP
C107: 26/06 | E107: AP27 | G107: 27/1 | I107: 27/2 | K107: AP28 | M107: 28/1 | O107: 28/2 | Q107: 28/3 | S107: 28/4 | U107: AP29 | X107: =COUNTIF(C105:U105,"ROW") -> 0 | Y107: 0 | Z107: 0 | AB107: ROW
C108: DA+06 | E108: DC+3 | G108: DA+09 | I108: DA+09 | K108: DB+0 | M108: DA+00 | O108: DA+09 | Q108: DA+00 | S108: DB+9 | U108: DC+3
Q110: Paddy
C111: =U102+1 -> 121 | E111: =C111+1 -> 122 | G111: =E111+1 -> 123 | I111: =G111+1 -> 124 | K111: =I111+1 -> 125 | M111: =K111+1 -> 126 | O111: =M111+1 -> 127 | Q111: =O111+1 -> 128 | S111: =Q111+1 -> 129 | U111: =S111+1 -> 130
D113: 419.6 | F113: 425.18 | H113: 287.54 | J113: 336.51 | L113: 325.3 | N113: 214.25 | P113: 455.95 | R113: 421.16 | T113: 423.79 | V113: 403.85 | W113: =D113+H113+J113+L113+D122+F113+F122+H122+J122+L122 -> 3725.44 | AE113: =SUM(D113:V113) -> 3713.13
A114: =A105+1 -> 13 | E114: ROW | K114: ROW | M114: ROW | X114: =COUNTIF(C114:U114,"F") -> 0 | Y114: =COUNTIF(C113:U113,"E") -> 0 | Z114: =COUNTIF(C115:V115,"Er") -> 0 | AB114: COM
X115: =COUNTIF(C115:U115,"U/P") -> 0 | Y115: 0 | Z115: 0 | AB115: WIP
C116: 29/1 | E116: 29/2 | G116: AP30 | I116: 30/1 | K116: 30/2 | M116: 30/3 | O116: AP31 | Q116: AP32 | S116: 32/1 | U116: 32/2 | X116: =COUNTIF(C114:U114,"ROW") -> 3 | Y116: 0 | Z116: 0 | AB116: ROW
C117: DA+06 | E117: DA+09 | G117: DC+0 | I117: DA+00 | K117: DA+00 | M117: DA+00 | O117: DC+9 | Q117: DC+9 | S117: DA+03 | U117: DA+03
U119: Paddy
C120: =U111+1 -> 131 | E120: =C120+1 -> 132 | G120: =E120+1 -> 133 | I120: =G120+1 -> 134 | K120: =I120+1 -> 135 | M120: =K120+1 -> 136 | O120: =M120+1 -> 137 | Q120: =O120+1 -> 138 | S120: =Q120+1 -> 139 | U120: =S120+1 -> 140
D122: 408.95 | F122: 324.03 | H122: 366.7 | J122: 473.31 | L122: 358.32 | N122: 477.82 | P122: 411.46 | R122: 406.23 | T122: 437.43 | V122: 455.92 | W122: =#REF!+#REF!+#REF!+#REF!+N122+#REF!+P122+R122+T122+V122 -> #REF! | AE122: =SUM(D122:V122) -> 4120.17
A123: =A114+1 -> 14 | X123: =COUNTIF(C123:U123,"F") -> 0 | Y123: =COUNTIF(C122:U122,"E") -> 0 | Z123: =COUNTIF(C124:V124,"Er") -> 0 | AB123: COM
X124: =COUNTIF(C124:U124,"U/P") -> 0 | Y124: 0 | Z124: 0 | AB124: WIP
C125: 32/3 | E125: AP33 | G125: AP34 | I125: 34/1 | K125: AP35 | M125: 35/1 | O125: AP36 | Q125: 36/1 | S125: 36/2 | U125: AP37 | X125: =COUNTIF(C123:U123,"ROW") -> 0 | Y125: 0 | Z125: 0 | AB125: ROW
C126: DA+09 | E126: DB+0 | G126: DC+6 | I126: DA+09 | K126: DC+9 | M126: DA+09 | O126: DC+9 | Q126: DA+09 | S126: DA+09 | U126: DD+3
C129: =U120+1 -> 141 | E129: =C129+1 -> 142 | G129: =E129+1 -> 143 | I129: =G129+1 -> 144 | K129: =I129+1 -> 145 | M129: =K129+1 -> 146 | O129: =M129+1 -> 147 | Q129: =O129+1 -> 148 | S129: =Q129+1 -> 149 | U129: =S129+1 -> 150
D131: 368.5 | F131: 419.77 | H131: 418.92 | J131: 386.49 | L131: 376.53 | N131: 404.74 | P131: 366.73 | R131: 274.59 | T131: 341.67 | V131: 425.86 | W131: =D131+H131+J131+L131+N131+F131+P131+R131+T131+V131 -> 3783.8 | AE131: =SUM(D131:V131) -> 3783.8
A132: =A123+1 -> 15 | X132: =COUNTIF(C132:U132,"F") -> 0 | Y132: =COUNTIF(C131:U131,"E") -> 0 | Z132: =COUNTIF(C133:V133,"Er") -> 0 | AB132: COM
...

Sheet ROW
A1: NAME OF PROJECT : FARHEGARH IV-BHINMAL 400KV D/C TRANSMISSION LINE
A2: Client : RAJASTHAN IV A POWER TRANSMISSION LTD.
A3: CONTRACTOR : KEC INTERNATIONAL LIMITED
A6: FOUNDATION STATUS
A7: SL. No. | B7: Location Number | C7: Span | D7: Tower Type | E7: AS PER RAPTL ROW CLEARED ON | F7: WORK COMMENCED KEC | G7: STATUS
A9: 1 | B9: 80/0
A10: =A9+1 -> 2 | B10: 66/4 | F10: ROW
A11: =A10+1 -> 3 | B11: 89/1 | F11: ROW
A12: =A11+1 -> 4 | B12: 102/1
A13: =A12+1 -> 5 | B13: 102/2 | F13: Anjana Const | H13: Previous Loc Done 99/2 on 25/4/2025
A14: =A13+1 -> 6 | B14: 107/1
A15: =A14+1 -> 7 | B15: 90/1 | F15: ROW
A16: =A15+1 -> 8 | B16: 81/1
A17: =A16+1 -> 9 | B17: 51/1
A18: =A17+1 -> 10 | B18: 99A/2
A19: =A18+1 -> 11 | B19: 61/1
A20: =A19+1 -> 12 | B20: 72/2
A21: =A20+1 -> 13 | B21: 73/1
A22: =A21+1 -> 14 | B22: 99/5
A23: =A22+1 -> 15 | B23: 56/2
A24: =A23+1 -> 16 | B24: 63/1
A25: =A24+1 -> 17 | B25: 114/1
A26: =A25+1 -> 18 | B26: 116/1
A27: =A26+1 -> 19 | B27: 56/1
... A40: =A39+1 -> 32 | B40: 147/7

Sheet June
B1: Sl No | C1: Loc No | D1: TOT | F1: Classification | G1: Starting Date | H1: Completion
B2: 1 | C2: 81/3 | D2: DA+0 | F2: Sandy | G2: 45799 | H2: 45812
B3: =B2+1 -> 2 | C3: 120/1 | D3: DA+6 | F3: Sandy | G3: 45807 | H3: 45813
B4: =B3+1 -> 3 | C4: 96/0 | D4: DC+0 | F4: DFR | G4: 45805 | H4: 45814
B5: =B4+1 -> 4 | C5: 75/0 | D5: DC+0 | F5: Sandy | G5: 45809 | H5: 45815
B6: =B5+1 -> 5 | C6: 147/2 | D6: DA+0 | F6: Sandy | G6: 45810 | H6: 45816
B7: =B6+1 -> 6 | C7: 82/2 | D7: DA+0 | F7: Sandy | G7: 45810 | H7: 45818
B8: =B7+1 -> 7 | C8: 79/0 | D8: DD+0 | F8: Sandy | G8: 45877 | H8: 45820
B9: =B8+1 -> 8 | C9: 147/5 | D9: DA+0 | F9: Sandy | G9: 45812 | H9: 45820
B10: =B9+1 -> 9 | C10: 119/0 | D10: DD+3 | F10: Sandy | G10: 45813 | H10: 45823
B11: =B10+1 -> 10 | C11: 82/1 | D11: DA+6 | F11: Sandy | G11: 45818 | H11: 45823
B12: =B11+1 -> 11 | C12: 147/0 | D12: DC+0 | F12: Sandy | G12: 45816 | H12: 45823
B13: =B12+1 -> 12 | C13: 78/0 | D13: DC+0 | F13: Sandy | G13: 45821 | H13: 45824
B14: =B13+1 -> 13 | C14: 147/4 | D14: DA+0 | F14: Sandy | G14: 45821 | H14: 45824
... B26: =B25+1 -> 25 | C26: 147/8 | D26: DA+0 | F26: Sandy | G26: 45833 | H26: 45838

Sheet Statutory Details
A1: Rajasthan IV A 400 KV LINE - STATUTORY APPROVAL STATUS
B2: KEC RESPONSIBILITY | F2: APRAAVA RESPONSIBILITY
A3: S N | B3: Loc No. | C3: Line Crossing | D3: Asset Owner | E3: Submission by KEC | F3: Submission to Asset Owner | G3: Date of Joint site visit | H3: Demand letter from Asset Owner | I3: Letter submission/ Demand fulfillment | J3: Date of NOC/ Approval | K3: Target date for NOC | L3: Status as on 31-03-2026 | M3: Remarks
A4: Power Line Crossing for Line (12 Nos)
A5: 1 | B5: AP 2 - 3/1 | C5: 400KV D/C | D5: APRAAVA | E5: 01.02.2026 | F5: 01.02.2026 | J5: Approved | L5: PL crossing Apraava's Line. Technical team approved during check survey
A6: 2 | B6: AP4-AP5 | C6: 220KV D/C | D6: AMPIN | E6: 01.04.2026 | K6: 30.04.2026
A7: 3 | B7: AP 5D - AP 5E | C7: 132KV S/C | D7: RRVPNL | E7: 21.02.2026 | F7: 06.03.2026 | K7: 15.04.2026 | L7: Joint Site visit planned by 7th April
A8: 4 | B8: AP 6D/5 - AP 7/0 | C8: 132KV D/C | D8: RRVPNL | E8: 21.02.2026 | F8: 06.03.2026 | K8: 15.04.2026 | L8: Joint Site visit planned by 7th April
A9: 5 | B9: AP25 - AP 26 | C9: 400KV D/C | D9: RRVPNL | E9: 25.09.2025 | F9: DONE | G9: DONE | J9: 07.11.2025
A10: 6 | B10: AP 27- AP 27A | C10: 220KV S/C | D10: RRVPNL | E10: 24.05.2025 | F10: 30.05.2025 | G10: 31.08.2025 | J10: 07.11.2025 | M10: Demand letter awiated
A11: 7 | B11: AP 50-AP 51 | C11: 220KV S/C | D11: RRVPNL | E11: 24.05.2025 | F11: 30.05.2025 | G11: 26.08.2025 | J11: 07.11.2025 | M11: Demand letter awiated | N11: Barmer
A12: 8 | B12: AP 58-AP 59 | C12: 132KV S/C | D12: RRVPNL | E12: 24.05.2025 | F12: 30.05.2025 | G12: 31.08.2025 | J12: 07.11.2025 | M12: Demand letter awiated
A13: 9 | B13: AP 111-AP 112 | C13: 132KV S/C | D13: RRVPNL | E13: 24.05.2025 | F13: 05.06.2025 | G13: 30.06.2025 | J13: 28.08.2025
A14: 10 | B14: AP 144-AP 145 | C14: 132KV S/C | D14: RRVPNL | E14: 24.05.2025 | F14: 05.06.2025 | G14: 30.06.2025 | J14: 28.08.2025 | N14: Sirohi
A15: 11 | B15: AP 152-AP 153 | C15: 220KV D/C | D15: RRVPNL | E15: 24.05.2025 | F15: 05.06.2025 | G15: 30.06.2025 | J15: 28.08.2025
A16: 12 | B16: AP 154-AP 155 | C16: 400KV D/C | D16: RRVPNL | E16: 25.09.2025 | F16: 21.11.2025 | G16: 28.01.2026 | J16: 17.02.2026
A17: NH/Expressway Crossing (02 Nos)
A18: 1 | B18: AP 43 - AP 44 | C18: Barmer-Jodhpur National Highway-25 | D18: NHAI | E18: 14.07.2025 | F18: 14.07.2025 | G18: 06.10.2025 | K18: 15.04.2026 | L18: Demand letter expected by 7th April
A19: 2 | B19: AP 121 - AP 122 | C19: Jamnagar-Amritsar Bharat Mala Expressway NH -754 | D19: NHAI | E19: 14.07.2025 | F19: 14.07.2025 | G19: 08.09.2025 | H19: 28.10.2025 | I19: 21.11.2025 | J19: 06.12.2025
A20: Railway Crossing (02 Nos)
A21: 1 | B21: AP 46 - AP 47 | C21: Barmer-Jodhpur Single Track Electrified | D21: NWR | E21: 14.07.2025 | F21: 03.08.2025 | G21: 27.08.2025 | H21: 13.11.2025 | I21: 19.11.2025 | J21: 13.11.2025
A22: 2 | B22: AP 150 - AP 151 | C22: Jalore-Bhinmal Single Track Electrified | D22: NWR | E22: 14.07.2025 | F22: 03.08.2025 | G22: 18.08.2025 | H22: 13.11.2025 | I22: 19.11.2025 | J22: 13.11.2025
A23: SH Crossing (07 Nos)
A24: 1 | B24: 5/6 - AP 5A/0 | C24: SH- 65 Sheo - Phalsund | D24: PWD | E24: 01.04.2026 | K24: 30.04.2026
A25: 2 | B25: AP 53-AP 54 | C25: Baytu (Balotra Road) -Chava (Barmer Road) | D25: PWD | E25: 31.05.2025 | F25: 25.06.2025 | G25: 13.08.2025 | J25: 15.10.2025
A26: 3 | B26: AP 71 - 71/1 | C26: Barmer-Sindhari | D26: PWD | E26: 31.05.2025 | F26: 25.06.2025 | G26: 26.08.2025 | H26: 24.09.2025 | I26: 45964 | J26: 45975
A27: 4 | B27: AP 92- AP 93 | C27: Sindhari-Gudamalani | D27: PWD | E27: 31.05.2025 | F27: 25.06.2025 | J27: 21.08.2025
A28: 5 | B28: 103/1-104/0 | C28: Bagoda-Sindhari SH | D28: PWD | E28: 21.02.2026 | F28: 06.03.2026 | K28: 15.04.2026 | L28: Joint Site visit planned by 7th April
A29: 6 | B29: 130/1 - AP 131 | C29: Bagoda-Sayla | D29: PWD | E29: 31.05.2025 | F29: 25.06.2025 | G29: 26.08.2025 | H29: 24.09.2025 | I29: 45964 | J29: 45975
A30: 7 | B30: AP 147/9 - AP 148 | C30: Siyawat/Daspa- Bhinmal | D30: PWD | E30: 31.05.2025 | F30: 25.06.2025 | G30: 26.08.2025 | H30: 24.09.2025 | I30: 45964 | J30: 45975
A31: Oil Line Crossing (06 Nos) | M31: Required document for final approval
A32: 1 | B32: AP 29 - AP 29/1 | C32: OIL Line | D32: Vedanta Cairn Oil & Pipeline | E32: 28.05.2025 | F32: 12.06.2025 | G32: 20.06.2025 | J32: 26.09.2025
A33: 2 | B33: AP 36A - AP 37 | C33: OIL Line | D33: Mangla Crude Oil Pipeline | E33: 28.05.2025 | F33: 11.06.2025 | G33: 10.07.2025 | H33: 17.11.2025 | I33: 31.12.2025 | K33: 46111 | L33: Hard copies submitted on 06.03.2026 | M33: 1. Joint agreement to be signed 2. Special contingency insurance policy (5cr) to be taken and policy shall be valid till one month after completion of work. 3. Supervision charges (E-payment mode) : Rs. 50,000 + 18% GST (Non-Refundable) 4. Processing fee (E-payment mode) : Rs. 25,000 + 18% GST (Non-Refundable) 5. Concrete slab work on pipeline at crossing to be done by Apraava.
A34: 3 | B34: AP 99B - AP 99C | C34: OIL Line | D34: GSPL | E34: 28.05.2025 | F34: 11.06.2025 | G34: 14.07.2025 | H34: 19.06.2025 | I34: 31.12.2025 | K34: 46111 | L34: Soft copies submitted through mail and hard copies will be submitted as per confirmation of address. | M34: 1. Joint agreement to be signed 2. Special contingency insurance policy (2.5cr) to be taken till the completion of work 3. Security deposit (DD) : Rs. 2 lakh - Refundable 4. Processing fee & Supervision charges (DD) : Rs.1.18 lakh (Non-Refundable) 5. AC mitigation Earthing work to be done by Apraava.
A35: 4 | B35: AP 102/1 - AP 102/2 | C35: OIL Line | D35: HPCL Rajasthan Refinery Ltd. | E35: 28.05.2025 | F35: 09.06.2025 | G35: 20.06.2025 | H35: 22.07.2025 | I35: 31.12.2025 | K35: 46111 | L35: Hard copies submitted on 06.03.2026 | M35: 1. Joint agreement to be signed 2. Special contingency insurance policy (5cr) to be taken and policy shall be valid till one month after completion of work. 3. Supervision charges (E-payment mode) : Rs. 50,000 + 18% GST (Non-Refundable) 4. Processing fee (E-payment mode) : Rs. 25,000 + 18% GST (Non-Refundable) 5. AC mitigation Earthing work to be done by Apraava.
A36: 5 | B36: AP 134 - AP 134A | C36: OIL Line | D36: BPPL | E36: 28.05.2025 | F36: 16.06.2025 | G36: 24.07.2025 | H36: 07.11.2025 | I36: 31.12.2025 | K36: 46111 | L36: Hard copies submitted on 06.03.2026 | M36: 1. Joint agreement to be signed 2. Processing fee (E-payment mode) : Rs. 25,000 + 18% GST (Non-Refundable) 3. Sepervision charges : Rs. 1.21 lakh - Non-Refundable 4. AC mitigation charges : Rs.9.36 lakh - Non-Refundable We need to conduct AC-DC interference survey to verify the effectiveness of the mitigation measures implemented, within 30 days of the completion of the crossing work and the charging of the HT Line.
A37: 6 | B37: AP 149 - AP 149A | C37: OIL Line | D37: HMEL | E37: 28.05.2025 | F37: 16.06.2025 | G37: 01.07.2025 | H37: 14.07.2025 | I37: 31.12.2025 | K37: 46111 | L37: Hard copies submitted on 06.03.2026 (Stringing work completed) | M37: 1. Joint agreement to be signed 2. Security deposit : Rs. 5 lakh - Refundable 3. Sepervision charges : Rs. 1.475 lakh - Non-Refundable 4. AC mitigation charges : Rs.3.304 lakh - Non-Refundable
A38: Forest Proposal (01 Nos)
A39: 1 | B39: FP/RJ/PWR_TRANS/554020/2025 | D39: MoECC | F39: 45939 | I39: 04.03.2026 | J39: 21.01.2026 (Stage-1) | K39: 46142 | L39: Demand letter received on 16.02.2026 Payment done on 04.03.2026 Processing for Stage-II approval
A40: Defence Proposal (01 Nos)
A41: 1 | B41: For Whole Line | D41: Ministry of Defence | F41: 14.08.2025 | J41: 46013
A42: Aviation Proposal (01 Nos)
A43: 1 | B43: For Whole Line | D43: NOCAS | F43: Applied for 497 loc. | J43: 497/497
A44: PTCC Proposal (01 Nos)
A45: 1 | B45: For Whole Line | F45: 07.02.2026 | K45: 30.04.2026 | L45: File submitted and NOC from Defence, Railway & Local BSNL office is awaited
A46: 765kV LILO Line
A47: Defence Proposal (01 Nos)
A48: 1 | B48: For Whole Line | D48: Ministry of Defence | L48: Will be submitted by 1st Apr 26 | M48: Due to ambiguity in submitting single or separate application for LI and LO circuits, process is delayed. Now got the clarity from PGCIL lines and separte application will be submitted.
A49: Aviation Proposal (01 Nos)
A50: 1 | B50: For Whole Line | D50: NOCAS | F50: 24.03.26 | L50: Will be submitted by 28th Mar 26
A51: PTCC Proposal (01 Nos)
A52: 1 | B52: For Whole Line | L52: Will be submitted by 7th Apr 26
A53: Section 164
A54: 1 | B54: For Whole Line | F54: 21.08.2025 | J54: 30.01.2026

Sheet Foundation
A1: NAME OF PROJECT : FARHEGARH IV-BHINMAL 400KV D/C TRANSMISSION LINE
A2: Client : RAJASTHAN IV A POWER TRANSMISSION LTD.
A3: CONTRACTOR : KEC INTERNATIONAL LIMITED
A5: FOUNDATION STATUS
A6: SL. No. | B6: Location Number | C6: Span | D6: Tower Type | E6: M10 | F6: M20 | G6: Excavation | H6: Reinforcement | I6: Stub | J6: RC | K6: Foundation type
L7: Starting date | M7: Completion Date | N7: Agency | O7: Remark | P7: Remarks
A8: 1 | B8: 83/1 | C8: 83/1 | D8: DA+3 | E8: 1.86 | F8: 12.47 | G8: 134.7 | H8: 1.115 | I8: 0.299 | K8: Sandy | L8: 45665 | M8: 45674 | N8: Mahadeep Company | O8: 45674 | P8: RCC Complete, Backfilling Done
A9: =A8+1 -> 2 | B9: 75/7 | C9: 75/7 | D9: DA+0 | E9: 1.57 | F9: 11.05 | G9: 115.3 | H9: 0.919 | I9: 0.299 | K9: Sandy | L9: 45675 | M9: 45684 | N9: AR Patel Contractor | P9: RCC Complete, Backfilling Done
A10: =A9+1 -> 3 | B10: 75/6 | D10: DA+0 | E10: 1.57 | F10: 11.05 | G10: 115.3 | H10: 0.919 | I10: 0.299 | K10: Sandy | L10: 45685 | M10: 45690 | N10: AR Patel Contractor | P10: RCC Complete, Backfilling Done
A11: =A10+1 -> 4 | B11: 75/4 | D11: DA+0 | E11: 1.57 | F11: 11.05 | G11: 115.3 | H11: 0.919 | I11: 0.299 | K11: Sandy | L11: 45686 | M11: 45693 | N11: OM Construction | P11: RCC Complete, Backfilling Done
A12: =A11+1 -> 5 | B12: 75/5 | D12: DA+0 | E12: 1.57 | F12: 11.05 | G12: 115.3 | H12: 0.919 | I12: 0.299 | K12: Sandy | L12: 45691 | M12: 45693 | N12: AR Patel Contractor | P12: RCC Complete, Backfilling Done
A13: =A12+1 -> 6 | B13: 77/2 | D13: DA+3 | E13: 1.86 | F13: 12.47 | G13: 134.7 | H13: 1.115 | I13: 0.299 | K13: Sandy | L13: 45691 | M13: 45697 | N13: AR Patel Contractor | P13: RCC Complete, Backfilling Done
A14: =A13+1 -> 7 | B14: 75/3 | D14: DA+3 | E14: 1.86 | F14: 12.47 | G14: 134.7 | H14: 1.115 | I14: 0.299 | K14: Sandy | L14: 24 | M14: 45698 | N14: OM Construction | P14: RCC Complete, Backfilling Done
A15: =A14+1 -> 8 | B15: 77/1 | D15: DA+0 | E15: 1.57 | F15: 11.05 | G15: 115.3 | H15: 0.919 | I15: 0.299 | K15: Sandy | L15: 45691 | M15: 45699 | N15: AAnjana Contractors | P15: RCC Complete, Backfilling Done
A16: =A15+1 -> 9 | B16: 77/3 | D16: DA+0 | E16: 1.57 | F16: 11.05 | G16: 115.3 | H16: 0.919 | I16: 0.299 | K16: Sandy | L16: 45696 | M16: 45702 | N16: AR Patel Contractor | P16: RCC Complete, Backfilling Done
A17: =A16+1 -> 10 | B17: 75/1 | D17: DA+0 | E17: 1.57 | F17: 11.05 | G17: 115.3 | H17: 0.919 | I17: 0.299 | K17: Sandy | L17: 45697 | M17: 45705 | N17: OM Construction | P17: RCC Complete, Backfilling Done
A18: =A17+1 -> 11 | B18: 77/4 | D18: DA+3 | E18: 1.86 | F18: 12.47 | G18: 134.7 | H18: 1.115 | I18: 0.299 | K18: Sandy | L18: 45699 | M18: 45705 | N18: AAnjana Contractors | P18: RCC Complete, Backfilling Done
A19: =A18+1 -> 12 | B19: 75/2 | D19: DA+0 | E19: 1.57 | F19: 11.05 | G19: 115.3 | H19: 0.919 | I19: 0.299 | K19: Sandy | L19: 45700 | M19: 45706 | N19: OM Construction | P19: RCC Complete, Backfilling Done
A20: =A19+1 -> 13 | B20: 77/5 | D20: DA+6 | E20: 1.86 | F20: 12.47 | G20: 134.7 | H20: 1.115 | I20: 0.299 | K20: Sandy | L20: 45701 | M20: 45707 | N20: AR Patel Contractor | P20: RCC Complete, Backfilling Done
A21: =A20+1 -> 14 | B21: 73/3 | D21: DA+9 | E21: 1.86 | F21: 12.47 | G21: 134.7 | H21: 1.115 | I21: 0.299 | K21: Sandy | L21: 45705 | M21: 45710 | N21: OM Construction | P21: RCC Complete, Backfilling Done
... A64: =A63+1 -> 57 | B64: 99C/2 | D64: DA+3 | E64: 1.86 | F64: 12.47 | G64: 134.7 | H64: 1.115 | I64: 0.299 | K64: Sandy | L64: 45795 | M64: 45802 | N64: Mundhan Trading Company | P64: RCC Complete, Backfilling Done
A65: =A64+1 -> 58 | B65: 105/0 | D65: DD+0 | E65: =1.81+1.12 -> 2.93 | F65: =8.16+12.18 -> 20.34 | G65: =79.95+144.9 -> 224.85 | H65: =1.476+1.188 -> 2.664 | I65: =(265.195+236.256)/1000 -> 0.501451 | K65: Sandy | L65: 45793 | M65: 45805 | N65: Gurukripa Enterprizes | P65: RCC Complete, Backfilling Done
A66: =A65+1 -> 59 | B66: 98A/0 | D66: DC+0 | E66: 1.6 | F66: 13.13 | G66: 87.25 | H66: 1.374 | I66: 0.501 | K66: DFR | L66: 45789 | M66: 45806 | N66: Ganga Construction Company | P66: RCC Complete, Backfilling Done
A67: =A66+1 -> 60 | B67: 62/5 | D67: DA+6 | E67: 1.86 | F67: 12.47 | G67: 134.7 | H67: 1.115 | I67: 0.299 | K67: Sandy | L67: 45779 | M67: 45808 | N67: Ram Shenai Construction | P67: RCC Complete, Backfilling Done
A68: =A67+1 -> 61 | B68: 81/3 | D68: DA+0 | E68: 1.57 | F68: 11.05 | G68: 115.3 | H68: 0.919 | I68: 0.299 | K68: Sandy | L68: 45799 | M68: 45812 | N68: Ram Shenai Construction | P68: RCC Complete, Backfilling Done
A69: =A68+1 -> 62 | B69: 120/1 | D69: DA+6 | E69: 1.86 | F69: 12.47 | G69: 134.7 | H69: 1.115 | I69: 0.299 | K69: Sandy | L69: 45807 | M69: 45813 | N69: Majisa Construction | P69: RCC Complete, Backfilling Done
A70: =A69+1 -> 63 | B70: 96/0 | D70: DC+0 | E70: 1.6 | F70: 13.13 | G70: 87.25 | H70: 1.374 | I70: 0.501 | K70: DFR | L70: 45805 | M70: 45814 | N70: Mundhan Trading Company | P70: RCC Complete, Backfilling Done
A71: =A70+1 -> 64 | B71: 75/0 | D71: DC+0 | E71: 1.6 | F71: 13.13 | G71: 87.25 | H71: 1.374 | I71: 0.501 | K71: Sandy | L71: 45809 | M71: 45815 | N71: OM Construction | P71: RCC Complete, Backfilling Done
A72: =A71+1 -> 65 | B72: 147/2 | D72: DA+0 | E72: 1.57 | F72: 11.05 | G72: 115.3 | H72: 0.919 | I72: 0.299 | K72: Sandy | L72: 45810 | M72: 45816 | N72: JP Enterprises | P72: RCC Complete, Backfilling Done
A73: =A72+1 -> 66 | B73: 82/2 | D73: DA+0 | E73: 1.57 | F73: 11.05 | G73: 115.3 | H73: 0.919 | I73: 0.299 | K73: Sandy | L73: 45810 | M73: 45818 | N73: AAnjana Contractors | P73: RCC Complete, Backfilling Done
A74: =A73+1 -> 67 | B74: 147/5 | D74: DA+0 | E74: 1.57 | F74: 11.05 | G74: 115.3 | H74: 0.919 | I74: 0.299 | K74: Sandy | L74: 45812 | M74: 45820 | N74: AR Patel Contractor | P74: RCC Complete, Backfilling Done
A75: =A74+1 -> 68 | B75: 79/0 | D75: DD+0 | E75: =1.81+1.12 -> 2.93 | F75: =8.16+12.18 -> 20.34 | G75: =79.95+144.9 -> 224.85 | H75: =1.476+1.188 -> 2.664 | I75: =(265.195+236.256)/1000 -> 0.501451 | K75: Sandy | L75: 45877 | M75: 45820 | N75: OM Construction | P75: RCC Complete, Backfilling Done
A76: =A75+1 -> 69 | B76: 119/0 | D76: DD+3 | E76: =1.81+1.12 -> 2.93 | F76: =8.16+12.18 -> 20.34 | G76: =79.95+144.9 -> 224.85 | H76: =1.476+1.188 -> 2.664 | I76: =(265.195+236.256)/1000 -> 0.501451 | K76: Sandy | L76: 45813 | M76: 45823 | N76: Majisa Construction | P76: RCC Complete, Backfilling Done
A77: =A76+1 -> 70 | B77: 147/0 | D77: DC+0 | E77: 1.6 | F77: 13.13 | G77: 87.25 | H77: 1.374 | I77: 0.501 | K77: Sandy | L77: 45816 | M77: 45823 | N77: JP Enterprises | P77: RCC Complete, Backfilling Done
A78: =A77+1 -> 71 | B78: 82/1 | D78: DA+6 | E78: 1.86 | F78: 12.47 | G78: 134.7 | H78: 1.115 | I78: 0.299 | K78: Sandy | L78: 45818 | M78: 45823 | N78: AAnjana Contractors | P78: RCC Complete, Backfilling Done
A79: =A78+1 -> 72 | B79: 147/4 | D79: DA+0 | E79: 1.57 | F79: 11.05 | G79: 115.3 | H79: 0.919 | I79: 0.299 | K79: Sandy | L79: 45821 | M79: 45824 | N79: AR Patel Contractor1 | P79: RCC Complete, Backfilling Done
A80: =A79+1 -> 73 | B80: 78/0 | D80: DC+0 | E80: 1.6 | F80: 13.13 | G80: 87.25 | H80: 1.374 | I80: 0.501 | K80: Sandy | L80: 45821 | M80: 45824 | N80: OM Construction | P80: RCC Complete, Backfilling Done
A81: =A80+1 -> 74 | B81: 74/0 | D81: DB+9 | E81: 1.68 | F81: 12.41 | G81: 143.4 | H81: 1.728 | I81: 0.414 | K81: Sandy | L81: 45824 | M81: 45828 | N81: OM Construction | P81: RCC Complete, Backfilling Done
A82: =A81+1 -> 75 | B82: 147/1 | D82: DA+0 | E82: 1.57 | F82: 11.05 | G82: 115.3 | H82: 0.919 | I82: 0.299 | K82: Sandy | L82: 45823 | M82: 45829 | N82: JP Enterprises | P82: RCC Complete, Backfilling Done
A83: =A82+1 -> 76 | B83: 147/7 | D83: DA+0 | E83: 1.57 | F83: 11.05 | G83: 115.3 | H83: 0.919 | I83: 0.299 | K83: Sandy | L83: 45823 | M83: 45830 | N83: AR Patel Contractor 2 | P83: RCC Complete, Backfilling Done
A84: =A83+1 -> 77 | B84: 95A/0 | D84: DB+0 | E84: 1.12 | F84: 9.63 | G84: 61.2 | H84: 1.865 | I84: 0.413 | K84: DFR | L84: 45824 | M84: 45831 | N84: Mundhan Trading Company | P84: RCC Complete, Backfilling Done
A85: =A84+1 -> 78 | B85: 146/2 | D85: DA+0 | E85: 1.57 | F85: 11.05 | G85: 115.3 | H85: 0.919 | I85: 0.299 | K85: Sandy | L85: 45830 | M85: 45833 | N85: JP Enterprises | P85: RCC Complete, Backfilling Done
A86: =A85+1 -> 79 | B86: 147/3 | D86: DA+0 | E86: 1.57 | F86: 11.05 | G86: 115.3 | H86: 0.919 | I86: 0.299 | K86: Sandy | L86: 45830 | M86: 45833 | N86: AR Patel Contractor | P86: RCC Complete, Backfilling Done
A87: =A86+1 -> 80 | B87: 73/0 | D87: DB+0 | E87: 1.68 | F87: 12.41 | G87: 143.4 | H87: 1.728 | I87: 0.414 | K87: Sandy | L87: 45828 | M87: 45834 | N87: OM Construction | P87: RCC Complete, Backfilling Done
A88: =A87+1 -> 81 | B88: 86/0 | D88: DD+0 | E88: =1.81+1.12 -> 2.93 | F88: =8.16+12.18 -> 20.34 | G88: =79.95+144.9 -> 224.85 | H88: =1.476+1.188 -> 2.664 | I88: =(265.195+236.256)/1000 -> 0.501451 | K88: Sandy | L88: 45825 | M88: 45835 | N88: AAnjana Contractors | P88: RCC Complete, Backfilling Done
A89: =A88+1 -> 82 | B89: 114/0 | D89: DC+0 | E89: 1.6 | F89: 13.13 | G89: 87.25 | H89: 1.374 | I89: 0.501 | K89: Sandy | L89: 45818 | M89: 45838 | N89: Goswami and Co | P89: RCC Complete, Backfilling Done
A90: =A89+1 -> 83 | B90: 146/1 | D90: DA+3 | E90: 1.86 | F90: 12.47 | G90: 134.7 | H90: 1.115 | I90: 0.299 | K90: Sandy | L90: 45833 | M90: 45838 | N90: JP Enterprises | P90: RCC Complete, Backfilling Done
A91: =A90+1 -> 84 | B91: 147/8 | D91: DA+0 | E91: 1.57 | F91: 11.05 | G91: 115.3 | H91: 0.919 | I91: 0.299 | K91: Sandy | L91: 45833 | M91: 45838 | N91: AR Patel Contractor 2 | P91: RCC Complete, Backfilling Done
A92: =A91+1 -> 85 | B92: 72/2 | D92: DA+3 | E92: 1.86 | F92: 12.47 | G92: 134.7 | H92: 1.115 | I92: 0.299 | K92: Sandy | L92: 45833 | M92: 45838 | N92: OM Construction | P92: RCC Complete, Backfilling Done
A93: =A92+1 -> 86 | B93: 95/1 | D93: DB+0 | E93: 1.12 | F93: 9.63 | G93: 61.2 | H93: 1.865 | I93: 0.413 | K93: DFR | L93: 45831 | M93: 45842 | N93: Baba Ramdev Construction | P93: RCC Complete, Backfilling Done
A94: =A93+1 -> 87 | B94: 148/3 | D94: DA+0 | E94: 1.57 | F94: 11.05 | G94: 115.3 | H94: 0.919 | I94: 0.299 | K94: Sandy | L94: 45835 | M94: 45843 | N94: AR Patel Contractor | P94: RCC Complete, Backfilling Done
A95: =A94+1 -> 88 | B95: 106/0 | D95: DC+6 | E95: 1.6 | F95: 13.13 | G95: 87.25 | H95: 1.374 | I95: 0.501 | K95: Sandy | L95: 45833 | M95: 45844 | N95: Mundhan Trading Company | P95: RCC Complete, Backfilling Done
A96: =A95+1 -> 89 | B96: 146/0 | D96: DC+0 | E96: 1.6 | F96: 13.13 | G96: 87.25 | H96: 1.374 | I96: 0.501 | K96: Sandy | L96: 45841 | M96: 45846 | N96: JP Enterprises | P96: RCC Complete, Backfilling Done
A97: =A96+1 -> 90 | B97: 148/1 | D97: DA+0 | E97: 1.57 | F97: 11.05 | G97: 115.3 | H97: 0.919 | I97: 0.299 | K97: Sandy | L97: 45842 | M97: 45846 | N97: AR Patel Contractor | P97: RCC Complete, Backfilling Done
A98: =A97+1 -> 91 | B98: 114/1 | D98: DA+9 | E98: 1.86 | F98: 12.47 | G98: 134.7 | H98: 1.115 | I98: 0.299 | K98: Sandy | L98: 45842 | M98: 45848 | N98: Goswami & Company | P98: RCC Complete, Backfilling Done
A99: =A98+1 -> 92 | B99: 148/2 | D99: DA+0 | E99: 1.57 | F99: 11.05 | G99: 115.3 | H99: 0.919 | I99: 0.299 | K99: Sandy | L99: 45845 | M99: 45848 | N99: AR Patel Contractor | P99: RCC Complete, Backfilling Done
A100: =A99+1 -> 93 | B100: 80/0 | D100: DB+3 | E100: 1.46 | F100: 15.22 | G100: 82 | H100: 1.723 | I100: =0.162+0.414 -> 0.576 | J100: 1MRC | K100: Sandy | L100: 45836 | M100: 45848 | N100: Mahadev Construction Company | P100: RCC Complete, Backfilling Done
A101: =A100+1 -> 94 | B101: 141/1 | D101: DA+0 | E101: 1.57 | F101: 11.05 | G101: 115.3 | H101: 0.919 | I101: 0.299 | K101: Sandy | L101: 45845 | M101: 45849 | N101: Mahadev Construction Company | P101: RCC Complete, Backfilling Done
A102: =A101+1 -> 95 | B102: 95/0 | D102: DB+6 | E102: 1.68 | F102: 12.41 | G102: 143.4 | H102: 1.728 | I102: 0.414 | K102: Sandy | L102: 45835 | M102: 45849 | N102: Baba Ramdev Construction | P102: RCC Complete, Backfilling Done
A103: =A102+1 -> 96 | B103: 148/4 | D103: DA+0 | E103: 1.57 | F103: 11.05 | G103: 115.3 | H103: 0.919 | I103: 0.299 | K103: Sandy | L103: 45848 | M103: 45850 | N103: AR Patel Contractor | P103: RCC Complete, Backfilling Done
A104: =A103+1 -> 97 | B104: 141/2 | D104: DA+6 | E104: 1.86 | F104: 12.47 | G104: 134.7 | H104: 1.115 | I104: 0.299 | K104: Sandy | L104: 45847 | M104: 45851 | N104: Mahadev Construction Company | P104: RCC Complete, Backfilling Done
A105: =A104+1 -> 98 | B105: 145/4 | D105: DA+3 | E105: 1.86 | F105: 12.47 | G105: 134.7 | H105: 1.115 | I105: 0.299 | K105: Sandy | L105: 45847 | M105: 45851 | N105: JP Enterprises | P105: RCC Complete, Backfilling Done
A106: =A105+1 -> 99 | B106: 125/1 | D106: DA+0 | E106: 1.57 | F106: 11.05 | G106: 115.3 | H106: 0.919 | I106: 0.299 | K106: Sandy | L106: 45842 | M106: 45852 | N106: Intense Wave Pvt Ltd | P106: RCC Complete, Backfilling Done
A107: =A106+1 -> 100 | B107: 133/6 | D107: DA+3 | E107: 1.86 | F107: 12.47 | G107: 134.7 | H107: 1.115 | I107: 0.299 | K107: Sandy | L107: 45848 | M107: 45852 | N107: OM Construction | P107: RCC Complete, Backfilling Done
A108: =A107+1 -> 101 | B108: 148/5 | D108: DA+0 | E108: 1.57 | F108: 11.05 | G108: 115.3 | H108: 0.919 | I108: 0.299 | K108: Sandy | L108: 45851 | M108: 45853 | N108: AR Patel Contractor | P108: RCC Complete, Backfilling Done
A109: =A108+1 -> 102 | B109: 109A/0 | D109: DB+6 | E109: 1.68 | F109: 12.41 | G109: 143.4 | H109: 1.728 | I109: 0.414 | K109: Sandy | L109: 45847 | M109: 45854 | N109: Mundhan Trading Company | P109: RCC Complete, Backfilling Done
A110: =A109+1 -> 103 | B110: 113A/0 | D110: DC+0 | E110: 1.6 | F110: 13.13 | G110: 87.25 | H110: 1.374 | I110: 0.501 | K110: Sandy | L110: 45846 | M110: 45854 | N110: Goswami & Company-1 | P110: RCC Complete, Backfilling Done
A111: =A110+1 -> 104 | B111: 133/5 | D111: DA+0 | E111: 1.57 | F111: 11.05 | G111: 115.3 | H111: 0.919 | I111: 0.299 | K111: Sandy | L111: 45852 | M111: 45854 | N111: OM Construction | P111: RCC Complete, Backfilling Done
A112: =A111+1 -> 105 | B112: 145/2 | D112: DA+0 | E112: 1.57 | F112: 11.05 | G112: 115.3 | H112: 0.919 | I112: 0.299 | K112: Sandy | L112: 45852 | M112: 45854 | N112: JP Enterprises | P112: RCC Complete, Backfilling Done
A113: =A112+1 -> 106 | B113: 142/0 | D113: DC+3 | E113: 2.07 | F113: 15.35 | G113: 162.6 | H113: 1.589 | I113: 0.501 | K113: Sandy | L113: 45850 | M113: 45855 | N113: Mahadev Construction Company | P113: RCC Complete, Backfilling Done
A114: =A113+1 -> 107 | B114: 115/0 | D114: DC+0,1MRC | K114: Sandy | L114: 45848 | M114: 45856 | N114: Goswami & Company-2 | P114: RCC Complete, Backfilling Done
A115: =A114+1 -> 108 | B115: 148/6 | D115: DA+0 | E115: 1.57 | F115: 11.05 | G115: 115.3 | H115: 0.919 | I115: 0.299 | K115: Sandy | L115: 45853 | M115: 45856 | N115: AR Patel Contractor | P115: RCC Complete, Backfilling Done
A116: =A115+1 -> 109 | B116: 77/0 | D116: DB+0 | E116: 1.12 | F116: 9.63 | G116: 61.2 | H116: 1.865 | I116: 0.413 | K116: Sandy | L116: 45846 | M116: 45857 | N116: Godara Enterprises | P116: RCC Complete, Backfilling Done
A117: =A116+1 -> 110 | B117: 133/4 | D117: DA+0 | E117: 1.57 | F117: 11.05 | G117: 115.3 | H117: 0.919 | I117: 0.299 | K117: Sandy | L117: 45855 | M117: 45859 | N117: OM Construction | P117: RCC Complete, Backfilling Done
A118: =A117+1 -> 111 | B118: 143/0 | D118: DC+3 | E118: 2.07 | F118: 15.35 | G118: 162.6 | H118: 1.589 | I118: 0.501 | K118: Sandy | L118: 45855 | M118: 45859 | N118: Mahadev Construction Company | P118: RCC Complete, Backfilling Done
A119: =A118+1 -> 112 | B119: 145/1 | D119: DA+3 | E119: 1.86 | F119: 12.47 | G119: 134.7 | H119: 1.115 | I119: 0.299 | K119: Sandy | L119: 45854 | M119: 45859 | N119: JP Enterprises | P119: RCC Complete, Backfilling Done
A120: =A119+1 -> 113 | B120: 148/7 | D120: DA+0 | E120: 1.57 | F120: 11.05 | G120: 115.3 | H120: 0.919 | I120: 0.299 | K120: Sandy | L120: 45857 | M120: 45861 | N120: AR Patel Contractor | P120: RCC Complete, Backfilling Done
A121: =A120+1 -> 114 | B121: 125/0 | D121: DC+3 | E121: 2.07 | F121: 15.35 | G121: 162.6 | H121: 1.589 | I121: 0.501 | K121: Sandy | L121: 45853 | M121: 45862 | N121: Intense Wave Pvt Ltd | P121: RCC Complete, Backfilling Done
A122: =A121+1 -> 115 | B122: 133/3 | D122: DA+0 | E122: 1.57 | F122: 11.05 | G122: 115.3 | H122: 0.919 | I122: 0.299 | K122: Sandy | L122: 45860 | M122: 45862 | N122: OM Construction | P122: RCC Complete, Backfilling Done
A123: =A122+1 -> 116 | B123: 94/0 | D123: DB+6 | E123: 1.68 | F123: 12.41 | G123: 143.4 | H123: 1.728 | I123: 0.414 | K123: Sandy | L123: 45851 | M123: 45862 | N123: Baba Ramdev Construction | P123: RCC Complete, Backfilling Done
A124: =A123+1 -> 117 | B124: 145/3 | D124: DA+0 | E124: 1.57 | F124: 11.05 | G124: 115.3 | H124: 0.919 | I124: 0.299 | K124: Sandy | L124: 45860 | M124: 45863 | N124: JP Enterprises | P124: RCC Complete, Backfilling Done
A125: =A124+1 -> 118 | B125: 126/2 | D125: DA+3 | E125: 1.86 | F125: 12.47 | G125: 134.7 | H125: 1.115 | I125: 0.299 | K125: Sandy | L125: 45853 | M125: 45864 | N125: MS Construction | P125: RCC Complete, Backfilling Done
A126: =A125+1 -> 119 | B126: 143/3 | D126: DA+3 | E126: 1.86 | F126: 12.47 | G126: 134.7 | H126: 1.115 | I126: 0.299 | K126: Sandy | L126: 45860 | M126: 45864 | N126: Mahadev Construction Company | P126: RCC Complete, Backfilling Done
... A134: =A133+1 -> 127 | B134: 149B/2 | D134: DA+0 | E134: 1.57 | F134: 11.05 | G134: 115.3 | H134: 0.919 | I134: 0.299 | K134: Sandy | L134: 45865 | M134: 45868 | N134: AR Patel Contractor | P134: RCC Complete, Backfilling Done
A135: =A134+1 -> 128 | B135: 111/0 | D135: DB+9,3MRC | K135: Sandy | L135: 45855 | M135: 45869 | N135: Goswami & Company-1 | P135: RCC Complete, Backfilling Done
A136: =A135+1 -> 129 | B136: 116/0 | D136: DD+0 | E136: =1.81+1.12 -> 2.93 | F136: =8.16+12.18 -> 20.34 | G136: =79.95+144.9 -> 224.85 | H136: =1.476+1.188 -> 2.664 | I136: =(265.195+236.256)/1000 -> 0.501451 | K136: Sandy | L136: 45861 | M136: 45869 | N136: Goswami & Company-2 | P136: RCC Complete, Backfilling Done
A137: =A136+1 -> 130 | B137: 129/1 | D137: DA+9 | E137: 1.86 | F137: 12.47 | G137: 134.7 | H137: 1.115 | I137: 0.299 | K137: Sandy | L137: 45863 | M137: 45869 | N137: Intense Wave Pvt Ltd | P137: RCC Complete, Backfilling Done
A138: =A137+1 -> 131 | B138: 133/7 | D138: DA+0 | E138: 1.57 | F138: 11.05 | G138: 115.3 | H138: 0.919 | I138: 0.299 | K138: Sandy | L138: 45868 | M138: 45869 | N138: OM Construction | P138: RCC Complete, Backfilling Done
A139: =A138+1 -> 132 | B139: 143/6 | D139: DA+0 | E139: 1.57 | F139: 11.05 | G139: 115.3 | H139: 0.919 | I139: 0.299 | K139: Sandy | L139: 45867 | M139: 45869 | N139: Mahadev Construction Company | P139: RCC Complete, Backfilling Done
A140: =A139+1 -> 133 | B140: 145/0 | D140: DD+6 | K140: Sandy | L140: 45863 | M140: 45869 | N140: JP Enterprises | P140: RCC Complete, Backfilling Done
A141: =A140+1 -> 134 | B141: 76/0 | D141: DC+0 | E141: 1.6 | F141: 13.13 | G141: 87.25 | H141: 1.374 | I141: 0.501 | K141: Sandy | L141: 45862 | M141: 45869 | N141: Baba Ramdev Construction | P141: RCC Complete, Backfilling Done
A142: =A141+1 -> 135 | B142: 98B/0 | D142: DD+0 | E142: =1.81+1.12 -> 2.93 | F142: =8.16+12.18 -> 20.34 | G142: =79.95+144.9 -> 224.85 | H142: =1.476+1.188 -> 2.664 | I142: =(265.195+236.256)/1000 -> 0.501451 | K142: DFR | L142: 45818 | M142: 45869 | N142: AAnjana Contractors | P142: RCC Complete, Backfilling Done
A143: =A142+1 -> 136 | B143: 126/1 | D143: DA+6 | E143: 1.86 | F143: 12.47 | G143: 134.7 | H143: 1.115 | I143: 0.299 | K143: Sandy | L143: 45865 | M143: 45871 | N143: MS Construction | P143: RCC Complete, Backfilling Done
A144: =A143+1 -> 137 | B144: 143/7 | D144: DA+3 | E144: 1.86 | F144: 12.47 | G144: 134.7 | H144: 1.115 | I144: 0.299 | K144: Sandy | L144: 45868 | M144: 45871 | N144: Mahadev Construction Company | P144: RCC Complete, Backfilling Done
A145: =A144+1 -> 138 | B145: 130/0 | D145: DC+6 | E145: 1.6 | F145: 13.13 | G145: 87.25 | H145: 1.374 | I145: 0.501 | K145: Sandy | L145: 45845 | M145: 45873 | N145: Sparkle Telenet Service | P145: RCC Complete, Backfilling Done
A146: =A145+1 -> 139 | B146: 143/5 | D146: DA+3 | E146: 1.86 | F146: 12.47 | G146: 134.7 | H146: 1.115 | I146: 0.299 | K146: Sandy | L146: 45872 | M146: 45873 | N146: Mahadev Construction Company | P146: RCC Complete, Backfilling Done
A147: =A146+1 -> 140 | B147: 97/1 | D147: DA+3 | E147: 1.86 | F147: 12.47 | G147: 134.7 | H147: 1.115 | I147: 0.299 | K147: Sandy | L147: 45869 | M147: 45874 | N147: AAnjana Contractors | P147: RCC Complete, Backfilling Done
A148: =A147+1 -> 141 | B148: 143/2 | D148: DA+0 | E148: 1.57 | F148: 11.05 | G148: 115.3 | H148: 0.919 | I148: 0.299 | K148: Sandy | L148: 45873 | M148: 45875 | N148: Mahadev Construction Company | P148: RCC Complete, Backfilling Done
A149: =A148+1 -> 142 | B149: 102/2 | D149: DA+0 | E149: 1.57 | F149: 11.05 | G149: 115.3 | H149: 0.919 | I149: 0.299 | K149: Sandy | L149: 45870 | M149: 45876 | N149: Mundhan Trading Company | P149: RCC Complete, Backfilling Done
A150: =A149+1 -> 143 | B150: 133/2 | D150: DA+0 | E150: 1.57 | F150: 11.05 | G150: 115.3 | H150: 0.919 | I150: 0.299 | K150: Sandy | L150: 45870 | M150: 45876 | N150: OM Construction | P150: RCC Complete, Backfilling Done
...

Sheet Royalty
O3: OM Construction
C4: Loc No | D4: TOT | E4: M-10 | F4: M-20
C5: 120/1 | D5: DA+6 | E5: 1.86 | F5: 12.47 | O5: 75/0 | P5: DC+0 | Q5: 1.6 | R5: 13.13
C6: 119/0 | D6: DD+3 | E6: 2.93 | F6: 20.34 | O6: 79/0 | P6: DD+0 | Q6: 2.93 | R6: 20.34
D7: CUM | E7: =SUM(E5:E6) -> 4.79 | F7: =SUM(F5:F6) -> 32.81 | J7: ROYALTY ISSUED | O7: 78/0 | P7: DC+0 | Q7: 1.6 | R7: 13.13
C8: CUM | D8: 20MM | E8: =E7*1.54*6/10 -> 4.42596 | F8: =F7*1.54*3/5.5 -> 27.5604 | G8: =SUM(E8:F8) -> 31.98636 | J8: 20MM | O8: 74/0 | P8: DB+9 | Q8: 1.68 | R8: 12.41
C9: CUM | D9: SAND | E9: =E8*1.54*3/10 -> 2.0447935 | F9: =F8*1.54*1.5/5.5 -> 11.575368 | G9: =SUM(E9:F9) -> 13.620162 | J9: 18.48 | O9: 73/0 | P9: DB+0 | Q9: 1.68 | R9: 12.41
C10: MT | D10: 20MM | G10: =G8*1600/1000 -> 51.178176 | H10: Required | J10: 14.67 | O10: 72/2 | P10: DA+3 | Q10: 1.86 | R10: 12.47
C11: MT | D11: SAND | G11: =G9*1600/1000 -> 21.792258 | H11: Required | J11: =SUM(J9:J10) -> 33.15 | Q11: =SUM(Q5:Q10) -> 11.35 | R11: =SUM(R5:R10) -> 83.89
O12: CUM | P12: 20MM | Q12: =Q11*1.54*6/10 -> 10.4874 | R12: =R11*1.54*3/5.5 -> 70.4676 | S12: =SUM(Q12:R12) -> 80.955
O13: CUM | P13: SAND | Q13: =Q12*1.54*3/10 -> 4.8451788 | R13: =R12*1.54*1.5/5.5 -> 29.596392 | S13: =SUM(Q13:R13) -> 34.441571
C14: 77/1 | D14: DA+0 | E14: 1.57 | F14: 11.05 | O14: MT | P14: 20MM | S14: =S12*1600/1000 -> 129.528
C15: 77/4 | D15: DA+3 | E15: 1.86 | F15: 12.47 | O15: MT | P15: SAND | S15: =S13*1600/1000 -> 55.106513
C16: 79/1 | D16: DA+9 | E16: 1.86 | F16: 12.47
C17: 76/1 | D17: DA+6 | E17: 1.86 | F17: 12.47
C18: 85/1 | D18: DA+0 | E18: 1.57 | F18: 11.05 | O18: JP Enterprises
C19: 87/1 | D19: DA+3 | E19: 1.86 | F19: 12.47 | P19: 147/2 | Q19: DA+0 | R19: 1.57 | S19: 11.05
C20: 87/2 | D20: DA+9 | E20: 1.86 | F20: 12.47 | P20: 147/0 | Q20: DC+0 | R20: 1.6 | S20: 13.13
C21: 91/1 | D21: DA+0 | E21: 1.57 | F21: 11.05 | P21: 147/1 | Q21: DA+0 | R21: 1.57 | S21: 11.05
C22: 91/2 | D22: DA+0 | E22: 1.57 | F22: 11.05 | P22: 146/2 | Q22: DA+0 | R22: 1.57 | S22: 11.05
C23: 99/2 | D23: DA+0 | E23: 1.08 | F23: 8.68 | P23: 146/1 | Q23: DA+3 | R23: 1.86 | S23: 12.47
C24: 97/0 | D24: DC+0 | E24: 1.6 | F24: 13.13 | R24: =SUM(R19:R23) -> 8.17 | S24: =SUM(S19:S23) -> 58.75
C25: 82/2 | D25: DA+0 | E25: 1.57 | F25: 11.05 | P25: CUM | Q25: 20MM | R25: =R24*1.54*6/10 -> 7.54908 | S25: =S24*1.54*3/5.5 -> 49.35 | T25: =SUM(R25:S25) -> 56.89908
C26: 82/1 | D26: DA+6 | E26: 1.86 | F26: 12.47 | P26: CUM | Q26: SAND | R26: =R25*1.54*3/10 -> 3.487675 | S26: =S25*1.54*1.5/5.5 -> 20.727 | T26: =SUM(R26:S26) -> 24.214675
C27: 86/0 | D27: DD+0 | E27: 2.93 | F27: 20.34 | P27: MT | Q27: 20MM | T27: =T25*1600/1000 -> 91.038528
C28: 85/0 | D28: DC+0 | E28: 1.6 | F28: 13.13 | P28: MT | Q28: SAND | T28: =T26*1600/1000 -> 38.74348
E29: =SUM(E14:E28) -> 26.22 | F29: =SUM(F14:F28) -> 185.35 | U29: Balance
C30: CUM | D30: 20MM | E30: =E29*1.54*6/10 -> 24.22728 | F30: =F29*1.54*3/5.5 -> 155.694 | G30: =SUM(E30:F30) -> 179.92128 | O30: Submitted | P30: MT | Q30: 20MM | T30: =16.74+14.83+18.51+18.5 -> 68.58 | U30: =T27-T30 -> 22.458528
C31: CUM | D31: SAND | E31: =E30*1.54*3/10 -> 11.193003 | F31: =F30*1.54*1.5/5.5 -> 65.39148 | G31: =SUM(E31:F31) -> 76.584483
C32: MT | D32: 20MM | G32: =G30*1600/1000 -> 287.87405
C33: MT | D33: SAND | G33: =G31*1600/1000 -> 122.53517

Sheet Sheet14
A2: 1 | B2: 95/1 | C2: DB+0 | E2: DFR | F2: 45831 | G2: 45842 | H2: Baba Ramdev Construction | I2: RCC Complete, Backfilling Done
A3: =A2+1 -> 2 | B3: 148/3 | C3: DA+0 | E3: Sandy | F3: 45835 | G3: 45843 | H3: AR Patel | I3: RCC Complete, Backfilling Done
A4: =A3+1 -> 3 | B4: 106/0 | C4: DC+6 | E4: Sandy | F4: 45833 | G4: 45844 | H4: Mundhan Trading Company | I4: RCC Complete, Backfilling Done
A5: =A4+1 -> 4 | B5: 148/1 | C5: DA+0 | E5: Sandy | F5: 45842 | G5: 45846 | H5: AR Patel | I5: RCC Complete, Backfilling Done
A6: =A5+1 -> 5 | B6: 146/0 | C6: DC+0 | E6: Sandy | F6: 45841 | G6: 45846 | H6: JP Enterprises | I6: RCC Complete, Backfilling Done
A7: =A6+1 -> 6 | B7: 80/0 | C7: DB+3 | D7: 1MRC | E7: Sandy | F7: 45836 | G7: 45848 | H7: Mahadev Enterprises | I7: RCC Complete, Backfilling Done
A8: =A7+1 -> 7 | B8: 114/1 | C8: DA+9 | E8: Sandy | F8: 45842 | G8: 45848 | H8: Goswami and Company | I8: RCC Complete, Backfilling Done
A9: =A8+1 -> 8 | B9: 148/2 | C9: DA+0 | E9: Sandy | F9: 45845 | G9: 45848 | H9: AR Patel | I9: RCC Complete, Backfilling Done
A10: =A9+1 -> 9 | B10: 95/0 | C10: DB+6 | E10: Sandy | F10: 45835 | G10: 45849 | H10: Baba Ramdev Construction | I10: RCC Complete, Backfilling Done
A11: =A10+1 -> 10 | B11: 141/1 | C11: DA+0 | E11: Sandy | F11: 45845 | G11: 45849 | H11: Mahadev Construction | I11: RCC Complete, Backfilling Done
A12: =A11+1 -> 11 | B12: 148/4 | C12: DA+0 | E12: Sandy | F12: 45848 | G12: 45850 | H12: AR Patel | I12: RCC Complete, Backfilling Done
A13: =A12+1 -> 12 | B13: 141/2 | C13: DA+6 | E13: Sandy | F13: 45847 | G13: 45851 | H13: Mahadev Construction | I13: RCC Complete, Backfilling Done
A14: =A13+1 -> 13 | B14: 145/4 | C14: DA+3 | E14: Sandy | F14: 45847 | G14: 45851 | H14: JP Enterprises | I14: RCC Complete, Backfilling Done
A15: =A14+1 -> 14 | B15: 133/6 | C15: DA+3 | E15: Sandy | F15: 45848 | G15: 45852 | H15: OM Construction | I15: RCC Complete, Backfilling Done
A16: =A15+1 -> 15 | B16: 125/1 | C16: DA+0 | E16: Sandy | F16: 45842 | G16: 45852 | H16: Instance Wave Pvt Ltd | I16: RCC Complete, Backfilling Done
A17: =A16+1 -> 16 | B17: 148/5 | C17: DA+0 | E17: Sandy | F17: 45851 | G17: 45853 | H17: AR Patel | I17: RCC Complete, Backfilling Done
A18: =A17+1 -> 17 | B18: 109A/0 | C18: DB+6 | E18: Sandy | F18: 45847 | G18: 45854 | H18: Mundhan Construction | I18: RCC Complete, Backfilling Done
A19: =A18+1 -> 18 | B19: 113A/0 | C19: DC+0 | E19: Sandy | F19: 45846 | G19: 45854 | H19: Goswami and Company-1 | I19: RCC Complete, Backfilling Done
... A51: =A50+1 -> 50 | B51: 116/0 | C51: DD+0 | E51: Sandy | F51: 45861 | G51: 45869 | H51: Goswami and Company-2 | I51: RCC Complete, Backfilling Done

Sheet Sheet7
D4: SL | E4: Loc | F4: TOT | G4: Gang | H4: Starting Date | I4: Completion
D5: 1 | E5: 148/3 | F5: DA+0 | G5: Gokul Sarkar | H5: 45898 | I5: 45904 | J5: Completed
D6: =D5+1 -> 2 | E6: 81/2 | F6: DA+3 | G6: Dipak | H6: 45901 | I6: 45905 | J6: Completed
D7: =D6+1 -> 3 | E7: 145/1 | F7: DA+3 | G7: Ayansh Const | H7: 45896 | I7: 45909 | J7: Completed
D8: =D7+1 -> 4 | E8: 81/4 | F8: DA+0 | G8: Dipak | H8: 45905 | I8: 45909 | J8: Completed
D9: =D8+1 -> 5 | E9: 148/2 | F9: DA+0 | G9: Gokul Sarkar | H9: 45905 | I9: 45910 | J9: Completed
D10: =D9+1 -> 6 | E10: 83/1 | F10: DA+3 | G10: Ahmed Construction | H10: 45898 | I10: 45911 | J10: Completed
D11: =D10+1 -> 7 | E11: 97/0 | F11: DC+0 | G11: Ajay Kumar1 | H11: 45901 | I11: 45911 | J11: Completed
D12: =D11+1 -> 8 | E12: 148/5 | F12: DA+0 | G12: Gokul Sarkar | H12: 45911 | I12: 45914 | J12: Completed
D13: =D12+1 -> 9 | E13: 145/2 | F13: DA+0 | G13: Ayansh Const | H13: 45909 | I13: 45914 | J13: Completed
D14: =D13+1 -> 10 | E14: 82/1 | F14: DA+6 | G14: Dipak | H14: 45909 | I14: 45914 | J14: Completed
D15: =D14+1 -> 11 | E15: 96/1 | F15: DA+0 | G15: Ajay Kumar1 | H15: 45901 | I15: 45915 | J15: Completed
D16: =D15+1 -> 12 | E16: 79/2 | F16: DA+0 | G16: Ahmed Construction | H16: 45911 | I16: 45915 | J16: Completed
D17: =D16+1 -> 13 | E17: 133/2 | F17: DA+0 | G17: Windbridge Energy | H17: 45897 | I17: 45916 | J17: Completed
... D34: =D33+1 -> 30 | E34: 149B/1 | F34: DA+3 | G34: Gokul Sarkar | H34: 45924 | I34: 45927 | J34: Completed

Sheet Erection 
A1: NAME OF PROJECT : FARHEGARH IV-BHINMAL 400KV D/C TRANSMISSION LINE
A2: Client : RAJASTHAN IV A POWER TRANSMISSION LTD.
A3: CONTRACTOR : KEC INTERNATIONAL LIMITED
A5: SL. No. | B5: Location No. | C5: Tower Type | D5: Tower Weight | E5: Gang Name | F5: Starting Date | G5: Completion Date | H5: Remarks
A6: 1 | B6: 77/2 | C6: DA+3 | D6: 11.145 | E6: Dipak | F6: 45831 | G6: 45836 | H6: Completed
A7: =A6+1 -> 2 | B7: 77/4 | C7: DA+3 | D7: 11.997 | E7: Dipak | F7: 45836 | G7: 45840 | H7: Completed
A8: =A7+1 -> 3 | B8: 75/7 | C8: DA+0 | D8: 11.145 | E8: Srikarni | F8: 45837 | G8: 45843 | H8: Completed
A9: =A8+1 -> 4 | B9: 77/5 | C9: DA+6 | D9: 13.072 | E9: Dipak | F9: 45841 | G9: 45843 | H9: Completed
A10: =A9+1 -> 5 | B10: 77/3 | C10: DA+0 | D10: 11.145 | E10: Dipak | F10: 45845 | G10: 45848 | H10: Completed
A11: =A10+1 -> 6 | B11: 77/1 | C11: DA+0 | D11: 11.145 | E11: Dipak | F11: 45849 | G11: 45852 | H11: Completed | M11: 185
A12: =A11+1 -> 7 | B12: 75/6 | C12: DA+0 | D12: 11.145 | E12: Dipak | F12: 45853 | G12: 45856 | H12: Completed
A13: =A12+1 -> 8 | B13: 75/5 | C13: DA+0 | D13: 11.145 | E13: Dipak | F13: 45857 | G13: 45860 | H13: Completed | K13: 90 | M13: 24
A14: =A13+1 -> 9 | B14: 75/4 | C14: DA+0 | D14: 11.145 | E14: Dipak | F14: 45860 | G14: 45863 | H14: Completed
A15: =A14+1 -> 10 | B15: 75/3 | C15: DA+3 | D15: 11.997 | E15: Dipak | F15: 45863 | G15: 45866 | H15: Completed
A16: =A15+1 -> 11 | B16: 75/2 | C16: DA+0 | D16: 11.145 | E16: Dipak | F16: 45867 | G16: 45869 | H16: Completed
A17: =A16+1 -> 12 | B17: 74/1 | C17: DA+0 | D17: 11.145 | E17: Ahmed Construction | F17: 45862 | G17: 45869 | H17: Completed
A18: =A17+1 -> 13 | B18: 75/1 | C18: DA+0 | D18: 11.145 | E18: Dipak | F18: 45870 | G18: 45873 | H18: Completed | J18: 41
A19: =A18+1 -> 14 | B19: 73/3 | C19: DA+9 | D19: 13.958 | E19: Ahmed Construction | F19: 45870 | G19: 45877 | H19: Completed
A20: =A19+1 -> 15 | B20: 75/0 | C20: DC+0 | D20: 18.727009 | E20: Dipak | F20: 45873 | G20: 45878 | H20: Completed
A21: =A20+1 -> 16 | B21: 73/2 | C21: DA+9 | D21: 13.958 | E21: Ahmed Construction | F21: 45877 | G21: 45885 | H21: Completed
A22: =A21+1 -> 17 | B22: 78/0 | C22: DC+0 | D22: 18.727009 | E22: Dipak | F22: 45879 | G22: 45885 | H22: Completed
A23: =A22+1 -> 18 | B23: 85/1 | C23: DA+0 | D23: 11.145 | E23: Ahmed Construction | F23: 45886 | G23: 45892 | H23: Completed
A24: =A23+1 -> 19 | B24: 79/0 | C24: DD+0 | D24: 21.41 | E24: Dipak | F24: 45886 | G24: 45892 | H24: Completed
A25: =A24+1 -> 20 | B25: 86/1 | C25: DA+6 | D25: 13.072 | E25: Ahmed Construction | F25: 45892 | G25: 45897 | H25: Completed
A26: =A25+1 -> 21 | B26: 80/1 | C26: DA+9 | D26: 13.958 | E26: Dipak | F26: 45892 | G26: 45897 | H26: Completed
A27: =A26+1 -> 22 | B27: 148/4 | C27: DA+0 | D27: 11.145 | E27: Gokul Sarkar | F27: 45896 | G27: 45898 | H27: Completed
A28: =A27+1 -> 23 | B28: 95A/1 | C28: DA+0 | D28: 11.145 | E28: Ajay Kumar | F28: 45892 | G28: 45900 | H28: Completed
A29: =A28+1 -> 24 | B29: 81/3 | C29: DA+0 | D29: 11.145 | E29: Dipak | F29: 45898 | G29: 45900 | H29: Completed
A30: =A29+1 -> 25 | B30: 148/3 | C30: DA+0 | D30: 11.145 | E30: Gokul Sarkar | F30: 45898 | G30: 45904 | H30: Completed
... A32: =A31+1 -> 27 | B32: 145/1 | C32: DA+3 | D32: 11.997 | E32: Ayansh Const | F32: 45896 | G32: 45909 | H32: Completed
A33: =A32+1 -> 28 | B33: 81/4 | C33: DA+0 | D33: 11.145 | E33: Dipak | F33: 45905 | G33: 45909 | H33: Completed | I33: 148/1 | J33: HOLD
A34: =A33+1 -> 29 | B34: 148/2 | C34: DA+0 | D34: 11.145 | E34: Gokul Sarkar | F34: 45905 | G34: 45910 | H34: Completed
A35: =A34+1 -> 30 | B35: 83/1 | C35: DA+3 | D35: 11.997 | E35: Ahmed Construction | F35: 45898 | G35: 45911 | H35: Completed
A36: =A35+1 -> 31 | B36: 97/0 | C36: DC+0 | D36: 18.727009 | E36: Ajay Kumar1 | F36: 45901 | G36: 45911 | H36: Completed
A37: =A36+1 -> 32 | B37: 148/5 | C37: DA+0 | D37: 11.145 | E37: Gokul Sarkar | F37: 45911 | G37: 45914 | H37: Completed
A38: =A37+1 -> 33 | B38: 145/2 | C38: DA+0 | D38: 11.145 | E38: Ayansh Const | F38: 45909 | G38: 45914 | H38: Completed
A39: =A38+1 -> 34 | B39: 82/1 | C39: DA+6 | D39: 13.072 | E39: Dipak | F39: 45909 | G39: 45914 | H39: Completed | J39: 113/0,DC+0
A40: =A39+1 -> 35 | B40: 96/1 | C40: DA+0 | D40: 11.145 | E40: Ajay Kumar1 | F40: 45901 | G40: 45915 | H40: Completed
A41: =A40+1 -> 36 | B41: 79/2 | C41: DA+0 | D41: 11.145 | E41: Ahmed Construction | F41: 45911 | G41: 45915 | H41: Completed | I41: 133/3
A42: =A41+1 -> 37 | B42: 133/2 | C42: DA+0 | D42: 11.145 | E42: Bhoi Enterprises | F42: 45897 | G42: 45916 | H42: Completed
A43: =A42+1 -> 38 | B43: 148/6 | C43: DA+0 | D43: 11.145 | E43: Gokul Sarkar | F43: 45914 | G43: 45919 | H43: Completed | I43: 148/7
A44: =A43+1 -> 39 | B44: 145/3 | C44: DA+0 | D44: 11.145 | E44: Ayansh Const | F44: 45914 | G44: 45919 | H44: Completed | I44: 145/4
A45: =A44+1 -> 40 | B45: 143/5 | C45: DA+3 | D45: 11.997 | E45: Prayag Saw1 | F45: 45911 | G45: 45917 | H45: Completed
A46: =A45+1 -> 41 | B46: 143/4 | C46: DA+3 | D46: 11.997 | E46: Prayag Saw2 | F46: 45911 | G46: 45917 | H46: Completed | I46: 143/2
A47: =A46+1 -> 42 | B47: 143/2 | C47: DA+0 | D47: 11.145 | E47: Prayag Saw1 | F47: 45918 | G47: 45920 | H47: Completed | I47: 143/3 | J47: 143/1
A48: =A47+1 -> 43 | B48: 143/6 | C48: DA+0 | D48: 11.145 | E48: Prayag Saw2 | F48: 45918 | G48: 45920 | H48: Completed | I48: 143/7
A49: =A48+1 -> 44 | B49: 97/1 | C49: DA+3 | D49: 11.997 | E49: Ajay Kumar2 | F49: 45911 | G49: 45921 | H49: Completed | I49: 98A/1
A50: =A49+1 -> 45 | B50: 113A/0 | C50: DC+0 | D50: 18.727009 | E50: Dipak | F50: 45914 | G50: 45921 | H50: Completed
A51: =A50+1 -> 46 | B51: 133/3 | C51: DA+0 | D51: 11.145 | E51: Bhoi Enterprises | F51: 45917 | G51: 45922 | H51: Completed | L51: 79/1 | M51: 64/3
A52: =A51+1 -> 47 | B52: 143/3 | C52: DA+3 | D52: 11.997 | E52: Prayag Saw1 | F52: 45921 | G52: 45923 | H52: Completed | I52: 98/0 | J52: ROW | K52: 98A/1
A53: =A52+1 -> 48 | B53: 143/7 | C53: DA+6 | D53: 13.072 | E53: Prayag Saw2 | F53: 45921 | G53: 45923 | H53: Completed
A54: =A53+1 -> 49 | B54: 148/7 | C54: DA+0 | D54: 11.145 | E54: Gokul Sarkar | F54: 45920 | G54: 45923 | H54: Completed
A55: =A54+1 -> 50 | B55: 98/1 | C55: DA+0 | D55: 11.145 | E55: Ajay Kumar1 | F55: 45915 | G55: 45924 | H55: Completed | I55: 115/0,116/1,114/0,112/1,111/0
A56: =A55+1 -> 51 | B56: 114/1 | C56: DA+9 | D56: 13.958 | E56: Dipak | F56: 45924 | G56: 45926 | H56: Completed | I56: 96/2 | J56: 45915 | K56: 76/0 | L56: 98A/0
A57: =A56+1 -> 52 | B57: 143/1 | C57: DA+6 | D57: 13.072 | E57: Prayag Saw2 | F57: 45922 | G57: 45927 | H57: Completed
A58: =A57+1 -> 53 | B58: 141/2 | C58: DA+6 | D58: 13.072 | E58: Prayag Saw1 | F58: 45924 | G58: 45927 | H58: Completed
A59: =A58+1 -> 54 | B59: 149B/1 | C59: DA+3 | D59: 11.997 | E59: Gokul Sarkar | F59: 45924 | G59: 45927 | H59: Completed
A60: =A59+1 -> 55 | B60: 76/1 | C60: DA+6 | D60: 13.072 | E60: Ahmed Construction | F60: 45919 | G60: 45927 | H60: Completed
A61: =A60+1 -> 56 | B61: 116/1 | C61: DA+0 | D61: 11.145 | E61: Dipak | F61: 45927 | G61: 45929 | H61: Completed | N61: 45929
A62: =A61+1 -> 57 | B62: 133/6 | C62: DA+3 | D62: 11.997 | E62: Bhoi Enterprises | F62: 45923 | G62: 45929 | H62: Completed | N62: 45930 | O62: 133/7
A63: =A62+1 -> 58 | B63: 149B/2 | C63: DA+0 | D63: 11.145 | E63: Gokul Sarkar | F63: 45927 | G63: 45930 | H63: Completed | N63: 45929 | O63: 147/7 | P63: 147/8 | Q63: 149/0 | R63: 149A/0
A64: =A63+1 -> 59 | B64: 145/4 | C64: DA+3 | D64: 11.997 | E64: Pritam Enterprises | F64: 45920 | G64: 45930 | H64: Completed | N64: 45929 | O64: 146/1
A65: =A64+1 -> 60 | B65: 141/1 | C65: DA+0 | D65: 11.145 | E65: Prayag Saw1 | F65: 45927 | G65: 45930 | H65: Completed
A66: =A65+1 -> 61 | B66: 143/0 | C66: DC+3 | D66: =(14703.841+4275.97)/1000 -> 18.979811 | E66: Prayag Saw2 | F66: 45927 | G66: 45930 | H66: Completed | N66: 45929 | O66: 142/0
A67: =A66+1 -> 62 | B67: 98A/1 | C67: DA+0 | D67: 11.145 | E67: Ajay Kumar2 | F67: 45923 | G67: 45931 | H67: Completed
A68: =A67+1 -> 63 | B68: 146/1 | C68: DA+3 | D68: 11.997 | E68: Pritam Enterprises | F68: 45930 | G68: 45933 | H68: Completed
A69: =A68+1 -> 64 | B69: 147/7 | C69: DA+0 | D69: 11.145 | E69: Gokul Sarkar | F69: 45930 | G69: 45933 | H69: Completed
A70: =A69+1 -> 65 | B70: 133/7 | C70: DA+0 | D70: 11.145 | E70: Bhoi Enterprises | F70: 45929 | G70: 45935 | H70: Completed
A71: =A70+1 -> 66 | B71: 146/2 | C71: DA+0 | D71: 11.145 | E71: Pritam Enterprises | F71: 45933 | G71: 45935 | H71: Completed
A72: =A71+1 -> 67 | B72: 116/0 | C72: DD+0 | D72: 21.41 | E72: Dipak | F72: 45930 | G72: 45937 | H72: Completed | X72: GST@18 | Y72: =#REF!*0.18 -> #REF!
A73: =A72+1 -> 68 | B73: 142/0 | C73: DC+3 | D73: =(14703.841+4275.97)/1000 -> 18.979811 | E73: Prayag Saw1 | F73: 45931 | G73: 45937 | H73: Completed | N73: ROW SINCE 3-10-25 to 5-10-25 | S73: 85/1 | T73: DA+0 | V73: DA+0 | W73: 3 | X73: 11.15 | Y73: =X73*W73 -> 33.45 | Z73: =511-72 -> 439
A74: =A73+1 -> 69 | B74: 144/0 | C74: DD+6 | D74: =(16972.938+2884.468+1298.28+5135.312)/1000 -> 26.290998 | E74: Prayag Saw2 | F74: 45931 | G74: 45938 | H74: Completed | Y74: 9000
A75: =A74+1 -> 70 | B75: 146/0 | C75: DC+0 | D75: 18.727009 | E75: Pritam Enterprises | F75: 45935 | G75: 45940 | H75: Completed | S75: 73/2 | T75: DA+9
A76: =A75+1 -> 71 | B76: 140/2 | C76: DA+3 | D76: 11.997 | E76: Prayag Saw1 | F76: 45938 | G76: 45940 | H76: Completed
A77: =A76+1 -> 72 | B77: 149/0 | C77: DD+0 | D77: 21.41 | E77: Gokul Sarkar | F77: 45933 | G77: 45940 | H77: Completed | X77: TOTAL | Y77: =SUM(Y72:Y72) -> #REF!
A78: =A77+1 -> 73 | B78: 133/8 | C78: DA+6 | D78: 13.072 | E78: Bhoi Enterprises | F78: 45935 | G78: 45941 | H78: Completed | X78: RETENTION | Y78: =Y77*0.05 -> #REF!
A79: =A78+1 -> 74 | B79: 140/3 | C79: DA+3 | D79: 11.997 | E79: Prayag Saw1 | F79: 45940 | G79: 45941 | H79: Completed | X79: TDS 1% | Y79: =Y77*0.01 -> #REF!
A80: =A79+1 -> 75 | B80: 147/0 | C80: DC+0 | D80: 18.727009 | E80: Pritam Enterprises | F80: 45940 | G80: 45942 | H80: Completed | X80: PF 10 | Y80: =Y77*0.1 -> #REF!
A81: =A80+1 -> 76 | B81: 115/0 | C81: DC+0 | D81: 18.727009 | E81: Dipak | F81: 45938 | G81: 45943 | H81: Completed | X81: GST 20 | Y81: =Y77*0.2 -> #REF!
A82: =A81+1 -> 77 | B82: 138/1 | C82: DA+0 | D82: 11.145 | E82: Prayag Saw2 | F82: 45938 | G82: 45943 | H82: Completed | X82: ADVANCE | Y82: 600000
A83: =A82+1 -> 78 | B83: 98A/0 | C83: DC+0 | D83: 18.727009 | E83: Ajay Kumar | F83: 45926 | G83: 45945 | H83: Completed | X83: TIGHT & PUNCH 10 | Y83: =Y77*0.1 -> #REF!
A84: =A83+1 -> 79 | B84: 149A/0 | C84: DD+0 | D84: 21.41 | E84: Gokul Sarkar | F84: 45940 | G84: 45945 | H84: Completed | X84: NET PAYABLE | Y84: =Y77-#REF!-Y82 -> #REF!
A85: =A84+1 -> 80 | B85: 133/4 | C85: DA+0 | D85: 11.145 | E85: Bhoi Enterprises | F85: 45941 | G85: 45945 | H85: Completed
A86: =A85+1 -> 81 | B86: 141/0 | C86: DC+0 | D86: 18.727009 | E86: Prayag Saw1 | F86: 45941 | G86: 45946 | H86: Completed
A87: =A86+1 -> 82 | B87: 147/3 | C87: DA+0 | D87: 11.145 | E87: Pritam Enterprises | F87: 45942 | G87: 45945 | H87: Completed
A88: =A87+1 -> 83 | B88: 138/2 | C88: DA+0 | D88: 11.145 | E88: Prayag Saw2 | F88: 45943 | G88: 45946 | H88: Completed
A89: =A88+1 -> 84 | B89: 110/0 | C89: DC+0 | D89: 18.727009 | E89: Dipak | F89: 45943 | G89: 45948 | H89: Completed
A90: =A89+1 -> 85 | B90: 133/1 | C90: DA+0 | D90: 11.145 | E90: Bhoi Enterprises | F90: 45945 | G90: 45949 | H90: Completed
A91: =A90+1 -> 86 | B91: 138/3 | C91: DA+0 | D91: 11.145 | E91: Prayag Saw2 | F91: 45946 | G91: 45949 | H91: Completed
A92: =A91+1 -> 87 | B92: 147/9 | C92: DA+0 | D92: 11.145 | E92: Gokul Sarkar | F92: 45946 | G92: 45949 | H92: Completed
A93: =A92+1 -> 88 | B93: 147/2 | C93: DA+0 | D93: 11.145 | E93: Pritam Enterprises | F93: 45945 | G93: 45949 | H93: Completed
A94: =A93+1 -> 89 | B94: 147/1 | C94: DA+0 | D94: 11.145 | E94: Pritam Enterprises | F94: 45949 | G94: 45952 | H94: Completed
A95: =A94+1 -> 90 | B95: 147/8 | C95: DA+0 | D95: 11.145 | E95: Gokul Sarkar | F95: 45949 | G95: 45952 | H95: Completed
A96: =A95+1 -> 91 | B96: 134A/0 | C96: DD+0 | D96: 21.41 | E96: Prayag Saw1 | F96: 45946 | G96: 45953 | H96: Completed
... A98: =A97+1 -> 93 | B98: 82/2 | C98: DA+0 | D98: 11.145 | E98: Namechand Mahto | F98: 45949 | G98: 45954 | H98: Completed
A99: =A98+1 -> 94 | B99: 138/0 | C99: DB+3 | D99: =(13334+4777.506)/1000 -> 18.111506 | E99: Prayag Saw2 | F99: 45949 | G99: 45954 | H99: Completed
A100: =A99+1 -> 95 | B100: 134A/2 | C100: DA+3 | D100: 11.997 | E100: Prayag Saw1 | F100: 45954 | G100: 45956 | H100: Completed
A101: =A100+1 -> 96 | B101: 112/0 | C101: DC+9 | D101: =(14703.841+2903.104+1061.94+ 5513.756)/1000 -> 24.182641 | E101: Dipak | F101: 45949 | G101: 45957 | H101: Completed
A102: =A101+1 -> 97 | B102: 147/6 | C102: DA+0 | E102: Pritam Enterprises | F102: 45953 | G102: 45956 | H102: Completed
A103: =A102+1 -> 98 | B103: 148/1 | C103: DA+0 | E103: Gokul Sarkar | F103: 45953 | G103: 45957 | H103: Completed
...

Sheet Completion date
A1: Location no | B1: Tower type | C1: FDN TYPE | D1: FDN CMP date | E1: Erection CMP Date | F1: Earthing CMP Date
A2: GANTRY | B2: GE | C2: =VLOOKUP(A2,Foundation!$B$8:$P$557,10, 0) -> #N/A | D2: =VLOOKUP(A2,Foundation!$B$8:$P$540,12, 0) -> #N/A | E2: =VLOOKUP(A2,'Erection Compiled '!$B$2:$Q$516,10, 0) -> #N/A | F2: =VLOOKUP(A2,Earthing!$B$7:$G$560,4, 0) -> #N/A
A3: 1/0 | B3: DE+0 | C3: =VLOOKUP(A3,Foundation!$B$8:$P$557,10, 0) -> #N/A | D3: =VLOOKUP(A3,Foundation!$B$8:$P$540,12, 0) -> #N/A | E3: =VLOOKUP(A3,'Erection Compiled '!$B$2:$Q$516,10, 0) -> #N/A | F3: =VLOOKUP(A3,Earthing!$B$7:$G$560,4, 0) -> #N/A
A4: 1A/0 | B4: DD+0 | C4: =VLOOKUP(A4,Foundation!$B$8:$P$557,10, 0) -> #N/A | D4: =VLOOKUP(A4,Foundation!$B$8:$P$540,12, 0) -> #N/A | E4: =VLOOKUP(A4,'Erection Compiled '!$B$2:$Q$516,10, 0) -> #N/A | F4: =VLOOKUP(A4,Earthing!$B$7:$G$560,4, 0) -> #N/A
A5: 2/0 | B5: DD+0 | C5: =VLOOKUP(A5,Foundation!$B$8:$P$557,10, 0) -> #N/A | D5: =VLOOKUP(A5,Foundation!$B$8:$P$540,12, 0) -> #N/A | E5: =VLOOKUP(A5,'Erection Compiled '!$B$2:$Q$516,10, 0) -> #N/A | F5: =VLOOKUP(A5,Earthing!$B$7:$G$560,4, 0) -> #N/A
A6: 2/1 | B6: Gantry UCS | C6: =VLOOKUP(A6,Foundation!$B$8:$P$557,10, 0) -> #N/A | D6: =VLOOKUP(A6,Foundation!$B$8:$P$540,12, 0) -> #N/A | E6: =VLOOKUP(A6,'Erection Compiled '!$B$2:$Q$516,10, 0) -> #N/A | F6: =VLOOKUP(A6,Earthing!$B$7:$G$560,4, 0) -> #N/A
A7: 3/0 | B7: Gantry UCS | C7: =VLOOKUP(A7,Foundation!$B$8:$P$557,10, 0) -> #N/A | D7: =VLOOKUP(A7,Foundation!$B$8:$P$540,12, 0) -> #N/A | E7: =VLOOKUP(A7,'Erection Compiled '!$B$2:$Q$516,10, 0) -> #N/A | F7: =VLOOKUP(A7,Earthing!$B$7:$G$560,4, 0) -> #N/A
A8: 3/1 | B8: DD+3 | C8: =VLOOKUP(A8,Foundation!$B$8:$P$557,10, 0) -> DFR | D8: =VLOOKUP(A8,Foundation!$B$8:$P$540,12, 0) -> 0 | E8: =VLOOKUP(A8,'Erection Compiled '!$B$2:$Q$516,10, 0) -> #N/A | F8: =VLOOKUP(A8,Earthing!$B$7:$G$560,4, 0) -> #N/A
A9: 4/0 | B9: DD+18 | C9: =VLOOKUP(A9,Foundation!$B$8:$P$557,10, 0) -> DFR | D9: =VLOOKUP(A9,Foundation!$B$8:$P$540,12, 0) -> 46081 | E9: =VLOOKUP(A9,'Erection Compiled '!$B$2:$Q$516,10, 0) -> #N/A | F9: =VLOOKUP(A9,Earthing!$B$7:$G$560,4, 0) -> #N/A
A10: 5/0 | B10: DD+9 | C10: =VLOOKUP(A10,Foundation!$B$8:$P$557,10, 0) -> #N/A | D10: =VLOOKUP(A10,Foundation!$B$8:$P$540,12, 0) -> #N/A | E10: =VLOOKUP(A10,'Erection Compiled '!$B$2:$Q$516,10, 0) -> #N/A | F10: =VLOOKUP(A10,Earthing!$B$7:$G$560,4, 0) -> #N/A
A11: 5/1 | B11: DA+0 | C11: =VLOOKUP(A11,Foundation!$B$8:$P$557,10, 0) -> #N/A | D11: =VLOOKUP(A11,Foundation!$B$8:$P$540,12, 0) -> #N/A | E11: =VLOOKUP(A11,'Erection Compiled '!$B$2:$Q$516,10, 0) -> #N/A | F11: =VLOOKUP(A11,Earthing!$B$7:$G$560,4, 0) -> #N/A
A12: 5/2 | B12: DA+0 | C12: =VLOOKUP(A12,Foundation!$B$8:$P$557,10, 0) -> #N/A | D12: =VLOOKUP(A12,Foundation!$B$8:$P$540,12, 0) -> #N/A | E12: =VLOOKUP(A12,'Erection Compiled '!$B$2:$Q$516,10, 0) -> #N/A | F12: =VLOOKUP(A12,Earthing!$B$7:$G$560,4, 0) -> #N/A
A13: 5/3 | B13: DA+0 | C13: =VLOOKUP(A13,Foundation!$B$8:$P$557,10, 0) -> #N/A | D13: =VLOOKUP(A13,Foundation!$B$8:$P$540,12, 0) -> #N/A | E13: =VLOOKUP(A13,'Erection Compiled '!$B$2:$Q$516,10, 0) -> #N/A | F13: =VLOOKUP(A13,Earthing!$B$7:$G$560,4, 0) -> #N/A
... A509: 150/0 | B509: DD+9 | C509: =VLOOKUP(A509,Foundation!$B$8:$P$557,10, 0) -> DFR | D509: =VLOOKUP(A509,Foundation!$B$8:$P$540,12, 0) -> 45959 | E509: =VLOOKUP(A509,'Erection Compiled '!$B$2:$Q$516,10, 0) -> 45998 | F509: =VLOOKUP(A509,Earthing!$B$7:$G$560,4, 0) -> 45959

Sheet Erection Compiled 
A1: SL No. | B1: Location No. | C1: Tower Type | D1: Classification | E1: Starting Date | F1: Tower Weight | G1: Status | K1: Completion Date | L1: Gang Name | M1: Gang Strength | N1: Remark
A2: 1 | B2: 77/2 | C2: DA+3 | E2: 45831 | F2: 11.997 | G2: COMPLETE | K2: 45836 | L2: Dipak
A3: =A2+1 -> 2 | B3: 77/4 | C3: DA+3 | E3: 45836 | F3: 11.997 | G3: COMPLETE | K3: 45840 | L3: Dipak
A4: =A3+1 -> 3 | B4: 75/7 | C4: DA+0 | E4: 45837 | F4: 11.145 | G4: COMPLETE | K4: 45843 | L4: Srikarni
A5: =A4+1 -> 4 | B5: 77/5 | C5: DA+6 | E5: 45841 | F5: 13.687 | G5: COMPLETE | K5: 45843 | L5: Dipak
A6: =A5+1 -> 5 | B6: 77/3 | C6: DA+0 | E6: 45845 | F6: 11.145 | G6: COMPLETE | K6: 45848 | L6: Dipak
A7: =A6+1 -> 6 | B7: 77/1 | C7: DA+0 | E7: 45849 | F7: 11.145 | G7: COMPLETE | K7: 45852 | L7: Dipak
A8: =A7+1 -> 7 | B8: 75/6 | C8: DA+0 | E8: 45853 | F8: 11.145 | G8: COMPLETE | K8: 45856 | L8: Dipak
A9: =A8+1 -> 8 | B9: 75/5 | C9: DA+0 | E9: 45857 | F9: 11.145 | G9: COMPLETE | K9: 45860 | L9: Dipak
A10: =A9+1 -> 9 | B10: 75/4 | C10: DA+0 | E10: 45860 | F10: 11.145 | G10: COMPLETE | K10: 45863 | L10: Dipak
A11: =A10+1 -> 10 | B11: 75/3 | C11: DA+3 | E11: 45863 | F11: 11.997 | G11: COMPLETE | K11: 45866 | L11: Dipak
A12: =A11+1 -> 11 | B12: 75/2 | C12: DA+0 | E12: 45867 | F12: 11.145 | G12: COMPLETE | K12: 45869 | L12: Dipak
A13: =A12+1 -> 12 | B13: 74/1 | C13: DA+0 | E13: 45862 | F13: 11.145 | G13: COMPLETE | K13: 45869 | L13: Ahmed Construction
A14: =A13+1 -> 13 | B14: 75/1 | C14: DA+0 | E14: 45870 | F14: 11.145 | G14: COMPLETE | K14: 45873 | L14: Dipak
A15: =A14+1 -> 14 | B15: 73/3 | C15: DA+9 | E15: 45870 | F15: 14.573 | G15: COMPLETE | K15: 45877 | L15: Ahmed Construction
A16: =A15+1 -> 15 | B16: 75/0 | C16: DC+0 | E16: 45873 | F16: 18.727 | G16: COMPLETE | K16: 45878 | L16: Dipak
A17: =A16+1 -> 16 | B17: 73/2 | C17: DA+9 | E17: 45877 | F17: 14.573 | G17: COMPLETE | K17: 45885 | L17: Ahmed Construction
A18: =A17+1 -> 17 | B18: 78/0 | C18: DC+0 | E18: 45879 | F18: 18.727 | G18: COMPLETE | K18: 45885 | L18: Dipak
A19: =A18+1 -> 18 | B19: 85/1 | C19: DA+0 | E19: 45886 | F19: 11.145 | G19: COMPLETE | K19: 45892 | L19: Ahmed Construction
A20: =A19+1 -> 19 | B20: 79/0 | C20: DD+0 | E20: 45886 | F20: 21.410 | G20: COMPLETE | K20: 45892 | L20: Dipak
A21: =A20+1 -> 20 | B21: 86/1 | C21: DA+6 | E21: 45892 | F21: 13.687 | G21: COMPLETE | K21: 45897 | L21: Ahmed Construction
A22: =A21+1 -> 21 | B22: 80/1 | C22: DA+9 | E22: 45892 | F22: 14.573 | G22: COMPLETE | K22: 45897 | L22: Dipak
A23: =A22+1 -> 22 | B23: 148/4 | C23: DA+0 | E23: 45896 | F23: 11.145 | G23: COMPLETE | K23: 45898 | L23: Gokul Sarkar | M23: 17
A24: =A23+1 -> 23 | B24: 81/3 | C24: DA+0 | E24: 45898 | F24: 11.145 | G24: COMPLETE | K24: 45900 | L24: Dipak
A25: =A24+1 -> 24 | B25: 95A/1 | C25: DA+0 | E25: 45892 | F25: 11.145 | G25: COMPLETE | K25: 45902 | L25: Ajay Kumar
A26: =A25+1 -> 25 | B26: 148/3 | C26: DA+0 | E26: 45898 | F26: 11.145 | G26: COMPLETE | K26: 45904 | L26: Gokul Sarkar | M26: 17
A27: =A26+1 -> 26 | B27: 81/2 | C27: DA+3 | E27: 45901 | F27: 11.997 | G27: COMPLETE | K27: 45905 | L27: Dipak
A28: =A27+1 -> 27 | B28: 145/1 | C28: DA+3 | E28: 45896 | F28: 11.997 | G28: COMPLETE | K28: 45909 | L28: Ayansh Const
A29: =A28+1 -> 28 | B29: 81/4 | C29: DA+0 | E29: 45905 | F29: 11.145 | G29: COMPLETE | K29: 45909 | L29: Dipak
A30: =A29+1 -> 29 | B30: 148/2 | C30: DA+0 | E30: 45905 | F30: 11.145 | G30: COMPLETE | K30: 45910 | L30: Gokul Sarkar | M30: 17
A31: =A30+1 -> 30 | B31: 83/1 | C31: DA+3 | E31: 45898 | F31: 11.997 | G31: COMPLETE | K31: 45911 | L31: Ahmed Construction
A32: =A31+1 -> 31 | B32: 97/0 | C32: DC+0 | E32: 45901 | F32: 18.727 | G32: COMPLETE | K32: 45911 | L32: Ajay Kumar1
A33: =A32+1 -> 32 | B33: 148/5 | C33: DA+0 | E33: 45911 | F33: 11.145 | G33: COMPLETE | K33: 45914 | L33: Gokul Sarkar | M33: 17
A34: =A33+1 -> 33 | B34: 145/2 | C34: DA+0 | E34: 45909 | F34: 11.145 | G34: COMPLETE | K34: 45914 | L34: Ayansh Const
A35: =A34+1 -> 34 | B35: 82/1 | C35: DA+6 | E35: 45909 | F35: 13.687 | G35: COMPLETE | K35: 45914 | L35: Dipak
A36: =A35+1 -> 35 | B36: 96/1 | C36: DA+0 | E36: 45901 | F36: 11.145 | G36: COMPLETE | K36: 45915 | L36: Ajay Kumar1
A37: =A36+1 -> 36 | B37: 79/2 | C37: DA+0 | E37: 45911 | F37: 11.145 | G37: COMPLETE | K37: 45915 | L37: Ahmed Construction
A38: =A37+1 -> 37 | B38: 133/2 | C38: DA+0 | E38: 45897 | F38: 11.145 | G38: COMPLETE | K38: 45916 | L38: Bhoi Enterprises | M38: 23
A39: =A38+1 -> 38 | B39: 148/6 | C39: DA+0 | E39: 45914 | F39: 11.145 | G39: COMPLETE | K39: 45919 | L39: Gokul Sarkar | M39: 17
A40: =A39+1 -> 39 | B40: 145/3 | C40: DA+0 | E40: 45914 | F40: 11.145 | G40: COMPLETE | K40: 45919 | L40: Ayansh Const
A41: =A40+1 -> 40 | B41: 143/5 | C41: DA+3 | E41: 45911 | F41: 11.997 | G41: COMPLETE | K41: 45917 | L41: Prayag Saw | M41: 26
A42: =A41+1 -> 41 | B42: 143/4 | C42: DA+3 | E42: 45911 | F42: 11.997 | G42: COMPLETE | K42: 45917 | L42: Prayag Saw2 | M42: 26
A43: =A42+1 -> 42 | B43: 143/2 | C43: DA+0 | E43: 45918 | F43: 11.145 | G43: COMPLETE | K43: 45920 | L43: Prayag Saw | M43: 26
A44: =A43+1 -> 43 | B44: 143/6 | C44: DA+0 | E44: 45918 | F44: 11.145 | G44: COMPLETE | K44: 45920 | L44: Prayag Saw2 | M44: 26
A45: =A44+1 -> 44 | B45: 97/1 | C45: DA+3 | E45: 45911 | F45: 11.997 | G45: COMPLETE | K45: 45921 | L45: Ajay Kumar2
A46: =A45+1 -> 45 | B46: 113A/0 | C46: DC+0 | E46: 45914 | F46: 18.727 | G46: COMPLETE | K46: 45921 | L46: Dipak
A47: =A46+1 -> 46 | B47: 133/3 | C47: DA+0 | E47: 45917 | F47: 11.145 | G47: COMPLETE | K47: 45922 | L47: Bhoi Enterprises | M47: 23
A48: =A47+1 -> 47 | B48: 143/3 | C48: DA+3 | E48: 45921 | F48: 11.997 | G48: COMPLETE | K48: 45923 | L48: Prayag Saw | M48: 26
A49: =A48+1 -> 48 | B49: 143/7 | C49: DA+6 | E49: 45921 | F49: 13.687 | G49: COMPLETE | K49: 45923 | L49: Prayag Saw2 | M49: 26
A50: =A49+1 -> 49 | B50: 148/7 | C50: DA+0 | E50: 45920 | F50: 11.145 | G50: COMPLETE | K50: 45923 | L50: Gokul Sarkar | M50: 17
A51: =A50+1 -> 50 | B51: 98/1 | C51: DA+0 | E51: 45915 | F51: 11.145 | G51: COMPLETE | K51: 45924 | L51: Ajay Kumar1
A52: =A51+1 -> 51 | B52: 114/1 | C52: DA+9 | E52: 45924 | F52: 14.573 | G52: COMPLETE | K52: 45926 | L52: Dipak
A53: =A52+1 -> 52 | B53: 143/1 | C53: DA+6 | E53: 45922 | F53: 13.687 | G53: COMPLETE | K53: 45927 | L53: Prayag Saw2 | M53: 26
A54: =A53+1 -> 53 | B54: 141/2 | C54: DA+6 | E54: 45924 | F54: 13.687 | G54: COMPLETE | K54: 45927 | L54: Prayag Saw | M54: 26
A55: =A54+1 -> 54 | B55: 149B/1 | C55: DA+3 | E55: 45924 | F55: 11.997 | G55: COMPLETE | K55: 45927 | L55: Gokul Sarkar | M55: 17
A56: =A55+1 -> 55 | B56: 76/1 | C56: DA+6 | E56: 45919 | F56: 13.687 | G56: COMPLETE | K56: 45927 | L56: Ahmed Construction
A57: =A56+1 -> 56 | B57: 116/1 | C57: DA+0 | E57: 45927 | F57: 11.145 | G57: COMPLETE | K57: 45929 | L57: Dipak
A58: =A57+1 -> 57 | B58: 133/6 | C58: DA+3 | E58: 45923 | F58: 11.997 | G58: COMPLETE | K58: 45929 | L58: Bhoi Enterprises | M58: 23
A59: =A58+1 -> 58 | B59: 149B/2 | C59: DA+0 | E59: 45927 | F59: 11.145 | G59: COMPLETE | K59: 45930 | L59: Gokul Sarkar | M59: 17
A60: =A59+1 -> 59 | B60: 145/4 | C60: DA+3 | E60: 45920 | F60: 11.997 | G60: COMPLETE | K60: 45930 | L60: Pritam Enterprises
A61: =A60+1 -> 60 | B61: 141/1 | C61: DA+0 | E61: 45927 | F61: 11.145 | G61: COMPLETE | K61: 45930 | L61: Prayag Saw | M61: 26
A62: =A61+1 -> 61 | B62: 143/0 | C62: DC+3 | E62: 45927 | F62: 20.006 | G62: COMPLETE | K62: 45930 | L62: Prayag Saw2 | M62: 26
A63: =A62+1 -> 62 | B63: 98A/1 | C63: DA+0 | E63: 45923 | F63: 11.145 | G63: COMPLETE | K63: 45931 | L63: Ajay Kumar2
A64: =A63+1 -> 63 | B64: 146/1 | C64: DA+3 | E64: 45930 | F64: 11.997 | G64: COMPLETE | K64: 45933 | L64: Pritam Enterprises
A65: =A64+1 -> 64 | B65: 147/7 | C65: DA+0 | E65: 45930 | F65: 11.145 | G65: COMPLETE | K65: 45933 | L65: Gokul Sarkar | M65: 17
A66: =A65+1 -> 65 | B66: 133/7 | C66: DA+0 | E66: 45929 | F66: 11.145 | G66: COMPLETE | K66: 45935 | L66: Bhoi Enterprises | M66: 23
A67: =A66+1 -> 66 | B67: 146/2 | C67: DA+0 | E67: 45933 | F67: 11.145 | G67: COMPLETE | K67: 45935 | L67: Pritam Enterprises
A68: =A67+1 -> 67 | B68: 116/0 | C68: DD+0 | E68: 45930 | F68: 21.410 | G68: COMPLETE | K68: 45937 | L68: Dipak
A69: =A68+1 -> 68 | B69: 142/0 | C69: DC+3 | E69: 45931 | F69: 20.006 | G69: COMPLETE | K69: 45937 | L69: Prayag Saw | M69: 26
A70: =A69+1 -> 69 | B70: 144/0 | C70: DD+6 | E70: 45931 | F70: 26.291 | G70: COMPLETE | K70: 45938 | L70: Prayag Saw2 | M70: 26
A71: =A70+1 -> 70 | B71: 146/0 | C71: DC+0 | E71: 45935 | F71: 18.727 | G71: COMPLETE | K71: 45940 | L71: Pritam Enterprises
A72: =A71+1 -> 71 | B72: 140/2 | C72: DA+3 | E72: 45938 | F72: 11.997 | G72: COMPLETE | K72: 45940 | L72: Prayag Saw | M72: 26
A73: =A72+1 -> 72 | B73: 149/0 | C73: DD+0 | E73: 45933 | F73: 21.410 | G73: COMPLETE | K73: 45940 | L73: Gokul Sarkar | M73: 17
A74: =A73+1 -> 73 | B74: 133/8 | C74: DA+6 | E74: 45935 | F74: 13.687 | G74: COMPLETE | K74: 45941 | L74: Bhoi Enterprises | M74: 23
A75: =A74+1 -> 74 | B75: 140/3 | C75: DA+3 | E75: 45940 | F75: 11.997 | G75: COMPLETE | K75: 45941 | L75: Prayag Saw | M75: 26
A76: =A75+1 -> 75 | B76: 147/0 | C76: DC+0 | E76: 45940 | F76: 18.727 | G76: COMPLETE | K76: 45942 | L76: Pritam Enterprises
A77: =A76+1 -> 76 | B77: 115/0 | C77: DC+0 | E77: 45938 | F77: 18.727 | G77: COMPLETE | K77: 45943 | L77: Dipak
A78: =A77+1 -> 77 | B78: 138/1 | C78: DA+0 | E78: 45938 | F78: 11.145 | G78: COMPLETE | K78: 45943 | L78: Prayag Saw2 | M78: 26
A79: =A78+1 -> 78 | B79: 98A/0 | C79: DC+0 | E79: 45926 | F79: 18.727 | G79: COMPLETE | K79: 45945 | L79: Ajay Kumar
A80: =A79+1 -> 79 | B80: 149A/0 | C80: DD+0 | E80: 45940 | F80: 21.410 | G80: COMPLETE | K80: 45945 | L80: Gokul Sarkar | M80: 17
A81: =A80+1 -> 80 | B81: 133/4 | C81: DA+0 | E81: 45941 | F81: 11.145 | G81: COMPLETE | K81: 45945 | L81: Bhoi Enterprises | M81: 23
A82: =A81+1 -> 81 | B82: 141/0 | C82: DC+0 | E82: 45941 | F82: 18.727 | G82: COMPLETE | K82: 45946 | L82: Prayag Saw | M82: 26
A83: =A82+1 -> 82 | B83: 147/3 | C83: DA+0 | E83: 45942 | F83: 11.145 | G83: COMPLETE | K83: 45945 | L83: Pritam Enterprises
A84: =A83+1 -> 83 | B84: 138/2 | C84: DA+0 | E84: 45943 | F84: 11.145 | G84: COMPLETE | K84: 45946 | L84: Prayag Saw2 | M84: 26
A85: =A84+1 -> 84 | B85: 110/0 | C85: DC+0 | E85: 45943 | F85: 18.727 | G85: COMPLETE | K85: 45948 | L85: Dipak
A86: =A85+1 -> 85 | B86: 133/1 | C86: DA+0 | E86: 45945 | F86: 11.145 | G86: COMPLETE | K86: 45949 | L86: Bhoi Enterprises | M86: 23
A87: =A86+1 -> 86 | B87: 138/3 | C87: DA+0 | E87: 45946 | F87: 11.145 | G87: COMPLETE | K87: 45949 | L87: Prayag Saw2 | M87: 26
A88: =A87+1 -> 87 | B88: 147/9 | C88: DA+0 | E88: 45946 | F88: 11.145 | G88: COMPLETE | K88: 45949 | L88: Gokul Sarkar | M88: 17
A89: =A88+1 -> 88 | B89: 147/2 | C89: DA+0 | E89: 45945 | F89: 11.145 | G89: COMPLETE | K89: 45949 | L89: Pritam Enterprises
A90: =A89+1 -> 89 | B90: 147/1 | C90: DA+0 | E90: 45949 | F90: 11.145 | G90: COMPLETE | K90: 45952 | L90: Pritam Enterprises
A91: =A90+1 -> 90 | B91: 147/8 | C91: DA+0 | E91: 45949 | F91: 11.145 | G91: COMPLETE | K91: 45952 | L91: Gokul Sarkar | M91: 17
A92: =A91+1 -> 91 | B92: 134A/0 | C92: DD+0 | E92: 45946 | F92: 21.410 | G92: COMPLETE | K92: 45953 | L92: Prayag Saw | M92: 26
A93: =A92+1 -> 92 | B93: 135/1 | C93: DA+0 | E93: 45949 | F93: 11.145 | G93: COMPLETE | K93: 45954 | L93: Bhoi Enterprises | M93: 23
A94: =A93+1 -> 93 | B94: 82/2 | C94: DA+0 | E94: 45949 | F94: 11.145 | G94: COMPLETE | K94: 45954 | L94: Namechand Mahto | M94: 20
A95: =A94+1 -> 94 | B95: 138/0 | C95: DB+3 | E95: 45949 | F95: 18.111 | G95: COMPLETE | K95: 45954 | L95: Prayag Saw2 | M95: 26
A96: =A95+1 -> 95 | B96: 134A/2 | C96: DA+3 | E96: 45954 | F96: 11.997 | G96: COMPLETE | K96: 45956 | L96: Prayag Saw | M96: 26
A97: =A96+1 -> 96 | B97: 112/0 | C97: DC+9 | E97: 45949 | F97: 24.183 | G97: COMPLETE | K97: 45957 | L97: Dipak
A98: =A97+1 -> 97 | B98: 147/6 | C98: DA+0 | E98: 45953 | F98: 11.145 | G98: COMPLETE | K98: 45956 | L98: Pritam Enterprises
A99: =A98+1 -> 98 | B99: 148/1 | C99: DA+0 | E99: 45953 | F99: 11.145 | G99: COMPLETE | K99: 45957 | L99: Gokul Sarkar | M99: 17
A100: =A99+1 -> 99 | B100: 147/5 | C100: DA+0 | E100: 45957 | F100: 11.145 | G100: COMPLETE | K100: 45958 | L100: Pritam Enterprises
...

Sheet Earthing
A1: NAME OF PROJECT : FARHEGARH IV-BHINMAL 400KV D/C TRANSMISSION LINE
A2: Client : RAJASTHAN IV A POWER TRANSMISSION LTD.
A3: CONTRACTOR : KEC INTERNATIONAL LIMITED
A5: SL. No. | B5: Location Number | C5: Tower Type | D5: Foundation type | E5: Completion Date | F5: Remarks
A7: =A6+1 -> 1 | B7: 75/7 | C7: DA+0 | D7: Sandy | E7: 45685 | F7: Complete | G7: RA-2
A8: =A7+1 -> 2 | B8: 75/6 | C8: DA+0 | D8: Sandy | E8: 45691 | F8: Complete | G8: RA-2
A9: =A8+1 -> 3 | B9: 75/3 | C9: DA+3 | D9: Sandy | E9: 45697 | F9: Complete | G9: RA-2
A10: =A9+1 -> 4 | B10: 77/5 | C10: DA+6 | D10: Sandy | E10: 45708 | F10: Complete | G10: RA-2
A11: =A10+1 -> 5 | B11: 73/3 | C11: DA+09 | D11: Sandy | E11: 45710 | F11: Complete | G11: RA-2
A12: =A11+1 -> 6 | B12: 75/1 | C12: DA+00 | D12: Sandy | E12: 45710 | F12: Complete | G12: RA-2
A13: =A12+1 -> 7 | B13: 75/2 | C13: DA+0 | D13: Sandy | E13: 45710 | F13: Complete | G13: RA-2
A14: =A13+1 -> 8 | B14: 77/1 | C14: DA+0 | D14: Sandy | E14: 45712 | F14: Complete | G14: RA-2
A15: =A14+1 -> 9 | B15: 77/4 | C15: DA+3 | D15: Sandy | E15: 45712 | F15: Complete | G15: RA-2
A16: =A15+1 -> 10 | B16: 79/1 | C16: DA+9 | D16: Sandy | E16: 45712 | F16: Complete | G16: RA-2
A17: =A16+1 -> 11 | B17: 73/2 | C17: DA+9 | D17: Sandy | E17: 45713 | F17: Complete | G17: RA-2
A18: =A17+1 -> 12 | B18: 95A/1 | C18: DA+0 | D18: DFR | E18: 45713 | F18: Complete | G18: RA-2
... A58: =A57+1 -> 52 | B58: 81/3 | C58: DA+0 | D58: Sandy | E58: 45813 | F58: Complete | G58: RA-6
A59: =A58+1 -> 53 | B59: 120/1 | C59: DA+6 | D59: Sandy | E59: 45814 | F59: Complete
A60: =A59+1 -> 54 | B60: 96/0 | C60: DC+0 | D60: Sandy | E60: 45815 | F60: Complete | G60: RA-6
A61: =A60+1 -> 55 | B61: 82/2 | C61: DA+0 | D61: Sandy | E61: 45818 | F61: Complete | G61: RA-6
A62: =A61+1 -> 56 | B62: 97/0 | C62: DC +0 | D62: Sandy | E62: 45818 | F62: Complete | G62: RA-6
A63: =A62+1 -> 57 | B63: 147/2 | C63: DA+0 | D63: Sandy | E63: 45821 | F63: Complete
A64: =A63+1 -> 58 | B64: 79/0 | C64: DD+0 | D64: Sandy | E64: 45822 | F64: Complete
A65: =A64+1 -> 59 | B65: 119/0 | C65: DD+3 | D65: Sandy | E65: 45823 | F65: Complete
A66: =A65+1 -> 60 | B66: 147/4 | C66: DA+0 | D66: Sandy | E66: 45824 | F66: Complete | G66: RA 9
A67: =A66+1 -> 61 | B67: 78/0 | C67: DC+0 | D67: Sandy | E67: 45824 | F67: Complete
A68: =A67+1 -> 62 | B68: 82/1 | C68: DA+6 | D68: Sandy | E68: 45824 | F68: Complete
A69: =A68+1 -> 63 | B69: 74/0 | C69: DB+9 | D69: Sandy | E69: 45828 | F69: Complete
A70: =A69+1 -> 64 | B70: 147/1 | C70: DA+0 | D70: Sandy | E70: 45830 | F70: Complete
A71: =A70+1 -> 65 | B71: 95A/0 | C71: DB+0 | D71: Sandy | E71: 45832 | F71: Complete
A72: =A71+1 -> 66 | B72: 146/2 | C72: DA+0 | D72: Sandy | E72: 45833 | F72: Complete
A73: =A72+1 -> 67 | B73: 147/0 | C73: DC+0 | D73: Sandy | E73: 45835 | F73: Complete
A74: =A73+1 -> 68 | B74: 73/0 | C74: DB+0 | D74: Sandy | E74: 45836 | F74: Complete
A75: =A74+1 -> 69 | B75: 147/3 | C75: DA+0 | D75: Sandy | E75: 45837 | F75: Complete | G75: RA 9
A76: =A75+1 -> 70 | B76: 147/7 | C76: DA+0 | D76: Sandy | E76: 45837 | F76: Complete | G76: RA 9
A77: =A76+1 -> 71 | B77: 86/0 | C77: DD+0 | D77: Sandy | E77: 45837 | F77: Complete | G77: RA-6
A78: =A77+1 -> 72 | B78: 147/8 | C78: DA+0 | D78: Sandy | E78: 45839 | F78: Complete | G78: RA 9
A79: =A78+1 -> 73 | B79: 72/2 | C79: DA+3 | D79: DFR | E79: 45839 | F79: Complete
A80: =A79+1 -> 74 | B80: 95/1 | C80: DB+0 | D80: DFR | E80: 45844 | F80: Complete
A81: =A80+1 -> 75 | B81: 106/0 | C81: DC+6 | D81: Sandy | E81: 45845 | F81: Complete
A82: =A81+1 -> 76 | B82: 114/0 | C82: DC+0 | D82: Sandy | E82: 45845 | F82: Complete
A83: =A82+1 -> 77 | B83: 146/0 | C83: DC+0 | D83: Sandy | E83: 45846 | F83: Complete
A84: =A83+1 -> 78 | B84: 146/1 | C84: DA+3 | D84: Sandy | E84: 45846 | F84: Complete
A85: =A84+1 -> 79 | B85: 114/1 | C85: DA+9 | D85: Sandy | E85: 45848 | F85: Complete
A86: =A85+1 -> 80 | B86: 80/0 | C86: DB+3,1MRC | D86: Sandy | E86: 45848 | F86: Complete
A87: =A86+1 -> 81 | B87: 145/4 | C87: DA+0 | D87: Sandy | E87: 45850 | F87: Complete | G87: RA 9
A88: =A87+1 -> 82 | B88: 133/6 | C88: DA+3 | D88: Sandy | E88: 45854 | F88: Complete | G88: RA 9
A89: =A88+1 -> 83 | B89: 95/0 | C89: DB+9 | D89: DFR | E89: 45854 | F89: Complete
A90: =A89+1 -> 84 | B90: 133/5 | C90: DA+0 | D90: Sandy | E90: 45855 | F90: Complete | G90: RA 9
A91: =A90+1 -> 85 | B91: 145/1 | C91: DA+3 | D91: Sandy | E91: 45855 | F91: Complete | G91: RA 9
A92: =A91+1 -> 86 | B92: 145/2 | C92: DA+0 | D92: Sandy | E92: 45855 | F92: Complete | G92: RA 9
A93: =A92+1 -> 87 | B93: 148/1 | C93: DA+0 | D93: Sandy | E93: 45855 | F93: Complete | G93: RA 9
A94: =A93+1 -> 88 | B94: 148/2 | C94: DA+0 | D94: Sandy | E94: 45855 | F94: Complete | G94: RA 9
A95: =A94+1 -> 89 | B95: 148/3 | C95: DA+0 | D95: Sandy | E95: 45855 | F95: Complete | G95: RA 9
A96: =A95+1 -> 90 | B96: 109A/0 | C96: DB+6 | D96: Sandy | E96: 45858 | F96: Complete
A97: =A96+1 -> 91 | B97: 113A/0 | C97: DC+0 | D97: Sandy | E97: 45858 | F97: Complete
A98: =A97+1 -> 92 | B98: 133/4 | C98: DA+0 | D98: Sandy | E98: 45858 | F98: Complete
A99: =A98+1 -> 93 | B99: 148/6 | C99: DA+0 | D99: Sandy | E99: 45859 | F99: Complete | G99: RA 9
A100: =A99+1 -> 94 | B100: 77/0 | C100: DB+0 | D100: Sandy | E100: 45859 | F100: Complete
A101: =A100+1 -> 95 | B101: 115/0 | C101: DC+0 | D101: Sandy | E101: 45860 | F101: Complete
A102: =A101+1 -> 96 | B102: 141/2 | C102: DA+6 | D102: Sandy | E102: 45862 | F102: Complete | G102: RA 9
A103: =A102+1 -> 97 | B103: 143/0 | C103: DC+3 | D103: Sandy | E103: 45862 | F103: Complete | G103: RA 9
A104: =A103+1 -> 98 | B104: 133/3 | C104: DA+0 | D104: Sandy | E104: 45863 | F104: Complete | G104: RA 9
A105: =A104+1 -> 99 | B105: 94/0 | C105: DB+6 | D105: Sandy | E105: 45863 | F105: Complete
A106: =A105+1 -> 100 | B106: 133/8 | C106: DA+6 | D106: Sandy | E106: 45864 | F106: Complete | G106: RA 9
A107: =A106+1 -> 101 | B107: 148/7 | C107: DA+0 | D107: Sandy | E107: 45865 | F107: Complete | G107: RA 9
A108: =A107+1 -> 102 | B108: 79/2 | C108: DA+0 | D108: Sandy | E108: 45866 | F108: Complete
A109: =A108+1 -> 103 | B109: 149B/1 | C109: DA+3 | D109: Sandy | E109: 45866 | F109: Complete | G109: RA 12
A110: =A109+1 -> 104 | B110: 99/3 | C110: DA+3 | D110: Sandy | E110: 45867 | F110: Complete
A111: =A110+1 -> 105 | B111: 110/0 | C111: DC+0 | D111: Sandy | E111: 45868 | F111: Complete
A112: =A111+1 -> 106 | B112: 149B/2 | C112: DA+0 | D112: Sandy | E112: 45869 | F112: Complete | G112: RA 12
A113: =A112+1 -> 107 | B113: 111/0 | C113: DB+9,3MRC | D113: Sandy | E113: 45870 | F113: Complete
A114: =A113+1 -> 108 | B114: 133/1 | C114: DA+0 | D114: Sandy | E114: 45870 | F114: Complete | G114: RA 9
A115: =A114+1 -> 109 | B115: 133/7 | C115: DA+0 | D115: Sandy | E115: 45870 | F115: Complete | G115: RA 9
A116: =A115+1 -> 110 | B116: 98B/0 | C116: DD+0 | D116: DFR | E116: 45871 | F116: Complete
A117: =A116+1 -> 111 | B117: 87/0 | C117: DC+0 | D117: Sandy | E117: 45871 | F117: Complete
A118: =A117+1 -> 112 | B118: 116/0 | C118: DD+0 | D118: Sandy | E118: 45872 | F118: Complete
A119: =A118+1 -> 113 | B119: 76/0 | C119: DC+0 | D119: Sandy | E119: 45872 | F119: Complete
A120: =A119+1 -> 114 | B120: 83/0 | C120: DC+0 | D120: Sandy | E120: 45874 | F120: Complete
A121: =A120+1 -> 115 | B121: 143/5 | C121: DA+3 | D121: Sandy | E121: 45875 | F121: Complete
A122: =A121+1 -> 116 | B122: 143/6 | C122: DA+0 | D122: Sandy | E122: 45875 | F122: Complete | G122: RA 9
A123: =A122+1 -> 117 | B123: 143/7 | C123: DA+3 | D123: Sandy | E123: 45875 | F123: Complete
A124: =A123+1 -> 118 | B124: 144/0 | C124: DD+6 | D124: Sandy | E124: 45875 | F124: Complete | G124: RA 9
A125: =A124+1 -> 119 | B125: 145/3 | C125: DA+0 | D125: Sandy | E125: 45875 | F125: Complete | G125: RA 9
A126: =A125+1 -> 120 | B126: 97/1 | C126: DA+3 | D126: Sandy | E126: 45875 | F126: Complete
A127: =A126+1 -> 121 | B127: 145/0 | C127: DD+6 | D127: Sandy | E127: 45876 | F127: Complete | G127: RA 9
A128: =A127+1 -> 122 | B128: 98/0 | C128: DC+0,1MRC | D128: Sandy | E128: 45876 | F128: Complete
A129: =A128+1 -> 123 | B129: 102/2 | C129: DA+0 | D129: Sandy | E129: 45877 | F129: Complete
A130: =A129+1 -> 124 | B130: 129/0 | C130: DC+0 | D130: Sandy | E130: 45877 | F130: Complete | G130: RA 9
A131: =A130+1 -> 125 | B131: 133/2 | C131: DA+0 | D131: Sandy | E131: 45877 | F131: Complete | G131: RA 9
A132: =A131+1 -> 126 | B132: 112/0 | C132: DC+9 | D132: Sandy | E132: 45879 | F132: Complete
A133: =A132+1 -> 127 | B133: 143/1 | C133: DA+6 | D133: Sandy | E133: 45881 | F133: Complete
A134: =A133+1 -> 128 | B134: 99/0 | C134: DC +0 | D134: Sandy | E134: 45881 | F134: Complete
A135: =A134+1 -> 129 | B135: 142/0 | C135: DC+3 | D135: Sandy | E135: 45882 | F135: Complete | G135: RA 9
A136: =A135+1 -> 130 | B136: 143/3 | C136: DA+3 | D136: Sandy | E136: 45882 | F136: Complete
A137: =A136+1 -> 131 | B137: 102/1 | C137: DA+0 | D137: Sandy | E137: 45885 | F137: Complete
A138: =A137+1 -> 132 | B138: 115/1 | C138: DB+9 | D138: Sandy | E138: 45885 | F138: Complete
A139: =A138+1 -> 133 | B139: 134A/4 | C139: DD+0 | D139: Sandy | E139: 45888 | F139: Complete | G139: RA 9
A140: =A139+1 -> 134 | B140: 140/2 | C140: DA+3 | D140: Sandy | E140: 45888 | F140: Complete | G140: RA 9
A141: =A140+1 -> 135 | B141: 140/3 | C141: DA+3 | D141: Sandy | E141: 45888 | F141: Complete | G141: RA 9
...

Sheet Final Check In And Tack Welding
B1: NAME OF PROJECT : FARHEGARH IV-BHINMAL 400KV D/C TRANSMISSION LINE
B2: Client : RAJASTHAN IV A POWER TRANSMISSION LTD.
B3: CONTRACTOR : KEC INTERNATIONAL LIMITED
B4: SL No | C4: Loc No | D4: Final Checking | E4: Tack Welding
B5: 1 | C5: 65/0 | D5: DONE
B6: =B5+1 -> 2 | C6: 65/1 | D6: DONE
B7: =B6+1 -> 3 | C7: 66/0 | D7: DONE
B8: =B7+1 -> 4 | C8: 109A/0 | D8: DONE
B9: =B8+1 -> 5 | C9: 110/0 | D9: DONE
B10: =B9+1 -> 6 | C10: 111/0 | D10: DONE
B11: =B10+1 -> 7 | C11: 112/0 | D11: DONE
B12: =B11+1 -> 8 | C12: 113/0 | D12: DONE
B13: =B12+1 -> 9 | C13: 113A/0 | D13: DONE
B14: =B13+1 -> 10 | C14: 114/1 | D14: DONE
B15: =B14+1 -> 11 | C15: 115/0 | D15: DONE
B16: =B15+1 -> 12 | C16: 115/1 | D16: DONE
B17: =B16+1 -> 13 | C17: 116/0 | D17: DONE
... B29: =B28+1 -> 25 | C29: 132/1 | D29: DONE
B30: =B29+1 -> 26 | C30: 132/2 | D30: DONE | E30: WIP
B31: =B30+1 -> 27 | C31: 132/3 | D31: DONE | E31: DONE
B32: =B31+1 -> 28 | C32: 132/4 | D32: DONE | E32: DONE
B33: =B32+1 -> 29 | C33: 133/0 | D33: DONE | E33: DONE
B34: =B33+1 -> 30 | C34: 133/1 | D34: DONE | E34: DONE
B35: =B34+1 -> 31 | C35: 133/2 | D35: DONE | E35: DONE
B36: =B35+1 -> 32 | C36: 133/3 | D36: DONE | E36: DONE
B37: =B36+1 -> 33 | C37: 133/4 | D37: DONE | E37: DONE
B38: =B37+1 -> 34 | C38: 133/5 | D38: DONE | E38: DONE
B39: =B38+1 -> 35 | C39: 133/6 | D39: DONE | E39: ROW
B40: =B39+1 -> 36 | C40: 133/7 | D40: DONE | E40: DONE
B41: =B40+1 -> 37 | C41: 133/8 | D41: DONE | E41: DONE
B42: =B41+1 -> 38 | C42: 134/0 | D42: DONE | E42: DONE
B43: =B42+1 -> 39 | C43: 134A/0 | D43: DONE
B44: =B43+1 -> 40 | C44: 134A/1 | D44: DONE
B45: =B44+1 -> 41 | C45: 134A/2 | D45: DONE
B46: =B45+1 -> 42 | C46: 134A/3 | D46: DONE
B47: =B46+1 -> 43 | C47: 134A/4 | D47: DONE
B48: =B47+1 -> 44 | C48: 135/0 | D48: DONE
B49: =B48+1 -> 45 | C49: 135/1 | D49: ROW
B50: =B49+1 -> 46 | C50: 135/2 | D50: WIP
B51: =B50+1 -> 47 | C51: 139/1 | D51: WIP
B52: =B51+1 -> 48 | C52: 140/0 | D52: DONE | E52: DONE
B53: =B52+1 -> 49 | C53: 140/1 | D53: DONE | E53: DONE
B54: =B53+1 -> 50 | C54: 140/2 | D54: DONE | E54: DONE
B55: =B54+1 -> 51 | C55: 140/3 | D55: DONE | E55: DONE
B56: =B55+1 -> 52 | C56: 141/0 | D56: DONE | E56: DONE
B57: =B56+1 -> 53 | C57: 141/1 | D57: DONE | E57: DONE
B58: =B57+1 -> 54 | C58: 141/2 | D58: DONE | E58: DONE
B59: =B58+1 -> 55 | C59: 142/0 | D59: DONE | E59: DONE
B60: =B59+1 -> 56 | C60: 143/0 | D60: DONE | E60: DONE
B61: =B60+1 -> 57 | C61: 143/1 | D61: DONE | E61: DONE
B62: =B61+1 -> 58 | C62: 143/2 | D62: DONE | E62: DONE
B63: =B62+1 -> 59 | C63: 143/3 | D63: DONE | E63: DONE
... B103: =B102+1 -> 99 | C103: 152/0 | D103: DONE | E103: ROW
B104: =B103+1 -> 100 | C104: 153/0 | D104: DONE
B105: =B104+1 -> 101 | C105: 153A/0 | D105: DONE | E105: DONE
B106: =B105+1 -> 102 | C106: 154/0 | D106: DONE | E106: DONE

Sheet Stringing Compiled 
D1: Number of TSE | E1: 1
A3: S.no | B3: Sec | C3: From AP | D3: To AP | E3: Span (M) | F3: Method | G3: Section Readiness | H3: P/O Starting Date | I3: P/O Completion Date | J3: P/O | K3: F/S Starting Date | L3: F/S/ Completion Date | M3: Length | N3: Status | O3: Gang Name | P3: Hindrance | Q3: Remarks
A4: 1 | B4: Bhinmal | C4: 149A/0 | D4: 149/0 | E4: 188 | F4: Manual | G4: Ready | H4: 46082 | I4: 46084 | K4: 46084 | L4: 46084 | M4: =E4 -> 188 | N4: complete | O4: Mahadev Enterprises | Q4: Final Sag Complete
A5: 2 | B5: Bhinmal | C5: 149/0 | D5: 148/0 | E5: 3031 | F5: TSE | G5: Ready | H5: 46054 | I5: 46059 | K5: 46097 | L5: 46099 | M5: =E5 -> 3031 | N5: complete | O5: Mahadev Enterprises | Q5: Final Sag Complete
A6: 3 | B6: Bhinmal | C6: 148/0 | D6: 147/0 | E6: 3666 | F6: TSE | G6: Ready | H6: 46060 | M6: =E6 -> 3666 | N6: WIP | O6: Mahadev Enterprises | Q6: Pilot wire pulling
A7: 4 | B7: Bhinmal | C7: 146/0 | D7: 145/0 | E7: 1970 | F7: TSE | G7: Ready | H7: 46067 | I7: 46069 | K7: 46073 | L7: 46075 | M7: =E7 -> 1970 | N7: complete | O7: Mahadev Enterprises | Q7: Final Sag Complete
A8: 5 | B8: Bhinmal | C8: 147/0 | D8: 146/0 | E8: 1223 | F8: TSE | G8: Ready | H8: 46071 | I8: 46076 | K8: 46101 | M8: =E8 -> 1223 | N8: WIP | O8: Mahadev Enterprises | Q8: Final Sag WIP
A9: 6 | B9: Bhinmal | C9: 150/0 | D9: 149B/3 | E9: 489 | F9: Manual | G9: Ready | H9: 46079 | I9: 46080 | K9: 46089 | L9: 46089 | M9: =E9 -> 489 | N9: complete | O9: Mahadev Enterprises | Q9: Final Sag Complete
A10: 7 | B10: Bhinmal | C10: 149B/0 | D10: 149A/0 | E10: 396 | F10: Manual | G10: Ready | H10: 46086 | I10: 46086 | K10: 46091 | L10: 46091 | M10: =E10 -> 396 | N10: complete | O10: Mahadev Enterprises | Q10: Final Sag Complete
A11: 8 | B11: Bhinmal | C11: 149B/3 | D11: 149B/0 | E11: 1265 | F11: TSE | G11: Ready | H11: 46086 | I11: 46090 | K11: 46089 | L11: 46091 | M11: =E11 -> 1265 | N11: complete | O11: Mahadev Enterprises | Q11: Final Sag Complete
A12: 9 | B12: Bhinmal | C12: 144/0 | D12: 143/0 | E12: 3275 | F12: TSE | G12: Ready | H12: 46104 | M12: =E12 -> 3275 | N12: WIP | O12: Mahadev Enterprises | Q12: Paying out WIP
A13: 10 | B13: Bhinmal | C13: 143/0 | D13: 142/0 | E13: 437 | F13: Manual | G13: Ready | H13: 46104 | I13: 46107 | M13: =E13 -> 437 | N13: WIP | O13: Mahadev Enterprises | Q13: Paying out Complete
D14: Total

Sheet Soil Investigation
A1: NAME OF PROJECT : FARHEGARH IV-BHINMAL 400KV D/C TRANSMISSION LINE
A2: Client : RAJASTHAN IV A POWER TRANSMISSION LTD.
A3: CONTRACTOR : KEC INTERNATIONAL LIMITED
A4: SOIL INVESTIGATION STATUS
A5: SL No. | B5: LOC. No. | C5: Tower Type | D5: Soil Investigation date | E5: Recommended Soil classification | F5: Remarks
A6: 1 | B6: 3/0 | C6: DD+25 | D6: 45689
A7: 2 | B7: 4/0 | C7: DC+0 | D7: 45689
A8: 3 | B8: 6/0 | C8: DD+18 | D8: 45688
A9: 4 | B9: 7/0 | C9: DB+0 | D9: 45688
A10: 5 | B10: 8/0 | C10: DB+0 | D10: 45688
A11: 6 | B11: 9/0 | C11: DB+0 | D11: 45688
A12: 7 | B12: 10/0 | C12: DC+9 | D12: 45687
A13: 8 | B13: 12/0 | C13: DD+0 | D13: 45687
A14: 9 | B14: 13/0 | C14: DC+0 | D14: 45687
A15: 10 | B15: 15/0 | C15: DC+6 | D15: 45686
A16: 11 | B16: 16/0 | C16: DC+0 | D16: 45686
A17: 12 | B17: 17/0 | C17: DB+0 | D17: 45686
... A60: 55 | B60: 133/0 | C60: DD+0 | D60: 45675
A61: 56 | B61: 133/1 | C61: DC+0 | D61: 45675 | F61: River Crossing
A62: 57 | B62: 133/2 | C62: DA+0 | D62: 45675 | F62: River Crossing
A63: 58 | B63: 133/3 | C63: DA+0 | D63: 45675
A64: 59 | B64: 134/0 | C64: DA+3 | D64: 45676
A65: 60 | B65: 137/0 | C65: DB+0 | D65: 45676
A66: 61 | B66: 138/0 | C66: DB+3 | D66: 45677
A67: 62 | B67: 141/0 | C67: DB+3 | D67: 45677
A68: 63 | B68: 144/0 | C68: DC+0 | D68: 45677
A69: 64 | B69: 145/0 | C69: DD+6 | D69: 45678
A70: 65 | B70: 147/0 | C70: DD+6 | D70: 45678
A71: 66 | B71: 148/0 | C71: DC+0 | D71: 45679
A72: 67 | B72: 150/0 | C72: DB+0 | D72: 45678
A73: 68 | B73: 151/0 | C73: DD+9 | D73: 45679
A74: 69 | B74: 152/0 | C74: DD+9 | D74: 45679
... A78: 73 | B78: 2/0 | C78: DD+25 | D78: 45744
A79: Total Completed | D79: 73

Sheet Sheet9
A1: 400 KV D/C (TWIN) FATEHGARH IV - BHINMAL (PG) TRANSMISSION LINE (VISUAL CHART)
A2: Name of Contractor:M/S KEC INTERNATIONAL LIMITED | Z2: AS ON | AB2: =NOW()-1 -> 46113.496
A3: PROGRESS AT A GLANCE :
S4: Stringing WIP | W4: Stringing Completed
A5: Sl. No. | C5: Activity | F5: UoM | H5: Total Qty | K5: Completed | N5: Balance | AA5: River Crossing
A7: 1 | C7: Detail survey | F7: Kms. | H7: 188.444 | K7: 188.444 | N7: =H7-K7 -> 0
A8: =A7+1 -> 2 | C8: Check survey | F8: Kms. | H8: 188.444 | K8: 178.075 | N8: =H8-K8 -> 10.369
A9: =A8+1 -> 3 | C9: CS Approval | F9: Kms. | H9: 188.444 | K9: 178.075 | N9: =H9-K9 -> 10.369
A10: =A9+1 -> 4 | C10: Soil Investigation | F10: Loc | H10: 73 | K10: 73 | N10: =H10-K10 -> 0
A11: =A10+1 -> 5 | C11: Foundation | F11: Loc | H11: 512 | K11: 208 | N11: =H11-K11 -> 304 | AA11: Erection WIP
A12: =A11+1 -> 6 | C12: Earthing | F12: Nos. | H12: 514 | K12: 190 | N12: =H12-K12 -> 324 | S12: Erection Comp | V12: Span | AC12: Rly. X-ing
A13: =A12+1 -> 7 | C13: Erection | F13: Loc | H13: 512 | K13: 75 | N13: =H13-K13 -> 437 | S13: Earthing
A14: =A13+1 -> 8 | C14: Tack Welding | F14: Nos. | H14: 512 | N14: =H14-K14 -> 512
A15: =A14+1 -> 9 | C15: Stringing(P/0) | F15: Kms. | H15: 188.444 | N15: 188.444 | S15: Pipe Line | X15: Excavation
A16: =A15+1 -> 10 | C16: Stringing (F/S) | F16: Kms. | H16: 188.444 | N16: 188.444 | Z16: NH | AA16: SH | AB16: 66/132/ 220/ 400
A17: GANTRY | D17: AP1 | F17: AP 1A | H17: AP2 | J17: AP3 | L17: 3/1 | N17: 3/2 | P17: 3/3 | R17: AP4 | T17: 4/1 | V17: 4/2 | X17: 4/3 | Z17: 4/4 | AB17: 4/5 | AC17: SH
AM18: U/P | AN18: ROW | AO18: CLEAR
C20: 89 | E20: 113 | G20: 264 | I20: 244 | K20: 657 | M20: 419.226 | O20: 420.01 | Q20: 416.531 | S20: 356.262 | U20: 343.074 | W20: 381.329 | Y20: 373.323 | AA20: 246.012 | AC20: 249.424 | AM20: =COUNTIF(B20:AB20,"U/P") -> 0 | AN20: =COUNTIF(C20:AC20,"ROW") -> 0 | AO20: =COUNTIF(D20:AD20,"C") -> 0
D22: DD+0 | F22: DD+3 | H22: DD+25 | J22: DD+25 | L22: DB+6 | N22: DA+0 | P22: DA+9 | R22: DC+0 | T22: DA+0 | V22: DA+0 | X22: DA+6 | Z22: DA+3 | AB22: DB+0
A23: REVISED DETAIL SURVEY REPORT SUBMITTED
B24: 4/6 | D24: 4/7 | F24: 4/8 | H24: 4/9 | J24: AP5 | L24: AP6 | N24: 6/1 | P24: 6/2 | R24: 6/3 | T24: 6/4 | V24: 6/5 | X24: 6/6 | Z24: 6/7 | AB24: AP7
C27: 399.707 | E27: 438.616 | G27: 400.604 | I27: 438.765 | K27: 226.315 | M27: 442.553 | O27: 389.329 | Q27: 359.361 | S27: 405.006 | U27: 426.518 | W27: 356.055 | Y27: 369.295 | AA27: 374.993 | AC27: 383.768 | AM27: =COUNTIF(B27:AB27,"U/P") -> 0 | AN27: =COUNTIF(C27:AC27,"ROW") -> 0 | AO27: =COUNTIF(D27:AD27,"C") -> 0
B29: DA+0 | D29: DA+6 | F29: DA+6 | H29: DA+3 | J29: DD+18 | L29: DD+18 | N29: DA+3 | P29: DA+0 | R29: DA+0 | T29: DA+0 | V29: DA+0 | X29: DA+0 | Z29: DA+0 | AB29: DB+0
A30: REVISED DETAIL SURVEY REPORT SUBMITTED
B31: 7/1 | F31: 7/2 | H31: 7/3 | J31: 7/4 | L31: 7/5 | N31: 7/6 | P31: 7/7 | R31: 7/8 | T31: 7/9 | V31: 7/10 | X31: AP8 | Z31: 8/1 | AB31: 8/2
D34: 396.38 | G34: 392.534 | I34: 332.162 | K34: 352.112 | M34: 389.393 | O34: 374.477 | Q34: 419.977 | S34: 387.899 | U34: 407.654 | W34: 402.357 | Y34: 372.259 | AA34: 410.949 | AC34: 379.075 | AM34: =COUNTIF(B34:AB34,"U/P") -> 0 | AN34: =COUNTIF(C34:AC34,"ROW") -> 0 | AO34: =COUNTIF(D34:AD34,"C") -> 0
T35: 1MRC
B36: DA+0 | F36: DA+0 | H36: DA+0 | J36: DA+0 | L36: DA+0 | N36: DA+0 | P36: DA+0 | R36: DA+3 | T36: DA+0 | V36: DA+3 | X36: DB+0 | Z36: DA+0 | AB36: DA+0
A37: WORK FRONT TO BE CLEARED
B38: 8/3 | D38: 8/4 | F38: AP9 | H38: 9/1 | J38: 9/2 | L38: 9/3 | N38: 9/4 | P38: 9/5 | R38: AP 10 | T38: 10/1 | V38: 10/2 | X38: 10/3 | Z38: 10/4 | AB38: 10/5
C41: 412.596 | E41: 340.112 | G41: 410.76 | I41: 427.9 | K41: 404.21 | M41: 398.446 | O41: 431.939 | Q41: 486.196 | S41: 369.717 | U41: 389.344 | W41: 395.602 | Y41: 375 | AA41: 462 | AC41: 382 | AM41: =COUNTIF(B41:AB41,"U/P") -> 0 | AN41: =COUNTIF(C41:AC41,"ROW") -> 0 | AO41: =COUNTIF(D41:AD41,"C") -> 0
B43: DA+0 | D43: DA+3 | F43: DB+0 | H43: DA+3 | J43: DA+6 | L43: DA+0 | N43: DA+3 | P43: DB+9 | R43: DC+3 | T43: DA+3 | V43: DA+0 | X43: DA+3 | Z43: DA+6 | AB43: DA+0
A44: WORK FRONT YET TO BE CLEARED
B45: 10/6 | D45: 10/7 | F45: 10/8 | H45: 10/9 | J45: 10/10 | L45: 10/11 | N45: 10/12 | P45: 10/13 | R45: 10/14 | T45: 10/15 | V45: AP11 | X45: 11/1 | Z45: 11/2 | AB45: 11/3
C48: 428 | E48: 411 | G48: 352 | I48: 405 | K48: 400.126 | M48: 384 | O48: 406 | Q48: 378 | S48: 373 | U48: 378.362 | W48: 433.995 | Y48: 370.685 | AA48: 323.972 | AC48: 384.462 | AM48: =COUNTIF(B48:AB48,"U/P") -> 0 | AN48: =COUNTIF(C48:AC48,"ROW") -> 0 | AO48: =COUNTIF(D48:AD48,"C") -> 0
B50: DA+0 | D50: DA+0 | F50: DA+0 | H50: DB+0 | J50: DA+0 | L50: DA+3 | N50: DA+3 | P50: DA+3 | R50: DA+0 | T50: DA+6 | V50: DB+0 | X50: DA+3 | Z50: DA+0 | AB50: DA+0
D51: 1 MRC-4 Leg | J51: 1 MRC-4 Leg
A52: WORK FRONT YET TO BE CLEARED
B54: 11/4 | D54: 11/5 | F54: 11/6 | H54: AP12 | J54: 12/1 | L54: 12/2 | N54: AP13 | P54: 13/1 | R54: 13/2 | T54: 13/3 | V54: AP14 | X54: 14/1 | Z54: AP15 | AB54: 15/1
C57: 381.188 | E57: 336.409 | G57: 438.97 | I57: 395.179 | K57: 388.12 | M57: 364.446 | O57: 404.572 | Q57: 432.27 | S57: 404.23 | U57: 416.621 | W57: 468.039 | Y57: 432.318 | AA57: 464.521 | AC57: 369.743 | AM57: =COUNTIF(B57:AB57,"U/P") -> 0 | AN57: =COUNTIF(C57:AC57,"ROW") -> 0 | AO57: =COUNTIF(D57:AD57,"C") -> 0
B59: DA+0 | D59: DA+0 | F59: DA+0 | H59: DB+0 | J59: DA+0 | L59: DA+3 | N59: DC+0 | P59: DA+9 | R59: DA+6 | T59: DA+3 | V59: DB+0 | X59: DB+9 | Z59: DC+9 | AB59: DA+6
I60: Pit A,B 1MRC | L60: B,C Bench | V60: 1 MRC -4 Leg
A61: WORK FRONT YET TO BE CLEARED
B62: AP16 | D62: 16/1 | F62: AP17 | H62: 17/1 | J62: AP18 | L62: 18/1 | N62: AP19 | P62: 19/1 | R62: 19/2 | T62: 19/3 | V62: AP20 | X62: 20/1 | Z62: 20/2 | AB62: 20/3
C65: 284.16 | E65: 270.742 | G65: 286.64 | I65: 291.699 | K65: 398.719 | M65: 425.465 | O65: 383.813 | Q65: 403.279 | S65: 355.215 | U65: 399.839 | W65: 287.442 | Y65: 390.748 | AA65: 364.274 | AC65: 337.546 | AM65: =COUNTIF(B65:AB65,"U/P") -> 0 | AN65: =COUNTIF(C65:AC65,"ROW") -> 0 | AO65: =COUNTIF(D65:AD65,"C") -> 0
B67: DD+0 | D67: DA+0 | F67: DB+0 | H67: DA+0 | J67: DC+0 | L67: DA+6 | N67: DD+0 | P67: DA+3 | R67: DA+0 | T67: DA+3 | V67: DC+0 | X67: DA+0 | Z67: DA+0 | AB67: DA+0
M68: Pit D 1MRC | X68: Pit B 1MRC
A69: WORK FRONT YET TO BE CLEARED
B70: 20/4 | D70: 20/5 | F70: 20/6 | H70: AP21 | J70: 21/1 | L70: 21/2 | N70: AP22 | P70: AP23 | R70: 23/1 | T70: 23/2 | V70: 23/3 | X70: AP24 | Z70: 24/1 | AB70: AP25
C73: 348.292 | E73: 418.835 | G73: 408.963 | I73: 365.467 | K73: 437.074 | M73: 363.142 | O73: 159.789 | Q73: 300.158 | S73: 293.131 | U73: 357.377 | W73: 341.409 | Y73: 362.905 | AA73: 421.052 | AC73: 216.448 | AM73: =COUNTIF(B73:AB73,"U/P") -> 0 | AN73: =COUNTIF(C73:AC73,"ROW") -> 0 | AO73: =COUNTIF(D73:AD73,"C") -> 0
B75: DA+0 | D75: DA+3 | F75: DA+9 | H75: DD+3 | J75: DA+0 | L75: DA+6 | N75: DB+3 | P75: DD+0 | R75: DB+3 | T75: DA+0 | V75: DA+0 | X75: DC+9 | Z75: DA+9 | AB75: DD+6
E76: 3MRC-4 LEG
A77: WORK FRONT YET TO BE CLEARED | X77: C/S REPORT TO BE APPROVED
B79: 25/1 | D79: 25/2 | F79: AP 26 | H79: AP 27 | J79: 27A/0 | L79: 27A/1 | N79: 27A/2 | P79: AP27B | R79: 27B/1 | T79: 27B/2 | V79: 27B/3 | X79: AP28 | Z79: 28/1 | AB79: AP29
C82: 439.695 | E82: 243.188 | G82: 333.219 | I82: 333.219 | K82: 363.001 | M82: 363.001 | O82: 356.124 | Q82: 376.245 | S82: 381.122 | U82: 364.433 | W82: 263.077 | Y82: 356.193 | AA82: 352.42 | AC82: 381.028 | AM82: =COUNTIF(B82:AB82,"U/P") -> 0 | AN82: =COUNTIF(C82:AC82,"ROW") -> 0 | AO82: =COUNTIF(D82:AD82,"C") -> 0
B84: GTY | D84: GTY | F84: DB+0 | H84: DC+9 | J84: DD+9 | L84: DA+0 | N84: DA+6 | P84: DC+0 | R84: DA+6 | T84: DA+0 | V84: DA+9 | X84: DB+3 | Z84: DA+3 | AB84: DB+9
A85: C/S REPORT YET TO BE APPROVED | I85: WORK FRONT TO BE CLEARED
B87: 29/1 | D87: 29/2 | F87: 29/3 | H87: AP30 | J87: 30/1 | L87: 30/2 | N87: 30/3 | P87: AP31 | R87: AP32 | T87: 32/1 | V87: 32/2 | X87: 32/3 | Z87: AP33 | AB87: AP34 | AD87: 34/1
C90: 419.603 | E90: 425.18 | G90: 425.18 | I90: 287.537 | K90: 336.512 | M90: 325.304 | O90: 214.253 | Q90: 455.946 | S90: 421 | U90: 419 | W90: 408 | Y90: 409.749 | AA90: 324.03 | AC90: 366.7 | AE90: 473.305 | AM90: =COUNTIF(A90:AB90,"U/P") -> 0 | AN90: =COUNTIF(A90:AC90,"ROW") -> 0 | AO90: =COUNTIF(B90:AD90,"C") -> 0
B92: DA+6 | D92: DA+9 | F92: DB+9 | H92: DC+0 | J92: DA+0 | L92: DA+0 | N92: DA+0 | P92: DC+9 | R92: DC+9 | T92: DA+3 | V92: DA+3 | X92: DA+9 | Z92: DB+0 | AB92: DC+6 | AD92: DA+9
A93: WORK FRONT TO BE CLEARED
B96: AP35 | D96: 35/1 | F96: AP36 | H96: 36/1 | J96: 36/2 | L96: 36A | N96: AP37 | P96: AP38 | R96: 38/1 | T96: 38/2 | V96: 38/3 | X96: 38/4 | Z96: 38/5 | AB96: AP39 | AD96: 39/1 | AF96: 39/2
C99: 358.321 | E99: 477.815 | G99: 415.464 | I99: 402.229 | K99: 437.434 | O99: 455.922 | Q99: 419.765 | S99: 418.917 | U99: 386.486 | W99: 376.53 | AC99: 404.739 | AE99: 366.729 | AG99: 274.587 | AM99: =COUNTIF(A99:AB99,"U/P") -> 0 | AN99: =COUNTIF(A99:AC99,"ROW") -> 0 | AO99: =COUNTIF(B99:AC99,"C") -> 0
B101: DC+9 | D101: DA+9 | F101: DC+6 | H101: DA+9 | J101: DA+0 | L101: DD+0 | N101: DD+0 | P101: DB+0 | R101: DB+6 | T101: DA+3 | V101: DA+9 | X101: DA+0 | Z101: DA+9 | AB101: DB+3 | AD101: DA+6 | AF101: DA+0
A102: WORK FRONT TO BE CLEARED
B104: 39/3 | D104: 39/4 | F104: AP40 | I104: AP41 | K104: 41/1 | M104: 41/2 | O104: 41/3 | Q104: AP42 | S104: 42/1 | U104: 42/2 | W104: 42/3
C107: 341.668 | E107: 425.863 | G107: 370.45 | H107: 397.61 | J107: 413.4 | L107: 423.65 | N107: 415.97 | P107: 415.35 | R107: 394.875 | S107: U/P | T107: 429.62 | V107: 381.905 | X107: 405.26 | AH107: =COUNTIF(B107:W107,"U/P") -> 1 | AI107: =COUNTIF(C107:X107,"ROW") -> 0 | AJ107: =COUNTIF(D107:Y107,"C") -> 0 | AM107: =COUNTIF(B107:AB107,"U/P") -> 1 | AN107: =COUNTIF(C107:AC107,"ROW") -> 0 | AO107: =COUNTIF(D107:AD107,"C") -> 0
S108: ROW
B109: DA+0 | D109: DA+6 | F109: DD+3 | I109: DB+0 | K109: DA+9 | M109: DA+0 | O109: DA+9 | Q109: DC+3 | S109: DA+9 | U109: DCT+6 | W109: DA+9
M110: Pit C,B 1MRC | R110: Benching ,Pit C,B 1MRC | W110: 3MRC-4 LEG
A111: WORK FRONT YET TO BE CLEARED
B112: 42/4 | D112: 42/5 | F112: 42/6 | H112: 42/7 | J112: AP43 | K112: NH | L112: AP44 | N112: 44/1 | P112: AP45 | R112: 45/1 | T112: 45/2 | V112: 45/3 | X112: 45/4 | Z112: AP46 | AB112: AP47
C115: 338.156 | E115: 288.303 | G115: 297.15 | I115: 195.903 | K115: 249.66 | M115: 374.48 | O115: 430.3 | Q115: 404.386 | S115: 341.423 | U115: 305.401 | W115: 319.981 | Y115: 345.621 | AA115: 223.151 | AC115: 393.817 | AM115: =COUNTIF(B115:AB115,"U/P") -> 0 | AN115: =COUNTIF(C115:AC115,"ROW") -> 0 | AO115: =COUNTIF(D115:AD115,"C") -> 0
B117: DA+9 | D117: DA+0 | F117: DA+3 | H117: DA+0 | J117: DC+6 | L117: DB+9 | N117: DA+9 | P117: DD+9 | R117: DA+0 | T117: DA+3 | V117: DA+0 | X117: DA+6 | Z117: DD+3 | AB117: DD+9
A118: 3MRC-4 LEG | D118: Benching | F118: 1MRC-4 leg | H118: Benching | L118: 3MRC | N118: 3MRC
A119: WORK FRONT YET TO BE CLEARED | Q119: REVISED CHECK SURVEY TO BE SUBMITTED
B120: 47/1 | D120: 47/2 | F120: AP48 | H120: AP49 | J120: AP50 | L120: AP51 | N120: 51/1 | P120: 51/2 | R120: 51/3 | T120: AP52 | V120: 52/1 | X120: AP53 | Y120: SH | Z120: AP54 | AB120: 54/1
C123: 435.136 | D123: U/P | E123: 403.209 | G123: 422.554 | I123: 353.484 | K123: 274.9 | M123: 465.033 | O123: 373.98 | Q123: 416.864 | S123: 381.019 | U123: 391.52 | W123: 374.93 | Y123: 248.57 | AA123: 384.17 | AC123: 330.76 | AM123: =COUNTIF(B123:AB123,"U/P") -> 1 | AN123: =COUNTIF(C123:AC123,"ROW") -> 0 | AO123: =COUNTIF(D123:AD123,"C") -> 0
D124: ROW
B125: DA+9 | D125: DA+9 | F125: DD+3 | H125: DD+3 | J125: DD+9 | L125: DD+18 | N125: DA+3 | P125: DA+0 | R125: DA+3 | T125: DB+0 | V125: DA+6 | X125: DD+0 | Z125: DC+0 | AB125: DA+3
J126: 3MRC | T126: 2MRC ?? | V126: 1MRC-4LEG
A127: REVISED C/S TO BE SUBMITTED | G127: WOK FRONT YET TO BE CLEARED | S127: WORK FRONT YET TO BE CLEARED
B129: 54/2 | D129: 54/3 | F129: AP55 | H129: AP56 | J129: 56/1 | L129: 56/2 | N129: 56/3 | P129: 56/4 | R129: 56/5 | T129: AP57 | V129: AP58 | X129: AP59 | Z129: 59/1 | AB129: AP60
L131: C
B132: C | C132: 285.32 | E132: 354.7 | G132: 420.54 | I132: 340.56 | K132: 336.52 | M132: 375.99 | O132: 308.41 | Q132: 444.84 | S132: 392.02 | U132: 407.803 | W132: 206.062 | Y132: 417.384 | AA132: 304.564 | AC132: 395.51 | AM132: =COUNTIF(B132:AB132,"U/P") -> 0 | AN132: =COUNTIF(C132:AC132,"ROW") -> 0 | AO132: =COUNTIF(B132:AD132,"C") -> 1
B134: DA+6 | D134: DA+3 | F134: DD+18 | H134: DB+9 | J134: DB+9 | L134: DA+0 | N134: DB+9 | P134: DA+6 | R134: DA+6 | T134: DB+9 | V134: DB+9 | X134: DC+9 | Z134: DA+0 | AB134: DD+0
D135: 1MRC-4Leg | F135: 3MRC-4 Leg | H135: 2MRC?? | L135: Pit | R135: B & RC?? | T135: B & RC?? | Z135: Benching
A136: WORK FRONT YET TO BE CLEARED | N136: ROW | U136: WORK FRONT YET TO BE CLEARED
B138: 60/1 | D138: 60/2 | F138: 60/3 | H138: AP61 | J138: 61/1 | L138: AP62 | N138: 62/1 | P138: 62/2 | R138: 62/3 | T138: 62/4 | V138: 62/5 | X138: AP63 | Z138: 63/1 | AB138: AP64
V140: ROW
C141: 431.02 | E141: 403.43 | G141: 420.36 | I141: 446.37 | K141: 297.58 | M141: 280.47 | O141: 272.69 | Q141: 347.88 | S141: 379.25 | U141: 398.7 | W141: 439.06 | X141: ROW | Y141: 360.21 | AA141: 379.58 | AC141: 384 | AM141: =COUNTIF(B141:AB141,"U/P") -> 0 | AN141: =COUNTIF(C141:AC141,"ROW") -> 1 | AO141: =COUNTIF(B141:AD141,"C") -> 0
B143: DA+9 | D143: DA+3 | F143: DA+9 | H143: DC+0 | J143: DA+9 | L143: DB+0 | N143: DA+0 | P143: DA+0 | R143: DA+9 | T143: DA+6 | V143: DA+6 | X143: DC+0 | Z143: DA+0 | AB143: DC+9
F144: RC 3M-4 Leg | N144: B Leg A&D,C Leg 1MRC | R144: 3MRC-4 Leg | AD144: 1MRC-4 Leg, A,D Benching,C Leg 1MRC
A145: WORK FRONT YET TO BE CLEARED | X145: ROW
B147: 64/1 | D147: 64/2 | F147: 64/3 | H147: 64/4 | J147: 64/5 | L147: 64/6 | N147: 64/7 | P147: AP65 | R147: 65/1 | T147: AP66 | V147: 66/1 | X147: 66/2 | Z147: 66/3 | AB147: 66/4
B150: ROW | C150: 442 | D150: ROW | E150: 397 | G150: 395 | I150: 432 | K150: 408 | M150: 426 | O150: 392.95 | Q150: 431.96 | S150: 426.02 | U150: 401 | W150: 437 | Y150: 402 | AA150: 436 | AC150: 392.28 | AM150: =COUNTIF(B150:AB150,"U/P") -> 0 | AN150: =COUNTIF(C150:AC150,"ROW") -> 1 | AO150: =COUNTIF(D150:AD150,"C") -> 0
B152: DA+9 | D152: DA+9 | F152: DA+9 | H152: DA+9 | J152: DA+9 | L152: DA+3 | N152: DA+3 | P152: DD+0 | R152: DB+9 | T152: DD+0 | V152: DA+9 | X152: DA+0 | Z152: DA+3 | AB152: DA+9
B153: 3MRC-4 Leg | D153: 1MRC-4 Leg | T153: 1MRC-4 Leg
B154: ROW | P154: ROW | AB154: ROW
B156: AP67 | D156: 67/1 | F156: 67/2 | H156: AP68 | J156: AP69 | L156: 69/1 | N156: 69/2 | P156: 69/3 | Q156: AP70 | S156: AP71 | U156: SH | V156: 71/1 | X156: 71/2 | Z156: 71/3 | AB156: AP72
...

Sheet VC 
A1: 52
A2: =NOW()-1 -> 46113.496
A3: Name of Contractor:M/S KEC INTERNATIONAL LIMITED
A4: PROGRESS AT A GLANCE :
S5: Stringing WIP | W5: Stringing Completed
A6: Sl. No. | C6: Activity | F6: UoM | H6: Total Qty | K6: Completed Till Date | N6: Balance | AD6: River Crossing
A8: 1 | C8: Detail survey | F8: Kms. | H8: 187.175 | K8: 187.175 | N8: =H8-K8 -> 0 | Q8: Oil pipeline
A9: =A8+1 -> 2 | C9: Check survey | F9: Kms. | H9: 187.175 | K9: 169.168 | N9: =H9-K9 -> 18.007 | Q9: Gas pipeline
A10: =A9+1 -> 3 | C10: Soil Investigation | F10: Loc | H10: 73 | K10: 73 | N10: =H10-K10 -> 0
A11: =A10+1 -> 4 | C11: Foundation | F11: Loc | H11: 495 | K11: 79 | N11: =H11-K11 -> 416 | AA11: Erection WIP
A12: =A11+1 -> 5 | C12: Earthing | F12: Nos. | H12: 497 | K12: 61 | N12: =H12-K12 -> 436 | S12: Erection Comp | V12: Span | AE12: Railway Crossing
A13: =A12+1 -> 6 | C13: Erection | F13: Loc | H13: 495 | N13: =H13-K13 -> 495 | S13: Earthing
A14: =A13+1 -> 7 | C14: Tack Welding | F14: Nos. | H14: 405 | N14: =H14-K14 -> 405
A15: =A14+1 -> 8 | C15: Stringing(Paying out) | F15: Kms. | H15: 187.175 | N15: =H15-K15 -> 187.175 | X15: Excavation
A16: =A15+1 -> 9 | C16: Stringing (Final Sag) | F16: Kms. | H16: 187.175 | N16: =H16-K16 -> 187.175 | Z16: NH/SH | AB16: 66/132/ 220/400KV
B18: 1 | D18: 2 | F18: 3 | H18: 4 | J18: 5 | L18: 6 | N18: 7 | P18: 8 | R18: 9 | T18: 10 | V18: 11 | X18: 12 | Z18: 13 | AB18: 14
B20: GNT | D20: AP1 | F20: AP1A | H20: AP2 | J20: AP3 | L20: 3/1 | N20: 3/2 | P20: 3/3 | R20: AP4 | T20: 4/1 | V20: 4/2 | X20: 4/3 | Z20: 4/4 | AB20: 4/5 | AF20: T | AG20: F | AH20: EA | AI20: ER | AJ20: Length | AK20: TW
C23: 96.534 | E23: 114.097 | G23: 290.581 | I23: 214.485 | K23: 451.783 | M23: 419.226 | O23: 420.01 | Q23: 416.531 | S23: 356.262 | U23: 343.074 | W23: 381.329 | Y23: 373.323 | AA23: 246.012 | AC23: 249.424 | AF23: 13
D25: DD+0 | F25: DD+3 | H25: DD+25 | J25: DD+25 | L25: DB+6 | N25: DA+0 | P25: DA+9 | R25: DC+0 | T25: DA+0 | V25: DA+0 | X25: DA+6 | Z25: DA+3 | AB25: DB+0
B28: 4/6 | D28: 4/7 | F28: 4/8 | H28: 4/9 | J28: AP5 | L28: AP6 | N28: 6/1 | P28: 6/2 | R28: 6/3 | T28: 6/4 | V28: 6/5 | X28: 6/6 | Z28: 6/7 | AB28: AP7
AF29: T | AG29: F | AH29: EA | AI29: ER | AJ29: Length | AK29: TW
C31: 399.707 | E31: 438.616 | G31: 400.604 | I31: 438.765 | K31: 226.315 | M31: 442.553 | O31: 389.329 | Q31: 359.361 | S31: 405.006 | U31: 426.518 | W31: 356.055 | Y31: 369.295 | AA31: 374.993 | AC31: 383.768 | AF31: 14
B33: DA+0 | D33: DA+6 | F33: DA+6 | H33: DA+3 | J33: DD+18 | L33: DD+18 | N33: DA+3 | P33: DA+0 | R33: DA+0 | T33: DA+0 | V33: DA+0 | X33: DA+0 | Z33: DA+0 | AB33: DB+0
B36: 7/1 | D36: 7/1 | F36: 7/2 | H36: 7/3 | J36: 7/4 | L36: 7/5 | N36: 7/6 | P36: 7/7 | R36: 7/8 | T36: 7/9 | V36: 7/10 | X36: AP8 | Z36: 8/1 | AB36: 8/2
AF37: T | AG37: F | AH37: EA | AI37: ER | AJ37: Length | AK37: TW
C39: 383.768 | E39: 396.38 | G39: 392.534 | I39: 332.162 | K39: 352.112 | M39: 389.393 | O39: 374.477 | Q39: 419.977 | S39: 387.899 | U39: 407.654 | W39: 402.357 | Y39: 372.259 | AA39: 410.949 | AC39: 379.075 | AF39: 14
B41: DA+0 | D41: DA+0 | F41: DA+0 | H41: DA+0 | J41: DA+0 | L41: DA+0 | N41: DA+0 | P41: DA+0 | R41: DA+3 | T41: DA+0 | V41: DA+0 | X41: DB+0 | Z41: DA+0 | AB41: DA+0
B44: 8/3 | D44: 8/4 | F44: AP9 | H44: 9/1 | J44: 9/2 | L44: 9/3 | N44: 9/4 | P44: 9/5 | R44: AP10 | T44: 10/1 | V44: 10/2 | X44: 10/3 | Z44: 10/4 | AB44: 10/5
AF45: T | AG45: F | AH45: EA | AI45: ER | AJ45: Length | AK45: TW
C47: 412.596 | E47: 340.112 | G47: 410.76 | I47: 427.9 | K47: 404.21 | M47: 398.446 | O47: 431.939 | Q47: 486.196 | S47: 369.717 | U47: 389.344 | W47: 395.602 | Y47: 372.377 | AA47: 431.547 | AC47: 370.651 | AF47: 14
B49: DA+0 | D49: DA+3 | F49: DB+0 | H49: DA+0 | J49: DA+6 | L49: DA+0 | N49: DA+3 | P49: DB+9 | R49: DC+3 | T49: DA+3 | V49: DA+0 | X49: DA+3 | Z49: DA+6 | AB49: DA+0
B52: 10/6 | D52: 10/7 | F52: 10/8 | H52: 10/9 | J52: 10/10 | L52: 10/11 | N52: 10/12 | P52: 10/13 | R52: 10/14 | T52: 10/15 | V52: AP11 | X52: 11/1 | Z52: 11/2 | AB52: 11/3
AF53: T | AG53: F | AH53: EA | AI53: ER | AJ53: Length | AK53: TW
C55: 345.352 | E55: 381.912 | G55: 366.819 | I55: 424.002 | K55: 400.126 | M55: 403.795 | O55: 437.705 | Q55: 399.87 | S55: 437.786 | U55: 378.362 | W55: 433.995 | Y55: 370.685 | AA55: 323.972 | AC55: 384.462 | AF55: 14
B57: DA+0 | D57: DA+0 | F57: DA+0 | H57: DB+0 | J57: DA+0 | L57: DA+3 | N57: DA+3 | P57: DA+3 | R57: DA+0 | T57: DA+6 | V57: DB+0 | X57: DA+3 | Z57: DA+0 | AB57: DA+0
B60: 11/4 | D60: 11/5 | F60: 11/6 | H60: AP12 | J60: 12/1 | L60: 12/2 | N60: AP13 | P60: 13/1 | R60: 13/2 | T60: 13/3 | V60: AP14 | X60: 14/1 | Z60: AP15 | AB60: 15/1
AF61: T | AG61: F | AH61: EA | AI61: ER | AJ61: Length | AK61: TW
C63: 381.188 | E63: 336.409 | G63: 438.97 | I63: 395.179 | K63: 388.12 | M63: 364.446 | O63: 404.572 | Q63: 432.27 | S63: 404.23 | U63: 416.621 | W63: 468.039 | Y63: 432.318 | AA63: 464.521 | AC63: 369.743 | AF63: 14
B65: DA+0 | D65: DA+0 | F65: DA+0 | H65: DB+0 | J65: DA+0 | L65: DA+3 | N65: DC+0 | P65: DA+9 | R65: DA+6 | T65: DA+3 | V65: DB+0 | X65: DB+9 | Z65: DC+9 | AB65: DA+6
B68: AP16 | D68: 16/1 | F68: AP17 | H68: 17/1 | J68: AP18 | L68: 18/1 | N68: AP19 | P68: 19/1 | R68: 19/2 | T68: 19/3 | V68: AP20 | X68: 20/1 | Z68: 20/2 | AB68: 20/3
AF69: T | AG69: F | AH69: EA | AI69: ER | AJ69: Length | AK69: TW
C71: 284.16 | E71: 270.742 | G71: 286.64 | I71: 291.699 | K71: 398.719 | M71: 425.465 | O71: 383.813 | Q71: 403.279 | S71: 355.215 | U71: 399.839 | W71: 287.442 | Y71: 390.748 | AA71: 364.274 | AC71: 337.546 | AF71: 14
B73: DD+0 | D73: DA+0 | F73: DB+0 | H73: DA+0 | J73: DC+0 | L73: DA+6 | N73: DD+0 | P73: DA+3 | R73: DA+0 | T73: DA+3 | V73: DC+0 | X73: DA+0 | Z73: DA+0 | AB73: DA+0
B76: 20/4 | D76: 20/5 | F76: 20/6 | H76: AP21 | J76: 21/1 | L76: 21/2 | N76: AP22 | P76: AP23 | R76: 23/1 | T76: 23/2 | V76: 23/3 | X76: AP24 | Z76: 24/1 | AB76: AP25
AF77: T | AG77: F | AH77: EA | AI77: ER | AJ77: Length | AK77: TW
C79: 348.292 | E79: 418.835 | G79: 408.963 | I79: 365.467 | K79: 437.074 | M79: 363.142 | O79: 159.789 | Q79: 300.158 | S79: 293.131 | U79: 357.377 | W79: 341.409 | Y79: 362.905 | AA79: 421.052 | AC79: 216.448 | AF79: 14
B81: DA+0 | D81: DA+3 | F81: DA+9 | H81: DD+3 | J81: DA+0 | L81: DA+6 | N81: DB+3 | P81: DD+0 | R81: DB+3 | T81: DA+0 | V81: DA+0 | X81: DC+9 | Z81: DA+9 | AB81: DD+30
B84: AP26 | D84: AP27 | F84: AP27A | H84: 27A/1 | J84: 27A/2 | L84: 27A/3 | N84: AP27B | P84: 27B/1 | R84: 27B/2 | T84: 27B/3 | V84: AP28 | X84: 28/1 | Z84: 28/2 | AB84: AP29
AF85: T | AG85: F | AH85: EA | AI85: ER | AJ85: Length | AK85: TW
C87: 439.695 | E87: 243.188 | G87: 333.219 | I87: 363.001 | K87: 356.124 | M87: 511.692 | O87: 376.245 | Q87: 381.122 | S87: 364.433 | U87: 263.077 | W87: 356.193 | Y87: 352.42 | AA87: 460.564 | AC87: 381.028 | AF87: 14
B89: DD+30 | D89: DC+0 | F89: DD+0 | H89: DA+3 | J89: DA+3 | L89: DB+0 | N89: DB+0 | P89: DA+0 | R89: DA+3 | T89: DA+9 | V89: DD+6 | X89: DA+0 | Z89: DB+9 | AB89: DC+6
B92: 29/1 | D92: 29/2 | F92: AP30 | H92: 30/1 | J92: 30/2 | L92: 30/3 | N92: AP31 | P92: AP32 | R92: 32/1 | T92: 32/2 | V92: 32/3 | X92: AP33 | Z92: AP34 | AB92: 34/1
AF93: T | AG93: F | AH93: EA | AI93: ER | AJ93: Length | AK93: TW
C95: 419.603 | E95: 425.18 | G95: 287.537 | I95: 336.512 | K95: 325.304 | M95: 214.253 | O95: 455.946 | Q95: 421 | S95: 419 | U95: 408 | W95: 409.749 | Y95: 324.03 | AA95: 366.7 | AC95: 473.305 | AF95: 14
B97: DA+3 | D97: DA+9 | F97: DC+0 | H97: DA+0 | J97: DA+0 | L97: DA+0 | N97: DC+9 | P97: DC+9 | R97: DA+3 | T97: DA+3 | V97: DA+9 | X97: DB+0 | Z97: DC+6 | AB97: DA+9
B100: AP35 | D100: 35/1 | F100: AP36 | H100: 36/1 | J100: 36/2 | L100: 36A | N100: AP37 | P100: 37/1 | R100: AP38 | T100: 38/1 | V100: 38/2 | X100: 38/3 | Z100: AP39 | AB100: 39/1 | AD100: 39/2
AF101: T | AG101: F | AH101: EA | AI101: ER | AJ101: Length | AK101: TW
C103: 358.321 | E103: 477.815 | G103: 415.464 | I103: 402.229 | K103: 437.434 | O103: 455.922 | Q103: 368.5 | S103: 419.765 | U103: 418.917 | W103: 386.486 | Y103: 376.53 | AA103: 404.739 | AC103: 366.729 | AE103: 274.587 | AF103: 14
B105: DC+9 | D105: DA+9 | F105: DC+9 | H105: DA+9 | J105: DA+9 | L105: DD+0 | N105: DD+0 | P105: DA+6 | R105: DB+0 | T105: DA+6 | V105: DA+9 | X105: DA+3 | Z105: DB+3 | AB105: DA+6 | AD105: DA+0
B108: 39/3 | D108: 39/4 | F108: 39/5 | H108: AP40 | J108: 40/1 | L108: 40/2 | N108: AP41 | P108: 41/1 | R108: 41/2 | T108: 41/3 | V108: AP42 | X108: 42/1 | Z108: 42/2 | AB108: 42/3
AF109: T | AG109: F | AH109: EA | AI109: ER | AJ109: Length | AK109: TW
C111: 341.668 | E111: 425.863 | G111: 394.307 | I111: 370.45 | K111: 436.754 | M111: 397.605 | O111: 413.401 | Q111: 423.645 | S111: 415.968 | U111: 415.349 | W111: 394.875 | Y111: 429.62 | AA111: 381.905 | AC111: 405.26 | AF111: 14
B113: DA+0 | D113: DA+0 | F113: DA+6 | H113: DD+3 | J113: DB+6 | L113: DA+6 | N113: DB+0 | P113: DA+9 | R113: DA+0 | T113: DA+9 | V113: DC+3 | X113: DA+9 | Z113: DCT+6 | AB113: DA+9
B116: 42/4 | D116: 42/5 | F116: 42/6 | H116: 42/7 | J116: AP43 | L116: AP44 | N116: 44/1 | P116: AP45 | R116: 45/1 | T116: 45/2 | V116: 45/3 | X116: 45/4 | Z116: AP46 | AB116: AP47
AF117: T | AG117: F | AH117: EA | AI117: ER | AJ117: Length | AK117: TW
AH118: s
C119: 338.156 | E119: 288.303 | G119: 297.148 | I119: 195.903 | K119: 249.66 | M119: 374.475 | O119: 443.95 | Q119: 404.386 | S119: 341.423 | U119: 305.401 | W119: 319.981 | Y119: 345.621 | AA119: 223.151 | AC119: 393.817 | AF119: 14
B121: DA+9 | D121: DA+0 | F121: DA+3 | H121: DA+0 | J121: DC+6 | L121: DB+9 | N121: DA+9 | P121: DD+9 | R121: DA+0 | T121: DA+3 | V121: DA+0 | X121: DA+6 | Z121: DD+3 | AB121: DD+9
B124: 47/1 | D124: 47/2 | F124: AP48 | H124: AP49 | J124: AP50 | L124: AP51 | N124: 51/1 | P124: 51/2 | R124: 51/3 | T124: AP52 | V124: 52/1 | X124: AP53 | Z124: AP54 | AB124: 54/1
AF125: T | AG125: F | AH125: EA | AI125: ER | AJ125: Length | AK125: TW
C127: 435.136 | E127: 403.209 | G127: 422.554 | I127: 353.484 | K127: 274.899 | M127: 465.033 | O127: 373.977 | Q127: 416.864 | S127: 381.019 | U127: 391.519 | W127: 374.934 | Y127: 248.567 | AA127: 384.17 | AC127: 330.764 | AF127: 14 | AG127: 1
B129: DA+9 | D129: DA+9 | F129: DD+3 | H129: DD+3 | J129: DD+9 | L129: DD+18 | N129: DA+3 | P129: DA+0 | R129: DA+3 | T129: DB+0 | V129: DA+6 | X129: DD+0 | Z129: DC+0 | AB129: DA+3
T130: RC 3M | V130: RC 1M
B132: 54/2 | D132: 54/3 | F132: AP55 | H132: AP56 | J132: 56/1 | L132: 56/2 | N132: 56/3 | P132: 56/4 | R132: 56/5 | T132: AP57 | V132: AP58 | X132: AP59 | Z132: 59/1 | AB132: AP60
AF133: T | AG133: F | AH133: EA | AI133: ER | AJ133: Length | AK133: TW
C135: 285.319 | E135: 354.7 | G135: 420.541 | I135: 340.559 | K135: 336.519 | M135: 375.992 | O135: 308.407 | Q135: 444.838 | S135: 392.016 | U135: 407.803 | W135: 206.062 | Y135: 417.384 | AA135: 304.564 | AC135: 395.509 | AF135: 14
B137: DA+6 | D137: DA+3 | F137: DD+18 | H137: DB+9 | J137: DB+9 | L137: DA+0 | N137: DB+9 | P137: DA+6 | R137: DA+6 | T137: DB+9 | V137: DB+9 | X137: DC+9 | Z137: DA+0 | AB137: DD+0
B138: RC 1M | D138: RC 1M | F138: RC 3M | H138: RC 3M | T138: RC 1M & 3M
B140: 60/1 | D140: 60/2 | F140: 60/3 | H140: AP61 | J140: 61/1 | L140: AP62 | N140: 62/1 | P140: 62/2 | R140: 62/3 | T140: 62/4 | V140: 62/5 | X140: AP63 | Z140: 63/1 | AB140: AP64
AF141: T | AG141: F | AH141: EA | AI141: ER | AJ141: Length | AK141: TW
C143: 431.017 | E143: 403.426 | G143: 420.357 | I143: 446.37 | K143: 297.577 | M143: 240.473 | O143: 312.687 | Q143: 347.884 | S143: 379.249 | U143: 398.697 | W143: 439.062 | Y143: 360.21 | AA143: 399.579 | AC143: 364 | AF143: 14
B145: DA+9 | D145: DA+3 | F145: DA+9 | H145: DC+0 | J145: DA+9 | L145: DB+0 | N145: DA+0 | P145: DA+0 | R145: DA+9 | T145: DA+6 | V145: DA+6 | X145: DC+0 | Z145: DA+0 | AB145: DC+9
F146: RC 3M | N146: RC 1M | R146: RC 3M | AB146: RC 1M
B148: 64/1 | D148: 64/2 | F148: 64/3 | H148: 64/4 | J148: 64/5 | L148: 64/6 | N148: 64/7 | P148: AP65 | R148: 65/1 | T148: AP66 | V148: 66/1 | X148: 66/2 | Z148: 66/3 | AB148: 66/4
AF149: T | AG149: F | AH149: EA | AI149: ER | AJ149: Length | AK149: TW
C151: 442 | E151: 397 | G151: 395 | I151: 432 | K151: 408 | M151: 426 | O151: 392.954 | Q151: 431.957 | S151: 426.02 | U151: 401 | W151: 437 | Y151: 402 | AA151: 436 | AC151: 392.283 | AF151: 14 | AG151: 8 | AH151: 2
B153: DA+9 | D153: DA+9 | F153: DA+9 | H153: DA+9 | J153: DA+9 | L153: DA+3 | N153: DA+3 | P153: DD+0 | R153: DB+9 | T153: DD+0 | V153: DA+9 | X153: DA+0 | Z153: DA+3 | AB153: DA+9
B154: RC 3M | D154: RC 1M | T154: RC 1M
B156: AP67 | D156: 67/1 | F156: 67/2 | H156: AP68 | J156: AP69 | L156: 69/1 | N156: 69/2 | P156: 69/3 | R156: AP70 | T156: AP71 | V156: 71/1 | X156: 71/2 | Z156: 71/3 | AB156: AP72
AF157: T | AG157: F | AH157: EA | AI157: ER | AJ157: Length | AK157: TW
C159: 402.5 | E159: 411.557 | G159: 438.461 | I159: 410.356 | K159: 379.755 | M159: 396.947 | O159: 414.594 | Q159: 352.994 | S159: 389.303 | U159: 237.59 | W159: 290.877 | Y159: 345.605 | AA159: 318.63 | AC159: 307.017 | AF159: 14
B161: DC+6 | D161: DA+6 | F161: DB+0 | H161: DB+9 | J161: DD+3 | L161: DA+6 | N161: DA+0 | P161: DA+0 | R161: DD+0 | T161: DB+0 | V161: DA+9 | X161: DA+0 | Z161: DA+0 | AB161: DD+0
B162: RC 1M | P162: RC 1M | Z162: RC 1M | AB162: RC 1M & 3M
B164: 72/1 | D164: 72/2 | F164: AP73 | H164: 73/1 | J164: 73/2 | L164: 73/3 | N164: AP74 | P164: 74/1 | R164: AP75 | T164: 75/1 | V164: 75/2 | X164: 75/3 | Z164: 75/4 | AB164: 75/5
AF165: T | AG165: F | AH165: EA | AI165: ER | AJ165: Length | AK165: TW
C167: 346.846 | D167: u/p | E167: 300.193 | F167: u/p | G167: 317 | I167: 454 | K167: 385 | M167: 417.688 | O167: 409.505 | Q167: 385.169 | S167: 345.191 | U167: 332.383 | W167: 393.622 | Y167: 387.948 | AA167: 340.348 | AC167: 393.121 | AF167: 14 | AG167: 8 | AH167: 7
B169: DA+3 | D169: DA+3 | F169: DB+0 | H169: DA+0 | J169: DA+9 | L169: DA+9 | N169: DB+9 | P169: DA+0 | R169: DC+0 | T169: DA+0 | V169: DA+0 | X169: DA+3 | Z169: DA+0 | AB169: DA+0
B170: RC 1M & 3M | H170: RC 3M
B172: 75/6 | D172: 75/7 | F172: AP76 | H172: 76/1 | J172: AP77 | L172: 77/1 | N172: 77/2 | P172: 77/3 | R172: 77/4 | T172: 77/5 | V172: AP78 | X172: 78/1 | Z172: AP79 | AB172: 79/1
AF173: T | AG173: F | AH173: EA | AI173: ER | AJ173: Length | AK173: TW
...

Sheet Sheet6
B3: SL No | C3: Loc No | D3: TOT | E3: Classificatin | F3: M-10 | G3: M-20
B4: 1 | C4: 83/1 | D4: DA+3 | E4: Sandy | F4: 1.86 | G4: 12.47
B5: =B4+1 -> 2 | C5: 75/7 | D5: DA+0 | E5: Sandy | F5: 1.57 | G5: 11.05
B6: =B5+1 -> 3 | C6: 75/6 | D6: DA+0 | E6: Sandy | F6: 1.57 | G6: 11.05
B7: =B6+1 -> 4 | C7: 75/5 | D7: DA+0 | E7: Sandy | F7: 1.57 | G7: 11.05
B8: =B7+1 -> 5 | C8: 75/4 | D8: DA+0 | E8: Sandy | F8: 1.57 | G8: 11.05
B9: =B8+1 -> 6 | C9: 75/3 | D9: DA+3 | E9: Sandy | F9: 1.86 | G9: 12.47
B10: =B9+1 -> 7 | C10: 75/1 | D10: DA+0 | E10: Sandy | F10: 1.57 | G10: 11.05
B11: =B10+1 -> 8 | C11: 75/2 | D11: DA+0 | E11: Sandy | F11: 1.57 | G11: 11.05
B12: =B11+1 -> 9 | C12: 77/1 | D12: DA+0 | E12: Sandy | F12: 1.57 | G12: 11.05
B13: =B12+1 -> 10 | C13: 77/2 | D13: DA+3 | E13: Sandy | F13: 1.86 | G13: 12.47
B14: =B13+1 -> 11 | C14: 77/3 | D14: DA+0 | E14: Sandy | F14: 1.57 | G14: 11.05
B15: =B14+1 -> 12 | C15: 77/4 | D15: DA+3 | E15: Sandy | F15: 1.86 | G15: 12.47
B16: =B15+1 -> 13 | C16: 77/5 | D16: DA+6 | E16: Sandy | F16: 1.86 | G16: 12.47
... B37: =B36+1 -> 34 | C37: 64/7 | D37: DA+3 | E37: Sandy | F37: 1.86 | G37: 12.47
B38: =B37+1 -> 35 | C38: 98A/1 | D38: DA+0 | E38: DFR | F38: 1.08 | G38: 8.68 | I38: ]]
B39: =B38+1 -> 36 | C39: 87/2 | D39: DA+9 | E39: Sandy | F39: 1.86 | G39: 12.47
B40: =B39+1 -> 37 | C40: 64/6 | D40: DA+3 | E40: Sandy | F40: 1.86 | G40: 12.47
B41: =B40+1 -> 38 | C41: 64/5 | D41: DA+9 | E41: Sandy | F41: 1.86 | G41: 12.47
F42: =SUM(F4:F41) -> 65.06 | G42: =SUM(G4:G41) -> 446.4 | H42: =SUM(F42:G42) -> 511.46

Sheet VC 51-121
A1: TB-507 400 KV (Twin) D/C Fatehgarh IV - Bhinmal Transmission Line
A2: DPR and VISUAL CHART
A4: DPR- | D4: As per Approved Check Survey | F4: No.Of Towers | G4: Length | H4: Foundation | K4: Earthing | L4: Tower Erection | O4: Stringing
H5: Com | I5: WIP | J5: Bal | K5: Com | L5: Com | M5: WIP | N5: Bal | O5: Com | P5: WIP | Q5: Bal
D6: AP 51- AP 121 | F6: 196 | G6: 74.398 | H6: 39 | I6: 4 | J6: =F6-H6-I6 -> 153 | K6: 25 | N6: =F6-L6 -> 196 | Q6: =G6-O6 -> 74.398
C8: =A8+1 -> 1 | E8: =C8+1 -> 2 | G8: =E8+1 -> 3 | I8: =G8+1 -> 4 | K8: =I8+1 -> 5 | M8: =K8+1 -> 6 | O8: =M8+1 -> 7 | Q8: =O8+1 -> 8 | S8: =Q8+1 -> 9
Y9: DA | AE9: DB | AJ9: DC | AO9: DD
D10: 465.03 | F10: 375.98 | H10: 414.86 | J10: 381.02 | L10: 353.63 | N10: 351.4 | P10: 433.26 | R10: 396.56 | T10: 408.11 | U10: =B10+F10+H10+J10+L10+D10+N10+P10+R10+T10 -> 3579.85 | X10: +0 | Y10: +3 | Z10: +6 | AA10: +9 | AD10: +0 | AE10: +3 | AF10: +6 | AG10: +9 | AI10: +0 | AJ10: +3 | AK10: +6 | AL10: +9 | AN10: +0 | AO10: +3 | AP10: +6 | AQ10: +9
G12: U/P | X12: =COUNTIF($C$14:$V$14, "DA+0") -> 1 | Y12: =COUNTIF($C$14:$V$14, "DA+3") -> 3 | Z12: =COUNTIF($C$14:$V$14, "DA+6") -> 1 | AA12: =COUNTIF($C$14:$V$14, "DA+9") -> 0 | AD12: =COUNTIF($C$14:$V$14, "DB+0") -> 1 | AE12: =COUNTIF($C$14:$V$14, "DB+3") -> 0 | AF12: =COUNTIF($C$14:$V$14, "DB+6") -> 0 | AG12: =COUNTIF($C$14:$V$14, "DB+9") -> 0 | AI12: =COUNTIF($C$14:$V$14, "DC+0") -> 0 | AJ12: =COUNTIF($C$14:$V$14, "DC+3") -> 0 | AK12: =COUNTIF($C$14:$V$14, "DC+6") -> 0 | AL12: =COUNTIF($C$14:$V$14, "DC+9") -> 0 | AN12: =COUNTIF($C$14:$V$14, "DD+0") -> 1 | AO12: =COUNTIF($C$14:$V$14, "DD+3") -> 0 | AP12: =COUNTIF($C$14:$V$14, "DD+6") -> 0 | AQ12: =COUNTIF($C$14:$V$14, "DD+9") -> 0
C13: AP51 | E13: 51/1 | G13: 51/2 | I13: 51/3 | K13: AP52 | M13: 52/1 | O13: AP53 | Q13: AP54 | S13: 54/1
C14: DD+18 | E14: DA+3 | G14: DA+0 | I14: DA+3 | K14: DB+0 | M14: DA+6 | O14: DD+0 | Q14: DC+00 | S14: DA+3
K15: RC | M15: RC
B17: =S8+1 -> 10 | D17: =B17+1 -> 11 | F17: =D17+1 -> 12 | H17: =F17+1 -> 13 | J17: =H17+1 -> 14 | L17: =J17+1 -> 15 | N17: =L17+1 -> 16 | P17: =N17+1 -> 17 | R17: =P17+1 -> 18 | T17: =R17+1 -> 19
C19: 425.22 | E19: 420.54 | G19: 340.56 | I19: 336.52 | K19: 375.99 | M19: 303.41 | O19: 448.76 | Q19: 393.09 | S19: 407.8 | U19: 206.06 | V19: =C19+G19+I19+K19+M19+E19+O19+Q19+S19+U19 -> 3657.95
B22: 54/2 | D22: 54/3 | F22: AP55 | H22: AP56 | J22: 56/1 | L22: 56/2 | N22: 56/3 | P22: 56/4 | R22: 56/5 | T22: AP57 | X22: =COUNTIF($B$23:$V$23, "DA+0") -> 1 | Y22: =COUNTIF($B$23:$V$23, "DA+3") -> 1 | Z22: =COUNTIF($B$23:$V$23, "DA+6") -> 3 | AA22: =COUNTIF($B$23:$V$23, "DA+9") -> 0 | AD22: =COUNTIF($B$23:$V$23, "DB+0") -> 0 | AE22: =COUNTIF($B$23:$V$23, "DB+3") -> 0 | AF22: =COUNTIF($B$23:$V$23, "DB+6") -> 0 | AG22: =COUNTIF($B$23:$V$23, "DB+9") -> 2 | AI22: =COUNTIF($B$23:$V$23, "DC+0") -> 0 | AJ22: =COUNTIF($B$23:$V$23, "DC+3") -> 0 | AK22: =COUNTIF($B$23:$V$23, "DC+6") -> 0 | AL22: =COUNTIF($B$23:$V$23, "DC+9") -> 0 | AN22: =COUNTIF($B$23:$V$23, "DD+0") -> 0 | AO22: =COUNTIF($B$23:$V$23, "DD+3") -> 0 | AP22: =COUNTIF($B$23:$V$23, "DD+6") -> 0 | AQ22: =COUNTIF($B$23:$V$23, "DD+9") -> 0
B23: DA+6 | D23: DA+3 | F23: DD+18 | H23: DB+09 | J23: DB+9 | L23: DA+0 | N23: DB+9 | P23: DA+6 | R23: DA+6 | T23: DB+09
B24: Benching &RC | D24: RC | F24: RC | H24: Benching &RC | T24: Benching &RC
B26: =T17+1 -> 20 | D26: =B26+1 -> 21 | F26: =D26+1 -> 22 | H26: =F26+1 -> 23 | J26: =H26+1 -> 24 | L26: =J26+1 -> 25 | N26: =L26+1 -> 26 | P26: =N26+1 -> 27 | R26: =P26+1 -> 28 | T26: =R26+1 -> 29
C28: 417.38 | E28: 304.56 | G28: 408.66 | I28: 434.89 | K28: 408.17 | M28: 398.59 | O28: 446.37 | Q28: 297.58 | S28: 240.47 | U28: 312.69 | V28: =C28+G28+I28+K28+M28+E28+O28+Q28+S28+U28 -> 3669.36
B31: AP58 | D31: AP59 | F31: 59/1 | H31: AP60 | J31: 60/1 | L31: 60/2 | N31: 60/3 | P31: AP61 | R31: 61/1 | T31: AP62
B32: DB+09 | D32: DC+09 | F32: DA+0 | H32: DD+00 | J32: DA+9 | L32: DA+0 | N32: DA+9 | P32: DC+00 | R32: DA+9 | T32: DB+00 | X32: =COUNTIF($B$32:$V$32, "DA+0") -> 2 | Y32: =COUNTIF($B$32:$V$32, "DA+3") -> 0 | Z32: =COUNTIF($B$32:$V$32, "DA+6") -> 0 | AA32: =COUNTIF($B$32:$V$32, "DA+9") -> 3 | AD32: =COUNTIF($B$32:$V$32, "DB+0") -> 0 | AE32: =COUNTIF($B$32:$V$32, "DB+3") -> 0 | AF32: =COUNTIF($B$32:$V$32, "DB+6") -> 0 | AG32: =COUNTIF($B$32:$V$32, "DB+9") -> 0 | AI32: =COUNTIF($B$32:$V$32, "DC+0") -> 0 | AJ32: =COUNTIF($B$32:$V$32, "DC+3") -> 0 | AK32: =COUNTIF($B$32:$V$32, "DC+6") -> 0 | AL32: =COUNTIF($B$32:$V$32, "DC+9") -> 0 | AN32: =COUNTIF($B$32:$V$32, "DD+0") -> 0 | AO32: =COUNTIF($B$32:$V$32, "DD+3") -> 0 | AP32: =COUNTIF($B$32:$V$32, "DD+6") -> 0 | AQ32: =COUNTIF($B$32:$V$32, "DD+9") -> 0
F33: Benching | N33: RC
B35: =T26+1 -> 30 | D35: =B35+1 -> 31 | F35: =D35+1 -> 32 | H35: =F35+1 -> 33 | J35: =H35+1 -> 34 | L35: =J35+1 -> 35 | N35: =L35+1 -> 36 | P35: =N35+1 -> 37 | R35: =P35+1 -> 38 | T35: =R35+1 -> 39
C37: 347.88 | E37: 379.25 | G37: 398.7 | I37: 439.06 | K37: 381.53 | M37: 379.71 | O37: 426.3 | Q37: 387.14 | U37: 423.77 | V37: =C37+G37+I37+K37+M37+E37+#REF!+O37+Q37+#REF! -> #REF!
B40: 62/1 | D40: 62/2 | F40: 62/3 | H40: 62/4 | J40: 62/5 | L40: AP63 | N40: 63/1 | P40: AP64 | R40: 64/1 | T40: 64/2
B41: DA+0 | D41: DA+0 | F41: DA+9 | H41: DA+6 | J41: DA+6 | L41: DC+00 | N41: DA+0 | P41: DC+09 | R41: DA+9 | T41: DA+9 | X41: =COUNTIF($B$41:$V$41, "DA+0") -> 3 | Y41: =COUNTIF($B$41:$V$41, "DA+3") -> 0 | Z41: =COUNTIF($B$41:$V$41, "DA+6") -> 2 | AA41: =COUNTIF($B$41:$V$41, "DA+9") -> 3 | AD41: =COUNTIF($B$41:$V$41, "DB+0") -> 0 | AE41: =COUNTIF($B$41:$V$41, "DB+3") -> 0 | AF41: =COUNTIF($B$41:$V$41, "DB+6") -> 0 | AG41: =COUNTIF($B$41:$V$41, "DB+9") -> 0 | AI41: =COUNTIF($B$41:$V$41, "DC+0") -> 0 | AJ41: =COUNTIF($B$41:$V$41, "DC+3") -> 0 | AK41: =COUNTIF($B$41:$V$41, "DC+6") -> 0 | AL41: =COUNTIF($B$41:$V$41, "DC+9") -> 0 | AN41: =COUNTIF($B$41:$V$41, "DD+0") -> 0 | AO41: =COUNTIF($B$41:$V$41, "DD+3") -> 0 | AP41: =COUNTIF($B$41:$V$41, "DD+6") -> 0 | AQ41: =COUNTIF($B$41:$V$41, "DD+9") -> 0
B42: RC | F42: RC | P42: Benching &RC | R42: RC | T42: RC
B43: =T35+1 -> 40 | D43: =B43+1 -> 41 | F43: =D43+1 -> 42 | H43: =F43+1 -> 43 | J43: =H43+1 -> 44 | L43: =J43+1 -> 45 | N43: =L43+1 -> 46 | P43: =N43+1 -> 47 | R43: =P43+1 -> 48 | T43: =R43+1 -> 49
C45: 407.9 | E45: 426.63 | G45: 392.27 | I45: 431.96 | K45: 426.02 | M45: 405.36 | O45: 411.93 | Q45: 423.77 | S45: 407.9 | U45: 426.63
B46: F | D46: F | F46: F | H46: F | J46: F | R46: F | T46: F
B47: Er | F47: Er
B48: 64/3 | D48: 64/4 | F48: 64/5 | H48: 64/6 | J48: 64/7 | L48: 65/0 | N48: 65/1 | P48: 66/0 | R48: 66/1 | T48: 66/2
B49: DA+9 | D49: DA+9 | F49: DA+9 | H49: DA+3 | J49: DA+3 | L49: DD+0 | N49: DB+09 | P49: DD+0 | R49: DA+9 | T49: DA+0 | V49: =#REF!+I77+K77+M77+O77+G77+Q77+S77+#REF!+#REF! -> #REF! | X49: =COUNTIF($B$49:$V$49, "DA+0") -> 1 | Y49: =COUNTIF($C$14:$V$14, "DA+3") -> 3 | Z49: =COUNTIF($C$14:$V$14, "DA+6") -> 1 | AA49: =COUNTIF($C$14:$V$14, "DA+9") -> 0 | AD49: =COUNTIF($B$49:$V$49, "DB+0") -> 0 | AE49: =COUNTIF($C$14:$V$14, "DB+3") -> 0 | AF49: =COUNTIF($C$14:$V$14, "DB+6") -> 0 | AG49: =COUNTIF($C$14:$V$14, "DB+9") -> 0 | AI49: =COUNTIF($B$49:$V$49, "DC+0") -> 0 | AJ49: =COUNTIF($C$14:$V$14, "DC+3") -> 0 | AK49: =COUNTIF($C$14:$V$14, "DC+6") -> 0 | AL49: =COUNTIF($C$14:$V$14, "DC+9") -> 0 | AN49: =COUNTIF($B$49:$V$49, "DD+0") -> 2 | AO49: =COUNTIF($C$14:$V$14, "DD+3") -> 0 | AP49: =COUNTIF($C$14:$V$14, "DD+6") -> 0 | AQ49: =COUNTIF($C$14:$V$14, "DD+9") -> 0
P50: RC
B51: =T43+1 -> 50 | D51: =B51+1 -> 51 | F51: =D51+1 -> 52 | H51: =F51+1 -> 53 | J51: =H51+1 -> 54 | L51: =J51+1 -> 55 | N51: =L51+1 -> 56 | P51: =N51+1 -> 57 | R51: =P51+1 -> 58 | T51: =R51+1 -> 59 | V51: =T51+1 -> 60
C53: 392.27 | E53: 431.96 | G53: 426.02 | I53: 405.36 | K53: 411.93 | M53: 350.33 | O53: 378.3 | Q53: 416.82 | S53: 371.85
B54: F | D54: ROW
B56: 66/3 | D56: 66/4 | F56: 67/0 | H56: 67/1 | J56: 67/2 | L56: AP68 | N56: AP69 | P56: 69/1 | R56: 69/2 | T56: 69/3 | V56: 70/0
B57: DA+3 | D57: DA+9 | F57: DC+6 | H57: DA+6 | J57: DB+0 | L57: DB+09 | N57: DD+3 | P57: DA+6 | R57: DA+0 | T57: DA+0 | V57: DD+00 | X57: =COUNTIF($B$57:$V$57, "DA+0") -> 2 | Y57: =COUNTIF($B$57:$V$57, "DA+3") -> 1 | Z57: =COUNTIF($B$57:$V$57, "DA+6") -> 2 | AA57: =COUNTIF($B$57:$V$57, "DA+9") -> 1 | AD57: =COUNTIF($B$57:$V$57, "DB+0") -> 1 | AE57: =COUNTIF($B$57:$V$57, "DB+3") -> 0 | AF57: =COUNTIF($B$57:$V$57, "DB+6") -> 0 | AG57: =COUNTIF($B$57:$V$57, "DB+9") -> 0 | AI57: =COUNTIF($B$57:$V$57, "DC+0") -> 0 | AJ57: =COUNTIF($B$57:$V$57, "DC+3") -> 0 | AK57: =COUNTIF($B$57:$V$57, "DC+6") -> 1 | AL57: =COUNTIF($B$57:$V$57, "DC+9") -> 0 | AN57: =COUNTIF($B$57:$V$57, "DD+0") -> 0 | AO57: =COUNTIF($B$57:$V$57, "DD+3") -> 1 | AP57: =COUNTIF($B$57:$V$57, "DD+6") -> 0 | AQ57: =COUNTIF($B$57:$V$57, "DD+9") -> 0
F58: RC | R58: Benching | T58: RC | V58: =A85+I77+K77+M77+O77+G77+Q77+S77+#REF!+C77 -> #REF!
B59: =V51+1 -> 61 | D59: =B59+1 -> 62 | F59: =D59+1 -> 63 | H59: =F59+1 -> 64 | J59: =H59+1 -> 65 | L59: =J59+1 -> 66 | N59: =L59+1 -> 67 | P59: =N59+1 -> 68 | R59: =P59+1 -> 69 | T59: =R59+1 -> 70
C61: 392.27 | E61: 431.96 | G61: 426.02 | I61: 405.36 | K61: 411.93 | M61: 350.33 | O61: 378.3 | Q61: 416.82 | S61: 371.85
T62: F
B64: AP71 | D64: 71/1 | F64: 71/2 | H64: 71/3 | J64: AP72 | L64: 72/1 | N64: 72/2 | P64: AP73 | R64: 73/1 | T64: 73/2
B65: DB+00 | D65: DA+9 | F65: DA+0 | H65: DA+0 | J65: DD+00 | L65: DA+3 | N65: DA+3 | P65: DB+00 | R65: DA+0 | T65: DA+9 | X65: =COUNTIF($B$65:$V$65, "DA+0") -> 3 | Y65: =COUNTIF($B$65:$V$65, "DA+3") -> 2 | Z65: =COUNTIF($B$65:$V$65, "DA+6") -> 0 | AA65: =COUNTIF($B$65:$V$65, "DA+9") -> 2 | AD65: =COUNTIF($B$65:$V$65, "DB+0") -> 0 | AE65: =COUNTIF($B$65:$V$65, "DA+3") -> 2 | AF65: =COUNTIF($B$65:$V$65, "DB+6") -> 0 | AG65: =COUNTIF($B$65:$V$65, "DB+9") -> 0 | AI65: =COUNTIF($B$65:$V$65, "DC+0") -> 0 | AJ65: =COUNTIF($B$65:$V$65, "DC+3") -> 0 | AK65: =COUNTIF($B$65:$V$65, "DC+6") -> 0 | AL65: =COUNTIF($B$65:$V$65, "DC+9") -> 0 | AN65: =COUNTIF($B$65:$V$65, "DD+0") -> 0 | AO65: =COUNTIF($B$65:$V$65, "DD+3") -> 0 | AP65: =COUNTIF($B$65:$V$65, "DD+6") -> 0 | AQ65: =COUNTIF($B$65:$V$65, "DD+9") -> 0
H66: RC | J66: Benching &RC | L66: RC | R66: Benching & RC | T66: CLEAR | V66: =A93+I85+K85+M85+O85+G85+Q85+S85+U85+C85 -> 3994.99
B67: =T59+1 -> 71 | D67: =B67+1 -> 72 | F67: =D67+1 -> 73 | H67: =F67+1 -> 74 | J67: =H67+1 -> 75 | L67: =J67+1 -> 76 | N67: =L67+1 -> 77 | P67: =N67+1 -> 78 | R67: =P67+1 -> 79 | T67: =R67+1 -> 80
C69: 385.17 | E69: 345.19 | G69: 332.38 | I69: 393.62 | K69: 387.95 | M69: 340.35 | O69: 393.12 | Q69: 328.54 | S69: 398.52
B70: F | F70: F | J70: F | L70: F | N70: F | P70: F | R70: F | T70: F
B71: Er | F71: Er | J71: Er | L71: Er | N71: Er | P71: Er | T71: Er
B72: 73/3 | D72: AP74 | F72: 74/1 | H72: AP75 | J72: 75/1 | L72: 75/2 | N72: 75/3 | P72: 75/4 | R72: 75/5 | T72: 75/6
B73: DA+9 | D73: DB+09 | F73: DA+0 | H73: DC+0 | J73: DA+0 | L73: DA+0 | N73: DA+3 | P73: DA+0 | R73: DA+0 | T73: DA+0 | X73: =COUNTIF($B$73:$V$73, "DA+0") -> 6 | Y73: =COUNTIF($B$73:$V$73, "DA+3") -> 1 | Z73: =COUNTIF($B$73:$V$73, "DA+6") -> 0 | AA73: =COUNTIF($B$73:$V$73, "DA+9") -> 1 | AD73: =COUNTIF($B$73:$V$73, "DB+0") -> 0 | AE73: =COUNTIF($B$73:$V$73, "DB+3") -> 0 | AF73: =COUNTIF($B$73:$V$73, "DB+6") -> 0 | AG73: =COUNTIF($B$73:$V$73, "DB+9") -> 0 | AI73: =COUNTIF($B$73:$V$73, "DC+0") -> 1 | AJ73: =COUNTIF($B$73:$V$73, "DC+3") -> 0 | AK73: =COUNTIF($B$73:$V$73, "DC+6") -> 0 | AL73: =COUNTIF($B$73:$V$73, "DC+9") -> 0 | AN73: =COUNTIF($B$73:$V$73, "DD+0") -> 0 | AO73: =COUNTIF($B$73:$V$73, "DD+3") -> 0 | AP73: =COUNTIF($B$73:$V$73, "DD+6") -> 0 | AQ73: =COUNTIF($B$73:$V$73, "DD+9") -> 0
B74: CLEAR | H74: Benching | J74: Benching | L74: Benching &RC
