Workbook
Name \0: #REF!
Name \2: #REF!
Name \3: #REF!
Name \4: #REF!
Name \A: #REF!
Name \A_1: "#REF!"
Name \a1: #REF!
Name \B: #REF!
Name \C: #REF!
Name \c1: #REF!
Name \d: #N/A
Name \E: #REF!
Name \f: #REF!
Name \g: #REF!
Name \H: #REF!
Name \I: #REF!
Name \j: #REF!
Name \k: #REF!
Name \KWS123: #N/A
Name \l: #REF!
Name \M: #REF!
Name \N: #REF!
Name \P: #REF!
Name \q: #N/A
Name \R: #REF!
Name \S: #REF!
Name \t: #N/A
Name \U: #REF!
Name \V: #REF!
Name \z: #REF!
Name _: #REF!
Name _________________________________________________________dol12: #REF!
Name _________________________________________________________in18900: #REF!
Name _________________________________________________________iv19000: #REF!
Name ________________________________________________________dol12: #REF!
Name ________________________________________________________dol6: #REF!
Name ________________________________________________________in18900: #REF!
Name ________________________________________________________iv19000: #REF!
Name _______________________________________________________dol12: #REF!
Name _______________________________________________________dol6: #REF!
Name _______________________________________________________in18900: #REF!
Name _______________________________________________________iv19000: #REF!
Name ______________________________________________________dol12: #REF!
Name ______________________________________________________dol6: #REF!
Name _____________________________________________________dol12: #REF!
Name _____________________________________________________dol6: #REF!
Name _____________________________________________________in18900: #REF!
Name _____________________________________________________iv19000: #REF!
Name ____________________________________________________dol12: #REF!
Name ____________________________________________________dol6: #REF!
Name ____________________________________________________in18900: #REF!
Name ____________________________________________________iv19000: #REF!
Name ___________________________________________________dol12: #REF!
Name ___________________________________________________dol6: #REF!
Name ___________________________________________________in18900: #REF!
Name ___________________________________________________iv19000: #REF!
Name __________________________________________________dol12: #REF!
Name __________________________________________________dol6: #REF!
Name __________________________________________________in18900: #REF!
Name __________________________________________________iv19000: #REF!

Sheet TB401 DPR.....
B1: Project Code | D1: TB-401 | F1: Date | H1: =TODAY() -> 46162 | I1: LOA Start Date | L1: 45041 | M1: Business Head (T&D)- India & Sri Lanka | P1: Rajinder Gupta
B2: Project Name | D2: 765KV D/C Fategarh-III Beawar Transmission Line | I2: LOA End Date | L2: 45498 | M2: PCH | P2: Sivaraman Nataraajan
B3: Client Name | D3: Strelite Power | I3: Time Extn | L3: 45498 | M3: Regional Manager | P3: Sandeep Singh Kumar
B4: LE Value | D4: Rs 312 Cr -Supply -Rs 227.5 Cr.; Service.-Rs 84.4 Cr | I4: Planning | L4: Shah Ali Khan | M4: Project Manager | P4: Virender Gupta
A5: Activity | B5: Unit | C5: LOA Qty. | D5: LE Qty | E5: Progress till Last Month | F5: Balance | G5: L2 for Dec'23 | H5: Plan for Dec.'23 | I5: Today's Progress | J5: Month Progress | K5: WIP | L5: Gangs at Present | M5: L2 Till Month-Dec.23 | N5: Progress Till Date | O5: Balance Work | P5: Remarks
A6: Route Alignment | B6: km | C6: 215 | D6: 202 | E6: 167 | F6: =D6-E6 -> 35 | G6: 0 | H6: 35 | M6: 215 | N6: =E6+J6 -> 167 | O6: =D6-N6 -> 35 | P6: 35 Km is hold due to ROW issues
A7: Detailed Survey | B7: km | C7: 215 | D7: 202 | E7: 202 | F7: =D7-E7 -> 0 | G7: 0 | M7: 215 | N7: =E7+J7 -> 202 | O7: =D7-N7 -> 0 | P7: SPTL Approved -202/202-Kms
A8: Check Survey | B8: km | C8: 215 | D8: 202 | E8: 92.704 | F8: =D8-E8 -> 109.296 | G8: 20 | H8: 50 | J8: 17.852 | M8: 160 | N8: =E8+J8 -> 110.556 | O8: =D8-N8 -> 91.444 | P8: 1. Total 7.854 Km is under review of SPTL. 2. Total check survey completed (Field work) 167 Km. 3. Total 60 Km check survey is hold due to row issues & Other issues.
A9: Foundation | B9: Nos | C9: 534 | D9: 521 | E9: 109 | F9: =D9-E9 -> 412 | G9: 75 | H9: 30 | J9: 1 | K9: 4 | L9: 3 | M9: 399 | N9: =E9+J9 -> 110 | O9: =D9-N9 -> 411 | AA9: =65/D9 -> 0.12476008 | AC9: =(D11-C9)/C9 -> -0.024344569 | AD9: =C9*AC9 -> -13 | AE9: =366-318 -> 48 | AF9: =318-12 -> 306
A10: Earthing | B10: Nos | C10: 534 | D10: 521 | E10: 106 | F10: =D10-E10 -> 415 | G10: 75 | H10: 30 | J10: 2 | M10: 399 | N10: =E10+J10 -> 108 | O10: =D10-N10 -> 413 | AA10: =65/D10 -> 0.12476008
A11: Tower Erection | B11: Nos | C11: 534 | D11: 521 | E11: 45 | F11: =D11-E11 -> 476 | G11: 75 | H11: 40 | I11: 2 | J11: 6 | K11: 5 | L11: 5 | M11: 260 | N11: =E11+J11 -> 51 | O11: =D11-N11 -> 470 | P11: 56/2 58/15 Complete | AA11: =65/D11 -> 0.12476008
A12: Tack welding | B12: Nos | C12: 534 | D12: 521 | E12: 15 | F12: =D12-E12 -> 506 | G12: 75 | H12: 40 | I12: 1 | J12: 3 | K12: 1 | L12: 1 | M12: 260 | N12: =E12+J12 -> 18 | O12: =D12-N12 -> 503 | P12: 56/7 complete | AA12: =65/D12 -> 0.12476008
A13: Stringing | B13: Km | C13: 215 | D13: 202 | E13: 0 | F13: =D13-E13 -> 202 | G13: 20 | M13: 25 | N13: =E13+J13 -> 0 | O13: =D13-N13 -> 202 | AA13: =20.635/D13 -> 0.10215347 | AD13: =103/151 -> 0.68211921
AA14: =20.635/D14 -> #DIV/0!

Sheet Eng.
A2: Tower | B2: Tower Design | D2: Test Tower | F2: Balance Structural Drawing. | H2: Tower | I2: Stub & Template Drawings | J2: Foundation
A3: Types | D3: Structural Drawing(BTB+0) | F3: (3M/6M/9M) | H3: Testing | J3: Design/Drg
B4: Target | C4: Status | D4: Target | E4: Status | F4: Target | G4: Status | J4: Target | K4: Status
A5: DA Tower | B5: 45058 | C5: Approved | D5: 45081 | E5: Approved | F5: 45101 | G5: Approved for proto | H5: Completed | I5: Approved | J5: 15-July | K5: Approved
A6: DB Tower | B6: 45076 | C6: Approved | D6: 45137 | E6: Approved | F6: 45126 | G6: Approvedin Cat-B | H6: Completed | I6: Approved for Proto | J6: DB all Fdn. By 25 -July | K6: Approved
A8: DD Tower | B8: 45098 | C8: Approved | D8: 30-Sept. | E8: Approved in Cat -B | F8: 45158 | G8: Approved in Cat -B | H8: Completed | I8: Approved in Cat -B | J8: 45138 | K8: Approved
A9: DC Tower | B9: 45123 | C9: Approved | D9: 45207 | E9: Approved in Cat -B | F9: 45188 | G9: Approved in Cat -B | H9: Completed | I9: Approved in Cat -B | J9: 45163 | K9: Approved

Sheet Fdn (Pkg -G Section -I)
A1: KEC INTERNATIONAL LIMITED | L1: Date: | M1: =TODAY() -> 46162
A2: LILO of 765 Kv DV Fatehgarh 3 Beawar TL
A3: FOUNDATION
A4: Sl. No. | B4: Month Sl. No. | C4: JMC No. | D4: Location No. | E4: Tower Type | F4: Classification | G4: Excavation Start | H4: Dt. of Start | I4: Dt. of Concrete | J4: Name of Sub-Contractor | K4: KEC representative | L4: KEC Section In-Charge | M4: Remarks
A6: 1 | B6: 1 | D6: 32/7 | E6: DA+0 | F6: SANDY | G6: 23.10.23 | H6: 25.10.23 | I6: 28.10.23 | J6: Shakti Construction | K6: Kumar Nayak | L6: Jish C Verghese | M6: Complete
A7: 2 | B7: 2 | D7: 32/5 | E7: DA+6 | F7: SANDY | G7: 29.10.23 | H7: 31.10.23 | I7: 04.11.2023 | J7: Shakti Construction | K7: Kumar Nayak | L7: Jish C Verghese | M7: Complete
A8: 3 | B8: 3 | D8: 32/1 | E8: DA+9 | F8: SANDY | G8: 03.11.23 | H8: 06.11.23 | I8: 10.11.23 | J8: Shakti Construction | K8: Kumar Nayak | L8: Jish C Verghese | M8: Complete
A9: 4 | B9: 4 | D9: 30/2 | E9: DA+0 | F9: SANDY | G9: 13.11.23 | H9: 15.11.23 | I9: 16.11.23 | J9: Shakti Construction | K9: Kumar Nayak | L9: Jish C Verghese | M9: Complete
A10: 5 | B10: 5 | D10: 32/0 | E10: DB2+6 | F10: SANDY | G10: 18.11.23 | H10: 20.11.23 | I10: 28.11.23 | J10: Shakti Construction | K10: Dipesh | L10: Jish C Verghese | M10: Complete
B11: Dec-23
A12: 1 | B12: 6 | D12: 31/3 | E12: DA+0 | F12: SANDY | G12: 28.11.23 | H12: 30.11.23 | I12: 04.12.23 | J12: Shakti Construction | K12: Dipesh | L12: Jish C Verghese | M12: Complete

Sheet Sheet2
C2: S.No | D2: Line | E2: Activity | F2: UOM | G2: LOA Qty | H2: L2 till Sep'25 | I2: Completed till Date | J2: Balance | K2: WIP | L2: Gangs | M2: Remarks
C3: 1 | D3: Samba- Jalandhar | E3: Survey | F3: Km | G3: 144 | H3: 70 | I3: 129.36 | J3: =G3-I3 -> 14.64 | L3: 2
E4: Foundation | F4: Nos | G4: 434 | H4: 17 | I4: 2 | J4: =G4-I4 -> 432 | K4: 4 | L4: 3
C5: 2 | D5: Kishepur- Samba | E5: Survey | F5: Km | G5: 33.103 | H5: 20 | I5: 8.56 | J5: =G5-I5 -> 24.543 | K5: 0.3 | L5: 1
E6: Foundation | F6: Nos | G6: 129 | J6: =G6-I6 -> 129
C7: 3 | D7: LILO-Kisthwar | E7: Survey | F7: Km | G7: 2.18 | H7: 2.18 | I7: 2.18 | J7: =G7-I7 -> 0
E8: Foundation | F8: Nos | G8: 14 | H8: 6 | J8: =G8-I8 -> 14
D9: Total | E9: Survey | F9: Km | G9: =G7+G5+G3 -> 179.283 | H9: =H7+H5+H3 -> 92.18 | I9: =I7+I5+I3 -> 140.1 | J9: =G9-I9 -> 39.183 | K9: =K7+K5+K3 -> 0.3 | L9: =L7+L5+L3 -> 3
E10: Foundation | F10: Nos | G10: =G8+G6+G4 -> 577 | H10: =H8+H6+H4 -> 23 | I10: =I8+I6+I4 -> 2 | J10: =G10-I10 -> 575 | K10: =K8+K6+K4 -> 4 | L10: =L8+L6+L4 -> 3
P13: S.No | Q13: Loc | R13: TOT | S13: S.No | T13: Loc | U13: TOT
P14: 1 | Q14: AP156 | R14: DC+0 | S14: =10+1 -> 11 | T14: AP91 | U14: DD+25
P15: =P14+1 -> 2 | Q15: 70/2 | R15: DA+0 | S15: =S14+1 -> 12 | T15: 153/2 | U15: DA+3
P16: =P15+1 -> 3 | Q16: 153/1 | R16: DA+0
P17: =P16+1 -> 4 | Q17: AP111 | R17: DC+0
P18: =P17+1 -> 5 | Q18: 136/3 | R18: DA+0
P19: =P18+1 -> 6 | Q19: 157/1 | R19: DA+0
P20: =P19+1 -> 7 | Q20: AP150 | R20: DC+0
P21: =P20+1 -> 8 | Q21: AP70 | R21: DC+3
P22: =P21+1 -> 9 | Q22: 136/4 | R22: DA+3
P23: =P22+1 -> 10 | Q23: AP68 | R23: DB+0

Sheet Sheet3
B2: Line | C2: Activity | D2: Section | E2: L2 Oct'25 | F2: Plan Oct'25 | G2: L2 Nov'25 | H2: Plan Nov'25 | I2: L2 Dec'25 | J2: Plan Dec'25 | K2: L2 (Oct'25-Dec'25) | L2: Plan (Oct'25-Dec'25)
B3: Samba-Jalandhar | C3: FDN | D3: Jammu | E3: 25 | F3: 10 | G3: 35 | H3: 10 | I3: 40 | J3: 20 | K3: =E3+G3+I3 -> 100 | L3: =F3+H3+J3+F5+H5+J5 -> 110
C4: Gangs | F4: 3 | H4: 3 | J4: 6
C5: FDN | D5: Punjab | F5: 15 | H5: 25 | J5: 30
C6: Gangs | F6: 5 | H6: 6 | J6: 6
B7: Kishenpur-Samba | C7: FDN | D7: Jammu | E7: 2 | G7: 7 | H7: 5 | I7: 10 | J7: 8 | K7: =E7+G7+I7 -> 19 | L7: =F7+H7+J7 -> 13
C8: Gangs | H8: 3 | J8: 4
B9: LILO-Kishtwar | C9: FDN | D9: Kishtwar | E9: 2 | G9: 2 | H9: 1 | J9: 1 | K9: =E9+G9+I9 -> 4 | L9: =F9+H9+J9 -> 2
C10: Gangs | H10: 1 | J10: 1
B11: Total | C11: FDN | E11: =E9+E7+E3 -> 29 | F11: =F3+F5+F7+F9 -> 25 | G11: =G9+G7+G3 -> 44 | H11: =H3+H5+H7+H9 -> 41 | I11: =I9+I7+I3 -> 50 | J11: =J3+J5+J7+J9 -> 59 | K11: =K9+K7+K3 -> 123 | L11: =L9+L7+L3 -> 125
C12: Gangs | F12: =F6+F4+F8+F10 -> 8 | H12: =H6+H4+H8+H10 -> 13 | J12: =J6+J4+J8+J10 -> 17

Sheet Sheet4
D6: Line | E6: Portion | F6: Section | G6: Length | H6: ROW Lead | I6: ROW Team | J6: Remarks
G7: Km | I7: Currently Working
D8: Samba-Jalandhar | E8: Jammu | F8: Gantry-AP52 | G8: 47 | H8: Karmanya Pathania | I8: ROW Team-1 Akhil S ( Engineer) / Radhe Shyam (Supervisor) | J8: At site since the works are in initial phase , hence we have engaged site engineer/supervisor for ROW document collection for time being , further we can engage separate ROW team as per requirement
E9: Punjab | F9: AP52 - AP115 | G9: 47 | I9: ROW Team -2 K Govind ( Section In charge) / Kuldeep Singh ( DET)
F10: AP115 - AP187 | G10: 48 | I10: ROW Team -3 Manish Nirala (Section In charge) / Govardhan (DET)
D11: Kishenpur-Samba | F11: Gantry- AP109 | G11: 33 | I11: ROW Team -4 Mukesh ( Admin) /Yadhuveer (Supervisor) | J11: Due to heavy rains/landslides local administration blocked the roads
D12: LILO | E12: Kishtewar | F12: AP1-Tapping Point | G12: 2.1 | J12: Due to heavy rains/landslides local administration blocked the roads

Sheet Sheet5

Sheet ROW
A1: KEC INTERNATIONAL LIMITED | F1: Date | G1: 46083
A2: 400kv D/C Samba-Jalandhar T/L-Punjab Portion
D4: Submitted | E4: =COUNTIF(E7:E247,"Submitted") -> 109 | F4: =COUNTIF(F7:F247,"Submitted") -> 90
D5: File Ready | E5: =COUNTIF(E7:E247,"File Ready") -> 10 | F5: =COUNTIF(F7:F247,"File Ready") -> 8
A6: S.No | B6: Tower | C6: TOT | D6: Foundation Completion Status | E6: Crop | F6: Land | G6: Remarks
A7: 1 | B7: AP53 | C7: DC+0
A8: =A7+1 -> 2 | B8: AP54 | C8: DC+6
A9: =A8+1 -> 3 | B9: AP55 | C9: DD+3
A10: =A9+1 -> 4 | B10: 55/1 | C10: DA+6
A11: =A10+1 -> 5 | B11: AP56 | C11: DC+3
A12: =A11+1 -> 6 | B12: 56/1 | C12: DA+6
A13: =A12+1 -> 7 | B13: 56/2 | C13: DA+3
A14: =A13+1 -> 8 | B14: 56/3 | C14: DA+6 | D14: WIP
A15: =A14+1 -> 9 | B15: 56/4 | C15: DA+6
A16: =A15+1 -> 10 | B16: AP57 | C16: DD+3
A17: =A16+1 -> 11 | B17: 57/1 | C17: DA+0
A18: =A17+1 -> 12 | B18: 57/2 | C18: DA+0
A19: =A18+1 -> 13 | B19: AP58 | C19: DC+0
A20: =A19+1 -> 14 | B20: AP59 | C20: DD+6
A21: =A20+1 -> 15 | B21: 59/1 | C21: DA+3
A22: =A21+1 -> 16 | B22: AP60 | C22: DB+6
A23: =A22+1 -> 17 | B23: 60/1 | C23: DA+0
A24: =A23+1 -> 18 | B24: AP61 | C24: DC+0
A25: =A24+1 -> 19 | B25: 61/1 | C25: DA+0
A26: =A25+1 -> 20 | B26: AP62 | C26: DB+0
... A40: =A39+1 -> 34 | B40: 67/1 | C40: DA+0
A41: =A40+1 -> 35 | B41: 67/2 | C41: DA+0 | D41: WIP
A42: =A41+1 -> 36 | B42: 67/3 | C42: DA+0 | D42: C
A43: =A42+1 -> 37 | B43: AP68 | C43: DB+0 | D43: C | E43: Submitted | F43: Submitted
A44: =A43+1 -> 38 | B44: AP69 | C44: DB+0 | D44: C
A45: =A44+1 -> 39 | B45: 69/1 | C45: DA+0 | D45: C | E45: Submitted | F45: Submitted
A46: =A45+1 -> 40 | B46: 69/2 | C46: DA+0 | D46: C | E46: Submitted | F46: Submitted
A47: =A46+1 -> 41 | B47: 69/3 | C47: DA+0 | D47: C | E47: Submitted | F47: Submitted
A48: =A47+1 -> 42 | B48: AP70 | C48: DC+3 | D48: C | E48: File Ready | F48: File Ready
A49: =A48+1 -> 43 | B49: 70/1 | C49: DA+9 | D49: C | E49: File Ready
A50: =A49+1 -> 44 | B50: 70/2 | C50: DA+0 | D50: C | E50: File Ready
A51: =A50+1 -> 45 | B51: AP70/3 | C51: DD+18
A52: =A51+1 -> 46 | B52: AP71 | C52: DC+9 | D52: WIP
A53: =A52+1 -> 47 | B53: 71/1 | C53: DA+3 | E53: Submitted | F53: Submitted
A54: =A53+1 -> 48 | B54: 71/2 | C54: DA+9 | D54: C
A55: =A54+1 -> 49 | B55: 71/3 | C55: DA+6 | D55: C | E55: Submitted
A56: =A55+1 -> 50 | B56: AP72 | C56: DB+3 | D56: C | E56: Submitted | F56: Submitted
A57: =A56+1 -> 51 | B57: 72/1 | C57: DA+3 | D57: C | E57: Submitted | F57: Submitted
A58: =A57+1 -> 52 | B58: 72/2 | C58: DA+6 | D58: C | E58: Submitted
A59: =A58+1 -> 53 | B59: AP74 | C59: DB+0 | D59: C | E59: Submitted | F59: Submitted
A60: =A59+1 -> 54 | B60: AP75 | C60: DB+9 | D60: C | E60: Submitted | F60: Submitted
A61: =A60+1 -> 55 | B61: AP76 | C61: DC+9
A62: =A61+1 -> 56 | B62: 76/1 | C62: DA+0 | D62: C | E62: Submitted | F62: Submitted
A63: =A62+1 -> 57 | B63: 76/2 | C63: DA+3 | D63: C | E63: Submitted | F63: Submitted
A64: =A63+1 -> 58 | B64: 76/3 | C64: DA+3 | D64: C | E64: Submitted | F64: Submitted
A65: =A64+1 -> 59 | B65: AP77 | C65: DB+3 | D65: C | E65: Submitted | F65: Submitted
A66: =A65+1 -> 60 | B66: 77/1 | C66: DA+3 | D66: C | E66: Submitted | F66: Submitted
A67: =A66+1 -> 61 | B67: 77/2 | C67: DB+0 | D67: C | E67: Submitted | F67: Submitted
A68: =A67+1 -> 62 | B68: 77/3 | C68: DA+0
A69: =A68+1 -> 63 | B69: AP78 | C69: DB+9
A70: =A69+1 -> 64 | B70: AP79 | C70: DD+9 | D70: C | E70: Submitted | F70: Submitted
A71: =A70+1 -> 65 | B71: AP80 | C71: DD+0 | D71: C | E71: Submitted | F71: Submitted
A72: =A71+1 -> 66 | B72: 80/1 | C72: DB+3 | D72: C | E72: File Ready | G72: Court Case , Indigrid rejected to submit
A73: =A72+1 -> 67 | B73: AP81 | C73: DD+9
A74: =A73+1 -> 68 | B74: AP82 | C74: DD+3
A75: =A74+1 -> 69 | B75: 82/1 | C75: DA+0 | D75: C | E75: Submitted | F75: Submitted
A76: =A75+1 -> 70 | B76: 82/2 | C76: DA+3 | D76: C | E76: Submitted | F76: Submitted
A77: =A76+1 -> 71 | B77: AP83 | C77: DD+25
A78: =A77+1 -> 72 | B78: AP84 | C78: DD+18
A79: =A78+1 -> 73 | B79: AP85 | C79: DB+0 | D79: C | E79: Submitted | F79: Submitted
A80: =A79+1 -> 74 | B80: 85/1 | C80: DA+9 | D80: C | E80: Submitted | F80: Submitted
A81: =A80+1 -> 75 | B81: AP86 | C81: DC+0
A82: =A81+1 -> 76 | B82: 86/1 | C82: DA+3 | D82: C | E82: File Ready | F82: File Ready
A83: =A82+1 -> 77 | B83: AP87 | C83: DB+9 | D83: C
A84: =A83+1 -> 78 | B84: 87/1 | C84: DA+3
A85: =A84+1 -> 79 | B85: 87/2 | C85: DA+3 | D85: C | E85: Submitted | F85: Submitted
A86: =A85+1 -> 80 | B86: AP88 | C86: DD+18
A87: =A86+1 -> 81 | B87: AP89 | C87: DD+18
A88: =A87+1 -> 82 | B88: 89/1 | C88: DA+3 | D88: C | E88: Submitted | F88: Submitted
A89: =A88+1 -> 83 | B89: AP90 | C89: DD+0 | D89: C | E89: Submitted | F89: Submitted
A90: =A89+1 -> 84 | B90: 90/1 | C90: DA+3 | D90: C | E90: Submitted | F90: Submitted
A91: =A90+1 -> 85 | B91: 90/2 | C91: DA+0 | D91: C | E91: Submitted | F91: Submitted
A92: =A91+1 -> 86 | B92: AP91 | C92: DD+25 | D92: C | E92: File Ready
A93: =A92+1 -> 87 | B93: AP92 | C93: DD+25 | D93: C | E93: Submitted | F93: Submitted
A94: =A93+1 -> 88 | B94: 92/1 | C94: DA+3 | D94: C | E94: Submitted | F94: Submitted
A95: =A94+1 -> 89 | B95: 92/2 | C95: DA+6 | D95: C | E95: Submitted | F95: Submitted
A96: =A95+1 -> 90 | B96: 92/3 | C96: DA+0 | D96: C | E96: Submitted | F96: Submitted
A97: =A96+1 -> 91 | B97: AP93 | C97: DC+0 | D97: C | E97: Submitted | F97: Submitted
A98: =A97+1 -> 92 | B98: 93/1 | C98: DA+0 | D98: C | E98: Submitted | F98: Submitted
A99: =A98+1 -> 93 | B99: 93/2 | C99: DA+0 | D99: C | E99: Submitted | F99: Submitted
A100: =A99+1 -> 94 | B100: AP94 | C100: DB+0 | D100: C | E100: Submitted | F100: Submitted
A101: =A100+1 -> 95 | B101: AP95 | C101: DC+3 | D101: C | E101: Submitted | F101: Submitted
A102: =A101+1 -> 96 | B102: 95/1 | C102: DA+0 | D102: C | E102: Submitted | F102: Submitted
A103: =A102+1 -> 97 | B103: 95/2 | C103: DA+0 | D103: C | E103: Submitted | F103: Submitted
A104: =A103+1 -> 98 | B104: 95/3 | C104: DA+0 | D104: C | E104: Submitted | F104: Submitted
... A107: =A106+1 -> 101 | B107: AP97 | C107: DD+3 | D107: C | E107: Submitted | F107: Submitted
A108: =A107+1 -> 102 | B108: 97/1 | C108: DA+0 | D108: C | E108: Submitted | G108: Panchayat Land
A109: =A108+1 -> 103 | B109: 97/2 | C109: DA+0 | D109: C | E109: Submitted | F109: Submitted
A110: =A109+1 -> 104 | B110: 97/3 | C110: DA+3 | D110: C | E110: Submitted | F110: Submitted
A111: =A110+1 -> 105 | B111: AP98 | C111: DB+3 | D111: C | E111: Submitted | F111: Submitted
A112: =A111+1 -> 106 | B112: 98/1 | C112: DA+3 | D112: C | E112: Submitted | F112: Submitted
A113: =A112+1 -> 107 | B113: AP99 | C113: DB+0 | D113: C | E113: Submitted | F113: Submitted
A114: =A113+1 -> 108 | B114: 99/1 | C114: DA+9 | D114: C | E114: Submitted | F114: Submitted
A115: =A114+1 -> 109 | B115: AP100 | C115: DC+3 | D115: C | E115: File Ready | F115: File Ready
A116: =A115+1 -> 110 | B116: AP101 | C116: DC+0
...

Sheet Sheet13 (2)
C2: Paticulars | D2: Plain Terrain | E2: Hilly Terrain
C3: Line Length (KM) | D3: 137 KM | E3: 36 KM
D4: =137/173 -> 0.79190751 | E4: =36/173 -> 0.20809249

Sheet TB-605
A1: s | B1: Project Code | C1: TB-605 | D1: Date | E1: 46161 | H1: President-T & D | I1: Ganesh Srinivasan
B2: Project Name | C2: Transmission Line Portion for “Transmission scheme for evacuation of power from Ratle HEP (850 MW) & Kiru HEP (624 MW): Part-A” | F2: LOA Start Date | G2: 45793 | H2: SBU Head- T&D | I2: Rajinder Gupta
B3: Client Name | C3: Ratle Kiru Power Transmission Ltd | F3: LOA End Date | G3: 46461 | H3: PCH | I3: NK Gupta
B4: Revised End Date | F4: Planning | G4: Aditya.M | H4: Project Manager | I4: Mithu Dutta
A5: Progress Summary - Ratle Kiru Power Transmission Ltd
A6: Activity | B6: Final Estimated Qty | C6: Cumulative L2 till Last Month | D6: Cumulative Progress till Last Month | E6: L2 for present Month | F6: Plan for the Month | G6: Today's Progress | H6: Progress till Date for the Month | I6: L2 till Current Month | J6: Completed till Date | K6: Balance Work | L6: Under Progress | M6: Gangs at Present | N6: Remarks
A7: Check Survey | B7: =B16+B24+B32+B40 -> 173.438 | C7: =C16+C24+C32+C40 -> 179.203 | D7: =D16+D24+D32+D40 -> 173.438 | E7: =E16+E24+E32+E40 -> 0 | F7: =F16+F24+F32+F40 -> 0 | G7: =G16+G24+G32+G40 -> 0 | H7: =H16+H24+H32+H40 -> 0 | I7: =+C7+E7 -> 179.203 | J7: =+H7+D7 -> 173.438 | L7: =L16+L24+L32+L40 -> 0 | M7: =M16+M24+M32+M40 -> 3
A8: Foundation | B8: =B17+B25+B33+B41 -> 523 | C8: =C17+C25+C33+C41 -> 370 | D8: =D17+D25+D33+D41 -> 306 | E8: =E17+E25+E33+E41 -> 55 | F8: =F17+F25+F33+F41 -> 72 | G8: =G17+G25+G33+G41 -> 5 | H8: =H17+H25+H33+H41 -> 33 | I8: =+C8+E8 -> 425 | J8: =+H8+D8 -> 339 | K8: =+B8-J8 -> 184 | L8: =L17+L25+L33+L41 -> 36 | M8: =M17+M25+M33+M41 -> 36
A9: Earthing | B9: =B18+B26+B34+B42 -> 523 | C9: =C18+C26+C34+C42 -> 370 | D9: =D18+D26+D34+D42 -> 252 | E9: =E18+E26+E34+E42 -> 55 | F9: =F18+F26+F34+F42 -> 70 | G9: =G18+G26+G34+G42 -> 0 | H9: =H18+H26+H34+H42 -> 28 | I9: =+C9+E9 -> 425 | J9: =+H9+D9 -> 280 | K9: =+B9-J9 -> 243 | L9: =L18+L26+L34+L42 -> 0 | M9: =M18+M26+M34+M42 -> 0
A10: Tower Erection | B10: =B19+B27+B35+B43 -> 523 | C10: =C19+C27+C35+C43 -> 239 | D10: =D19+D27+D35+D43 -> 157 | E10: =E19+E27+E35+E43 -> 63 | F10: =F19+F27+F35+F43 -> 75 | G10: =G19+G27+G35+G43 -> 2 | H10: =H19+H27+H35+H43 -> 31 | I10: =+C10+E10 -> 302 | J10: =+H10+D10 -> 188 | K10: =+B10-J10 -> 335 | L10: =L19+L27+L35+L43 -> 7 | M10: =M19+M27+M35+M43 -> 7
A11: Tack welding | B11: =B20+B28+B36+B44 -> 523 | C11: =C20+C28+C36+C44 -> 239 | D11: =D20+D28+D36+D44 -> 0 | E11: =E20+E28+E36+E44 -> 63 | F11: =F20+F28+F36+F44 -> 75 | G11: =G20+G28+G36+G44 -> 0 | H11: =H20+H28+H36+H44 -> 0 | I11: =+C11+E11 -> 302 | J11: =+H11+D11 -> 0 | K11: =+B11-J11 -> 523 | L11: =L20+L28+L36+L44 -> 0 | M11: =M20+M28+M36+M44 -> 0
A12: Stringing | B12: =B21+B29+B37+B45 -> 173.438 | C12: =C21+C29+C37+C45 -> 5 | D12: =D21+D29+D37+D45 -> 0 | E12: =E21+E29+E37+E45 -> 15 | F12: =F21+F29+F37+F45 -> 0 | G12: =G21+G29+G37+G45 -> 0 | H12: =H21+H29+H37+H45 -> 0 | I12: =+C12+E12 -> 20 | J12: =+H12+D12 -> 0 | K12: =+B12-J12 -> 173.438 | L12: =L21+L29+L37+L45 -> 0 | M12: =M21+M29+M37+M45 -> 0
A13: Line Wise Progress
A14: 400 kV Samba- Jalandhar D/C Line(Quad) - Wind Zone - 5-Jammu Portion
A15: Activity | B15: Final Estimated Qty | C15: Cumulative L2 till Last Month | D15: Cumulative Progress till Last Month | E15: L2 for present Month | F15: Plan for the Month | G15: Today's Progress | H15: Progress till Date for the Month | I15: L2 till Current Month | J15: Completed till Date | K15: Balance Work | L15: Under Progress | M15: Gangs at Present | N15: Remarks
A16: Check Survey | B16: 46.92 | C16: 49 | D16: 46.92 | I16: =+C16+E16 -> 49 | J16: =+H16+D16 -> 46.92 | K16: =+B16-J16 -> 0
A17: Foundation | B17: 126 | C17: 100 | D17: 90 | E17: 15 | F17: 20 | G17: 1 | H17: 5 | I17: =+C17+E17 -> 115 | J17: =+H17+D17 -> 95 | K17: =+B17-J17 -> 31 | L17: 8 | M17: 8
A18: Earthing | B18: 126 | C18: 100 | D18: 73 | E18: 15 | F18: 20 | H18: 10 | I18: =+C18+E18 -> 115 | J18: =+H18+D18 -> 83 | K18: =+B18-J18 -> 43
A19: Tower Erection | B19: 126 | C19: 73 | D19: 64 | E19: 15 | F19: 20 | G19: 1 | H19: 12 | I19: =+C19+E19 -> 88 | J19: =+H19+D19 -> 76 | K19: =+B19-J19 -> 50 | L19: 3 | M19: 3
A20: Tack welding | B20: 126 | C20: 73 | D20: 0 | E20: 15 | F20: 20 | I20: =+C20+E20 -> 88 | J20: =+H20+D20 -> 0 | K20: =+B20-J20 -> 126 | L20: 0 | M20: 0
A21: Stringing | B21: 46.92 | C21: 2 | D21: 0 | E21: 5 | I21: =+C21+E21 -> 7 | J21: =+H21+D21 -> 0 | K21: =+B21-J21 -> 46.92 | L21: 0 | M21: 0
A22: 400 kV Samba- Jalandhar D/C Line(Quad) - Wind Zone - 5- Punjab Portion
A23: Activity | B23: Final Estimated Qty | C23: Cumulative L2 till Last Month | D23: Cumulative Progress till Last Month | E23: L2 for present Month | F23: Plan for the Month | G23: Today's Progress | H23: Progress till Date for the Month | I23: L2 till Current Month | J23: Completed till Date | K23: Balance Work | L23: Under Progress | M23: Gangs at Present | N23: Remarks
A24: Check Survey | B24: 90 | C24: 95 | D24: 90 | I24: =+C24+E24 -> 95 | J24: =+H24+D24 -> 90 | K24: =+B24-J24 -> 0 | M24: 2
A25: Foundation | B25: 263 | C25: 197 | D25: 166 | E25: 30 | F25: 40 | G25: 4 | H25: 27 | I25: =+C25+E25 -> 227 | J25: =+H25+D25 -> 193 | K25: =+B25-J25 -> 70 | L25: 15 | M25: 18
A26: Earthing | B26: 263 | C26: 197 | D26: 147 | E26: 30 | F26: 40 | H26: 18 | I26: =+C26+E26 -> 227 | J26: =+H26+D26 -> 165 | K26: =+B26-J26 -> 98 | L26: 0
A27: Tower Erection | B27: 263 | C27: 142 | D27: 91 | E27: 30 | F27: 45 | G27: 1 | H27: 19 | I27: =+C27+E27 -> 172 | J27: =+H27+D27 -> 110 | K27: =+B27-J27 -> 153 | L27: 3 | M27: 3
A28: Tack welding | B28: 263 | C28: 142 | D28: 0 | E28: 30 | F28: 45 | I28: =+C28+E28 -> 172 | J28: =+H28+D28 -> 0 | K28: =+B28-J28 -> 263 | L28: 0 | M28: 0
A29: Stringing | B29: 90 | C29: 3 | D29: 0 | E29: 10 | I29: =+C29+E29 -> 13 | J29: =+H29+D29 -> 0 | K29: =+B29-J29 -> 90 | L29: 0 | M29: 0
A30: 400 kV Kishenpur-Samba D/C Line (Quad) - Wind Zone-5
A31: Activity | B31: Final Estimated Qty | C31: Cumulative L2 till Last Month | D31: Cumulative Progress till Last Month | E31: L2 for present Month | F31: Plan for the Month | G31: Today's Progress | H31: Progress till Date for the Month | I31: L2 till Current Month | J31: Completed till Date | K31: Balance Work | L31: Under Progress | M31: Gangs at Present | N31: Remarks
A32: Check Survey | B32: 33.103 | C32: 33.103 | D32: 33.103 | I32: =+C32+E32 -> 33.103 | J32: =+H32+D32 -> 33.103 | K32: =+B32-J32 -> 0 | M32: 1
A33: Foundation | B33: 116 | C33: 59 | D33: 50 | E33: 10 | F33: 10 | H33: 1 | I33: =+C33+E33 -> 69 | J33: =+H33+D33 -> 51 | K33: =+B33-J33 -> 65 | L33: 7 | M33: 7
A34: Earthing | B34: 116 | C34: 59 | D34: 32 | E34: 10 | F34: 10 | I34: =+C34+E34 -> 69 | J34: =+H34+D34 -> 32 | K34: =+B34-J34 -> 84 | L34: 0
A35: Tower Erection | B35: 116 | C35: 20 | D35: 2 | E35: 15 | F35: 10 | I35: =+C35+E35 -> 35 | J35: =+H35+D35 -> 2 | K35: =+B35-J35 -> 114 | L35: 1 | M35: 1
A36: Tack welding | B36: 116 | C36: 20 | D36: 0 | E36: 15 | F36: 10 | I36: =+C36+E36 -> 35 | J36: =+H36+D36 -> 0 | K36: =+B36-J36 -> 116 | L36: 0 | M36: 0
A37: Stringing | B37: 33.103 | C37: 0 | D37: 0 | I37: =+C37+E37 -> 0 | J37: =+H37+D37 -> 0 | K37: =+B37-J37 -> 33.103 | L37: 0 | M37: 0
A38: 400kV DC LILO at Kistwar(Twin) Line - Wind Zone-2
A39: Activity | B39: Final Estimated Qty | C39: Cumulative L2 till Last Month | D39: Cumulative Progress till Last Month | E39: L2 for present Month | F39: Plan for the Month | G39: Today's Progress | H39: Progress till Date for the Month | I39: L2 till Current Month | J39: Completed till Date | K39: Balance Work | L39: Under Progress | M39: Gangs at Present | N39: Remarks
A40: Check Survey | B40: 3.415 | C40: 2.1 | D40: 3.415 | I40: =+C40+F40 -> 2.1 | J40: =+H40+D40 -> 3.415 | K40: =+B40-J40 -> 0
A41: Foundation | B41: 18 | C41: 14 | D41: 0 | F41: 2 | I41: =+C41+E41 -> 14 | J41: =+H41+D41 -> 0 | K41: =+B41-J41 -> 18 | L41: 6 | M41: 3
A42: Earthing | B42: 18 | C42: 14 | D42: 0 | I42: =+C42+E42 -> 14 | J42: =+H42+D42 -> 0 | K42: =+B42-J42 -> 18 | L42: 0
A43: Tower Erection | B43: 18 | C43: 4 | D43: 0 | E43: 3 | I43: =+C43+E43 -> 7 | J43: =+H43+D43 -> 0 | K43: =+B43-J43 -> 18 | L43: 0 | M43: 0
A44: Tack welding | B44: 18 | C44: 4 | D44: 0 | E44: 3 | I44: =+C44+E44 -> 7 | J44: =+H44+D44 -> 0 | K44: =+B44-J44 -> 18 | L44: 0 | M44: 0
A45: Stringing | B45: 3.415 | C45: 0 | D45: 0 | I45: =+C45+E45 -> 0 | J45: =+H45+D45 -> 0 | K45: =+B45-J45 -> 3.415 | L45: 0 | M45: 0
A46: Supply Status
A47: Line | B47: Description | C47: Final Estimated Qty | D47: L2 till May'26 | E47: Qty Supplied till May'26 | F47: Remarks
A48: Samba-Jalandhar | B48: Stubs | C48: =262+127 -> 389 | D48: =100+120+150+64 -> 434 | E48: 361
B49: Towers | C49: 389 | D49: =101+115+107 -> 323 | E49: 318
A50: Samba-Kishenpur | B50: Stubs | C50: 116 | D50: 129 | E50: 103
B51: Towers | C51: 116 | D51: 129 | E51: 61
A52: LILO at Kishtwar | B52: Stubs | C52: 18 | D52: 14 | E52: 10
B53: Towers | C53: 18 | D53: 14

Sheet Sheet19
C3: DA+3PS SD 1MR | D3: 1 | E3: 56/4
C4: DB+9 WET | D4: 1 | E4: 164/0 | H4: Tap | J4: 56 | K4: 56/4 | L4: 55
C5: DD+18/25 PS | D5: 1 | E5: 78/0 | H5: Suf | I5: 1 | J5: 57/1 | K5: 59/1 | L5: 57/2
C6: DA+3 FS | D6: 1 | E6: 144/1 | H6: Suf | I6: 2 | J6: 64/1 | K6: 62/1 | L6: 62/2
C7: DA+0 WET | D7: 3 | E7: 159/1,2,3 | H7: Suf | I7: 3 | J7: 82 | K7: 83 | L7: 84
C8: DD+0 WET | D8: 1 | E8: 110/0 | H8: KDR | J8: 65/4 | K8: 65/5 | L8: AP66
C9: DD+3PS SD 1MRC | D9: 1 | E9: 57/0 | H9: Aman Enter | J9: 61/1
C10: DD 18/25 PS 2MRC | D10: 1 | E10: 84/0 | H10: Ramesh
C11: DA+0PS SD1MRC | D11: 3
C12: DA+3PS SD 1MRC | D12: 1

Sheet Sheet16
C2: S.No | D2: Gang | E2: Line | F2: Remarks
C3: 1 | D3: Pawan Kumar Sharma | E3: J-S (Jammu) | F3: Gang idle since 4-4-26 at Loc: 40/3 due to ROW
C4: =C3+1 -> 2 | D4: Md. Ikrar | E4: J-S(Punjab) | F4: Loc: 144/4 completed on 5-4-2026 and no work front available due to crop harvesting
C5: =C4+1 -> 3 | D5: Ms. Hussain | E5: J-S(Punjab) | F5: Loc: 144/3 will be completed on 6-4-2026 and no work front availabl due to crop harvesting
C6: =C5+1 -> 4

Sheet Sheet14
B1: S.No | C1: Month | D1: Concreting | F1: Cement | G1: TMT
D2: M10 | E2: M20
D3: M3 | E3: M3 | F3: Bags | G3: MT
B4: 1 | C4: 45901 | D4: 14.664 | E4: 135.088 | F4: =ROUND((D4*4.4)+(E4*8),0) -> 1145 | G4: 8.44
B5: =B4+1 -> 2 | C5: 45931 | D5: 76.132 | E5: 667.004 | F5: =ROUND((D5*4.4)+(E5*8),0) -> 5671 | G5: 47.8
B6: =B5+1 -> 3 | C6: 45962 | D6: 283.933 | E6: 2687.36 | F6: =ROUND((D6*4.4)+(E6*8),0) -> 22748 | G6: 176.38
B7: =B6+1 -> 4 | C7: 45992 | D7: 415.90302 | E7: 3983.996 | F7: =ROUND((D7*4.4)+(E7*8),0) -> 33702 | G7: 264.63 | L7: Concreting (M3) | M7: Tower Erection(MT)
B8: =B7+1 -> 5 | C8: 46023 | D8: 411.1974 | E8: 4750.4 | F8: =ROUND((D8*4.4)+(E8*8),0) -> 39812 | G8: 164.07 | L8: 21381 | M8: 2332
B9: =B8+1 -> 6 | C9: 46054 | D9: 411.1974 | E9: 4300.4 | F9: =ROUND((D9*4.4)+(E9*8),0) -> 36212 | G9: 264.45
B10: =B9+1 -> 7 | C10: 46082 | D10: 296.343 | E10: 2947.484 | F10: =ROUND((D10*4.4)+(E10*8),0) -> 24884 | G10: 199.54
B11: Total | D11: =SUM(D4:D10) -> 1909.3698 | E11: =SUM(E4:E10) -> 19471.732 | F11: =SUM(F4:F10) -> 164174 | G11: =SUM(G4:G10) -> 1125.31

Sheet Sheet12
C1: Supply Portion
C2: S.No | D2: Material | E2: UOM | F2: BOQ Qty | G2: Final Estimated Qty | H2: L2 till Mar'26 | I2: Supplied Qty | J2: Balance to Supply
C3: 1 | D3: Stubs | E3: EA | F3: 434 | G3: 389 | H3: 434 | I3: 353 | J3: =G3-I3 -> 36
C4: 2 | D4: Towers | E4: EA | F4: 434 | G4: 389 | H4: 216 | I4: 314 | J4: =G4-I4 -> 75
C7: S.No | D7: Activity | E7: UOM | F7: BOQ Qty | G7: Final Estimated Qty | H7: L2 till Feb'26 | I7: Completed till Feb'26 | J7: L2 Mar'26 | K7: Progress in Mar'26 | L7: Cumm L2 till Mar'26 | M7: Cumm. Progress till Mar'26 | N7: Balance | O7: Remarks
C8: 400 kV D/C Samba - Jalandhar TL
C9: 1 | D9: Survey | E9: Km | F9: 143 | G9: 137 | H9: 143 | I9: 136 | L9: =H9+J9 -> 143 | M9: =I9+K9 -> 136 | N9: =G9-M9 -> 1
C10: 2 | D10: Foundation | E10: EA | F10: 434 | G10: 389 | H10: 207 | I10: 202 | J10: 45 | K10: 28 | L10: =H10+J10 -> 252 | M10: =I10+K10 -> 230 | N10: =G10-M10 -> 159 | O10: 19 Gangs
C11: 3 | D11: Tower Erection | E11: EA | F11: 434 | G11: 389 | H11: 125 | I11: 55 | J11: 45 | K11: 48 | L11: =H11+J11 -> 170 | M11: =I11+K11 -> 103 | N11: =G11-M11 -> 286 | O11: 10 Gangs
C12: 4 | D12: Stringing | E12: Km | F12: 143 | G12: 137 | N12: =G12-M12 -> 137
C13: 400kV D/C Samba -Kishenpur TL
C14: 1 | D14: Survey | E14: Km | F14: 33 | G14: 33 | H14: 33 | I14: 33 | L14: =H14+J14 -> 33 | M14: =I14+K14 -> 33
C15: 2 | D15: Foundation | E15: EA | F15: 129 | G15: 116 | H15: 39 | I15: 37 | J15: 11 | K15: 7 | L15: =H15+J15 -> 50 | M15: =I15+K15 -> 44 | N15: =G15-M15 -> 72 | O15: 6 Gangs
C16: 3 | D16: Tower Erection | E16: EA | F16: 129 | G16: 116 | J16: 5 | K16: 2 | L16: =H16+J16 -> 5 | M16: =I16+K16 -> 2 | N16: =G16-M16 -> 114 | O16: 1 Gang
C17: 4 | D17: Stringing | E17: Km | F17: 33 | G17: 33 | N17: =G17-M17 -> 33
C18: LILO-Kisthwar
C19: 1 | D19: Survey | E19: Km | F19: 2 | G19: 3.4 | H19: 2 | I19: 3.4 | L19: =H19+J19 -> 2 | M19: =I19+K19 -> 3.4
C20: 2 | D20: Foundation | E20: EA | F20: 14 | G20: 18 | H20: 14 | L20: =H20+J20 -> 14 | N20: =G20-M20 -> 18 | O20: 3 Gangs
C21: 3 | D21: Tower Erection | E21: EA | F21: 14 | G21: 18 | J21: 2 | L21: =H21+J21 -> 2 | N21: =G21-M21 -> 18
C22: 4 | D22: Stringing | E22: Km | F22: 2 | G22: 3.4 | N22: =G22-M22 -> 3.4
C27: Supply Portion
C28: S.No | D28: Material | E28: UOM | F28: BOQ Qty | G28: Final Estimated Qty | H28: L2 till Mar'26 | I28: Supplied Qty | J28: Balance to Supply
C29: 1 | D29: Stubs | E29: EA | F29: 129 | G29: 116 | H29: 129 | I29: 64 | J29: =G29-I29 -> 52
C30: 2 | D30: Towers | E30: EA | F30: 129 | G30: 116 | H30: 129 | I30: 41 | J30: =G30-I30 -> 75
C32: Service Portion
C33: S.No | D33: Activity | E33: UOM | F33: BOQ Qty | G33: Final Estimated Qty | H33: L2 till Feb'26 | I33: Completed till Feb'26 | J33: L2 Mar'26 | K33: Progress in Mar'26 | L33: Cumm L2 till Mar'26 | M33: Cumm. Progress till Mar'26 | N33: Balance | O33: Remarks
C39: Supply Portion
C40: S.No | D40: Material | E40: UOM | F40: BOQ Qty | G40: Final Estimated Qty | H40: L2 till Mar'26 | I40: Supplied Qty | J40: Balance to Supply
C41: 1 | D41: Stubs | E41: EA | F41: 14 | G41: 18 | H41: 14 | I41: 10 | J41: =G41-I41 -> 8
C42: 2 | D42: Towers | E42: EA | F42: 14 | G42: 18 | H42: 14 | J42: =G42-I42 -> 18
C45: S.No | D45: Activity | E45: UOM | F45: BOQ Qty | G45: Final Estimated Qty | H45: L2 till Feb'26 | I45: Completed till Feb'26 | J45: L2 Mar'26 | K45: Progress in Mar'26 | L45: Cumm L2 till Mar'26 | M45: Cumm. Progress till Mar'26 | N45: Balance | O45: Remarks

Sheet Sheet13
C2: Paticulars | D2: Jammu Portion | E2: Punjab Portion
C3: Line Length (KM) | D3: 83 KM | E3: 90 KM
D4: =83/173 -> 0.47976879 | E4: =90/173 -> 0.52023121

Sheet Sheet15
C2: Supply Portion
C3: S.No | D3: Line | E3: LOA Cr | F3: Billed till date Cr | G3: Balance Cr
C4: 1 | D4: 400 kV Samba- Jalandhar D/C line (Quad) | E4: 155.09 | F4: 88.06 | G4: =E4-F4 -> 67.03
C5: 2 | D5: 400 kV Kishenpur-Samba D/C line (Quad) | E5: 67.47 | F5: =176387266/10^7 -> 17.638727 | G5: =E5-F5 -> 49.831273
C6: 3 | D6: LILO of 400 kV Kishenpur- Dulhasti line (Twin) at Kishtwar S/s | E6: 6.43 | F6: =1439185/10^7 -> 0.1439185 | G6: =E6-F6 -> 6.2860815
C7: Total | E7: =SUM(E4:E6) -> 228.99 | F7: =SUM(F4:F6) -> 105.84265 | G7: =SUM(G4:G6) -> 123.14735
C9: Service Portion
C10: S.No | D10: Line | E10: LOA Cr | F10: Billed till date Cr | G10: Balance Cr
C11: 1 | D11: 400 kV Samba- Jalandhar D/C line (Quad) | E11: 119.32273 | F11: =305299128/10^7 -> 30.529913 | G11: =E11-F11 -> 88.792813
C12: =C11+1 -> 2 | D12: 400 kV Kishenpur-Samba D/C line (Quad) | E12: 50.13038 | F12: =46321408/10^7 -> 4.6321408 | G12: =E12-F12 -> 45.498239 | J12: =88.06+17.64+0.14 -> 105.84
C13: =C12+1 -> 3 | D13: LILO of 400 kV Kishenpur- Dulhasti line (Twin) at Kishtwar S/s | E13: 4.4045142 | G13: =E13-F13 -> 4.4045142
C14: =C13+1 -> 4 | D14: Unit Rate Schedule for Services | E14: 6.4654119 | G14: =E14-F14 -> 6.4654119
C15: =C14+1 -> 5 | D15: ROW Schedule | E15: 5.9322034 | G15: =E15-F15 -> 5.9322034
C16: Total | E16: =SUM(E11:E15) -> 186.25524 | F16: =SUM(F11:F15) -> 35.162054 | G16: =SUM(G11:G15) -> 151.09318
F17: 1.5

Sheet TB401 DPR
A1: Project Progress for TB-401/408,Section-II
A2: 765KV D/C Fategarh-III Beawar Transmission Line | D2: TB-401 | G2: LOA Date | I2: Pkg-G -26.04.23 | L2: Completion Period | N2: 45747 | Q2: Date: | R2: =TODAY() -> 46162
D3: TB-408 | I3: Pkg-F - 11.09.23 | L3: Completion Period | N3: 45747
A4: .
A5: Activity | B5: Qty as per LOA | C5: Qty Received | D5: L2 | F5: Overall Progress | H5: Mar'25 | J5: Balance | K5: Apr'25 | O5: Plan | Q5: Remarks
D6: 45656 | E6: Till Mar-25 | F6: As on date | G6: Till Mar-25 | H6: Plan | I6: Actual | J6: As on date | K6: Plan | L6: WIP | M6: Today comp | N6: Actual | O6: 45536 | P6: 45474
A7: Details Survey | B7: 215 | C7: =C8+C9 -> 189.53 | E7: =E8+E9 -> 203 | F7: =F8+F9 -> 199.841 | G7: =G8+G9 -> 199.841
A8: Pkg-G (Section-II) | C8: 101.1 | E8: =215/2 -> 107.5 | F8: 101.1 | G8: 101.1
A9: Pkg-F (Section-II) | C9: 88.43 | E9: =(65+65+41+20)/2 -> 95.5 | F9: 98.741 | G9: 98.741
A10: Check Survey | B10: 215 | C10: =C11+C12 -> 189.53 | D10: =D11+D12 -> 0 | E10: =E11+E12 -> 203 | F10: =F11+F12 -> 189.526 | G10: =G11+G12 -> 184.552 | H10: =H11+H12 -> 14.88 | I10: =I11+I12 -> 6.08 | J10: =J11+J12 -> 0.004 | ... L10: =L11+L12 -> 0 | N10: =N11+N12 -> 4.974 | O10: =O11+O12 -> 0
A11: Pkg-G (Section-II) | C11: 101.1 | E11: =215/2 -> 107.5 | F11: =G11+N11 -> 101.096 | G11: 101.096 | H11: 6.08 | I11: 6.08 | J11: =C11-G11-N11 -> 0.004
A12: Pkg-F (Section-II) | C12: 88.43 | E12: =(65+65+41+20)/2 -> 95.5 | F12: =G12+N12 -> 88.43 | G12: =79.653+3.803 -> 83.456 | H12: 8.8 | J12: =C12-G12-N12 -> 0 | N12: 4.974
A13: Foundation | B13: 534 | C13: =C14+C15 -> 488 | D13: =D14+D15 -> 0 | E13: =E14+E15 -> 488 | F13: =F14+F15 -> 485 | G13: =G14+G15 -> 485 | H13: =H14+H15 -> 9 | I13: =I14+I15 -> 6 | J13: =J14+J15 -> 3 | ... L13: =L14+L15 -> 3 | N13: =N14+N15 -> 0 | O13: =O14+O15 -> 0 | P13: =P14+P15 -> 0
A14: Pkg-G (Section-II) | C14: 265 | E14: 265 | F14: =G14+N14 -> 265 | G14: 265 | H14: 5 | I14: 5 | J14: =C14-G14-N14 -> 0 | S14: 9649905358 | T14: D S Jangid
A15: Pkg-F (Section-II) | C15: 223 | E15: 223 | F15: =G15+N15 -> 220 | G15: 220 | H15: 4 | I15: 1 | J15: =C15-G15-N15 -> 3 | L15: 3 | S15: 7014675307 | T15: jangid
A16: Gang / Worker | K16: 10/180 | L16: 02/55
A17: Erection | B17: 534 | C17: =C18+C19 -> 488 | D17: =D18+D19 -> 0 | E17: =E18+E19 -> 488 | F17: =F18+F19 -> 367 | G17: =G18+G19 -> 365 | H17: =H18+H19 -> 36 | I17: =I18+I19 -> 24 | J17: =J18+J19 -> 121 | ... P17: =P18+P19 -> 0
A18: Pkg-G (Section-II) | C18: 265 | E18: 265 | F18: =G18+N18 -> 201 | G18: 201 | H18: 20 | I18: 11 | J18: =C18-G18-N18 -> 64 | L18: 0
A19: Pkg-F (Section-II) | C19: 223 | E19: 223 | F19: =G19+N19 -> 166 | G19: 164 | H19: 16 | I19: 13 | J19: =C19-G19-N19 -> 57 | L19: 4 | M19: 1 | N19: 2 | Q19: 70/10 Complete
A20: Gang / Worker | K20: 7/240 | L20: 4/241
A21: Stringing Payout | B21: 215 | C21: =C22+C23 -> 189.53 | D21: =D22+D23 -> 0 | E21: =E22+E23 -> 189.53 | F21: =F22+F23 -> 94.743 | G21: =G22+G23 -> 94.743 | H21: =H22+H23 -> 0 | I21: =I22+I23 -> 9.18 | J21: =J22+J23 -> 94.787 | ... O21: =O22+O23 -> 0 | P21: 15
A22: Pkg-G (Section-II) | C22: 101.1 | E22: 101.1 | F22: =G22+N22 -> 52.284 | G22: 52.284 | J22: =C22-G22-N22 -> 48.816
A23: Pkg-F (Section-II) | C23: 88.43 | E23: 88.43 | F23: =G23+N23 -> 42.459 | G23: 42.459 | I23: 9.18 | J23: =C23-G23-N23 -> 45.971 | L23: 1.881
A24: Gang / Worker | L24: 2/154
A25: Stringing Final sag | B25: 215 | C25: =C26+C27 -> 189.53 | D25: =D26+D27 -> 0 | E25: =E26+E27 -> 189.53 | F25: =F26+F27 -> 88.935 | G25: =G26+G27 -> 88.935 | H25: =H26+H27 -> 0 | I25: =I26+I27 -> 14.161 | J25: =J26+J27 -> 100.595 | ... O25: =O26+O27 -> 0 | P25: 15
A26: Pkg-G (Section-II) | C26: 101.1 | E26: 101.1 | F26: =G26+N26 -> 49.703 | G26: 49.703 | I26: 4.981 | J26: =C26-G26-N26 -> 51.397 | L26: =7.562-4.981 -> 2.581
A27: Pkg-F (Section-II) | C27: 88.43 | E27: 88.43 | F27: =G27+N27 -> 39.232 | G27: 39.232 | I27: 9.18 | J27: =C27-G27-N27 -> 49.198 | L27: 3.227
A28: Gang / Worker | L28: 2/154

Sheet Survey-Summary
B1: PROJECT NAME | C1: INDIGRID - 400kV D/C QUAD WZ-5 SAMBA-JALANDHAR & KISHENPUR-SAMBA TL | Z1: COMP | AA1: APPROVED
B2: START DATE (NOA DATE) | C2: 16-MAY-2025 | Z2: PENDING | AA2: UNDER REVIEW
B3: KEC PROJECT | C3: TB-605 | AA3: PENDING
B4: NAME OF CLIENT | C4: RATLE KIRU POWER TRANSMISSION LIMITED
B5: TITLE | C5: SITE SURVEY STATUS
B7: TEAM FORMATION | H7: CHECK SURVEY SUMMARY (KM)
B8: Portion | C8: SURVEY LEAD | D8: TEAM MEMBERS | E8: MACHINE | F8: LINE NAME | G8: SECTION LENGTH | H8: COMPLETED | I8: BALANCE | J8: SUBMITTED | K8: APPROVED | L8: APPROVAL PENDING | M8: REMARK
B9: Jammu | C9: 1)BIPPAN SHARMA | D9: 2) Shiv Kumar( Asst Surveyor) | E9: DGPS-1 TS-02 | F9: 400kV D/C Jalandar - Samba T/L (GANTRY TO AP 52) | G9: 46.915 | H9: =45.61+0.83 -> 46.44 | I9: =G9-H9 -> 0.475 | J9: =39.202+4.505+2.346 -> 46.053 | K9: 46.053 | L9: =J9-K9 -> 0 | M9: 0.48 km is from Sambha Gantyry to AP 4
D10: 3) Sahil Raj(Asst Surveyor) | F10: 400kV D/C Samba - Kishenpur T/L | G10: 33 | H10: =7.63+0.34+0.29+0.3+0.83+2.257+0.79+0.849+1.044+0.76+0.7+0.4+0.3+0.964+0.684+2+3+4 -> 27.138 | I10: =G10-H10 -> 5.862 | J10: 19.6 | K10: 19.6 | L10: =J10-K10 -> 0 | M10: AP4-AP14, AP24-AP55, AP55-AP70, AP70-AP86,AP95-AP109 C/S Completed AP15-AP24 - Re-routing required due to landsliding (Hold) AP86-AP95 - Hold due to under powerline crossing
D11: 4) Sunil (Survey Helper) | F11: LILO at Kistwar | G11: 2.18 | H11: 2.18 | I11: =G11-H11 -> 0 | J11: 2.18 | K11: 2.18 | L11: =J11-K11 -> 0 | M11: Contour completed 12 Locations out of 13 location AP 11 conturing not done due to ROW since 29th Jul'25
D12: 5) Sanjhi Ram((Survey Helper) | I12: =G12-H12 -> 0 | L12: =J12-K12 -> 0
B13: Punjab | C13: 1)RAJ KAMAL GHOSH | D13: 2) Anupam Basak (Survayor DET) | E13: TS-01 | F13: 400kV D/C Jalandar - Samba T/L ( AP 52-115) | G13: 47.25 | H13: 46.474 | I13: =G13-H13 -> 0.776 | J13: 45.892 | K13: =13.05+32.842 -> 45.892 | L13: =J13-K13 -> 0
D14: 3) Kuldeep singh (supervisor DET) | I14: =G14-H14 -> 0 | L14: =J14-K14 -> 0
D15: 4) Vickey Ghosh (Survey DET) | I15: =G15-H15 -> 0 | L15: =J15-K15 -> 0
D16: 5) Rupak Kumar (Survey Helper) | L16: =J16-K16 -> 0
B17: Punjab | C17: 1)SAGAR MAJHI | D17: 2) Surajit Majhi(Asst Surveyor) | E17: TS-01 | F17: 400kV D/C Jalandar - Samba T/L ( AP 115-187) | G17: 47.805 | H17: =34.985+1.456+2.013+2.516 -> 40.97 | I17: =G17-H17 -> 6.835 | J17: 47.81 | K17: 23.519 | L17: =J17-K17 -> 24.291
D18: 3) Rudra Madhav (supervisor DET) | I18: =G18-H18 -> 0 | L18: =J18-K18 -> 0
D19: 4)Gordhan Ram (supervisor DET) | I19: =G19-H19 -> 0 | L19: =J19-K19 -> 0
I20: =G20-H20 -> 0 | L20: =J20-K20 -> 0
B21: TOTAL (KM) | G21: =SUM(G9:G20) -> 177.15 | H21: =SUM(H9:H20) -> 163.202 | I21: =SUM(I9:I20) -> 13.948 | J21: =SUM(J9:J20) -> 161.535 | K21: =SUM(K9:K20) -> 137.244 | L21: =SUM(L9:L20) -> 24.291 | M21: =SUM(M9:M20) -> 0
G26: 400kV D/C Samba-Jalandhar C/S -Details
G27: S.No | H27: Section | I27: Section | J27: Length | K27: Submitted | L27: Approval Date | M27: Remarks
J28: Km | K28: Date
G29: 1 | H29: AP20-AP30 | I29: Jammu | J29: 10.43 | K29: 45846 | L29: 45854
G30: 2 | H30: AP30-AP41 | I30: Jammu | J30: 13.72 | K30: 45857 | L30: 45862
G31: 3 | H31: AP41-AP51 | I31: Jammu | J31: 15.05 | K31: 45868 | L31: 45873
G32: 4 | H32: AP15-AP20 | I32: Jammu | J32: 4.51 | K32: 45908 | L32: 45909
G33: 5 | H33: AP5-AP15 | I33: Jammu | J33: 2.346 | K33: 45918 | L33: 45930
G34: 5 | H34: AP53-AP66 | I34: Punjab | J34: 11.37 | K34: 45875 | L34: 45894
G35: 6 | H35: AP70-AP84 | I35: Punjab | J35: 11.41 | K35: 45885 | L35: 45900
G36: 7 | H36: AP84-AP96 | I36: Punjab | J36: 10.07 | K36: 45890 | L36: 45894
G37: 8 | H37: AP115-AP123 | I37: Punjab | J37: 6.93 | K37: 45888 | L37: 45904
G38: 9 | H38: AP131-AP140 | I38: Punjab | J38: 10.3 | K38: 45888 | L38: 45904
G39: 10 | H39: AP145-AP153 | I39: Punjab | J39: 6.29 | K39: 45892 | L39: 45904
G40: 11 | H40: AP96-AP115 | I40: Punjab | J40: 9.626 | K40: 45913 | L40: 45961
G41: 12 | H41: AP66-AP70 | I41: Punjab | J41: 3.42 | K41: 45919 | L41: 45961
G42: 13 | H42: AP153-AP175 | I42: Punjab | J42: 12.083 | K42: 45922 | M42: Route diversion in between 168-175 to be finalized
G43: Total | J43: =SUM(J29:J42) -> 127.555
G45: 400kV D/C Kishenpur-Samba C/S -Details
G46: S.No | H46: Section | I46: Section | J46: Length | K46: Submitted | L46: Approval Date | M46: Remarks
J47: Km | K47: Date
G48: 1 | H48: AP95-AP109 | I48: Jammu | J48: 3.13 | K48: 45908 | L48: 45909
G49: =G48+1 -> 2 | H49: AP78-AP86 | I49: Jammu | J49: 1.945 | K49: 45927 | L49: 45930
G50: =G49+1 -> 3 | H50: AP24-AP39 | I50: Jammu | J50: 5.5 | K50: 16-10-2025 30-10-2025 | L50: 45962
G51: =G50+1 -> 4 | H51: AP39-AP55 | I51: Jammu | J51: 5.463 | K51: 45985 | L51: 45994
G52: =G51+1 -> 5 | H52: AP4-AP14 | I52: Jammu | J52: 3.597 | K52: 45994 | L52: 45994
G53: Total | J53: =SUM(J48:J52) -> 19.635
G55: LILO-Kisthewar C/S -Details
G56: S.No | H56: Section | I56: Section | J56: Length | K56: Submitted | L56: Approval Date | M56: Remarks
J57: Km | K57: Date
G58: 1 | H58: TP-Gantry | I58: Kishtwar | J58: 2.18 | K58: 30-08-2025 08-09-2025 27-09-2025 | L58: 45930
G59: Total | J59: =SUM(J58:J58) -> 2.18

Sheet Sheet6
D2: Survey
D3: Line | E3: Portion | F3: Scope | G3: Completed | H3: Submitted | I3: Approved
D4: S-J | E4: Jammu | F4: 46.92 | G4: 46.44 | H4: 46.44 | I4: 46.44
D5: S-J | E5: Punjab | F5: 95.06 | G5: 95.06 | H5: 84.936 | I5: 72.85
D6: K-S | F6: 33.103 | G6: 23.393 | H6: 16.04 | I6: 10.6
D7: LILO | F7: 2.18 | G7: 2.18 | H7: 2.18 | I7: 2.18
D8: Total | F8: =SUM(F4:F7) -> 177.263 | G8: =SUM(G4:G7) -> 167.073 | H8: =SUM(H4:H7) -> 149.596 | I8: =SUM(I4:I7) -> 132.07
F10: 16.04 | J10: 10.58
F11: 45.892 | J11: 45.892
F12: 46.06 | J12: 46.06
F13: 20.674 | G13: 18.37 | J13: 20.674
F14: 12.08
F15: 2.18
J16: =66.566+6.29 -> 72.856

Sheet Approved Survey
A1: KEC INTERNATIONAL LIMITED
A2: 400 kV Samba- Jalandhar D/C Line(Quad) - Wind Zone - 5 | H2: 400 kV Samba- Kishenpur D/C Line(Quad) - Wind Zone - 5
A3: Approved Check Survey Sections | H3: Approved Check Survey Sections
A4: S.No | B4: Portion | C4: Section | D4: Length Km | H4: S.No | I4: Section | J4: Length Km
A5: 1 | B5: Jammu | C5: AP5-AP6 | D5: =119.059/1000 -> 0.119059 | H5: 1 | I5: AP78-AP86 | J5: 1.945
A6: =A5+1 -> 2 | B6: Jammu | C6: AP6-AP7 | D6: =92.496/1000 -> 0.092496 | H6: 2 | I6: AP95-AP109 | J6: 3.13
A7: =A6+1 -> 3 | B7: Jammu | C7: AP7-AP8 | D7: =134.988/1000 -> 0.134988 | H7: 3 | I7: AP24-AP39 | J7: 5.5
A8: =A7+1 -> 4 | B8: Jammu | C8: AP8-AP9 | D8: =365.176/1000 -> 0.365176 | H8: Total | J8: =SUM(J5:J7) -> 10.575
A9: =A8+1 -> 5 | B9: Jammu | C9: AP9-AP10 | D9: =236.697/1000 -> 0.236697
A10: =A9+1 -> 6 | B10: Jammu | C10: AP10-AP11 | D10: =213.152/1000 -> 0.213152 | H10: LILO-Kishtwar
A11: =A10+1 -> 7 | B11: Jammu | C11: AP11-AP12 | D11: =206.593/1000 -> 0.206593 | H11: Approved Check Survey Sections
A12: =A11+1 -> 8 | B12: Jammu | C12: AP12-AP13 | D12: =289.862/1000 -> 0.289862 | H12: S.No | I12: Section | J12: Length Km
A13: =A12+1 -> 9 | B13: Jammu | C13: AP13-AP14 | D13: =402.938/1000 -> 0.402938 | H13: 1 | I13: AP1-TP | J13: 2.18
A14: =A13+1 -> 10 | B14: Jammu | C14: AP14-AP15 | D14: =284.883/1000 -> 0.284883
A15: =A14+1 -> 11 | B15: Jammu | C15: AP15-AP16 | D15: =1673.439/1000 -> 1.673439
A16: =A15+1 -> 12 | B16: Jammu | C16: AP16-AP17 | D16: =285.948/1000 -> 0.285948
A17: =A16+1 -> 13 | B17: Jammu | C17: AP17-AP18 | D17: =401.159/1000 -> 0.401159
A18: =A17+1 -> 14 | B18: Jammu | C18: AP18-AP19 | D18: =1055.218/1000 -> 1.055218
A19: =A18+1 -> 15 | B19: Jammu | C19: AP19-AP20 | D19: =1088.747/1000 -> 1.088747
A20: =A19+1 -> 16 | B20: Jammu | C20: AP20-AP21 | D20: =485.93/1000 -> 0.48593
A21: =A20+1 -> 17 | B21: Jammu | C21: AP21-AP22 | D21: =712.337/1000 -> 0.712337
A22: =A21+1 -> 18 | B22: Jammu | C22: AP22-AP23 | D22: =1177.079/1000 -> 1.177079
A23: =A22+1 -> 19 | B23: Jammu | C23: AP23-AP24 | D23: =2454.951/1000 -> 2.454951
A24: =A23+1 -> 20 | B24: Jammu | C24: AP24-AP25 | D24: =366.044/1000 -> 0.366044
A25: =A24+1 -> 21 | B25: Jammu | C25: AP25-AP26 | D25: =1028.029/1000 -> 1.028029
A26: =A25+1 -> 22 | B26: Jammu | C26: AP26-AP27 | D26: =442.371/1000 -> 0.442371
A27: =A26+1 -> 23 | B27: Jammu | C27: AP27-AP28 | D27: =739.739/1000 -> 0.739739
A28: =A27+1 -> 24 | B28: Jammu | C28: AP28-AP29 | D28: =445.991/1000 -> 0.445991
A29: =A28+1 -> 25 | B29: Jammu | C29: AP29-AP30 | D29: =2573.629/1000 -> 2.573629
A30: =A29+1 -> 26 | B30: Jammu | C30: AP30-AP31 | D30: =2514.73/1000 -> 2.51473
A31: =A30+1 -> 27 | B31: Jammu | C31: AP31-AP32 | D31: =2374.48/1000 -> 2.37448
A32: =A31+1 -> 28 | B32: Jammu | C32: AP32-AP33 | D32: =836.984/1000 -> 0.836984
A33: =A32+1 -> 29 | B33: Jammu | C33: AP33-AP34 | D33: =967.8/1000 -> 0.9678
A34: =A33+1 -> 30 | B34: Jammu | C34: AP34-AP35 | D34: =819.907/1000 -> 0.819907
A35: =A34+1 -> 31 | B35: Jammu | C35: AP35-AP36 | D35: =820.234/1000 -> 0.820234
A36: =A35+1 -> 32 | B36: Jammu | C36: AP36-AP37 | D36: =439.8/1000 -> 0.4398
A37: =A36+1 -> 33 | B37: Jammu | C37: AP37-AP38 | D37: =1203.4/1000 -> 1.2034
A38: =A37+1 -> 34 | B38: Jammu | C38: AP38-AP39 | D38: =775.272/1000 -> 0.775272
A39: =A38+1 -> 35 | B39: Jammu | C39: AP39-AP40 | D39: =1209.893/1000 -> 1.209893
A40: =A39+1 -> 36 | B40: Jammu | C40: AP40-AP41 | D40: =1760.473/1000 -> 1.760473
A41: =A40+1 -> 37 | B41: Jammu | C41: AP41-AP42 | D41: =212.44/1000 -> 0.21244
A42: =A41+1 -> 38 | B42: Jammu | C42: AP42-AP43 | D42: =1361.04/1000 -> 1.36104
A43: =A42+1 -> 39 | B43: Jammu | C43: AP43-AP44 | D43: =1911.9/1000 -> 1.9119
A44: =A43+1 -> 40 | B44: Jammu | C44: AP44-AP45 | D44: =1474.69/1000 -> 1.47469
A45: =A44+1 -> 41 | B45: Jammu | C45: AP45-AP46 | D45: =1079.5/1000 -> 1.0795
A46: =A45+1 -> 42 | B46: Jammu | C46: AP46-AP47 | D46: =2216.45/1000 -> 2.21645
A47: =A46+1 -> 43 | B47: Jammu | C47: AP47-AP48 | D47: =1360.36/1000 -> 1.36036
A48: =A47+1 -> 44 | B48: Jammu | C48: AP48-AP49 | D48: =371.5/1000 -> 0.3715
A49: =A48+1 -> 45 | B49: Jammu | C49: AP49-AP50 | D49: =203.3/1000 -> 0.2033
A50: =A49+1 -> 46 | B50: Jammu | C50: AP50-AP50A | D50: =409.91/1000 -> 0.40991
A51: =A50+1 -> 47 | B51: Jammu | C51: AP50A-AP51 | D51: =4450.9/1000 -> 4.4509
A52: =A51+1 -> 48 | B52: Punjab | C52: AP53-AP54 | D52: =416.66/1000 -> 0.41666
A53: =A52+1 -> 49 | B53: Punjab | C53: AP54-AP55 | D53: =389.29/1000 -> 0.38929
A54: =A53+1 -> 50 | B54: Punjab | C54: AP55-AP56 | D54: =793.45/1000 -> 0.79345
A55: =A54+1 -> 51 | B55: Punjab | C55: AP56-AP57 | D55: =1906.1/1000 -> 1.9061
A56: =A55+1 -> 52 | B56: Punjab | C56: AP57-AP58 | D56: =982.37/1000 -> 0.98237
A57: =A56+1 -> 53 | B57: Punjab | C57: AP58-AP59 | D57: =406.44/1000 -> 0.40644
A58: =A57+1 -> 54 | B58: Punjab | C58: AP59-AP60 | D58: =788.04/1000 -> 0.78804
A59: =A58+1 -> 55 | B59: Punjab | C59: AP60-AP61 | D59: =757.58/1000 -> 0.75758
A60: =A59+1 -> 56 | B60: Punjab | C60: AP61-AP62 | D60: =563.92/1000 -> 0.56392
A61: =A60+1 -> 57 | B61: Punjab | C61: AP62-AP63 | D61: =1081.23/1000 -> 1.08123
A62: =A61+1 -> 58 | B62: Punjab | C62: AP63-AP64 | D62: =450.86/1000 -> 0.45086
A63: =A62+1 -> 59 | B63: Punjab | C63: AP64-AP65 | D63: =602.84/1000 -> 0.60284
A64: =A63+1 -> 60 | B64: Punjab | C64: AP65-AP66 | D64: =2228.49/1000 -> 2.22849
A65: =A64+1 -> 61 | B65: Punjab | C65: AP70-AP71 | D65: =1598.955/1000 -> 1.598955
A66: =A65+1 -> 62 | B66: Punjab | C66: AP71-AP72 | D66: =1666.222/1000 -> 1.666222
A67: =A66+1 -> 63 | B67: Punjab | C67: AP72-AP73 | D67: =809.571/1000 -> 0.809571
A68: =A67+1 -> 64 | B68: Punjab | C68: AP73-AP74 | D68: =406.688/1000 -> 0.406688
A69: =A68+1 -> 65 | B69: Punjab | C69: AP74-AP75 | D69: =316.253/1000 -> 0.316253
A70: =A69+1 -> 66 | B70: Punjab | C70: AP75-AP76 | D70: =248.423/1000 -> 0.248423
A71: =A70+1 -> 67 | B71: Punjab | C71: AP76-AP77 | D71: =1681.454/1000 -> 1.681454
A72: =A71+1 -> 68 | B72: Punjab | C72: AP77-AP78 | D72: =1630.396/1000 -> 1.630396
A73: =A72+1 -> 69 | B73: Punjab | C73: AP78-AP79 | D73: =320.743/1000 -> 0.320743
A74: =A73+1 -> 70 | B74: Punjab | C74: AP79-AP80 | D74: =242.225/1000 -> 0.242225
A75: =A74+1 -> 71 | B75: Punjab | C75: AP80-AP81 | D75: =839.249/1000 -> 0.839249
A76: =A75+1 -> 72 | B76: Punjab | C76: AP81-AP82 | D76: =242.663/1000 -> 0.242663
A77: =A76+1 -> 73 | B77: Punjab | C77: AP82-AP83 | D77: =1149.152/1000 -> 1.149152
A78: =A77+1 -> 74 | B78: Punjab | C78: AP83-AP84 | D78: =251.516/1000 -> 0.251516
A79: =A78+1 -> 75 | B79: Punjab | C79: AP84-AP85 | D79: =445.126/1000 -> 0.445126
A80: =A79+1 -> 76 | B80: Punjab | C80: AP85-AP86 | D80: =838.553/1000 -> 0.838553
A81: =A80+1 -> 77 | B81: Punjab | C81: AP86-AP87 | D81: =836.764/1000 -> 0.836764
A82: =A81+1 -> 78 | B82: Punjab | C82: AP87-AP88 | D82: =1185.42/1000 -> 1.18542
A83: =A82+1 -> 79 | B83: Punjab | C83: AP88-AP89 | D83: =211.063/1000 -> 0.211063
A84: =A83+1 -> 80 | B84: Punjab | C84: AP89-AP90 | D84: =618.229/1000 -> 0.618229
A85: =A84+1 -> 81 | B85: Punjab | C85: AP90-AP91 | D85: =1181.01/1000 -> 1.18101
A86: =A85+1 -> 82 | B86: Punjab | C86: AP91-AP92 | D86: =247.685/1000 -> 0.247685
A87: =A86+1 -> 83 | B87: Punjab | C87: AP92-AP93 | D87: =1455.156/1000 -> 1.455156
A88: =A87+1 -> 84 | B88: Punjab | C88: AP93-AP94 | D88: =889.075/1000 -> 0.889075
A89: =A88+1 -> 85 | B89: Punjab | C89: AP94-AP95 | D89: =411.542/1000 -> 0.411542
A90: =A89+1 -> 86 | B90: Punjab | C90: AP95-AP96 | D90: =1751.019/1000 -> 1.751019
A91: =A90+1 -> 87 | B91: Punjab | C91: AP115-AP116 | D91: =751.41/1000 -> 0.75141
A92: =A91+1 -> 88 | B92: Punjab | C92: AP116-AP117 | D92: =515.47/1000 -> 0.51547
A93: =A92+1 -> 89 | B93: Punjab | C93: AP117-AP118 | D93: =1409.68/1000 -> 1.40968
A94: =A93+1 -> 90 | B94: Punjab | C94: AP118-AP119 | D94: =634.36/1000 -> 0.63436
A95: =A94+1 -> 91 | B95: Punjab | C95: AP119-AP120 | D95: =518.18/1000 -> 0.51818
A96: =A95+1 -> 92 | B96: Punjab | C96: AP120-AP121 | D96: =1212.37/1000 -> 1.21237
A97: =A96+1 -> 93 | B97: Punjab | C97: AP121-AP122 | D97: =1136.859/1000 -> 1.136859
A98: =A97+1 -> 94 | B98: Punjab | C98: AP122-AP123 | D98: =753.546/1000 -> 0.753546
A99: =A98+1 -> 95 | B99: Punjab | C99: AP131-AP132 | D99: =2841.988/1000 -> 2.841988
A100: =A99+1 -> 96 | B100: Punjab | C100: AP132-AP133 | D100: =816.077/1000 -> 0.816077
...

Sheet Approved CS J-S Line
A1: Line: 400 kV D/C Quad Jalandhar-Samba TL
A2: Approved Check Survey Tower Schedule
A3: AS PER DETAIL SURVEY | J3: AS PER CHECK SURVEY
A4: Sr. No. | B4: Tower No. | C4: Type of Tower | D4: Span Length (m) | E4: Section Length (m) | F4: Angle of Deviation | G4: UTM Coordinates | J4: Sr. No. | K4: Tower No. | L4: Type of Tower | M4: Raised Chimney | Q4: Leg Extension | U4: Span Length (m) | V4: Section Length (m) | W4: Reduced Level | X4: Angle of Deviation | Y4: UTM Coordinates | AA4: Crossing/Remarks
G5: Easting | H5: Northing | M5: LEG A | N5: LEG B | O5: LEG C | P5: LEG D | Q5: LEG A | R5: LEG B | S5: LEG C | T5: LEG D | Y5: Easting | Z5: Northing
A6: 1 | B6: AP 5/0 | C6: DD+18 | E6: 0 | F6: 47°01'57"L | G6: 516661.84 | H6: 3596578.1 | J6: 1 | K6: AP 5/0 | L6: DD+0 | M6: 0 | N6: 0 | O6: 0 | P6: 0 | Q6: 0 | R6: 0 | S6: 0 | T6: 0 | V6: 0 | W6: 384.3 | X6: 47°01'59"LT | Y6: 516472.78 | Z6: 3598642.7
D7: 119.059 | U7: 119.059 | AA7: 2 nos 11 KV,Road Crossing
A8: =A6+1 -> 2 | B8: AP 6/0 | C8: DA+0 | E8: =E6+D7 -> 119.059 | F8: 40°54'41"R | G8: 516805.33 | H8: 3596183.2 | J8: =J6+1 -> 2 | K8: AP 6/0 | L8: DD+9 | M8: 0 | N8: 0 | O8: 0 | P8: 0 | Q8: 0 | R8: 0 | S8: 0 | T8: 0 | V8: =U7 -> 119.059 | W8: 384.202 | X8: 40°54'42"RT | Y8: 516557.85 | Z8: 3598559.4
D9: 92.496 | U9: 92.496
A10: =A8+1 -> 3 | B10: AP 7/0 | C10: DA+0 | E10: =E8+D9 -> 211.555 | F10: 47°08'48"L | G10: 516948.8 | H10: 3595788.3 | J10: =J8+1 -> 3 | K10: AP 7/0 | L10: DD+25 | M10: 0 | N10: 0 | O10: 0 | P10: 0 | Q10: 0 | R10: 0 | S10: 0 | T10: 0 | V10: =V8+U9 -> 211.555 | W10: 382.166 | X10: 47°08'48"LT | Y10: 516565.42 | Z10: 3598467.2
D11: 134.989 | U11: 134.988 | AA11: 400 KV(JAL-SAM) line Crossing
A12: =A10+1 -> 4 | B12: AP 8/0 | C12: DA+6 | E12: =E10+D11 -> 346.544 | F12: 41°15'08"R | G12: 517087.16 | H12: 3595407.5 | J12: =J10+1 -> 4 | K12: AP 8/0 | L12: DD+25 | M12: 0 | N12: 0 | O12: 0 | P12: 0 | Q12: 0 | R12: 0 | S12: 0 | T12: 0 | V12: =V10+U11 -> 346.543 | W12: 377.89 | X12: 41°15'08"RT | Y12: 516671.56 | Z12: 3598383.8
D13: 365.175 | U13: 365.176 | AA13: Nalla Crossing
A14: =A12+1 -> 5 | B14: AP 9/0 | C14: DC+6 | E14: =E12+D13 -> 711.719 | F14: 37°05'47"R | G14: 517233.3 | H14: 3595005.3 | J14: =J12+1 -> 5 | K14: AP 9/0 | L14: DD+9 | M14: 0 | N14: 0 | O14: 0 | P14: 0 | Q14: 0 | R14: 0 | S14: 0 | T14: 0 | V14: =V12+U13 -> 711.719 | W14: 373.28 | X14: 37°05'47"RT | Y14: 516738.65 | Z14: 3598024.8
D15: 236.697 | U15: 236.697 | AA15: 2 nos 25KV,Railway Crossing
A16: =A14+1 -> 6 | B16: AP 10/0 | C16: DC+3 | E16: =E14+D15 -> 948.416 | F16: 20°40'31"L | G16: 517425.65 | H16: 3594793.7 | J16: =J14+1 -> 6 | K16: AP 10/0 | L16: DD+9 | M16: 0 | N16: 0 | O16: 0 | P16: 0 | Q16: 0 | R16: 0 | S16: 0 | T16: 0 | V16: =V14+U15 -> 948.416 | W16: 364.063 | X16: 20°40'31"LT | Y16: 516633 | Z16: 3597813
D17: 213.252 | U17: 213.252
A18: =A16+1 -> 7 | B18: AP 11/0 | C18: DC+3 | E18: =E16+D17 -> 1161.668 | F18: 51°34'01"R | G18: 517777.57 | H18: 3594601.2 | J18: =J16+1 -> 7 | K18: AP 11/0 | L18: DD+25 | M18: 0 | N18: 0 | O18: 0 | P18: 0 | Q18: 0 | R18: 0 | S18: 0 | T18: 0 | V18: =V16+U17 -> 1161.668 | W18: 361.99 | X18: 51°34'02"RT | Y18: 516611.32 | Z18: 3597600.9
D19: 206.592 | U19: 206.593 | AA19: Cannal,11 KV,Road,400 kv(JAL-SAM) Line Crossing
A20: =A18+1 -> 8 | B20: AP 12/0 | C20: DA+0 | E20: =E18+D19 -> 1368.26 | F20: 47°50'12"L | G20: 517986.28 | H20: 3594326.4 | J20: =J18+1 -> 8 | K20: AP 12/0 | L20: DD+30 | M20: 0 | N20: 0 | O20: 0 | P20: 0 | Q20: 0 | R20: 0 | S20: 0 | T20: 0 | V20: =V18+U19 -> 1368.261 | W20: 353.883 | X20: 47°50'13"LT | Y20: 516437.27 | Z20: 3597489.6
D21: 289.862 | U21: 289.862 | AA21: 220 kv(HRN-SAM) Line Crossing
A22: =A20+1 -> 9 | B22: AP 13/0 | C22: DA+0 | E22: =E20+D21 -> 1658.122 | F22: 39°08'44"L | G22: 518204.06 | H22: 3594039.8 | J22: =J20+1 -> 9 | K22: AP 13/0 | L22: DD+25 | M22: 0 | N22: 0 | O22: 0 | P22: 0 | Q22: 1.5 | R22: 1.5 | S22: 0 | T22: 0 | V22: =V20+U21 -> 1658.123 | W22: 348.38 | X22: 39°08'44"LT | Y22: 516389.11 | Z22: 3597203.7
D23: 402.938 | U23: 402.938 | AA23: Cannal,Cart Track Crossing
A24: =A22+1 -> 10 | B24: AP 14/0 | C24: DC+0 | E24: =E22+D23 -> 2061.06 | F24: 14°33'47"R | G24: 518415.92 | H24: 3593760.9 | J24: =J22+1 -> 10 | K24: AP 14/0 | L24: DB+9 | M24: 0 | N24: 0 | O24: 0 | P24: 0 | Q24: 0 | R24: 0 | S24: 2 | T24: 0 | V24: =V22+U23 -> 2061.061 | W24: 345.17 | X24: 14°33'47"RT | Y24: 516588.02 | Z24: 3596853.3
D25: 284.883 | U25: 284.883 | AA25: River,220 KV(BAR-HRN)Line Crossing
A26: =A24+1 -> 11 | B26: AP 15/0 | C26: DA+0 | E26: =E24+D25 -> 2345.943 | F26: 4°57'01"L | G26: 518741.12 | H26: 3593584.5 | J26: =J24+1 -> 11 | K26: AP 15/0 | L26: DD+18 | M26: 0 | N26: 0 | O26: 0 | P26: 0 | Q26: 1.5 | R26: 0 | S26: 0 | T26: 0 | V26: =V24+U25 -> 2345.944 | W26: 341.282 | X26: 4°57'01"LT | Y26: 516661.84 | Z26: 3596578.1
D27: 420.199 | U27: 412.199 | AA27: Canal crosssing
A28: =A26+1 -> 12 | B28: 15/1 | C28: DA+0 | G28: 516805.33 | H28: 3596183.2 | J28: =J26+1 -> 12 | K28: 15/1 | L28: DA+0 | M28: 0 | N28: 0 | O28: 0 | P28: 0 | Q28: 0 | R28: 0 | S28: 0 | T28: 0 | W28: 337.118 | Y28: 516802.6 | Z28: 3596190.7
D29: 420.127 | U29: 428.128
A30: =A28+1 -> 13 | B30: 15/2 | C30: DA+0 | G30: 516948.8 | H30: 3595788.3 | J30: =J28+1 -> 13 | K30: 15/2 | L30: DA+0 | M30: 0 | N30: 0 | O30: 0 | P30: 0 | Q30: 0 | R30: 0 | S30: 0 | T30: 0 | W30: 331.591 | Y30: 516948.8 | Z30: 3595788.3
D31: 405.152 | U31: 405.152 | AA31: Road and LT Line crossing
A32: =A30+1 -> 14 | B32: 15/3 | C32: DA+6 | G32: 517087.16 | H32: 3595407.5 | J32: =J30+1 -> 14 | K32: 15/3 | L32: DA+9 | M32: 0 | N32: 0 | O32: 0 | P32: 0 | Q32: 0 | R32: 0 | S32: 0 | T32: 0 | W32: 327.063 | Y32: 517087.16 | Z32: 3595407.5
D33: 427.96 | U33: 427.96
A34: =A32+1 -> 15 | B34: AP 16/0 | C34: DC+6 | E34: =D27+D29+D31+D33 -> 1673.438 | F34: 22°18'18"LT | G34: 517233.3 | H34: 3595005.3 | J34: =J32+1 -> 15 | K34: AP 16/0 | L34: DC+0 | M34: 0 | N34: 0 | O34: 0 | P34: 0 | Q34: 0 | R34: 0 | S34: 0 | T34: 0 | V34: =U27+U29+U31+U33 -> 1673.439 | W34: 320.406 | X34: 22°18'18"LT | Y34: 517233.3 | Z34: 3595005.3
D35: 285.948 | U35: 285.948 | AA35: 11 KV,Road,LTLine Crossing
A36: =A34+1 -> 16 | B36: AP 17/0 | C36: DC+3 | E36: =D35 -> 285.948 | F36: 19°02'28"LT | G36: 517425.65 | H36: 3594793.7 | J36: =J34+1 -> 16 | K36: AP 17/0 | L36: DC+3 | M36: 0 | N36: 0 | O36: 0 | P36: 0 | Q36: 0 | R36: 0 | S36: 0 | T36: 0 | V36: =U35 -> 285.948 | W36: 317.232 | X36: 19°02'28"LT | Y36: 517425.65 | Z36: 3594793.7 | AA36: LTLine to be shifted
D37: 401.159 | U37: 401.159 | AA37: 11KV,66KV,Road,LTLine Crossing
A38: =A36+1 -> 17 | B38: AP 18/0 | C38: DC+3 | E38: =D37 -> 401.159 | F38: 24°05'21"RT | G38: 517777.57 | H38: 3594601.2 | J38: =J36+1 -> 17 | K38: AP 18/0 | L38: DC+0 | M38: 0 | N38: 0 | O38: 0 | P38: 0 | Q38: 0 | R38: 0 | S38: 0 | T38: 0 | V38: =U37 -> 401.159 | W38: 315.046 | X38: 24°05'21"RT | Y38: 517777.57 | Z38: 3594601.2
D39: 345 | U39: 345 | AA39: LTLine Crossing
A40: =A38+1 -> 18 | B40: 18/1 | C40: DA+0 | G40: 517986.28 | H40: 3594326.4 | J40: =J38+1 -> 18 | K40: 18/1 | L40: DA+0 | M40: 0 | N40: 0 | O40: 0 | P40: 0 | Q40: 0 | R40: 0 | S40: 0 | T40: 0 | W40: 316.217 | Y40: 517986.28 | Z40: 3594326.4
D41: 360 | U41: 360.001
A42: =A40+1 -> 19 | B42: 18/2 | C42: DA+0 | G42: 518204.06 | H42: 3594039.8 | J42: =J40+1 -> 19 | K42: 18/2 | L42: DA+0 | M42: 0 | N42: 0 | O42: 0 | P42: 0 | Q42: 0 | R42: 0 | S42: 0 | T42: 0 | W42: 317.215 | Y42: 518204.06 | Z42: 3594039.8
D43: 350.217 | U43: 350.217 | AA43: Canal crosssing
A44: =A42+1 -> 20 | B44: AP 19/0 | C44: DC+0 | E44: =D39+D41+D43 -> 1055.217 | F44: 24°17'20"LT | G44: 518415.92 | H44: 3593760.9 | J44: =J42+1 -> 20 | K44: AP 19/0 | L44: DC+0 | M44: 0 | N44: 0 | O44: 0 | P44: 0 | Q44: 0 | R44: 0 | S44: 0 | T44: 0 | V44: =U39+U41+U43 -> 1055.218 | W44: 317.08 | X44: 24°17'20"LT | Y44: 518415.92 | Z44: 3593760.9
D45: 370 | U45: 369.999 | AA45: LTLine,Road Crossing
A46: =A44+1 -> 21 | B46: 19/1 | C46: DA+0 | G46: 518741.12 | H46: 3593584.5 | J46: =J44+1 -> 21 | K46: 19/1 | L46: DA+0 | M46: 0 | N46: 0 | O46: 0 | P46: 0 | Q46: 0 | R46: 0 | S46: 0 | T46: 0 | W46: 318.753 | Y46: 518741.12 | Z46: 3593584.5
D47: 360 | U47: 360 | AA47: Canal,nalla crosssing
A48: =A46+1 -> 22 | B48: 19/2 | C48: DA+0 | G48: 519057.54 | H48: 3593412.7 | J48: =J46+1 -> 22 | K48: 19/2 | L48: DA+0 | M48: 0 | N48: 0 | O48: 0 | P48: 0 | Q48: 0 | R48: 0 | S48: 0 | T48: 0 | W48: 318.952 | Y48: 519057.54 | Z48: 3593412.7
D49: 358.747 | U49: 358.748 | AA49: Road and LT Line crossing
A50: =A48+1 -> 23 | B50: 20/0 | C50: DB+6 | E50: 0 | G50: 519372.85 | H50: AP24-AP39 | J50: =J48+1 -> 23 | K50: 20/0 | L50: DB+6 | M50: Comments by RKPTL , need to be rectified by M/s. KEC | N50: 1.5 | O50: 1.5 | P50: 1.5 | V50: 0 | W50: 320.649 | Y50: 519372.85 | Z50: 3593241.6
D51: 485.93 | U51: 485.93 | AA51: River Crossing
A52: =A50+1 -> 24 | B52: 21/0 | C52: DD+6 | E52: =D51 -> 485.93 | F52: 39° 17' 49"RT | G52: 519776.1 | H52: 3592970.5 | J52: =J50+1 -> 24 | K52: 21/0 | L52: DD+6 | M52: 1.5 | N52: 1.5 | O52: 1.5 | P52: 1.5 | V52: =U51 -> 485.93 | W52: 319.74 | X52: 39°17'49" RT | Y52: 519776.1 | Z52: 3592970.5
D53: 325 | U53: 325 | AA53: 2 nos LT Line,Cart Track
A54: =A52+1 -> 25 | B54: 21/1 | C54: DA+0 | G54: 519869.96 | H54: 3592659.3 | J54: =J52+1 -> 25 | K54: 21/1 | L54: DA+0 | M54: 0 | N54: 0 | O54: 0 | P54: 0 | W54: 316.858 | Y54: 519869.96 | Z54: 3592659.3 | AA54: LT Line to be shifted
D55: 387.337 | U55: 387.337 | AA55: 11 kv Line Crossing
A56: =A54+1 -> 26 | B56: 22/0 | C56: DC+3 | E56: =D53+D55 -> 712.337 | F56: 15°58'43"LT | G56: 519981.82 | H56: 3592288.5 | J56: =J54+1 -> 26 | K56: 22/0 | L56: DC+3 | M56: 0 | N56: 0 | O56: 0 | P56: 0 | V56: =U53+U55 -> 712.337 | W56: 312.93 | X56: 15°58'43"LT | Y56: 519981.82 | Z56: 3592288.5
D57: 390 | U57: 390 | AA57: 3nos LT Line,Road,11 KV Crossing
A58: =A56+1 -> 27 | B58: 22/1 | C58: DA+3 | G58: 520192.88 | H58: 3591960.6 | J58: =J56+1 -> 27 | K58: 22/1 | L58: DA+3 | M58: 0 | N58: 0 | O58: 0 | P58: 0 | W58: 310.637 | Y58: 520192.88 | Z58: 3591960.6
D59: 388.629 | U59: 388.629 | AA59: LT Line crosiing
A60: =A58+1 -> 28 | B60: 22/2 | C60: DA+3 | G60: 520403.2 | H60: 3591633.8 | J60: =J58+1 -> 28 | K60: 22/2 | L60: DA+3 | M60: 0 | N60: 0 | O60: 0 | P60: 0 | W60: 306.671 | Y60: 520403.2 | Z60: 3591633.8
D61: 398.45 | U61: 398.45 | AA61: 2 nos LT Line Crossing
A62: =A60+1 -> 29 | B62: 23/0 | C62: DB+0 | E62: =D57+D59+D61 -> 1177.079 | F62: 9°30'47"LT | G62: 520618.83 | H62: 3591298.7 | J62: =J60+1 -> 29 | K62: 23/0 | L62: DB+0 | M62: 0 | N62: 0 | O62: 0 | P62: 0 | V62: =U57+U59+U61 -> 1177.079 | W62: 303.472 | X62: 9°30'47"LT | Y62: 520618.83 | Z62: 3591298.7
D63: 419.999 | U63: 435.999 | AA63: Road and LT Line Crossing
A64: =A62+1 -> 30 | B64: 23/1 | C64: DA+6 | G64: 520901.38 | H64: 3590987.9 | J64: =J62+1 -> 30 | K64: 23/1 | L64: DA+6 | M64: 0 | N64: 0 | O64: 0 | P64: 0 | W64: 299.951 | Y64: 520912.14 | Z64: 3590976.1
D65: 400 | U65: 384 | AA65: Road,LT Line,11 KV Line Crossing
A66: =A64+1 -> 31 | B66: 23/2 | C66: DA+3 | G66: 521170.46 | H66: 3590692 | J66: =J64+1 -> 31 | K66: 23/2 | L66: DA+3 | M66: 0 | N66: 0 | O66: 0 | P66: 0 | W66: 296.476 | Y66: 521170.46 | Z66: 3590692
D67: 420 | U67: 420 | AA67: LT Line Crossing
A68: =A66+1 -> 32 | B68: 23/3 | C68: DA+3 | G68: 521453.01 | H68: 3590381.2 | J68: =J66+1 -> 32 | K68: 23/3 | L68: DA+3 | M68: 0 | N68: 0 | O68: 0 | P68: 0 | W68: 293.587 | Y68: 521453.01 | Z68: 3590381.2
D69: 410 | U69: 410 | AA69: 2 nos LT Line Crossing
A70: =A68+1 -> 33 | B70: 23/4 | C70: DA+3 | G70: 521728.82 | H70: 3590077.9 | J70: =J68+1 -> 33 | K70: 23/4 | L70: DA+3 | M70: 0 | N70: 0 | O70: 0 | P70: 0 | W70: 290.264 | Y70: 521728.82 | Z70: 3590077.9
D71: 407.25 | U71: 407.25 | AA71: 2 LT Line,Nalla Crossing
A72: =A70+1 -> 34 | B72: 23/5 | C72: DA+3 | G72: 522002.79 | H72: 3589776.6 | J72: =J70+1 -> 34 | K72: 23/5 | L72: DA+3 | M72: 0 | N72: 0 | O72: 0 | P72: 0 | W72: 286.229 | Y72: 522002.79 | Z72: 3589776.6
D73: 397.702 | U73: 397.702 | AA73: 11 KV,Nalla,Road Crossing
A74: =A72+1 -> 35 | B74: 24/0 | C74: DC+0 | E74: =D63+D65+D67+D69+D71+D73 -> 2454.951 | F74: 26° 06' 39"RT | G74: 522270.33 | H74: 3589482.3 | J74: =J72+1 -> 35 | K74: 24/0 | L74: DC+3 | M74: 0 | N74: 0 | O74: 0 | P74: 0 | V74: =U63+U65+U67+U69+U71+U73 -> 2454.951 | W74: 284.901 | X74: 26°6'39"RT | Y74: 522270.33 | Z74: 3589482.3
D75: 310.147 | U75: 366.004 | AA75: 2 nos LT Line, Road Crossing
A76: =A74+1 -> 36 | B76: 25/0 | C76: DD+0 | E76: =D75 -> 310.147 | F76: 35° 11' 52"LT | G76: 522356.69 | H76: 3589184.4 | J76: =J74+1 -> 36 | K76: 25/0 | L76: DD+0 | M76: 0 | N76: 0 | O76: 0 | P76: 0 | V76: =U75 -> 366.004 | W76: 282.934 | X76: 36°50'56"LT | Y76: 522372.24 | Z76: 3589130.8
D77: 374.999 | U77: 372.4 | AA77: Nalla Crossing
A78: =A76+1 -> 37 | B78: 25/1 | C78: DA+0 | G78: 522649.61 | H78: 3588950.3 | J78: =J76+1 -> 37 | K78: 25/1 | L78: DA+0 | M78: 0 | N78: 0 | O78: 0 | P78: 0 | W78: 282.874 | Y78: 522669.71 | Z78: 3588906.7
D79: 330 | U79: 311.866 | AA79: Drain, 2nos LT Line,Road Crossing,
A80: =A78+1 -> 38 | B80: 25/2 | C80: DA+0 | G80: 522907.39 | H80: 3588744.2 | J80: =J78+1 -> 38 | K80: 25/2 | L80: DA+0 | M80: 0 | N80: 0 | O80: 0 | P80: 0 | W80: 283.88 | Y80: 522918.83 | Z80: 3588719.1
D81: 366.046 | U81: 343.763 | AA81: LT Line Crossing
A82: =A80+1 -> 39 | B82: 26/0 | C82: DD+0 | E82: =D77+D79+D81 -> 1071.045 | F82: 49° 51' 22"RT | G82: 523193.32 | H82: 3588515.7 | J82: =J80+1 -> 39 | K82: 26/0 | L82: DD+0 | M82: 0 | N82: 0 | O82: 0 | P82: 0 | V82: =U77+U79+U81 -> 1028.029 | W82: 284.271 | X82: 51°30'37"RT | Y82: 523193.43 | Z82: 3588512.3
D83: 445.757 | U83: 442.371 | AA83: River Crossing
A84: =A82+1 -> 40 | B84: 27/0 | C84: DB+0 | E84: =D83 -> 445.757 | F84: 10° 41' 31"RT | G84: 523205.05 | H84: 3588070.1 | J84: =J82+1 -> 40 | K84: 27/0 | L84: DB+0 | M84: 0 | N84: 0 | O84: 0 | P84: 0 | V84: =U83 -> 442.371 | W84: 299.465 | X84: 10°41'20"RT | Y84: 523205.05 | Z84: 3588070.1
D85: 320 | U85: 360 | AA85: LT Line Crossing
A86: =A84+1 -> 41 | B86: 27/1 | C86: DA+3 | G86: 523153.98 | H86: 3587754.2 | J86: =J84+1 -> 41 | K86: 27/1 | L86: DA+3 | M86: 1 | N86: 1 | O86: 1 | P86: 1 | W86: 295.54 | Y86: 523147.59 | Z86: 3587714.7 | AA86: Contouring Required
D87: 419.739 | U87: 379.739 | AA87: Road Crossing
A88: =A86+1 -> 42 | B88: 28/0 | C88: DC+6 | E88: =D85+D87 -> 739.739 | F88: 27° 47' 33"LT | G88: 523086.98 | H88: 3587339.8 | J88: =J86+1 -> 42 | K88: 28/0 | L88: DC+6 | M88: 2 | N88: 2 | O88: 2 | P88: 2 | V88: =U85+U87 -> 739.739 | W88: 299.027 | X88: 27°47'33"LT | Y88: 523086.98 | Z88: 3587339.8 | AA88: Contouring Required
D89: 445.991 | U89: 445.991 | AA89: 11 KV Line,Road Crossing
A90: =A88+1 -> 43 | B90: 29/0 | C90: DC+9 | E90: =D89 -> 445.991 | F90: 22° 59' 55"LT | G90: 523229.3 | H90: 3586917.2 | J90: =J88+1 -> 43 | K90: 29/0 | L90: DC+9 | M90: 2 | N90: 2 | O90: 2 | P90: 2 | V90: =U89 -> 445.991 | W90: 297.021 | X90: 22°59'55"LT | Y90: 523229.3 | Z90: 3586917.2 | AA90: Contouring Required
D91: 378 | U91: 373 | AA91: LT Line Crossing
A92: =A90+1 -> 44 | B92: 29/1 | C92: DA+0 | G92: 523480.3 | H92: 3586634.5 | J92: =J90+1 -> 44 | K92: 29/1 | L92: DA+0 | M92: 0 | N92: 0 | O92: 0 | P92: 0 | W92: 295.767 | Y92: 523476.98 | Z92: 3586638.3 | AA92: LT Line to be shifted,Contouring Required
D93: 361 | U93: 374
A94: =A92+1 -> 45 | B94: 29/2 | C94: DA+3 | G94: 523720.01 | H94: 3586364.6 | J94: =J92+1 -> 45 | K94: 29/2 | L94: DA+3 | M94: 1 | N94: 1 | O94: 1 | P94: 1 | W94: 287.94 | Y94: 523725.33 | Z94: 3586358.6
D95: 356 | U95: 352
A96: =A94+1 -> 46 | B96: 29/3 | C96: DA+0 | G96: 523956.41 | H96: 3586098.4 | J96: =J94+1 -> 46 | K96: 29/3 | L96: DA+0 | M96: 0 | N96: 0 | O96: 0 | P96: 0 | W96: 296.014 | Y96: 523959.06 | Z96: 3586095.4 | AA96: Conturing Required
D97: 410 | U97: 406
A98: =A96+1 -> 47 | B98: 29/4 | C98: DA+0 | G98: 524228.65 | H98: 3585791.8 | J98: =J96+1 -> 47 | K98: 29/4 | L98: DA+0 | M98: 0 | N98: 0 | O98: 0 | P98: 0 | W98: 298.58 | Y98: 524228.65 | Z98: 3585791.8 | AA98: Conturing Required
D99: 358 | U99: 352 | AA99: 11 KV Line Crossing
A100: =A98+1 -> 48 | B100: 29/5 | C100: DA+0 | G100: 524466.37 | H100: 3585524.2 | J100: =J98+1 -> 48 | K100: 29/5 | L100: DA+0 | M100: 0 | N100: 0 | O100: 0 | P100: 0 | W100: 296.73 | Y100: 524462.39 | Z100: 3585528.6
...

Sheet Approved CS K-S Line
A1: Line: 400 kV D/C Quad Kishenpur-Samba TL
A2: Approved Check Survey Tower Schedule
A3: AS PER DETAIL SURVEY | J3: AS PER CHECK SURVEY
A4: Sr. No. | B4: Tower No. | C4: Type of Tower | D4: Span Length (m) | E4: Section Length (m) | F4: Angle of Deviation | G4: UTM Coordinates | J4: Sr. No. | K4: Tower No. | L4: Type of Tower | M4: Raised Chimney | Q4: Leg Extension | U4: Span Length (m) | V4: Section Length (m) | W4: Reduced Level | X4: Angle of Deviation | Y4: UTM Coordinates | AA4: Crossing/Remarks
G5: Easting | H5: Northing | M5: LEG A | N5: LEG B | O5: LEG C | P5: LEG D | Q5: LEG A | R5: LEG B | S5: LEG C | T5: LEG D | Y5: Easting | Z5: Northing
A6: 1 | B6: AP 78/0 | C6: DC+9 | E6: 0 | F6: 28°55'39"L | G6: 515334.47 | H6: 3621567.2 | J6: 1 | K6: AP 78/0 | L6: DC+9 | M6: 0 | N6: 0 | O6: 0 | P6: 0 | Q6: 1 | R6: 0 | S6: 3 | T6: 3 | V6: 0 | W6: 524.77 | X6: 29°55'53"L | Y6: 515334.47 | Z6: 3621567.1
D7: 361.044 | U7: 340.277
A8: 2 | B8: AP 79/0 | C8: DD+9 | E8: =E6+D7 -> 361.044 | F8: 31°39'03"R | G8: 515034.27 | H8: 3621767.7 | J8: 2 | K8: AP 79/0 | L8: DD+9 | M8: 0 | N8: 0 | O8: 0 | P8: 0 | Q8: 0 | R8: 1 | S8: 0 | T8: 0 | V8: =V6+U7 -> 340.277 | W8: 524.982 | X8: 30°11'47"R | Y8: 515048.27 | Z8: 3621751.2 | AA8: LT LINE TO BE SHIFTED
D9: 374.114 | U9: 392.251 | AA9: NALLA CROSSING
A10: 3 | B10: AP 80/0 | C10: DD+3 | E10: =E8+D9 -> 735.158 | F10: 36°56'25"L | G10: 514878.54 | H10: 3622107.9 | J10: 3 | K10: AP 80/0 | L10: DD+3 | M10: 0 | N10: -1.5 | O10: 0 | P10: 0 | Q10: 0 | R10: 0 | S10: 0 | T10: 1 | V10: =V8+U9 -> 732.528 | W10: 532.688 | X10: 30°16'26"L | Y10: 514869.85 | Z10: 3622100.5
D11: 148.51 | U11: 144.77
A12: 4 | B12: AP 81/0 | C12: DD+18 | E12: =E10+D11 -> 883.668 | F12: 49°18'55"L | G12: 514747.98 | H12: 3622178.7 | J12: 4 | K12: AP 81/0 | L12: DD+18 | M12: 0 | N12: 0 | O12: 0 | P12: 0 | Q12: 0 | R12: 0 | S12: 0 | T12: 2 | V12: =V10+U11 -> 877.298 | W12: 535.86 | X12: 53°31'26"L | Y12: 514747.98 | Z12: 3622178.7
D13: 195.926 | U13: 195.926 | AA13: 220 KV S/C CROSSING(KSN-SRN)
A14: 5 | B14: AP 82/0 | C14: DD+18 | E14: =E12+D13 -> 1079.594 | F14: 5°38'12"R | G14: 514564.89 | H14: 3622108.9 | J14: 5 | K14: AP 82/0 | L14: DD+18 | M14: 0 | N14: 0 | O14: 0 | P14: 0 | Q14: 1 | R14: 3 | S14: 4 | T14: 4 | V14: =V12+U13 -> 1073.224 | W14: 532.66 | X14: 5°38'20"R | Y14: 514564.89 | Z14: 3622108.9
D15: 194.627 | U15: 194.623 | AA15: 220 D/C CROSSING(KSN-SRN)
A16: 6 | B16: AP 83/0 | C16: DD+25 | E16: =E14+D15 -> 1274.221 | F16: 46°40'30"R | G16: 514377.09 | H16: 3622057.8 | J16: 6 | K16: AP 83/0 | L16: DD+25 | M16: 0 | N16: 0 | O16: 0 | P16: 0 | Q16: 0 | R16: 0 | S16: 3 | T16: 0 | V16: =V14+U15 -> 1267.847 | W16: 522.13 | X16: 46°40'25"R | Y16: 514377.09 | Z16: 3622057.9
D17: 123.478 | U17: 123.478
A18: 7 | B18: AP 84/0 | C18: DC+9 | E18: =E16+D17 -> 1397.699 | F18: 26°50'39"R | G18: 514271.76 | H18: 3622122.3 | J18: 7 | K18: AP 84/0 | L18: DC+9 | M18: 0 | N18: 0 | O18: 0 | P18: 0 | Q18: 3 | R18: 3 | S18: 3 | T18: 3 | V18: =V16+U17 -> 1391.325 | W18: 525.46 | X18: 26°50'39"R | Y18: 514271.76 | Z18: 3622122.3 | AA18: CONTOUR NOT REQUIRED
D19: 358.138 | U19: 358.134
A20: 8 | B20: AP 85/0 | C20: DC+0 | E20: =E18+D19 -> 1755.837 | F20: 18°33'39"R | G20: 514083.58 | H20: 3622427 | J20: 8 | K20: AP 85/0 | L20: DC+0 | M20: 0 | N20: -1.5 | O20: 0 | P20: 1 | Q20: 0 | R20: 0 | S20: 0 | T20: 0 | V20: =V18+U19 -> 1749.459 | W20: 513.5 | X20: 18°33'34"R | Y20: 514083.58 | Z20: 3622427
D21: 195.995 | U21: 195.99 | AA21: LT LINE,2 NOS 11 KV CROSSING
A22: 9 | B22: AP 86/0 | C22: DD+0 | E22: =E20+D21 -> 1951.832 | F22: 37°33'24"L | G22: 514039.03 | H22: 3622617.9 | J22: 9 | K22: AP 86/0 | L22: DD+0 | M22: 0 | N22: 0 | O22: 1.5 | P22: 0 | Q22: 0 | R22: 0 | S22: 0 | T22: 0 | V22: =V20+U21 -> 1945.449 | W22: 519.05 | Y22: 514039.03 | Z22: 3622617.9
U23: 402.938 | AA23: Cannal,Cart Track Crossing
A25: =A22+1 -> 10 | B25: AP 95/0 | C25: DD+0 | E25: 0 | F25: 49° 37' 37"RT | G25: 511950.67 | H25: 3623917.5 | J25: =J22+1 -> 10 | K25: AP 95/0 | L25: DD+0 | M25: 0 | N25: -1.5 | O25: 0 | P25: 1.5 | Q25: 0 | R25: 0 | S25: 0 | T25: 0 | V25: 0 | W25: 483.848 | X25: 47° 47' 09"RT | Y25: 511953.99 | Z25: 3623920
D26: 216.941 | U26: 215.857 | AA26: LT Line,2 NOS 11KV Line Crossing
A27: =A25+1 -> 11 | B27: AP 96/0 | C27: DC+0 | E27: =E25+D26 -> 216.941 | F27: 23° 11' 17"RT | G27: 511872.02 | H27: 3624119.7 | J27: =J25+1 -> 11 | K27: AP 96/0 | L27: DC-3 | M27: 0 | N27: 0 | O27: 0 | P27: 3 | Q27: 0 | R27: 0 | S27: 1 | T27: 0 | V27: =V25+U26 -> 215.857 | W27: 480.277 | X27: 24° 15' 00"RT | Y27: 511872.02 | Z27: 3624119.7
D28: 166.009 | U28: 166.009 | AA28: LT Line Crossing
A29: =A27+1 -> 12 | B29: AP 97/0 | C29: DC+0 | E29: =E27+D28 -> 382.95 | F29: 25° 05' 24"LT | G29: 511877.62 | H29: 3624285.6 | J29: =J27+1 -> 12 | K29: AP 97/0 | L29: DC-3 | M29: 0 | N29: 0 | O29: 0 | P29: 0 | Q29: 0 | R29: 0 | S29: 0 | T29: 0 | V29: =V27+U28 -> 381.866 | W29: 485.367 | X29: 25° 09' 02"LT | Y29: 511877.62 | Z29: 3624285.6 | AA29: Contour Not Required
D30: 242.696 | U30: 242.696 | AA30: Nalla and LT Line crossing
A31: =A29+1 -> 13 | B31: AP 98/0 | C31: DD+9 | E31: =E29+D30 -> 625.646 | F31: 48° 10' 12"LT | G31: 511782.17 | H31: 3624508.8 | J31: =J29+1 -> 13 | K31: AP 98/0 | L31: DD+9 | M31: 0 | N31: 0 | O31: 0 | P31: 0 | Q31: 2 | R31: 2 | S31: 3 | T31: 2 | V31: =V29+U30 -> 624.562 | W31: 486.733 | X31: 48° 10' 19"LT | Y31: 511782.17 | Z31: 3624508.8
D32: 202.992 | U32: 202.992 | AA32: 132 KV S/C Line Crossing
A33: =A31+1 -> 14 | B33: AP 99/0 | C33: DD+18 | E33: =E31+D32 -> 828.638 | F33: 58° 23' 34"RT | G33: 511589.86 | H33: 3624573.7 | J33: =J31+1 -> 14 | K33: AP 99/0 | L33: DD+18 | M33: 0 | N33: 0 | O33: 0 | P33: 0 | Q33: 0 | R33: 0 | S33: 0 | T33: 0 | V33: =V31+U32 -> 827.554 | W33: 468.882 | X33: 58° 23' 34"RT | Y33: 511589.86 | Z33: 3624573.7 | AA33: Contour Not Required
D34: 155.699 | U34: 155.699
A35: =A33+1 -> 15 | B35: AP 100/0 | C35: DD+9 | E35: =E33+D34 -> 984.337 | F35: 45° 03' 40"RT | G35: 511554.99 | H35: 3624725.5 | J35: =J33+1 -> 15 | K35: AP 100/0 | L35: DD+9 | M35: 0 | N35: 0 | O35: 0 | P35: 0 | Q35: 0 | R35: 0 | S35: 0 | T35: 0 | V35: =V33+U34 -> 983.253 | W35: 468.116 | X35: 45° 03' 40"RT | Y35: 511554.99 | Z35: 3624725.5
D36: 491.503 | U36: 491.503 | AA36: Nalla and LT Line crossing
A37: =A35+1 -> 16 | B37: AP 101/0 | C37: DD+9 | E37: =E35+D36 -> 1475.84 | F37: 34° 37' 48"LT | G37: 511816.34 | H37: 3625141.7 | J37: =J35+1 -> 16 | K37: AP 101/0 | L37: DD+9 | M37: 0 | N37: 0 | O37: 0 | P37: 0 | Q37: 0 | R37: 0 | S37: 0 | T37: 0 | V37: =V35+U36 -> 1474.756 | W37: 482.052 | X37: 34° 37' 48"LT | Y37: 511816.34 | Z37: 3625141.7 | AA37: Contour Not Required
D38: 136.501 | U38: 136.501
A39: =A37+1 -> 17 | B39: AP 102/0 | C39: DD+0 | E39: =E37+D38 -> 1612.341 | F39: 49° 54' 56"LT | G39: 511810.37 | H39: 3625278.1 | J39: =J37+1 -> 17 | K39: AP 102/0 | L39: DD+0 | M39: 0 | N39: 0 | O39: 0 | P39: 0 | Q39: 0 | R39: 1 | S39: 0 | T39: 0 | V39: =V37+U38 -> 1611.257 | W39: 479.213 | X39: 49° 54' 56"LT | Y39: 511810.37 | Z39: 3625278.1
D40: 122.195 | U40: 122.195 | AA40: 11 kv Line Crossing
A41: =A39+1 -> 18 | B41: AP 103/0 | C41: DD+6 | E41: =E39+D40 -> 1734.536 | F41: 37° 03' 00"RT | G41: 511713.53 | H41: 3625352.6 | J41: =J39+1 -> 18 | K41: AP 103/0 | L41: DD+6 | M41: 0 | N41: 0 | O41: 0 | P41: 0 | Q41: 1 | R41: 0 | S41: 0 | T41: 1 | V41: =V39+U40 -> 1733.452 | W41: 476.5 | X41: 37° 03' 00"RT | Y41: 511713.53 | Z41: 3625352.6
D42: 185.672 | U42: 185.672 | AA42: Electrified Railway crossing,11 KV Crossing
A43: =A41+1 -> 19 | B43: AP 104/0 | C43: DD+9 | E43: =E41+D42 -> 1920.208 | F43: 24° 32' 24"LT | G43: 511664.34 | H43: 3625531.7 | J43: =J41+1 -> 19 | K43: AP 104/0 | L43: DD+9 | M43: 0 | N43: 0 | O43: 0 | P43: 0 | Q43: 0 | R43: 0 | S43: 0 | T43: 0 | V43: =V41+U42 -> 1919.124 | W43: 475.575 | X43: 24° 32' 24"LT | Y43: 511664.34 | Z43: 3625531.7 | AA43: Contour Not Required
D44: 303.562 | U44: 303.562
A45: =A43+1 -> 20 | B45: AP 105/0 | C45: DD+0 | E45: =E43+D44 -> 2223.77 | F45: 55° 28' 40"RT | G45: 511469.59 | H45: 3625764.5 | J45: =J43+1 -> 20 | K45: AP 105/0 | L45: DD+0 | M45: 0 | N45: 0 | O45: 0 | P45: 0 | Q45: 0 | R45: 0 | S45: 1 | T45: 0 | V45: =V43+U44 -> 2222.686 | W45: 475.007 | X45: 55° 28' 40"RT | Y45: 511469.59 | Z45: 3625764.5
D46: 287.716 | U46: 287.716 | AA46: 2nos 11KV Line Crossing
A47: =A45+1 -> 21 | B47: AP 106/0 | C47: DB+0 | E47: =E45+D46 -> 2511.486 | F47: 13° 39' 57"RT | G47: 511546.81 | H47: 3626041.7 | J47: =J45+1 -> 21 | K47: AP 106/0 | L47: DB+0 | M47: 0 | N47: 0 | O47: 0 | P47: 0 | Q47: 0 | R47: 0 | S47: 0 | T47: 0 | V47: =V45+U46 -> 2510.402 | W47: 469.175 | X47: 13° 39' 57"RT | Y47: 511546.81 | Z47: 3626041.7 | AA47: Contour Not Required
D48: 425.991 | U48: 425.991
A49: =A47+1 -> 22 | B49: AP 107/0 | C49: DC+0 | E49: =E47+D48 -> 2937.477 | F49: 27° 39' 10"RT | G49: 511754.88 | H49: 3626413.4 | J49: =J47+1 -> 22 | K49: AP 107/0 | L49: DC+0 | M49: -1.5 | N49: -1.5 | O49: 0 | P49: 0 | Q49: 0 | R49: 0 | S49: 0 | T49: 0 | V49: =V47+U48 -> 2936.393 | W49: 457.977 | X49: 27° 39' 10"RT | Y49: 511754.88 | Z49: 3626413.4 | AA49: 2nos LTLine crossing
D50: 141.744 | H50: AP24-AP39 | U50: 141.744
A51: =A49+1 -> 23 | B51: AP 108/0 | C51: DC+0 | E51: =E49+D50 -> 3079.221 | F51: 16° 58' 12"LT | G51: 511873.6 | H51: 3626490.8 | J51: =J49+1 -> 23 | K51: AP 108/0 | L51: DC+0 | M51: 0 | N51: 0 | O51: 0 | P51: 0 | Q51: 0 | R51: 0 | S51: 0 | T51: 0 | V51: =V49+U50 -> 3078.137 | W51: 458.784 | X51: 16° 58' 12"LT | Y51: 511873.6 | Z51: 3626490.8 | AA51: Contour Not Required
D52: 52.346 | U52: 52.346
A53: =A51+1 -> 24 | B53: AP 109/0 | C53: DD+0 | E53: =E51+D52 -> 3131.567 | G53: 511907.19 | H53: 3626531 | J53: =J51+1 -> 24 | K53: AP 109/0 | L53: DD+0 | M53: 0 | N53: 0 | O53: 0 | P53: 0 | Q53: 0 | R53: 0 | S53: 0 | T53: 0 | V53: =V51+U52 -> 3130.483 | W53: 458.578 | Y53: 511907.19 | Z53: 3626531 | AA53: Contour Not Required

Sheet Foundation JS-Line -Jammu
A1: KEC INTERNATIONAL LIMITED | O1: Date: | P1: ='TB-605'!E1 -> 46161
A2: 400 kV Samba- Jalandhar D/C Line(Quad) - Wind Zone - 5-Jammu Portion
A3: FOUNDATION
A5: S.No | B5: Loc No. | C5: Tower Type | D5: Classification | E5: Conc Volume | F5: Start Date | G5: Foundation | M5: Earthing | N5: FDN Status | O5: Gang Name | P5: Gang Strength | Q5: Remark
G6: Excavation | H6: Stub Setting | I6: PCC | J6: Rebar Placing | K6: RCC | L6: Completion Date
A7: 1 | B7: 29/5 | C7: DA+0 | D7: WET | E7: 34.389 | F7: 45866 | G7: 45876 | H7: 45879 | I7: 45879 | J7: 45879 | K7: 45880 | L7: 45880 | M7: 45994 | N7: Completed | O7: Rakesh | P7: 8
A8: =A7+1 -> 2 | B8: 29/4 | C8: DA+0 | D8: DRY | E8: 21.318 | F8: 45880 | G8: 45890 | H8: 45890 | I8: 45891 | J8: 45891 | K8: 45906 | L8: 45906 | M8: 45994 | N8: Completed | O8: Rakesh | P8: 5
A9: =A8+1 -> 3 | B9: 29/3 | C9: DA+0 | D9: DRY | E9: 21.318 | F9: 45900 | G9: 45921 | H9: 45921 | I9: 45922 | J9: 45922 | K9: 45924 | L9: 45924 | N9: Completed | O9: Adishiv | P9: 12 | Q9: Completed & 1 leg 1.5 M RC pending
A10: =A9+1 -> 4 | B10: 27/0 | C10: DB+0 | D10: WET | E10: =65.112+6.59 -> 71.702 | F10: 45907 | G10: 45916 | H10: 45918 | I10: 45918 | J10: 45919 | K10: 45920 | L10: 45920 | M10: 46032 | N10: Completed | O10: Adishiv | P10: 12
A11: =A10+1 -> 5 | B11: 17/0 | C11: DC+3 | D11: FS | E11: 142.45 | F11: 45910 | G11: 45982 | H11: 45983 | I11: 45983 | J11: 45983 | K11: 45984 | L11: 45984 | M11: 45998 | N11: Completed | O11: Md.Farooq | P11: 12 | Q11: Benching work completed on 21.9.25 Pit B- Casting completed. Work on hold since 12th Oct'25 & restart from 07th Nov'25 & completed on 23rd Nov'25
A12: =A11+1 -> 6 | B12: 18/0 | C12: DC+0 | D12: FS | E12: =122.268+12.044 -> 134.312 | F12: 45911 | G12: 45944 | H12: 45944 | I12: 45944 | J12: 45944 | K12: 45946 | L12: 45946 | M12: 45948 | N12: Completed | O12: Md. Sharif | P12: 20
A13: =A12+1 -> 7 | B13: 29/6 | C13: DA+3 | D13: WET | F13: 45940 | G13: 45944 | H13: 45944 | I13: 45945 | J13: 45945 | K13: 45946 | L13: 45946 | M13: 45948 | N13: Completed | O13: Adishiv | P13: 12 | Q13: Intially work started on 26.9.25 but due to high water table work was hold till 3.10.25 and as advised by RKPTL team loc shifted about 60 mtrs and work resumed from 10.10.25 & completed on 16.10.25
A14: =A13+1 -> 8 | B14: 30/3 | C14: DA+6 | D14: PS | F14: 45960 | G14: 45983 | H14: 45984 | I14: 45984 | J14: 45985 | K14: 45985 | L14: 45985 | M14: 45987 | N14: Completed | O14: Kewal Krishan | P14: 9
A15: =A14+1 -> 9 | B15: 23/1 | C15: DA+6 | D15: WET | F15: 45925 | G15: 45965 | H15: 45968 | I15: 45968 | J15: 45969 | K15: 45971 | L15: 45971 | M15: 45997 | N15: Completed | O15: Vishal | P15: 8
A16: =A15+1 -> 10 | B16: 29/1 | C16: DA+0 | D16: WET | F16: 45933 | G16: 45937 | H16: 45939 | I16: 45939 | J16: 45939 | K16: 45940 | L16: 45940 | M16: 45959 | N16: Completed | O16: Adishiv | P16: 12 | Q16: RC Casting done by Anil Sharma on 11.02.2026
A17: 11 | B17: 22/1 | C17: DA+3 | D17: WET | F17: 45940 | G17: 45957 | H17: 45957 | I17: 45957 | J17: 45957 | K17: 45958 | L17: 45958 | M17: 45981 | N17: Completed | O17: ANB Construction | P17: 5
A18: 12 | B18: 15/2 | C18: DA+0 | D18: FS | F18: 45948 | G18: 45970 | H18: 45979 | I18: 45980 | J18: 45980 | K18: 45980 | L18: 45980 | M18: 45998 | N18: Completed | O18: Balwanth Singh | P18: 21
A19: 13 | B19: 31/1 | C19: DA+3 | D19: PS | F19: 45947 | G19: 45957 | H19: 45958 | I19: 45958 | J19: 45959 | K19: 45960 | L19: 45960 | M19: 45981 | N19: Completed | O19: Md. Sharif | P19: 24
A20: 14 | B20: 22/0 | C20: DC+3 | D20: WET | F20: 45948 | G20: 45960 | H20: 45961 | I20: 45961 | J20: 45961 | K20: 45961 | L20: 45961 | M20: 45980 | N20: Completed | O20: Surjeet | P20: 10
A21: 15 | B21: 21/1 | C21: DA+0 | D21: WET | F21: 45958 | G21: 45960 | H21: 45961 | I21: 45961 | J21: 45961 | K21: 45961 | L21: 45961 | M21: 45970 | N21: Completed | O21: Surjeet | P21: 19
A22: =A21+1 -> 16 | B22: 31/3 | C22: DA+0 | D22: PS | F22: 45960 | G22: 45968 | H22: 45970 | I22: 45970 | J22: 45971 | K22: 45972 | L22: 45972 | M22: 45972 | N22: Completed | O22: Md. Sharif | P22: 12
A23: =A22+1 -> 17 | B23: 22/2 | C23: DA+3 | D23: WET | F23: 45959 | G23: 45971 | H23: 45973 | I23: 45973 | J23: 45973 | K23: 45974 | L23: 45974 | M23: 45981 | N23: Completed | O23: ANB Construction | P23: 8
A24: =A23+1 -> 18 | B24: 15/1 | C24: DA+0 | D24: PS | F24: 45967 | G24: 45974 | H24: 45978 | I24: 45978 | J24: 45978 | K24: 45978 | L24: 45978 | M24: 45993 | N24: Completed | O24: Balwanth Singh | P24: 21
A25: =A24+1 -> 19 | B25: 40/0 | C25: DC+3 | D25: PS | F25: 45970 | G25: 45991 | H25: 45993 | I25: 45993 | J25: 45994 | K25: 45994 | L25: 45994 | M25: 46006 | N25: Completed | O25: Pawan Kumar Shama | P25: 15
A26: =A25+1 -> 20 | B26: 20/0 | C26: DB+6 | D26: WET | F26: 45973 | G26: 45986 | H26: 45989 | I26: 45989 | J26: 45990 | K26: 45991 | L26: 45991 | M26: 45995 | N26: Completed | O26: Surjeet | P26: 8
A27: =A26+1 -> 21 | B27: 27/1 | C27: DA+3 | D27: WET | F27: 45975 | G27: 45978 | H27: 45983 | I27: 45983 | J27: 45984 | K27: 45984 | L27: 45984 | M27: 45998 | N27: Completed | O27: Md.Sharif | P27: 40 | Q27: RC Casting Pending
A28: =A27+1 -> 22 | B28: AP32 | C28: DB+0 | D28: FS | F28: 45973 | G28: 45982 | H28: 45983 | I28: 45984 | J28: 45984 | K28: 45987 | L28: 45987 | M28: 45993 | N28: Completed | O28: Md.Sharif
A29: =A28+1 -> 23 | B29: 23/0 | C29: DB+0 | D29: FS | F29: 45976 | G29: 45997 | H29: 45998 | I29: 45998 | J29: 45999 | K29: 111743 | L29: 46000 | M29: 46002 | N29: Completed | O29: ANB Construction | P29: 9
A30: =A29+1 -> 24 | B30: 30/5 | C30: DA+9 | D30: PS | F30: 45977 | G30: 45989 | H30: 45990 | I30: 45990 | J30: 45990 | K30: 45990 | L30: 45990 | M30: 45996 | N30: Completed | O30: Akram | P30: 15
A31: =A30+1 -> 25 | B31: 40/1 | C31: DA+3 | D31: WET | F31: 45977 | G31: 45990 | H31: 45991 | I31: 45991 | J31: 45991 | K31: 45991 | L31: 45991 | M31: 45997 | N31: Completed | O31: Thakur Cosnt | P31: 7
A32: =A31+1 -> 26 | B32: 19/2 | C32: DA+0 | D32: FS | F32: 45984 | G32: 46002 | H32: 46002 | I32: 46004 | J32: 46004 | K32: 46004 | L32: 46004 | M32: 46007 | N32: Completed | O32: Balwanth Singh | P32: 9
A33: =A32+1 -> 27 | B33: 18/1 | C33: DA+0 | D33: PS | F33: 45986 | G33: 45996 | H33: 45997 | I33: 45997 | J33: 45997 | K33: 45997 | L33: 45997 | M33: 45998 | N33: Completed | O33: Md.Farooq | P33: 12
A34: =A33+1 -> 28 | B34: AP28 | C34: DC+6 | D34: WET | F34: 45988 | G34: 45989 | H34: 45992 | I34: 45992 | J34: 45992 | K34: 45995 | L34: 45995 | M34: 45994 | N34: Completed | O34: Md. Sharif | P34: 35
A35: =A34+1 -> 29 | B35: 30/2 | C35: DA+0 | D35: PS | F35: 45988 | G35: 46000 | H35: 46001 | I35: 46001 | J35: 46001 | K35: 46003 | L35: 46003 | M35: 46007 | N35: Completed | O35: Kewal Krishan | P35: 8
A36: =A35+1 -> 30 | B36: 23/4 | C36: DA+3 | D36: FS | F36: 45991 | G36: 46019 | H36: 46021 | I36: 46022 | J36: 46022 | K36: 46022 | L36: 46022 | M36: 46029 | N36: Completed | O36: Anil Sharma | P36: 7 | Q36: Pit B, C, D- Casting Completed Pit A- Prop Setting/PCC
A37: =A36+1 -> 31 | B37: 29/0 | C37: DC+9 | D37: WET | F37: 45994 | G37: 45997 | H37: 45998 | I37: 45999 | J37: 46000 | K37: 46001 | L37: 46001 | M37: 46003 | N37: Completed | O37: Md. Sharif | P37: 28
A38: =A37+1 -> 32 | B38: 23/5 | C38: DA+3 | D38: FS | F38: 45994 | G38: 46011 | H38: 46012 | I38: 46012 | J38: 46012 | K38: 46012 | L38: 46012 | M38: 46105 | N38: Completed | O38: Balwanth Singh | P38: 20
A39: =A38+1 -> 33 | B39: 39/2 | C39: DA+0 | D39: FS | F39: 45996 | G39: 46003 | H39: 46003 | I39: 46004 | J39: 46004 | K39: 46004 | L39: 46004 | M39: 46006 | N39: Completed | O39: Pawan Kumar Shama | P39: 17
A40: =A39+1 -> 34 | B40: 30/4 | C40: DA+0 | D40: FS | F40: 45996 | G40: 46009 | H40: 46010 | I40: 46010 | J40: 46010 | K40: 46010 | L40: 46010 | M40: 46014 | N40: Completed | O40: Akram | P40: 15
A41: =A40+1 -> 35 | B41: AP33 | C41: DC+0 | D41: FS | F41: 46000 | G41: 46019 | H41: 46022 | I41: 46022 | J41: 46022 | K41: 46022 | L41: 46022 | M41: 46007 | N41: Completed | O41: Adishiv | P41: 8 | Q41: Pit A,D,C - Casting Completed Pit B- Excavation Completed
A42: =A41+1 -> 36 | B42: AP19 | C42: DC+0 | D42: FS | F42: 46001 | G42: 46013 | H42: 46014 | I42: 46014 | J42: 46014 | K42: 46015 | L42: 46015 | M42: 46012 | N42: Completed | O42: Md.Farooq | P42: 12
A43: =A42+1 -> 37 | B43: AP43 | C43: DD+3 | D43: WET | F43: 46002 | G43: 46011 | H43: 46012 | I43: 46014 | J43: 46014 | K43: 46016 | L43: 46016 | M43: 46025 | N43: Completed | O43: Thakur Cosnt | P43: 16
A44: =A43+1 -> 38 | B44: AP45 | C44: DB+0 | D44: WET | F44: 46003 | G44: 46011 | H44: 46013 | I44: 46013 | J44: 46014 | K44: 46014 | L44: 46014 | M44: 46016 | N44: Completed | O44: Md. Sharif | P44: 28
A45: =A44+1 -> 39 | B45: 31/2 | C45: DA+0 | D45: FS | F45: 46007 | G45: 46015 | H45: 46016 | I45: 46016 | J45: 46018 | K45: 46018 | L45: 46018 | M45: 46041 | N45: Completed | O45: Gulam | P45: 12
A46: =A45+1 -> 40 | B46: 46/1 | C46: DA+0 | D46: PS | F46: 46008 | G46: 46015 | H46: 46015 | I46: 46016 | J46: 46016 | K46: 46016 | L46: 46016 | M46: 46024 | N46: Completed | O46: Pawan Kumar Shama | P46: 17
A47: =A46+1 -> 41 | B47: AP31 | C47: DB+0 | D47: FS | F47: 46010 | G47: 46033 | H47: 46038 | I47: 46038 | J47: 46038 | K47: 46040 | L47: 46040 | M47: 46024 | N47: Completed | O47: Akram | P47: 15
A48: =A47+1 -> 42 | B48: AP16 | C48: DC+0 | D48: FS | F48: 46026 | G48: 46043 | H48: 46046 | I48: 46046 | J48: 46047 | K48: 46047 | L48: 46047 | N48: Completed | O48: Balwanth Singh | P48: 20 | Q48: Pit B,C,D - Casting Completed
A49: =A48+1 -> 43 | B49: 18/2 | C49: DA+6 | D49: FS | F49: 46016 | G49: 46028 | H49: 46029 | I49: 46029 | J49: 46029 | K49: 46030 | L49: 46030 | M49: 46044 | N49: Completed | O49: Md.Farooq | P49: 12
A50: =A49+1 -> 44 | B50: AP26 | C50: DD+0 | D50: FS | F50: 46015 | G50: 46026 | H50: 46027 | I50: 46029 | J50: 46029 | K50: 46030 | L50: 46030 | M50: 46099 | N50: Completed | O50: Balwanth Singh | P50: 20
A51: =A50+1 -> 45 | B51: 43/1 | C51: DA+6 | D51: FS | F51: 46018 | G51: 46024 | H51: 46024 | I51: 46024 | J51: 46025 | K51: 46026 | L51: 46026 | M51: 46044 | N51: Completed | O51: Thakur Cosnt | P51: 16
A52: =A51+1 -> 46 | B52: 31/4 | C52: DA+3 | D52: FS | F52: 46020 | G52: 46029 | H52: 46030 | I52: 46030 | J52: 46030 | K52: 46031 | L52: 46031 | M52: 46032 | N52: Completed | O52: Gulam | P52: 12
A53: =A52+1 -> 47 | B53: 46/3 | C53: DA+0 | D53: FS | F53: 46020 | G53: 46029 | H53: 46031 | I53: 46031 | J53: 46031 | K53: 46031 | L53: 46031 | M53: 46032 | N53: Completed | O53: Pawan Kumar Shama | P53: 17
A54: =A53+1 -> 48 | B54: AP30 | C54: DB+0 | D54: FS | F54: 46026 | G54: 46043 | H54: 46051 | I54: 46051 | J54: 46051 | K54: 46053 | L54: 46053 | M54: 46111 | N54: Completed | O54: Akram | P54: 18
A55: =A54+1 -> 49 | B55: 43/2 | C55: DA+0 | D55: FS | F55: 46029 | G55: 46033 | H55: 46034 | I55: 46034 | J55: 46034 | K55: 46034 | L55: 46034 | M55: 46043 | N55: Completed | O55: Thakur Cosnt | P55: 16
A56: =A55+1 -> 50 | B56: 32/1 | C56: DA+6 | D56: FS | F56: 46030 | G56: 46051 | H56: 46052 | I56: 46052 | J56: 46052 | K56: 46052 | L56: 46052 | M56: 46055 | N56: Completed | O56: Anil Sharma | P56: 7
A57: =A56+1 -> 51 | B57: 33/1 | C57: DA+0 | D57: FS/FS(SD) | F57: 46031 | G57: 46148 | H57: 46149 | I57: 46149 | J57: 46149 | K57: 46149 | L57: 46149 | N57: Completed | O57: Adishiv/Thakur Const-1 | P57: 10
A58: =A57+1 -> 52 | B58: 25/2 | C58: DA+0 | D58: FS | F58: 46033 | G58: 46042 | H58: 46043 | I58: 46043 | J58: 46043 | K58: 46043 | L58: 46043 | M58: 46054 | N58: Completed | O58: Balwanth Singh | P58: 20
A59: =A58+1 -> 53 | B59: 45/2 | C59: DA+0 | D59: PS | F59: 46034 | G59: 46042 | H59: 46043 | I59: 46043 | J59: 46043 | K59: 46043 | L59: 46043 | M59: 46061 | N59: Completed | O59: Pawan Kumar Shama | P59: 12
A60: =A59+1 -> 54 | B60: 19/1 | C60: DA+0 | D60: FS | F60: 46034 | G60: 46041 | H60: 46042 | I60: 46042 | J60: 46042 | K60: 46042 | L60: 46042 | M60: 46044 | N60: Completed | O60: Md.Farooq | P60: 10
A61: =A60+1 -> 55 | B61: 31/5 | C61: DA+3 | D61: FS | F61: 46036 | G61: 46044 | H61: 46044 | I61: 46044 | J61: 46044 | K61: 46044 | L61: 46044 | M61: 46044 | N61: Completed | O61: Gulam | P61: 10
A62: =A61+1 -> 56 | B62: 50A/7 | C62: DA+6 | D62: PS | F62: 46053 | G62: 46066 | H62: 46066 | I62: 46066 | J62: 46066 | K62: 46067 | L62: 46067 | M62: 46076 | N62: Completed | O62: Wani Const | P62: 8
A63: =A62+1 -> 57 | B63: 44/3 | C63: DA+0 | D63: FS | F63: 46038 | G63: 46042 | H63: 46043 | I63: 46043 | J63: 46043 | K63: 46043 | L63: 46043 | M63: 46077 | N63: Completed | O63: Thakur Cosnt | P63: 16
A64: =A63+1 -> 58 | B64: 44/2 | C64: DA+0 | D64: FS | F64: 46051 | G64: 46059 | H64: 46059 | I64: 46059 | J64: 46060 | K64: 46060 | L64: 46060 | M64: 46078 | N64: Completed | O64: Thakur Cosnt | P64: 16
A65: =A64+1 -> 59 | B65: AP21 | C65: DD+6 | D65: WET | F65: 46051 | G65: 46079 | H65: 46080 | I65: 46080 | J65: 46080 | K65: 46080 | L65: 46080 | N65: Completed | O65: Akram | P65: 18
A66: =A65+1 -> 60 | B66: 45/1 | C66: DA+3 | D66: PS | F66: 46051 | G66: 46057 | H66: 46058 | I66: 46058 | J66: 46058 | K66: 46058 | L66: 46058 | M66: 46078 | N66: Completed | O66: Pawan Kumar Shama | P66: 12
A67: =A66+1 -> 61 | B67: AP15 | C67: DD+18 | D67: WET | F67: 46053 | G67: 46059 | H67: 46059 | I67: 46059 | J67: 46059 | K67: 46061 | L67: 46061 | M67: 46106 | N67: Completed | O67: Balwanth Singh | P67: 20
A68: =A67+1 -> 62 | B68: AP12 | C68: DD+30 | D68: WET /PS | F68: 46056 | G68: 46070 | H68: 46071 | I68: 46071 | J68: 46071 | K68: 46073 | L68: 46073 | N68: Completed | O68: Gulam | P68: 10
A69: =A68+1 -> 63 | B69: 25/1 | C69: DA+0 | D69: FS | F69: 46058 | G69: 46065 | H69: 46065 | I69: 46065 | J69: 46065 | K69: 46066 | L69: 46066 | M69: 46079 | N69: Completed | O69: Balwanth Singh | P69: 20
A70: =A69+1 -> 64 | B70: AP35 | C70: DD+0 | D70: FS | F70: 46058 | G70: 46153 | N70: WIP | O70: Adishiv | P70: 8 | Q70: Pit A,B,D - Casting Completed Pit C - Block Level
A71: =A70+1 -> 65 | B71: AP46 | C71: DB+0 | D71: FS | F71: 46063 | G71: 46073 | H71: 46073 | I71: 46073 | J71: 46073 | K71: 46073 | L71: 46073 | M71: 46147 | N71: Completed | O71: Pawan Kumar Shama | P71: 12
A72: =A71+1 -> 66 | B72: AP44 | C72: DB+0 | D72: PS | F72: 46064 | G72: 46073 | H72: 46073 | I72: 46073 | J72: 46073 | K72: 46073 | L72: 46073 | M72: 46098 | N72: Completed | O72: Thakur Cosnt | P72: 16
A73: =A72+1 -> 67 | B73: AP25 | C73: DD+0 | D73: FS | F73: 46068 | G73: 46078 | H73: 46078 | I73: 46078 | J73: 46078 | K73: 46078 | L73: 46078 | M73: 46099 | N73: Completed | O73: Balwanth Singh | P73: 20
A74: =A73+1 -> 68 | B74: 29/2 | C74: DA+3 | D74: PS (SD) | F74: 46066 | G74: 46086 | H74: 46088 | I74: 46088 | J74: 46088 | K74: 46088 | L74: 46088 | M74: 46094 | N74: Completed | O74: Anil Sharma | P74: 8
A75: =A74+1 -> 69 | B75: 50A/8 | C75: DA+0 | D75: PS | F75: 46070 | G75: 46078 | H75: 46078 | I75: 46078 | J75: 46078 | K75: 46078 | L75: 46078 | M75: 46094 | N75: Completed | O75: Wani Const | P75: 8
A76: =A75+1 -> 70 | B76: 44/1 | C76: DA+0 | D76: PS | F76: 46076 | G76: 46079 | H76: 46080 | I76: 46080 | J76: 46080 | K76: 46080 | L76: 46080 | M76: 46082 | N76: Completed | O76: Thakur Cosnt | P76: 16
A77: =A76+1 -> 71 | B77: 33/2 | C77: DA+0 | D77: PS | F77: 46076 | G77: 46089 | H77: 46090 | I77: 46090 | J77: 46090 | K77: 46090 | L77: 46090 | N77: Completed | O77: Gulam | P77: 10
A78: =A77+1 -> 72 | B78: 46/5 | C78: DA+6 | D78: FS | F78: 46076 | G78: 46086 | H78: 46086 | I78: 46086 | J78: 46086 | K78: 46086 | L78: 46086 | M78: 46099 | N78: Completed | O78: Pawan Kumar Shama | P78: 12
A79: =A78+1 -> 73 | B79: 50A/3 | C79: DA+3 | D79: PS (SD) | F79: 46082 | G79: 46086 | H79: 46087 | I79: 46087 | J79: 46087 | K79: 46087 | L79: 46087 | M79: 46099 | N79: Completed | O79: Wani Const | P79: 8
A80: =A79+1 -> 74 | B80: AP14 | C80: DB+9 | D80: DFR | F80: 46082 | G80: 46086 | H80: 46089 | I80: 46089 | J80: 46089 | K80: 46089 | L80: 46089 | M80: 46105 | N80: Completed | O80: Balwanth Singh | P80: 20
A81: =A80+1 -> 75 | B81: AP24 | C81: DC+3 | D81: PS | F81: 46082 | G81: 46095 | H81: 46095 | I81: 46095 | J81: 46095 | K81: 46096 | L81: 46096 | M81: 46105 | N81: Completed | O81: Balwanth Singh | P81: 20
A82: =A81+1 -> 76 | B82: 30/1 | C82: DA+6 | D82: FS (SD) | F82: 46086 | O82: Akram/Anil Sharma | P82: 10 | Q82: Pit C -Excavation Due to ROW work on hold
A83: =A82+1 -> 77 | B83: 43/3 | C83: DA+3 | D83: PS | F83: 46086 | G83: 46088 | H83: 46089 | I83: 46089 | J83: 46089 | K83: 46089 | L83: 46089 | M83: 46100 | N83: Completed | O83: Thakur Cosnt | P83: 16
A84: =A83+1 -> 78 | B84: 43/4 | C84: DA+0 | D84: PS(SD) | F84: 46089 | G84: 46101 | H84: 46102 | I84: 46102 | J84: 46102 | K84: 46102 | L84: 46102 | M84: 46104 | N84: Completed | O84: Thakur Cosnt | P84: 16
A85: =A84+1 -> 79 | B85: 46/4 | C85: DA+0 | D85: FS | F85: 46089 | G85: 46092 | H85: 46092 | I85: 46092 | J85: 46092 | K85: 46092 | L85: 46092 | M85: 46100 | N85: Completed | O85: Pawan Kumar Shama | P85: 12
A86: =A85+1 -> 80 | B86: AP34 | C86: DB+0 | D86: FS | F86: 46111 | G86: 46134 | H86: 46136 | I86: 46137 | J86: 46137 | K86: 46137 | L86: 46137 | M86: 46143 | N86: Completed | O86: Gulam | P86: 10
A87: =A86+1 -> 81 | B87: 46/2 | C87: DA+0 | D87: PS(SD) | F87: 46094 | G87: 46108 | H87: 46109 | I87: 46109 | J87: 46109 | K87: 46109 | L87: 46109 | M87: 46111 | N87: Completed | O87: Pawan Kumar Shama | P87: 12
A88: =A87+1 -> 82 | B88: 15/3 | C88: DA+9 | D88: FS | F88: 46094 | G88: 46110 | H88: 46111 | I88: 46111 | J88: 46111 | K88: 46111 | L88: 46111 | M88: 46144 | N88: Completed | O88: Anil Sharma | P88: 10
A89: =A88+1 -> 83 | B89: 38/1 | C89: DA+3 | D89: FS | F89: 46103 | G89: 46110 | H89: 46111 | I89: 46111 | J89: 46111 | K89: 46111 | L89: 46111 | M89: 46120 | N89: Completed | O89: Pawan Kumar Shama-2 | P89: 8
A90: =A89+1 -> 84 | B90: 42/3 | C90: DA+0 | D90: PS | F90: 46106 | G90: 46111 | H90: 46112 | I90: 46112 | J90: 46112 | K90: 46112 | L90: 46112 | M90: 46120 | N90: Completed | O90: Thakur Cosnt | P90: 16
A91: =A90+1 -> 85 | B91: 47/1 | C91: DA+0 1M | D91: PS | F91: 46107 | G91: 46116 | H91: 46117 | I91: 46117 | J91: 46117 | K91: 46117 | L91: 46117 | M91: 46144 | N91: Completed | O91: Sufiyan Ali | P91: 14
A92: =A91+1 -> 86 | B92: AP47 | C92: DB+0 | D92: PS (SD) | F92: 46130 | G92: 46136 | H92: 46137 | I92: 46137 | J92: 46137 | K92: 46138 | L92: 46138 | M92: 46144 | N92: Completed | O92: Sufiyan Ali | P92: 12
A93: =A92+1 -> 87 | B93: 40/2 | C93: DA+3 | D93: PS | F93: 46112 | G93: 46124 | H93: 46125 | I93: 46125 | J93: 46125 | K93: 46125 | L93: 46125 | M93: 46147 | N93: Completed | O93: Pawan Sharma-2 | P93: 10
A94: =A93+1 -> 88 | B94: AP7 | C94: DD+30 | D94: WET | F94: 46113 | G94: 46128 | H94: 46133 | I94: 46137 | J94: 46141 | K94: 46141 | L94: 46141 | N94: Completed | O94: Anil Sharma | P94: 10
A95: =A94+1 -> 89 | B95: 42/2 | C95: DA+0 | D95: FS | F95: 46123 | G95: 46127 | H95: 46128 | I95: 46128 | J95: 46128 | K95: 46128 | L95: 46128 | M95: 46143 | N95: Completed | O95: Thakur Cosnt | P95: 14
A96: =A95+1 -> 90 | B96: AP1 | C96: DD+0 | D96: DFR | F96: 46121 | G96: 46129 | H96: 46130 | I96: 46130 | J96: 46130 | K96: 46130 | L96: 46130 | M96: 46143 | N96: Completed | O96: Pawan Sharma-1 | P96: 12
A97: =A96+1 -> 91 | B97: AP6 | C97: DD+9 | D97: WET | F97: 46123 | G97: 46141 | H97: 46142 | I97: 46142 | J97: 46142 | K97: 46142 | L97: 46142 | N97: Completed | O97: Balwanth Singh | P97: 10
A98: =A97+1 -> 92 | B98: AP41 | C98: DD+30 | D98: PS | F98: 46130 | G98: 46141 | H98: 46142 | I98: 46142 | J98: 46142 | K98: 46142 | L98: 46142 | M98: 46148 | N98: Completed | O98: Pawan Sharma-2 | P98: 10
A99: =A98+1 -> 93 | B99: 37/1 | C99: DA+3 | D99: FS | F99: 46136 | G99: 46140 | H99: 46141 | I99: 46141 | J99: 46141 | K99: 46141 | L99: 46141 | M99: 46145 | N99: Completed | O99: Pawan Sharma-1 | P99: 12
A100: =A99+1 -> 94 | B100: AP38 | C100: DB+0 | D100: PS | F100: 46145 | G100: 46155 | H100: 46156 | I100: 46156 | J100: 46156 | K100: 46156 | L100: 46156 | N100: Completed | O100: Pawan Sharma-1 | P100: 12
A101: =A100+1 -> 95 | B101: 40/3 | C101: DB+3 | D101: FS | F101: 46147 | G101: 46157 | H101: 46158 | I101: 46158 | J101: 46158 | K101: 46158 | L101: 46158 | N101: Completed | O101: Pawan Sharma-2 | P101: 10
...

Sheet Sheet10
C1: S.No | D1: Loc | E1: TOT | F1: Classification | G1: M10 | H1: M20
C2: 1 | D2: 29/2 | E2: DA+3 | F2: PS (SD) | G2: 7.812 | H2: 51.824
C3: =C2+1 -> 2 | D3: 33/2 | E3: DA+0 | F3: PS | G3: 4.822 | H3: 35.692
C4: =C3+1 -> 3 | D4: 46/5 | E4: DA+6 | F4: FS | G4: 6.138 | H4: 43.392
C5: =C4+1 -> 4 | D5: 50A/3 | E5: DA+3 | F5: PS (SD) | G5: 7.812 | H5: 51.824
C6: =C5+1 -> 5 | D6: AP14 | E6: DB+9 | F6: DFR | G6: 4.177 | H6: 46.652
C7: =C6+1 -> 6 | D7: AP24 | E7: DC+3 | F7: PS | G7: 10.31 | H7: 107.913
C8: =C7+1 -> 7 | D8: 43/3 | E8: DA+3 | F8: PS | G8: 4.822 | H8: 35.692
C9: =C8+1 -> 8 | D9: 43/4 | E9: DA+0 | F9: PS(SD) | G9: 7.442 | H9: 49.652
C10: =C9+1 -> 9 | D10: 46/4 | E10: DA+0 | F10: FS | G10: 5.789 | H10: 41.344
C11: =C10+1 -> 10 | D11: 46/2 | E11: DA+0 | F11: PS(SD) | G11: 7.442 | H11: 49.652
C12: =C11+1 -> 11 | D12: 38/1 | E12: DA+3 | F12: FS | G12: 6.138 | H12: 43.392
C13: =C12+1 -> 12 | D13: AP35 | E13: DD+0 | F13: FS | G13: 16.453 | H13: 192.504
C14: =C13+1 -> 13 | D14: 15/3 | E14: DA+9 | F14: FS | G14: 6.138 | H14: 43.392
C15: =C14+1 -> 14 | D15: AP148 | E15: DD+25 2MRC | F15: PS | G15: =3.248*4 -> 12.992 | H15: =43.355*4 -> 173.42
C16: =C15+1 -> 15 | D16: AP69 | E16: DB+0 | F16: PS (SD) | G16: 11.705 | H16: 102.852
C17: =C16+1 -> 16 | D17: AP149 | E17: DD+25 | F17: PS | G17: 12.993 | H17: 156.08 | O17: =1465.821 -> 1465.821
C18: =C17+1 -> 17 | D18: 67/2 | E18: DA+0 | F18: PS (SD) | G18: 7.442 | H18: 49.652 | O18: =O17*15000/10^7 -> 2.1987315
C19: =C18+1 -> 18 | D19: AP127 | E19: DD+30 2MRC | F19: PS | G19: =3.097*4 -> 12.388 | H19: =41.768*4 -> 167.072 | O19: =759*15000/10^7 -> 1.1385
C20: =C19+1 -> 19 | D20: AP136 | E20: DC+3 | F20: WET | G20: 9.33 | H20: 99.608
C21: =C20+1 -> 20 | D21: 67/1 | E21: DA+0 | F21: PS(SD) | G21: 7.442 | H21: 49.652
C22: =C21+1 -> 21 | D22: AP145 | E22: DB+0 | F22: PS (SD) | G22: 11.705 | H22: 102.852
C23: =C22+1 -> 22 | D23: AP67 | E23: DD+0 | F23: PS(SD) | G23: 20.402 | H23: 231.904
C24: =C23+1 -> 23 | D24: 152/3 | E24: DA+0 1M RC | F24: PS | G24: =1.206*4 -> 4.824 | H24: =10.67*4 -> 42.68
C25: =C24+1 -> 24 | D25: AP71 | E25: DC+9 | F25: PS (SD) | G25: 16.745 | H25: 160.736
C26: =C25+1 -> 25 | D26: 56/3 | E26: DA+6 | F26: PS (SD) | G26: 7.812 | H26: 51.824
C27: =C26+1 -> 26 | D27: AP152 | E27: DD+0 | F27: WET | G27: 12.168 | H27: 147.432
C28: =C27+1 -> 27 | D28: AP108 | E28: DD+25 | F28: PS | G28: 12.993 | H28: 156.08
C29: =C28+1 -> 28 | D29: AP83 | E29: DD+25 | F29: DFR | G29: 6.728 | H29: 90.848
C30: =C29+1 -> 29 | D30: AP10 | E30: DB+9 | F30: DFR | G30: 4.177 | H30: 46.652 | M30: =1818.493*15000/10^7 -> 2.7277395
C31: =C30+1 -> 30 | D31: AP24 | E31: DC+0 | F31: DFR | G31: 5.202 | H31: 64.882
C32: =C31+1 -> 31 | D32: AP6 | E32: DC+9 | F32: DFR | G32: 5.597 | H32: 68.18 | M32: =255*15000/10^7 -> 0.3825
C33: =C32+1 -> 32 | D33: AP95 | E33: DD+0 | F33: DFR | G33: 7.393 | H33: 97.712
C34: =C33+1 -> 33 | D34: AP40 | E34: DB-3 | F34: DFR | G34: 3.89 | H34: 44.472
C35: =C34+1 -> 34 | D35: AP82 | E35: DD+18 | F35: DFR | G35: 6.728 | H35: 90.848
G36: =SUM(G2:G35) -> 295.951 | H36: =SUM(H2:H35) -> 2988.363
D40: 29/2
D41: 33/2
D42: 46/5
D43: 50A/3
D44: AP14
D45: AP24
D46: 43/3
D47: 43/4
D48: 46/4
D49: AP148
D50: AP69
D51: AP149
... D55: 67/1

Sheet Erection -Jammu
A1: KEC INTERNATIONAL LIMITED | I1: Date: | J1: ='TB-605'!E1 -> 46161
A2: 400 kV Samba- Jalandhar D/C Line(Quad) - Wind Zone - 5-Jammu Portion
A3: TOWER ERECTION
A5: S.No | B5: Loc No. | C5: Tower Type | D5: Weight MT | E5: Conc Volume | F5: Starting Date | G5: Completion Date | H5: Status | I5: Gang Name | J5: Gang Strength | K5: Remark
A7: 1 | B7: 29/5 | C7: DA+0 | D7: 18.339 | E7: 34.389 | F7: 45988 | G7: 45994 | H7: Completed | I7: Raj Labour Suppliers | J7: 23
A8: =A7+1 -> 2 | B8: 29/4 | C8: DA+0 | D8: 18.339 | E8: 21.318 | F8: 45996 | G8: 46001 | H8: Completed | I8: Raj Labour Suppliers | J8: 23
A9: =A8+1 -> 3 | B9: 27/0 | C9: DB+0 | D9: 27.92 | E9: 21.318 | F9: 46002 | G9: 45982 | H9: Completed | I9: Raj Labour Suppliers | J9: 23
A10: 4 | B10: 29/6 | C10: DA+3 | D10: 19.44 | F10: 46013 | G10: 46020 | H10: Completed | I10: Raj Labour Suppliers | J10: 20
A11: =A10+1 -> 5 | B11: 15/1 | C11: DA+0 | D11: 18.339 | F11: 46016 | G11: 46027 | H11: Completed | I11: Anbi Construction | J11: 15
A12: =A11+1 -> 6 | B12: 30/3 | C12: DA+6 | D12: 22.68 | F12: 46020 | G12: 46030 | H12: Completed | I12: Raj Labour Suppliers | J12: 20
A13: =A12+1 -> 7 | B13: 15/2 | C13: DA+0 | D13: 18.339 | F13: 46029 | G13: 46038 | H13: Completed | I13: Anbi Construction | J13: 15
A14: =A13+1 -> 8 | B14: 30/5 | C14: DA+9 | D14: 24.149 | F14: 46031 | G14: 46040 | H14: Completed | I14: Raj Labour Suppliers | J14: 20
A15: =A14+1 -> 9 | B15: AP18 | C15: DC+0 | D15: 32.22 | F15: 46040 | G15: 46053 | H15: Completed | I15: Anbi Construction | J15: 21
A16: =A15+1 -> 10 | B16: 30/4 | C16: DA+0 | D16: 18.339 | F16: 46040 | G16: 46044 | H16: Completed | I16: Raj Labour Suppliers | J16: 22
A17: =A16+1 -> 11 | B17: 31/1 | C17: DA+3 | D17: 19.44 | F17: 46047 | G17: 46054 | H17: Completed | I17: Raj Labour Suppliers | J17: 22
A18: =A17+1 -> 12 | B18: 31/2 | C18: DA+0 | D18: 18.339 | F18: 46054 | G18: 46059 | H18: Completed | I18: Raj Labour Suppliers | J18: 22
A19: =A18+1 -> 13 | B19: 19/2 | C19: DA+0 | D19: 18.339 | F19: 46054 | G19: 46060 | H19: Completed | I19: Anbi Construction | J19: 21
A20: =A19+1 -> 14 | B20: 23/1 | C20: DA+0 | D20: 18.339 | F20: 46058 | G20: 46063 | H20: Completed | I20: Kushboo Devi | J20: 21 | K20: Due to row gang idle for 2 days 07-02-2026 to 08-02-2026
A21: =A20+1 -> 15 | B21: 31/3 | C21: DA+0 | D21: 18.339 | F21: 46059 | G21: 46061 | H21: Completed | I21: Raj Labour Suppliers | J21: 22
A22: =A21+1 -> 16 | B22: 19/1 | C22: DA+0 | D22: 18.339 | F22: 46061 | G22: 46066 | H22: Completed | I22: Anvi Construction | J22: 21
A23: =A22+1 -> 17 | B23: 31/4 | C23: DA+3 | D23: 19.44 | F23: 46062 | G23: 46066 | H23: Completed | I23: Raj Labour Suppliers | J23: 22
A24: =A23+1 -> 18 | B24: AP23 | C24: DB+0 | D24: 27.92 | F24: 46064 | G24: 46068 | H24: Completed | I24: Kushboo Devi | J24: 21
A25: =A24+1 -> 19 | B25: AP32 | C25: DB+0 | D25: =27.921 -> 27.921 | F25: 46066 | G25: 46073 | H25: Completed | I25: Raj Labour Suppliers | J25: 22
A26: =A25+1 -> 20 | B26: AP19 | C26: DC+0 | D26: 32.222 | F26: 46066 | G26: 46077 | H26: Completed | I26: Anvi Construction | J26: 21
A27: =A26+1 -> 21 | B27: 23/5 | C27: DA+3 | D27: 19.44 | F27: 46068 | G27: 46072 | H27: Completed | I27: Kushboo Devi | J27: 21
A28: =A27+1 -> 22 | B28: 40/1 | C28: DA+3 | D28: 19.44 | F28: 46069 | G28: 46076 | H28: Completed | I28: ASC Infra Pvt Ltd | J28: 26
A29: =A28+1 -> 23 | B29: 45/2 | C29: DA+0 | D29: 18.339 | F29: 46070 | G29: 46078 | H29: Completed | I29: Raju Kumar | J29: =18+5 -> 23
A30: =A29+1 -> 24 | B30: 32/1 | C30: DA+6 | D30: 22.68 | F30: 46073 | G30: 46078 | H30: Completed | I30: Raj Labour Suppliers | J30: 22
A31: =A30+1 -> 25 | B31: 23/4 | C31: DA+3 | D31: 19.44 | F31: 46073 | G31: 46075 | H31: Completed | I31: Kushboo Devi | J31: 21
A32: =A31+1 -> 26 | B32: AP26 | C32: DD+0 | D32: 42.226 | F32: 46075 | G32: 46084 | H32: Completed | I32: Kushboo Devi | J32: 21
A33: =A32+1 -> 27 | B33: 39/2 | C33: DA+0 | D33: 18.339 | F33: 46077 | G33: 46081 | H33: Completed | I33: ASC Infra Pvt Ltd | J33: 26
A34: =A33+1 -> 28 | B34: 18/2 | C34: DA+6 | D34: 22.68 | F34: 46077 | G34: 46085 | H34: Completed | I34: Anvi Construction | J34: 21
A35: =A34+1 -> 29 | B35: 31/5 | C35: DA+3 | D35: 19.44 | F35: 46088 | G35: 46091 | H35: Completed | I35: Niva Sarkar Mandal | J35: 20
A36: =A35+1 -> 30 | B36: AP40 | C36: DC+3 | D36: 33.53 | F36: 46081 | G36: 46089 | H36: Completed | I36: ASC Infra Pvt Ltd | J36: 26
A37: =A36+1 -> 31 | B37: 18/1 | C37: DA+0 | D37: 18.339 | F37: 46086 | G37: 46093 | H37: Completed | I37: Anvi Construction | J37: 21
A38: =A37+1 -> 32 | B38: 25/2 | C38: DA+0 | D38: 18.339 | F38: 46086 | G38: 46093 | H38: Completed | I38: Kushboo Devi | J38: 20
A39: =A38+1 -> 33 | B39: 44/3 | C39: DA+0 | D39: 18.339 | F39: 46089 | G39: 46093 | H39: Completed | I39: ASC Infra Pvt Ltd | J39: 26
A40: =A39+1 -> 34 | B40: 29/1 | C40: DA+0 | D40: 18.339 | F40: 46090 | G40: 46104 | H40: Completed | I40: Century Engineering | J40: 18
A41: =A40+1 -> 35 | B41: 44/2 | C41: DA+0 | D41: 18.339 | F41: 46093 | G41: 46097 | H41: Completed | I41: ASC Infra Pvt Ltd | J41: 26
... A79: =A78+1 -> 73 | B79: AP46 | C79: DB+0 | D79: 27.92 | F79: 46152 | G79: 46157 | H79: Completed | I79: ASC Infra Pvt Ltd | J79: 24
A80: =A79+1 -> 74 | B80: AP29 | C80: DC+9 | F80: 46152 | G80: 46158 | H80: Completed | I80: Kushboo Devi-2 | J80: 22
A81: =A80+1 -> 75 | B81: 30/2 | C81: DA+0 | D81: 18.34 | F81: 46157 | G81: 46159 | H81: Completed | I81: Kushboo Devi | J81: 20
A82: =A81+1 -> 76 | B82: AP45 | C82: DB+0 | D82: 27.92 | F82: 46157 | H82: Cross Arm Fitting | I82: ASC Infra Pvt Ltd | J82: 24
A83: =A82+1 -> 77 | B83: 27/1 | C83: DA+3 | D83: 19.44 | F83: 46158 | H83: Completed | I83: Kushboo Devi-2 | J83: 22
A84: =A83+1 -> 78 | B84: 33/1 | C84: DA+0 | D84: 18.34 | F84: 46159 | H84: Material Shifting | I84: Kushboo Devi | J84: 20
A85: =A84+1 -> 79 | B85: AP28 | C85: DC+6 | F85: 46161 | H85: Material Shifting | I85: Kushboo Devi-2 | J85: 22

Sheet Vertical Chart -JS Line Jammu 
A1: KEC INTERNATIONAL LIMITED
A2: 400 kV Samba- Jalandhar D/C Line(Quad) - Wind Zone - 5-Jammu Portion
A3: Vertical Chart
J4: Complete | L4: =COUNTIF($L$8:$L$256,"Clear") -> 95 | M4: =COUNTIF($M$8:$M$256,"C") -> 83 | N4: =COUNTIF($N$8:$N$256,"C") -> 73 | O4: =COUNTIF($O$8:$O$256,"C") -> 59 | P4: =COUNTIF($P$8:$P$256,"C") -> 0
J5: WIP | M5: =COUNTIF($M$8:$M$256,"WIP") -> 9 | N5: =COUNTIF($N$8:$N$256,"WIP") -> 0 | O5: =COUNTIF($O$8:$O$256,"WIP") -> 3 | P5: =COUNTIF($P$8:$P$256,"WIP") -> 0
A6: S.No | B6: Tower | C6: TOT | D6: Angle of Deviation | E6: Raised Chimney | I6: FDN Classification | J6: Span Length (Mtr) | K6: Section Length (m) | L6: ROW | M6: Foundation | N6: Earthing | O6: Tower Erection | P6: Tack Welding | Q6: Stringing | R6: Remarks
E7: LEG A | F7: LEG B | G7: LEG C | H7: LEG D
A8: 1 | B8: AP5 | C8: DD+0 | D8: 47°01'59"LT | E8: 0 | F8: 0 | G8: 0 | H8: 0 | K8: 0
J9: 119.059
A10: =A8+1 -> 2 | B10: AP6 | C10: DD+9 | D10: 40°54'42"RT | E10: 0 | F10: 0 | G10: 0 | H10: 0 | K10: =J9 -> 119.059 | L10: Clear | M10: WIP
J11: 92.496
A12: =A10+1 -> 3 | B12: AP7 | C12: DD+30 | D12: 47°08'48"LT | E12: 4 | F12: 5 | G12: 4 | H12: 3 | I12: WET | K12: =J11 -> 92.496 | L12: Clear | M12: WIP
J13: 134.988 | R13: 400 KV D/C Line Jalandhar to Samba
A14: =A12+1 -> 4 | B14: AP8 | C14: DD+30 | D14: 41°15'08"RT | E14: 4 | F14: 5 | G14: 4 | H14: 3 | K14: =J13 -> 134.988
J15: 365.176
A16: =A14+1 -> 5 | B16: AP9 | C16: DD+9 | D16: 37°05'47"RT | E16: 0 | F16: 0 | G16: 0 | H16: 0 | K16: =J15 -> 365.176
J17: 236.697 | R17: Railway Crossing Electrified (Jammu/Delhi)
A18: =A16+1 -> 6 | B18: AP10 | C18: DD+9 | D18: 20°40'31"LT | E18: 0 | F18: 0 | G18: 0 | H18: 0 | K18: =J17 -> 236.697
J19: 213.252
A20: =A18+1 -> 7 | B20: AP11 | C20: DD+25 | D20: 51°34'02"RT | E20: 0 | F20: 0 | G20: 0 | H20: 0 | K20: =J19 -> 213.252
J21: 206.593 | R21: 400 KV D/C Line Jalandhar to Samba
A22: =A20+1 -> 8 | B22: AP12 | C22: DD+30 | D22: 47°50'13"LT | E22: 0 | F22: 0 | G22: 0 | H22: 0 | I22: WET/PS | K22: =J21 -> 206.593 | L22: Clear | M22: C
J23: 289.862 | R23: 220 KV D/C Line Samba To Hiranagar
A24: =A22+1 -> 9 | B24: AP13 | C24: DD+25 | D24: 39°08'44"LT | E24: 1.5 | F24: 1.5 | G24: 0 | H24: 0 | K24: =J23 -> 289.862
J25: 402.938
A26: =A24+1 -> 10 | B26: AP14 | C26: DB+9 | D26: 14°33'47"RT | E26: 0 | F26: 0 | G26: 2 | H26: 0 | I26: DFR | K26: =J25 -> 402.938 | L26: Clear | M26: C | N26: C
J27: 284.883 | R27: 220 KV D/C Line Bishnah-Hiranagar
A28: =A26+1 -> 11 | B28: AP15 | C28: DD+18 | D28: 4°57'01"LT | E28: 1.5 | F28: 0 | G28: 0 | H28: 0 | I28: WET | K28: =J27 -> 284.883 | L28: Clear | M28: C | N28: C
J29: 412.199
A30: =A28+1 -> 12 | B30: 15/1 | C30: DA+0 | E30: 0 | F30: 0 | G30: 0 | H30: 0 | I30: PS | L30: Clear | M30: C | N30: C | O30: C
J31: 428.128
A32: =A30+1 -> 13 | B32: 15/2 | C32: DA+0 | E32: 0 | F32: 0 | G32: 0 | H32: 0 | I32: FS | L32: Clear | M32: C | N32: C | O32: C
J33: 405.152
A34: =A32+1 -> 14 | B34: 15/3 | C34: DA+9 | E34: 0 | F34: 0 | G34: 0 | H34: 0 | I34: FS | L34: Clear | M34: C | O34: C
J35: 427.96
A36: =A34+1 -> 15 | B36: AP16 | C36: DC+0 | D36: 22°18'18"LT | E36: 0 | F36: 0 | G36: 0 | H36: 0 | I36: FS | K36: =J29+J31+J33+J35 -> 1673.439 | L36: Clear | M36: C | O36: C
J37: 285.948
A38: =A36+1 -> 16 | B38: AP17 | C38: DC+3 | D38: 19°02'28"LT | E38: 0 | F38: 0 | G38: 0 | H38: 0 | I38: FS | K38: =J37 -> 285.948 | L38: Clear | M38: C | N38: C | O38: C
J39: 401.159 | R39: 66 KV H Pole (Sandhi) Ghagwal To Rajpura
A40: =A38+1 -> 17 | B40: AP18 | C40: DC+0 | D40: 24°05'21"RT | E40: 0 | F40: 0 | G40: 0 | H40: 0 | I40: FS | K40: =J39 -> 401.159 | L40: Clear | M40: C | N40: C | O40: C
J41: 345
A42: =A40+1 -> 18 | B42: 18/1 | C42: DA+0 | E42: 0 | F42: 0 | G42: 0 | H42: 0 | I42: PS | L42: Clear | M42: C | N42: C | O42: C
J43: 360.001
A44: =A42+1 -> 19 | B44: 18/2 | C44: DA+6 | E44: 0 | F44: 0 | G44: 0 | H44: 0 | I44: FS | L44: Clear | M44: C | N44: C | O44: C
J45: 350.217
A46: =A44+1 -> 20 | B46: AP19 | C46: DC+0 | D46: 24°17'20"LT | E46: 0 | F46: 0 | G46: 0 | H46: 0 | I46: FS | K46: =J41+J43+J45 -> 1055.218 | L46: Clear | M46: C | N46: C | O46: C
J47: 369.999
A48: =A46+1 -> 21 | B48: 19/1 | C48: DA+0 | E48: 0 | F48: 0 | G48: 0 | H48: 0 | I48: PS | L48: Clear | M48: C | N48: C | O48: C
J49: 360
A50: =A48+1 -> 22 | B50: 19/2 | C50: DA+0 | E50: 0 | F50: 0 | G50: 0 | H50: 0 | I50: FS | L50: Clear | M50: C | N50: C | O50: C
J51: 358.748
A52: =A50+1 -> 23 | B52: AP20 | C52: DB+6 | D52: 5°25'51"RT | E52: 1.5 | F52: 1.5 | G52: 1.5 | H52: 1.5 | I52: WET | K52: =J47+J49+J51 -> 1088.747 | L52: Clear | M52: C | N52: C | O52: C
J53: 485.93
A54: =A52+1 -> 24 | B54: AP21 | C54: DD+6 | D54: 39°17'49" RT | E54: 1.5 | F54: 1.5 | G54: 1.5 | H54: 1.5 | I54: WET | K54: =J53 -> 485.93 | L54: Clear | M54: C
J55: 325
A56: =A54+1 -> 25 | B56: 21/1 | C56: DA+0 | E56: 0 | F56: 0 | G56: 0 | H56: 0 | I56: WET | L56: Clear | M56: C | N56: C
J57: 387.337
A58: =A56+1 -> 26 | B58: AP22 | C58: DC+3 | D58: 15°58'43"LT | E58: 0 | F58: 0 | G58: 0 | H58: 0 | I58: WET | K58: =J55+J57 -> 712.337 | L58: Clear | M58: C | N58: C
J59: 390
A60: =A58+1 -> 27 | B60: 22/1 | C60: DA+3 | E60: 0 | F60: 0 | G60: 0 | H60: 0 | I60: WET | L60: Clear | M60: C | N60: C
J61: 388.629
A62: 28 | B62: 22/2 | C62: DA+3 | E62: 0 | F62: 0 | G62: 0 | H62: 0 | I62: WET | L62: Clear | M62: C | N62: C
J63: 398.45
A64: 29 | B64: AP23 | C64: DB+0 | D64: 9°30'47"LT | E64: 0 | F64: 0 | G64: 0 | H64: 0 | I64: FS | K64: =J59+J61+J63 -> 1177.079 | L64: Clear | M64: C | N64: C | O64: C
J65: 435.999
A66: 30 | B66: 23/1 | C66: DA+6 | E66: 0 | F66: 0 | G66: 0 | H66: 0 | I66: WET | L66: Clear | M66: C | N66: C | O66: C
J67: 384
A68: 31 | B68: 23/2 | C68: DA+3 | E68: 0 | F68: 0 | G68: 0 | H68: 0 | L68: Clear | M68: WIP
J69: 420
A70: 32 | B70: 23/3 | C70: DA+3 | E70: 0 | F70: 0 | G70: 0 | H70: 0 | L70: Clear
J71: 410
A72: 33 | B72: 23/4 | C72: DA+3 | E72: 0 | F72: 0 | G72: 0 | H72: 0 | I72: FS | L72: Clear | M72: C | N72: C | O72: C
J73: 407.25
A74: 34 | B74: 23/5 | C74: DA+3 | E74: 0 | F74: 0 | G74: 0 | H74: 0 | I74: FS | L74: Clear | M74: C | N74: C | O74: C
J75: 397.702
A76: 35 | B76: AP24 | C76: DC+3 | D76: 26°6'39"RT | E76: 0 | F76: 0 | G76: 0 | H76: 0 | I76: PS | K76: =J65+J67+J69+J71+J73+J75 -> 2454.951 | L76: Clear | M76: C | N76: C | O76: C
J77: 366.004
A78: 36 | B78: AP25 | C78: DD+0 | D78: 36°50'56"LT | E78: 0 | F78: 0 | G78: 0 | H78: 0 | I78: FS | K78: =J77 -> 366.004 | L78: Clear | M78: C | N78: C | O78: C
J79: 372.4
A80: 37 | B80: 25/1 | C80: DA+0 | E80: 0 | F80: 0 | G80: 0 | H80: 0 | I80: PS | L80: Clear | M80: C | N80: C | O80: C
J81: 311.866
A82: 38 | B82: 25/2 | C82: DA+0 | E82: 0 | F82: 0 | G82: 0 | H82: 0 | I82: FS | L82: Clear | M82: C | N82: C | O82: C
J83: 343.763
A84: 39 | B84: AP26 | C84: DD+0 | D84: 51°30'37"RT | E84: 0 | F84: 0 | G84: 0 | H84: 0 | I84: FS | K84: =J79+J81+J83 -> 1028.029 | L84: Clear | M84: C | N84: C | O84: C
J85: 442.371
A86: 40 | B86: AP27 | C86: DB+0 | D86: 10°41'20"RT | E86: 0 | F86: 0 | G86: 0 | H86: 0 | I86: WET | K86: =J85 -> 442.371 | L86: Clear | M86: C | N86: C | O86: C
J87: 360
A88: 41 | B88: 27/1 | C88: DA+3 | E88: 1.5 | G88: 1.5 | H88: 2.5 | I88: WET | L88: Clear | M88: C | N88: C
J89: 379.739
A90: 42 | B90: AP28 | C90: DC+6 | D90: 27°47'33"LT | E90: 1.5 | F90: 2.5 | G90: 1.5 | H90: 1.5 | I90: WET | K90: =J87+J89 -> 739.739 | L90: Clear | M90: C | N90: C
J91: 445.991
A92: 43 | B92: AP29 | C92: DC+9 | D92: 22°59'55"LT | E92: 1.5 | F92: 3 | G92: 3 | H92: 1.5 | I92: WET | K92: =J91 -> 445.991 | L92: Clear | M92: C | N92: C
J93: 373
A94: 44 | B94: 29/1 | C94: DA+0 | E94: 1.5 | F94: 1.5 | G94: 0 | H94: 0 | I94: WET | L94: Clear | M94: C | N94: C | O94: C
J95: 374
A96: 45 | B96: 29/2 | C96: DA+3 | E96: 1 | F96: 1 | G96: 1 | H96: 1 | I96: PS(SD) | L96: Clear | M96: C | N96: C | O96: WIP
J97: 352
A98: 46 | B98: 29/3 | C98: DA+0 | E98: 1.5 | F98: 0 | G98: 0 | H98: 0 | I98: DRY | L98: Clear | M98: C
J99: 406
A100: 47 | B100: 29/4 | C100: DA+0 | E100: 0 | F100: 0 | G100: 0 | H100: 0 | I100: DRY | L100: Clear | M100: C | N100: C | O100: C
...

Sheet Sheet17
B2: S.No | C2: Line | D2: Portion | E2: Line Qty | F2: Foundation Completed | G2: Tower Erection Completed | H2: Tower Erection WIP | I2: Gap between Foundation & Erection | J2: Tower Erection Gangs Available at Site | K2: Remarks
B3: 1 | C3: Samba-Jalandhar | D3: Jammu | E3: 137 | F3: 81 | G3: 51 | H3: 4 | I3: =F3-G3-H3 -> 26 | J3: 5 | K3: 10 locations ROW clear - Work front for 5 gangs i.e; 2 loc per gang 2 Locations -supply of DD18/25/30 Extensions required 5 locations -Crop harvesting required 4 locations under ROW
B4: =B3+1 -> 2 | C4: Samba-Jalandhar | D4: Punjab | E4: 262 | F4: 154 | G4: 66 | H4: 6 | I4: =F4-G4-H4 -> 82 | J4: 7 | K4: 4 locations - ROW Clear 9 Locations - Supply of DD 18/25/30 extensions required 1 locations - Transposition tower supply required Due to standing crop (wheat) at maximum locations farmers are not allowing for tower erection work . Expected for crop harvesting in next 1 week time
B5: =B4+1 -> 3 | C5: Samba-Kishenpur | E5: 116 | F5: 44 | G5: 2 | H5: 1 | I5: =F5-G5-H5 -> 41 | J5: 1 | K5: 8 locations - ROW Clear 27 locations - supply of unequal leg extensions required / DD18/25/30 M extension required 5 locations under ROW

Sheet Erection -SK
A1: KEC INTERNATIONAL LIMITED | I1: Date: | J1: ='TB-605'!E1 -> 46161
A2: 400kV D/C Samba -Kishenpur TL
A3: TOWER ERECTION
A5: S.No | B5: Loc No. | C5: Tower Type | D5: Weight MT | E5: Conc Volume | F5: Starting Date | G5: Completion Date | H5: Status | I5: Gang Name | J5: Gang Strength | K5: Remark
A7: 1 | B7: 30/1 | C7: DA+0 | D7: 18.34 | F7: 46099 | G7: 46105 | H7: Completed | I7: Anvi Construction | J7: 18
A8: =A7+1 -> 2 | B8: AP27A | C8: DB+6 | D8: 34.578 | F8: 46105 | G8: 46112 | H8: Completed | I8: Anvi Construction | J8: 23
A9: =A8+1 -> 3 | B9: AP31 | C9: DB+9 | F9: 46121 | H9: Cage Part | I9: Anvi Construction | J9: 18 | K9: Work restart from 16-05-2026

Sheet Sheet7
B3: S.No | C3: Loc | D3: TOT | E3: RC | F3: RC | G3: RC | H3: RC
B4: 1 | C4: AP144 | D4: DB+0
B5: =B4+1 -> 2
B6: =B5+1 -> 3
B7: =B6+1 -> 4 | E7: 1 | F7: 1 | G7: 1 | H7: 1
B8: =B7+1 -> 5
B9: =B8+1 -> 6 | C9: AP145 | D9: DB+0 | E9: 2 | F9: 2 | G9: 2 | H9: 2
B10: =B9+1 -> 7
B11: =B10+1 -> 8
B12: =B11+1 -> 9
B13: =B12+1 -> 10
B14: =B13+1 -> 11
B15: =B14+1 -> 12 | I15: Hussain
B16: =B15+1 -> 13 | I16: Hussain
B17: =B16+1 -> 14 | I17: Hussain
B18: =B17+1 -> 15 | I18: Hussain
B19: =B18+1 -> 16
B20: =B19+1 -> 17
B21: =B20+1 -> 18
B22: =B21+1 -> 19 | E22: 1 | F22: 1 | G22: 1 | H22: 1
B23: =B22+1 -> 20
B24: =B23+1 -> 21
B25: =B24+1 -> 22
B26: =B25+1 -> 23
B27: =B26+1 -> 24
B28: =B27+1 -> 25
B29: =B28+1 -> 26
B30: =B29+1 -> 27
B31: =B30+1 -> 28
B32: =B31+1 -> 29
B33: =B32+1 -> 30
B34: =B33+1 -> 31
... B48: =B47+1 -> 45
B49: =B48+1 -> 46 | C49: AP66 | D49: DC+0
B50: =B49+1 -> 47 | C50: AP67 | D50: DD+0
B51: =B50+1 -> 48 | C51: 67/1 | D51: DA+0
B52: =B51+1 -> 49 | C52: 67/2 | D52: DA+0
B53: =B52+1 -> 50 | C53: 67/3 | D53: DA+0
B54: =B53+1 -> 51 | C54: AP68 | D54: DB+0
B55: =B54+1 -> 52
B56: =B55+1 -> 53
B57: =B56+1 -> 54
B58: =B57+1 -> 55 | C58: 69/3 | D58: DA+0
B59: =B58+1 -> 56 | C59: AP70 | D59: DC+3

Sheet Sheet8
C2: Tower | D2: Structure | E2: Supplied Qty till date | F2: Material DI received and will dispatch in 1 week | G2: Total | I2: Tower | J2: Supplied Qty | K2: Material Under Transit | L2: Total
C3: DA | D3: Basic Tower Body | E3: =34+39+12+2 -> 87 | G3: =E3+F3 -> 87 | I3: DA+0 | J3: 34 | L3: =J3+K3 -> 34
D4: +0MBE | E4: =34+12+2 -> 48 | G4: =E4+F4 -> 48 | I4: DA+3 | J4: 39 | L4: =J4+K4 -> 39
D5: +3MBE | E5: 39 | G5: =E5+F5 -> 39 | I5: DA+6 | J5: 12 | L5: =J5+K5 -> 12
D6: +6MBE | E6: 12 | G6: =E6+F6 -> 12 | I6: DA+9 | J6: 2 | L6: =J6+K6 -> 2
D7: +9MBE | E7: 2 | G7: =E7+F7 -> 2 | L7: =J7+K7 -> 0
C9: DB | D9: Basic Tower Body | E9: =10+2+1 -> 13 | F9: 16 | G9: =E9+F9 -> 29 | I9: DB+0 | J9: 10 | K9: 14 | L9: =J9+K9 -> 24
D10: +0MBE | E10: 11 | F10: 16 | G10: =E10+F10 -> 27 | I10: DB+3 | J10: 2 | L10: =J10+K10 -> 2
D11: +3MBE | E11: 2 | G11: =E11+F11 -> 2 | I11: DB+6 | J11: 1 | L11: =J11+K11 -> 1
D12: +6MBE | E12: 1 | G12: =E12+F12 -> 1 | I12: DB+9 | K12: 2 | L12: =J12+K12 -> 2
D13: +9MBE | F13: 2 | G13: =E13+F13 -> 2 | L13: =J13+K13 -> 0
C15: DC | D15: Basic Tower Body | E15: 5 | G15: =E15+F15 -> 5 | I15: DC+0 | L15: =J15+K15 -> 0
D16: +0MBE | E16: 2 | G16: =E16+F16 -> 2 | I16: DC+3 | J16: 3 | L16: =J16+K16 -> 3
D17: +3MBE | E17: 3 | G17: =E17+F17 -> 3 | I17: DC+6 | J17: 2 | L17: =J17+K17 -> 2
D18: +6MBE | E18: 2 | G18: =E18+F18 -> 2 | I18: DC+9 | L18: =J18+K18 -> 0
D19: +9MBE | L19: =J19+K19 -> 0
C21: DD | D21: Basic Tower Body | E21: 5 | F21: =20-1 -> 19 | G21: =E21+F21 -> 24 | I21: DD+0 | K21: 13 | L21: =J21+K21 -> 13
D22: +0MBE | E22: 2 | F22: 18 | G22: =E22+F22 -> 20 | I22: DD+3 | J22: 3 | K22: 1 | L22: =J22+K22 -> 4
D23: +3MBE | E23: 3 | F23: 1 | G23: =E23+F23 -> 4 | I23: DD+6 | J23: 2 | L23: =J23+K23 -> 2
D24: +6MBE | E24: 2 | G24: =E24+F24 -> 2 | I24: DD+9 | K24: 5 | L24: =J24+K24 -> 5
D25: +9MBE | F25: 5 | G25: =E25+F25 -> 5 | L25: =J25+K25 -> 0
D26: +18MBE | L26: =J26+K26 -> 0
D27: +25MBE | L27: =J27+K27 -> 0
D28: +30MBE | L28: =J28+K28 -> 0
C29: Total | E29: =E21+E15+E9+E3 -> 110 | F29: =F21+F15+F9+F3 -> 35 | G29: =G21+G15+G9+G3 -> 145 | I29: Total | J29: =SUM(J3:J28) -> 110 | K29: =SUM(K3:K28) -> 35 | L29: =SUM(L3:L28) -> 145

Sheet LILO
A1: KEC INTERNATIONAL LIMITED | N1: Date: | O1: ='TB-605'!E1 -> 46161
A2: LILO Kishtwar - Wind Zone - 2
A3: FOUNDATION
A5: S.No | B5: Loc No. | C5: Tower Type | D5: Classification | E5: Conc Volume | F5: Start Date | G5: Foundation | L5: Completion Date | M5: Status | N5: Gang Name | O5: Gang Strength | P5: Remark
G6: Excavation | H6: Stub Setting | I6: PCC | J6: Rebar Placing | K6: RCC
A7: 1 | B7: AP7 | C7: DDM+E0+0 | D7: DFR | E7: =31.932+4.177 -> 36.109 | F7: 46121 | M7: WIP | N7: Zaffar | O7: 12 | P7: Pit D-Casting upto 1st part chimney Pit C - Casting upto 1st part chimney Pit A - Casting Completed Pit B- Excavation
A8: =A7+1 -> 2 | B8: AP8 | C8: DDM+E6+3 | D8: DFR | E8: =31.932+4.177 -> 36.109 | F8: 46109 | M8: WIP | N8: Bittu | O8: 8 | P8: Pit A - Casting upto frustrum
A9: =A8+1 -> 3 | B9: AP9 | C9: DDM+E0+0 | D9: DFR | E9: =31.932+4.177 -> 36.109 | F9: 46110 | M9: WIP | N9: Bhat Const. | O9: 7 | P9: Excavation WIP
A10: =A9+1 -> 4 | B10: AP10 | C10: DDM+E6+3 | D10: DFR | E10: =31.932+4.177 -> 36.109 | F10: 46140 | M10: WIP | N10: Bhat Const. | O10: 7 | P10: Excavation WIP
A11: =A10+1 -> 5 | B11: 8/1 | C11: DDM+E6+3 | D11: DFR | E11: =31.932+4.177 -> 36.109 | F11: 46160 | M11: WIP | N11: Bittu | O11: 5 | P11: Excavation WIP
A12: =A11+1 -> 6 | B12: AP6 | C12: DDM+E0+0 | D12: DFR | E12: =31.932+4.177 -> 36.109 | F12: 46150 | M12: WIP | N12: Zaffar | O12: 8 | P12: Excavation WIP

Sheet Erection-Punjab
A1: KEC INTERNATIONAL LIMITED | I1: Date: | J1: ='TB-605'!E1 -> 46161
A2: 400 kV Samba- Jalandhar D/C Line(Quad) - Wind Zone - 5- Punjab Portion
A3: TOWER ERECTION
A5: S.No | B5: Loc No. | C5: Tower Type | D5: Weight MT | E5: Conc Volume | F5: Starting Date | G5: Completion Date | H5: Status | I5: Gang Name | J5: Gang Strength | K5: Remark
A7: 1 | B7: 89/1 | C7: DA+3 | D7: 19.44 | E7: 34.389 | F7: 46055 | G7: 46059 | H7: Completed | I7: Saritha Devi | J7: 30
A8: =A7+1 -> 2 | B8: 117/3 | C8: DA+0 | D8: 18.339 | F8: 46056 | G8: 46060 | H8: Completed | I8: Poonam Kumari | J8: 34
A9: =A8+1 -> 3 | B9: 95/3 | C9: DA+0 | D9: 18.339 | F9: 46059 | G9: 46061 | H9: Completed | I9: Saritha Devi | J9: 30
A10: =A9+1 -> 4 | B10: 97/2 | C10: DA+0 | D10: 18.339 | F10: 46058 | G10: 46062 | H10: Completed | I10: Jwala Singh | J10: 22
A11: =A10+1 -> 5 | B11: 92/2 | C11: DA+6 | D11: 22.68 | E11: 21.318 | F11: 46055 | G11: 46063 | H11: Completed | I11: Dhruv Strategic | J11: 32
A12: =A11+1 -> 6 | B12: 117/1 | C12: DA+0 | D12: 18.339 | F12: 46060 | G12: 46064 | H12: Completed | I12: Poonam Kumari | J12: 34
A13: =A12+1 -> 7 | B13: 95/2 | C13: DA+0 | D13: 18.339 | F13: 46061 | G13: 46064 | H13: Completed | I13: Saritha Devi | J13: 30
A14: =A13+1 -> 8 | B14: 97/1 | C14: DA+0 | D14: 18.339 | F14: 46062 | G14: 46065 | H14: Completed | I14: Jwala Singh | J14: 22
A15: =A14+1 -> 9 | B15: 95/4 | C15: DA+0 | D15: 18.339 | F15: 46064 | G15: 46066 | H15: Completed | I15: Saritha Devi | J15: 30
A16: =A15+1 -> 10 | B16: 117/2 | C16: DA+3 | D16: 19.44 | F16: 46064 | G16: 46069 | H16: Completed | I16: Poonam Kumari-1 | J16: 34
A17: =A16+1 -> 11 | B17: 92/3 | C17: DA+0 | D17: 18.339 | F17: 46065 | G17: 46069 | H17: Completed | I17: Poonam Kumari-2 | J17: 30
A18: =A17+1 -> 12 | B18: 131/4 | C18: DA+0 | D18: 18.339 | F18: 46065 | G18: 46070 | H18: Completed | I18: ZR Construction | J18: 30
A19: =A18+1 -> 13 | B19: 97/3 | C19: DA+3 | D19: 19.44 | F19: 46065 | G19: 46070 | H19: Completed | I19: Jwala Singh | J19: 22
A20: =A19+1 -> 14 | B20: AP96 | C20: DC+0 | D20: 32.222 | F20: 46066 | G20: 46070 | H20: Completed | I20: Saritha Devi | J20: 30
A21: =A20+1 -> 15 | B21: 93/2 | C21: DA+0 | D21: 18.339 | F21: 46070 | G21: 46073 | H21: Completed | I21: Poonam Kumari-2 | J21: 30
A22: =A21+1 -> 16 | B22: AP115 | C22: DB+0 | D22: 27.92 | F22: 46069 | G22: 46073 | H22: Completed | I22: Poonam Kumari-1 | J22: 34
A23: =A22+1 -> 17 | B23: 98/1 | C23: DA+3 | D23: 19.44 | F23: 46070 | G23: 46073 | H23: Completed | I23: Jwala Singh | J23: 22
... A45: =A44+1 -> 39 | B45: 156/4 | C45: DA+0 | D45: 18.34 | F45: 46088 | G45: 46094 | H45: Completed | I45: Vijay Bhagat | J45: 25
A46: =A45+1 -> 40 | B46: 130/2 | C46: DA+0 | D46: 18.34 | F46: 46089 | G46: 46094 | H46: Completed | I46: ZR Construction | J46: 30 | K46: Due to ROW work hampered on 09-03-2026
A47: =A46+1 -> 41 | B47: 90/2 | C47: DA+0 | D47: 18.34 | F47: 46090 | G47: 46093 | H47: Completed | I47: Saritha Devi | J47: 30
A48: =A47+1 -> 42 | B48: AP102 | C48: DB+0 | D48: 27.92 | F48: 46092 | G48: 46095 | H48: Completed | I48: Jwala Singh | J48: 22
A49: =A48+1 -> 43 | B49: AP77 | C49: DB+3 | D49: 29.492 | F49: 46092 | G49: 46098 | H49: Completed | I49: Rakesh | J49: 23
A50: =A49+1 -> 44 | B50: 95/1 | C50: DA+0 | D50: 18.34 | F50: 46093 | G50: 46096 | H50: Completed | I50: Saritha Devi | J50: 30
A51: =A50+1 -> 45 | B51: 131/6 | C51: DA+9 | D51: 24.149 | F51: 46094 | G51: 46100 | H51: Completed | I51: ZR Construction | J51: 30
A52: =A51+1 -> 46 | B52: AP157 | C52: DB+0 | D52: 27.92 | F52: 46094 | G52: 46102 | H52: Completed | I52: Vijay Bhagat | J52: 25
A53: =A52+1 -> 47 | B53: AP111 | C53: DC+0 | D53: 32.222 | F53: 46094 | G53: 46103 | H53: Completed | I53: Poonam Kumari | J53: 30
A54: =A53+1 -> 48 | B54: AP100 | C54: DC+3 | D54: 33.53 | F54: 46095 | G54: 46100 | H54: Completed | I54: Jwala Singh | J54: 22
A55: =A54+1 -> 49 | B55: 69/3 | C55: DA+0 | D55: 18.34 | F55: 46098 | G55: 46102 | H55: Completed | I55: Saritha Devi | J55: 30
A56: =A55+1 -> 50 | B56: 77/1 | C56: DA+3 | D56: 19.44 | F56: 46098 | G56: 46103 | H56: Completed | I56: Rakesh | J56: 23
A57: =A56+1 -> 51 | B57: 136/1 | C57: DA+3 | D57: 19.44 | F57: 46102 | G57: 46112 | H57: Completed | I57: ZR Construction | J57: 30
A58: =A57+1 -> 52 | B58: AP104 | C58: DB+0 | D58: 27.92 | F58: 46101 | G58: 46104 | H58: Completed | I58: Jwala Singh | J58: 22
... A115: =A114+1 -> 109 | B115: 152/4 | C115: DA+0 | D115: 18.34 | F115: 46156 | G115: 46158 | H115: Completed | I115: Jwala Singh | J115: 25
A116: =A115+1 -> 110 | B116: 130/1 | C116: DA+0 | D116: 18.34 | F116: 46157 | H116: Body u/p | I116: Vijay Bhagat-2 | J116: 20
A117: =A116+1 -> 111 | B117: AP90 | C117: DD+0 | F117: 46158 | H117: Middle Section | I117: Saritha Devi | J117: 24
A118: =A117+1 -> 112 | B118: 152/3 | C118: DA+0 | F118: 46158 | H118: Completed | I118: Jwala Singh | J118: 25
A119: =A118+1 -> 113 | B119: 153/2 | C119: DA+3 | F119: 46161 | H119: Material Shifting | I119: Jwala Singh | J119: 25

Sheet Vertical Chart -JS Line Punjab
A1: KEC INTERNATIONAL LIMITED
A2: 400 kV Samba- Jalandhar D/C Line(Quad) - Wind Zone - 5-Punjab Portion
A3: Vertical Chart
J4: Complete | L4: =COUNTIF($L$8:$L$488,"Clear") -> 207 | M4: =COUNTIF($M$8:$M$488,"C") -> 193 | N4: =COUNTIF($N$8:$N$488,"C") -> 166 | O4: =COUNTIF($O$8:$O$594,"C") -> 110 | P4: =COUNTIF($P$8:$P$417,"C") -> 0
J5: WIP | M5: =COUNTIF($M$8:$M$488,"WIP") -> 14 | N5: =COUNTIF($N$8:$N$417,"WIP") -> 0 | O5: =COUNTIF($O$8:$O$553,"WIP") -> 3 | P5: =COUNTIF($P$8:$P$417,"WIP") -> 0
A6: S.No | B6: Tower | C6: TOT | D6: Angle of Deviation | E6: Raised Chimney | I6: FDN Classification | J6: Span Length (Mtr) | K6: Section Length (m) | L6: ROW | M6: Foundation | N6: Earthing | O6: Tower Erection | P6: Tack Welding | Q6: Stringing | R6: Remarks
E7: LEG A | F7: LEG B | G7: LEG C | H7: LEG D
A8: 1 | B8: AP53 | C8: DC+0 | D8: 29°2'38"RT | K8: 0
J9: 416.658
A10: =A8+1 -> 2 | B10: AP54 | C10: DC+6 | D10: 15°23'08"RT | K10: =J9 -> 416.658
J11: 389.277
A12: =A10+1 -> 3 | B12: AP55 | C12: DD+3 | D12: 38°18'51"RT | I12: PS | K12: =J11 -> 389.277 | L12: Clear | M12: WIP
J13: 384.151
A14: =A12+1 -> 4 | B14: 55/1 | C14: DA+6 | I14: PS (SD) | K14: =J13 -> 384.151 | L14: Clear | M14: C | N14: C
J15: 409.3
A16: =A14+1 -> 5 | B16: AP56 | C16: DC+3 | D16: 25°53'58"RT | I16: PS (SD) | K16: =J15 -> 409.3 | L16: Clear | M16: C
J17: 409.72
A18: =A16+1 -> 6 | B18: 56/1 | C18: DA+6 | K18: =J17 -> 409.72
J19: 406.732
A20: =A18+1 -> 7 | B20: 56/2 | C20: DA+3 | I20: FS(PD) | K20: =J19 -> 406.732 | L20: Clear | M20: C
J21: 404.913
A22: =A20+1 -> 8 | B22: 56/3 | C22: DA+6 | I22: PS (SD) | K22: =J21 -> 404.913 | L22: Clear | M22: C | N22: C
J23: 285.563
A24: =A22+1 -> 9 | B24: 56/4 | C24: DA+6 | I24: PS (SD) | K24: =J23 -> 285.563 | L24: Clear | M24: C
J25: 399.174
A26: =A24+1 -> 10 | B26: AP57 | C26: DD+3 | D26: 39°39'47"LT | I26: PS(SD) | K26: =J25 -> 399.174 | L26: Clear | M26: C
J27: 343.784
A28: =A26+1 -> 11 | B28: 57/1 | C28: DA+0 | I28: PS(SD) | K28: =J27 -> 343.784 | L28: Clear | M28: C
J29: 313.063
A30: =A28+1 -> 12 | B30: 57/2 | C30: DA+0 | I30: PS(SD) | L30: Clear | M30: C
J31: 325.525
A32: =A30+1 -> 13 | B32: AP58 | C32: DC+0 | D32: 24°19'0"RT
J33: 406.443
A34: =A32+1 -> 14 | B34: AP59 | C34: DD+6 | D34: 47°09'41"LT | I34: PS(SD) | L34: Clear | M34: C
J35: 423.081
A36: =A34+1 -> 15 | B36: 59/1 | C36: DA+3 | I36: FS(PD) | K36: =J29+J31+J33+J35 -> 1468.112 | L36: Clear | M36: WIP
J37: 364.958
A38: =A36+1 -> 16 | B38: AP60 | C38: DB+6 | D38: 8°29'30"LT | I38: PS(SD) | K38: =J37 -> 364.958 | L38: Clear | M38: C
J39: 380.949
A40: =A38+1 -> 17 | B40: 60/1 | C40: DA+0 | I40: PS(SD) | K40: =J39 -> 380.949 | L40: Clear | M40: WIP
J41: 376.626
A42: =A40+1 -> 18 | B42: AP61 | C42: DC+0 | D42: 21°54'40"RT | I42: PS(SD) | L42: Clear | M42: C | N42: C
J43: 299.077
A44: =A42+1 -> 19 | B44: 61/1 | C44: DA+0 | I44: PS(SD) | L44: Clear | M44: C | N44: C
J45: 264.842
A46: =A44+1 -> 20 | B46: AP62 | C46: DB+0 | D46: 4°52'18"RT | K46: =J41+J43+J45 -> 940.545
J47: 364.064
A48: =A46+1 -> 21 | B48: 62/1 | C48: DA+0 | I48: PS(SD) | L48: Clear | M48: C
J49: 319.184
A50: =A48+1 -> 22 | B50: 62/2 | C50: DA+0 | I50: PS(SD) | L50: Clear | M50: C | N50: C
J51: 397.985
A52: =A50+1 -> 23 | B52: AP63 | C52: DB+9 | D52: 12°25'23"LT | I52: PS(SD) | K52: =J47+J49+J51 -> 1081.233 | L52: Clear | M52: C | N52: C
J53: 450.859
A54: =A52+1 -> 24 | B54: AP64 | C54: DC+9 | D54: 17°10'17"RT | I54: PS(SD) | L54: Clear | M54: C | N54: C
J55: 326.477
A56: =A54+1 -> 25 | B56: 64/1 | C56: DA+0 | I56: PS(SD) | L56: Clear | M56: C | N56: C
J57: 276.363
A58: =A56+1 -> 26 | B58: AP65 | C58: DB+0 | D58: 12°37'37"RT | K58: =J55+J57 -> 602.84
J59: 307.216
A60: =A58+1 -> 27 | B60: 65/1 | C60: DA+0 | I60: PS(SD) | L60: Clear | M60: WIP
J61: 389.397
A62: =A60+1 -> 28 | B62: 65/2 | C62: DA+6 | I62: PS(SD) | L62: Clear | M62: C | N62: C
J63: 368.792
A64: =A62+1 -> 29 | B64: 65/3 | C64: DA+0 | K64: =J59+J61+J63 -> 1065.405
J65: 404.386
A66: =A64+1 -> 30 | B66: 65/4 | C66: DA+3 | I66: PS(SD) | L66: Clear | M66: C
J67: 378.135
A68: =A66+1 -> 31 | B68: 65/5 | C68: DA+3 | I68: PS(SD) | L68: Clear | M68: WIP
J69: 370.482
A70: =A68+1 -> 32 | B70: AP66 | C70: DC+0 | D70: 26°31'54"RT
J71: 199.386
A72: =A70+1 -> 33 | B72: AP67 | C72: DD+0 | D72: 42°51'4"LT | I72: PS (SD) | L72: Clear | M72: C | N72: C
J73: 294.009
A74: =A72+1 -> 34 | B74: 67/1 | C74: DA+0 | I74: PS (SD) | L74: Clear | M74: C | N74: C | O74: C
J75: 312.708
A76: =A74+1 -> 35 | B76: 67/2 | C76: DA+0 | I76: PS (SD) | K76: =J65+J67+J69+J71+J73+J75 -> 1959.106 | L76: Clear | M76: C | N76: C
J77: 321.893 | R77: 66 KV H Pole Gurdaspur To Gahlari T/L
A78: =A76+1 -> 36 | B78: 67/3 | C78: DA+0 | I78: PS (SD) | K78: =J77 -> 321.893 | L78: Clear | M78: C | N78: C | O78: C
J79: 382.475
A80: =A78+1 -> 37 | B80: AP68 | C80: DB+0 | D80: 12°54'1"LT | I80: PS (SD) | L80: Clear | M80: C | N80: C | O80: C
J81: 388.11
A82: =A80+1 -> 38 | B82: AP69 | C82: DB+0 | D82: 5°21'56"RT | I82: PS (SD) | L82: Clear | M82: C | N82: C | O82: C
J83: 382.675
A84: =A82+1 -> 39 | B84: 69/1 | C84: DA+0 | I84: FS | K84: =J79+J81+J83 -> 1153.26 | L84: Clear | M84: C | N84: C | O84: C
J85: 390.446
A86: =A84+1 -> 40 | B86: 69/2 | C86: DA+0 | I86: FS | K86: =J85 -> 390.446 | L86: Clear | M86: C | N86: C | O86: C
J87: 361.751
A88: =A86+1 -> 41 | B88: 69/3 | C88: DA+0 | I88: WET | L88: Clear | M88: C | N88: C | O88: C
J89: 396.035
A90: =A88+1 -> 42 | B90: AP70 | C90: DC+3 | D90: 28°33'28"RT | I90: PS (SD) | L90: Clear | M90: C | N90: C | O90: C
J91: 435.862
A92: =A90+1 -> 43 | B92: 70/1 | C92: DA+9 | I92: PS (SD) | K92: =J91 -> 435.862 | L92: Clear | M92: C | N92: C
J93: 333.945
A94: =A92+1 -> 44 | B94: 70/2 | C94: DA+0 | I94: PS (SD) | L94: Clear | M94: C | N94: C | O94: C
J95: 502.836
A96: =A94+1 -> 45 | B96: AP70/3 | C96: DD+18 | D96: 2°59'27"LT | E96: 1 | F96: 1 | G96: 1 | H96: 1 | I96: PS (SD) | L96: Clear | M96: C
J97: 326.311
A98: =A96+1 -> 46 | B98: AP71 | C98: DC+9 | D98: 17°25'49"LT | I98: PS (SD) | L98: Clear | M98: C | N98: C
J99: 415.29
A100: =A98+1 -> 47 | B100: 71/1 | C100: DA+3 | I100: PS (SD) | L100: Clear | M100: C
...

Sheet Foundation -JS Line- Punjab
A1: KEC International Ltd | O1: Date: | P1: ='TB-605'!E1 -> 46161
A2: 400 kV Samba- Jalandhar D/C Line(Quad) - Wind Zone - 5-Punjab Portion
A3: FOUNDATION
A5: S.No | B5: Loc No. | C5: Tower Type | D5: Classification | E5: Conc Volume | F5: Start Date | G5: Foundation | L5: Completion Date | M5: FDN Status | N5: Earthing | O5: Gang Name | P5: Gang Strength | Q5: Remark
G6: Excavation | H6: Stub Setting | I6: PCC | J6: Rebar Placing | K6: RCC
A7: 1 | B7: 90/1 | C7: DA+3 | D7: WET | E7: =31.932+4.177 -> 36.109 | F7: 45925 | G7: 46033 | H7: 46033 | I7: 46033 | J7: 46033 | K7: 46033 | L7: 46033 | M7: Completed | O7: Anchal Singh | P7: 25 | Q7: 3 pits casting completed on 24.10.25. After clearence of ROW on 09.01.26, Work resumed since 10.01.26 in the 4th pit and work completed on 11.01.26
A8: =A7+1 -> 2 | B8: 117/1 | C8: DA+0 | D8: WET | F8: 45943 | G8: 45948 | H8: 45948 | I8: 45949 | J8: 45949 | K8: 45950 | L8: 45950 | M8: Completed | O8: Sakrala Material | P8: 10
A9: =A8+1 -> 3 | B9: 92/3 | C9: DA+0 | D9: WET | F9: 45946 | G9: 45955 | H9: 45955 | I9: 45955 | J9: 45956 | K9: 45957 | L9: 45957 | M9: Completed | O9: MS Constructions | P9: 9
A10: =A9+1 -> 4 | B10: 92/2 | C10: DA+6 | D10: WET | F10: 45949 | G10: 45955 | H10: 45957 | I10: 45957 | J10: 45958 | K10: 45958 | L10: 45958 | M10: Completed | O10: MS Constructions | P10: 10
A11: =A10+1 -> 5 | B11: 71/3 | C11: DA+6 | D11: WET | F11: 45947 | G11: 45949 | H11: 45950 | I11: 45950 | J11: 45951 | K11: 45953 | L11: 45953 | M11: Completed | O11: Ramesh | P11: 12
A12: =A11+1 -> 6 | B12: 72/2 | C12: DA+6 | D12: WET | F12: 45953 | G12: 45954 | H12: 45955 | I12: 45955 | J12: 45956 | K12: 45958 | L12: 45958 | M12: Completed | O12: Ramesh | P12: 12
A13: =A12+1 -> 7 | B13: 117/3 | C13: DA+0 | D13: WET | F13: 45953 | G13: 45955 | H13: 45956 | I13: 45957 | J13: 45959 | K13: 45959 | L13: 45959 | M13: Completed | N13: 45965 | O13: Sakrala Material | P13: 10
A14: =A13+1 -> 8 | B14: 74/0 | C14: DB+0 | D14: WET | F14: 45955 | G14: 45957 | H14: 45961 | I14: 45961 | J14: 45962 | K14: 45967 | L14: 45967 | M14: Completed | N14: 45973 | O14: Ramesh | P14: 16
A15: =A14+1 -> 9 | B15: 72/0 | C15: DB+3 | D15: WET | F15: 45962 | G15: 45963 | H15: 45964 | I15: 45965 | J15: 45966 | K15: 45970 | L15: 45970 | M15: Completed | N15: 45973 | O15: Ramesh
A16: =A15+1 -> 10 | B16: 89/1 | C16: DA+3 | D16: WET | F16: 45956 | G16: 45960 | H16: 45961 | I16: 45961 | J16: 45961 | K16: 45961 | L16: 45961 | M16: Completed | N16: 45968 | O16: Anchal Singh | P16: =8+15 -> 23
A17: =A16+1 -> 11 | B17: 93/1 | C17: DA+0 | D17: WET | F17: 45957 | G17: 45958 | H17: 45960 | I17: 45960 | J17: 45960 | K17: 45961 | L17: 45961 | M17: Completed | N17: 45970 | O17: MS Constructions | P17: 19
A18: =A17+1 -> 12 | B18: 117/2 | C18: DA+3 | D18: WET | F18: 45956 | G18: 45958 | H18: 45962 | I18: 45962 | J18: 45963 | K18: 45965 | L18: 45965 | M18: Completed | N18: 45967 | O18: Sakrala Material | P18: 20
A19: =A18+1 -> 13 | B19: 118/1 | C19: DA+0 | D19: WET | F19: 45963 | G19: 45964 | H19: 45965 | I19: 45965 | J19: 45965 | K19: 45967 | L19: 45967 | M19: Completed | N19: 45969 | O19: Sakrala Material
A20: =A19+1 -> 14 | B20: 95/2 | C20: DA+0 | D20: WET | F20: 45959 | G20: 45965 | H20: 45966 | I20: 45967 | J20: 45967 | K20: 45969 | L20: 45969 | M20: Completed | N20: 45970 | O20: Ikrar/MS Hussain | P20: 13
A21: =A20+1 -> 15 | B21: 95/3 | C21: DA+0 | D21: WET | F21: 45961 | G21: 45969 | H21: 45970 | I21: 45970 | J21: 45970 | K21: 45971 | L21: 45971 | M21: Completed | N21: 45972 | O21: Ikrar/MS Hussain
A22: =A21+1 -> 16 | B22: 93/2 | C22: DA+0 | D22: WET | F22: 45959 | G22: 45960 | H22: 45963 | I22: 45963 | J22: 45963 | K22: 45965 | L22: 45965 | M22: Completed | O22: MS Constructions | P22: 19
A23: =A22+1 -> 17 | B23: 92/1 | C23: DA+3 | D23: WET | F23: 45964 | G23: 45968 | H23: 45970 | I23: 45970 | J23: 45971 | K23: 45971 | L23: 45971 | M23: Completed | N23: 45975 | O23: MS Constructions
A24: =A23+1 -> 18 | B24: 97/2 | C24: DA+0 | D24: WET | F24: 45960 | G24: 45963 | H24: 45969 | I24: 45970 | J24: 45971 | K24: 45973 | L24: 45973 | M24: Completed | N24: 45977 | O24: Md. Latif | P24: 25
A25: =A24+1 -> 19 | B25: 97/1 | C25: DA+0 | D25: WET | F25: 45963 | G25: 45967 | H25: 45971 | I25: 45972 | J25: 45972 | K25: 45974 | L25: 45974 | M25: Completed | N25: 45977 | O25: Md. Latif
A26: =A25+1 -> 20 | B26: AP90 | C26: DD+0 | D26: WET | F26: 45962 | G26: 45978 | H26: 45979 | I26: 45979 | J26: 45981 | K26: 45983 | L26: 45983 | M26: Completed | N26: 45980 | O26: Anchal Singh | P26: 25
A27: =A26+1 -> 21 | B27: AP118 | C27: DC+0 | D27: WET | F27: 45968 | G27: 45973 | H27: 45974 | I27: 45974 | J27: 45974 | K27: 45977 | L27: 45977 | M27: Completed | N27: 45980 | O27: Sakrala Material | P27: 20
A28: =A27+1 -> 22 | B28: 131/1 | C28: DA+3 | D28: WET | F28: 45967 | G28: 46003 | H28: 46003 | I28: 45975 | J28: 45975 | K28: 45976 | L28: 45976 | M28: Completed | N28: 45982 | O28: TCC Construction | P28: 16
A29: =A28+1 -> 23 | B29: 95/1 | C29: DA+0 | D29: WET | F29: 45970 | G29: 45974 | H29: 45975 | I29: 45975 | J29: 45975 | K29: 45976 | L29: 45976 | M29: Completed | N29: 45977 | O29: Ikrar/MS Hussain | P29: 20
A30: =A29+1 -> 24 | B30: AP93 | C30: DC+0 | D30: WET | F30: 45971 | G30: 45978 | H30: 45979 | I30: 45979 | J30: 45979 | K30: 45980 | L30: 45980 | M30: Completed | N30: 45992 | O30: MS Constructions | P30: 19
A31: =A30+1 -> 25 | B31: 76/2 | C31: DA+3 | D31: WET | F31: 45972 | G31: 45973 | H31: 45974 | I31: 45974 | J31: 45974 | K31: 45975 | L31: 45975 | M31: Completed | N31: 45976 | O31: Ramesh | P31: 16
A32: =A31+1 -> 26 | B32: 97/3 | C32: DA+3 | D32: WET | F32: 45972 | G32: 45973 | H32: 45976 | I32: 45979 | J32: 45979 | K32: 45981 | L32: 45981 | M32: Completed | N32: 45982 | O32: Md. Latif | P32: 25
A33: =A32+1 -> 27 | B33: AP98 | C33: DB+3 | D33: WET | F33: 45973 | G33: 45980 | H33: 45982 | I33: 45982 | J33: 45984 | K33: 45985 | L33: 45985 | M33: Completed | N33: 45992 | O33: Md. Latif
A34: =A33+1 -> 28 | B34: 95/4 | C34: DA+0 | D34: WET | F34: 45974 | G34: 45979 | H34: 45980 | I34: 45980 | J34: 45981 | K34: 45981 | L34: 45981 | M34: Completed | N34: 45982 | O34: Ikrar | P34: 11
A35: =A34+1 -> 29 | B35: 76/1 | C35: DA+0 | D35: WET | F35: 45975 | G35: 45976 | H35: 45976 | I35: 45977 | J35: 45977 | K35: 45979 | L35: 45979 | M35: Completed | N35: 45980 | O35: Ramesh | P35: 16
A36: =A35+1 -> 30 | B36: 131/3 | C36: DA+3 | D36: WET | F36: 45976 | G36: 45977 | H36: 45979 | I36: 45979 | J36: 45980 | K36: 45980 | L36: 45980 | M36: Completed | N36: 45982 | O36: TCC Construction | P36: 16
A37: =A36+1 -> 31 | B37: AP116 | C37: DCT+0 | D37: FS | F37: 45977 | G37: 45988 | H37: 45989 | I37: 45989 | J37: 45989 | K37: 45991 | L37: 45991 | M37: Completed | N37: 45992 | O37: Sakrala Material | P37: 20
A38: =A37+1 -> 32 | B38: AP96 | C38: DC+0 | D38: WET | F38: 45978 | G38: 45988 | H38: 45988 | I38: 45988 | J38: 45989 | K38: 45990 | L38: 45990 | M38: Completed | N38: 45992 | O38: MS Hussain | P38: 12
A39: =A38+1 -> 33 | B39: AP77 | C39: DB+3 | D39: WET | F39: 45979 | G39: 46001 | H39: 46002 | I39: 46002 | J39: 46002 | K39: 46004 | L39: 46004 | M39: Completed | N39: 46005 | O39: Ramesh | P39: 16 | Q39: 2 pits casting completed on 22.11.2025 Balance 2 pits under ROW till 08.12.2025 Work resumed from 09.12.2025 & Completed on 13.12.25
A40: =A39+1 -> 34 | B40: 131/2 | C40: DA+3 | D40: WET | F40: 45980 | G40: 45982 | H40: 45983 | I40: 45984 | J40: 45984 | K40: 45985 | L40: 45985 | M40: Completed | N40: 45987 | O40: TCC Construction | P40: 16
A41: =A40+1 -> 35 | B41: AP94 | C41: DB+0 | D41: WET | F41: 45981 | G41: 45985 | H41: 45986 | I41: 45986 | J41: 45987 | K41: 45988 | L41: 45988 | M41: Completed | N41: 45996 | O41: MS Constructions | P41: 19
A42: =A41+1 -> 36 | B42: 98/1 | C42: DA+3 | D42: WET | F42: 45981 | G42: 45984 | H42: 45986 | I42: 45986 | J42: 45987 | K42: 45987 | L42: 45987 | M42: Completed | N42: 45987 | O42: Md. Latif | P42: 12
A43: =A42+1 -> 37 | B43: 103/1 | C43: DA+0 | D43: WET | F43: 45983 | G43: 45987 | H43: 45988 | I43: 45988 | J43: 45989 | K43: 45989 | L43: 45989 | M43: Completed | N43: 45989 | O43: Ikrar | P43: 11
A44: =A43+1 -> 38 | B44: 131/4 | C44: DA+0 | D44: WET | F44: 45983 | G44: 45988 | H44: 45989 | I44: 45989 | J44: 45990 | K44: 45991 | L44: 45991 | M44: Completed | N44: 45992 | O44: TCC Construction | P44: 16
A45: =A44+1 -> 39 | B45: AP87 | C45: DB+9 | D45: PS | F45: 45982 | G45: 45988 | H45: 45990 | I45: 45990 | J45: 45990 | K45: 45991 | L45: 45991 | M45: Completed | N45: 45994 | O45: Anchal Singh | P45: 25
A46: =A45+1 -> 40 | B46: AP99 | C46: DB+0 | D46: WET | F46: 45984 | G46: 45987 | H46: 45988 | I46: 45989 | J46: 45989 | K46: 45991 | L46: 45991 | M46: Completed | N46: 46001 | O46: Md. Latif | P46: 15
A47: =A46+1 -> 41 | B47: AP75 | C47: DB+9 | D47: FS | F47: 45986 | G47: 45989 | H47: 45990 | I47: 45990 | J47: 45990 | K47: 45992 | L47: 45992 | M47: Completed | N47: 45992 | O47: Ramesh | P47: 16
A48: =A47+1 -> 42 | B48: 82/2 | C48: DA+3 | D48: WET | F48: 45987 | G48: 45993 | H48: 45994 | I48: 45994 | J48: 45995 | K48: 45996 | L48: 45996 | M48: Completed | N48: 45999 | O48: Anchal Singh | P48: 25
A49: =A48+1 -> 43 | B49: AP100 | C49: DC+3 | D49: WET | F49: 45987 | G49: 45994 | H49: 45996 | I49: 45996 | J49: 45997 | K49: 45998 | L49: 45998 | M49: Completed | N49: 46001 | O49: Md. Latif | P49: 13
A50: =A49+1 -> 44 | B50: AP117 | C50: DB+0 | D50: WET | F50: 45990 | G50: 45995 | H50: 45996 | I50: 45997 | J50: 45997 | K50: 111743 | L50: 46000 | M50: Completed | N50: 46000 | O50: Sakrala Material | P50: 20
A51: =A50+1 -> 45 | B51: AP95 | C51: DC+3 | D51: WET | F51: 45990 | G51: 45996 | H51: 45996 | I51: 45997 | J51: 45997 | K51: 45998 | L51: 45998 | M51: Completed | N51: 45998 | O51: MS Constructions | P51: 19
... A53: =A52+1 -> 47 | B53: AP103 | C53: DD+0 | D53: WET | F53: 45993 | G53: 46006 | H53: 46007 | I53: 46007 | J53: 46008 | K53: 46009 | L53: 46009 | M53: Completed | N53: 46003 | O53: Ikrar | P53: 11
A54: =A53+1 -> 48 | B54: 99/1 | C54: DA+9 | D54: WET | F54: 45992 | G54: 45994 | H54: 45996 | I54: 05-12-205 | J54: 45996 | K54: 45997 | L54: 45997 | M54: Completed | N54: 46002 | O54: Md. Latif | P54: 12
A55: =A54+1 -> 49 | B55: 82/1 | C55: DA+0 | D55: WET | F55: 45994 | G55: 45996 | H55: 45999 | I55: 46000 | J55: 46000 | K55: 46001 | L55: 46001 | M55: Completed | N55: 46002 | O55: Anchal Singh | P55: 25
A56: =A55+1 -> 50 | B56: 76/3 | C56: DA+3 | D56: WET | F56: 45994 | G56: 45994 | H56: 45994 | I56: 45994 | J56: 45995 | K56: 45997 | L56: 45997 | M56: Completed | N56: 45998 | O56: Ramesh | P56: 16
A57: =A56+1 -> 51 | B57: 77/2 | C57: DB+0 | D57: WET | F57: 45996 | G57: 45996 | H57: 45996 | I57: 45997 | J57: 45998 | K57: 46001 | L57: 46001 | M57: Completed | N57: 46003 | O57: Ramesh | P57: 16
A58: =A57+1 -> 52 | B58: AP106 | C58: DD+6 | D58: WET | F58: 45996 | G58: 46002 | H58: 46003 | I58: 46003 | J58: 46004 | K58: 46006 | L58: 46006 | M58: Completed | N58: 46008 | O58: Md. Latif | P58: 25
A59: =A58+1 -> 53 | B59: AP104 | C59: DB+0 | D59: WET | F59: 45996 | G59: 46002 | H59: 46002 | I59: 46003 | J59: 46003 | K59: 46004 | L59: 46004 | M59: Completed | N59: 46006 | O59: MS Hussain | P59: 12
A60: =A59+1 -> 54 | B60: AP135 | C60: DB+3 | D60: WET | F60: 45996 | G60: 45998 | H60: 46000 | I60: 46000 | J60: 46003 | K60: 46007 | L60: 46007 | M60: Completed | N60: 46011 | O60: Ram Sadotra | P60: 40
A61: =A60+1 -> 55 | B61: 135/1 | C61: DA+6 | D61: WET | F61: 45998 | G61: 46000 | H61: 46002 | I61: 46003 | J61: 46005 | K61: 46020 | L61: 46020 | M61: Completed | N61: 46025 | O61: Ram Sadotra | P61: 40 | Q61: Since farmers left water in the field work hampered since 14.12.25. Work restarted from 28.12.25 and completed on 29.12.25
A62: =A61+1 -> 56 | B62: 85/1 | C62: DA+9 | D62: WET | F62: 45997 | G62: 46003 | H62: 46005 | I62: 46005 | J62: 46006 | K62: 46007 | L62: 46007 | M62: Completed | N62: 46012 | O62: Anchal Singh | P62: 25
A63: =A62+1 -> 57 | B63: 106/1 | C63: DA+0 | D63: WET | F63: 46001 | G63: 46005 | H63: 46007 | I63: 46007 | J63: 46007 | K63: 46008 | L63: 46008 | M63: Completed | N63: 46013 | O63: Md. Latif | P63: 25
A64: =A63+1 -> 58 | B64: 136/1 | C64: DA+3 | D64: WET | F64: 46002 | G64: 46003 | H64: 46006 | I64: 46006 | J64: 46008 | K64: 46010 | L64: 46010 | M64: Completed | N64: 46015 | O64: Ram Sadotra | P64: 40
A65: =A64+1 -> 59 | B65: 130/2 | C65: DA+0 | D65: WET | F65: 46003 | G65: 46006 | H65: 46006 | I65: 46006 | J65: 46006 | K65: 46008 | L65: 46008 | M65: Completed | N65: 46011 | O65: MS Constructions | P65: 20
A66: =A65+1 -> 60 | B66: AP85 | C66: DB+0 | D66: WET | F66: 46003 | G66: 46009 | H66: 46011 | I66: 46011 | J66: 46014 | K66: 46015 | L66: 46015 | M66: Completed | N66: 46017 | O66: Anchal Singh | P66: 25
A67: =A66+1 -> 61 | B67: 135/2 | C67: DA+3 | D67: WET | F67: 46004 | G67: 46005 | H67: 46007 | I67: 46008 | J67: 46009 | K67: 46012 | L67: 46012 | M67: Completed | N67: 46016 | O67: Ram Sadotra | P67: 40
A68: =A67+1 -> 62 | B68: 77/1 | C68: DA+3 | D68: WET | F68: 46004 | G68: 46005 | H68: 46005 | I68: 46005 | J68: 46006 | K68: 46007 | L68: 46007 | M68: Completed | N68: 46009 | O68: Ramesh | P68: 16
A69: =A68+1 -> 63 | B69: 102/1 | C69: DA+6 | D69: WET | F69: 46005 | G69: 46008 | H69: 46008 | I69: 46008 | J69: 46008 | K69: 46009 | L69: 46009 | M69: Completed | N69: 46009 | O69: MS Hussain | P69: 12
A70: =A69+1 -> 64 | B70: 130/1 | C70: DA+0 | D70: WET | F70: 46007 | G70: 46008 | H70: 46009 | I70: 46010 | J70: 46010 | K70: 46011 | L70: 46011 | M70: Completed | N70: 46011 | O70: MS Constructions | P70: 20
A71: =A70+1 -> 65 | B71: AP80 | C71: DD+0 | D71: PS | F71: 46007 | G71: 46012 | H71: 46013 | I71: 46013 | J71: 46014 | K71: 46016 | L71: 46016 | M71: Completed | N71: 46017 | O71: Ramesh | P71: 16
A72: =A71+1 -> 66 | B72: 116/1 | C72: DA+0 | D72: WET | F72: 46008 | G72: 46009 | H72: 46010 | I72: 46010 | J72: 46010 | K72: 46011 | L72: 46011 | M72: Completed | N72: 46012 | O72: Md. Latif | P72: 25
A73: =A72+1 -> 67 | B73: 156/4 | C73: DA+0 | D73: WET | F73: 46009 | G73: 46012 | H73: 46012 | I73: 46016 | J73: 46016 | K73: 46017 | L73: 46017 | M73: Completed | N73: 46025 | O73: Md. Latif | P73: 25
... A108: =A107+1 -> 102 | B108: AP92 | C108: DD+25 | D108: PS | F108: 46043 | G108: 46061 | H108: 46062 | I108: 46062 | J108: 46063 | K108: 46066 | L108: 46066 | M108: Completed | N108: 46070 | O108: Anchal Singh | P108: 20
A109: =A108+1 -> 103 | B109: 71/2 | C109: DA+6 DA+9 | D109: WET | F109: 46040 | G109: 46042 | H109: 46042 | I109: 46042 | J109: 46042 | K109: 46043 | L109: 46043 | M109: Completed | N109: 46044 | O109: Ramesh | P109: 16 | Q109: Loc: 71/2 -recasted with DA+9 Started : 11-2-26 & Completed : 12-2-26
A110: =A109+1 -> 104 | B110: 151/1 | C110: DA+0 | D110: WET | F110: 46040 | G110: 46044 | H110: 46052 | I110: 46052 | J110: 46053 | K110: 46053 | L110: 46053 | M110: Completed | N110: 46054 | O110: Ms. Hussain | P110: 13
A111: =A110+1 -> 105 | B111: 69/1 | C111: DA+0 | D111: FS | F111: 46040 | G111: 46044 | H111: 46044 | I111: 46044 | J111: 46044 | K111: 46049 | L111: 46049 | M111: Completed | N111: 46072 | O111: Sufiyan Ali | P111: 25
A112: =A111+1 -> 106 | B112: AP139 | C112: DB+0 | D112: WET | F112: 46042 | G112: 46057 | H112: 46058 | I112: 46058 | J112: 46058 | K112: 46059 | L112: 46059 | M112: Completed | O112: Ram Sadotra | P112: 40
A113: =A112+1 -> 107 | B113: 155/2 | C113: DA+0 | D113: WET | F113: 46042 | G113: 46051 | H113: 46051 | I113: 46051 | J113: 46052 | K113: 46052 | L113: 46052 | M113: Completed | N113: 46052 | O113: Md. Latif | P113: 25
A114: =A113+1 -> 108 | B114: 115/1 | C114: DA+6 | D114: WET | F114: 46043 | G114: 46052 | H114: 46052 | I114: 46052 | J114: 46053 | K114: 46053 | L114: 46053 | M114: Completed | N114: 46055 | O114: Sakrala Material | P114: 20
A115: =A114+1 -> 109 | B115: 136/2 | C115: DA+3 | D115: WET | F115: 46044 | G115: 46059 | H115: 46060 | I115: 46060 | J115: 46063 | K115: 46064 | L115: 46064 | M115: Completed | N115: 46068 | O115: Ram Sadotra | P115: 40
A116: =A115+1 -> 110 | B116: 155/3 | C116: DA+0 | D116: WET | F116: 46045 | G116: 46052 | H116: 46053 | I116: 46053 | J116: 46053 | K116: 46053 | L116: 46053 | M116: Completed | N116: 46058 | O116: Md. Latif | P116: 25
A117: =A116+1 -> 111 | B117: AP97 | C117: DD+3 | D117: WET | F117: 46051 | G117: 46059 | H117: 46059 | I117: 46059 | J117: 46060 | K117: 46061 | L117: 46061 | M117: Completed | N117: 46060 | O117: Sufiyan Ali | P117: 20
A118: =A117+1 -> 112 | B118: AP155 | C118: DD+0 | D118: WET | F118: 46053 | G118: 46059 | H118: 46060 | I118: 46060 | J118: 46062 | K118: 46062 | L118: 46062 | M118: Completed | N118: 46063 | O118: Md. Latif | P118: 25
A119: =A118+1 -> 113 | B119: 151/2 | C119: DA+3 | D119: WET | F119: 46056 | G119: 46059 | H119: 46059 | I119: 46059 | J119: 46059 | K119: 46060 | L119: 46060 | M119: Completed | N119: 46060 | O119: Ms. Hussain | P119: 13
A120: =A119+1 -> 114 | B120: 152/4 | C120: DA+0 | D120: WET | F120: 46057 | G120: 45327 | H120: 46063 | I120: 46063 | J120: 46064 | K120: 46065 | L120: 46065 | M120: Completed | N120: 46067 | O120: Ram Sadotra | P120: 40
A121: =A120+1 -> 115 | B121: AP156 | C121: DC+0 | D121: WET | F121: 46058 | G121: 46066 | H121: 46066 | I121: 46066 | J121: 46067 | K121: 46067 | L121: 46067 | M121: Completed | N121: 46068 | O121: Md. Latif | P121: 25
A122: =A121+1 -> 116 | B122: 70/2 | C122: DA+0 | D122: PS(SD) | F122: 46058 | G122: 46073 | H122: 46073 | I122: 46073 | J122: 46073 | K122: 46074 | L122: 46074 | M122: Completed | N122: 46073 | O122: Ramesh | P122: 16
A123: =A122+1 -> 117 | B123: 153/1 | C123: DA+0 | D123: WET | F123: 46059 | G123: 46063 | H123: 46064 | I123: 46064 | J123: 46066 | K123: 46066 | L123: 46066 | M123: Completed | N123: 46067 | O123: Ram Sadotra | P123: 40
A124: =A123+1 -> 118 | B124: AP111 | C124: DC+0 | D124: WET | F124: 46059 | G124: 46067 | H124: 46067 | I124: 46067 | J124: 46068 | K124: 46072 | L124: 46072 | M124: Completed | N124: 46072 | O124: Sakrala Material | P124: 20
... A156: =A155+1 -> 150 | B156: AP125 | C156: DD+18 | D156: PS | F156: 46105 | G156: 46115 | H156: 46116 | I156: 46116 | J156: 46116 | K156: 46118 | L156: 46118 | M156: Completed | N156: 46115 | O156: MS Constructions | P156: 16
A157: =A156+1 -> 151 | B157: AP124 | C157: DB+9 | D157: PS | F157: 46104 | G157: 46110 | H157: 46111 | I157: 46111 | J157: 46111 | K157: 46111 | L157: 46111 | M157: Completed | O157: Ram Sadotra | P157: 16
A158: =A157+1 -> 152 | B158: AP70/3 | C158: DD+18 1MRC | D158: PS(SD) | F158: 46143 | G158: 46155 | H158: 46157 | I158: 46157 | J158: 46157 | K158: 46161 | L158: 46161 | M158: Completed | O158: Ramesh | P158: 16
A159: =A158+1 -> 153 | B159: AP109 | C159: DD+30 | D159: PS | F159: 46106 | G159: 46119 | H159: 46119 | I159: 46122 | J159: 46122 | K159: 46124 | L159: 46124 | M159: Completed | N159: 46125 | O159: Anchal Singh | P159: 15
A160: =A159+1 -> 154 | B160: 144/4 | C160: DA+0 | D160: PS(SD) | F160: 46106 | G160: 46116 | H160: 46116 | I160: 46116 | J160: 46116 | K160: 46117 | L160: 46117 | M160: Completed | N160: 46150 | O160: Ikrar | P160: 12
A161: =A160+1 -> 155 | B161: 144/3 | C161: DA+6 | D161: PS(SD) | F161: 46110 | G161: 46116 | H161: 46117 | I161: 46117 | J161: 46118 | K161: 46119 | L161: 46119 | M161: Completed | N161: 46119 | O161: MS Hussain | P161: 11
A162: =A161+1 -> 156 | B162: 65/2 | C162: DA+6 | D162: PS(SD) | F162: 46111 | G162: 46116 | H162: 46118 | I162: 46118 | J162: 46118 | K162: 46119 | L162: 46119 | M162: Completed | N162: 46122 | O162: Sufiyan Ai | P162: 10
A163: =A162+1 -> 157 | B163: AP59 | C163: DD+6 | D163: PS(SD) | F163: 46123 | G163: 46133 | H163: 46133 | I163: 46137 | J163: 46137 | K163: 46139 | L163: 46139 | M163: Completed | O163: Sufiyan Ai | P163: 13
A164: =A163+1 -> 158 | B164: AP165 | C164: DB+6 1MRC | D164: FS | F164: 46116 | G164: 46129 | H164: 46130 | I164: 46130 | J164: 46131 | K164: 46134 | L164: 46134 | M164: Completed | N164: 46146 | O164: Ram Sadotra | P164: 15
A165: =A164+1 -> 159 | B165: 55/1 | C165: DA+6 | D165: PS(SD) | F165: 46123 | G165: 46138 | H165: 46138 | I165: 46138 | J165: 46138 | K165: 46140 | L165: 46140 | M165: Completed | N165: 46143 | O165: Wani Const | P165: 8
A166: =A165+1 -> 160 | B166: AP61 | C166: DC+0 | D166: PS(SD) | F166: 46120 | G166: 46127 | H166: 46130 | I166: 46130 | J166: 46130 | K166: 46133 | L166: 46133 | M166: Completed | N166: 46149 | O166: Sufiyan Ali | P166: 12
A167: =A166+1 -> 161 | B167: AP126 | C167: DB+0 | D167: WET | F167: 46118 | G167: 46124 | H167: 46125 | I167: 46125 | J167: 46126 | K167: 46127 | L167: 46127 | M167: Completed | N167: 46127 | O167: MS Constructions | P167: 16
...

Sheet Sheet9
D2: S.No | E2: Loc | F2: TOT | G2: Classification | H2: Start Date | I2: End Darte | J2: JMC
D3: 1 | E3: 153/0 | F3: DC+0 | G3: WET | H3: 46039 | I3: 46058 | J3: 105 | K3: OK
D4: =D3+1 -> 2 | E4: AP139 | F4: DB+0 | G4: WET | H4: 46042 | I4: 46059 | J4: =J3+1 -> 106 | K4: OK
D5: =D4+1 -> 3 | E5: 151/2 | F5: DA+3 | G5: WET | H5: 46056 | I5: 46060 | J5: =J4+1 -> 107 | K5: OK
D6: =D5+1 -> 4 | E6: AP97 | F6: DD+3 | G6: WET | H6: 46051 | I6: 46061 | J6: =J5+1 -> 108 | K6: OK
D7: =D6+1 -> 5 | E7: AP155 | F7: DD+0 | G7: WET | H7: 46053 | I7: 46062 | J7: =J6+1 -> 109 | K7: OK
D8: =D7+1 -> 6 | E8: 136/2 | F8: DA+3 | G8: WET | H8: 46044 | I8: 46064 | J8: =J7+1 -> 110 | K8: OK
D9: =D8+1 -> 7 | E9: AP130 | F9: DD+18 | G9: PS | H9: 46040 | I9: 46065 | J9: =J8+1 -> 111 | K9: OK
D10: =D9+1 -> 8 | E10: 152/4 | F10: DA+0 | G10: WET | H10: 46057 | I10: 46065 | J10: =J9+1 -> 112 | K10: OK
D11: =D10+1 -> 9 | E11: AP92 | F11: DD+25 | G11: PS | H11: 46043 | I11: 46066 | J11: =J10+1 -> 113 | K11: OK | P11: =8+30+40+26 -> 104
D12: =D11+1 -> 10 | E12: 153/1 | F12: DA+0 | G12: WET | H12: 46059 | I12: 46066 | J12: =J11+1 -> 114 | K12: OK
D13: =D12+1 -> 11 | E13: AP156 | F13: DC+0 | G13: WET | H13: 46058 | I13: 46067 | J13: =J12+1 -> 115 | K13: OK
D14: =D13+1 -> 12 | E14: 136/3 | F14: DA+0 | G14: WET | H14: 46062 | I14: 46068 | J14: =J13+1 -> 116 | K14: OK
D15: =D14+1 -> 13 | E15: 157/1 | F15: DA+0 | G15: WET | H15: 46062 | I15: 46068 | J15: =J14+1 -> 117 | K15: OK
D16: =D15+1 -> 14 | E16: 72/1 | F16: DA+3 | G16: WET | H16: 46067 | I16: 46070 | J16: =J15+1 -> 118 | K16: OK
D17: =D16+1 -> 15 | E17: AP150 | F17: DC+0 | G17: WET | H17: 46062 | I17: 46071 | J17: =J16+1 -> 119 | K17: OK
D18: =D17+1 -> 16 | E18: AP70 | F18: DC+3 | G18: PS(SD) | H18: 46063 | I18: 46071 | J18: =J17+1 -> 120 | K18: OK
D19: =D18+1 -> 17 | E19: 153/2 | F19: DA+3 | G19: WET | H19: 46066 | I19: 46071 | J19: =J18+1 -> 121 | K19: OK
D20: =D19+1 -> 18 | E20: AP111 | F20: DC+0 | G20: WET | H20: 46059 | I20: 46072 | J20: =J19+1 -> 122 | K20: OK
D21: =D20+1 -> 19 | E21: 136/4 | F21: DA+3 | G21: WET | H21: 46065 | I21: 46073 | J21: =J20+1 -> 123 | K21: OK
D22: =D21+1 -> 20 | E22: 70/2 | F22: DA+0 | G22: PS(SD) | H22: 46058 | I22: 46074 | J22: =J21+1 -> 124 | K22: OK
D23: =D22+1 -> 21 | E23: AP68 | F23: DB+0 | G23: PS(SD) | H23: 46063 | I23: 46074 | J23: =J22+1 -> 125 | K23: OK
... D32: =D31+1 -> 30 | E32: AP114 | F32: DB+0 | G32: WET | H32: 46074 | I32: 46081 | J32: =J31+1 -> 134 | K32: OK
D33: =D32+1 -> 31 | E33: 71/2 | F33: DA+9 | G33: WET | J33: 135 | K33: OK
D34: =D33+1 -> 32 | E34: 69/0 | H34: 46077 | I34: 46082 | J34: 136 | K34: OK
D37: S.No | E37: Loc | F37: TOT | G37: Classification | H37: Start Date | I37: End Darte | J37: JMC
D38: 1 | E38: AP148 | F38: DD+25 2MRC | G38: PS | H38: 46072 | I38: 46097 | J38: 140
D39: =D38+1 -> 2 | E39: AP149 | F39: DD+25 | G39: PS | H39: 46074 | I39: 46091 | J39: 137
D40: =D39+1 -> 3 | E40: 67/2 | F40: DA+0 | G40: PS (SD) | H40: 46085 | I40: 46094 | J40: 138 | K40: OK
D41: =D40+1 -> 4 | E41: AP71 | F41: DC+9 | G41: PS (SD) | H41: 46084 | I41: 46104 | J41: 143 | K41: OK
D42: =D41+1 -> 5 | E42: AP152 | F42: DD+0 | G42: WET | H42: 46081 | I42: 46107 | J42: 145
D43: =D42+1 -> 6 | E43: AP127 | F43: DD+30 2MRC | G43: PS | H43: 46082 | I43: 46096 | J43: 139
D44: =D43+1 -> 7 | E44: AP145 | F44: DB+0 | G44: PS (SD) | H44: 46082 | I44: 46106 | J44: 144
D45: =D44+1 -> 8 | E45: AP136 | F45: DC+3 | G45: WET | H45: 46083 | I45: 46099 | J45: 141
D46: =D45+1 -> 9 | E46: 67/1 | F46: DA+0 | G46: PS(SD) | H46: 46094 | I46: 46100 | J46: 142 | K46: OK
D47: =D46+1 -> 10 | E47: AP108 | F47: DD+25 | G47: PS | H47: 46082 | I47: 46109 | J47: 146 | K47: OK

Sheet ROW Front vs Progress
B2: S.No | C2: Line | D2: ROW Clearence Work Front | E2: Completed | F2: WIP | G2: Balance
B3: 1 | C3: Samba-Jalandhar (Jammu Portion) | D3: 95 | E3: 84 | F3: 7 | G3: =D3-E3-F3 -> 4
B4: =B3+1 -> 2 | C4: Samba-Jalandhar (Punjab Portion) | D4: 181 | E4: 158 | F4: 10 | G4: =D4-E4-F4 -> 13
B5: =B4+1 -> 3 | C5: Samba-Kishenpur | D5: 56 | E5: 46 | F5: 7 | G5: =D5-E5-F5 -> 3
B6: =B5+1 -> 4 | C6: LILO-Kishtwar | D6: 4 | F6: 3 | G6: =D6-E6-F6 -> 1
B7: Total | D7: =SUM(D3:D6) -> 336 | E7: =SUM(E3:E6) -> 288 | F7: =SUM(F3:F6) -> 27 | G7: =SUM(G3:G6) -> 21
D38: 46098 | E38: 3

Sheet Hindrance
A1: Hindrance Details.
A2: S.No | B2: Line | C2: From | D2: To | E2: Days | F2: Status | G2: Impact Location / Work | H2: Hindrance Details | I2: Remarks
A3: 1 | B3: 400 kV D/C Samba-Jalandhar | C3: 45867 | D3: 45868 | E3: 2 | F3: Closed | G3: Loc: 29/5 (Foundation) | H3: Due to heavy rains at site excavated Pits (B,C,D) collapsed and site works are hampered
A4: =A3+1 -> 2 | B4: 400 kV D/C Samba-Jalandhar | C4: 45870 | D4: 45870 | E4: 1 | F4: Closed | G4: Loc: 29/5 (Foundation) | H4: Due to heavy rains PCC, Steel Binding, RCC work in Pit B
A5: =A4+1 -> 3 | B5: 400 kV D/C Kishenpur-Samba | C5: 45875 | D5: 45875 | E5: 1 | F5: Closed | G5: Check Survey Work | H5: Due to landslides, road blocked and at site unable to carry out the survey work
A6: =A5+1 -> 4 | B6: 400 kV D/C Samba-Jalandhar | C6: 45876 | D6: 45876 | E6: 1 | F6: Closed | G6: Loc: 29/5 (Foundation) | H6: Due to heavy rains at site , RCC work hampered in Pit A
A7: =A6+1 -> 5 | B7: 400 kV D/C Samba-Jalandhar | C7: 45878 | D7: 45878 | E7: 1 | F7: Closed | G7: Loc: 29/5 (Foundation) | H7: Due to heavy rains at site , RCC work hampered in Pit C
A8: =A7+1 -> 6 | B8: 400 kV D/C Samba-Jalandhar | C8: 45881 | D8: 45883 | E8: 3 | F8: Closed | G8: Loc: 29/4 (Foundation) | H8: Due to heavy rains for continous 3 days site excavation work hampered
A9: =A8+1 -> 7 | B9: 400 kV D/C Kishenpur-Samba | C9: 45881 | D9: 45881 | E9: 1 | F9: Closed | G9: Check Survey Work | H9: Due to rains /landslides, at site unable to carry out the survey work
A10: =A9+1 -> 8 | B10: 400 kV D/C Kishenpur-Samba | C10: 45885 | D10: 45887 | E10: 3 | F10: Closed | G10: Check Survey Work | H10: Due to rains/ landslides , at site unable to carry out the survey work
A11: =A10+1 -> 9 | B11: 400 kV D/C Samba-Jalandhar | C11: 45886 | D11: 45887 | E11: 2 | F11: Closed | G11: Loc: 29/4 (Foundation) | H11: Due to heavy rains for continous 2 days site Stub Setting , PCC , Steel Binding work hampered
A12: =A11+1 -> 10 | B12: 400 kV D/C Samba-Jalandhar | C12: 45889 | D12: 8,9&10 | E12: 0.5 | F12: Closed | G12: 38 | H12: Due to heavy rains Pit B - Stub Setting, PCC, Pit C - RCC work and also unable to carry out survey work in the line
A13: =A12+1 -> 11 | B13: 400 kV D/C Samba-Jalandhar | C13: 45892 | D13: 11 | E13: 6 | F13: Closed | G13: Loc: 29/4 (Foundation) & Check Survey Work | H13: Due to heavy rains Pit B - Stub Setting, PCC, Pit C - RCC work and also unable to carry out survey work in the line | J13: 1
A14: =A13+1 -> 12 | B14: 400 kV D/C Kishenpur-Samba | C14: 45892 | D14: 45897 | E14: 6 | F14: Closed | H14: Due to continous heavy rains / floods for 6 days all site related works are hampered
A15: =A14+1 -> 13 | B15: 400 kV D/C Samba-Jalandhar | C15: 45899 | D15: 45903 | E15: 5 | F15: Closed | G15: Loc: 29/4 & Loc: 29/3 (Foundation) & Check Survey Work | H15: Due to heavy rains / floods landslides occurred and there is no approach for carrying out site activities and all roads are blocked by local gov. authority
A16: =A15+1 -> 14 | B16: 400 kV D/C Kishenpur-Samba | C16: 45898 | D16: 45911 | E16: 14 | F16: Closed | G16: Check Survey Work
A17: =A16+1 -> 15 | B17: LILO-Kishtwar | C17: 45897 | D17: 45917 | E17: =D17-C17 -> 20 | F17: Closed | G17: All site works | H17: Due to heavy rains/floods NH closed & also due to local political issues administration issued section 144 , 163
A18: =A17+1 -> 16 | B18: 400 kV D/C Samba-Jalandhar | C18: 45928 | D18: 45929 | E18: 2 | F18: Closed | G18: Loc: 90/1 -Foundation Works | H18: Due to farmers issues work on hold
A19: =A18+1 -> 17 | B19: 400 kV D/C Samba-Jalandhar | C19: 45935 | D19: 45937 | E19: 3 | F19: Closed | G19: All site works | H19: Due to heavy rains work hampered | J19: =J13+1 -> 2
A20: =A19+1 -> 18 | B20: 400 kV D/C Kishenpur-Samba | C20: 45935 | D20: 45939 | E20: =D20-C20 -> 4 | F20: Closed | G20: All site works | H20: Due to heavy rains work hampered Roads closed by local administration due to landslides
A21: =A20+1 -> 19 | B21: LILO-Kishtwar | C21: 45935 | D21: 19&20 | E21: 3 | F21: Closed | G21: All site works | H21: Due to heavy rains work hampered
A22: =A21+1 -> 20 | B22: 400 kV D/C Samba-Jalandhar | C22: 45943 | D22: 21 | E22: 3 | F22: Closed | G22: Loc: 90/1 -Foundation Works | H22: Due to farmers issues work on hold for 3 days
A23: =A22+1 -> 21 | B23: 400 kV D/C Samba-Jalandhar | C23: 45948 | D23: 22 | E23: 1 | F23: Closed | G23: Loc: 90/1 -Foundation Works | H23: Due to farmers issues work on hold
A24: =A23+1 -> 22 | B24: 400 kV D/C Samba-Jalandhar | C24: 45954 | D24: 45981 | E24: =D24-C24 -> 27 | F24: Closed | G24: Loc: 90/1 - 4th pit works | H24: Due to farmers issues work on hold
A25: =A24+1 -> 23 | B25: 400 kV D/C Samba-Jalandhar | C25: 45995 | D25: 45997 | E25: 3 | F25: Closed | G25: Foundation works at loc: 23/4 | H25: Due to ROW - foundation work hampered
A26: =A25+1 -> 24 | B26: 400 kV D/C Samba-Jalandhar | C26: 46002 | D26: 46005 | E26: =D26-C26 -> 3 | F26: Closed | G26: Foundation works at loc: 115/0 | H26: Due to ROW - foundation work hampered
A27: =A26+1 -> 25 | B27: 400 kV D/C Samba-Jalandhar | C27: 46005 | D27: 46007 | E27: =D27-C27 -> 2 | F27: Closed | G27: Contractor pawan kumar sharma , required further work front , the team is idle since 14-12-2025 after completion of loc: 39/2 on 13.12.25 | H27: Due to ROW - foundation work hampered
A28: =A27+1 -> 26 | B28: 400 kV D/C Kishenpur-Samba | C28: 46003 | D28: 46005 | E28: 2 | F28: Closed | G28: Foundation Works at AP32 , due to ROW issues | H28: Due to ROW - foundation work hampered
A29: =A28+1 -> 27 | B29: 400 kV D/C Samba-Jalandhar | C29: 46010 | D29: 46011 | E29: 2 | F29: Closed | G29: Contractor Ikrar , required further work front , the team is idle since 19-12-2025 after completion of loc: 103/0 on 18.12.25 | H29: Due to ROW - foundation work hampered
A30: =A29+1 -> 28 | B30: 400 kV D/C Kishenpur-Samba | C30: 46013 | D30: 46014 | E30: 2 | F30: Closed | G30: Contractor -Naresh idle for work front since 22-12-2025 at Loc: 52/0 | H30: Due to ROW - foundation work hampered
A31: =A30+1 -> 29 | B31: LILO-Kishtwar | C31: 46021 | D31: 46038 | E31: =D31-C31 -> 17 | F31: Closed | G31: Due to approach issue / ROW clearence required for loc: AP5 Foundation work hampered. Work on hold in LILO Line as advised by RKPTL | H31: Due to ROW/ Route diversion
A32: =A31+1 -> 30 | B32: 400 kV D/C Samba-Jalandhar | C32: 46024 | D32: 46026 | E32: =D32-C32 -> 2 | F32: Closed | G32: Work front required for vendor Ram Sadotra after completion of Loc: 138/2 . 2 teams engaged by Ram Sadotra - 1 team being mobilized at 152 section from 05-01-2026 & 2nd team required work front | H32: Due to ROW
A33: =A32+1 -> 31 | B33: 400 kV D/C Samba-Jalandhar | C33: 46045 | D33: 46054 | E33: =D33-C33 -> 9 | F33: Closed | G33: All site works | H33: Due to heavy rains
A34: =A33+1 -> 32 | B34: 400 kV D/C Samba-Jalandhar Kishenpur Samba Jammu Portion | C34: 46054 | D34: 46057 | E34: =D34-C34 -> 3 | F34: Closed | G34: All Foundation Works | H34: Due to non availabilty of cement
A35: =A34+1 -> 33 | B35: 400 kV D/C Samba-Jalandhar Jammu Portion | C35: 46060 | D35: 46061 | E35: 2 | F35: Closed | G35: 23/1- Tower Erection Works | H35: Due to ROW
A36: =A35+1 -> 34 | B36: 400kV D/C Samba Kishenpur | C36: 46087 | D36: 46088 | E36: 2 | F36: Closed | G36: AP10 - Foundation Work ROW Work Hampered , local villagers not allowing to do work | H36: Due to ROW
A37: =A36+1 -> 35 | B37: 400 kV D/C Samba-Jalandhar Punjab Portion | C37: 46090 | D37: =C37 -> 46090 | E37: 1 | F37: Closed | G37: 130/2- Due to ROW , Tower Erection Work Hampered | H37: Due to ROW
A38: =A37+1 -> 36 | B38: 400 kV D/C Samba-Jalandhar 400 kV D/C Samba-Kishenpur LILO | C38: 46096 | D38: 46103 | E38: 8 | F38: Closed | G38: Due to heavy rains all site works hampered | H38: Due to Rains
A39: =A38+1 -> 37 | B39: LILO -Kisthwar | C39: 46103 | D39: 46121 | E39: =D39-C39 -> 18 | F39: Closed | G39: Due to ROW work hampered at Loc: AP7 | H39: ROW
A40: =A39+1 -> 38 | B40: 400 kV D/C Samba-Jalandhar TL | C40: 46116 | D40: 46119 | E40: 3 | F40: Closed | G40: Due to ROW at Loc: 40/3 - Work not yet started Since ROW not cleared as on 7-4-2026 . Loc AP1 allocated to the vendor as replacement | H40: ROW
A41: =A40+1 -> 39 | B41: 400 kV D/C Samba-Jalandhar 400 kV D/C Samba-Kishenpur LILO | C41: 46119 | D41: 46121 | E41: 3 | F41: Closed | G41: Due to heavy rains all site works hampered | H41: Due to Rains
A42: =A41+1 -> 40 | B42: LILO -Kisthwar | C42: 46118 | D42: 46121 | E42: 4 | F42: Closed | G42: Due to ROW work hampered at Loc: AP9 | H42: ROW
A43: =A42+1 -> 41 | B43: 400kV D/C Samba-Jalandhar | C43: 46120 | D43: 46122 | E43: 3 | F43: Closed | G43: Due to ROW/ Crop Harvesting - Saritha Devi Erection Gang Idle since 08-04-2026 after completion of loc: AP70 | H43: ROW
A44: =A43+1 -> 42 | B44: 400kV D/C Samba-Jalandhar | C44: 46114 | D44: 46122 | E44: =D44-C44 -> 8 | F44: Closed | G44: Erection Material Shifting Completed at Loc: 114/0 , but due to ROW erection work not started. ROW resolved on 10-4-2026 . After completion of Loc AP85 gang will be engaged at loc | H44: ROW
A45: =A44+1 -> 43 | B45: LILO-Kisthwar | C45: 46141 | D45: 46143 | E45: 3 | F45: Closed | G45: Due to heavy rains all site works hampered | H45: Due to Rains
A46: =A45+1 -> 44 | B46: LILO-Kisthwar | C46: 46150 | D46: 46151 | E46: 2 | F46: Closed | G46: Due to ROW work hampered | H46: ROW

Sheet Foundation -KS Line
A1: KEC INTERNATIONAL LIMITED | N1: Date: | O1: ='TB-605'!E1 -> 46161
A2: 400 kV Kishenpur -Samba T/L
A3: FOUNDATION
A5: S.No | B5: Loc No. | C5: Tower Type | D5: Classification | E5: Start Date | F5: Foundation | K5: Completion Date | L5: Status | M5: Earthing | N5: Gang Name | O5: Gang Strength | P5: Remark
F6: Excavation | G6: Stub Setting | H6: PCC | I6: Rebar Placing | J6: RCC
A7: 1 | B7: 85/0 | C7: DC+0 | D7: DFR | E7: 45931 | F7: 45945 | G7: 45953 | H7: 45953 | I7: 45954 | J7: 45956 | K7: 45956 | L7: Completed | M7: 45970 | N7: Ankush Sharma | O7: 8
A8: 2 | B8: 86/0 | C8: DD+0 | D8: DFR | E8: 45954 | F8: 45967 | G8: 45968 | H8: 45970 | I8: 45970 | J8: 45971 | K8: 45971 | L8: Completed | M8: 45972 | N8: Ankush Sharma | O8: 13
A9: 3 | B9: 106/0 | C9: DB+0 | D9: DFR | E9: 45944 | F9: 45953 | G9: 45960 | H9: 45960 | I9: 45961 | J9: 45961 | K9: 45961 | L9: Completed | M9: 45981 | N9: Naresh | O9: 8
A10: 4 | B10: 28/0 | C10: DC+3 | D10: DFR | E10: 45954 | F10: 45960 | G10: 45967 | H10: 45967 | I10: 45968 | J10: 45969 | K10: 45969 | L10: Completed | M10: 45975 | N10: Asish Gupta | O10: 9
A11: 5 | B11: 27/0 | C11: DB+3 | D11: DFR | E11: 45968 | F11: 45990 | G11: 45991 | H11: 45991 | I11: 45991 | J11: 45991 | K11: 45991 | L11: Completed | M11: 45995 | N11: Asish Gupta | O11: 10
A12: 6 | B12: 25/0 | C12: DB+0 | D12: DFR | E12: 45975 | F12: 45979 | G12: 45981 | H12: 45982 | I12: 22-11-205 | J12: 45983 | K12: 45983 | L12: Completed | M12: 45995
A13: 7 | B13: 97/0 | C13: DC-3 | D13: DFR | E13: 45958 | F13: 45965 | G13: 45988 | H13: 45989 | I13: 45990 | J13: 45990 | K13: 45990 | L13: Completed | M13: 45995 | N13: BS Const | O13: 10
A14: 8 | B14: AP107 | C14: DC+0 | D14: DFR | E14: 45963 | F14: 45979 | G14: 45981 | H14: 45982 | I14: 22-11-205 | J14: 45983 | K14: 45983 | L14: Completed | M14: 45994 | N14: Naresh | O14: 12
A15: 9 | B15: AP79 | C15: DD+9 | D15: DFR | E15: 45971 | F15: 45988 | G15: 45988 | H15: 45988 | I15: 45988 | J15: 45988 | K15: 45988 | L15: Completed | M15: 45999 | N15: Ankush Sharma | O15: 13
A16: 10 | B16: AP33 | C16: DB+6 | D16: DFR | E16: 45975 | F16: 45979 | G16: 45989 | H16: 45989 | I16: 45990 | J16: 45990 | K16: 45990 | L16: Completed | M16: 45994 | N16: Akthar | O16: 10
A17: =A16+1 -> 11 | B17: AP29 | C17: DD-3 | D17: WET | E17: 45984 | F17: 45997 | G17: 45997 | H17: 45997 | I17: 45998 | J17: 45999 | K17: 45999 | L17: Completed | M17: 46024 | N17: Asish Gupta | O17: 10
A18: =A17+1 -> 12 | B18: AP32 | C18: DC-3 | D18: WET | E18: 45987 | F18: 46008 | G18: 46009 | H18: 46009 | I18: 46009 | J18: 46010 | K18: 46010 | L18: Completed | M18: 46012 | N18: Akthar | O18: 10
A19: =A18+1 -> 13 | B19: AP80 | C19: DD+3 | D19: DFR | E19: 45989 | F19: 46009 | G19: 46010 | H19: 46011 | I19: 46012 | J19: 46012 | K19: 46012 | L19: Completed | M19: 46014 | N19: Ankush Sharma | O19: 13
A20: =A19+1 -> 14 | B20: AP105 | C20: DD+0 | D20: DFR | E20: 45993 | F20: 46000 | G20: 46006 | H20: 46006 | I20: 46007 | J20: 46008 | K20: 46008 | L20: Completed | M20: 46009 | N20: Naresh | O20: 12
A21: =A20+1 -> 15 | B21: AP96 | C21: DC-3 | D21: DFR | E21: 45994 | F21: 46009 | G21: 46009 | H21: 46009 | I21: 46012 | J21: 46012 | K21: 46012 | L21: Completed | M21: 46017 | N21: BS Const | O21: 10
A22: =A21+1 -> 16 | B22: 30/1 | C22: DA+0 | D22: WET | E22: 45999 | F22: 46007 | G22: 46007 | H22: 46007 | I22: 46007 | J22: 46008 | K22: 46008 | L22: Completed | M22: 46025 | N22: Asish Gupta | O22: 10
A23: =A22+1 -> 17 | B23: AP43 | C23: DC-3 | D23: DFR | E23: 46012 | F23: 46019 | G23: 46021 | H23: 46022 | I23: 46022 | J23: 46022 | K23: 46022 | L23: Completed | M23: 46024 | N23: Akthar | O23: 10
A24: =A23+1 -> 18 | B24: AP31 | C24: DB+9 | D24: WET | E24: 46012 | F24: 46016 | G24: 46017 | H24: 46017 | I24: 46018 | J24: 46019 | K24: 46019 | L24: Completed | M24: 46032 | N24: Asish Gupta | O24: 10
A25: =A24+1 -> 19 | B25: AP51 | C25: DB+0 | D25: DFR | E25: 46016 | F25: 46019 | G25: 46025 | H25: 46026 | I25: 46026 | J25: 46027 | K25: 46027 | L25: Completed | M25: 46030 | N25: BS Const | O25: 10
A26: =A25+1 -> 20 | B26: AP52 | C26: DC-3 | D26: DFR | E26: 46016 | F26: 46019 | G26: 46021 | H26: 46021 | I26: 46021 | J26: 46025 | K26: 46025 | L26: Completed | M26: 46026 | N26: Naresh | O26: 12
A27: =A26+1 -> 21 | B27: AP54 | C27: DD+9 | D27: DFR | E27: 46016 | F27: 46022 | G27: 46025 | H27: 46026 | I27: 46027 | J27: 46029 | K27: 46029 | L27: Completed | M27: 46034 | N27: Ankush Sharma | O27: 13
A28: =A27+1 -> 22 | B28: AP30 | C28: DD+0 | D28: WET | E28: 46019 | F28: 46031 | G28: 46033 | H28: 46033 | I28: 46033 | J28: 46034 | K28: 46034 | L28: Completed | M28: Completed | N28: Asish Gupta | O28: 10
A29: =A28+1 -> 23 | B29: AP44 | C29: DD-3 | D29: DFR | E29: 46020 | F29: 46034 | G29: 46038 | H29: 46039 | I29: 46039 | J29: 46041 | K29: 46041 | L29: Completed | M29: 46043 | N29: Akthar | O29: 10
A30: =A29+1 -> 24 | B30: AP26 | C30: DB-3 | D30: DFR | E30: 46033 | F30: 46041 | G30: 46041 | H30: 46042 | I30: 46042 | J30: 46043 | K30: 46043 | L30: Completed | M30: 46044 | N30: Asish Gupta | O30: 10
A31: =A30+1 -> 25 | B31: AP81 | C31: DD+18 | D31: WET | E31: 46034 | F31: 46076 | G31: 46078 | H31: 46079 | I31: 46079 | J31: 46079 | K31: 46079 | L31: Completed | N31: Ankush Sharma | O31: 13
A32: =A31+1 -> 26 | B32: AP8 | C32: DD+0 | D32: DRY | E32: 46037 | F32: 46056 | G32: 46060 | H32: 46060 | I32: 46060 | J32: 46063 | K32: 46063 | L32: Completed | M32: 46064 | N32: Kulbhushan | O32: 6
A33: =A32+1 -> 27 | B33: AP108 | C33: DC+0 | D33: DFR | E33: 46039 | F33: 46053 | G33: 46053 | H33: 46053 | I33: 46053 | J33: 46053 | K33: 46053 | L33: Completed | M33: Completed | N33: Naresh | O33: 12
A34: =A33+1 -> 28 | B34: AP27A | C34: DB+6 | D34: FS | E34: 46040 | F34: 46053 | G34: 46053 | H34: 46053 | I34: 46053 | J34: 46053 | K34: 46053 | L34: Completed | M34: Completed | N34: Asish Gupta | O34: 10
A35: =A34+1 -> 29 | B35: AP39 | C35: DB+0 | D35: DFR | E35: 46041 | N35: Akthar | O35: 10 | P35: Prop Setting/PCC Work on hold due to forest area
A36: =A35+1 -> 30 | B36: 8/2 | C36: DB+3 | D36: DFR | E36: 46044 | F36: 46053 | G36: 46053 | H36: 46053 | I36: 46053 | J36: 46053 | K36: 46053 | L36: Completed | M36: Completed | N36: Md. Farooq | O36: 6
A37: =A36+1 -> 31 | B37: AP9 | C37: DB+9 | D37: DFR | E37: 46056 | F37: 46079 | G37: 46080 | H37: 46080 | I37: 46080 | J37: 46080 | K37: 46080 | L37: Completed | N37: Asish Gupta | O37: 10
A38: =A37+1 -> 32 | B38: AP11 | C38: DD+18 | D38: DFR | E38: 46056 | F38: 46076 | G38: 46077 | H38: 46077 | I38: 46077 | J38: 46077 | K38: 46077 | L38: Completed | N38: Akthar | O38: 10
A39: =A38+1 -> 33 | B39: 8/1 | C39: DB+3 | D39: DFR | E39: 46058 | F39: 46071 | G39: 46071 | H39: 46071 | I39: 46071 | J39: 46071 | K39: 46071 | L39: Completed | M39: Completed | N39: Kulbhushan | O39: 6
A40: =A39+1 -> 34 | B40: 26/1 | C40: DB | D40: DFR | E40: 46060 | F40: 46077 | G40: 46080 | H40: 46080 | I40: 46080 | J40: 46080 | K40: 46080 | L40: Completed | M40: Completed | N40: Asish Gupta | O40: 10
A41: =A40+1 -> 35 | B41: 9/1 | C41: DD+18 | D41: DFR | E41: 46063 | F41: 46079 | G41: 46081 | H41: 46081 | I41: 46081 | J41: 46081 | K41: 46081 | L41: Completed | N41: Asish Gupta | O41: 10
A42: =A41+1 -> 36 | B42: AP53 | C42: DC+3 | D42: DFR | E42: 11-02-025 | F42: 46072 | G42: 46077 | H42: 46077 | I42: 46079 | J42: 46079 | K42: 46079 | L42: Completed | N42: BS Const | O42: 10
A43: =A42+1 -> 37 | B43: AP84 | C43: DC+9 | D43: DFR | E43: 46071 | F43: 46076 | G43: 46077 | H43: 46080 | I43: 46080 | J43: 46081 | K43: 46081 | L43: Completed | N43: Naresh | O43: 10
A44: =A43+1 -> 38 | B44: AP83 | C44: DD+25 | D44: DFR | E44: 46071 | F44: 46105 | G44: 46106 | H44: 46107 | I44: 46107 | J44: 46107 | K44: 46107 | L44: Completed | N44: Ankush Sharma | O44: 10
A45: =A44+1 -> 39 | B45: AP7 | C45: DC+9 | D45: DFR | E45: 46073 | F45: 46079 | G45: 46080 | H45: 46080 | I45: 46080 | J45: 46080 | K45: 46080 | L45: Completed | M45: Completed | N45: Kulbhushan | O45: 12
A46: =A45+1 -> 40 | B46: AP10 | C46: DB+9 | D46: DFR | E46: 46081 | F46: 46088 | G46: 46089 | H46: 46089 | I46: 46089 | J46: 46089 | K46: 46089 | L46: Completed | M46: Completed | N46: Akthar | O46: 10
A47: =A46+1 -> 41 | B47: AP24 | C47: DC+0 | D47: DFR | E47: 46089 | F47: 46106 | G47: 46108 | H47: 46108 | I47: 46110 | J47: 46111 | K47: 46111 | L47: Completed | N47: Ganesh | O47: 10
A48: =A47+1 -> 42 | B48: AP6 | C48: DC+9 | D48: DFR | E48: 46089 | F48: 46106 | G48: 46107 | H48: 46107 | I48: 46108 | J48: 46109 | K48: 46109 | L48: Completed | N48: Kulbhushan | O48: 12
A49: =A48+1 -> 43 | B49: AP95 | C49: DD+0 | D49: DFR | E49: 46089 | F49: 46108 | G49: 46109 | H49: 46110 | I49: 46111 | J49: 46112 | K49: 46112 | L49: Completed | N49: BS Const | O49: 10
A50: =A49+1 -> 44 | B50: AP40 | C50: DB-3 | D50: DFR | E50: 46092 | F50: 46108 | G50: 46109 | H50: 46109 | I50: 46109 | J50: 46110 | K50: 46110 | L50: Completed | N50: Ganesh | O50: 10
A51: =A50+1 -> 45 | B51: AP82 | C51: DD+18 | D51: DFR | E51: 46093 | F51: 46106 | G51: 46107 | H51: 46107 | I51: 46107 | J51: 46108 | K51: 46108 | L51: Completed | N51: Naresh | O51: 13
A52: =A51+1 -> 46 | B52: AP87 | C52: DC+9 | D52: DFR | E52: 46103 | F52: 46123 | G52: 46123 | H52: 46125 | I52: 46125 | J52: 46127 | K52: 46127 | L52: Completed | N52: Ankush Sharma | O52: 10
A53: =A52+1 -> 47 | B53: AP5 | C53: DD+3 | D53: DFR | E53: 46111 | F53: 46134 | G53: 46136 | H53: 46136 | I53: 46138 | J53: 46139 | K53: 46139 | L53: Completed | N53: Kulbhushan | O53: 12
A54: =A53+1 -> 48 | B54: AP109 | C54: DD+0 | D54: DFR | E54: 46116 | F54: 46121 | G54: 46127 | H54: 46127 | I54: 46127 | J54: 46128 | K54: 46132 | L54: Completed | N54: Naresh | O54: 13
A55: =A54+1 -> 49 | B55: AP94 | C55: DC+0 | D55: DFR | E55: 46119 | F55: 46141 | G55: 46142 | H55: 46142 | I55: 46142 | J55: 46142 | K55: 46142 | L55: Completed | N55: BS Const | O55: 12
A56: =A55+1 -> 50 | B56: AP42 | C56: DB+3 | D56: DFR | E56: 46116 | F56: 46130 | G56: 46130 | H56: 46132 | I56: 46133 | J56: 46139 | K56: 46139 | L56: Completed | N56: Ganesh | O56: 10
A57: =A56+1 -> 51 | B57: AP88 | C57: DD+0 | D57: WET | E57: 46127 | F57: 46138 | G57: 46139 | H57: 46139 | I57: 46140 | J57: 46141 | K57: 46141 | L57: Completed | N57: Ankush Sharma | O57: 10
A58: =A57+1 -> 52 | B58: AP104 | C58: DD+9 | D58: DFR | E58: 46131 | F58: 46146 | G58: 46147 | H58: 46147 | I58: 46147 | J58: 46149 | K58: 46149 | L58: Completed | N58: Naresh | O58: 13
A59: =A58+1 -> 53 | B59: AP45 | C59: DD+9 | D59: DFR | E59: 46131 | F59: 46158 | G59: 46159 | L59: WIP | N59: Ganesh | O59: 10 | P59: Pit A,B,C - Casting Completed Pit D-Prop Setting
A60: =A59+1 -> 54 | B60: AP49 | C60: DC+9 | D60: DFR | E60: 46133 | F60: 46158 | G60: 46159 | L60: WIP | N60: Rumal Singh | O60: 7 | P60: Pit A,B,D - Casting Completed Pit C -Steel Binding
A61: =A60+1 -> 55 | B61: AP88A | C61: DD+0 | D61: WET | E61: 46142 | F61: 46159 | L61: WIP | N61: Ankush Sharma | O61: 10 | P61: Pit A,C,D - Casting upto frustrum
A62: =A61+1 -> 56 | B62: AP90 | C62: DD+0 | D62: WET | E62: 46147 | L62: WIP | N62: BS Const | O62: 10 | P62: Pit C,D- Steel Binding WIP
A63: =A62+1 -> 57 | B63: AP103 | C63: DD+6 | D63: WET | E63: 46147 | L63: WIP | N63: Naresh | O63: 13 | P63: Pit C - Casting Completed Pit A - Casting upto frustrum Pit B - Steel Binding
A64: =A63+1 -> 58 | B64: AP1 | C64: DD+0 | D64: DFR | E64: 46152 | L64: WIP | N64: Kulbhushan | O64: 10 | P64: Pit B-Casting upto frustrum
A65: =A64+1 -> 59 | B65: AP39 | C65: DB+0 | D65: DFR | E65: 46157 | L65: WIP | N65: Ganesh | O65: 10 | P65: Pit B,C,D - Casting Completd
A66: =A65+1 -> 60 | B66: AP35 | C66: DC+9 | D66: DFR | E66: 46158 | L66: WIP | N66: RK Singh | P66: Excavation

Sheet Manpower
M1: Date | N1: ='Foundation JS-Line -Jammu'!P1 -> 46161
B2: MAN POWER & MACHINERY RESOURCES
B3: Type of Staff | C3: M/s. KEC | D3: Manpower in Gangs | F3: Line | G3: Qty | H3: Manpower in Gangs | J3: Line | K3: Qty | L3: CIVIL Machinery & Plant | M3: Working | N3: Idle | O3: Total | P3: Adhshiv | Q3: Vishal | R3: Md S | S3: Bal | T3: Zaff | U3: KK | V3: Anchal | W3: Ramesh | X3: MS | Y3: Ikrar | Z3: Latif | AA3: Sakra
D4: Team | E4: Foundation | H4: Team | I4: Tower Erection | L4: JCB | M4: =4+10+1 -> 15 | O4: =M4+N4 -> 15 | Q4: 2 | S4: 2 | U4: 1 | V4: 1 | W4: 1 | X4: 1 | Y4: 1 | AA4: 1 | AB4: =SUM(P4:AA4) -> 10
B5: Project Manager | C5: 1 | D5: 1&2 | E5: Pawan Kumar Sharma | F5: J-S (Jammu) | G5: 22 | H5: 1 | I5: Kushboo Devi-1 | J5: J-S (Jammu) | K5: 20 | L5: Ajax Flori | M5: 18 | O5: =M5+N5 -> 18 | P5: 1 | S5: 1 | T5: 1 | W5: 1 | X5: 1 | AA5: 1 | AB5: =SUM(P5:AA5) -> 6
B6: ROW Lead | C6: 2 | D6: 3 | E6: Thakur Const | F6: J-S (Jammu) | G6: 11 | H6: =H5+1 -> 2 | I6: Saritha Devi | J6: J-S (Punjab) | K6: 24 | L6: Water Tanker | M6: 12 | O6: =M6+N6 -> 12 | P6: 1 | R6: 1 | T6: 1 | V6: 1 | X6: 1 | AB6: =SUM(P6:AA6) -> 5
B7: ROWOfficer /Patwari | C7: 5 | D7: 4 | E7: Anil Sharma | F7: J-S (Jammu) | G7: 12 | H7: =H6+1 -> 3 | I7: Jwala Singh | J7: J-S (Punjab) | K7: 25 | L7: Dewatering Pump | M7: 13 | O7: =M7+N7 -> 13 | AB7: =SUM(P7:AA7) -> 0
B8: Planning/Cons. Manager | C8: 3 | D8: 5,6,7,8,9&10 | E8: Sufiyan Ali | F8: J-S (Punjab) | G8: 69 | H8: =H7+1 -> 4 | I8: Vijay Kumar Bhagat-2 | J8: J-S (Punjab) | K8: 20 | L8: Tractor | M8: =4+7 -> 11 | O8: =M8+N8 -> 11 | P8: 1 | Q8: 2 | R8: 5 | S8: 2 | T8: 2 | U8: 1 | AB8: =SUM(P8:AA8) -> 13
B9: Commercial Incharge/ Officer | C9: 2 | D9: 11 | E9: MS Constructions | F9: J-S (Punjab) | G9: 16 | H9: =H8+1 -> 5 | I9: ASC Infra | J9: J-S (Jammu) | K9: 24 | L9: Mixer Machine | M9: 12 | O9: =M9+N9 -> 12 | P9: 1 | T9: 1 | U9: 1 | V9: 1 | X9: 1 | Y9: 1 | AA9: 1 | AB9: =SUM(P9:AA9) -> 7
B10: Quality Incharge/ Engineer | C10: 7 | D10: 12 | E10: Ankush Sharma | F10: K-S | G10: 13 | H10: =H9+1 -> 6 | I10: Kushboo Devi-2 | J10: J-S (Jammu) | K10: 22 | L10: Poclain | M10: =7+1+2+1 -> 11 | O10: =M10+N10 -> 11 | P10: 1 | Q10: 1 | R10: 1 | S10: 1 | T10: 1 | U10: 1 | V10: 2 | X10: 1 | Y10: 2 | Z10: 1 | AB10: =SUM(P10:AA10) -> 12
B11: EHS lead / Officer | C11: 9 | D11: 13 | E11: Naresh | F11: K-S | G11: 12 | H11: =H10+1 -> 7 | I11: Anvi Const | J11: K-S | K11: 18 | L11: Boring Motor | M11: 11 | O11: =M11+N11 -> 11 | P11: 1 | R11: 1 | S11: 1 | T11: 1 | W11: 1 | Z11: 1 | AA11: 1 | AB11: =SUM(P11:AA11) -> 7
B12: Sr. Surveyor | C12: 3 | D12: 14 | E12: Ashish Gupta | F12: K-S | G12: 12 | P12: 2 | Q12: 1 | R12: 4 | U12: 4 | AB12: =SUM(P12:AA12) -> 11
B13: Surveyor | C13: 1 | D13: 15 | E13: Balveer | F13: K-S | G13: 11
B14: Asst. Surveyor | C14: 5 | D14: 16&17 | E14: Ram Sadotra | F14: J-S (Punjab) | G14: 23
B15: Store Incharge/Asst | C15: 4 | D15: 18 | E15: Kulbhushan | F15: K-S | G15: 13
B16: Section Incharge/Engineer | C16: 5 | D16: 19 | E16: MS Hussain | F16: J-S (Punjab) | G16: 11
B17: Line Engineer/Supervisor | C17: 20 | D17: 20 | E17: Bitu Kumar | F17: LILO | G17: 13
D18: 21 | E18: Zaffar | F18: LILO | G18: 15
D19: 22 | E19: Bhat Const | F19: LILO | G19: 14
D20: 23 | E20: Ballwant Singh | F20: J-S (Jammu) | G20: 10
D21: 24 | E21: Tapseer | F21: J-S (Punjab) | G21: 10
D22: 25 | E22: Ikrar | F22: J-S (Punjab) | G22: 10
D23: 26 | E23: KDR Engg | F23: J-S (Punjab) | G23: 11
D24: 27 | E24: Ramesh | F24: J-S (Punjab) | G24: 12
D25: 28 | E25: Aman Enterprises | F25: J-S (Punjab) | G25: 10
D26: 29 | E26: Samsad | F26: J-S(Jammu) | G26: 15
D27: 30 | E27: Ramji Structure | F27: J-S (Punjab) | G27: 10
D28: 31 | E28: Adishiv | F28: J-S (Jammu) | G28: 5
D29: 32 | E29: V-Raj | F29: J-S (Jammu) | G29: 8
D30: 33 | E30: Md.Sharif | F30: J-S (Punjab) | G30: 10
B31: Total staff | C31: =SUM(C4:C20) -> 67 | E31: Total | G31: =SUM(G5:G30) -> 378 | I31: Total | K31: =SUM(K5:K22) -> 153 | L31: Total Machinery & Plant | M31: =SUM(M4:M20) -> 103 | O31: =SUM(O4:O20) -> 103
D42: 46101 | E42: 6

Sheet Sum
B2: Foundation
B3: S.No | C3: Line | D3: Gangs Available | E3: Additional Gangs | G3: Total Gangs
E4: Planned by 3rd May | F4: Planned by 10th May
B5: 1 | C5: Samba-Jalandhar | D5: 18 | E5: 1 | F5: 4 | G5: =SUM(D5:F5) -> 23
B6: =B5+1 -> 2 | C6: Samba-Kishenpur | D6: 6 | G6: =SUM(D6:F6) -> 6
B7: =B6+1 -> 3 | C7: LILO-Kisthwar | D7: 3 | G7: =SUM(D7:F7) -> 3
D8: =SUM(D5:D7) -> 27 | E8: =SUM(E5:E7) -> 1 | F8: =SUM(F5:F7) -> 4 | G8: =SUM(G5:G7) -> 32
B10: Tower Erection
B11: S.No | C11: Line | D11: Gangs Available | E11: Additional Gangs
E12: Planned by 3rd May | F12: Planned by 10th May | G12: Total Gangs
B13: 1 | C13: Samba-Jalandhar | D13: 9 | E13: 3 | F13: 4 | G13: =SUM(D13:F13) -> 16
B14: =B13+1 -> 2 | C14: Samba-Kishenpur | F14: 4 | G14: =SUM(D14:F14) -> 4
D15: =SUM(D13:D14) -> 9 | E15: =SUM(E13:E14) -> 3 | F15: =SUM(F13:F14) -> 8 | G15: =SUM(G13:G14) -> 20
B17: Stringing
B18: S.No | C18: Line | D18: Gangs Available | E18: Additional Gangs
E19: Planned by 3rd May | F19: Planned by 10th May | G19: Total Gangs
B20: 1 | C20: Samba-Jalandhar | F20: 1 | G20: =SUM(D20:F20) -> 1
F21: =SUM(F20:F20) -> 1 | G21: =SUM(G20:G20) -> 1

Sheet Sheet18
B1: Foundation | H1: Tower Erection | N1: Stringing
B2: Samba- Jalandhar TL-Jammu | H2: Samba- Jalandhar TL-Jammu | N2: Samba- Jalandhar TL
B3: S.No | C3: Sub Vendor | D3: Available | E3: Mobilization Planned | F3: Remarks | H3: S.No | I3: Sub Vendor | J3: Available | K3: Mobilization Planned | L3: Remarks | N3: S.No | O3: Sub Vendor | P3: Available | Q3: Mobilization Planned | R3: Remarks
B4: 1 | C4: Balwant Singh-1 | D4: 11 | H4: 1 | I4: Kushboo Devi-1 | J4: 20 | N4: 1 | O4: Jiyaul Hoque | Q4: 10 | R4: Mob Planned by 10th May
B5: =B4+1 -> 2 | C5: Balwant Singh-2 | D5: 10 | H5: =H4+1 -> 2 | I5: Kushboo Devi-2 | J5: 22 | N5: Total | Q5: =SUM(Q1:Q4) -> 10
B6: =B5+1 -> 3 | C6: Pawan Sharma-1 | D6: 12 | H6: =H5+1 -> 3 | I6: ASIC Infra | J6: 23
B7: =B6+1 -> 4 | C7: Pawan Sharma-2 | D7: 10 | H7: =H6+1 -> 4 | I7: Niva Sarkar Mandal | K7: 20 | L7: Mob Planned by 3rd May
B8: =B7+1 -> 5 | C8: Anil Sharma | D8: 10 | H8: Total | J8: =SUM(J4:J7) -> 65 | K8: =SUM(K4:K7) -> 20
B9: =B8+1 -> 6 | C9: TCC | D9: 10
B10: =B9+1 -> 7 | C10: Pawan Sharma-3 | E10: 12 | F10: Mob Planned by 10th May
B11: =B10+1 -> 8 | C11: Samsad | E11: 13 | F11: Mob Planned by 8th May
B12: =B11+1 -> 9 | C12: VR Construction | E12: 12 | F12: Mob Planned by 6th May
B13: Total | D13: =SUM(D4:D12) -> 63 | E13: =SUM(E4:E12) -> 37
B15: Samba- Jalandhar TL-Punjab | H15: Samba- Jalandhar TL- Punjab
B16: S.No | C16: Sub Vendor | D16: Available | E16: Mobilization Planned | F16: Remarks | H16: S.No | I16: Sub Vendor | J16: Available | K16: Mobilization Planned | L16: Remarks
B17: 1 | C17: Tapseer | D17: 11 | H17: 1 | I17: Saritha Devi | J17: 24
B18: =B17+1 -> 2 | C18: Sufiyan Ali-1 | D18: 11 | H18: =H17+1 -> 2 | I18: Jwala Singh | J18: 25
B19: =B18+1 -> 3 | C19: Sufiyan Ali-2 | D19: 10 | H19: =H18+1 -> 3 | I19: Vijay B-1 | J19: 20
B20: =B19+1 -> 4 | C20: Sufiyan Ali-3 | D20: 10 | H20: =H19+1 -> 4 | I20: ZR Construction-1 | J20: 21
B21: =B20+1 -> 5 | C21: KDR Engg | D21: 12 | H21: =H20+1 -> 5 | I21: Rakesh-1 | J21: 23
B22: =B21+1 -> 6 | C22: Aman Enterprises | D22: 10 | H22: =H21+1 -> 6 | I22: Vijay Kumar Bhagat | J22: 20
B23: =B22+1 -> 7 | C23: Ramesh | D23: 12 | H23: =H22+1 -> 7 | I23: ZR Construction-2 | K23: 20 | L23: Mob Planned by 8th May
B24: =B23+1 -> 8 | C24: MS Construction | D24: 16 | H24: =H23+1 -> 8 | I24: Rakesh -2 | K24: 24 | L24: Mob Planned by 10th May
B25: =B24+1 -> 9 | C25: MS Hussain | D25: 12 | H25: =H24+1 -> 9 | I25: Karni Const-1 | K25: 20 | L25: Mob Planned by 3rd May
B26: =B25+1 -> 10 | C26: Ikrar | D26: 13 | H26: =H25+1 -> 10 | I26: Karni Const-2 | K26: 20 | L26: Mob Planned by 3rd May
B27: =B26+1 -> 11 | C27: Ram Sadotra-1 | D27: 12 | H27: =H26+1 -> 11 | I27: Karni Const-3 | K27: 22 | L27: Mob Planned by 6th May
B28: =B27+1 -> 12 | C28: Ram Sadotra-2 | D28: 10 | H28: =H27+1 -> 12 | I28: Karni Const-4 | K28: 21 | L28: Mob Planned by 6th May
B29: =B28+1 -> 13 | C29: Ramji Structre-1 | E29: 12 | F29: Mob Planned by 3rd May | H29: Total | J29: =SUM(J17:J28) -> 133 | K29: =SUM(K17:K28) -> 127
B30: =B29+1 -> 14 | C30: Ramji Structre-2 | E30: 12 | F30: Mob Planned by 5th May
B31: Total | D31: =SUM(D17:D30) -> 139 | E31: =SUM(E17:E30) -> 24
H32: Samba-Kishenpur
B33: Samba-Kishenpur | H33: S.No | I33: Sub Vendor | J33: Available | K33: Mobilization Planned | L33: Remarks
B34: S.No | C34: Sub Vendor | D34: Available | E34: Remarks | H34: 1 | I34: Anvi Construction | K34: 20 | L34: Mob Planned by 5th May
B35: 1 | C35: Naresh | D35: 12 | H35: =H34+1 -> 2 | I35: Horil Mahato | K35: 22 | L35: Mob Planned by 7th May
B36: =B35+1 -> 2 | C36: Ankush Sharma | D36: 13 | H36: =H35+1 -> 3 | I36: Jaya Prakash Mahato | K36: 23 | L36: Mob Planned by 10th May
B37: =B36+1 -> 3 | C37: Ganesh | D37: 10 | H37: =H36+1 -> 4 | I37: Mohan Mahato | K37: 20 | L37: Mob Planned by 10th May
B38: =B37+1 -> 4 | C38: Rumal Singh | D38: 10 | H38: Total | K38: =SUM(K34:K37) -> 85
B39: =B38+1 -> 5 | C39: BS Construction | D39: 10
B40: =B39+1 -> 6 | C40: Kalbushan | D40: 11
B41: Total | D41: =SUM(D35:D40) -> 66
B43: LILO -Kisthwar
B44: S.No | C44: Sub Vendor | D44: Available | E44: Remarks
B45: 1 | C45: Zaffar | D45: 8
B46: =B45+1 -> 2 | C46: Bittu | D46: 14
B47: =B46+1 -> 3 | C47: Bhat Const. | D47: 17
B48: Total | D48: =SUM(D45:D47) -> 39

Sheet JS-Supply Stubs
A1: Stubs - SJ Line
A2: Tower | B2: Structure | C2: UOM | D2: Qty as per Approved C/S Jammu | E2: Qty as per Approved C/S Punjab | F2: Total Qty as per approved C/S | G2: Material Received in Jammu | H2: Material Received in Punjab | I2: Total Received | J2: Balance | K2: Remarks
A3: DA | B3: STUB(UPTO+9M) | C3: Set | D3: 74 | E3: 124 | F3: =D3+E3 -> 198 | G3: 80 | H3: =10+103+3 -> 116 | I3: =G3+H3 -> 196 | J3: =F3-I3 -> 2
B4: 1M RC | C4: Legs | D4: 8 | E4: 4 | F4: =D4+E4 -> 12 | G4: 8 | H4: 4 | I4: =G4+H4 -> 12 | J4: =F4-I4 -> 0
B5: 1.5M RC | C5: Legs | D5: 5 | E5: 12 | F5: =D5+E5 -> 17 | G5: 5 | H5: 10 | I5: =G5+H5 -> 15 | J5: =F5-I5 -> 2
B6: 2M RC | C6: Legs | F6: =D6+E6 -> 0 | H6: 0 | I6: =G6+H6 -> 0 | J6: =F6-I6 -> 0
B7: 2M RC | C7: Legs | F7: =D7+E7 -> 0 | H7: 0 | I7: =G7+H7 -> 0 | J7: =F7-I7 -> 0
B8: 2.5M RC | C8: Legs | D8: 1 | F8: =D8+E8 -> 1 | G8: 1 | H8: 0 | I8: =G8+H8 -> 1 | J8: =F8-I8 -> 0 | N8: DA | O8: 5
A9: DB | B9: STUB(UPTO+9M) | C9: Set | D9: 17 | E9: 38 | F9: =D9+E9 -> 55 | G9: 20 | H9: 33 | I9: =G9+H9 -> 53 | J9: =F9-I9 -> 2 | N9: DB | O9: 5
B10: 1M RC | C10: Legs | E10: 4 | F10: =D10+E10 -> 4 | H10: 4 | I10: =G10+H10 -> 4 | J10: =F10-I10 -> 0 | N10: DC | O10: 2
B11: 1.5M RC | C11: Legs | D11: 4 | E11: 4 | F11: =D11+E11 -> 8 | G11: 4 | H11: 4 | I11: =G11+H11 -> 8 | J11: =F11-I11 -> 0 | N11: DD | O11: 2
B12: 2M RC | C12: Legs | D12: 1 | F12: =D12+E12 -> 1 | G12: 1 | H12: 4 | I12: =G12+H12 -> 5 | J12: =F12-I12 -> -4 | K12: Qty recived as per approved survey , but due to revison of survey qty became excess
A13: DC | B13: STUB(UPTO+9M) | C13: Set | D13: 13 | E13: 33 | F13: =D13+E13 -> 46 | G13: 20 | H13: 24 | I13: =G13+H13 -> 44 | J13: =F13-I13 -> 2
B14: 1M RC | C14: Legs | F14: =D14+E14 -> 0 | H14: 0 | I14: =G14+H14 -> 0 | J14: =F14-I14 -> 0
B15: 1.5M RC | C15: Legs | D15: 5 | E15: 4 | F15: =D15+E15 -> 9 | G15: 5 | H15: 4 | I15: =G15+H15 -> 9 | J15: =F15-I15 -> 0
B16: 2M RC | C16: Legs | F16: =D16+E16 -> 0 | H16: 0 | I16: =G16+H16 -> 0 | J16: =F16-I16 -> 0
B17: 2.5M RC | C17: Legs | D17: 1 | F17: =D17+E17 -> 1 | G17: 1 | H17: 0 | I17: =G17+H17 -> 1 | J17: =F17-I17 -> 0
B18: 3M RC | C18: Legs | D18: 2 | F18: =D18+E18 -> 2 | G18: 2 | H18: 0 | I18: =G18+H18 -> 2 | J18: =F18-I18 -> 0
A19: DD | B19: STUB(UPTO+9M) | C19: Set | D19: 10 | E19: 20 | F19: =D19+E19 -> 30 | G19: 10 | H19: 20 | I19: =G19+H19 -> 30 | J19: =F19-I19 -> 0
B20: 1M RC | C20: Legs | E20: 4 | F20: =D20+E20 -> 4 | H20: 4 | I20: =G20+H20 -> 4 | J20: =F20-I20 -> 0
B21: 1.5M RC | C21: Legs | D21: 4 | E21: 4 | F21: =D21+E21 -> 8 | G21: 4 | H21: 4 | I21: =G21+H21 -> 8 | J21: =F21-I21 -> 0
B22: 2M RC | C22: Legs | D22: 4 | F22: =D22+E22 -> 4 | G22: 4 | H22: 4 | I22: =G22+H22 -> 8 | J22: =F22-I22 -> -4 | K22: Qty recived as per approved survey , but due to revison of survey qty became excess
B23: 3M RC | C23: Legs | F23: =D23+E23 -> 0 | H23: 0 | I23: =G23+H23 -> 0 | J23: =F23-I23 -> 0
B24: STUB (+18/+25/+30M) | C24: Set | D24: 9.25 | E24: 22 | F24: =D24+E24 -> 31.25 | G24: =5+3 -> 8 | H24: 22 | I24: =G24+H24 -> 30 | J24: =F24-I24 -> 1.25
B25: 1.5M RC | C25: Legs | D25: 3 | F25: =D25+E25 -> 3 | G25: 3 | H25: 0 | I25: =G25+H25 -> 3 | J25: =F25-I25 -> 0
B26: 2M RC | C26: Legs | D26: 8 | E26: 24 | F26: =D26+E26 -> 32 | G26: 4 | H26: =20+8 -> 28 | I26: =G26+H26 -> 32 | J26: =F26-I26 -> 0
B27: 4M RC | C27: Legs | D27: 4 | F27: =D27+E27 -> 4 | G27: 4 | H27: 0 | I27: =G27+H27 -> 4 | J27: =F27-I27 -> 0
B28: 3M RC | C28: Legs | D28: 2 | F28: =D28+E28 -> 2 | G28: 2 | H28: 0 | I28: =G28+H28 -> 2 | J28: =F28-I28 -> 0
B29: 5M RC | C29: Legs | D29: 2 | F29: =D29+E29 -> 2 | G29: 2 | H29: 0 | I29: =G29+H29 -> 2 | J29: =F29-I29 -> 0
A30: Total | D30: =D3+D9+D13+D19+D24+((D4)/4)+(D21/4)+(D25/4)+(D20/4)+(D10/4) -> 127 | E30: =E3+E9+E13+E19+E24+((E4)/4)+(E21/4)+(E25/4)+(E20/4)+(E10/4) -> 241 | F30: =F3+F9+F13+F19+F24+((F4)/4)+(F21/4)+(F25/4)+(F20/4)+(F10/4) -> 368 | G30: =G3+G9+G13+G19+G24+((G4)/4)+(G21/4)+(G25/4)+(G20/4)+(G10/4) -> 141.75 | H30: =H3+H9+H13+H19+H24+((H4)/4)+(H21/4)+(H25/4)+(H20/4)+(H10/4) -> 219 | I30: =I3+I9+I13+I19+I24+((I4)/4)+(I21/4)+(I25/4)+(I20/4)+(I10/4) -> 360.75 | J30: =J3+J9+J13+J19+J24+((J4)/4)+(J21/4)+(J25/4)+(J20/4)+(J10/4) -> 7.25

Sheet JS Supply Towers
A1: TOWERS - SJ Line
A2: Tower | B2: Structure | C2: Qty as per Approved C/S Jammu | D2: Qty as per Approved C/S Punjab | E2: Total Qty as per approved C/S | F2: Material Received in Jammu | G2: Material Received in Punjab | H2: Total Received | I2: Inspection Completed on 18th Mar'26 and Material under transit | J2: Balance | K2: Remarks
A3: DA | B3: Basic Tower Body | C3: 76 | D3: 125 | E3: =C3+D3 -> 201 | F3: 84 | G3: 98 | H3: =F3+G3 -> 182 | J3: =E3-H3-I3 -> 19
B4: +0MBE | C4: 52 | D4: 88 | E4: =C4+D4 -> 140 | F4: 62 | G4: 59 | H4: =F4+G4 -> 121 | J4: =E4-H4-I4 -> 19
B5: +3MBE | C5: 24 | D5: 37 | E5: =C5+D5 -> 61 | F5: 22 | G5: 39 | H5: =F5+G5 -> 61 | J5: =E5-H5-I5 -> 0
B6: +6MBE | C6: 10 | D6: 14 | E6: =C6+D6 -> 24 | F6: 10 | G6: 14 | H6: =F6+G6 -> 24 | J6: =E6-H6-I6 -> 0
B7: +9MBE | C7: 2 | D7: 5 | E7: =C7+D7 -> 7 | F7: 2 | G7: 3 | H7: =F7+G7 -> 5 | J7: =E7-H7-I7 -> 2
E8: =C8+D8 -> 0 | F8: 0 | G8: 0 | H8: =F8+G8 -> 0 | J8: =E8-H8-I8 -> 0
A9: DB | B9: Basic Tower Body | C9: 17 | D9: 39 | E9: =C9+D9 -> 56 | F9: 7 | G9: 39 | H9: =F9+G9 -> 46 | J9: =E9-H9-I9 -> 10
B10: +0MBE | C10: 16 | D10: 33 | E10: =C10+D10 -> 49 | F10: 6 | G10: 33 | H10: =F10+G10 -> 39 | J10: =E10-H10-I10 -> 10
B11: +3MBE | C11: 1 | D11: 6 | E11: =C11+D11 -> 7 | F11: 1 | G11: 6 | H11: =F11+G11 -> 7 | J11: =E11-H11-I11 -> 0
B12: +6MBE | C12: 1 | D12: 4 | E12: =C12+D12 -> 5 | F12: 1 | G12: 2 | H12: =F12+G12 -> 3 | J12: =E12-H12-I12 -> 2
B13: +9MBE | C13: 2 | D13: 6 | E13: =C13+D13 -> 8 | F13: 2 | G13: 5 | H13: =F13+G13 -> 7 | J13: =E13-H13-I13 -> 1
E14: =C14+D14 -> 0 | F14: 0 | G14: 0 | H14: =F14+G14 -> 0 | J14: =E14-H14-I14 -> 0
A15: DC | B15: Basic Tower Body | C15: 13 | D15: 32 | E15: =C15+D15 -> 45 | F15: 23 | G15: 10 | H15: =F15+G15 -> 33 | I15: =2+2 -> 4 | J15: =E15-H15-I15 -> 8
B16: +0MBE | C16: 9 | D16: 25 | E16: =C16+D16 -> 34 | F16: 20 | G16: 5 | H16: =F16+G16 -> 25 | I16: =1+1 -> 2 | J16: =E16-H16-I16 -> 7
B17: +3MBE | C17: 4 | D17: 7 | E17: =C17+D17 -> 11 | F17: 3 | G17: 5 | H17: =F17+G17 -> 8 | I17: =1+1 -> 2 | J17: =E17-H17-I17 -> 1
B18: +6MBE | C18: 1 | D18: 2 | E18: =C18+D18 -> 3 | F18: 0 | G18: 2 | H18: =F18+G18 -> 2 | J18: =E18-H18-I18 -> 1
B19: +9MBE | C19: 2 | D19: 4 | E19: =C19+D19 -> 6 | F19: 0 | G19: 3 | H19: =F19+G19 -> 3 | I19: =1+1 -> 2 | J19: =E19-H19-I19 -> 1
E20: =C20+D20 -> 0 | F20: 0 | G20: 0 | H20: =F20+G20 -> 0 | J20: =E20-H20-I20 -> 0
A21: DD | B21: Basic Tower Body | C21: 21 | D21: 44 | E21: =C21+D21 -> 65 | F21: 18 | G21: 35 | H21: =F21+G21 -> 53 | J21: =E21-H21-I21 -> 12
B22: +0MBE | C22: 20 | D22: 39 | E22: =C22+D22 -> 59 | F22: 17 | G22: 30 | H22: =F22+G22 -> 47 | J22: =E22-H22-I22 -> 12
B23: +3MBE | C23: 1 | D23: 5 | E23: =C23+D23 -> 6 | F23: 1 | G23: 5 | H23: =F23+G23 -> 6 | J23: =E23-H23-I23 -> 0
B24: +6MBE | C24: 1 | D24: 2 | E24: =C24+D24 -> 3 | F24: 1 | G24: 2 | H24: =F24+G24 -> 3 | J24: =E24-H24-I24 -> 0
B25: +9MBE | C25: 3 | D25: 5 | E25: =C25+D25 -> 8 | F25: 3 | G25: 5 | H25: =F25+G25 -> 8 | J25: =E25-H25-I25 -> 0
B26: +18MBE | C26: 1 | D26: 10 | E26: =C26+D26 -> 11 | F26: 0 | G26: 0 | H26: =F26+G26 -> 0 | I26: 6 | J26: =E26-H26-I26 -> 5
B27: +25MBE | C27: 4 | D27: 8 | E27: =C27+D27 -> 12 | F27: 0 | G27: 0 | H27: =F27+G27 -> 0 | I27: 8 | J27: =E27-H27-I27 -> 4
B28: +30MBE | C28: 5 | D28: 4 | E28: =C28+D28 -> 9 | F28: 0 | G28: 0 | H28: =F28+G28 -> 0 | I28: 1 | J28: =E28-H28-I28 -> 8
E29: =C29+D29 -> 0 | F29: 0 | G29: 0 | H29: =F29+G29 -> 0 | J29: =E29-H29-I29 -> 0
A30: DCT | B30: Basic Tower Body | D30: 1 | E30: =C30+D30 -> 1 | F30: 0 | G30: 0 | H30: =F30+G30 -> 0 | J30: =E30-H30-I30 -> 1
B31: +0MBE | D31: 1 | E31: =C31+D31 -> 1 | F31: 0 | G31: 0 | H31: =F31+G31 -> 0 | J31: =E31-H31-I31 -> 1
A32: Total | C32: =C21+C15+C9+C3+C30 -> 127 | D32: =D21+D15+D9+D3+D30 -> 241 | E32: =E21+E15+E9+E3+E30 -> 368 | F32: =F21+F15+F9+F3+F30 -> 132 | G32: =G21+G15+G9+G3+G30 -> 182 | H32: =H21+H15+H9+H3+H30 -> 314 | I32: =I21+I15+I9+I3+I30 -> 4 | J32: =J21+J15+J9+J3+J30 -> 50

Sheet SK Supply Stubs
A1: Stubs - SK Line
A2: Tower | B2: Structure | C2: UOM | D2: Qty as per C/S. Approved | E2: Material Received | F2: Balance | G2: Remarks
A3: DA | B3: STUB(UPTO+9M) | C3: Set | D3: 1 | E3: 2 | F3: =D3-E3 -> -1 | G3: Qty recived as per approved survey , but due to revison of survey qty became excess
B4: 1M RC | C4: Leg | E4: 0 | F4: =D4-E4 -> 0
B5: 1.5M RC | C5: Leg | E5: 2 | F5: =D5-E5 -> -2 | G5: Qty recived as per approved survey , but due to revison of survey qty became excess
B6: 2M RC | C6: Leg | E6: 0 | F6: =D6-E6 -> 0
B7: 2.5M RC | C7: Leg | E7: 0 | F7: =D7-E7 -> 0
A8: DB | B8: STUB(UPTO+9M) | C8: Set | D8: 33.5 | E8: 31 | F8: =D8-E8 -> 2.5 | L8: =6/4 -> 1.5
B9: 1M RC | C9: Leg | D9: 6 | E9: 6 | F9: =D9-E9 -> 0
B10: 1.5M RC | C10: Leg | D10: 16 | E10: 15 | F10: =D10-E10 -> 1
B11: 2M RC | C11: Leg | D11: 4 | E11: 4 | F11: =D11-E11 -> 0
B12: 3M RC | C12: Leg | D12: 8 | E12: 8 | F12: =D12-E12 -> 0
B13: 5M RC | C13: Leg | D13: 1 | E13: 0 | F13: =D13-E13 -> 1
B14: 6M RC | C14: Leg | D14: 1 | E14: 0 | F14: =D14-E14 -> 1
B15: 8M RC | C15: Leg | D15: 2 | E15: 0 | F15: =D15-E15 -> 2
B16: 12M RC | C16: Leg | D16: 1 | E16: 0 | F16: =D16-E16 -> 1
A17: DC | B17: STUB(UPTO+9M) | C17: Set | D17: 33.25 | E17: 31 | F17: =D17-E17 -> 2.25
B18: 1M RC | C18: Leg | D18: 7 | E18: 7 | F18: =D18-E18 -> 0
B19: 1.5M RC | C19: Leg | D19: 4 | E19: 4 | F19: =D19-E19 -> 0
B20: 2M RC | C20: Leg | D20: 8 | E20: 7 | F20: =D20-E20 -> 1
B21: 2.5M RC | C21: Leg | E21: 0 | F21: =D21-E21 -> 0
B22: 3M RC | C22: Leg | D22: 8 | E22: 8 | F22: =D22-E22 -> 0
B23: 4M RC | C23: Leg | D23: 1 | E23: 0 | F23: =D23-E23 -> 1
B24: 5M RC | C24: Leg | D24: 2 | E24: 2 | F24: =D24-E24 -> 0
B25: 8M RC | C25: Leg | D25: 1 | E25: 0 | F25: =D25-E25 -> 1
B26: 10M RC | C26: Leg | D26: 2 | E26: 0 | F26: =D26-E26 -> 2
