Workbook
Name \0: #REF!
Name \0: #REF!
Name \0: #REF!
Name \0: #REF!
Name \0: #REF!
Name \01: #REF!
Name \1: #N/A
Name \2: #REF!
Name \2: #REF!
Name \2: #REF!
Name \2: #REF!
Name \3: #REF!
Name \4: #REF!
Name \A: #REF!
Name \A: #REF!
Name \A: #REF!
Name \A: #REF!
Name \A_1: "#REF!"
Name \a1: #REF!
Name \aa: #REF!
Name \B: #REF!
Name \B: #REF!
Name \B: #REF!
Name \B: #REF!
Name \C: #REF!
Name \C: #REF!
Name \c1: #REF!
Name \d: #N/A
Name \E: #REF!
Name \f: #REF!
Name \f: #REF!
Name \g: #REF!
Name \H: #REF!
Name \H: #REF!
Name \H: #REF!
Name \H: #REF!
Name \I: #REF!
Name \j: #REF!
Name \k: #REF!
Name \KWS123: #N/A
Name \l: #REF!
Name \l: #REF!
Name \l: #REF!
Name \l: #REF!
Name \l: #REF!
Name \M: #REF!
Name \N: #REF!
Name \P: #REF!
Name \Q: #REF!
Name \q: #N/A
Name \R: #REF!
Name \R: #REF!
Name \R: #REF!
Name \R: #REF!
Name \R: #REF!
Name \S: #REF!
Name \t: #N/A
Name \U: #REF!
Name \U: #REF!
Name \U: #REF!

Sheet TA413_PBNTL
A1: TA413 : 765 KV D/C Bikaner III - Neemrana II TL02 | M1: 27.05.2026
A2: Name of Client: PowerGrid Bikaner Neemrana Transmission Limited (Power Grid Corporation of India) | K2: Project Duration : 21 Month EOT -30/06/2026
A3: Name of Line: 765 KV D/C Bikaner III - Neemrana II TL02 LOA Value: 389.96 Crore
A4: NOA No: CC/T/W-TW/DOM/A04/23/10569/NOA-1&2/24-103421/01&02 Date.12/03/2024 Amendment -II Comp Value As on: 390 Crore
A5: Office: Hansera, Bikaner, Rajasthan.
A6: Sl. No. | B6: Activity | C6: LOA Quantity | D6: As per latest Estimate | E6: Cumm. Progress up to last Month | F6: Cumm L2 Schedule till Apr'26 | G6: Plan for this Month | H6: Current Month Achieved (As on dated ) | I6: Today | J6: Cumulative Progress | K6: Balance | L6: No of Gangs | M6: Remarks
A7: 1 | B7: Detail Survey (Km) | C7: 112.611 | D7: 117.85085 | E7: 117.85085 | F7: 112.611 | H7: =D7-E7 -> 0 | I7: 0 | J7: =E7+H7 -> 117.85085 | K7: =D7-J7 -> 0 | M7: Completed
A8: 2 | B8: Soil Investigation (Nos.) | C8: 29 | D8: 29 | E8: 26 | F8: 0 | H8: 0 | I8: 0 | J8: =E8+H8 -> 26 | K8: 0 | M8: Completed
A9: 3 | B9: Check Survey approved(Km) | C9: 112.611 | D9: 117.85085 | E9: 117.85085 | F9: 112.611 | H9: 0 | I9: 0 | J9: =E9+H9 -> 117.85085 | K9: =D9-J9 -> 0 | M9: Completed
A10: 4 | B10: Excavation | C10: 287 | D10: 316 | E10: =17+21+18+41+36+24+32+35+31+19+23+10+4+2+1+1+1 -> 316 | F10: 287 | G10: 0 | H10: 0 | I10: 0 | J10: =E10+H10 -> 316 | K10: =D10-J10 -> 0 | M10: Completed
A11: 5 | B11: Foundation (Nos.) | C11: =C10 -> 287 | D11: 316 | E11: =17+21+18+41+36+24+32+35+31+19+23+10+4+2+1+1+1 -> 316 | F11: 287 | G11: 0 | H11: 0 | I11: 0 | J11: =E11+H11 -> 316 | K11: =D11-J11 -> 0 | M11: Completed
A12: 6 | B12: Earthing (Nos.) | C12: =C11 -> 287 | D12: 309 | E12: =26+70+28+16+29+8+75+25+15+6+6+3 -> 307 | F12: =F11 -> 287 | G12: 0 | H12: 0 | I12: 0 | J12: =E12+H12 -> 307 | K12: =D12-J12 -> 2
A13: 7 | B13: Tower Erection (Nos) | C13: 287 | D13: 306 | E13: 302 | F13: 287 | G13: 1 | H13: 0 | I13: 0 | J13: =E13+H13 -> 302 | K13: =D13-J13 -> 4
A14: 8 | B14: Tack Welding | C14: =C13 -> 287 | D14: 306 | E14: =126+15+30+40+13 -> 224 | F14: 287 | G14: 40 | H14: 31 | I14: 0 | J14: =E14+H14 -> 255 | K14: =D14-J14 -> 51 | L14: 1 | M14: G_1:- M.S Enterprises
A15: 9 | B15: Bird Guard (Set of Three) | C15: 241 | D15: 244 | E15: 0 | G15: 50 | H15: 99 | I15: 0 | J15: =E15+H15 -> 99 | K15: =D15-J15 -> 145 | L15: 2 | M15: G_1:- Jetha Ram - G_2 Mahendra Banjara
A16: 10 | B16: Stringing (Km) | C16: 112.611 | D16: =D7 -> 117.85085 | E16: =21.496+4.922+4.901+8.229+9.801+14.275+4.965 -> 68.589 | F16: 112 | G16: 18 | H16: =2.669+2.379+1.004+2.548 -> 8.6 | I16: 2.548 | J16: =E16+H16 -> 77.189 | K16: =D16-J16 -> 40.661851 | L16: 2 | M16: G_1:- Rahim Khan (15 MP) | O16: =D17-E17 -> 45.588851
A17: a) | B17: Paying Out | C17: =C16 -> 112.611 | D17: =D7 -> 117.85085 | E17: =21.496+4.922+4.901+8.229+9.801+10.151+4.124+8.638 -> 72.262 | F17: 112 | G17: 18 | H17: =2.379+2.548 -> 4.927 | I17: 0 | J17: =E17+H17 -> 77.189 | K17: =D17-J17 -> 40.661851 | M17: G_2:- SK infra (MP 45)
A18: b) | B18: Final Sag | C18: =C17 -> 112.611 | D18: =D7 -> 117.85085 | E18: =21.496+4.922+4.901+8.229+9.801+10.151+4.124+4.965 -> 68.589 | F18: 112 | G18: 18 | H18: =H16 -> 8.6 | I18: =I16 -> 2.548 | J18: =E18+H18 -> 77.189 | K18: =D18-J18 -> 40.661851
A19: 11 | B19: OPGW (Km) | C19: =C18 -> 112.611 | D19: =D7 -> 117.85085 | E19: =13.612+4.6+18.591+22.959 -> 59.762 | F19: 112 | G19: 25 | H19: 0 | I19: 0 | J19: =+E19+H19 -> 59.762 | K19: =D19-J19 -> 58.088851
A24: .
E260: 2MRC Sandy
E261: 2MRC Sandy
E262: 2MRC Sandy

Sheet Visual Chart
B1: KEC INTERNATIONAL LIMITED
B2: =TA413_PBNTL!A3 -> Name of Line: 765 KV D/C Bikaner III - Neemrana II TL02 LOA Value: 389.96 Crore | V2: Visual Chart | AQ2: =TA413_PBNTL!M1 -> 27.05.2026
C4: S. No. | E4: Description | I4: UOM | K4: Total Qty | M4: Completed | P4: Balance | T4: Power Line Crossing | AC4: Stringing U/P | AL4: Stringing completed
C5: 1 | E5: Foundation | I5: Nos | K5: =TA413_PBNTL!D11 -> 316 | M5: =TA413_PBNTL!J11 -> 316 | P5: =K5-M5 -> 0 | AC5: Tack Welding U/P | AL5: Tack Welding completed
C6: 2 | E6: Earthing | I6: Nos | K6: =TA413_PBNTL!D12 -> 309 | M6: =TA413_PBNTL!J12 -> 307 | P6: =K6-M6 -> 2 | T6: NH / SH Crossing | AC6: Erection U/P | AJ6: 4 | AL6: Erection completed
C7: 3 | E7: Tower Erection | I7: Nos | K7: =TA413_PBNTL!D13 -> 306 | M7: =TA413_PBNTL!J13 -> 302 | P7: =K7-M7 -> 4 | AA7: 1 | AC7: Foundation U/P | AL7: Foundation completed
C8: 4 | E8: Rough Sag | I8: KM | K8: =TA413_PBNTL!D17 -> 117.85085 | M8: =TA413_PBNTL!J17 -> 77.189 | P8: =K8-M8 -> 40.661851 | T8: Railway Crossing | AJ8: 3
C9: 5 | E9: Final Sag | I9: KM | K9: =TA413_PBNTL!D18 -> 117.85085 | M9: =TA413_PBNTL!J18 -> 77.189 | P9: =K9-M9 -> 40.661851 | AA9: 1 | AC9: Excavation U/P | AJ9: 2 | AL9: Excavation completed
T10: Canal | AL10: Earthing completed
Q12: =O12+1 -> 1 | S12: 2 | U12: =S12+1 -> 3 | W12: =U12+1 -> 4 | Y12: =W12+1 -> 5 | AA12: =Y12+1 -> 6 | AC12: =AA12+1 -> 7 | AE12: =AC12+1 -> 8 | AG12: =AE12+1 -> 9 | AI12: =AG12+1 -> 10 | AK12: =AI12+1 -> 11 | AM12: =AK12+1 -> 12 | AO12: =AM12+1 -> 13 | AQ12: =AO12+1 -> 14 | AS12: =AQ12+1 -> 15
D13: Hold | O13: Gantry | Q13: 1/0 | S13: 2A/0 | U13: 2A/1 | W13: 2A/2 | Y13: 2A/3 | AA13: 2A/4 | AC13: 2A/5 | AE13: 2A/6 | AG13: 3A/0 | AI13: 3A/1 | AK13: 3A/2 | AM13: 3A/3 | AO13: 3A/4 | AQ13: 3A/5 | AS13: 3A/6
D15: Foundation ROW
K16: Bikaner III Gantry | P16: 150 | Q16: 3 | R16: 290.21 | S16: 3 | T16: =VLOOKUP(S13,'Location Summary'!$G$2:$H$604,2,FALSE) -> 378 | U16: 3 | V16: =VLOOKUP(U13,'Location Summary'!$G$2:$H$604,2,FALSE) -> 381 | W16: 3 | X16: =VLOOKUP(W13,'Location Summary'!$G$2:$H$604,2,FALSE) -> 419 | Y16: 3 | Z16: =VLOOKUP(Y13,'Location Summary'!$G$2:$H$604,2,FALSE) -> 422 | AA16: 3 | AB16: =VLOOKUP(AA13,'Location Summary'!$G$2:$H$604,2,FALSE) -> 399 | AC16: 3 | AD16: =VLOOKUP(AC13,'Location Summary'!$G$2:$H$604,2,FALSE) -> 423 | AE16: 3 | AF16: =VLOOKUP(AE13,'Location Summary'!$G$2:$H$604,2,FALSE) -> 414.992 | AG16: 3 | AH16: =VLOOKUP(AG13,'Location Summary'!$G$2:$H$604,2,FALSE) -> 409 | AI16: 3 | AJ16: =VLOOKUP(AI13,'Location Summary'!$G$2:$H$604,2,FALSE) -> 402 | AK16: 3 | AL16: =VLOOKUP(AK13,'Location Summary'!$G$2:$H$604,2,FALSE) -> 409 | AM16: 3 | AN16: =VLOOKUP(AM13,'Location Summary'!$G$2:$H$604,2,FALSE) -> 337 | AO16: 3 | AP16: =VLOOKUP(AO13,'Location Summary'!$G$2:$H$604,2,FALSE) -> 365 | AQ16: 3 | AR16: =VLOOKUP(AQ13,'Location Summary'!$G$2:$H$604,2,FALSE) -> 378 | AS16: 3 | AT16: =VLOOKUP(AS13,'Location Summary'!$G$2:$H$604,2,FALSE) -> 391.467
D17: Erection ROW | Q17: 2 | S17: 2 | U17: 2 | W17: 2 | Y17: 2 | AA17: 2 | AC17: 2 | AE17: 2 | AG17: 2 | AI17: 2 | AK17: 2 | AM17: 2 | AO17: 2 | AQ17: 2 | AS17: 2
O18: Gantry | Q18: =VLOOKUP(Q13,'Location Summary'!$C$2:$J$604,2,FALSE) -> DD60+0 | S18: =VLOOKUP(S13,'Location Summary'!$C$2:$J$604,2,FALSE) -> DD45+0 | U18: =VLOOKUP(U13,'Location Summary'!$C$2:$J$604,2,FALSE) -> DA+0 | W18: =VLOOKUP(W13,'Location Summary'!$C$2:$J$604,2,FALSE) -> DA+3 | Y18: =VLOOKUP(Y13,'Location Summary'!$C$2:$J$604,2,FALSE) -> DA+3 | AA18: =VLOOKUP(AA13,'Location Summary'!$C$2:$J$604,2,FALSE) -> DA+3 | AC18: =VLOOKUP(AC13,'Location Summary'!$C$2:$J$604,2,FALSE) -> DA+3 | AE18: =VLOOKUP(AE13,'Location Summary'!$C$2:$J$604,2,FALSE) -> DA+6 | AG18: =VLOOKUP(AG13,'Location Summary'!$C$2:$J$604,2,FALSE) -> DD45+3 | AI18: =VLOOKUP(AI13,'Location Summary'!$C$2:$J$604,2,FALSE) -> DA+3 | AK18: =VLOOKUP(AK13,'Location Summary'!$C$2:$J$604,2,FALSE) -> DA+3 | AM18: =VLOOKUP(AM13,'Location Summary'!$C$2:$J$604,2,FALSE) -> DA+0 | AO18: =VLOOKUP(AO13,'Location Summary'!$C$2:$J$604,2,FALSE) -> DA+0 | AQ18: =VLOOKUP(AQ13,'Location Summary'!$C$2:$J$604,2,FALSE) -> DA+3 | AS18: =VLOOKUP(AS13,'Location Summary'!$C$2:$J$604,2,FALSE) -> DA+0
C20: =AS12+1 -> 16 | E20: =C20+1 -> 17 | G20: =E20+1 -> 18 | I20: =G20+1 -> 19 | K20: =I20+1 -> 20 | M20: =K20+1 -> 21 | O20: =M20+1 -> 22 | Q20: =O20+1 -> 23 | S20: =Q20+1 -> 24 | U20: =S20+1 -> 25 | W20: =U20+1 -> 26 | Y20: =W20+1 -> 27 | AA20: =Y20+1 -> 28 | AC20: =AA20+1 -> 29 | AE20: =AC20+1 -> 30 | AG20: =AE20+1 -> 31 | AI20: =AG20+1 -> 32 | AK20: =AI20+1 -> 33 | AM20: =AK20+1 -> 34 | AO20: =AM20+1 -> 35 | AQ20: =AO20+1 -> 36 | AS20: =AQ20+1 -> 37
C21: 3B/0 | E21: 3B/1 | G21: 3B/2 | I21: 3B/3 | K21: 4/0 | M21: 4/5 | O21: 4A/0 | Q21: 4A/1 | S21: 4A/2 | U21: 4A/3 | W21: 4A/4 | Y21: 4A/5 | AA21: 4A/6 | AC21: 5/0 | AE21: 5/1 | AG21: 5/2 | AI21: 5/3 | AK21: 5/4 | AM21: 5/5 | AO21: 5/6 | AQ21: 5/7 | AS21: 5/8
C24: 3 | D24: =VLOOKUP(C21,'Location Summary'!$G$2:$H$604,2,FALSE) -> 356 | E24: 3 | F24: =VLOOKUP(E21,'Location Summary'!$G$2:$H$604,2,FALSE) -> 439 | G24: 3 | H24: =VLOOKUP(G21,'Location Summary'!$G$2:$H$604,2,FALSE) -> 377 | I24: 3 | J24: =VLOOKUP(I21,'Location Summary'!$G$2:$H$604,2,FALSE) -> 455.07 | K24: 3 | L24: =VLOOKUP(K21,'Location Summary'!$G$2:$H$604,2,FALSE) -> 344.163 | M24: 3 | N24: =VLOOKUP(M21,'Location Summary'!$G$2:$H$604,2,FALSE) -> 365 | O24: 3 | P24: =VLOOKUP(O21,'Location Summary'!$G$2:$H$604,2,FALSE) -> 340 | Q24: 3 | R24: =VLOOKUP(Q21,'Location Summary'!$G$2:$H$604,2,FALSE) -> 420 | S24: 3 | T24: =VLOOKUP(S21,'Location Summary'!$G$2:$H$604,2,FALSE) -> 415 | U24: 3 | V24: =VLOOKUP(U21,'Location Summary'!$G$2:$H$604,2,FALSE) -> 365 | W24: 3 | X24: =VLOOKUP(W21,'Location Summary'!$G$2:$H$604,2,FALSE) -> 330 | Y24: 3 | Z24: =VLOOKUP(Y21,'Location Summary'!$G$2:$H$604,2,FALSE) -> 457 | AA24: 3 | AB24: =VLOOKUP(AA21,'Location Summary'!$G$2:$H$604,2,FALSE) -> 354.611 | AC24: 3 | AD24: =VLOOKUP(AC21,'Location Summary'!$G$2:$H$604,2,FALSE) -> 428.389 | AE24: 3 | AF24: =VLOOKUP(AE21,'Location Summary'!$G$2:$H$604,2,FALSE) -> 340 | AG24: 3 | AH24: =VLOOKUP(AG21,'Location Summary'!$G$2:$H$604,2,FALSE) -> 375 | AI24: 3 | AJ24: =VLOOKUP(AI21,'Location Summary'!$G$2:$H$604,2,FALSE) -> 365 | AK24: 3 | AL24: =VLOOKUP(AK21,'Location Summary'!$G$2:$H$604,2,FALSE) -> 460 | AM24: 3 | AN24: =VLOOKUP(AM21,'Location Summary'!$G$2:$H$604,2,FALSE) -> 380 | AO24: 3 | AP24: =VLOOKUP(AO21,'Location Summary'!$G$2:$H$604,2,FALSE) -> 410 | AQ24: 3 | AR24: =VLOOKUP(AQ21,'Location Summary'!$G$2:$H$604,2,FALSE) -> 400 | AS24: 3 | AT24: =VLOOKUP(AS21,'Location Summary'!$G$2:$H$604,2,FALSE) -> 420
C25: 2 | E25: 2 | G25: 2 | I25: 2 | K25: 2 | M25: 2 | O25: 2 | Q25: 2 | S25: 2 | U25: 2 | W25: 2 | Y25: 2 | AA25: 2 | AC25: 2 | AE25: 2 | AG25: 2 | AI25: 2 | AK25: 2 | AM25: 2 | AO25: 2 | AQ25: 2 | AS25: 2
C26: =VLOOKUP(C21,'Location Summary'!$C$2:$J$604,2,FALSE) -> DB1+9 | E26: =VLOOKUP(E21,'Location Summary'!$C$2:$J$604,2,FALSE) -> DA+3 | G26: =VLOOKUP(G21,'Location Summary'!$C$2:$J$604,2,FALSE) -> DA+9 | I26: =VLOOKUP(I21,'Location Summary'!$C$2:$J$604,2,FALSE) -> DA+6 | K26: =VLOOKUP(K21,'Location Summary'!$C$2:$J$604,2,FALSE) -> DB2+9 | M26: =VLOOKUP(M21,'Location Summary'!$C$2:$J$604,2,FALSE) -> DA+6 | O26: =VLOOKUP(O21,'Location Summary'!$C$2:$J$604,2,FALSE) -> DB1+3 | Q26: =VLOOKUP(Q21,'Location Summary'!$C$2:$J$604,2,FALSE) -> DA+6 | S26: =VLOOKUP(S21,'Location Summary'!$C$2:$J$604,2,FALSE) -> DA+6 | U26: =VLOOKUP(U21,'Location Summary'!$C$2:$J$604,2,FALSE) -> DA+9 | W26: =VLOOKUP(W21,'Location Summary'!$C$2:$J$604,2,FALSE) -> DA+6 | Y26: =VLOOKUP(Y21,'Location Summary'!$C$2:$J$604,2,FALSE) -> DA+9 | AA26: =VLOOKUP(AA21,'Location Summary'!$C$2:$J$604,2,FALSE) -> DA+9 | AC26: =VLOOKUP(AC21,'Location Summary'!$C$2:$J$604,2,FALSE) -> DB1+6 | AE26: =VLOOKUP(AE21,'Location Summary'!$C$2:$J$604,2,FALSE) -> DA+6 | AG26: =VLOOKUP(AG21,'Location Summary'!$C$2:$J$604,2,FALSE) -> DA+9 | AI26: =VLOOKUP(AI21,'Location Summary'!$C$2:$J$604,2,FALSE) -> DA+9 | AK26: =VLOOKUP(AK21,'Location Summary'!$C$2:$J$604,2,FALSE) -> DA-1.5 | AM26: =VLOOKUP(AM21,'Location Summary'!$C$2:$J$604,2,FALSE) -> DA+6 | AO26: =VLOOKUP(AO21,'Location Summary'!$C$2:$J$604,2,FALSE) -> DA+3 | AQ26: =VLOOKUP(AQ21,'Location Summary'!$C$2:$J$604,2,FALSE) -> DA+9 | AS26: =VLOOKUP(AS21,'Location Summary'!$C$2:$J$604,2,FALSE) -> DA+6
C28: =AS20+1 -> 38 | E28: =C28+1 -> 39 | G28: =E28+1 -> 40 | I28: =G28+1 -> 41 | K28: =I28+1 -> 42 | M28: =K28+1 -> 43 | O28: =M28+1 -> 44 | Q28: =O28+1 -> 45 | S28: =Q28+1 -> 46 | U28: =S28+1 -> 47 | W28: =U28+1 -> 48 | Y28: =W28+1 -> 49 | AA28: =Y28+1 -> 50 | AC28: =AA28+1 -> 51 | AE28: =AC28+1 -> 52 | AG28: =AE28+1 -> 53 | AI28: =AG28+1 -> 54 | AK28: =AI28+1 -> 55 | AM28: =AK28+1 -> 56 | AO28: =AM28+1 -> 57 | AQ28: =AO28+1 -> 58 | AS28: =AQ28+1 -> 59
C29: 5/9 | E29: 5/10 | G29: 5A/0 | I29: 6/0 | K29: 6/1 | M29: 6/2 | O29: 6/3 | Q29: 6/4 | S29: 6/5 | U29: 6/6 | W29: 6/7 | Y29: 6/8 | AA29: 6/9 | AC29: 6/10 | AE29: 6/11 | AG29: 6/12 | AI29: 7/0 | AK29: 7/1 | AM29: 7/2 | AO29: 7/3 | AQ29: 7/4 | AS29: 7/5
C32: 3 | D32: =VLOOKUP(C29,'Location Summary'!$G$2:$H$604,2,FALSE) -> 345 | E32: 3 | F32: =VLOOKUP(E29,'Location Summary'!$G$2:$H$604,2,FALSE) -> 495 | G32: 3 | H32: =VLOOKUP(G29,'Location Summary'!$G$2:$H$604,2,FALSE) -> 419.48 | I32: 3 | J32: =VLOOKUP(I29,'Location Summary'!$G$2:$H$604,2,FALSE) -> 350.52 | K32: 3 | L32: =VLOOKUP(K29,'Location Summary'!$G$2:$H$604,2,FALSE) -> 445 | M32: 3 | N32: =VLOOKUP(M29,'Location Summary'!$G$2:$H$604,2,FALSE) -> 390 | O32: 3 | P32: =VLOOKUP(O29,'Location Summary'!$G$2:$H$604,2,FALSE) -> 350 | Q32: 3 | R32: =VLOOKUP(Q29,'Location Summary'!$G$2:$H$604,2,FALSE) -> 490 | S32: 3 | T32: =VLOOKUP(S29,'Location Summary'!$G$2:$H$604,2,FALSE) -> 350 | U32: 3 | V32: =VLOOKUP(U29,'Location Summary'!$G$2:$H$604,2,FALSE) -> 347 | W32: 3 | X32: =VLOOKUP(W29,'Location Summary'!$G$2:$H$604,2,FALSE) -> 373 | Y32: 3 | Z32: =VLOOKUP(Y29,'Location Summary'!$G$2:$H$604,2,FALSE) -> 380 | AA32: 3 | AB32: =VLOOKUP(AA29,'Location Summary'!$G$2:$H$604,2,FALSE) -> 335 | AC32: 3 | AD32: =VLOOKUP(AC29,'Location Summary'!$G$2:$H$604,2,FALSE) -> 315 | AE32: 3 | AF32: =VLOOKUP(AE29,'Location Summary'!$G$2:$H$604,2,FALSE) -> 410 | AG32: 3 | AH32: =VLOOKUP(AG29,'Location Summary'!$G$2:$H$604,2,FALSE) -> 365.716 | AI32: 3 | AJ32: =VLOOKUP(AI29,'Location Summary'!$G$2:$H$604,2,FALSE) -> 319.284 | AK32: 3 | AL32: =VLOOKUP(AK29,'Location Summary'!$G$2:$H$604,2,FALSE) -> 465 | AM32: 3 | AN32: =VLOOKUP(AM29,'Location Summary'!$G$2:$H$604,2,FALSE) -> 375 | AO32: 3 | AP32: =VLOOKUP(AO29,'Location Summary'!$G$2:$H$604,2,FALSE) -> 355 | AQ32: 3 | AR32: =VLOOKUP(AQ29,'Location Summary'!$G$2:$H$604,2,FALSE) -> 420 | AS32: 3 | AT32: =VLOOKUP(AS29,'Location Summary'!$G$2:$H$604,2,FALSE) -> 315
C33: 2 | E33: 2 | G33: 2 | I33: 2 | K33: 2 | M33: 2 | O33: 2 | Q33: 2 | S33: 2 | U33: 2 | W33: 2 | Y33: 2 | AA33: 2 | AC33: 2 | AE33: 2 | AG33: 2 | AI33: 2 | AK33: 2 | AM33: 2 | AO33: 2 | AQ33: 2 | AS33: 2
C34: =VLOOKUP(C29,'Location Summary'!$C$2:$J$604,2,FALSE) -> DA+6 | E34: =VLOOKUP(E29,'Location Summary'!$C$2:$J$604,2,FALSE) -> DA+9 | G34: =VLOOKUP(G29,'Location Summary'!$C$2:$J$604,2,FALSE) -> DB1+12 | I34: =VLOOKUP(I29,'Location Summary'!$C$2:$J$604,2,FALSE) -> DB1+9 | K34: =VLOOKUP(K29,'Location Summary'!$C$2:$J$604,2,FALSE) -> DA+9 | M34: =VLOOKUP(M29,'Location Summary'!$C$2:$J$604,2,FALSE) -> DA+6 | O34: =VLOOKUP(O29,'Location Summary'!$C$2:$J$604,2,FALSE) -> DA+3 | Q34: =VLOOKUP(Q29,'Location Summary'!$C$2:$J$604,2,FALSE) -> DA+9 | S34: =VLOOKUP(S29,'Location Summary'!$C$2:$J$604,2,FALSE) -> DA+9 | U34: =VLOOKUP(U29,'Location Summary'!$C$2:$J$604,2,FALSE) -> DA-3 | W34: =VLOOKUP(W29,'Location Summary'!$C$2:$J$604,2,FALSE) -> DA+1.5 | Y34: =VLOOKUP(Y29,'Location Summary'!$C$2:$J$604,2,FALSE) -> DA+3 | AA34: =VLOOKUP(AA29,'Location Summary'!$C$2:$J$604,2,FALSE) -> DA+6 | AC34: =VLOOKUP(AC29,'Location Summary'!$C$2:$J$604,2,FALSE) -> DA+1.5 | AE34: =VLOOKUP(AE29,'Location Summary'!$C$2:$J$604,2,FALSE) -> DA-1.5 | AG34: =VLOOKUP(AG29,'Location Summary'!$C$2:$J$604,2,FALSE) -> DA+1.5 | AI34: =VLOOKUP(AI29,'Location Summary'!$C$2:$J$604,2,FALSE) -> DB2+0 | AK34: =VLOOKUP(AK29,'Location Summary'!$C$2:$J$604,2,FALSE) -> DA-3 | AM34: =VLOOKUP(AM29,'Location Summary'!$C$2:$J$604,2,FALSE) -> DA+6 | AO34: =VLOOKUP(AO29,'Location Summary'!$C$2:$J$604,2,FALSE) -> DA+9 | AQ34: =VLOOKUP(AQ29,'Location Summary'!$C$2:$J$604,2,FALSE) -> DA+6 | AS34: =VLOOKUP(AS29,'Location Summary'!$C$2:$J$604,2,FALSE) -> DA+6
C36: =AS28+1 -> 60 | E36: =C36+1 -> 61 | G36: =E36+1 -> 62 | I36: =G36+1 -> 63 | K36: =I36+1 -> 64 | M36: =K36+1 -> 65 | O36: =M36+1 -> 66 | Q36: =O36+1 -> 67 | S36: =Q36+1 -> 68 | U36: =S36+1 -> 69 | W36: =U36+1 -> 70 | Y36: =W36+1 -> 71 | AA36: =Y36+1 -> 72 | AC36: =AA36+1 -> 73 | AE36: =AC36+1 -> 74 | AG36: =AE36+1 -> 75 | AI36: =AG36+1 -> 76 | AK36: =AI36+1 -> 77 | AM36: =AK36+1 -> 78 | AO36: =AM36+1 -> 79 | AQ36: =AO36+1 -> 80 | AS36: =AQ36+1 -> 81
C37: 7/6 | E37: 7A/0 | G37: 7A/1 | I37: 7A/2 | K37: 7A/3 | M37: 7A/4 | O37: 7A/5 | Q37: 8/0 | S37: 8/1 | U37: 8/2 | W37: 8/3 | Y37: 8/4 | AA37: 8/5 | AC37: 8/6 | AE37: 8/7 | AG37: 8/8 | AI37: 8/9 | AK37: 8/10 | AM37: 8/11 | AO37: 8A/0 | AQ37: 9/0 | AS37: 9/1
C40: 3 | D40: =VLOOKUP(C37,'Location Summary'!$G$2:$H$604,2,FALSE) -> 450 | E40: 3 | F40: =VLOOKUP(E37,'Location Summary'!$G$2:$H$604,2,FALSE) -> 435 | G40: 3 | H40: =VLOOKUP(G37,'Location Summary'!$G$2:$H$604,2,FALSE) -> 385 | I40: 3 | J40: =VLOOKUP(I37,'Location Summary'!$G$2:$H$604,2,FALSE) -> 390 | K40: 3 | L40: =VLOOKUP(K37,'Location Summary'!$G$2:$H$604,2,FALSE) -> 405 | M40: 3 | N40: =VLOOKUP(M37,'Location Summary'!$G$2:$H$604,2,FALSE) -> 390 | O40: 3 | P40: =VLOOKUP(O37,'Location Summary'!$G$2:$H$604,2,FALSE) -> 429.77 | Q40: 3 | R40: =VLOOKUP(Q37,'Location Summary'!$G$2:$H$604,2,FALSE) -> 350 | S40: 3 | T40: =VLOOKUP(S37,'Location Summary'!$G$2:$H$604,2,FALSE) -> 330 | U40: 3 | V40: =VLOOKUP(U37,'Location Summary'!$G$2:$H$604,2,FALSE) -> 390 | W40: 3 | X40: =VLOOKUP(W37,'Location Summary'!$G$2:$H$604,2,FALSE) -> 400 | Y40: 3 | Z40: =VLOOKUP(Y37,'Location Summary'!$G$2:$H$604,2,FALSE) -> 338 | AA40: 3 | AB40: =VLOOKUP(AA37,'Location Summary'!$G$2:$H$604,2,FALSE) -> 357 | AC40: 3 | AD40: =VLOOKUP(AC37,'Location Summary'!$G$2:$H$604,2,FALSE) -> 335 | AE40: 3 | AF40: =VLOOKUP(AE37,'Location Summary'!$G$2:$H$604,2,FALSE) -> 415 | AG40: 3 | AH40: =VLOOKUP(AG37,'Location Summary'!$G$2:$H$604,2,FALSE) -> 375 | AI40: 3 | AJ40: =VLOOKUP(AI37,'Location Summary'!$G$2:$H$604,2,FALSE) -> 375 | AK40: 3 | AL40: =VLOOKUP(AK37,'Location Summary'!$G$2:$H$604,2,FALSE) -> 375 | AM40: 3 | AN40: =VLOOKUP(AM37,'Location Summary'!$G$2:$H$604,2,FALSE) -> 415 | AO40: 3 | AP40: =VLOOKUP(AO37,'Location Summary'!$G$2:$H$604,2,FALSE) -> 466.63 | AQ40: 3 | AR40: =VLOOKUP(AQ37,'Location Summary'!$G$2:$H$604,2,FALSE) -> 418.372 | AS40: 3 | AT40: =VLOOKUP(AS37,'Location Summary'!$G$2:$H$604,2,FALSE) -> 410
C41: 2 | E41: 2 | G41: 2 | I41: 2 | K41: 2 | M41: 2 | O41: 2 | Q41: 2 | S41: 2 | U41: 2 | W41: 2 | Y41: 2 | AA41: 2 | AC41: 2 | AE41: 2 | AG41: 2 | AI41: 2 | AK41: 2 | AM41: 2 | AO41: 2 | AQ41: 2 | AS41: 2
C42: =VLOOKUP(C37,'Location Summary'!$C$2:$J$604,2,FALSE) -> DA-1.5 | E42: =VLOOKUP(E37,'Location Summary'!$C$2:$J$604,2,FALSE) -> DB1+6 | G42: =VLOOKUP(G37,'Location Summary'!$C$2:$J$604,2,FALSE) -> DA+1.5 | I42: =VLOOKUP(I37,'Location Summary'!$C$2:$J$604,2,FALSE) -> DA+3 | K42: =VLOOKUP(K37,'Location Summary'!$C$2:$J$604,2,FALSE) -> DA+3 | M42: =VLOOKUP(M37,'Location Summary'!$C$2:$J$604,2,FALSE) -> DA+3 | O42: =VLOOKUP(O37,'Location Summary'!$C$2:$J$604,2,FALSE) -> DA+3 | Q42: =VLOOKUP(Q37,'Location Summary'!$C$2:$J$604,2,FALSE) -> DB1+0 | S42: =VLOOKUP(S37,'Location Summary'!$C$2:$J$604,2,FALSE) -> DA-3 | U42: =VLOOKUP(U37,'Location Summary'!$C$2:$J$604,2,FALSE) -> DA+6 | W42: =VLOOKUP(W37,'Location Summary'!$C$2:$J$604,2,FALSE) -> DA+9 | Y42: =VLOOKUP(Y37,'Location Summary'!$C$2:$J$604,2,FALSE) -> DA+6 | AA42: =VLOOKUP(AA37,'Location Summary'!$C$2:$J$604,2,FALSE) -> DA+9 | AC42: =VLOOKUP(AC37,'Location Summary'!$C$2:$J$604,2,FALSE) -> DA+3 | AE42: =VLOOKUP(AE37,'Location Summary'!$C$2:$J$604,2,FALSE) -> DA+3 | AG42: =VLOOKUP(AG37,'Location Summary'!$C$2:$J$604,2,FALSE) -> DA+9 | AI42: =VLOOKUP(AI37,'Location Summary'!$C$2:$J$604,2,FALSE) -> DA+3 | AK42: =VLOOKUP(AK37,'Location Summary'!$C$2:$J$604,2,FALSE) -> DA+0 | AM42: =VLOOKUP(AM37,'Location Summary'!$C$2:$J$604,2,FALSE) -> DA+9 | AO42: =VLOOKUP(AO37,'Location Summary'!$C$2:$J$604,2,FALSE) -> DB1+12 | AQ42: =VLOOKUP(AQ37,'Location Summary'!$C$2:$J$604,2,FALSE) -> DB1+12 | AS42: =VLOOKUP(AS37,'Location Summary'!$C$2:$J$604,2,FALSE) -> DA+3
C44: =AS36+1 -> 82 | E44: =C44+1 -> 83 | G44: =E44+1 -> 84 | I44: =G44+1 -> 85 | K44: =I44+1 -> 86 | M44: =K44+1 -> 87 | O44: =M44+1 -> 88 | Q44: =O44+1 -> 89 | S44: =Q44+1 -> 90 | U44: =S44+1 -> 91 | W44: =U44+1 -> 92 | Y44: =W44+1 -> 93 | AA44: =Y44+1 -> 94 | AC44: =AA44+1 -> 95 | AE44: =AC44+1 -> 96 | AG44: =AE44+1 -> 97 | AI44: =AG44+1 -> 98 | AK44: =AI44+1 -> 99 | AM44: =AK44+1 -> 100 | AO44: =AM44+1 -> 101 | AQ44: =AO44+1 -> 102 | AS44: =AQ44+1 -> 103
C45: 9/2 | E45: 9/3 | G45: 9/4 | I45: 9/5 | K45: 9/6 | M45: 9/7 | O45: 9/8 | Q45: 9/9 | S45: 9/10 | U45: 9/11 | W45: 10/0 | Y45: 10/1 | AA45: 10/2 | AC45: 11/0 | AE45: 12/0 | AG45: 13/0 | AI45: 13A/0 | AK45: 14/0 | AM45: 15/0 | AO45: 15/1 | AQ45: 15/2 | AS45: 15/3
AF46: 132kV | AL46: 400kV
C48: 3 | D48: =VLOOKUP(C45,'Location Summary'!$G$2:$H$604,2,FALSE) -> 395 | E48: 3 | F48: =VLOOKUP(E45,'Location Summary'!$G$2:$H$604,2,FALSE) -> 395 | G48: 3 | H48: =VLOOKUP(G45,'Location Summary'!$G$2:$H$604,2,FALSE) -> 425 | I48: 3 | J48: =VLOOKUP(I45,'Location Summary'!$G$2:$H$604,2,FALSE) -> 415 | K48: 3 | L48: =VLOOKUP(K45,'Location Summary'!$G$2:$H$604,2,FALSE) -> 405 | M48: 3 | N48: =VLOOKUP(M45,'Location Summary'!$G$2:$H$604,2,FALSE) -> 435 | O48: 3 | P48: =VLOOKUP(O45,'Location Summary'!$G$2:$H$604,2,FALSE) -> 405 | Q48: 3 | R48: =VLOOKUP(Q45,'Location Summary'!$G$2:$H$604,2,FALSE) -> 435 | S48: 3 | T48: =VLOOKUP(S45,'Location Summary'!$G$2:$H$604,2,FALSE) -> 395 | U48: 3 | V48: =VLOOKUP(U45,'Location Summary'!$G$2:$H$604,2,FALSE) -> 431.548 | W48: 3 | X48: =VLOOKUP(W45,'Location Summary'!$G$2:$H$604,2,FALSE) -> 363.452 | Y48: 3 | Z48: =VLOOKUP(Y45,'Location Summary'!$G$2:$H$604,2,FALSE) -> 295 | AA48: 3 | AB48: =VLOOKUP(AA45,'Location Summary'!$G$2:$H$604,2,FALSE) -> 345.731 | AC48: 3 | AD48: =VLOOKUP(AC45,'Location Summary'!$G$2:$H$604,2,FALSE) -> 242.89 | AE48: 3 | AF48: =VLOOKUP(AE45,'Location Summary'!$G$2:$H$604,2,FALSE) -> 329.73 | AG48: 3 | AH48: =VLOOKUP(AG45,'Location Summary'!$G$2:$H$604,2,FALSE) -> 416.88 | AI48: 3 | AJ48: =VLOOKUP(AI45,'Location Summary'!$G$2:$H$604,2,FALSE) -> 480.27 | AK48: 3 | AL48: =VLOOKUP(AK45,'Location Summary'!$G$2:$H$604,2,FALSE) -> 223.82 | AM48: 3 | AN48: =VLOOKUP(AM45,'Location Summary'!$G$2:$H$604,2,FALSE) -> 405.915 | AO48: 3 | AP48: =VLOOKUP(AO45,'Location Summary'!$G$2:$H$604,2,FALSE) -> 405 | AQ48: 3 | AR48: =VLOOKUP(AQ45,'Location Summary'!$G$2:$H$604,2,FALSE) -> 420 | AS48: 3 | AT48: =VLOOKUP(AS45,'Location Summary'!$G$2:$H$604,2,FALSE) -> 415
C49: 2 | E49: 2 | G49: 2 | I49: 2 | K49: 2 | M49: 2 | O49: 2 | Q49: 2 | S49: 2 | U49: 2 | W49: 2 | Y49: 2 | AA49: 2 | AC49: 2 | AE49: 2 | AG49: 2 | AI49: 2 | AK49: 2 | AM49: 2 | AO49: 2 | AQ49: 2 | AS49: 2
C50: =VLOOKUP(C45,'Location Summary'!$C$2:$J$604,2,FALSE) -> DA+3 | E50: =VLOOKUP(E45,'Location Summary'!$C$2:$J$604,2,FALSE) -> DA+0 | G50: =VLOOKUP(G45,'Location Summary'!$C$2:$J$604,2,FALSE) -> DA+6 | I50: =VLOOKUP(I45,'Location Summary'!$C$2:$J$604,2,FALSE) -> DA+3 | K50: =VLOOKUP(K45,'Location Summary'!$C$2:$J$604,2,FALSE) -> DA+3 | M50: =VLOOKUP(M45,'Location Summary'!$C$2:$J$604,2,FALSE) -> DA+9 | O50: =VLOOKUP(O45,'Location Summary'!$C$2:$J$604,2,FALSE) -> DA+0 | Q50: =VLOOKUP(Q45,'Location Summary'!$C$2:$J$604,2,FALSE) -> DA+0 | S50: =VLOOKUP(S45,'Location Summary'!$C$2:$J$604,2,FALSE) -> DA+3 | U50: =VLOOKUP(U45,'Location Summary'!$C$2:$J$604,2,FALSE) -> DA+3 | W50: =VLOOKUP(W45,'Location Summary'!$C$2:$J$604,2,FALSE) -> DB1+6 | Y50: =VLOOKUP(Y45,'Location Summary'!$C$2:$J$604,2,FALSE) -> DA+3 | AA50: =VLOOKUP(AA45,'Location Summary'!$C$2:$J$604,2,FALSE) -> DA+3 | AC50: =VLOOKUP(AC45,'Location Summary'!$C$2:$J$604,2,FALSE) -> DD45+0 | AE50: =VLOOKUP(AE45,'Location Summary'!$C$2:$J$604,2,FALSE) -> DB1+9 | AG50: =VLOOKUP(AG45,'Location Summary'!$C$2:$J$604,2,FALSE) -> DD60+9 | AI50: =VLOOKUP(AI45,'Location Summary'!$C$2:$J$604,2,FALSE) -> DB1+9 | AK50: =VLOOKUP(AK45,'Location Summary'!$C$2:$J$604,2,FALSE) -> DD60+18 | AM50: =VLOOKUP(AM45,'Location Summary'!$C$2:$J$604,2,FALSE) -> DD60+25 | AO50: =VLOOKUP(AO45,'Location Summary'!$C$2:$J$604,2,FALSE) -> DA+6 | AQ50: =VLOOKUP(AQ45,'Location Summary'!$C$2:$J$604,2,FALSE) -> DA+3 | AS50: =VLOOKUP(AS45,'Location Summary'!$C$2:$J$604,2,FALSE) -> DA+3
AC51: NH-62 | AJ51: RC 4 Leg
C52: =AS44+1 -> 104 | E52: =C52+1 -> 105 | G52: =E52+1 -> 106 | I52: =G52+1 -> 107 | K52: =I52+1 -> 108 | M52: =K52+1 -> 109 | O52: =M52+1 -> 110 | Q52: =O52+1 -> 111 | S52: =Q52+1 -> 112 | U52: =S52+1 -> 113 | W52: =U52+1 -> 114 | Y52: =W52+1 -> 115 | AA52: =Y52+1 -> 116 | AC52: =AA52+1 -> 117 | AE52: =AC52+1 -> 118 | AG52: =AE52+1 -> 119 | AI52: =AG52+1 -> 120 | AK52: =AI52+1 -> 121 | AM52: =AK52+1 -> 122 | AO52: =AM52+1 -> 123 | AQ52: =AO52+1 -> 124 | AS52: =AQ52+1 -> 125
C53: 15/4 | E53: 15/5 | G53: 15/6 | I53: 15/7 | K53: 15/8 | M53: 15/9 | O53: 15/10 | Q53: 15/11 | S53: 15/12 | U53: 16/0 | W53: 17/0 | Y53: 18/0 | AA53: 18/1 | AC53: 18/2 | AE53: 18/3 | AG53: 18/4 | AI53: 18/5 | AK53: 18/6 | AM53: 18/7 | AO53: 19/0 | AQ53: 20/0 | AS53: 20/1
C56: 3 | D56: =VLOOKUP(C53,'Location Summary'!$G$2:$H$604,2,FALSE) -> 410 | E56: 3 | F56: =VLOOKUP(E53,'Location Summary'!$G$2:$H$604,2,FALSE) -> 285 | G56: 3 | H56: =VLOOKUP(G53,'Location Summary'!$G$2:$H$604,2,FALSE) -> 355 | I56: 3 | J56: =VLOOKUP(I53,'Location Summary'!$G$2:$H$604,2,FALSE) -> 355 | K56: 3 | L56: =VLOOKUP(K53,'Location Summary'!$G$2:$H$604,2,FALSE) -> 410 | M56: 3 | N56: =VLOOKUP(M53,'Location Summary'!$G$2:$H$604,2,FALSE) -> 430 | O56: 3 | P56: =VLOOKUP(O53,'Location Summary'!$G$2:$H$604,2,FALSE) -> 385 | Q56: 3 | R56: =VLOOKUP(Q53,'Location Summary'!$G$2:$H$604,2,FALSE) -> 455 | S56: 3 | T56: =VLOOKUP(S53,'Location Summary'!$G$2:$H$604,2,FALSE) -> 288.425 | U56: 3 | V56: =VLOOKUP(U53,'Location Summary'!$G$2:$H$604,2,FALSE) -> 392.69 | W56: 3 | X56: =VLOOKUP(W53,'Location Summary'!$G$2:$H$604,2,FALSE) -> 398.4 | Y56: 3 | Z56: =VLOOKUP(Y53,'Location Summary'!$G$2:$H$604,2,FALSE) -> 307.595 | AA56: 3 | AB56: =VLOOKUP(AA53,'Location Summary'!$G$2:$H$604,2,FALSE) -> 390 | AC56: 3 | AD56: =VLOOKUP(AC53,'Location Summary'!$G$2:$H$604,2,FALSE) -> 380 | AE56: 3 | AF56: =VLOOKUP(AE53,'Location Summary'!$G$2:$H$604,2,FALSE) -> 405 | AG56: 3 | AH56: =VLOOKUP(AG53,'Location Summary'!$G$2:$H$604,2,FALSE) -> 335 | AI56: 3 | AJ56: =VLOOKUP(AI53,'Location Summary'!$G$2:$H$604,2,FALSE) -> 425 | AK56: 3 | AL56: =VLOOKUP(AK53,'Location Summary'!$G$2:$H$604,2,FALSE) -> 402 | AM56: 3 | AN56: =VLOOKUP(AM53,'Location Summary'!$G$2:$H$604,2,FALSE) -> 385.434 | AO56: 3 | AP56: =VLOOKUP(AO53,'Location Summary'!$G$2:$H$604,2,FALSE) -> 279.36 | AQ56: 3 | AR56: =VLOOKUP(AQ53,'Location Summary'!$G$2:$H$604,2,FALSE) -> 388.515 | AS56: 3 | AT56: =VLOOKUP(AS53,'Location Summary'!$G$2:$H$604,2,FALSE) -> 330
G57: 2 | I57: 2 | K57: 2 | M57: 2 | O57: 2 | Q57: 2 | S57: 2 | U57: 2 | W57: 2 | Y57: 2 | AA57: 2 | AC57: 2 | AE57: 2 | AG57: 2 | AI57: 2 | AK57: 2 | AM57: 2 | AO57: 2 | AQ57: 2 | AS57: 2
C58: =VLOOKUP(C53,'Location Summary'!$C$2:$J$604,2,FALSE) -> DA+6 | E58: =VLOOKUP(E53,'Location Summary'!$C$2:$J$604,2,FALSE) -> DA+3 | G58: =VLOOKUP(G53,'Location Summary'!$C$2:$J$604,2,FALSE) -> DA+9 | I58: =VLOOKUP(I53,'Location Summary'!$C$2:$J$604,2,FALSE) -> DA+0 | K58: =VLOOKUP(K53,'Location Summary'!$C$2:$J$604,2,FALSE) -> DA+1.5 | M58: =VLOOKUP(M53,'Location Summary'!$C$2:$J$604,2,FALSE) -> DA+0 | O58: =VLOOKUP(O53,'Location Summary'!$C$2:$J$604,2,FALSE) -> DA-1.5 | Q58: =VLOOKUP(Q53,'Location Summary'!$C$2:$J$604,2,FALSE) -> DA+0 | S58: =VLOOKUP(S53,'Location Summary'!$C$2:$J$604,2,FALSE) -> DA+6 | U58: =VLOOKUP(U53,'Location Summary'!$C$2:$J$604,2,FALSE) -> DC2+0 | W58: =VLOOKUP(W53,'Location Summary'!$C$2:$J$604,2,FALSE) -> DC1+3 | Y58: =VLOOKUP(Y53,'Location Summary'!$C$2:$J$604,2,FALSE) -> DB2+6 | AA58: =VLOOKUP(AA53,'Location Summary'!$C$2:$J$604,2,FALSE) -> DA+3 | AC58: =VLOOKUP(AC53,'Location Summary'!$C$2:$J$604,2,FALSE) -> DA+1.5 | AE58: =VLOOKUP(AE53,'Location Summary'!$C$2:$J$604,2,FALSE) -> DA+6 | AG58: =VLOOKUP(AG53,'Location Summary'!$C$2:$J$604,2,FALSE) -> DA-3 | AI58: =VLOOKUP(AI53,'Location Summary'!$C$2:$J$604,2,FALSE) -> DA+0 | AK58: =VLOOKUP(AK53,'Location Summary'!$C$2:$J$604,2,FALSE) -> DA+9 | AM58: =VLOOKUP(AM53,'Location Summary'!$C$2:$J$604,2,FALSE) -> DA+1.5 | AO58: =VLOOKUP(AO53,'Location Summary'!$C$2:$J$604,2,FALSE) -> DD60+3 | AQ58: =VLOOKUP(AQ53,'Location Summary'!$C$2:$J$604,2,FALSE) -> DD60+3 | AS58: =VLOOKUP(AS53,'Location Summary'!$C$2:$J$604,2,FALSE) -> DA-3
K59: Canal | AN59: RLY
C60: =AS52+1 -> 126 | E60: =C60+1 -> 127 | G60: =E60+1 -> 128 | I60: =G60+1 -> 129 | K60: =I60+1 -> 130 | M60: =K60+1 -> 131 | O60: =M60+1 -> 132 | Q60: =O60+1 -> 133 | S60: =Q60+1 -> 134 | U60: =S60+1 -> 135 | W60: =U60+1 -> 136 | Y60: =W60+1 -> 137 | AA60: =Y60+1 -> 138 | AC60: =AA60+1 -> 139 | AE60: =AC60+1 -> 140 | AG60: =AE60+1 -> 141 | AI60: =AG60+1 -> 142 | AK60: =AI60+1 -> 143 | AM60: =AK60+1 -> 144 | AO60: =AM60+1 -> 145 | AQ60: =AO60+1 -> 146 | AS60: =AQ60+1 -> 147
C61: 20/2 | E61: 20/3 | G61: 20/4 | I61: 20/5 | K61: 20/6 | M61: 21/0 | O61: 21/1 | Q61: 21/2 | S61: 21/3 | U61: 21/4 | W61: 21/5 | Y61: 22/0 | AA61: 23/0 | AC61: 23A/0 | AE61: 24/0 | AG61: 25/0 | AI61: 26/0 | AK61: 27/0 | AM61: 27/1 | AO61: 27/2 | AQ61: 27/3 | AS61: 27/4
Z62: 220kV | AF62: 400kV | AJ62: 765kV
C64: 3 | D64: =VLOOKUP(C61,'Location Summary'!$G$2:$H$604,2,FALSE) -> 340 | E64: 3 | F64: =VLOOKUP(E61,'Location Summary'!$G$2:$H$604,2,FALSE) -> 420 | G64: 3 | H64: =VLOOKUP(G61,'Location Summary'!$G$2:$H$604,2,FALSE) -> 396 | I64: 3 | J64: =VLOOKUP(I61,'Location Summary'!$G$2:$H$604,2,FALSE) -> 355 | K64: 3 | L64: =VLOOKUP(K61,'Location Summary'!$G$2:$H$604,2,FALSE) -> 320.652 | M64: 3 | N64: =VLOOKUP(M61,'Location Summary'!$G$2:$H$604,2,FALSE) -> 326.348 | O64: 3 | P64: =VLOOKUP(O61,'Location Summary'!$G$2:$H$604,2,FALSE) -> 427 | Q64: 3 | R64: =VLOOKUP(Q61,'Location Summary'!$G$2:$H$604,2,FALSE) -> 410 | S64: 3 | T64: =VLOOKUP(S61,'Location Summary'!$G$2:$H$604,2,FALSE) -> 405 | U64: 3 | V64: =VLOOKUP(U61,'Location Summary'!$G$2:$H$604,2,FALSE) -> 300 | W64: 3 | X64: =VLOOKUP(W61,'Location Summary'!$G$2:$H$604,2,FALSE) -> 415.187 | Y64: 3 | Z64: =VLOOKUP(Y61,'Location Summary'!$G$2:$H$604,2,FALSE) -> 259.05 | AA64: 3 | AB64: =VLOOKUP(AA61,'Location Summary'!$G$2:$H$604,2,FALSE) -> 440.46 | AC64: 3 | AD64: =VLOOKUP(AC61,'Location Summary'!$G$2:$H$604,2,FALSE) -> 496.69 | AE64: 3 | AF64: =VLOOKUP(AE61,'Location Summary'!$G$2:$H$604,2,FALSE) -> 244.03 | AG64: 3 | AH64: =VLOOKUP(AG61,'Location Summary'!$G$2:$H$604,2,FALSE) -> 237.43 | AI64: 3 | AJ64: =VLOOKUP(AI61,'Location Summary'!$G$2:$H$604,2,FALSE) -> 203.48 | AK64: 3 | AL64: =VLOOKUP(AK61,'Location Summary'!$G$2:$H$604,2,FALSE) -> 453.688 | AM64: 3 | AN64: =VLOOKUP(AM61,'Location Summary'!$G$2:$H$604,2,FALSE) -> 345 | AO64: 3 | AP64: =VLOOKUP(AO61,'Location Summary'!$G$2:$H$604,2,FALSE) -> 360 | AQ64: 3 | AR64: =VLOOKUP(AQ61,'Location Summary'!$G$2:$H$604,2,FALSE) -> 410 | AS64: 3 | AT64: =VLOOKUP(AS61,'Location Summary'!$G$2:$H$604,2,FALSE) -> 350
C65: 2 | E65: 2 | G65: 2 | I65: 2 | K65: 2 | M65: 2 | O65: 2 | Q65: 2 | S65: 2 | U65: 2 | W65: 2 | Y65: 2 | AA65: 2 | AC65: 2 | AE65: 2 | AG65: 2 | AI65: 2 | AK65: 2 | AM65: 2 | AO65: 2 | AQ65: 2 | AS65: 2
C66: =VLOOKUP(C61,'Location Summary'!$C$2:$J$604,2,FALSE) -> DA-3 | E66: =VLOOKUP(E61,'Location Summary'!$C$2:$J$604,2,FALSE) -> DA+1.5 | G66: =VLOOKUP(G61,'Location Summary'!$C$2:$J$604,2,FALSE) -> DA+3 | I66: =VLOOKUP(I61,'Location Summary'!$C$2:$J$604,2,FALSE) -> DA+0 | K66: =VLOOKUP(K61,'Location Summary'!$C$2:$J$604,2,FALSE) -> DA-3 | M66: =VLOOKUP(M61,'Location Summary'!$C$2:$J$604,2,FALSE) -> DB1+0 | O66: =VLOOKUP(O61,'Location Summary'!$C$2:$J$604,2,FALSE) -> DA+0 | Q66: =VLOOKUP(Q61,'Location Summary'!$C$2:$J$604,2,FALSE) -> DA+6 | S66: =VLOOKUP(S61,'Location Summary'!$C$2:$J$604,2,FALSE) -> DA+6 | U66: =VLOOKUP(U61,'Location Summary'!$C$2:$J$604,2,FALSE) -> DA+0 | W66: =VLOOKUP(W61,'Location Summary'!$C$2:$J$604,2,FALSE) -> DA+0 | Y66: =VLOOKUP(Y61,'Location Summary'!$C$2:$J$604,2,FALSE) -> DC2+15 | AA66: =VLOOKUP(AA61,'Location Summary'!$C$2:$J$604,2,FALSE) -> DB2+9 | AC66: =VLOOKUP(AC61,'Location Summary'!$C$2:$J$604,2,FALSE) -> DB1+9 | AE66: =VLOOKUP(AE61,'Location Summary'!$C$2:$J$604,2,FALSE) -> DD60+18 | AG66: =VLOOKUP(AG61,'Location Summary'!$C$2:$J$604,2,FALSE) -> DD60+18 | AI66: =VLOOKUP(AI61,'Location Summary'!$C$2:$J$604,2,FALSE) -> DD60+35 | AK66: =VLOOKUP(AK61,'Location Summary'!$C$2:$J$604,2,FALSE) -> DD60+35 | AM66: =VLOOKUP(AM61,'Location Summary'!$C$2:$J$604,2,FALSE) -> DA+9 | AO66: =VLOOKUP(AO61,'Location Summary'!$C$2:$J$604,2,FALSE) -> DA-1.5 | AQ66: =VLOOKUP(AQ61,'Location Summary'!$C$2:$J$604,2,FALSE) -> DA+1.5 | AS66: =VLOOKUP(AS61,'Location Summary'!$C$2:$J$604,2,FALSE) -> DA+1.5
C68: =AS60+1 -> 148 | E68: =C68+1 -> 149 | G68: =E68+1 -> 150 | I68: =G68+1 -> 151 | K68: =I68+1 -> 152 | M68: =K68+1 -> 153 | O68: =M68+1 -> 154 | Q68: =O68+1 -> 155 | S68: =Q68+1 -> 156 | U68: =S68+1 -> 157 | W68: =U68+1 -> 158 | Y68: =W68+1 -> 159 | AA68: =Y68+1 -> 160 | AC68: =AA68+1 -> 161 | AE68: =AC68+1 -> 162 | AG68: =AE68+1 -> 163 | AI68: =AG68+1 -> 164 | AK68: =AI68+1 -> 165 | AM68: =AK68+1 -> 166 | AO68: =AM68+1 -> 167 | AQ68: =AO68+1 -> 168 | AS68: =AQ68+1 -> 169
C69: 27/5 | E69: 27/6 | G69: 28/0 | I69: 29/0 | K69: 29/1 | M69: 29/2 | O69: 29/3 | Q69: 29/4 | S69: 29/5 | U69: 29A/0 | W69: 29A/1 | Y69: 29A/2 | AA69: 29A/3 | AC69: 29A/4 | AE69: 29A/5 | AG69: 29A/6 | AI69: 30/0 | AK69: 30/1 | AM69: 30/2 | AO69: 30/3 | AQ69: 30/4 | AS69: 30/5
C72: 3 | D72: =VLOOKUP(C69,'Location Summary'!$G$2:$H$604,2,FALSE) -> 355 | E72: 3 | F72: =VLOOKUP(E69,'Location Summary'!$G$2:$H$604,2,FALSE) -> 274.587 | G72: 3 | H72: =VLOOKUP(G69,'Location Summary'!$G$2:$H$604,2,FALSE) -> 211.21 | I72: 3 | J72: =VLOOKUP(I69,'Location Summary'!$G$2:$H$604,2,FALSE) -> 384.204 | K72: 3 | L72: =VLOOKUP(K69,'Location Summary'!$G$2:$H$604,2,FALSE) -> 430 | M72: 3 | N72: =VLOOKUP(M69,'Location Summary'!$G$2:$H$604,2,FALSE) -> 370 | O72: 3 | P72: =VLOOKUP(O69,'Location Summary'!$G$2:$H$604,2,FALSE) -> 390 | Q72: 3 | R72: =VLOOKUP(Q69,'Location Summary'!$G$2:$H$604,2,FALSE) -> 435 | S72: 3 | T72: =VLOOKUP(S69,'Location Summary'!$G$2:$H$604,2,FALSE) -> 370 | U72: 3 | V72: =VLOOKUP(U69,'Location Summary'!$G$2:$H$604,2,FALSE) -> 455 | W72: 3 | X72: =VLOOKUP(W69,'Location Summary'!$G$2:$H$604,2,FALSE) -> 325 | Y72: 3 | Z72: =VLOOKUP(Y69,'Location Summary'!$G$2:$H$604,2,FALSE) -> 395 | AA72: 3 | AB72: =VLOOKUP(AA69,'Location Summary'!$G$2:$H$604,2,FALSE) -> 345 | AC72: 3 | AD72: =VLOOKUP(AC69,'Location Summary'!$G$2:$H$604,2,FALSE) -> 345 | AE72: 3 | AF72: =VLOOKUP(AE69,'Location Summary'!$G$2:$H$604,2,FALSE) -> 440 | AG72: 3 | AH72: =VLOOKUP(AG69,'Location Summary'!$G$2:$H$604,2,FALSE) -> 364.008 | AI72: 3 | AJ72: =VLOOKUP(AI69,'Location Summary'!$G$2:$H$604,2,FALSE) -> 295.993 | AK72: 3 | AL72: =VLOOKUP(AK69,'Location Summary'!$G$2:$H$604,2,FALSE) -> 425 | AM72: 3 | AN72: =VLOOKUP(AM69,'Location Summary'!$G$2:$H$604,2,FALSE) -> 315 | AO72: 3 | AP72: =VLOOKUP(AO69,'Location Summary'!$G$2:$H$604,2,FALSE) -> 380 | AQ72: 3 | AR72: =VLOOKUP(AQ69,'Location Summary'!$G$2:$H$604,2,FALSE) -> 430 | AS72: 3 | AT72: =VLOOKUP(AS69,'Location Summary'!$G$2:$H$604,2,FALSE) -> 380
C73: 2 | E73: 2 | G73: 2 | I73: 2 | K73: 2 | M73: 2 | O73: 2 | Q73: 2 | S73: 2 | U73: 2 | W73: 2 | Y73: 2 | AA73: 2 | AC73: 2 | AE73: 2 | AG73: 2 | AI73: 2 | AK73: 2 | AM73: 2 | AO73: 2 | AQ73: 2 | AS73: 2
C74: =VLOOKUP(C69,'Location Summary'!$C$2:$J$604,2,FALSE) -> DA-1.5 | E74: =VLOOKUP(E69,'Location Summary'!$C$2:$J$604,2,FALSE) -> DA-3 | G74: =VLOOKUP(G69,'Location Summary'!$C$2:$J$604,2,FALSE) -> DC2-3 | I74: =VLOOKUP(I69,'Location Summary'!$C$2:$J$604,2,FALSE) -> DC1+0 | K74: =VLOOKUP(K69,'Location Summary'!$C$2:$J$604,2,FALSE) -> DA+6 | M74: =VLOOKUP(M69,'Location Summary'!$C$2:$J$604,2,FALSE) -> DA+0 | O74: =VLOOKUP(O69,'Location Summary'!$C$2:$J$604,2,FALSE) -> DA+0 | Q74: =VLOOKUP(Q69,'Location Summary'!$C$2:$J$604,2,FALSE) -> DA+3 | S74: =VLOOKUP(S69,'Location Summary'!$C$2:$J$604,2,FALSE) -> DA+0 | U74: =VLOOKUP(U69,'Location Summary'!$C$2:$J$604,2,FALSE) -> DB1+0 | W74: =VLOOKUP(W69,'Location Summary'!$C$2:$J$604,2,FALSE) -> DA+6 | Y74: =VLOOKUP(Y69,'Location Summary'!$C$2:$J$604,2,FALSE) -> DA+6 | AA74: =VLOOKUP(AA69,'Location Summary'!$C$2:$J$604,2,FALSE) -> DA+6 | AC74: =VLOOKUP(AC69,'Location Summary'!$C$2:$J$604,2,FALSE) -> DA+3 | AE74: =VLOOKUP(AE69,'Location Summary'!$C$2:$J$604,2,FALSE) -> DA+6 | AG74: =VLOOKUP(AG69,'Location Summary'!$C$2:$J$604,2,FALSE) -> DA+9 | AI74: =VLOOKUP(AI69,'Location Summary'!$C$2:$J$604,2,FALSE) -> DB1+0 | AK74: =VLOOKUP(AK69,'Location Summary'!$C$2:$J$604,2,FALSE) -> DA+0 | AM74: =VLOOKUP(AM69,'Location Summary'!$C$2:$J$604,2,FALSE) -> DA+9 | AO74: =VLOOKUP(AO69,'Location Summary'!$C$2:$J$604,2,FALSE) -> DA+3 | AQ74: =VLOOKUP(AQ69,'Location Summary'!$C$2:$J$604,2,FALSE) -> DA+9 | AS74: =VLOOKUP(AS69,'Location Summary'!$C$2:$J$604,2,FALSE) -> DA+0
G75: Exp. Way
C76: =AS68+1 -> 170 | E76: =C76+1 -> 171 | G76: =E76+1 -> 172 | I76: =G76+1 -> 173 | K76: =I76+1 -> 174 | M76: =K76+1 -> 175 | O76: =M76+1 -> 176 | Q76: =O76+1 -> 177 | S76: =Q76+1 -> 178 | U76: =S76+1 -> 179 | W76: =U76+1 -> 180 | Y76: =W76+1 -> 181 | AA76: =Y76+1 -> 182 | AC76: =AA76+1 -> 183 | AE76: =AC76+1 -> 184 | AG76: =AE76+1 -> 185 | AI76: =AG76+1 -> 186 | AK76: =AI76+1 -> 187 | AM76: =AK76+1 -> 188 | AO76: =AM76+1 -> 189 | AQ76: =AO76+1 -> 190 | AS76: =AQ76+1 -> 191
C77: 30/6 | E77: 30/7 | G77: 30/8 | I77: 30/9 | K77: 30/10 | M77: 31/0 | O77: 31/1 | Q77: 31/2 | S77: 31/3 | U77: 31/4 | W77: 31/5 | Y77: 31/6 | AA77: 31/7 | AC77: 31/8 | AE77: 31/9 | AG77: 31/10 | AI77: 32/0 | AK77: 32/1 | AM77: 32/2 | AO77: 32/3 | AQ77: 32/4 | AS77: 32/5
C80: 3 | D80: =VLOOKUP(C77,'Location Summary'!$G$2:$H$604,2,FALSE) -> 335 | E80: 3 | F80: =VLOOKUP(E77,'Location Summary'!$G$2:$H$604,2,FALSE) -> 395 | G80: 3 | H80: =VLOOKUP(G77,'Location Summary'!$G$2:$H$604,2,FALSE) -> 390 | I80: 3 | J80: =VLOOKUP(I77,'Location Summary'!$G$2:$H$604,2,FALSE) -> 350 | K80: 3 | L80: =VLOOKUP(K77,'Location Summary'!$G$2:$H$604,2,FALSE) -> 428.239 | M80: 3 | N80: =VLOOKUP(M77,'Location Summary'!$G$2:$H$604,2,FALSE) -> 376.761 | O80: 3 | P80: =VLOOKUP(O77,'Location Summary'!$G$2:$H$604,2,FALSE) -> 410 | Q80: 3 | R80: =VLOOKUP(Q77,'Location Summary'!$G$2:$H$604,2,FALSE) -> 430 | S80: 3 | T80: =VLOOKUP(S77,'Location Summary'!$G$2:$H$604,2,FALSE) -> 380 | U80: 3 | V80: =VLOOKUP(U77,'Location Summary'!$G$2:$H$604,2,FALSE) -> 445 | W80: 3 | X80: =VLOOKUP(W77,'Location Summary'!$G$2:$H$604,2,FALSE) -> 385 | Y80: 3 | Z80: =VLOOKUP(Y77,'Location Summary'!$G$2:$H$604,2,FALSE) -> 420 | AA80: 3 | AB80: =VLOOKUP(AA77,'Location Summary'!$G$2:$H$604,2,FALSE) -> 415 | AC80: 3 | AD80: =VLOOKUP(AC77,'Location Summary'!$G$2:$H$604,2,FALSE) -> 310 | AE80: 3 | AF80: =VLOOKUP(AE77,'Location Summary'!$G$2:$H$604,2,FALSE) -> 445 | AG80: 3 | AH80: =VLOOKUP(AG77,'Location Summary'!$G$2:$H$604,2,FALSE) -> 316.608 | AI80: 3 | AJ80: =VLOOKUP(AI77,'Location Summary'!$G$2:$H$604,2,FALSE) -> 385.51 | AK80: 3 | AL80: =VLOOKUP(AK77,'Location Summary'!$G$2:$H$604,2,FALSE) -> 410 | AM80: 3 | AN80: =VLOOKUP(AM77,'Location Summary'!$G$2:$H$604,2,FALSE) -> 390 | AO80: 3 | AP80: =VLOOKUP(AO77,'Location Summary'!$G$2:$H$604,2,FALSE) -> 450 | AQ80: 3 | AR80: =VLOOKUP(AQ77,'Location Summary'!$G$2:$H$604,2,FALSE) -> 370 | AS80: 3 | AT80: =VLOOKUP(AS77,'Location Summary'!$G$2:$H$604,2,FALSE) -> 439
C81: 2 | E81: 2 | G81: 2 | I81: 2 | K81: 2 | M81: 2 | O81: 2 | Q81: 2 | S81: 2 | U81: 2 | W81: 2 | Y81: 2 | AA81: 2 | AC81: 2 | AE81: 2 | AG81: 2 | AI81: 2 | AK81: 2 | AM81: 2 | AO81: 2 | AQ81: 2 | AS81: 2
C82: =VLOOKUP(C77,'Location Summary'!$C$2:$J$604,2,FALSE) -> DA+6 | E82: =VLOOKUP(E77,'Location Summary'!$C$2:$J$604,2,FALSE) -> DA-3 | G82: =VLOOKUP(G77,'Location Summary'!$C$2:$J$604,2,FALSE) -> DA+3 | I82: =VLOOKUP(I77,'Location Summary'!$C$2:$J$604,2,FALSE) -> DA-3 | K82: =VLOOKUP(K77,'Location Summary'!$C$2:$J$604,2,FALSE) -> DA+3 | M82: =VLOOKUP(M77,'Location Summary'!$C$2:$J$604,2,FALSE) -> DB1+0 | O82: =VLOOKUP(O77,'Location Summary'!$C$2:$J$604,2,FALSE) -> DA+3 | Q82: =VLOOKUP(Q77,'Location Summary'!$C$2:$J$604,2,FALSE) -> DA+1.5 | S82: =VLOOKUP(S77,'Location Summary'!$C$2:$J$604,2,FALSE) -> DA+3 | U82: =VLOOKUP(U77,'Location Summary'!$C$2:$J$604,2,FALSE) -> DA-1.5 | W82: =VLOOKUP(W77,'Location Summary'!$C$2:$J$604,2,FALSE) -> DA+6 | Y82: =VLOOKUP(Y77,'Location Summary'!$C$2:$J$604,2,FALSE) -> DA+9 | AA82: =VLOOKUP(AA77,'Location Summary'!$C$2:$J$604,2,FALSE) -> DA+0 | AC82: =VLOOKUP(AC77,'Location Summary'!$C$2:$J$604,2,FALSE) -> DA+0 | AE82: =VLOOKUP(AE77,'Location Summary'!$C$2:$J$604,2,FALSE) -> DA+1.5 | AG82: =VLOOKUP(AG77,'Location Summary'!$C$2:$J$604,2,FALSE) -> DA+4.5 | AI82: =VLOOKUP(AI77,'Location Summary'!$C$2:$J$604,2,FALSE) -> DB2+0 | AK82: =VLOOKUP(AK77,'Location Summary'!$C$2:$J$604,2,FALSE) -> DA+6 | AM82: =VLOOKUP(AM77,'Location Summary'!$C$2:$J$604,2,FALSE) -> DA+9 | AO82: =VLOOKUP(AO77,'Location Summary'!$C$2:$J$604,2,FALSE) -> DA+6 | AQ82: =VLOOKUP(AQ77,'Location Summary'!$C$2:$J$604,2,FALSE) -> DA+9 | AS82: =VLOOKUP(AS77,'Location Summary'!$C$2:$J$604,2,FALSE) -> DA+9
AS83: RC 4 Leg
C84: =AS76+1 -> 192 | E84: =C84+1 -> 193 | G84: =E84+1 -> 194 | I84: =G84+1 -> 195 | K84: =I84+1 -> 196 | M84: =K84+1 -> 197 | O84: =M84+1 -> 198 | Q84: =O84+1 -> 199 | S84: =Q84+1 -> 200 | U84: =S84+1 -> 201 | W84: =U84+1 -> 202 | Y84: =W84+1 -> 203 | AA84: =Y84+1 -> 204 | AC84: =AA84+1 -> 205 | AE84: =AC84+1 -> 206 | AG84: =AE84+1 -> 207 | AI84: =AG84+1 -> 208 | AK84: =AI84+1 -> 209 | AM84: =AK84+1 -> 210 | AO84: =AM84+1 -> 211 | AQ84: =AO84+1 -> 212 | AS84: =AQ84+1 -> 213
C85: 32/6 | E85: 32/7 | G85: 32A/0 | I85: 32A/1 | K85: 33/0 | M85: 33/1 | O85: 33/2 | Q85: 33/3 | S85: 33/4 | U85: 33/5 | W85: 33/6 | Y85: 33/7 | AA85: 33/8 | AC85: 33/9 | AE85: 34/0 | AG85: 34/1 | AI85: 34/2 | AK85: 34/3 | AM85: 34/4 | AO85: 34/5 | AQ85: 34/6 | AS85: 34/7
C88: 3 | D88: =VLOOKUP(C85,'Location Summary'!$G$2:$H$604,2,FALSE) -> 360 | E88: 3 | F88: =VLOOKUP(E85,'Location Summary'!$G$2:$H$604,2,FALSE) -> 479 | G88: 3 | H88: =VLOOKUP(G85,'Location Summary'!$G$2:$H$604,2,FALSE) -> 402 | I88: 3 | J88: =VLOOKUP(I85,'Location Summary'!$G$2:$H$604,2,FALSE) -> 438.439 | K88: 3 | L88: =VLOOKUP(K85,'Location Summary'!$G$2:$H$604,2,FALSE) -> 430.56 | M88: 3 | N88: =VLOOKUP(M85,'Location Summary'!$G$2:$H$604,2,FALSE) -> 406 | O88: 3 | P88: =VLOOKUP(O85,'Location Summary'!$G$2:$H$604,2,FALSE) -> 435 | Q88: 3 | R88: =VLOOKUP(Q85,'Location Summary'!$G$2:$H$604,2,FALSE) -> 405 | S88: 3 | T88: =VLOOKUP(S85,'Location Summary'!$G$2:$H$604,2,FALSE) -> 420 | U88: 3 | V88: =VLOOKUP(U85,'Location Summary'!$G$2:$H$604,2,FALSE) -> 405 | W88: 3 | X88: =VLOOKUP(W85,'Location Summary'!$G$2:$H$604,2,FALSE) -> 415 | Y88: 3 | Z88: =VLOOKUP(Y85,'Location Summary'!$G$2:$H$604,2,FALSE) -> 355 | AA88: 3 | AB88: =VLOOKUP(AA85,'Location Summary'!$G$2:$H$604,2,FALSE) -> 380 | AC88: 3 | AD88: =VLOOKUP(AC85,'Location Summary'!$G$2:$H$604,2,FALSE) -> 398.203 | AE88: 3 | AF88: =VLOOKUP(AE85,'Location Summary'!$G$2:$H$604,2,FALSE) -> 441.798 | AG88: 3 | AH88: =VLOOKUP(AG85,'Location Summary'!$G$2:$H$604,2,FALSE) -> 395 | AI88: 3 | AJ88: =VLOOKUP(AI85,'Location Summary'!$G$2:$H$604,2,FALSE) -> 375 | AK88: 3 | AL88: =VLOOKUP(AK85,'Location Summary'!$G$2:$H$604,2,FALSE) -> 445 | AM88: 3 | AN88: =VLOOKUP(AM85,'Location Summary'!$G$2:$H$604,2,FALSE) -> 395 | AO88: 3 | AP88: =VLOOKUP(AO85,'Location Summary'!$G$2:$H$604,2,FALSE) -> 435 | AQ88: 3 | AR88: =VLOOKUP(AQ85,'Location Summary'!$G$2:$H$604,2,FALSE) -> 330 | AS88: 3 | AT88: =VLOOKUP(AS85,'Location Summary'!$G$2:$H$604,2,FALSE) -> 330
C89: 2 | E89: 2 | G89: 2 | I89: 2 | K89: 2 | M89: 2 | O89: 2 | Q89: 2 | S89: 2 | U89: 2 | W89: 2 | Y89: 2 | AA89: 2 | AC89: 2 | AE89: 2 | AG89: 2 | AI89: 2 | AK89: 2 | AM89: 2 | AO89: 2 | AQ89: 2 | AS89: 2
C90: =VLOOKUP(C85,'Location Summary'!$C$2:$J$604,2,FALSE) -> DA+9 | E90: =VLOOKUP(E85,'Location Summary'!$C$2:$J$604,2,FALSE) -> DA+3 | G90: =VLOOKUP(G85,'Location Summary'!$C$2:$J$604,2,FALSE) -> DB1+9 | I90: =VLOOKUP(I85,'Location Summary'!$C$2:$J$604,2,FALSE) -> DA+6 | K90: =VLOOKUP(K85,'Location Summary'!$C$2:$J$604,2,FALSE) -> DB1+9 | M90: =VLOOKUP(M85,'Location Summary'!$C$2:$J$604,2,FALSE) -> DA+9 | O90: =VLOOKUP(O85,'Location Summary'!$C$2:$J$604,2,FALSE) -> DA+9 | Q90: =VLOOKUP(Q85,'Location Summary'!$C$2:$J$604,2,FALSE) -> DA+3 | S90: =VLOOKUP(S85,'Location Summary'!$C$2:$J$604,2,FALSE) -> DA+3 | U90: =VLOOKUP(U85,'Location Summary'!$C$2:$J$604,2,FALSE) -> DA+0 | W90: =VLOOKUP(W85,'Location Summary'!$C$2:$J$604,2,FALSE) -> DA+6 | Y90: =VLOOKUP(Y85,'Location Summary'!$C$2:$J$604,2,FALSE) -> DA+6 | AA90: =VLOOKUP(AA85,'Location Summary'!$C$2:$J$604,2,FALSE) -> DA+3 | AC90: =VLOOKUP(AC85,'Location Summary'!$C$2:$J$604,2,FALSE) -> DA+1.5 | AE90: =VLOOKUP(AE85,'Location Summary'!$C$2:$J$604,2,FALSE) -> DB1+6 | AG90: =VLOOKUP(AG85,'Location Summary'!$C$2:$J$604,2,FALSE) -> DA+9 | AI90: =VLOOKUP(AI85,'Location Summary'!$C$2:$J$604,2,FALSE) -> DA+9 | AK90: =VLOOKUP(AK85,'Location Summary'!$C$2:$J$604,2,FALSE) -> DA+1.5 | AM90: =VLOOKUP(AM85,'Location Summary'!$C$2:$J$604,2,FALSE) -> DA+6 | AO90: =VLOOKUP(AO85,'Location Summary'!$C$2:$J$604,2,FALSE) -> DA+9 | AQ90: =VLOOKUP(AQ85,'Location Summary'!$C$2:$J$604,2,FALSE) -> DA+3 | AS90: =VLOOKUP(AS85,'Location Summary'!$C$2:$J$604,2,FALSE) -> DA+0
C91: RC 4 Leg | K91: RC 4 Leg | M91: RC 4 Leg
C92: =AS84+1 -> 214 | D92: 5 | E92: =C92+1 -> 215 | G92: =E92+1 -> 216 | I92: =G92+1 -> 217 | K92: =I92+1 -> 218 | M92: =K92+1 -> 219 | O92: =M92+1 -> 220 | Q92: =O92+1 -> 221 | S92: =Q92+1 -> 222 | U92: =S92+1 -> 223 | W92: =U92+1 -> 224 | Y92: =W92+1 -> 225 | AA92: =Y92+1 -> 226 | AC92: =AA92+1 -> 227 | AE92: =AC92+1 -> 228 | AG92: =AE92+1 -> 229 | AI92: =AG92+1 -> 230 | AK92: =AI92+1 -> 231 | AM92: =AK92+1 -> 232 | AO92: =AM92+1 -> 233 | AQ92: =AO92+1 -> 234 | AS92: =AQ92+1 -> 235
C93: 34/8 | E93: 34/9 | G93: 34/10 | I93: 34/11 | K93: 34/12 | M93: 35/0 | O93: 35/1 | Q93: 35/2 | S93: 35/3 | U93: 35/4 | W93: 35/5 | Y93: 35/6 | AA93: 35/7 | AC93: 35/8 | AE93: 35/9 | AG93: 35/10 | AI93: 35/11 | AK93: 36/0 | AM93: 36A/0 | AO93: 36A/1 | AQ93: 36B/0 | AS93: N37/0
C96: 3 | D96: =VLOOKUP(C93,'Location Summary'!$G$2:$H$604,2,FALSE) -> 400 | E96: 3 | F96: =VLOOKUP(E93,'Location Summary'!$G$2:$H$604,2,FALSE) -> 310 | G96: 3 | H96: =VLOOKUP(G93,'Location Summary'!$G$2:$H$604,2,FALSE) -> 325 | I96: 3 | J96: =VLOOKUP(I93,'Location Summary'!$G$2:$H$604,2,FALSE) -> 365 | K96: 3 | L96: =VLOOKUP(K93,'Location Summary'!$G$2:$H$604,2,FALSE) -> 351.79 | M96: 3 | N96: =VLOOKUP(M93,'Location Summary'!$G$2:$H$604,2,FALSE) -> 393.209 | O96: 3 | P96: =VLOOKUP(O93,'Location Summary'!$G$2:$H$604,2,FALSE) -> 435 | Q96: 3 | R96: =VLOOKUP(Q93,'Location Summary'!$G$2:$H$604,2,FALSE) -> 405 | S96: 3 | T96: =VLOOKUP(S93,'Location Summary'!$G$2:$H$604,2,FALSE) -> 405 | U96: 3 | V96: =VLOOKUP(U93,'Location Summary'!$G$2:$H$604,2,FALSE) -> 435 | W96: 3 | X96: =VLOOKUP(W93,'Location Summary'!$G$2:$H$604,2,FALSE) -> 345 | Y96: 3 | Z96: =VLOOKUP(Y93,'Location Summary'!$G$2:$H$604,2,FALSE) -> 395 | AA96: 3 | AB96: =VLOOKUP(AA93,'Location Summary'!$G$2:$H$604,2,FALSE) -> 440 | AC96: 3 | AD96: =VLOOKUP(AC93,'Location Summary'!$G$2:$H$604,2,FALSE) -> 400 | AE96: 3 | AF96: =VLOOKUP(AE93,'Location Summary'!$G$2:$H$604,2,FALSE) -> 440 | AG96: 3 | AH96: =VLOOKUP(AG93,'Location Summary'!$G$2:$H$604,2,FALSE) -> 330 | AI96: 3 | AJ96: =VLOOKUP(AI93,'Location Summary'!$G$2:$H$604,2,FALSE) -> 493.084 | AK96: 3 | AL96: =VLOOKUP(AK93,'Location Summary'!$G$2:$H$604,2,FALSE) -> 454 | AM96: 3 | AN96: =VLOOKUP(AM93,'Location Summary'!$G$2:$H$604,2,FALSE) -> 451 | AO96: 3 | AP96: =VLOOKUP(AO93,'Location Summary'!$G$2:$H$604,2,FALSE) -> 375.7 | AQ96: 3 | AR96: =VLOOKUP(AQ93,'Location Summary'!$G$2:$H$604,2,FALSE) -> 420.81 | AS96: 3 | AT96: =VLOOKUP(AS93,'Location Summary'!$G$2:$H$604,2,FALSE) -> 469.33
C97: 2 | E97: 2 | G97: 2 | I97: 2 | K97: 2 | M97: 2 | O97: 2 | Q97: 2 | S97: 2 | U97: 2 | W97: 2 | Y97: 2 | AA97: 2 | AC97: 2 | AE97: 2 | AG97: 2 | AI97: 2 | AK97: 2 | AM97: 2 | AO97: 2 | AQ97: 2 | AS97: 2
C98: =VLOOKUP(C93,'Location Summary'!$C$2:$J$604,2,FALSE) -> DA+0 | E98: =VLOOKUP(E93,'Location Summary'!$C$2:$J$604,2,FALSE) -> DA+1.5 | G98: =VLOOKUP(G93,'Location Summary'!$C$2:$J$604,2,FALSE) -> DA-3 | I98: =VLOOKUP(I93,'Location Summary'!$C$2:$J$604,2,FALSE) -> DA+1.5 | K98: =VLOOKUP(K93,'Location Summary'!$C$2:$J$604,2,FALSE) -> DA+3 | M98: =VLOOKUP(M93,'Location Summary'!$C$2:$J$604,2,FALSE) -> DB2+0 | O98: =VLOOKUP(O93,'Location Summary'!$C$2:$J$604,2,FALSE) -> DA+6 | Q98: =VLOOKUP(Q93,'Location Summary'!$C$2:$J$604,2,FALSE) -> DA+6 | S98: =VLOOKUP(S93,'Location Summary'!$C$2:$J$604,2,FALSE) -> DA-3 | U98: =VLOOKUP(U93,'Location Summary'!$C$2:$J$604,2,FALSE) -> DA+9 | W98: =VLOOKUP(W93,'Location Summary'!$C$2:$J$604,2,FALSE) -> DA+9 | Y98: =VLOOKUP(Y93,'Location Summary'!$C$2:$J$604,2,FALSE) -> DA+6 | AA98: =VLOOKUP(AA93,'Location Summary'!$C$2:$J$604,2,FALSE) -> DA+3 | AC98: =VLOOKUP(AC93,'Location Summary'!$C$2:$J$604,2,FALSE) -> DA+6 | AE98: =VLOOKUP(AE93,'Location Summary'!$C$2:$J$604,2,FALSE) -> DA+1.5 | AG98: =VLOOKUP(AG93,'Location Summary'!$C$2:$J$604,2,FALSE) -> DA+3 | AI98: =VLOOKUP(AI93,'Location Summary'!$C$2:$J$604,2,FALSE) -> DA+3 | AK98: =VLOOKUP(AK93,'Location Summary'!$C$2:$J$604,2,FALSE) -> DB2+3 | AM98: =VLOOKUP(AM93,'Location Summary'!$C$2:$J$604,2,FALSE) -> DB1+9 | AO98: =VLOOKUP(AO93,'Location Summary'!$C$2:$J$604,2,FALSE) -> DA+3 | AQ98: =VLOOKUP(AQ93,'Location Summary'!$C$2:$J$604,2,FALSE) -> DB2+9 | AS98: =VLOOKUP(AS93,'Location Summary'!$C$2:$J$604,2,FALSE) -> DC2+15
AQ99: HMPL OIL PIPE LINE
C100: =AS92+1 -> 236 | E100: =C100+1 -> 237 | G100: =E100+1 -> 238 | I100: =G100+1 -> 239 | K100: =I100+1 -> 240 | M100: =K100+1 -> 241 | O100: =M100+1 -> 242 | Q100: =O100+1 -> 243 | S100: =Q100+1 -> 244 | U100: =S100+1 -> 245 | W100: =U100+1 -> 246 | Y100: =W100+1 -> 247 | AA100: =Y100+1 -> 248 | AC100: =AA100+1 -> 249 | AE100: =AC100+1 -> 250 | AG100: =AE100+1 -> 251 | AI100: =AG100+1 -> 252 | AK100: =AI100+1 -> 253 | AM100: =AK100+1 -> 254 | AO100: =AM100+1 -> 255 | AQ100: =AO100+1 -> 256 | AS100: =AQ100+1 -> 257
C101: N37A/0 | E101: 37/2 | G101: 37/3 | I101: 37/4 | K101: 37/5 | M101: 37A/0 | O101: 37A/1 | Q101: 37A/2 | S101: 37A/3 | U101: 37A/4 | W101: 37A/5 | Y101: 37A/6 | AA101: 38/0 | AC101: 38/1 | AE101: 38/2 | AG101: 38/3 | AI101: 38/4 | AK101: 38/5 | AM101: 38/6 | AO101: 38/7 | AQ101: 38/8 | AS101: 38/9
C104: 3 | D104: =VLOOKUP(C101,'Location Summary'!$G$2:$H$604,2,FALSE) -> 411.28 | E104: 3 | F104: =VLOOKUP(E101,'Location Summary'!$G$2:$H$604,2,FALSE) -> 405 | G104: 3 | H104: =VLOOKUP(G101,'Location Summary'!$G$2:$H$604,2,FALSE) -> 430 | I104: 3 | J104: =VLOOKUP(I101,'Location Summary'!$G$2:$H$604,2,FALSE) -> 410 | K104: 3 | L104: =VLOOKUP(K101,'Location Summary'!$G$2:$H$604,2,FALSE) -> 420 | M104: 3 | N104: =VLOOKUP(M101,'Location Summary'!$G$2:$H$604,2,FALSE) -> 280 | O104: 3 | P104: =VLOOKUP(O101,'Location Summary'!$G$2:$H$604,2,FALSE) -> 345 | Q104: 3 | R104: =VLOOKUP(Q101,'Location Summary'!$G$2:$H$604,2,FALSE) -> 330 | S104: 3 | T104: =VLOOKUP(S101,'Location Summary'!$G$2:$H$604,2,FALSE) -> 455 | U104: 3 | V104: =VLOOKUP(U101,'Location Summary'!$G$2:$H$604,2,FALSE) -> 340 | W104: 3 | X104: =VLOOKUP(W101,'Location Summary'!$G$2:$H$604,2,FALSE) -> 435 | Y104: 3 | Z104: =VLOOKUP(Y101,'Location Summary'!$G$2:$H$604,2,FALSE) -> 398.589 | AA104: 3 | AB104: =VLOOKUP(AA101,'Location Summary'!$G$2:$H$604,2,FALSE) -> 426.411 | AC104: 3 | AD104: =VLOOKUP(AC101,'Location Summary'!$G$2:$H$604,2,FALSE) -> 390 | AE104: 3 | AF104: =VLOOKUP(AE101,'Location Summary'!$G$2:$H$604,2,FALSE) -> 335 | AG104: 3 | AH104: =VLOOKUP(AG101,'Location Summary'!$G$2:$H$604,2,FALSE) -> 440 | AI104: 3 | AJ104: =VLOOKUP(AI101,'Location Summary'!$G$2:$H$604,2,FALSE) -> 280 | AK104: 3 | AL104: =VLOOKUP(AK101,'Location Summary'!$G$2:$H$604,2,FALSE) -> 450 | AM104: 3 | AN104: =VLOOKUP(AM101,'Location Summary'!$G$2:$H$604,2,FALSE) -> 285 | AO104: 3 | AP104: =VLOOKUP(AO101,'Location Summary'!$G$2:$H$604,2,FALSE) -> 445 | AQ104: 3 | AR104: =VLOOKUP(AQ101,'Location Summary'!$G$2:$H$604,2,FALSE) -> 360 | AS104: 3 | AT104: =VLOOKUP(AS101,'Location Summary'!$G$2:$H$604,2,FALSE) -> 430
C105: 2 | E105: 2 | G105: 2 | I105: 2 | K105: 2 | M105: 2 | O105: 2 | Q105: 2 | S105: 2 | U105: 2 | W105: 2 | Y105: 2 | AA105: 2 | AC105: 2 | AE105: 2 | AG105: 2 | AI105: 2 | AK105: 2 | AM105: 2 | AO105: 2 | AQ105: 2 | AS105: 2
C106: =VLOOKUP(C101,'Location Summary'!$C$2:$J$604,2,FALSE) -> DB2+9 | E106: =VLOOKUP(E101,'Location Summary'!$C$2:$J$604,2,FALSE) -> DA+3 | G106: =VLOOKUP(G101,'Location Summary'!$C$2:$J$604,2,FALSE) -> DA-1.5 | I106: =VLOOKUP(I101,'Location Summary'!$C$2:$J$604,2,FALSE) -> DA+9 | K106: =VLOOKUP(K101,'Location Summary'!$C$2:$J$604,2,FALSE) -> DA+3 | M106: =VLOOKUP(M101,'Location Summary'!$C$2:$J$604,2,FALSE) -> DB1+0 | O106: =VLOOKUP(O101,'Location Summary'!$C$2:$J$604,2,FALSE) -> DA+3 | Q106: =VLOOKUP(Q101,'Location Summary'!$C$2:$J$604,2,FALSE) -> DA+1.5 | S106: =VLOOKUP(S101,'Location Summary'!$C$2:$J$604,2,FALSE) -> DA+3 | U106: =VLOOKUP(U101,'Location Summary'!$C$2:$J$604,2,FALSE) -> DA+9 | W106: =VLOOKUP(W101,'Location Summary'!$C$2:$J$604,2,FALSE) -> DA+3 | Y106: =VLOOKUP(Y101,'Location Summary'!$C$2:$J$604,2,FALSE) -> DA+3 | AA106: =VLOOKUP(AA101,'Location Summary'!$C$2:$J$604,2,FALSE) -> DB1+3 | AC106: =VLOOKUP(AC101,'Location Summary'!$C$2:$J$604,2,FALSE) -> DA+0 | AE106: =VLOOKUP(AE101,'Location Summary'!$C$2:$J$604,2,FALSE) -> DA+0 | AG106: =VLOOKUP(AG101,'Location Summary'!$C$2:$J$604,2,FALSE) -> DA+3 | AI106: =VLOOKUP(AI101,'Location Summary'!$C$2:$J$604,2,FALSE) -> DA+1.5 | AK106: =VLOOKUP(AK101,'Location Summary'!$C$2:$J$604,2,FALSE) -> DA+3 | AM106: =VLOOKUP(AM101,'Location Summary'!$C$2:$J$604,2,FALSE) -> DA+6 | AO106: =VLOOKUP(AO101,'Location Summary'!$C$2:$J$604,2,FALSE) -> DA+9 | AQ106: =VLOOKUP(AQ101,'Location Summary'!$C$2:$J$604,2,FALSE) -> DA+1.5 | AS106: =VLOOKUP(AS101,'Location Summary'!$C$2:$J$604,2,FALSE) -> DA+0
C108: =AS100+1 -> 258 | E108: =C108+1 -> 259 | G108: =E108+1 -> 260 | I108: =G108+1 -> 261 | K108: =I108+1 -> 262 | M108: =K108+1 -> 263 | O108: =M108+1 -> 264 | Q108: =O108+1 -> 265 | S108: =Q108+1 -> 266 | U108: =S108+1 -> 267 | W108: =U108+1 -> 268 | Y108: =W108+1 -> 269 | AA108: =Y108+1 -> 270 | AC108: =AA108+1 -> 271 | AE108: =AC108+1 -> 272 | AG108: =AE108+1 -> 273 | AI108: =AG108+1 -> 274 | AK108: =AI108+1 -> 275 | AM108: =AK108+1 -> 276 | AO108: =AM108+1 -> 277 | AQ108: =AO108+1 -> 278 | AS108: =AQ108+1 -> 279
C109: 38/10 | E109: 39/0 | G109: 39/1 | I109: 39/2 | K109: 39/3 | M109: 39/4 | O109: 39/5 | Q109: 39/6 | S109: 39/7 | U109: 39/8 | W109: 39/9 | Y109: 39/10 | AA109: 39/11 | AC109: 40/0 | AE109: 40/1 | AG109: 40/2 | AI109: 40/3 | AK109: 40/4 | AM109: 40/5 | AO109: 40/6 | AQ109: 40/7 | AS109: 40/8
C112: 3 | D112: =VLOOKUP(C109,'Location Summary'!$G$2:$H$604,2,FALSE) -> 322.266 | E112: 3 | F112: =VLOOKUP(E109,'Location Summary'!$G$2:$H$604,2,FALSE) -> 392.73 | G112: 3 | H112: =VLOOKUP(G109,'Location Summary'!$G$2:$H$604,2,FALSE) -> 395 | I112: 3 | J112: =VLOOKUP(I109,'Location Summary'!$G$2:$H$604,2,FALSE) -> 385 | K112: 3 | L112: =VLOOKUP(K109,'Location Summary'!$G$2:$H$604,2,FALSE) -> 340 | M112: 3 | N112: =VLOOKUP(M109,'Location Summary'!$G$2:$H$604,2,FALSE) -> 395 | O112: 3 | P112: =VLOOKUP(O109,'Location Summary'!$G$2:$H$604,2,FALSE) -> 410 | Q112: 3 | R112: =VLOOKUP(Q109,'Location Summary'!$G$2:$H$604,2,FALSE) -> 415 | S112: 3 | T112: =VLOOKUP(S109,'Location Summary'!$G$2:$H$604,2,FALSE) -> 415 | U112: 3 | V112: =VLOOKUP(U109,'Location Summary'!$G$2:$H$604,2,FALSE) -> 350 | W112: 3 | X112: =VLOOKUP(W109,'Location Summary'!$G$2:$H$604,2,FALSE) -> 425 | Y112: 3 | Z112: =VLOOKUP(Y109,'Location Summary'!$G$2:$H$604,2,FALSE) -> 350 | AA112: 3 | AB112: =VLOOKUP(AA109,'Location Summary'!$G$2:$H$604,2,FALSE) -> 444.081 | AC112: 3 | AD112: =VLOOKUP(AC109,'Location Summary'!$G$2:$H$604,2,FALSE) -> 260.918 | AE112: 3 | AF112: =VLOOKUP(AE109,'Location Summary'!$G$2:$H$604,2,FALSE) -> 385 | AG112: 3 | AH112: =VLOOKUP(AG109,'Location Summary'!$G$2:$H$604,2,FALSE) -> 435 | AI112: 3 | AJ112: =VLOOKUP(AI109,'Location Summary'!$G$2:$H$604,2,FALSE) -> 385 | AK112: 3 | AL112: =VLOOKUP(AK109,'Location Summary'!$G$2:$H$604,2,FALSE) -> 455 | AM112: 3 | AN112: =VLOOKUP(AM109,'Location Summary'!$G$2:$H$604,2,FALSE) -> 370 | AO112: 3 | AP112: =VLOOKUP(AO109,'Location Summary'!$G$2:$H$604,2,FALSE) -> 400 | AQ112: 3 | AR112: =VLOOKUP(AQ109,'Location Summary'!$G$2:$H$604,2,FALSE) -> 350 | AS112: 3 | AT112: =VLOOKUP(AS109,'Location Summary'!$G$2:$H$604,2,FALSE) -> 470
C113: 2 | E113: 2 | G113: 2 | I113: 2 | K113: 2 | M113: 2 | O113: 2 | Q113: 2 | S113: 2 | U113: 2 | W113: 2 | Y113: 2 | AA113: 2 | AC113: 2 | AE113: 2 | AG113: 2 | AI113: 2 | AK113: 2 | AM113: 2 | AO113: 2 | AQ113: 2 | AS113: 2
C114: =VLOOKUP(C109,'Location Summary'!$C$2:$J$604,2,FALSE) -> DA+3 | E114: =VLOOKUP(E109,'Location Summary'!$C$2:$J$604,2,FALSE) -> DB2+0 | G114: =VLOOKUP(G109,'Location Summary'!$C$2:$J$604,2,FALSE) -> DA-1.5 | I114: =VLOOKUP(I109,'Location Summary'!$C$2:$J$604,2,FALSE) -> DA+3 | K114: =VLOOKUP(K109,'Location Summary'!$C$2:$J$604,2,FALSE) -> DA+1.5 | M114: =VLOOKUP(M109,'Location Summary'!$C$2:$J$604,2,FALSE) -> DA+3 | O114: =VLOOKUP(O109,'Location Summary'!$C$2:$J$604,2,FALSE) -> DA+1.5 | Q114: =VLOOKUP(Q109,'Location Summary'!$C$2:$J$604,2,FALSE) -> DA+1.5 | S114: =VLOOKUP(S109,'Location Summary'!$C$2:$J$604,2,FALSE) -> DA+3 | U114: =VLOOKUP(U109,'Location Summary'!$C$2:$J$604,2,FALSE) -> DA+1.5 | W114: =VLOOKUP(W109,'Location Summary'!$C$2:$J$604,2,FALSE) -> DA+6 | Y114: =VLOOKUP(Y109,'Location Summary'!$C$2:$J$604,2,FALSE) -> DA+3 | AA114: =VLOOKUP(AA109,'Location Summary'!$C$2:$J$604,2,FALSE) -> DA+6 | AC114: =VLOOKUP(AC109,'Location Summary'!$C$2:$J$604,2,FALSE) -> DB1+6 | AE114: =VLOOKUP(AE109,'Location Summary'!$C$2:$J$604,2,FALSE) -> DA+9 | AG114: =VLOOKUP(AG109,'Location Summary'!$C$2:$J$604,2,FALSE) -> DA+6 | AI114: =VLOOKUP(AI109,'Location Summary'!$C$2:$J$604,2,FALSE) -> DA+3 | AK114: =VLOOKUP(AK109,'Location Summary'!$C$2:$J$604,2,FALSE) -> DA+6 | AM114: =VLOOKUP(AM109,'Location Summary'!$C$2:$J$604,2,FALSE) -> DA+9 | AO114: =VLOOKUP(AO109,'Location Summary'!$C$2:$J$604,2,FALSE) -> DA+9 | AQ114: =VLOOKUP(AQ109,'Location Summary'!$C$2:$J$604,2,FALSE) -> DA+3 | AS114: =VLOOKUP(AS109,'Location Summary'!$C$2:$J$604,2,FALSE) -> DA-1.5
AE115: RC 4 Leg
C116: =AS108+1 -> 280 | E116: =C116+1 -> 281 | G116: =E116+1 -> 282 | I116: =G116+1 -> 283 | K116: =I116+1 -> 284 | M116: =K116+1 -> 285 | O116: =M116+1 -> 286 | Q116: =O116+1 -> 287 | S116: =Q116+1 -> 288 | U116: =S116+1 -> 289 | W116: =U116+1 -> 290 | Y116: =W116+1 -> 291 | AA116: =Y116+1 -> 292 | AC116: =AA116+1 -> 293 | AE116: =AC116+1 -> 294 | AG116: =AE116+1 -> 295 | AI116: =AG116+1 -> 296 | AK116: =AI116+1 -> 297 | AM116: =AK116+1 -> 298 | AO116: =AM116+1 -> 299 | AQ116: 300 | AS116: 301
C117: 40/9 | E117: 40/10 | G117: 40/11 | I117: 40A/0 | K117: 41/0 | M117: 41/1 | O117: 42/0 | Q117: 42/1 | S117: 42/2 | U117: 42/3 | W117: 43/0 | Y117: 43/1 | AA117: 43/2 | AC117: 43/3 | AE117: 43/4 | AG117: 43/5 | AI117: 43/6 | AK117: 43/7 | AM117: 43/8 | AO117: 44/0 | AQ117: 44/1 | AS117: 44/2
C120: 3 | D120: =VLOOKUP(C117,'Location Summary'!$G$2:$H$604,2,FALSE) -> 355 | E120: 3 | F120: =VLOOKUP(E117,'Location Summary'!$G$2:$H$604,2,FALSE) -> 485 | G120: 3 | H120: =VLOOKUP(G117,'Location Summary'!$G$2:$H$604,2,FALSE) -> 315 | I120: 3 | J120: =VLOOKUP(I117,'Location Summary'!$G$2:$H$604,2,FALSE) -> 410.61 | K120: 3 | L120: =VLOOKUP(K117,'Location Summary'!$G$2:$H$604,2,FALSE) -> 358 | M120: 3 | N120: =VLOOKUP(M117,'Location Summary'!$G$2:$H$604,2,FALSE) -> 465.782 | O120: 3 | P120: =VLOOKUP(O117,'Location Summary'!$G$2:$H$604,2,FALSE) -> 419.998 | Q120: 3 | R120: =VLOOKUP(Q117,'Location Summary'!$G$2:$H$604,2,FALSE) -> 375 | S120: 3 | T120: =VLOOKUP(S117,'Location Summary'!$G$2:$H$604,2,FALSE) -> 464 | U120: 3 | V120: =VLOOKUP(U117,'Location Summary'!$G$2:$H$604,2,FALSE) -> 424.891 | W120: 3 | X120: =VLOOKUP(W117,'Location Summary'!$G$2:$H$604,2,FALSE) -> 341.866 | Y120: 3 | Z120: =VLOOKUP(Y117,'Location Summary'!$G$2:$H$604,2,FALSE) -> 375 | AA120: 3 | AB120: =VLOOKUP(AA117,'Location Summary'!$G$2:$H$604,2,FALSE) -> 375 | AC120: 3 | AD120: =VLOOKUP(AC117,'Location Summary'!$G$2:$H$604,2,FALSE) -> 355 | AE120: 3 | AF120: =VLOOKUP(AE117,'Location Summary'!$G$2:$H$604,2,FALSE) -> 405 | AG120: 3 | AH120: =VLOOKUP(AG117,'Location Summary'!$G$2:$H$604,2,FALSE) -> 375 | AI120: 3 | AJ120: =VLOOKUP(AI117,'Location Summary'!$G$2:$H$604,2,FALSE) -> 385 | AK120: 3 | AL120: =VLOOKUP(AK117,'Location Summary'!$G$2:$H$604,2,FALSE) -> 415 | AM120: 3 | AN120: =VLOOKUP(AM117,'Location Summary'!$G$2:$H$604,2,FALSE) -> 409.546 | AO120: 3 | AP120: =VLOOKUP(AO117,'Location Summary'!$G$2:$H$604,2,FALSE) -> 400 | AQ120: 3 | AR120: =VLOOKUP(AQ117,'Location Summary'!$G$2:$H$678,2,FALSE) -> 427 | AS120: 3 | AT120: =VLOOKUP(AS117,'Location Summary'!$G$2:$H$678,2,FALSE) -> 366
C121: 2 | E121: 2 | G121: 2 | I121: 2 | K121: 2 | M121: 2 | O121: 2 | Q121: 2 | S121: 2 | U121: 2 | W121: 2 | Y121: 2 | AA121: 2 | AC121: 2 | AE121: 2 | AG121: 2 | AI121: 2 | AK121: 2 | AM121: 2 | AO121: 2 | AQ121: 2 | AS121: 2
C122: =VLOOKUP(C117,'Location Summary'!$C$2:$J$604,2,FALSE) -> DA+9 | E122: =VLOOKUP(E117,'Location Summary'!$C$2:$J$604,2,FALSE) -> DA+3 | G122: =VLOOKUP(G117,'Location Summary'!$C$2:$J$604,2,FALSE) -> DA+9 | I122: =VLOOKUP(I117,'Location Summary'!$C$2:$J$604,2,FALSE) -> DB1+9 | K122: =VLOOKUP(K117,'Location Summary'!$C$2:$J$604,2,FALSE) -> DB1+9 | M122: =VLOOKUP(M117,'Location Summary'!$C$2:$J$604,2,FALSE) -> DA+9 | O122: =VLOOKUP(O117,'Location Summary'!$C$2:$J$604,2,FALSE) -> DB2+0 | Q122: =VLOOKUP(Q117,'Location Summary'!$C$2:$J$604,2,FALSE) -> DA+3 | S122: =VLOOKUP(S117,'Location Summary'!$C$2:$J$604,2,FALSE) -> DA+9 | U122: =VLOOKUP(U117,'Location Summary'!$C$2:$J$604,2,FALSE) -> DB1+9 | W122: =VLOOKUP(W117,'Location Summary'!$C$2:$J$604,2,FALSE) -> DB1+0 | Y122: =VLOOKUP(Y117,'Location Summary'!$C$2:$J$604,2,FALSE) -> DA-1.5 | AA122: =VLOOKUP(AA117,'Location Summary'!$C$2:$J$604,2,FALSE) -> DA+6 | AC122: =VLOOKUP(AC117,'Location Summary'!$C$2:$J$604,2,FALSE) -> DA-1.5 | AE122: =VLOOKUP(AE117,'Location Summary'!$C$2:$J$604,2,FALSE) -> DA+0 | AG122: =VLOOKUP(AG117,'Location Summary'!$C$2:$J$604,2,FALSE) -> DC2+0 | AI122: =VLOOKUP(AI117,'Location Summary'!$C$2:$J$604,2,FALSE) -> DA+3 | AK122: =VLOOKUP(AK117,'Location Summary'!$C$2:$J$604,2,FALSE) -> DA+0 | AM122: =VLOOKUP(AM117,'Location Summary'!$C$2:$J$604,2,FALSE) -> DA+9 | AO122: =VLOOKUP(AO117,'Location Summary'!$C$2:$J$604,2,FALSE) -> DB1+6 | AQ122: =VLOOKUP(AQ117,'Location Summary'!$C$2:$J$604,2,FALSE) -> DA+3 | AS122: =VLOOKUP(AS117,'Location Summary'!$C$2:$J$678,2,FALSE) -> DA+3
AF123: TP TWR
C124: 302 | E124: 303 | G124: 304 | I124: 305 | K124: 306 | M124: Common Point
C125: 44/3 | E125: 44/4 | G125: 44/5 | I125: 45/0 | K125: 46/0
J126: 132KV
C128: 3 | D128: =VLOOKUP(C125,'Location Summary'!$G$2:$H$678,2,FALSE) -> 350 | E128: 3 | F128: =VLOOKUP(E125,'Location Summary'!$G$2:$H$678,2,FALSE) -> 383 | G128: 3 | H128: =VLOOKUP(G125,'Location Summary'!$G$2:$H$678,2,FALSE) -> 457.155 | I128: 3 | J128: =VLOOKUP(I125,'Location Summary'!$G$2:$H$678,2,FALSE) -> 208.53 | K128: 3
C129: 2 | E129: 2 | G129: 2 | I129: 2 | K129: 2
C130: =VLOOKUP(C125,'Location Summary'!$C$2:$J$678,2,FALSE) -> DA+3 | E130: =VLOOKUP(E125,'Location Summary'!$C$2:$J$678,2,FALSE) -> DA+0 | G130: =VLOOKUP(G125,'Location Summary'!$C$2:$J$678,2,FALSE) -> DA+0 | I130: =VLOOKUP(I125,'Location Summary'!$C$2:$J$678,2,FALSE) -> DB1+9 | K130: =VLOOKUP(K125,'Location Summary'!$C$2:$J$678,2,FALSE) -> DB1+12
K131: CP
C132: Progress overview (Tower wise breakups)
C133: TOT | E133: Total Qty in No's | G133: FDN | J133: ERE
G134: Comp. | I134: Bal. | J134: Comp. | L134: Balance | P134: SUNSURE(SOLAR) ROUTE DIVERTED AREA | AG134: OILPIPE LINE ROUTE DIVERTED AREA
...

Sheet Stringing
A1: =Erection!A1 -> KEC International Limited
A2: =Erection!A2 -> TA413 : 765 KV D/C Bikaner III - Neemrana II TL02
A3: Details of Stringing | U3: =TA413_PBNTL!M1 -> 27.05.2026
A4: CUMM. SR.NO | B4: MONTH SR.NO. | C4: Section | R4: =SUM(R6:R33)/10^7 -> 7.1955488
C5: From | D5: To | E5: Length in Km's | F5: Cum. Length in Km's | G5: TSE/Manual | H5: Insulator hoisting Start | I5: Insulator Hoisting Complete | J5: Paying Out Start | K5: Paying Out Completed | L5: Final sag start | M5: Final sag complete | N5: Earthwire Final Sag | O5: Jumpuring | P5: Spacering | Q5: Clipping | R5: Revenue | S5: JMC Status | T5: Name of the Contractor | U5: Remarks
A6: 1 | B6: 1 | C6: AP-34 | D6: AP-35 | E6: 4.898588 | F6: =E6 -> 4.898588 | G6: TSE | H6: =I6-2 -> 45694 | I6: 45696 | J6: 45709 | K6: 45714 | L6: =M6-3 -> 45717 | M6: 45720 | N6: 45721 | O6: complete | P6: complete | Q6: complete | R6: =958667.19*E6 -> 4696115.6 | S6: Received | T6: SK Infratech | U6: Completed | V6: Gang Engauged on : 18-01-25
A7: 2 | B7: 1 | C7: 37A/0 | D7: AP-38/0 | E7: =2583.589/1000 -> 2.583589 | F7: =E7+F6 -> 7.482177 | G7: TSE | H7: =I7-2 -> 45727 | I7: 45729 | J7: 45733 | K7: 45736 | L7: =M7-3 -> 45760 | M7: 45763 | N7: 45764 | O7: 45768 | P7: 45783 | Q7: complete | R7: =958667.19*E7 -> 2476802 | S7: Received | T7: SK Infratech | U7: Completed
A8: 3 | B8: 2 | C8: AP-38 | D8: AP-39 | E8: 4.163677 | F8: =E8+F7 -> 11.645854 | G8: TSE | H8: =I8-2 -> 45742 | I8: 45744 | J8: 45745 | K8: 45752 | L8: =M8-1 -> 45762 | M8: 45763 | N8: 45764 | O8: complete | P8: complete | Q8: complete | R8: =958667.19*E8 -> 3991580.5 | S8: Received | T8: SK Infratech | U8: Completed | V8: =R10+R11 -> 4921849.1 | X8: =V8/10^7 -> 0.49218491
A9: 4 | B9: 3 | C9: AP-39 | D9: AP-40 | E9: 4.716 | F9: =E9+F8 -> 16.361854 | G9: TSE | H9: =I9-2 -> 45751 | I9: 45753 | J9: 45772 | K9: 45776 | L9: =M9-1 -> 45776 | M9: 45777 | N9: 45804 | O9: complete | P9: 46014 | Q9: 46014 | R9: =958667.19*E9 -> 4521074.5 | S9: Received | T9: SK Infratech | U9: Completed
A10: 5 | B10: 4 | C10: AP-7 | D10: AP-7A | E10: =2699.284/1000 -> 2.699284 | F10: =E10+F9 -> 19.061138 | G10: TSE | H10: =I10-2 -> 45890 | I10: 45892 | J10: 45896 | K10: 45904 | L10: =M10-1 -> 45917 | M10: 45918 | N10: 45918 | O10: complete | P10: complete | Q10: complete | R10: =958667.19*E10 -> 2587715 | S10: Received | T10: Rahim Khan | U10: Completed | V10: Gang Engauged on: 16.08.25
A11: 6 | B11: 4 | C11: AP-7A | D11: AP-8 | E11: =2434.77/1000 -> 2.43477 | F11: =E11+F10 -> 21.495908 | G11: TSE | H11: =I11-2 -> 45908 | I11: 45910 | J11: 45912 | K11: 45916 | L11: =M11-1 -> 45924 | M11: 45925 | N11: 45925 | O11: complete | P11: complete | Q11: complete | R11: =958667.19*E11 -> 2334134.1 | S11: Received | T11: Rahim Khan | U11: Completed
A12: 7 | B12: 5 | C12: AP-8 | D12: AP-8A | E12: =4455/1000 -> 4.455 | F12: =E12+F11 -> 25.950908 | G12: TSE | H12: =I12-2 -> 45929 | I12: 45931 | J12: 45935 | K12: 45945 | L12: =M12-1 -> 45951 | M12: 45952 | N12: 45952 | O12: 45958 | P12: complete | Q12: complete | R12: =958667.19*E12 -> 4270862.3 | S12: Received | T12: Rahim Khan | U12: Completed
A13: 8 | B13: 6 | C13: AP-8A | D13: AP-9/0 | E13: =466.629/1000 -> 0.466629 | F13: =E13+F12 -> 26.417537 | G13: Manual | H13: =I13-2 -> 45929 | I13: 45931 | J13: 45933 | K13: 45935 | L13: =M13-1 -> 45956 | M13: 45957 | N13: 45957 | O13: 9/0 Balance | P13: complete | Q13: complete | R13: =958667.19*E13 -> 447341.91 | S13: Received | T13: Rahim Khan | U13: Completed
A14: 9 | B14: 7 | C14: AP-6 | D14: AP-7 | E14: =4901.236/1000 -> 4.901236 | F14: =E14+F13 -> 31.318773 | G14: TSE | H14: =I14-2 -> 45973 | I14: 45975 | J14: 45980 | K14: 45984 | L14: =M14-1 -> 45988 | M14: 45989 | N14: 45991 | O14: 46015 | P14: 46010 | Q14: complete | R14: =958667.19*E14 -> 4698654.1 | S14: Received | T14: Rahim Khan | U14: Completed | V14: Gang Engauged 03/09/25
A15: 10 | B15: 8 | C15: AP-5A | D15: AP-6 | E15: =419.48/1000 -> 0.41948 | F15: =E15+F14 -> 31.738253 | G15: Manual | H15: =I15-2 -> 45986 | I15: 45988 | J15: 45966 | K15: 45970 | L15: =M15-1 -> 46002 | M15: 46003 | N15: =M15 -> 46003 | O15: 46033 | P15: 46010 | Q15: complete | R15: =958667.19*E15 -> 402141.71 | S15: Received | T15: Rahim Khan | U15: Completed
A16: 11 | B16: 9 | C16: AP-5 | D16: AP-5A | E16: =4418.389/1000 -> 4.418389 | F16: =E16+F15 -> 36.156642 | G16: TSE | H16: 45985 | I16: 45996 | J16: 45998 | K16: 46003 | L16: =M16-1 -> 46012 | M16: 46013 | N16: 46027 | O16: 46069 | P16: 46031 | Q16: complete | R16: =958667.19*E16 -> 4235764.6 | S16: Received | T16: Rahim Khan | U16: Completed
A17: 12 | B17: 10 | C17: AP-4A | D17: AP-5/0 | E17: =2681.611/1000 -> 2.681611 | F17: =E17+F16 -> 38.838253 | G17: TSE | H17: =I17-2 -> 46003 | I17: 46005 | J17: 46006 | K17: 46013 | L17: =M17-1 -> 46021 | M17: 46022 | N17: 46024 | O17: 46074 | P17: 46041 | Q17: 46033 | R17: =958667.19*E17 -> 2570772.5 | S17: Received | T17: Rahim Khan | U17: Completed
A18: 13 | B18: 1 | C18: AP-4 | D18: AP4A/0 | E18: =709.163/1000 -> 0.709163 | F18: =E18+F17 -> 39.547416 | G18: TSE | H18: =I18-2 -> 46014 | I18: 46016 | J18: 46018 | K18: 46022 | L18: 46036 | M18: 46040 | N18: 46040 | O18: complete | P18: complete | Q18: complete | R18: =958667.19*E18 -> 679851.3 | S18: Received | T18: Rahim Khan | U18: Completed
A19: 14 | B19: 2 | C19: =D21 -> AP-33 | D19: AP-34 | E19: =4049.764/1000 -> 4.049764 | F19: =E19+F18 -> 43.59718 | G19: TSE | H19: =I19-5 -> 46021 | I19: 46026 | J19: 46029 | K19: 46035 | L19: 46043 | M19: 46046 | N19: 46047 | O19: complete | P19: complete | Q19: complete | R19: =958667.19*E19 -> 3882375.9 | S19: Received | T19: SK Infratech | U19: Completed | V19: Noor Alam
A20: 15 | B20: 3 | C20: AP3B/0 | D20: AP4/0 | E20: 1.627 | F20: =E20+F19 -> 45.22418 | G20: TSE | H20: 46032 | I20: 46034 | J20: 46036 | K20: 46039 | L20: 46046 | M20: 46049 | N20: 46050 | O20: complete | P20: complete | Q20: 46054 | R20: =958667.19*E20 -> 1559751.5 | S20: Received | T20: Rahim Khan | U20: Completed
A21: 16 | B21: 4 | C21: AP-32A | D21: AP-33 | E21: 0.84 | F21: =E21+F20 -> 46.06418 | G21: TSE | H21: =I21-3 -> 46038 | I21: =J21+3 -> 46041 | J21: 46038 | K21: 46041 | L21: 46053 | M21: 46059 | N21: =M21+1 -> 46060 | O21: complete | P21: complete | Q21: complete | R21: =958667.19*E21 -> 805280.44 | S21: Received | T21: SK Infratech | U21: Completed
A22: 17 | B22: 5 | C22: AP32/0 | D22: AP32A/0 | E22: 3.284 | F22: =E22+F21 -> 49.34818 | G22: TSE | H22: =J22-4 -> 46043 | I22: =H22+3 -> 46046 | J22: 46047 | K22: 46052 | L22: 46053 | M22: 46059 | N22: =M22+1 -> 46060 | O22: complete | P22: complete | Q22: complete | R22: =958667.19*E22 -> 3148263.1 | S22: Received | T22: SK Infratech | U22: Completed
A23: 18 | B23: 1 | C23: 2A/0 | D23: 3A/0 | E23: 2.837 | F23: =E23+F22 -> 52.18518 | G23: TSE | H23: 46062 | I23: =J23-3 -> 46068 | J23: 46071 | K23: 46079 | L23: 46080 | M23: 46084 | N23: 46086 | O23: Half side balance | P23: complete | Q23: complete | R23: =958667.19*E23 -> 2719738.8 | S23: Received | T23: Rahim Khan | U23: Completed
A24: 19 | B24: 2 | C24: 3A/0 | D24: 3B/0 | E24: =2691.467/1000 -> 2.691467 | F24: =E24+F23 -> 54.876647 | G24: TSE | H24: 46053 | I24: =J24-2 -> 46059 | J24: 46061 | K24: 46066 | L24: 46080 | M24: 46084 | N24: 46086 | O24: complete | P24: complete | Q24: complete | R24: =958667.19*E24 -> 2580221.1 | S24: Received | T24: Rahim Khan | U24: Completed
A25: 20 | B25: 4 | C25: 1/0 | D25: 2A/0 | E25: 0.29 | F25: =E25+F24 -> 55.166647 | G25: Manual | H25: =I25-2 -> 46063 | I25: =J25-2 -> 46065 | J25: 46067 | K25: 46071 | L25: 46090 | M25: 46094 | N25: =M25+1 -> 46095 | O25: Balance | P25: complete | Q25: complete | R25: =958667.19*E25 -> 278013.49 | S25: Received | T25: Rahim Khan | U25: Completed
A26: 21 | B26: 3 | C26: 31/0 | D26: 32/0 | E26: 4.333 | F26: =E26+F25 -> 59.499647 | G26: TSE | H26: 46024 | I26: =J26-2 -> 46061 | J26: 46063 | K26: 46068 | L26: 46083 | M26: 46091 | N26: =M26+1 -> 46092 | O26: complete | P26: complete | Q26: complete | R26: =958667.19*E26 -> 4153904.9 | S26: Received | T26: SK Infratech | U26: Completed
A27: 22 | B27: 1 | C27: 30/0 | D27: 31/0 | E27: 4.124 | F27: =E27+F26 -> 63.623647 | G27: TSE | H27: 46069 | I27: =J27-2 -> 46078 | J27: 46080 | K27: 46087 | L27: 46093 | M27: 46097 | N27: =M27+1 -> 46098 | O27: complete | P27: complete | Q27: complete | R27: =958667.19*E27 -> 3953543.5 | S27: Received | T27: SK Infratech | U27: Completed
A28: 23 | B28: 1 | C28: 9/0 | D28: 10/0 | E28: =4964.92/1000 -> 4.96492 | F28: =E28+F27 -> 68.588567 | G28: TSE | H28: 46084 | I28: 46101 | J28: 46109 | K28: 46114 | L28: 46118 | M28: 46122 | N28: 46122 | O28: complete | P28: complete | Q28: complete | R28: =958667.19*E28 -> 4759705.9 | T28: Rahim Khan | U28: Completed
A29: 24 | B29: 1 | C29: 29A/0 | D29: 30/0 | E29: =2669.007/1000 -> 2.669007 | F29: =E29+F28 -> 71.257574 | G29: TSE | H29: =I29-3 -> 46118 | I29: 46121 | J29: 46134 | K29: 46140 | L29: 46142 | M29: 46145 | N29: 46146 | Q29: complete | R29: =958667.19*E29 -> 2558689.4 | T29: SK Infratech | U29: Completed
A30: 25 | B30: 2 | C30: 10/0 | D30: 11/0 | E30: =1004.183/1000 -> 1.004183 | F30: =E30+F29 -> 72.261757 | G30: TSE | H30: =I30-4 -> 46112 | I30: =J30-3 -> 46116 | J30: 46119 | K30: 46121 | L30: 46154 | M30: 46158 | N30: 46158 | P30: complete | Q30: complete | R30: =958667.19*E30 -> 962677.29 | T30: Rahim Khan | U30: Completed
A31: 26 | B31: 3 | C31: 29/0 | D31: 29A/0 | E31: =2379.204/1000 -> 2.379204 | F31: =E31+F30 -> 74.640961 | G31: TSE | H31: =I31-4 -> 46140 | I31: =J31-6 -> 46144 | J31: 46150 | K31: 46154 | L31: 46155 | M31: 46158 | N31: 46158 | Q31: 3 balance | R31: =958667.19*E31 -> 2280864.8 | T31: SK Infratech | U31: Completed
A32: 27 | C32: 27/0 | D32: 28/0 | E32: =2548.275/1000 -> 2.548275 | F32: =E32+F31 -> 77.189236 | G32: TSE | H32: 46159 | I32: 46162 | J32: 46162 | K32: 46165 | L32: 46166 | T32: SK Infratech | U32: Final sag U/P
A33: 28 | C33: 13/0 | D33: 13A/0 | E33: =416.878/1000 -> 0.416878 | F33: =E33+F31 -> 75.057839 | G33: Manual | H33: 46082 | I33: 46087 | R33: =958667.19*E33 -> 399647.26 | T33: BSPL | U33: Rough sag arangment (Work Hold) | V33: 20
A34: 29 | C34: 11/0 | D34: 12/0 | E34: =242.89/1000 -> 0.24289 | F34: =E34+F33 -> 75.300729 | G34: Manual | T34: Rahim Khan | U34: Bit cutting
A35: 30
A36: 31
A37: 32
A38: 33
A39: 34

Sheet Stretch readiness 
A2: Stretch Readiness Status - 765 KV D/C Bikaner III - Neemrana II TL02 TA-413
B4: Description | C4: Stringing Type | D4: Line length | E4: TSE/Manual Completed | F4: Stringing Compl | G4: Balanced | H4: Remarks
B5: Stringing | C5: 62 | D5: =SUM(C11:C72)/1000 -> 117.85605 | E5: =SUM(E6:E7) -> 27 | F5: =SUM(F6:F7) -> 77.19087 | G5: =D5-F5 -> 40.665184
B6: TSE | C6: 37 | D6: =D5-D7 -> 109.28516 | E6: =COUNTIFS($D$11:$D$72,"TSE",$L$11:$L$72,"Completed") -> 24 | F6: =SUMIFS($C$11:$C$72,$D$11:$D$72,"TSE",$L$11:$L$72,"Completed")/1000 -> 76.01455 | G6: =D6-F6 -> 33.270609 | H6: 2 | M6: =C6-E6 -> 13 | N6: =D6-F6 -> 33.270609
B7: Manual | C7: 25 | D7: =ROUNDUP(SUMIF($D$11:$D$72,$B7,$C$11:$C$72),3)/1000 -> 8.570895 | E7: =COUNTIFS($D$11:$D$72,"Manual",$L$11:$L$72,"Completed") -> 3 | F7: =SUMIFS($C$11:$C$72,$D$11:$D$72,"Manual",$L$11:$L$72,"Completed")/1000 -> 1.17632 | G7: =D7-F7 -> 7.394575 | H7: 0 | M7: =C7-E7 -> 22 | N7: =D7-F7 -> 7.394575
A9: Sl No. | B9: Section | C9: Section Length (M) | D9: Type | E9: Crossing details | F9: No. of Locations (Including for end twr) | G9: Foundation | I9: Erection | L9: Stringing
G10: Completed | H10: Balance | I10: Completed | J10: Balance | K10: Month | L10: Remarks
A11: =IF(B11="","",SUBTOTAL(3,$B$11:B11)) -> 1 | B11: Gantry - AP-1 | C11: 150.014 | D11: Manual | F11: 1 | G11: 1 | H11: =F11-G11 -> 0 | I11: 1 | J11: =F11-I11 -> 0 | K11: mar'26 | L11: pending due to gy not yet ready
A12: =IF(B12="","",SUBTOTAL(3,$B$11:B12)) -> 2 | B12: AP-1 - AP-2A | C12: 290.21 | D12: Manual | F12: 1 | G12: 1 | H12: =F12-G12 -> 0 | I12: 1 | J12: =F12-I12 -> 0 | K12: Jan'26 | L12: Completed
A13: =IF(B13="","",SUBTOTAL(3,$B$11:B13)) -> 3 | B13: AP/2A - AP/3A | C13: 2836.992 | D13: TSE | F13: 7 | G13: 7 | H13: =F13-G13 -> 0 | I13: 7 | J13: =F13-I13 -> 0 | K13: Jan'26 | L13: Completed
A14: =IF(B14="","",SUBTOTAL(3,$B$11:B14)) -> 4 | B14: AP3A/0-AP3B/0 | C14: 2691.467 | D14: TSE | F14: 7 | G14: 7 | H14: =F14-G14 -> 0 | I14: 7 | J14: =F14-I14 -> 0 | K14: Jan'26 | L14: Completed
A15: =IF(B15="","",SUBTOTAL(3,$B$11:B15)) -> 5 | B15: AP3B/0-AP4/0 | C15: 1627.07 | D15: TSE | F15: 4 | G15: 4 | H15: =F15-G15 -> 0 | I15: 4 | J15: =F15-I15 -> 0 | K15: Jan'26 | L15: Completed | M15: Stringing for stringing
A16: =IF(B16="","",SUBTOTAL(3,$B$11:B16)) -> 6 | B16: AP-4 - AP-4A/0 | C16: 709.163 | D16: TSE | F16: 2 | G16: 2 | H16: =F16-G16 -> 0 | I16: 2 | J16: =F16-I16 -> 0 | K16: comp | L16: Completed
A17: =IF(B17="","",SUBTOTAL(3,$B$11:B17)) -> 7 | B17: AP-4A/0 - AP-5 | C17: 2681.611 | D17: TSE | F17: 7 | G17: 7 | H17: =F17-G17 -> 0 | I17: 7 | J17: =F17-I17 -> 0 | K17: comp | L17: Completed
A18: =IF(B18="","",SUBTOTAL(3,$B$11:B18)) -> 8 | B18: AP-5 - AP-5A/0 | C18: 4418.389 | D18: TSE | F18: 11 | G18: 11 | H18: =F18-G18 -> 0 | I18: 11 | J18: =F18-I18 -> 0 | K18: comp | L18: Completed
A19: =IF(B19="","",SUBTOTAL(3,$B$11:B19)) -> 9 | B19: AP-5A/0 - AP-6 | C19: 419.48 | D19: Manual | F19: 1 | G19: 1 | H19: =F19-G19 -> 0 | I19: 1 | J19: =F19-I19 -> 0 | K19: comp | L19: Completed
A20: =IF(B20="","",SUBTOTAL(3,$B$11:B20)) -> 10 | B20: AP-6 - AP-7 | C20: 4901.236 | D20: TSE | F20: 13 | G20: 13 | H20: =F20-G20 -> 0 | I20: 13 | J20: =F20-I20 -> 0 | K20: comp | L20: Completed
A21: =IF(B21="","",SUBTOTAL(3,$B$11:B21)) -> 11 | B21: AP-7 - AP-7A/0 | C21: 2699.284 | D21: TSE | F21: 7 | G21: 7 | H21: =F21-G21 -> 0 | I21: 7 | J21: =F21-I21 -> 0 | K21: comp | L21: Completed
A22: =IF(B22="","",SUBTOTAL(3,$B$11:B22)) -> 12 | B22: AP-7A/0 - AP-8/0 | C22: 2434.77 | D22: TSE | F22: 6 | G22: 6 | H22: =F22-G22 -> 0 | I22: 6 | J22: =F22-I22 -> 0 | K22: comp | L22: Completed
A23: =IF(B23="","",SUBTOTAL(3,$B$11:B23)) -> 13 | B23: AP-8/0 - AP-8A/0 | C23: 4455 | D23: TSE | F23: 12 | G23: 12 | H23: =F23-G23 -> 0 | I23: 12 | J23: =F23-I23 -> 0 | K23: comp | L23: Completed
A24: =IF(B24="","",SUBTOTAL(3,$B$11:B24)) -> 14 | B24: AP-8A/0 - AP-9/0 | C24: 466.63 | D24: Manual | F24: 1 | G24: 1 | H24: =F24-G24 -> 0 | I24: 1 | J24: =F24-I24 -> 0 | K24: comp | L24: Completed
A25: =IF(B25="","",SUBTOTAL(3,$B$11:B25)) -> 15 | B25: AP-9/0 - AP-10/0 | C25: 4964.92 | D25: TSE | F25: 12 | G25: 12 | H25: =F25-G25 -> 0 | I25: 12 | J25: =F25-I25 -> 0 | K25: Jan'26 | L25: Completed
A26: =IF(B26="","",SUBTOTAL(3,$B$11:B26)) -> 16 | B26: AP-10/0 - AP-11/0 | C26: 1004.183 | D26: TSE | F26: 3 | G26: 3 | H26: =F26-G26 -> 0 | I26: 3 | J26: =F26-I26 -> 0 | K26: Feb'26 | L26: Completed
A27: =IF(B27="","",SUBTOTAL(3,$B$11:B27)) -> 17 | B27: AP-11/0 - AP-12/0 | C27: 242.89 | D27: Manual | E27: NH-62 | F27: 1 | G27: 1 | H27: =F27-G27 -> 0 | I27: 1 | J27: =F27-I27 -> 0 | K27: Feb'26 | L27: WIP | M27: Stringing for stringing
A28: =IF(B28="","",SUBTOTAL(3,$B$11:B28)) -> 18 | B28: AP-12/0 - AP-13/0 | C28: 329.73 | D28: Manual | E28: 132 KV | F28: 1 | G28: 1 | H28: =F28-G28 -> 0 | I28: 1 | J28: =F28-I28 -> 0 | K28: Feb'26 | L28: Ready for stringing
A29: =IF(B29="","",SUBTOTAL(3,$B$11:B29)) -> 19 | B29: AP-13/0 - AP-13A/0 | C29: 416.88 | D29: Manual | F29: 1 | G29: 1 | H29: =F29-G29 -> 0 | I29: 1 | J29: =F29-I29 -> 0 | K29: Feb'26 | L29: Insulator hoisting complete
A30: =IF(B30="","",SUBTOTAL(3,$B$11:B30)) -> 20 | B30: AP-13A/0 - AP-14/0 | C30: 480.27 | D30: Manual | F30: 1 | G30: 1 | H30: =F30-G30 -> 0 | I30: 1 | J30: =F30-I30 -> 0 | K30: Feb'26 | L30: Ready for stringing
A31: =IF(B31="","",SUBTOTAL(3,$B$11:B31)) -> 21 | B31: AP-14/0 - AP-15/0 | C31: 223.82 | D31: Manual | E31: 400KV | F31: 1 | G31: 1 | H31: =F31-G31 -> 0 | I31: 1 | J31: =F31-I31 -> 0 | K31: Feb'26 | L31: Ready for stringing
A32: =IF(B32="","",SUBTOTAL(3,$B$11:B32)) -> 22 | B32: AP-15/0 - AP-16/0 | C32: 5019.34 | D32: TSE | F32: 13 | G32: 13 | H32: =F32-G32 -> 0 | I32: 12 | J32: =F32-I32 -> 1 | K32: Feb'26 | L32: Strech Not Ready
A33: =IF(B33="","",SUBTOTAL(3,$B$11:B33)) -> 23 | B33: AP-16/0 - AP-17/0 | C33: 392.69 | D33: Manual | F33: 1 | G33: 1 | H33: =F33-G33 -> 0 | I33: 1 | J33: =F33-I33 -> 0 | K33: Feb'26
A34: =IF(B34="","",SUBTOTAL(3,$B$11:B34)) -> 24 | B34: AP-17/0 - AP-18/0 | C34: 398.4 | D34: Manual | F34: 1 | G34: 1 | H34: =F34-G34 -> 0 | I34: 1 | J34: =F34-I34 -> 0 | K34: Feb'26
A35: =IF(B35="","",SUBTOTAL(3,$B$11:B35)) -> 25 | B35: AP-18/0 - AP-19/0 | C35: 3030.029 | D35: TSE | F35: 8 | G35: 8 | H35: =F35-G35 -> 0 | I35: 8 | J35: =F35-I35 -> 0 | K35: Feb'26
A36: =IF(B36="","",SUBTOTAL(3,$B$11:B36)) -> 26 | B36: AP-19/0 - AP-20/0 | C36: 279.36 | D36: Manual | E36: Railway | F36: 1 | G36: 1 | H36: =F36-G36 -> 0 | I36: 1 | J36: =F36-I36 -> 0 | K36: Feb'26
A37: =IF(B37="","",SUBTOTAL(3,$B$11:B37)) -> 27 | B37: AP-20/0 - AP-21/0 | C37: 2550.167 | D37: TSE | F37: 7 | G37: 7 | H37: =F37-G37 -> 0 | I37: 7 | J37: =F37-I37 -> 0 | K37: mar'26
A38: =IF(B38="","",SUBTOTAL(3,$B$11:B38)) -> 28 | B38: AP-21/0 - AP-22/0 | C38: 2283.535 | D38: TSE | F38: 6 | G38: 6 | H38: =F38-G38 -> 0 | I38: 6 | J38: =F38-I38 -> 0 | K38: mar'26
A39: =IF(B39="","",SUBTOTAL(3,$B$11:B39)) -> 29 | B39: AP-22/0 - AP-23/0 | C39: 259.05 | D39: Manual | E39: 220KV | F39: 1 | G39: 1 | H39: =F39-G39 -> 0 | I39: 1 | J39: =F39-I39 -> 0 | K39: mar'26
A40: =IF(B40="","",SUBTOTAL(3,$B$11:B40)) -> 30 | B40: AP-23/0 - AP-23A/0 | C40: 440.46 | D40: Manual | F40: 1 | G40: 1 | H40: =F40-G40 -> 0 | I40: 1 | J40: =F40-I40 -> 0 | K40: mar'26
A41: =IF(B41="","",SUBTOTAL(3,$B$11:B41)) -> 31 | B41: AP-23A/0 - AP-24/0 | C41: 496.69 | D41: Manual | F41: 1 | G41: 1 | H41: =F41-G41 -> 0 | I41: 1 | J41: =F41-I41 -> 0 | K41: mar'26
A42: =IF(B42="","",SUBTOTAL(3,$B$11:B42)) -> 32 | B42: AP-24/0 - AP-25/0 | C42: 244.03 | D42: Manual | E42: 400KV | F42: 1 | G42: 1 | H42: =F42-G42 -> 0 | I42: 1 | J42: =F42-I42 -> 0 | K42: mar'26
A43: =IF(B43="","",SUBTOTAL(3,$B$11:B43)) -> 33 | B43: AP-25/0 - AP-26/0 | C43: 237.43 | D43: Manual | F43: 1 | G43: 1 | H43: =F43-G43 -> 0 | I43: 1 | J43: =F43-I43 -> 0 | K43: mar'26
A44: =IF(B44="","",SUBTOTAL(3,$B$11:B44)) -> 34 | B44: AP-26/0 - AP-27/0 | C44: 203.48 | D44: Manual | E44: 765KV | F44: 1 | G44: 1 | H44: =F44-G44 -> 0 | I44: 1 | J44: =F44-I44 -> 0 | K44: Feb'26
A45: =IF(B45="","",SUBTOTAL(3,$B$11:B45)) -> 35 | B45: AP-27/0 - AP-28/0 | C45: 2548.275 | D45: TSE | F45: 7 | G45: 7 | H45: =F45-G45 -> 0 | I45: 7 | J45: =F45-I45 -> 0 | K45: Feb'26 | L45: Completed
A46: =IF(B46="","",SUBTOTAL(3,$B$11:B46)) -> 36 | B46: AP-28/0 - AP-29/0 | C46: 211.21 | D46: Manual | E46: Exp-Way | F46: 1 | G46: 1 | H46: =F46-G46 -> 0 | I46: 1 | J46: =F46-I46 -> 0 | K46: Feb'26
A47: =IF(B47="","",SUBTOTAL(3,$B$11:B47)) -> 37 | B47: AP-29/0 - AP-29A/0 | C47: 2379.204 | D47: TSE | F47: 6 | G47: 6 | H47: =F47-G47 -> 0 | I47: 6 | J47: =F47-I47 -> 0 | K47: Feb'26 | L47: Completed
A48: =IF(B48="","",SUBTOTAL(3,$B$11:B48)) -> 38 | B48: AP-29A/0 - AP-30/0 | C48: 2669.008 | D48: TSE | F48: 7 | G48: 7 | H48: =F48-G48 -> 0 | I48: 7 | J48: =F48-I48 -> 0 | K48: Feb'26 | L48: Completed
A49: =IF(B49="","",SUBTOTAL(3,$B$11:B49)) -> 39 | B49: AP-30/0 - AP-31/0 | C49: 4124.232 | D49: TSE | F49: 11 | G49: 11 | H49: =F49-G49 -> 0 | I49: 11 | J49: =F49-I49 -> 0 | K49: Feb'26 | L49: Completed | M49: Stringing for stringing
A50: =IF(B50="","",SUBTOTAL(3,$B$11:B50)) -> 40 | B50: AP-31/0 - AP-32/0 | C50: 4333.369 | D50: TSE | F50: 11 | G50: 11 | H50: =F50-G50 -> 0 | I50: 11 | J50: =F50-I50 -> 0 | K50: Jan'26 | L50: Completed | M50: Stringing for stringing
A51: =IF(B51="","",SUBTOTAL(3,$B$11:B51)) -> 41 | B51: AP-32/0 - AP-32A/0 | C51: 3283.51 | D51: TSE | F51: 8 | G51: 8 | H51: =F51-G51 -> 0 | I51: 8 | J51: =F51-I51 -> 0 | K51: Jan'26 | L51: Completed | M51: Stringing for stringing
A52: =IF(B52="","",SUBTOTAL(3,$B$11:B52)) -> 42 | B52: AP-32A/0 - AP-33/0 | C52: 840.439 | D52: TSE | F52: 2 | G52: 2 | H52: =F52-G52 -> 0 | I52: 2 | J52: =F52-I52 -> 0 | K52: Jan'26 | L52: Completed | M52: Stringing for stringing
A53: =IF(B53="","",SUBTOTAL(3,$B$11:B53)) -> 43 | B53: AP-33/0 - AP-34/0 | C53: 4049.763 | D53: TSE | F53: 10 | G53: 10 | H53: =F53-G53 -> 0 | I53: 10 | J53: =F53-I53 -> 0 | K53: Jan'26 | L53: Completed | M53: Stringing for stringing
A54: =IF(B54="","",SUBTOTAL(3,$B$11:B54)) -> 44 | B54: AP-34/0 - AP-35/0 | C54: 4898.588 | D54: TSE | F54: 13 | G54: 13 | H54: =F54-G54 -> 0 | I54: 13 | J54: =F54-I54 -> 0 | K54: comp | L54: Completed
A55: =IF(B55="","",SUBTOTAL(3,$B$11:B55)) -> 45 | B55: AP-35/0 - AP-36/0 | C55: 4916.293 | D55: TSE | F55: 12 | G55: 12 | H55: =F55-G55 -> 0 | I55: 12 | J55: =F55-I55 -> 0 | K55: mar'26 | L55: Ready for stringing
A56: =IF(B56="","",SUBTOTAL(3,$B$11:B56)) -> 46 | B56: AP-36/0 - AP-36A/0 | C56: 454 | D56: Manual | F56: 1 | G56: 1 | H56: =F56-G56 -> 0 | I56: 1 | J56: =F56-I56 -> 0 | K56: mar'26
A57: =IF(B57="","",SUBTOTAL(3,$B$11:B57)) -> 47 | B57: AP-36A/0 - AP 36B/0 | C57: 826.7 | D57: TSE | F57: 2 | G57: 2 | H57: =F57-G57 -> 0 | I57: 1 | J57: =F57-I57 -> 1 | K57: mar'26
A58: =IF(B58="","",SUBTOTAL(3,$B$11:B58)) -> 48 | B58: AP-36B/0 - AP-N37/0 | C58: 420.81 | D58: Manual | F58: 1 | G58: 1 | H58: =F58-G58 -> 0 | I58: 0 | J58: =F58-I58 -> 1 | K58: mar'26
A59: =IF(B59="","",SUBTOTAL(3,$B$11:B59)) -> 49 | B59: AP-N37/0 - AP-N37A/0 | C59: 469.33 | D59: Manual | F59: 1 | G59: 1 | H59: =F59-G59 -> 0 | I59: 0 | J59: =F59-I59 -> 1
A60: =IF(B60="","",SUBTOTAL(3,$B$11:B60)) -> 50 | B60: AP-N37A/0 - AP-37A/0 | C60: 2076.28 | D60: TSE | F60: 5 | G60: 5 | H60: =F60-G60 -> 0 | I60: 5 | J60: =F60-I60 -> 0 | K60: comp
A61: =IF(B61="","",SUBTOTAL(3,$B$11:B61)) -> 51 | B61: AP-37A/0 - AP-38/0 | C61: 2583.589 | D61: TSE | F61: 7 | G61: 7 | H61: =F61-G61 -> 0 | I61: 7 | J61: =F61-I61 -> 0 | L61: Completed
A62: =IF(B62="","",SUBTOTAL(3,$B$11:B62)) -> 52 | B62: AP-38/0 - AP-39/0 | C62: 4163.677 | D62: TSE | F62: 11 | G62: 11 | H62: =F62-G62 -> 0 | I62: 11 | J62: =F62-I62 -> 0 | K62: comp | L62: Completed
A63: =IF(B63="","",SUBTOTAL(3,$B$11:B63)) -> 53 | B63: AP-39/0 - AP-40/0 | C63: 4716.811 | D63: TSE | F63: 12 | G63: 12 | H63: =F63-G63 -> 0 | I63: 12 | J63: =F63-I63 -> 0 | K63: comp | L63: Completed
A64: =IF(B64="","",SUBTOTAL(3,$B$11:B64)) -> 54 | B64: AP-40/0 - AP-40A/0 | C64: 4665.918 | D64: TSE | F64: 12 | G64: 12 | H64: =F64-G64 -> 0 | I64: 12 | J64: =F64-I64 -> 0 | K64: mar'26 | M64: Stringing for stringing
A65: =IF(B65="","",SUBTOTAL(3,$B$11:B65)) -> 55 | B65: AP-40A/0 - AP-41/0 | C65: 410.61 | D65: Manual | F65: 1 | G65: 1 | H65: =F65-G65 -> 0 | I65: 1 | J65: =F65-I65 -> 0 | K65: mar'26
A66: =IF(B66="","",SUBTOTAL(3,$B$11:B66)) -> 56 | B66: AP-41/0 - AP-42/0 | C66: 823.782 | D66: TSE | F66: 2 | G66: 2 | H66: =F66-G66 -> 0 | I66: 2 | J66: =F66-I66 -> 0 | K66: mar'26
A67: =IF(B67="","",SUBTOTAL(3,$B$11:B67)) -> 57 | B67: AP-42/0 - AP-42/3 | C67: 1258.998 | D67: TSE | F67: 3 | G67: 3 | H67: =F67-G67 -> 0 | I67: 3 | J67: =F67-I67 -> 0 | K67: mar'26
A68: =IF(B68="","",SUBTOTAL(3,$B$11:B68)) -> 58 | B68: AP-42/3 - AP-43/0 | C68: 424.891 | D68: Manual | F68: 1 | G68: 1 | H68: =F68-G68 -> 0 | I68: 1 | J68: =F68-I68 -> 0 | K68: mar'26
A69: =IF(B69="","",SUBTOTAL(3,$B$11:B69)) -> 59 | B69: AP-43/0 - AP-43/5 | C69: 1851.866 | D69: TSE | F69: 5 | G69: 5 | H69: =F69-G69 -> 0 | I69: 5 | J69: =F69-I69 -> 0 | K69: mar'26
A70: =IF(B70="","",SUBTOTAL(3,$B$11:B70)) -> 60 | B70: AP-43/5-AP-44/0 | C70: 1584.546 | D70: TSE | F70: 4 | G70: 4 | H70: =F70-G70 -> 0 | I70: 4 | J70: =F70-I70 -> 0 | K70: Feb'26
A71: =IF(B71="","",SUBTOTAL(3,$B$11:B71)) -> 61 | B71: AP-44/0-AP45/0 | C71: 2383.155 | D71: TSE | F71: 6 | G71: 6 | H71: =F71-G71 -> 0 | I71: 6 | J71: =F71-I71 -> 0 | K71: Feb'26
A72: =IF(B72="","",SUBTOTAL(3,$B$11:B72)) -> 62 | B72: AP-45/0-AP-46/0 | C72: 208.53 | D72: Manual | F72: 1 | G72: 1 | H72: =F72-G72 -> 0 | I72: 1 | J72: =F72-I72 -> 0 | K72: Feb'26
C73: =SUM(C11:C72)/1000 -> 117.85605 | F73: =SUM(F11:F72) -> 306 | G73: =SUM(G11:G72) -> 306 | H73: =SUM(H11:H72) -> 0 | I73: =SUM(I11:I72) -> 302 | J73: =SUM(J11:J72) -> 4
A74: Sl no. | B74: Type | C74: Total Length (Km) | G74: =G73+7 -> 313
A75: 1 | B75: TSE | C75: =SUMIF(D11:D72,B75,C11:C72)/1000 -> 109.28516
A76: 2 | B76: Manual | C76: =SUMIF(D11:D72,B76,C11:C72)/1000 -> 8.570895
A77: Total=>> | C77: =C76+C75 -> 117.85605
A80: Description | B80: Stringing Type | C80: Line length | D80: TSE/Manual Completed | E80: Line length | F80: Balance Section | G80: Balance(km)
A81: TSE | B81: 37 | C81: 110.1701 | D81: 21 | E81: 70.083008 | F81: =B81-D81 -> 16 | G81: =C81-E81 -> 40.087088
A82: Manual | B82: 25 | C82: 7.680735 | D82: 3 | E82: 1.17632 | F82: =B82-D82 -> 22 | G82: =C82-E82 -> 6.504415
A83: Stringing | B83: =SUBTOTAL(9,B81:B82) -> 62 | C83: =SUBTOTAL(9,C81:C82) -> 117.85083 | D83: =SUBTOTAL(9,D81:D82) -> 24 | E83: =SUBTOTAL(9,E81:E82) -> 71.259328 | F83: =SUBTOTAL(9,F81:F82) -> 38 | G83: =SUBTOTAL(9,G81:G82) -> 46.591503
N298: Ved

Sheet Erection
A1: KEC International Limited
A2: TA413 : 765 KV D/C Bikaner III - Neemrana II TL02
A3: Details of Erection | H3: =SUBTOTAL(9,H5:H307) -> 14162.896 | I3: =SUBTOTAL(9,I5:I307) -> 1319.5343 | K3: =TA413_PBNTL!M1 -> 27.05.2026
A4: CUMM. SR.NO | B4: MONTH SR.NO. | C4: Loc. No. | D4: Type of Tower | E4: Start | F4: Complete | G4: Gang name | H4: Weight | I4: Revenue | J4: Name of Supervisor | K4: Remarks | L4: JMC Status
A5: 1 | B5: 1 | C5: 29A/2 | D5: =IFERROR(VLOOKUP(C5,Foundation!$C$5:$D$554,2,0),"") -> DA+6 | E5: 45547 | F5: 45556 | G5: Bhagwan construction | H5: =VLOOKUP(D5,$D$313:$I$342,6,0) -> 43.804424 | I5: =IFERROR(VLOOKUP(D5,$D$313:$K$342,8,0)/10^5,"") -> 4.0811881 | J5: Manoj Kumar Gupta | K5: Completed | L5: Received
A6: =A5+1 -> 2 | B6: 2 | C6: 29/5 | D6: =IFERROR(VLOOKUP(C6,Foundation!$C$5:$D$554,2,0),"") -> DA+0 | E6: =F5 -> 45556 | F6: 45562 | G6: Bhagwan construction | H6: =VLOOKUP(D6,$D$313:$I$342,6,0) -> 36.159756 | I6: =IFERROR(VLOOKUP(D6,$D$313:$K$342,8,0)/10^5,"") -> 3.3689466 | J6: Manoj Kumar Gupta | K6: Completed | L6: Received
A7: =A6+1 -> 3 | B7: 1 | C7: 29/3 | D7: =IFERROR(VLOOKUP(C7,Foundation!$C$5:$D$554,2,0),"") -> DA+0 | E7: =F6+1 -> 45563 | F7: 45568 | G7: Bhagwan construction | H7: =VLOOKUP(D7,$D$313:$I$342,6,0) -> 36.159756 | I7: =IFERROR(VLOOKUP(D7,$D$313:$K$342,8,0)/10^5,"") -> 3.3689466 | J7: Manoj Kumar Gupta | K7: Completed | L7: Received
A8: =A7+1 -> 4 | B8: 2 | C8: 29/4 | D8: =IFERROR(VLOOKUP(C8,Foundation!$C$5:$D$554,2,0),"") -> DA+3 | E8: 45568 | F8: 45573 | G8: Bhagwan construction | H8: =VLOOKUP(D8,$D$313:$I$342,6,0) -> 37.931088 | I8: =IFERROR(VLOOKUP(D8,$D$313:$K$342,8,0)/10^5,"") -> 3.5339788 | J8: Manoj Kumar Gupta | K8: Completed | L8: Received
A9: =A8+1 -> 5 | B9: 3 | C9: 29A/6 | D9: =IFERROR(VLOOKUP(C9,Foundation!$C$5:$D$554,2,0),"") -> DA+9 | E9: 45568 | F9: 45579 | G9: Bhagwan construction | H9: =VLOOKUP(D9,$D$313:$I$342,6,0) -> 45.697022 | I9: =IFERROR(VLOOKUP(D9,$D$313:$K$342,8,0)/10^5,"") -> 4.2575184 | J9: Manoj Kumar Gupta | K9: Completed | L9: Received
A10: =A9+1 -> 6 | B10: 4 | C10: 30/1 | D10: =IFERROR(VLOOKUP(C10,Foundation!$C$5:$D$554,2,0),"") -> DA+0 | E10: 45574 | F10: 45582 | G10: Bhagwan construction | H10: =VLOOKUP(D10,$D$313:$I$342,6,0) -> 36.159756 | I10: =IFERROR(VLOOKUP(D10,$D$313:$K$342,8,0)/10^5,"") -> 3.3689466 | J10: Kartik Mahto | K10: Completed | L10: Received
A11: =A10+1 -> 7 | B11: 5 | C11: 29A/1 | D11: =IFERROR(VLOOKUP(C11,Foundation!$C$5:$D$554,2,0),"") -> DA+6 | E11: =F9 -> 45579 | F11: 45590 | G11: Bhagwan construction | H11: =VLOOKUP(D11,$D$313:$I$342,6,0) -> 43.804424 | I11: =IFERROR(VLOOKUP(D11,$D$313:$K$342,8,0)/10^5,"") -> 4.0811881 | J11: Manoj Kumar Gupta | K11: Completed | L11: Received
A12: =A11+1 -> 8 | B12: 1 | C12: 34/8 | D12: =IFERROR(VLOOKUP(C12,Foundation!$C$5:$D$554,2,0),"") -> DA+0 | E12: 45608 | F12: 45620 | G12: Vasu dev singh-1 | H12: =VLOOKUP(D12,$D$313:$I$342,6,0) -> 36.159756 | I12: =IFERROR(VLOOKUP(D12,$D$313:$K$342,8,0)/10^5,"") -> 3.3689466 | J12: Raju Mahto | K12: Completed | L12: Received
A13: =A12+1 -> 9 | B13: 2 | C13: 34/12 | D13: =IFERROR(VLOOKUP(C13,Foundation!$C$5:$D$554,2,0),"") -> DA+3 | E13: 45610 | F13: 45621 | G13: Vasu dev singh-2 | H13: =VLOOKUP(D13,$D$313:$I$342,6,0) -> 37.931088 | I13: =IFERROR(VLOOKUP(D13,$D$313:$K$342,8,0)/10^5,"") -> 3.5339788 | J13: Mustak | K13: Completed | L13: Received
A14: =A13+1 -> 10 | B14: 1 | C14: 34/4 | D14: =IFERROR(VLOOKUP(C14,Foundation!$C$5:$D$554,2,0),"") -> DA+6 | E14: 45621 | F14: 45630 | G14: Vasu dev singh-1 | H14: =VLOOKUP(D14,$D$313:$I$342,6,0) -> 43.804424 | I14: =IFERROR(VLOOKUP(D14,$D$313:$K$342,8,0)/10^5,"") -> 4.0811881 | J14: Raju Mahto | K14: Completed | L14: Received
A15: =A14+1 -> 11 | B15: 2 | C15: 34/7 | D15: =IFERROR(VLOOKUP(C15,Foundation!$C$5:$D$554,2,0),"") -> DA+0 | E15: 45622 | F15: 45638 | G15: Vasu dev singh-2 | H15: =VLOOKUP(D15,$D$313:$I$342,6,0) -> 36.159756 | I15: =IFERROR(VLOOKUP(D15,$D$313:$K$342,8,0)/10^5,"") -> 3.3689466 | J15: Raju Mahto | K15: Completed | L15: Received
A16: =A15+1 -> 12 | B16: 3 | C16: 34/3 | D16: =IFERROR(VLOOKUP(C16,Foundation!$C$5:$D$554,2,0),"") -> DA+1.5 | E16: 45631 | F16: 45642 | G16: Vasu dev singh-1 | H16: =VLOOKUP(D16,$D$313:$I$342,6,0) -> 37.138324 | I16: =IFERROR(VLOOKUP(D16,$D$313:$K$342,8,0)/10^5,"") -> 3.4601182 | J16: Manoj Kumar Gupta | K16: Completed | L16: Received
A17: =A16+1 -> 13 | B17: 4 | C17: 8/1 | D17: =IFERROR(VLOOKUP(C17,Foundation!$C$5:$D$554,2,0),"") -> DA-3 | E17: 45633 | F17: 45642 | G17: Punam Devi-2 | H17: =VLOOKUP(D17,$D$313:$I$342,6,0) -> 34.78981 | I17: =IFERROR(VLOOKUP(D17,$D$313:$K$342,8,0)/10^5,"") -> 3.2413109 | J17: Sanjay Kumar | K17: Completed | L17: Received
A18: =A17+1 -> 14 | B18: 5 | C18: 34/9 | D18: =IFERROR(VLOOKUP(C18,Foundation!$C$5:$D$554,2,0),"") -> DA+1.5 | E18: 45639 | F18: 45647 | G18: Vasu dev singh-2 | H18: =VLOOKUP(D18,$D$313:$I$342,6,0) -> 37.138324 | I18: =IFERROR(VLOOKUP(D18,$D$313:$K$342,8,0)/10^5,"") -> 3.4601182 | J18: Mustak & Abul | K18: Completed | L18: Received
A19: =A18+1 -> 15 | B19: 6 | C19: 35/7 | D19: =IFERROR(VLOOKUP(C19,Foundation!$C$5:$D$554,2,0),"") -> DA+3 | E19: 45639 | F19: 45648 | G19: Punam Devi-2 | H19: =VLOOKUP(D19,$D$313:$I$342,6,0) -> 37.931088 | I19: =IFERROR(VLOOKUP(D19,$D$313:$K$342,8,0)/10^5,"") -> 3.5339788 | J19: Kartik Mahto | K19: Completed | L19: Received
A20: =A19+1 -> 16 | B20: 7 | C20: 7A/5 | D20: =IFERROR(VLOOKUP(C20,Foundation!$C$5:$D$554,2,0),"") -> DA+3 | E20: 45643 | F20: 45650 | G20: Punam Devi-2 | H20: =VLOOKUP(D20,$D$313:$I$342,6,0) -> 37.931088 | I20: =IFERROR(VLOOKUP(D20,$D$313:$K$342,8,0)/10^5,"") -> 3.5339788 | J20: Sanjay Kumar | K20: Completed | L20: Received
A21: =A20+1 -> 17 | B21: 8 | C21: 36A/1 | D21: =IFERROR(VLOOKUP(C21,Foundation!$C$5:$D$554,2,0),"") -> DA+3 | E21: 45639 | F21: 45651 | G21: Punam Devi-3 | H21: =VLOOKUP(D21,$D$313:$I$342,6,0) -> 37.931088 | I21: =IFERROR(VLOOKUP(D21,$D$313:$K$342,8,0)/10^5,"") -> 3.5339788 | J21: Haridas | K21: Completed | L21: Received
A22: =A21+1 -> 18 | B22: 9 | C22: 7/1 | D22: =IFERROR(VLOOKUP(C22,Foundation!$C$5:$D$554,2,0),"") -> DA-3 | E22: 45641 | F22: 45652 | G22: Punam Devi-1 | H22: =VLOOKUP(D22,$D$313:$I$342,6,0) -> 34.78981 | I22: =IFERROR(VLOOKUP(D22,$D$313:$K$342,8,0)/10^5,"") -> 3.2413109 | J22: Raju Mahto | K22: Completed | L22: Received
A23: =A22+1 -> 19 | B23: 10 | C23: 35/8 | D23: =IFERROR(VLOOKUP(C23,Foundation!$C$5:$D$554,2,0),"") -> DA+6 | E23: 45649 | F23: 45654 | G23: Punam Devi-2 | H23: =VLOOKUP(D23,$D$313:$I$342,6,0) -> 43.804424 | I23: =IFERROR(VLOOKUP(D23,$D$313:$K$342,8,0)/10^5,"") -> 4.0811881 | J23: Kartik Mahto | K23: Completed | L23: Received
... A44: =A43+1 -> 40 | B44: 18 | C44: 35/9 | D44: =IFERROR(VLOOKUP(C44,Foundation!$C$5:$D$554,2,0),"") -> DA+1.5 | E44: 45674 | F44: 45681 | G44: Punam Devi-2 | H44: =VLOOKUP(D44,$D$313:$I$342,6,0) -> 37.138324 | I44: =IFERROR(VLOOKUP(D44,$D$313:$K$342,8,0)/10^5,"") -> 3.4601182 | J44: Kartik Mahto | K44: Completed | L44: Received
A45: =A44+1 -> 41 | B45: 19 | C45: 8/8 | D45: =IFERROR(VLOOKUP(C45,Foundation!$C$5:$D$554,2,0),"") -> DA+9 | E45: =F40 -> 45677 | F45: 45682 | G45: Punam Devi-1 | H45: =VLOOKUP(D45,$D$313:$I$342,6,0) -> 45.697022 | I45: =IFERROR(VLOOKUP(D45,$D$313:$K$342,8,0)/10^5,"") -> 4.2575184 | J45: Gangadin sahoo | K45: Completed | L45: Received
A46: =A45+1 -> 42 | B46: 20 | C46: 34/1 | D46: =IFERROR(VLOOKUP(C46,Foundation!$C$5:$D$554,2,0),"") -> DA+9 | E46: =F41 -> 45678 | F46: 45686 | G46: Vasu dev singh-1 | H46: =VLOOKUP(D46,$D$313:$I$342,6,0) -> 45.697022 | I46: =IFERROR(VLOOKUP(D46,$D$313:$K$342,8,0)/10^5,"") -> 4.2575184 | J46: Manoj Kumar Gupta | K46: Completed | L46: Received
A47: =A46+1 -> 43 | B47: 21 | C47: 38/3 | D47: =IFERROR(VLOOKUP(C47,Foundation!$C$5:$D$554,2,0),"") -> DA+3 | E47: 45681 | F47: 45686 | G47: Punam Devi-2 | H47: =VLOOKUP(D47,$D$313:$I$342,6,0) -> 37.931088 | I47: =IFERROR(VLOOKUP(D47,$D$313:$K$342,8,0)/10^5,"") -> 3.5339788 | J47: Kartik Mahto | K47: Completed | L47: Received
A48: =A47+1 -> 44 | B48: 22 | C48: 8/9 | D48: =IFERROR(VLOOKUP(C48,Foundation!$C$5:$D$554,2,0),"") -> DA+3 | E48: 45682 | F48: 45687 | G48: Punam Devi-4 | H48: =VLOOKUP(D48,$D$313:$I$342,6,0) -> 37.931088 | I48: =IFERROR(VLOOKUP(D48,$D$313:$K$342,8,0)/10^5,"") -> 3.5339788 | J48: Gangadin sahoo | K48: Completed | L48: Received
A49: =A48+1 -> 45 | B49: 23 | C49: 37/5 | D49: =IFERROR(VLOOKUP(C49,Foundation!$C$5:$D$554,2,0),"") -> DA+3 | E49: =F42 -> 45679 | F49: 45687 | G49: Punam Devi-3 | H49: =VLOOKUP(D49,$D$313:$I$342,6,0) -> 37.931088 | I49: =IFERROR(VLOOKUP(D49,$D$313:$K$342,8,0)/10^5,"") -> 3.5339788 | J49: Haridas | K49: Completed | L49: Received
A50: =A49+1 -> 46 | B50: 24 | C50: 7A/0 | D50: =IFERROR(VLOOKUP(C50,Foundation!$C$5:$D$554,2,0),"") -> DB1+6 | E50: =F43 -> 45679 | F50: 45688 | G50: Punam Devi-2 | H50: =VLOOKUP(D50,$D$313:$I$342,6,0) -> 65.027779 | I50: =IFERROR(VLOOKUP(D50,$D$313:$K$342,8,0)/10^5,"") -> 6.0585341 | J50: Raju Mahto | K50: Completed | L50: Received
A51: =A50+1 -> 47 | B51: 25 | C51: 34/0 | D51: =IFERROR(VLOOKUP(C51,Foundation!$C$5:$D$554,2,0),"") -> DB1+6 | E51: 45674 | F51: 45688 | G51: Vasu dev singh-1 | H51: =VLOOKUP(D51,$D$313:$I$342,6,0) -> 65.027779 | I51: =IFERROR(VLOOKUP(D51,$D$313:$K$342,8,0)/10^5,"") -> 6.0585341 | J51: Mustak & Abul | K51: Completed | L51: Received
A52: =A51+1 -> 48 | B52: 1 | C52: 8/10 | D52: =IFERROR(VLOOKUP(C52,Foundation!$C$5:$D$554,2,0),"") -> DA+0 | E52: 45687 | F52: 45691 | G52: Punam Devi-4 | H52: =VLOOKUP(D52,$D$313:$I$342,6,0) -> 36.159756 | I52: =IFERROR(VLOOKUP(D52,$D$313:$K$342,8,0)/10^5,"") -> 3.3689466 | J52: Gangadin sahoo | K52: Completed | L52: Received
A53: =A52+1 -> 49 | B53: 2 | C53: 38/6 | D53: =IFERROR(VLOOKUP(C53,Foundation!$C$5:$D$554,2,0),"") -> DA+6 | E53: 45686 | F53: 45692 | G53: Punam Devi-1 | H53: =VLOOKUP(D53,$D$313:$I$342,6,0) -> 43.804424 | I53: =IFERROR(VLOOKUP(D53,$D$313:$K$342,8,0)/10^5,"") -> 4.0811881 | J53: Kartik Mahto | K53: Completed | L53: Received
A54: =A53+1 -> 50 | B54: 3 | C54: 37A/2 | D54: =IFERROR(VLOOKUP(C54,Foundation!$C$5:$D$554,2,0),"") -> DA+1.5 | E54: 45686 | F54: 45695 | G54: Punam Devi-3 | H54: =VLOOKUP(D54,$D$313:$I$342,6,0) -> 37.138324 | I54: =IFERROR(VLOOKUP(D54,$D$313:$K$342,8,0)/10^5,"") -> 3.4601182 | J54: Haridas | K54: Completed | L54: Received
A55: =A54+1 -> 51 | B55: 4 | C55: 33/6 | D55: =IFERROR(VLOOKUP(C55,Foundation!$C$5:$D$554,2,0),"") -> DA+6 | E55: 45686 | F55: 45696 | G55: Vasu dev singh-2 | H55: =VLOOKUP(D55,$D$313:$I$342,6,0) -> 43.804424 | I55: =IFERROR(VLOOKUP(D55,$D$313:$K$342,8,0)/10^5,"") -> 4.0811881 | J55: Manoj Kumar Gupta | K55: Completed | L55: Received
A56: =A55+1 -> 52 | B56: 5 | C56: 8/2 | D56: =IFERROR(VLOOKUP(C56,Foundation!$C$5:$D$554,2,0),"") -> DA+6 | E56: 45691 | F56: 45696 | G56: Punam Devi-4 | H56: =VLOOKUP(D56,$D$313:$I$342,6,0) -> 43.804424 | I56: =IFERROR(VLOOKUP(D56,$D$313:$K$342,8,0)/10^5,"") -> 4.0811881 | J56: Gangadin sahoo | K56: Completed | L56: Received
A57: =A56+1 -> 53 | B57: 6 | C57: 7/6 | D57: =IFERROR(VLOOKUP(C57,Foundation!$C$5:$D$554,2,0),"") -> DA-1.5 | E57: 45688 | F57: 45698 | G57: Punam Devi-2 | H57: =VLOOKUP(D57,$D$313:$I$342,6,0) -> 35.601762 | I57: =IFERROR(VLOOKUP(D57,$D$313:$K$342,8,0)/10^5,"") -> 3.3169592 | J57: Raju Mahto | K57: Completed | L57: Received
A58: =A57+1 -> 54 | B58: 7 | C58: 38/4 | D58: =IFERROR(VLOOKUP(C58,Foundation!$C$5:$D$554,2,0),"") -> DA+1.5 | E58: 45693 | F58: 45698 | G58: Punam Devi-1 | H58: =VLOOKUP(D58,$D$313:$I$342,6,0) -> 37.138324 | I58: =IFERROR(VLOOKUP(D58,$D$313:$K$342,8,0)/10^5,"") -> 3.4601182 | J58: Kartik Mahto | K58: Completed | L58: Received
A59: =A58+1 -> 55 | B59: 8 | C59: 8/0 | D59: =IFERROR(VLOOKUP(C59,Foundation!$C$5:$D$554,2,0),"") -> DB1+0 | E59: 45697 | F59: 45702 | G59: Punam Devi-4 | H59: =VLOOKUP(D59,$D$313:$I$342,6,0) -> 55.450851 | I59: =IFERROR(VLOOKUP(D59,$D$313:$K$342,8,0)/10^5,"") -> 5.1662671 | J59: Gangadin sahoo | K59: Completed | L59: Received
A60: =A59+1 -> 56 | B60: 9 | C60: 38/5 | D60: =IFERROR(VLOOKUP(C60,Foundation!$C$5:$D$554,2,0),"") -> DA+3 | E60: 45699 | F60: 45703 | G60: Punam Devi-1 | H60: =VLOOKUP(D60,$D$313:$I$342,6,0) -> 37.931088 | I60: =IFERROR(VLOOKUP(D60,$D$313:$K$342,8,0)/10^5,"") -> 3.5339788 | J60: Kartik Mahto | K60: Completed | L60: Received
A61: =A60+1 -> 57 | B61: 10 | C61: 37A/1 | D61: =IFERROR(VLOOKUP(C61,Foundation!$C$5:$D$554,2,0),"") -> DA+3 | E61: 45696 | F61: 45704 | G61: Punam Devi-3 | H61: =VLOOKUP(D61,$D$313:$I$342,6,0) -> 37.931088 | I61: =IFERROR(VLOOKUP(D61,$D$313:$K$342,8,0)/10^5,"") -> 3.5339788 | J61: Haridas | K61: Completed | L61: Received
A62: =A61+1 -> 58 | B62: 11 | C62: 33/5 | D62: =IFERROR(VLOOKUP(C62,Foundation!$C$5:$D$554,2,0),"") -> DA+0 | E62: 45688 | F62: 45706 | G62: Vasu dev singh-1 | H62: =VLOOKUP(D62,$D$313:$I$342,6,0) -> 36.159756 | I62: =IFERROR(VLOOKUP(D62,$D$313:$K$342,8,0)/10^5,"") -> 3.3689466 | J62: Mustak & Abul | K62: Completed | L62: Received
... A72: =A71+1 -> 68 | B72: 21 | C72: 37A/5 | D72: =IFERROR(VLOOKUP(C72,Foundation!$C$5:$D$554,2,0),"") -> DA+3 | E72: 45712 | F72: 45716 | G72: Punam Devi-1 | H72: =VLOOKUP(D72,$D$313:$I$342,6,0) -> 37.931088 | I72: =IFERROR(VLOOKUP(D72,$D$313:$K$342,8,0)/10^5,"") -> 3.5339788 | J72: Prabhakar | K72: Completed | L72: Received
A73: =A72+1 -> 69 | B73: 1 | C73: 33/8 | D73: =IFERROR(VLOOKUP(C73,Foundation!$C$5:$D$554,2,0),"") -> DA+3 | E73: =F62 -> 45706 | F73: 45720 | G73: Vasu dev singh-1 | H73: =VLOOKUP(D73,$D$313:$I$342,6,0) -> 37.931088 | I73: =IFERROR(VLOOKUP(D73,$D$313:$K$342,8,0)/10^5,"") -> 3.5339788 | J73: Kartik Mahto | K73: Completed | L73: Received
A74: =A73+1 -> 70 | B74: 2 | C74: 9/3 | D74: =IFERROR(VLOOKUP(C74,Foundation!$C$5:$D$554,2,0),"") -> DA+0 | E74: =F71+1 -> 45717 | F74: 45720 | G74: Punam Devi-4 | H74: =VLOOKUP(D74,$D$313:$I$342,6,0) -> 36.159756 | I74: =IFERROR(VLOOKUP(D74,$D$313:$K$342,8,0)/10^5,"") -> 3.3689466 | J74: Raju Mahto | K74: Completed | L74: Received
A75: =A74+1 -> 71 | B75: 3 | C75: 38/1 | D75: =IFERROR(VLOOKUP(C75,Foundation!$C$5:$D$554,2,0),"") -> DA+0 | E75: =F72+1 -> 45717 | F75: 45722 | G75: Punam Devi-1 | H75: =VLOOKUP(D75,$D$313:$I$342,6,0) -> 36.159756 | I75: =IFERROR(VLOOKUP(D75,$D$313:$K$342,8,0)/10^5,"") -> 3.3689466 | J75: Prabhakar | K75: Completed | L75: Received
A76: =A75+1 -> 72 | B76: 4 | C76: 37A/4 | D76: =IFERROR(VLOOKUP(C76,Foundation!$C$5:$D$554,2,0),"") -> DA+9 | E76: =F69 -> 45713 | F76: 45722 | G76: Punam Devi-3 | H76: =VLOOKUP(D76,$D$313:$I$342,6,0) -> 45.697022 | I76: =IFERROR(VLOOKUP(D76,$D$313:$K$342,8,0)/10^5,"") -> 4.2575184 | J76: Haridas | K76: Completed | L76: Received
A77: =A76+1 -> 73 | B77: 5 | C77: 37A/6 | D77: =IFERROR(VLOOKUP(C77,Foundation!$C$5:$D$554,2,0),"") -> DA+3 | E77: =F66+1 -> 45712 | F77: 45724 | G77: Vasu dev singh-2 | H77: =VLOOKUP(D77,$D$313:$I$342,6,0) -> 37.931088 | I77: =IFERROR(VLOOKUP(D77,$D$313:$K$342,8,0)/10^5,"") -> 3.5339788 | J77: Prabhakar | K77: Completed | L77: Received
A78: =A77+1 -> 74 | B78: 6 | C78: 9/4 | D78: =IFERROR(VLOOKUP(C78,Foundation!$C$5:$D$554,2,0),"") -> DA+6 | E78: =F74+1 -> 45721 | F78: 45725 | G78: Punam Devi-4 | H78: =VLOOKUP(D78,$D$313:$I$342,6,0) -> 43.804424 | I78: =IFERROR(VLOOKUP(D78,$D$313:$K$342,8,0)/10^5,"") -> 4.0811881 | J78: Gangadin sahoo | K78: Completed | L78: Received
A79: =A78+1 -> 75 | B79: 7 | C79: 37A/0 | D79: =IFERROR(VLOOKUP(C79,Foundation!$C$5:$D$554,2,0),"") -> DB1+0 | E79: =F70+1 -> 45716 | F79: 45727 | G79: Punam Devi-2 | H79: =VLOOKUP(D79,$D$313:$I$342,6,0) -> 55.450851 | I79: =IFERROR(VLOOKUP(D79,$D$313:$K$342,8,0)/10^5,"") -> 5.1662671 | J79: Kartik Mahto | K79: Completed | L79: Received
A80: =A79+1 -> 76 | B80: 8 | C80: 38/2 | D80: =IFERROR(VLOOKUP(C80,Foundation!$C$5:$D$554,2,0),"") -> DA+0 | E80: =F75+1 -> 45723 | F80: 45727 | G80: Punam Devi-1 | H80: =VLOOKUP(D80,$D$313:$I$342,6,0) -> 36.159756 | I80: =IFERROR(VLOOKUP(D80,$D$313:$K$342,8,0)/10^5,"") -> 3.3689466 | J80: Manoj Kumar Gupta | K80: Completed | L80: Received
A81: =A80+1 -> 77 | B81: 9 | C81: 39/7 | D81: =IFERROR(VLOOKUP(C81,Foundation!$C$5:$D$554,2,0),"") -> DA+3 | E81: =F76+1 -> 45723 | F81: 45729 | G81: Punam Devi-3 | H81: =VLOOKUP(D81,$D$313:$I$342,6,0) -> 37.931088 | I81: =IFERROR(VLOOKUP(D81,$D$313:$K$342,8,0)/10^5,"") -> 3.5339788 | J81: Haridas | K81: Completed | L81: Received
A82: =A81+1 -> 78 | B82: 10 | C82: 9/2 | D82: =IFERROR(VLOOKUP(C82,Foundation!$C$5:$D$554,2,0),"") -> DA+3 | E82: =F78+1 -> 45726 | F82: 45729 | G82: Punam Devi-4 | H82: =VLOOKUP(D82,$D$313:$I$342,6,0) -> 37.931088 | I82: =IFERROR(VLOOKUP(D82,$D$313:$K$342,8,0)/10^5,"") -> 3.5339788 | J82: Gangadin sahoo | K82: Completed | L82: Received
A83: =A82+1 -> 79 | B83: 11 | C83: 15/2 | D83: =IFERROR(VLOOKUP(C83,Foundation!$C$5:$D$554,2,0),"") -> DA+3 | E83: =F82+1 -> 45730 | F83: 45734 | G83: Punam Devi-4 | H83: =VLOOKUP(D83,$D$313:$I$342,6,0) -> 37.931088 | I83: =IFERROR(VLOOKUP(D83,$D$313:$K$342,8,0)/10^5,"") -> 3.5339788 | J83: Gangadin sahoo | K83: Completed | L83: Received
A84: =A83+1 -> 80 | B84: 12 | C84: 38/7 | D84: =IFERROR(VLOOKUP(C84,Foundation!$C$5:$D$554,2,0),"") -> DA+9 | E84: =F80+1 -> 45728 | F84: 45734 | G84: Punam Devi-1 | H84: =VLOOKUP(D84,$D$313:$I$342,6,0) -> 45.697022 | I84: =IFERROR(VLOOKUP(D84,$D$313:$K$342,8,0)/10^5,"") -> 4.2575184 | J84: Manoj Kumar Gupta | K84: Completed | L84: Received
A85: =A84+1 -> 81 | B85: 13 | C85: 39/2 | D85: =IFERROR(VLOOKUP(C85,Foundation!$C$5:$D$554,2,0),"") -> DA+3 | E85: =F79+1 -> 45728 | F85: 45735 | G85: Punam Devi-2 | H85: =VLOOKUP(D85,$D$313:$I$342,6,0) -> 37.931088 | I85: =IFERROR(VLOOKUP(D85,$D$313:$K$342,8,0)/10^5,"") -> 3.5339788 | J85: Kartik Mahto | K85: Completed | L85: Received
A86: =A85+1 -> 82 | B86: 14 | C86: 39/5 | D86: =IFERROR(VLOOKUP(C86,Foundation!$C$5:$D$554,2,0),"") -> DA+1.5 | E86: =F81+1 -> 45730 | F86: 45736 | G86: Punam Devi-3 | H86: =VLOOKUP(D86,$D$313:$I$342,6,0) -> 37.138324 | I86: =IFERROR(VLOOKUP(D86,$D$313:$K$342,8,0)/10^5,"") -> 3.4601182 | J86: Haridas | K86: Completed | L86: Received
A87: =A86+1 -> 83 | B87: 15 | C87: 39/0 | D87: =IFERROR(VLOOKUP(C87,Foundation!$C$5:$D$554,2,0),"") -> DB2+0 | E87: =F77+1 -> 45725 | F87: 45737 | G87: Vasu dev singh-2 | H87: =VLOOKUP(D87,$D$313:$I$342,6,0) -> 59.500628 | I87: =IFERROR(VLOOKUP(D87,$D$313:$K$342,8,0)/10^5,"") -> 5.5435783 | J87: Raju Mahto | K87: Completed | L87: Received
A88: =A87+1 -> 84 | B88: 16 | C88: 15/3 | D88: =IFERROR(VLOOKUP(C88,Foundation!$C$5:$D$554,2,0),"") -> DA+3 | E88: =F83+1 -> 45735 | F88: 45738 | G88: Punam Devi-4 | H88: =VLOOKUP(D88,$D$313:$I$342,6,0) -> 37.931088 | I88: =IFERROR(VLOOKUP(D88,$D$313:$K$342,8,0)/10^5,"") -> 3.5339788 | J88: Gangadin sahoo | K88: Completed | L88: Received
A89: =A88+1 -> 85 | B89: 17 | C89: 38/8 | D89: =IFERROR(VLOOKUP(C89,Foundation!$C$5:$D$554,2,0),"") -> DA+1.5 | E89: =F84+1 -> 45735 | F89: 45740 | G89: Punam Devi-1 | H89: =VLOOKUP(D89,$D$313:$I$342,6,0) -> 37.138324 | I89: =IFERROR(VLOOKUP(D89,$D$313:$K$342,8,0)/10^5,"") -> 3.4601182 | J89: Manoj Kumar Gupta | K89: Completed | L89: Received
A90: =A89+1 -> 86 | B90: 18 | C90: 39/3 | D90: =IFERROR(VLOOKUP(C90,Foundation!$C$5:$D$554,2,0),"") -> DA+1.5 | E90: 45736 | F90: 45741 | G90: Punam Devi-2 | H90: =VLOOKUP(D90,$D$313:$I$342,6,0) -> 37.138324 | I90: =IFERROR(VLOOKUP(D90,$D$313:$K$342,8,0)/10^5,"") -> 3.4601182 | J90: Kartik Mahto | K90: Completed | L90: Received
A91: =A90+1 -> 87 | B91: 19 | C91: 39/4 | D91: =IFERROR(VLOOKUP(C91,Foundation!$C$5:$D$554,2,0),"") -> DA+3 | E91: 45737 | F91: 45743 | G91: Punam Devi-3 | H91: =VLOOKUP(D91,$D$313:$I$342,6,0) -> 37.931088 | I91: =IFERROR(VLOOKUP(D91,$D$313:$K$342,8,0)/10^5,"") -> 3.5339788 | J91: Haridas | K91: Completed | L91: Received
A92: =A91+1 -> 88 | B92: 20 | C92: 15/4 | D92: =IFERROR(VLOOKUP(C92,Foundation!$C$5:$D$554,2,0),"") -> DA+6 | E92: 45739 | F92: 45743 | G92: Punam Devi-4 | H92: =VLOOKUP(D92,$D$313:$I$342,6,0) -> 43.804424 | I92: =IFERROR(VLOOKUP(D92,$D$313:$K$342,8,0)/10^5,"") -> 4.0811881 | J92: Gangadin sahoo | K92: Completed | L92: Received
A93: =A92+1 -> 89 | B93: 21 | C93: 39/1 | D93: =IFERROR(VLOOKUP(C93,Foundation!$C$5:$D$554,2,0),"") -> DA-1.5 | E93: 45738 | F93: 45745 | G93: Vasu dev singh-2 | H93: =VLOOKUP(D93,$D$313:$I$342,6,0) -> 35.601762 | I93: =IFERROR(VLOOKUP(D93,$D$313:$K$342,8,0)/10^5,"") -> 3.3169592 | J93: Raju Mahto | K93: Completed | L93: Received
A94: =A93+1 -> 90 | B94: 22 | C94: 39/9 | D94: =IFERROR(VLOOKUP(C94,Foundation!$C$5:$D$554,2,0),"") -> DA+6 | E94: 45741 | F94: 45746 | G94: Punam Devi-1 | H94: =VLOOKUP(D94,$D$313:$I$342,6,0) -> 43.804424 | I94: =IFERROR(VLOOKUP(D94,$D$313:$K$342,8,0)/10^5,"") -> 4.0811881 | J94: Manoj Kumar Gupta | K94: Completed | L94: Received
A95: =A94+1 -> 91 | B95: 23 | C95: 40/2 | D95: =IFERROR(VLOOKUP(C95,Foundation!$C$5:$D$554,2,0),"") -> DA+6 | E95: 45742 | F95: 45747 | G95: Punam Devi-2 | H95: =VLOOKUP(D95,$D$313:$I$342,6,0) -> 43.804424 | I95: =IFERROR(VLOOKUP(D95,$D$313:$K$342,8,0)/10^5,"") -> 4.0811881 | J95: Kartik Mahto | K95: Completed | L95: Received
A96: =A95+1 -> 92 | B96: 24 | C96: 15/5 | D96: =IFERROR(VLOOKUP(C96,Foundation!$C$5:$D$554,2,0),"") -> DA+3 | E96: 45742 | F96: 45747 | G96: Punam Devi-4 | H96: =VLOOKUP(D96,$D$313:$I$342,6,0) -> 37.931088 | I96: =IFERROR(VLOOKUP(D96,$D$313:$K$342,8,0)/10^5,"") -> 3.5339788 | J96: Gangadin sahoo | K96: Completed | L96: Received
A97: =A96+1 -> 93 | B97: 25 | C97: 39/8 | D97: =IFERROR(VLOOKUP(C97,Foundation!$C$5:$D$554,2,0),"") -> DA+1.5 | E97: 45377 | F97: 45747 | G97: Punam Devi-3 | H97: =VLOOKUP(D97,$D$313:$I$342,6,0) -> 37.138324 | I97: =IFERROR(VLOOKUP(D97,$D$313:$K$342,8,0)/10^5,"") -> 3.4601182 | J97: Haridas | K97: Completed | L97: Received
A98: =A97+1 -> 94 | B98: 1 | C98: 39/10 | D98: =IFERROR(VLOOKUP(C98,Foundation!$C$5:$D$554,2,0),"") -> DA+3 | E98: 45747 | F98: 45752 | G98: Punam Devi-3 | H98: =VLOOKUP(D98,$D$313:$I$342,6,0) -> 37.931088 | I98: =IFERROR(VLOOKUP(D98,$D$313:$K$342,8,0)/10^5,"") -> 3.5339788 | J98: Haridas | K98: Completed | L98: Received
A99: =A98+1 -> 95 | B99: 2 | C99: 15/6 | D99: =IFERROR(VLOOKUP(C99,Foundation!$C$5:$D$554,2,0),"") -> DA+9 | E99: 45747 | F99: 45753 | G99: Punam Devi-4 | H99: =VLOOKUP(D99,$D$313:$I$342,6,0) -> 45.697022 | I99: =IFERROR(VLOOKUP(D99,$D$313:$K$342,8,0)/10^5,"") -> 4.2575184 | J99: Gangadin sahoo | K99: Completed | L99: Received
A100: =A99+1 -> 96 | B100: 3 | C100: 39/11 | D100: =IFERROR(VLOOKUP(C100,Foundation!$C$5:$D$554,2,0),"") -> DA+6 | E100: 45746 | F100: 45756 | G100: Punam Devi-1 | H100: =VLOOKUP(D100,$D$313:$I$342,6,0) -> 43.804424 | I100: =IFERROR(VLOOKUP(D100,$D$313:$K$342,8,0)/10^5,"") -> 4.0811881 | J100: Manoj Kumar Gupta | K100: Completed | L100: Received
A101: =A100+1 -> 97 | B101: 4 | C101: 40/3 | D101: =IFERROR(VLOOKUP(C101,Foundation!$C$5:$D$554,2,0),"") -> DA+3 | E101: 45747 | F101: 45756 | G101: Punam Devi-2 | H101: =VLOOKUP(D101,$D$313:$I$342,6,0) -> 37.931088 | I101: =IFERROR(VLOOKUP(D101,$D$313:$K$342,8,0)/10^5,"") -> 3.5339788 | J101: Kartik Mahto | K101: Completed | L101: Received
... A111: =A110+1 -> 107 | B111: 3 | C111: 7/3 | D111: =IFERROR(VLOOKUP(C111,Foundation!$C$5:$D$554,2,0),"") -> DA+9 | E111: 45847 | F111: 45859 | G111: Pritam Enterprises | H111: =VLOOKUP(D111,$D$313:$I$342,6,0) -> 45.697022 | I111: =IFERROR(VLOOKUP(D111,$D$313:$K$342,8,0)/10^5,"") -> 4.2575184 | J111: Sanjay Kumar | K111: Completed | L111: Received
A112: =A111+1 -> 108 | B112: 4 | C112: 32/5 | D112: =IFERROR(VLOOKUP(C112,Foundation!$C$5:$D$554,2,0),"") -> DA+9 | E112: =F109+1 -> 45854 | F112: 45863 | G112: Punam Kumari | H112: =VLOOKUP(D112,$D$313:$I$342,6,0) -> 45.697022 | I112: =IFERROR(VLOOKUP(D112,$D$313:$K$342,8,0)/10^5,"") -> 4.2575184 | J112: Manoj Gupta | K112: Completed | L112: Received
A113: =A112+1 -> 109 | B113: 5 | C113: 6/1 | D113: =IFERROR(VLOOKUP(C113,Foundation!$C$5:$D$554,2,0),"") -> DA+9 | E113: 45854 | F113: 45864 | G113: Jwala Singh-1 | H113: =VLOOKUP(D113,$D$313:$I$342,6,0) -> 45.697022 | I113: =IFERROR(VLOOKUP(D113,$D$313:$K$342,8,0)/10^5,"") -> 4.2575184 | J113: Aman Singh | K113: Completed | L113: Received
A114: =A113+1 -> 110 | B114: 6 | C114: 32/2 | D114: =IFERROR(VLOOKUP(C114,Foundation!$C$5:$D$554,2,0),"") -> DA+9 | E114: =F110+1 -> 45856 | F114: 45864 | G114: Amit Kumar Singh | H114: =VLOOKUP(D114,$D$313:$I$342,6,0) -> 45.697022 | I114: =IFERROR(VLOOKUP(D114,$D$313:$K$342,8,0)/10^5,"") -> 4.2575184 | J114: Suraj Kumar | K114: Completed | L114: Received
A115: =A114+1 -> 111 | B115: 7 | C115: 7/0 | D115: =IFERROR(VLOOKUP(C115,Foundation!$C$5:$D$554,2,0),"") -> DB2+0 | E115: =F111+1 -> 45860 | F115: 45869 | G115: Pritam Enterprises | H115: =VLOOKUP(D115,$D$313:$I$342,6,0) -> 59.500628 | I115: =IFERROR(VLOOKUP(D115,$D$313:$K$342,8,0)/10^5,"") -> 5.5435783 | J115: Sanjay Kumar | K115: Completed | L115: Received
A116: =A115+1 -> 112 | B116: 8 | C116: 32/7 | D116: =IFERROR(VLOOKUP(C116,Foundation!$C$5:$D$554,2,0),"") -> DA+3 | E116: 45864 | F116: 45869 | G116: Punam Kumari | H116: =VLOOKUP(D116,$D$313:$I$342,6,0) -> 37.931088 | I116: =IFERROR(VLOOKUP(D116,$D$313:$K$342,8,0)/10^5,"") -> 3.5339788 | J116: Manoj Gupta | K116: Completed | L116: Received
A117: =A116+1 -> 113 | B117: 1 | C117: 31/0 | D117: =IFERROR(VLOOKUP(C117,Foundation!$C$5:$D$554,2,0),"") -> DB1+0 | E117: 45854 | F117: 45870 | G117: SK Samiul -1 | H117: =VLOOKUP(D117,$D$313:$I$342,6,0) -> 55.450851 | I117: =IFERROR(VLOOKUP(D117,$D$313:$K$342,8,0)/10^5,"") -> 5.1662671 | J117: Haridas | K117: Completed | L117: Received
A118: =A117+1 -> 114 | B118: 2 | C118: 42/0 | D118: =IFERROR(VLOOKUP(C118,Foundation!$C$5:$D$554,2,0),"") -> DB2+0 | E118: 45859 | F118: 45871 | G118: Fouzi Ratto | H118: =VLOOKUP(D118,$D$313:$I$342,6,0) -> 59.500628 | I118: =IFERROR(VLOOKUP(D118,$D$313:$K$342,8,0)/10^5,"") -> 5.5435783 | J118: Manirul | K118: Completed | L118: Received
A119: =A118+1 -> 115 | B119: 3 | C119: 8/11 | D119: =IFERROR(VLOOKUP(C119,Foundation!$C$5:$D$554,2,0),"") -> DA+9 | E119: 45853 | F119: 45872 | G119: Jwala Singh-1 | H119: =VLOOKUP(D119,$D$313:$I$342,6,0) -> 45.697022 | I119: =IFERROR(VLOOKUP(D119,$D$313:$K$342,8,0)/10^5,"") -> 4.2575184 | J119: Rudra Prasad | K119: Completed | L119: Received
A120: =A119+1 -> 116 | B120: 4 | C120: 30/10 | D120: =IFERROR(VLOOKUP(C120,Foundation!$C$5:$D$554,2,0),"") -> DA+3 | E120: 45856 | F120: 45872 | G120: SK.Samiul -2 | H120: =VLOOKUP(D120,$D$313:$I$342,6,0) -> 37.931088 | I120: =IFERROR(VLOOKUP(D120,$D$313:$K$342,8,0)/10^5,"") -> 3.5339788 | J120: Haridas | K120: Completed | L120: Received
A121: =A120+1 -> 117 | B121: 5 | C121: 32/3 | D121: =IFERROR(VLOOKUP(C121,Foundation!$C$5:$D$554,2,0),"") -> DA+6 | E121: =F114+1 -> 45865 | F121: 45874 | G121: Amit Kumar Singh | H121: =VLOOKUP(D121,$D$313:$I$342,6,0) -> 43.804424 | I121: =IFERROR(VLOOKUP(D121,$D$313:$K$342,8,0)/10^5,"") -> 4.0811881 | J121: Suraj Kumar | K121: Completed | L121: Received
A122: =A121+1 -> 118 | B122: 6 | C122: 42/1 | D122: =IFERROR(VLOOKUP(C122,Foundation!$C$5:$D$554,2,0),"") -> DA+3 | E122: =F118 -> 45871 | F122: 45875 | G122: Fouzi Ratto | H122: =VLOOKUP(D122,$D$313:$I$342,6,0) -> 37.931088 | I122: =IFERROR(VLOOKUP(D122,$D$313:$K$342,8,0)/10^5,"") -> 3.5339788 | J122: Manirul | K122: Completed | L122: Received
A123: =A122+1 -> 119 | B123: 7 | C123: 40/1 | D123: =IFERROR(VLOOKUP(C123,Foundation!$C$5:$D$554,2,0),"") -> DA+9 | E123: 45844 | F123: 45876 | G123: Bambole Traders | H123: =VLOOKUP(D123,$D$313:$I$342,6,0) -> 45.697022 | I123: =IFERROR(VLOOKUP(D123,$D$313:$K$342,8,0)/10^5,"") -> 4.2575184 | J123: Susheel Kumar | K123: Completed | L123: Received
A124: =A123+1 -> 120 | B124: 8 | C124: 6/2 | D124: =IFERROR(VLOOKUP(C124,Foundation!$C$5:$D$554,2,0),"") -> DA+6 | E124: =F119+1 -> 45873 | F124: 45877 | G124: Jwala Singh-1 | H124: =VLOOKUP(D124,$D$313:$I$342,6,0) -> 43.804424 | I124: =IFERROR(VLOOKUP(D124,$D$313:$K$342,8,0)/10^5,"") -> 4.0811881 | J124: Sanjay Kumar | K124: Completed | L124: Received
A125: =A124+1 -> 121 | B125: 9 | C125: 32A/0 | D125: =IFERROR(VLOOKUP(C125,Foundation!$C$5:$D$554,2,0),"") -> DB1+9 | E125: =F116+1 -> 45870 | F125: 45878 | G125: Punam Kumari | H125: =VLOOKUP(D125,$D$313:$I$342,6,0) -> 66.780901 | I125: =IFERROR(VLOOKUP(D125,$D$313:$K$342,8,0)/10^5,"") -> 6.2218697 | J125: Manoj Kumar Gupta | K125: Completed | L125: Received
A126: =A125+1 -> 122 | B126: 10 | C126: 35/2 | D126: =IFERROR(VLOOKUP(C126,Foundation!$C$5:$D$554,2,0),"") -> DA+6 | E126: =F116+1 -> 45870 | F126: 45878 | G126: Jwala Singh-2 | H126: =VLOOKUP(D126,$D$313:$I$342,6,0) -> 43.804424 | I126: =IFERROR(VLOOKUP(D126,$D$313:$K$342,8,0)/10^5,"") -> 4.0811881 | J126: Rudra Prasad | K126: Completed | L126: Received
A127: =A126+1 -> 123 | B127: 11 | C127: 6/12 | D127: =IFERROR(VLOOKUP(C127,Foundation!$C$5:$D$554,2,0),"") -> DA+1.5 | E127: =F115+1 -> 45870 | F127: 45878 | G127: Pritam Enterprises-1 | H127: =VLOOKUP(D127,$D$313:$I$342,6,0) -> 37.138324 | I127: =IFERROR(VLOOKUP(D127,$D$313:$K$342,8,0)/10^5,"") -> 3.4601182 | J127: Sanjay Kumar | K127: Completed | L127: Received
A128: =A127+1 -> 124 | B128: 12 | C128: 31/1 | D128: =IFERROR(VLOOKUP(C128,Foundation!$C$5:$D$554,2,0),"") -> DA+3 | E128: =F117+1 -> 45871 | F128: 45879 | G128: SK Samiul -1 | H128: =VLOOKUP(D128,$D$313:$I$342,6,0) -> 37.931088 | I128: =IFERROR(VLOOKUP(D128,$D$313:$K$342,8,0)/10^5,"") -> 3.5339788 | J128: Haridas | K128: Completed | L128: Received
A129: =A128+1 -> 125 | B129: 13 | C129: 31/2 | D129: =IFERROR(VLOOKUP(C129,Foundation!$C$5:$D$554,2,0),"") -> DA+1.5 | E129: =F120+1 -> 45873 | F129: 45880 | G129: SK.Samiul -2 | H129: =VLOOKUP(D129,$D$313:$I$342,6,0) -> 37.138324 | I129: =IFERROR(VLOOKUP(D129,$D$313:$K$342,8,0)/10^5,"") -> 3.4601182 | J129: Haridas | K129: Completed | L129: Received
A130: =A129+1 -> 126 | B130: 14 | C130: 42/2 | D130: =IFERROR(VLOOKUP(C130,Foundation!$C$5:$D$554,2,0),"") -> DA+9 | E130: =F122+1 -> 45876 | F130: 45880 | G130: Fouzi Ratto | H130: =VLOOKUP(D130,$D$313:$I$342,6,0) -> 45.697022 | I130: =IFERROR(VLOOKUP(D130,$D$313:$K$342,8,0)/10^5,"") -> 4.2575184 | J130: Manirul | K130: Completed | L130: Received
A131: =A130+1 -> 127 | B131: 15 | C131: 40/9 | D131: =IFERROR(VLOOKUP(C131,Foundation!$C$5:$D$554,2,0),"") -> DA+9 | E131: 45870 | F131: 45882 | G131: Pinki Devi | H131: =VLOOKUP(D131,$D$313:$I$342,6,0) -> 45.697022 | I131: =IFERROR(VLOOKUP(D131,$D$313:$K$342,8,0)/10^5,"") -> 4.2575184 | J131: Manirul | K131: Completed | L131: Received
A132: =A131+1 -> 128 | B132: 16 | C132: 6/5 | D132: =IFERROR(VLOOKUP(C132,Foundation!$C$5:$D$554,2,0),"") -> DA+9 | E132: 45871 | F132: 45882 | G132: Pritam Enterprises-2 | H132: =VLOOKUP(D132,$D$313:$I$342,6,0) -> 45.697022 | I132: =IFERROR(VLOOKUP(D132,$D$313:$K$342,8,0)/10^5,"") -> 4.2575184 | J132: Sanjay Kumar | K132: Completed | L132: Received
A133: =A132+1 -> 129 | B133: 17 | C133: 32/4 | D133: =IFERROR(VLOOKUP(C133,Foundation!$C$5:$D$554,2,0),"") -> DA+9 | E133: =F121+2 -> 45876 | F133: 45883 | G133: Amit Kumar Singh | H133: =VLOOKUP(D133,$D$313:$I$342,6,0) -> 45.697022 | I133: =IFERROR(VLOOKUP(D133,$D$313:$K$342,8,0)/10^5,"") -> 4.2575184 | J133: Suraj Kumar | K133: Completed | L133: Received
A134: =A133+1 -> 130 | B134: 18 | C134: 6/3 | D134: =IFERROR(VLOOKUP(C134,Foundation!$C$5:$D$554,2,0),"") -> DA+3 | E134: =F124 -> 45877 | F134: 45883 | G134: Jwala Singh-1 | H134: =VLOOKUP(D134,$D$313:$I$342,6,0) -> 37.931088 | I134: =IFERROR(VLOOKUP(D134,$D$313:$K$342,8,0)/10^5,"") -> 3.5339788 | J134: Sanjay Kumar | K134: Completed | L134: Received
A135: =A134+1 -> 131 | B135: 19 | C135: 8A/0 | D135: =IFERROR(VLOOKUP(C135,Foundation!$C$5:$D$554,2,0),"") -> DB1+12 | E135: 45876 | F135: 45883 | G135: Punam Kumari-2 | H135: =VLOOKUP(D135,$D$313:$I$342,6,0) -> 70.788265 | I135: =IFERROR(VLOOKUP(D135,$D$313:$K$342,8,0)/10^5,"") -> 6.5952294 | J135: Sanjay Kumar | K135: Completed | L135: Received
A136: =A135+1 -> 132 | B136: 20 | C136: 33/2 | D136: =IFERROR(VLOOKUP(C136,Foundation!$C$5:$D$554,2,0),"") -> DA+9 | E136: =F125 -> 45878 | F136: 45886 | G136: Punam Kumari-1 | H136: =VLOOKUP(D136,$D$313:$I$342,6,0) -> 45.697022 | I136: =IFERROR(VLOOKUP(D136,$D$313:$K$342,8,0)/10^5,"") -> 4.2575184 | J136: Manoj Kumar Gupta | K136: Completed | L136: Received
A137: =A136+1 -> 133 | B137: 21 | C137: 6/10 | D137: =IFERROR(VLOOKUP(C137,Foundation!$C$5:$D$554,2,0),"") -> DA+1.5 | E137: =F127 -> 45878 | F137: 45887 | G137: Pritam Enterprises-1 | H137: =VLOOKUP(D137,$D$313:$I$342,6,0) -> 37.138324 | I137: =IFERROR(VLOOKUP(D137,$D$313:$K$342,8,0)/10^5,"") -> 3.4601182 | J137: Sanjay Kumar | K137: Completed | L137: Received
A138: =A137+1 -> 134 | B138: 22 | C138: 9/5 | D138: =IFERROR(VLOOKUP(C138,Foundation!$C$5:$D$554,2,0),"") -> DA+3 | E138: =F135+1 -> 45884 | F138: 45888 | G138: Punam Kumari-2 | H138: =VLOOKUP(D138,$D$313:$I$342,6,0) -> 37.931088 | I138: =IFERROR(VLOOKUP(D138,$D$313:$K$342,8,0)/10^5,"") -> 3.5339788 | J138: Narayan Mahto | K138: Completed | L138: Received
...

Sheet L2 Plan vs Actual
A1: Project :- TL02 for Bikaner-III - Neemrana-II 765 KV DC Line Part-I associated with Transmission system for excavation of power from Rajasthan REZ Ph-IV (Part-I) (Bikaner Complex: 7.7 GW)
A2: Ref. :- CC/T/W-TW/DOM/A04/23/10569/NOA-1 & 2/24-103421/01 & 02 Date. 12/03/2024
A3: Line Length :- 112 KM | E3: Status as on | F3: =TA413_PBNTL!M1 -> 27.05.2026
A4: S.No. | B4: Activity / Description | C4: UOM | D4: Qty | E4: Start Date | F4: End Date | G4: L2 | H4: Cumm. Till date | I4: Balance | J4: 0 | K4: =J4+1 -> 1 | L4: =K4+1 -> 2 | M4: =L4+1 -> 3 | N4: =M4+1 -> 4 | O4: =N4+1 -> 5 | P4: =O4+1 -> 6 | Q4: =P4+1 -> 7 | R4: =Q4+1 -> 8 | ... AE4: =AD4+1 -> 21
G5: Till date | J5: 45352 | K5: 45383 | L5: 45413 | M5: 45444 | N5: 45474 | O5: 45505 | P5: 45536 | Q5: 45566 | R5: 45597 | S5: 45627 | T5: 45658 | U5: 45689 | V5: 45717 | W5: 45748 | X5: 45778 | Y5: 45809 | Z5: 45839 | AA5: 45870 | AB5: 45901 | AC5: 45931 | AD5: 45962 | AE5: 45992
B6: Supplies
A7: 1 | B7: Line Materials | C7: % | D7: 100 | E7: 45371 | F7: 45738
A8: a | B8: Vendor Finalisation | C8: % | D8: 100 | E8: 45371 | F8: 45406
A9: b | B9: Submission / Approval of Drawings | C9: % | D9: 100 | E9: 45383 | F9: 45411 | K9: 1
A10: c | B10: Receipt at site of Stubs & Earthing | C10: EA | D10: 287 | E10: 45400 | F10: 45616 | G10: =SUM(K10:V10) -> 287 | K10: 25 | L10: 50 | M10: 50 | N10: 50 | P10: 80 | R10: 32
B11: Stubs - Actual Status | H11: 313 | I11: =D10-H11 -> -26 | K11: 0 | L11: 5 | M11: =105+25 -> 130 | N11: 10 | P11: 40 | Q11: 16 | S11: 44 | T11: 34
B12: Earthing Rod - Actual Status | H12: 309 | I12: =D10-H12 -> -22 | L12: 107 | M12: 13 | N12: 10 | O12: 45 | R12: 25 | T12: 79
A13: d | B13: Receipt at site of Towers | C13: EA | D13: 287 | E13: 45434 | F13: 45708 | G13: =SUM(K13:V13) -> 287 | I13: =G13-H15 -> -5 | L13: 40 | M13: 40 | O13: 40 | P13: 30 | Q13: 30 | S13: 70 | U13: 37
D14: 13873.345 | G14: =SUM(K14:V14) -> 13873.58 | I14: =G14-H16 -> 898.58 | L14: =L13*48.34 -> 1933.6 | M14: =M13*48.34 -> 1933.6 | O14: =O13*48.34 -> 1933.6 | P14: =P13*48.34 -> 1450.2 | Q14: =Q13*48.34 -> 1450.2 | S14: =S13*48.34 -> 3383.8 | U14: =U13*48.34 -> 1788.58
B15: Actual Status of Tower | C15: EA | H15: 292 | I15: =D13-H15 -> -5 | N15: 40 | O15: 80 | P15: =15+10+20 -> 45 | Q15: 21 | R15: 16 | S15: 21 | T15: 8 | U15: 2
B16: Actual Status of Tower | C16: MT | H16: 12975 | I16: =D14-H16 -> 898.345 | L16: 234.638 | M16: =396.581+1110.769 -> 1507.35 | N16: 1340.159 | O16: 1578.296 | P16: 1417.352 | Q16: =28.513*20 -> 570.26 | R16: 615.531 | S16: 1100 | T16: 1231.414
A17: e | B17: Receipt of Insulators at site | C17: EA | D17: 10480 | E17: 45482 | F17: 45646 | G17: =SUM(K17:S17) -> 10480 | I17: =G17-H18 -> 580 | N17: 4192 | Q17: 3144 | S17: 3144
B18: Actual Status | H18: 9900 | I18: =D17-H18 -> 580 | N18: 4192
A19: f | B19: Receipt of Hardware Fittings & Accessories at site | C19: % | D19: 100 | E19: 45482 | F19: 45646 | G19: =SUM(K19:T19) -> 1 | I19: =G19-H20 -> 1 | N19: 0.4 | Q19: 0.3 | S19: 0.3
B20: Actual Status | H20: =SUM(J20:AE20) -> 0 | I20: =D19-H20 -> 100
A21: g | B21: Receipt of Conductors at site | C21: Km | D21: 4095 | E21: 45422 | F21: 45738 | G21: =SUM(K21:V21) -> 4095 | I21: =G21-H22 -> 0.015 | L21: 200 | M21: 500 | N21: 400 | O21: 300 | P21: 400 | Q21: 300 | R21: 300 | S21: 400 | T21: 400 | U21: 400 | V21: 495
B22: Actual Status | H22: 4094.985 | I22: =D21-H22 -> 0.015 | L22: 264 | M22: 59.8 | N22: 524.239 | O22: 99.987 | P22: 249.458 | Q22: =200+299.972 -> 499.972 | R22: 249.898 | S22: =249.898+249.963 -> 499.861 | T22: 474.987 | U22: 1025.168
A23: h | B23: Receipt of Conductors Accessories at site | C23: % | D23: 1 | E23: 45485 | F23: 45651 | G23: =SUM(K23:S23) -> 1 | I23: =G23-H24 -> 0 | N23: 0.4 | Q23: 0.3 | S23: 0.3
B24: Actual Status | H24: =SUM(J24:AE24) -> 1 | I24: =D23-H24 -> 0 | O24: 0.4 | R24: 0.3 | T24: 0.3
A25: i | B25: Receipt of Earth Wire & its Accessories at site | C25: % | D25: 1 | E25: 45470 | F25: 45651 | G25: =SUM(K25:T25) -> 1 | I25: =G25-H26 -> 0 | M25: 0.4 | P25: 0.4 | S25: 0.2
B26: Actual Status | H26: =SUM(J26:AE26) -> 1 | I26: =D25-H26 -> 0 | N26: 0.4 | O26: 0.4 | T26: 0.2
A27: j | B27: Receipt of OPGW & its Accessories at site | C27: % | D27: 1 | E27: 45544 | F27: 45651 | G27: =SUM(K27:S27) -> 1 | I27: =G27-H28 -> 1 | P27: 0.7 | S27: 0.3
B28: Actual Status | H28: =SUM(J28:AE28) -> 0 | I28: =D27-H28 -> 1
A29: k | B29: Receipt of Aviation materials | C29: % | D29: 1 | E29: 45658 | F29: 45688 | G29: =SUM(K29:Q29) -> 0 | I29: =G29-H30 -> 0 | T29: 1
B30: Actual Status | H30: =SUM(J30:AE30) -> 0 | I30: =D29-H30 -> 1
B31: Service
A32: 1 | B32: Establishment of Site Office/Store, Mobilization | C32: % | D32: 100 | E32: 45371 | F32: 45411
A33: =A32+1 -> 2 | B33: Route Alignment Submission and Approval | C33: Km | D33: 112 | E33: 45384 | F33: 45402 | K33: 112
B34: Actual Status | D34: =SUM(J34:AE34) -> 115 | H34: =SUM(J34:AE34) -> 115 | L34: 115
A35: =A33+1 -> 3 | B35: Detailed survey Submission and Approval | C35: Km | D35: 112 | E35: 45404 | F35: 45532 | G35: =SUM(K35:Q35) -> 112 | I35: =G35-H36 -> -3 | K35: 10 | L35: 22 | M35: 34 | N35: 34 | O35: 12
B36: Actual Status | D36: =SUM(J36:AE36) -> 115 | H36: =SUM(J36:AE36) -> 115 | L36: 32.706 | M36: 31.918 | O36: 50.376
A37: =A35+1 -> 4 | B37: Check survey Submission and Approval | C37: Km | D37: 112 | E37: 45409 | F37: 45592 | G37: =SUM(K37:Q37) -> 112 | I37: =G37-H38 -> -2.972 | K37: 5 | L37: 12 | M37: 20 | N37: 20 | O37: 20 | P37: 20 | Q37: 15
B38: Actual Status | D38: =SUM(J38:AE38) -> 114.972 | H38: =SUM(J38:AE38) -> 114.972 | L38: 5.969 | M38: 9.941 | N38: 33.643 | O38: 29.496 | P38: 5.08 | Q38: 7.984 | R38: 15.688 | S38: =2.21+0.048 -> 2.258 | T38: =0.226+4.687 -> 4.913
A39: =A37+1 -> 5 | B39: Submission of Forest proposal (If any) | C39: % | D39: 100 | E39: 45444 | F39: 45473 | G39: =SUM(K39:N39) -> 1 | I39: =G39-H40 -> 0 | M39: 1
B40: Actual Status | D40: =SUM(J40:AE40) -> 1 | H40: =SUM(J40:AE40) -> 1 | M40: 1
A41: =A39+1 -> 6 | B41: Foundation | C41: EA | D41: 287 | E41: 45431 | F41: 45860 | G41: =SUM(K41:Z41) -> 287 | I41: =G41-H42 -> -26 | L41: 6 | M41: 18 | N41: 18 | O41: 20 | P41: 22 | Q41: 22 | R41: 25 | S41: 25 | T41: 30 | U41: 30 | V41: 25 | W41: 15 | X41: 15 | Y41: 10 | Z41: 6
B42: Actual Status | D42: =SUM(J42:AE42) -> 313 | H42: =SUM(J42:AE42) -> 313 | L42: 0 | M42: 14 | N42: 20 | O42: 23 | P42: 40 | Q42: 36 | R42: 24 | S42: 32 | T42: 35 | U42: 31 | V42: 19 | W42: 23 | X42: 10 | Y42: 4 | Z42: 2
A43: =A41+1 -> 7 | B43: Tower Erection | C43: EA | D43: 287 | E43: 45457 | F43: 45925 | G43: =SUM(K43:AB43) -> 287 | I43: =G43-H44 -> -7 | M43: 4 | N43: 15 | O43: 15 | P43: 22 | Q43: 20 | R43: 22 | S43: 22 | T43: 22 | U43: 22 | V43: 22 | W43: 22 | X43: 20 | Y43: 20 | Z43: 20 | AA43: 12 | AB43: 7
B44: Actual Status | D44: =SUM(J44:AE44) -> 294 | H44: =SUM(J44:AE44) -> 294 | M44: 0 | N44: 0 | P44: 2 | Q44: 5 | R44: 2 | S44: 13 | T44: 25 | U44: 21 | V44: 25 | W44: 11 | Z44: 8 | AA44: 44 | AB44: 62 | AC44: 39 | AD44: 24 | AE44: 13
A45: =A43+1 -> 8 | B45: Stringing | Conductor | C45: Km | D45: 112 | E45: 45520 | F45: 45958 | G45: =SUM(K45:AC45) -> 112 | I45: =G45-H46 -> 72.451 | O45: 4 | P45: 4 | Q45: 8 | R45: 8 | S45: 8 | T45: 8 | U45: 10 | V45: 10 | W45: 10 | X45: 10 | Y45: 8 | Z45: 8 | AA45: 8 | AB45: 4 | AC45: 4
B46: Actual Status | D46: =SUM(J46:AE46) -> 39.549 | H46: =SUM(J46:AE46) -> 39.549 | V46: 4.899 | W46: 11.464 | AB46: 5.134 | AC46: 4.922 | AD46: 4.901 | AE46: 8.229
A47: =A45+1 -> 9 | B47: Stringing || OPGW | C47: Km | D47: 112 | E47: 45386 | F47: 45991 | G47: =SUM(K47:AD47) -> 112 | I47: =G47-H48 -> 98.388 | W47: 15 | X47: 20 | Y47: 20 | Z47: 20 | AA47: 10 | AB47: 10 | AC47: 10 | AD47: 7
B48: Actual Status | D48: =SUM(J48:AE48) -> 13.612 | H48: =SUM(J48:AE48) -> 13.612 | W48: 13.612
A49: =A47+1 -> 10 | B49: Testing & Commisioning | C49: % | D49: 100 | E49: 45931 | F49: 46002 | G49: =SUM(K49:S49) -> 0 | I49: =G49-H50 -> 0 | AC49: 0.4 | AD49: 0.5 | AE49: 0.1
B50: Actual Status | D50: =SUM(J50:AE50) -> 0 | H50: =SUM(J50:AE50) -> 0

Sheet Survey summary
A1: Survey and Profile Drawing Status | E1: Detail Survey | K1: Check Survey
A2: S.No. | B2: Section | C2: Length | D2: Detail Survey | E2: Detail Survey data to Engg | F2: Profile by Engg | G2: TS Site Check | H2: Final Profile | I2: Submission to PGCIL | J2: Approval by PGCIL | K2: Check Survey | L2: Re-Profile by Engg. | M2: Submission to PGCIL | N2: Approval
A3: 1 | B3: AP 0 - AP 3 | C3: =772.154/1000 -> 0.772154 | D3: 45435 | E3: 45442 | F3: 45442 | G3: 45434 | H3: 45516 | I3: 45516 | J3: 45516
A4: 2 | B4: AP 3 - AP 4 | C4: =4860.728/1000 -> 4.860728 | D4: 45435 | E4: 45442 | F4: 45442 | G4: 45434 | H4: 45437 | I4: 45437 | J4: 45513 | K4: 45516 | M4: 45516 | N4: 45516
A5: 3 | B5: AP 4 - AP 5 | C5: =5066.611/1000 -> 5.066611 | D5: 45420 | E5: 45427 | F5: 45429 | G5: 45434 | H5: 45437 | I5: 45437 | J5: 45440 | K5: 45526 | M5: 45526 | N5: 45492
A6: =A5+1 -> 4 | B6: AP 5 - AP 6 | C6: =4837.87/1000 -> 4.83787 | D6: 45420 | E6: 45427 | F6: 45429 | G6: 45447 | H6: 45447 | I6: 45448 | J6: 45456 | K6: 45500 | M6: 2 | N6: 45503
A7: =A6+1 -> 5 | B7: AP 6 - AP 7 | C7: =4901.24/1000 -> 4.90124 | D7: 45420 | E7: 45427 | F7: 45429 | G7: 45434 | H7: 45440 | I7: 45440 | J7: 45440 | K7: 45526 | M7: 45526 | N7: 45523
A8: =A7+1 -> 6 | B8: AP 7 - AP 8 | C8: =5134.054/1000 -> 5.134054 | D8: 45420 | E8: 45427 | F8: 45429 | G8: 45434 | H8: 45440 | I8: 45440 | J8: 45440 | K8: 45500 | M8: 45500 | N8: 45503
A9: =A8+1 -> 7 | B9: AP 8 - AP 9 | C9: =4921.629/1000 -> 4.921629 | D9: 45418 | E9: 45420 | F9: 45421 | G9: 45429 | H9: 45429 | I9: 45430 | J9: 45440 | K9: 45448 | M9: 45456 | N9: 45456
A10: =A9+1 -> 8 | B10: AP 9 - AP 11 | C10: =5969.103/1000 -> 5.969103 | D10: 45416 | E10: 45420 | F10: 45421 | G10: 45425 | H10: 45426 | I10: 45428 | J10: 45428 | K10: 45427 | L10: 45427 | M10: 45428 | N10: 45428
A11: =A10+1 -> 9 | B11: AP 11 - AP 15 | C11: =1693.584/1000 -> 1.693584 | D11: 45425 | E11: 45427 | F11: 45433 | G11: 45438 | H11: 45439 | I11: 45439 | J11: 45439 | K11: 45497 | M11: 45497 | N11: 45632
A12: =A11+1 -> 10 | B12: AP 15 - AP 16 | C12: =5019.34/1000 -> 5.01934 | D12: 45425 | E12: 45427 | F12: 45433 | G12: 45438 | H12: 45439 | I12: 45439 | J12: 45439 | K12: 45454 | M12: 45454 | N12: 45454
A13: =A12+1 -> 11 | B13: AP 16 - AP 19 | C13: 3.821 | D13: 45425 | E13: 45427 | F13: 45433 | G13: 45447 | H13: 45448 | I13: 45448 | J13: 45456 | K13: 45583 | M13: 45583 | N13: 45583
A14: =A13+1 -> 12 | B14: AP 19 - AP 20 | C14: =279.36/1000 -> 0.27936 | D14: 45425 | E14: 45427 | F14: 45433 | G14: 45447 | H14: 45448 | I14: 45448 | J14: 45456 | K14: 45528 | M14: 45528
A15: =A14+1 -> 13 | B15: AP 20 - AP 21 | C15: =2550.167/1000 -> 2.550167 | D15: 45425 | E15: 45427 | F15: 45433 | G15: 45447 | H15: 45448 | I15: 45448 | J15: 45456 | K15: 45465 | M15: 45465 | N15: 45484
A16: =A15+1 -> 14 | B16: AP 21 - AP 22 | C16: 2.2835 | D16: 45425 | E16: 45427 | F16: 45433 | G16: 45447 | H16: 45448 | I16: 45448 | J16: 45456 | K16: 45693 | M16: 45693
A17: =A16+1 -> 15 | B17: AP 23 - AP 27 | C17: 1.881 | D17: 45425 | E17: 45427 | F17: 45433 | G17: 45446 | H17: 45455 | I17: 45455 | J17: 45456 | K17: 45497 | M17: 45497 | N17: 06.12.2024
A18: =A17+1 -> 16 | B18: AP 27 - AP 28 | C18: =2548.275/1000 -> 2.548275 | D18: 45425 | E18: 45427 | F18: 45433 | G18: 45446 | H18: 45455 | I18: 45455 | J18: 45456 | K18: 45476 | M18: 45477 | N18: 45484
A19: =A18+1 -> 17 | B19: AP 28 - AP 29 | C19: =211.209/1000 -> 0.211209 | D19: 45425 | E19: 45427 | F19: 45433 | G19: 45446 | H19: 45455 | I19: 45455 | J19: 45456 | K19: 45497 | M19: 45497 | N19: 45693
A20: =A19+1 -> 18 | B20: AP 29 - AP 30 | C20: =5048.211/1000 -> 5.048211 | D20: 45425 | E20: 45427 | F20: 45433 | G20: 45446 | H20: 45455 | I20: 45455 | J20: 45456 | K20: 45490 | M20: 45490 | N20: 45491
A21: =A20+1 -> 19 | B21: AP 30 - AP 31 | C21: =4124.232/1000 -> 4.124232 | D21: 45425 | E21: 45427 | F21: 45433 | G21: 45446 | H21: 45455 | I21: 45455 | J21: 45456 | K21: 45490 | L21: 45490 | M21: 45490 | N21: 45490
A22: =A21+1 -> 20 | B22: AP 31 - AP 32 | C22: =4333.369/1000 -> 4.333369 | D22: 45425 | E22: 45427 | F22: 45433 | G22: 45446 | H22: 45455 | I22: 45455 | J22: 45456 | K22: 45477 | L22: 45477 | M22: 45477 | N22: 45484
A23: =A22+1 -> 21 | B23: AP 32 - AP 33 | C23: =4123.949/1000 -> 4.123949 | D23: 45434 | E23: 45442 | F23: 45449 | G23: 01-07-2024 | H23: 45502 | I23: 45502 | J23: 45502 | K23: 45516 | M23: 45516 | N23: 45516
A24: =A23+1 -> 22 | B24: AP 33 - AP 34 | C24: =4049.764/1000 -> 4.049764 | D24: 45434 | E24: 45442 | F24: 45449 | G24: 01-07-2024 | H24: 45502 | I24: 45502 | J24: 45502 | K24: 45516 | M24: 45516 | N24: 45516
A25: =A24+1 -> 23 | B25: AP 34 - AP 35 | C25: =4898.588/1000 -> 4.898588 | D25: 45434 | E25: 45442 | F25: 45449 | G25: 03-07-2024 | H25: 45502 | I25: 45502 | J25: 45502 | K25: 45516 | M25: 45516 | N25: 45516
A26: =A25+1 -> 24 | B26: AP 35 - AP 37 | C26: =6661.82/1000 -> 6.66182 | D26: 45434 | E26: 45442 | F26: 45449 | G26: 03-07-2024 | H26: 45502 | I26: 45502 | J26: 45502 | K26: 45516 | M26: 45516 | N26: 45516
A27: =A26+1 -> 25 | B27: AP 37 - AP 38 | C27: =5079.983/1000 -> 5.079983 | D27: 45434 | E27: 45442 | F27: 45449 | G27: 06-07-2024 | H27: 45502 | I27: 45502 | J27: 45502 | K27: 45551 | M27: 45551 | N27: 45551
A28: =A27+1 -> 26 | B28: AP 38 - AP 39 | C28: 4.163 | D28: 45434 | E28: 45442 | F28: 45449 | G28: 06-07-2024 | H28: 45502 | I28: 45502 | J28: 45502 | K28: 45583 | M28: 45583 | N28: 45583
A29: =A28+1 -> 27 | B29: AP 39 - AP 40 | C29: 4.717 | D29: 45434 | E29: 45442 | F29: 45449 | G29: 06-07-2024 | H29: 45502 | I29: 45502 | J29: 45502 | K29: 45597 | M29: 45597 | N29: 45597
A30: =A29+1 -> 28 | B30: AP 40 - AP 41 | C30: =5026.525/1000 -> 5.026525 | D30: 45434 | E30: 45442 | F30: 45449 | G30: 07-07-2024 | H30: 45502 | I30: 45502 | J30: 45502 | K30: 45597 | M30: 45597 | N30: 45597
A31: =A30+1 -> 29 | B31: AP 41 - AP 44 | C31: =5944.083/1000 -> 5.944083 | D31: 45434 | E31: 45442 | F31: 45449 | G31: 07-07-2024 | H31: 45502 | I31: 45502 | J31: 45502 | K31: 45597 | M31: 45597 | N31: 45597
A32: =A31+1 -> 30 | B32: AP 44 - AP 46 | C32: =2591.68/1000 -> 2.59168 | D32: 45708 | E32: 45708 | F32: 45708 | G32: 45708 | H32: 45708 | I32: 45708 | J32: 45708 | K32: 45708 | M32: 45708 | N32: 45708
B33: Total Length | C33: =SUM(C3:C32) -> 117.51303 | D33: =SUMIF(D3:D32,"<>",$C$3:$C$32) -> 117.51303 | E33: =SUMIF(E3:E32,"<>",$C$3:$C$32) -> 117.51303 | F33: =SUMIF(F3:F32,"<>",$C$3:$C$32) -> 117.51303 | G33: =SUMIF(G3:G32,"<>",$C$3:$C$32) -> 117.51303 | H33: =SUMIF(H3:H32,"<>",$C$3:$C$32) -> 117.51303 | I33: =SUMIF(I3:I32,"<>",$C$3:$C$32) -> 117.51303 | J33: =SUMIF(J3:J32,"<>",$C$3:$C$32) -> 117.51303 | K33: =SUMIF(K4:K32,"<>",$C$4:$C$32) -> 116.74087 | L33: =SUMIF(L4:L32,"<>",$C$4:$C$32) -> 14.426704 | M33: =SUMIF(M4:M32,"<>",$C$4:$C$32) -> 116.74087 | N33: =SUMIF(N4:N32,"<>",$C$4:$C$32) -> 114.17801
B34: Balance | D34: =$D$33-D33 -> 0 | E34: =$D$33-E33 -> 0 | F34: =$D$33-F33 -> 0 | G34: =$D$33-G33 -> 0 | H34: =$D$33-H33 -> 0 | I34: =$D$33-I33 -> 0 | J34: =$D$33-J33 -> 0 | K34: =$D$33-K33 -> 0.772154 | ... N34: =$D$33-N33 -> 3.335014
I36: Bal. Approval pending | J36: =I33-J33 -> 0 | M36: Bal. Approval pending | N36: =M33-N33 -> 2.56286
C38: 2.283

Sheet Detailed Survey 
A1: KEC International Limited
A2: =TA413_PBNTL!A3 -> Name of Line: 765 KV D/C Bikaner III - Neemrana II TL02 LOA Value: 389.96 Crore
A3: Detailed Survey | J3: =TA413_PBNTL!M1 -> 27.05.2026
A4: Sl.No. | B4: SPAN | D4: Profile Status | E4: Route Length | F4: Section Length (Km) | G4: Submitted For Approval | H4: Approved Date | I4: Profile approval date | J4: Remarks
B5: From Section | C5: To Section
A6: 1 | B6: Gnatry BKN -III | C6: 1/0 | E6: 0.15 | F6: =E6 -> 0.15 | G6: 45709 | H6: 45709 | I6: 45709
A7: =A6+1 -> 2 | B7: =C6 -> 1/0 | C7: 2A/0 | E7: 0.29021 | F7: =E7 -> 0.29021 | G7: 45709 | H7: 45709 | I7: 45709
A8: =A7+1 -> 3 | B8: =C7 -> 2A/0 | C8: 3A/0 | E8: 2.836992 | F8: =E8 -> 2.836992 | G8: 45709 | H8: 45709 | I8: 45709 | J8: STATE HIGHWAY SH-3
A9: =A8+1 -> 4 | B9: =C8 -> 3A/0 | C9: 3B/0 | E9: 2.691 | F9: =E9 -> 2.691 | G9: 45709 | H9: 45709 | I9: 45709
A10: =A9+1 -> 5 | B10: 3B/0 | C10: 4/0 | E10: 1.627 | F10: =E10 -> 1.627 | G10: 45709 | H10: 45709 | I10: 45709
A11: =A10+1 -> 6 | B11: 4/0 | C11: 4A/0 | E11: 0.709163 | F11: =E11 -> 0.709163 | G11: 45492 | H11: 45492 | I11: 45492
A12: =A11+1 -> 7 | B12: 4A/0 | C12: 5/0 | E12: 2.681611 | F12: =E12 -> 2.681611 | G12: 45492 | H12: 45492 | I12: 45492
A13: =A12+1 -> 8 | B13: 5/0 | C13: 5A/0 | E13: 4.418389 | F13: =E13 -> 4.418389 | G13: 45503 | H13: 45503 | I13: 45503
A14: =A13+1 -> 9 | B14: 5A/0 | C14: 6/0 | D14: Submiteed | E14: 0.41948 | F14: =E14 -> 0.41948 | G14: 45448 | H14: 45460 | I14: 45460
A15: =A14+1 -> 10 | B15: =C14 -> 6/0 | C15: 7/0 | D15: Submiteed | E15: 4.9099 | F15: =E15 -> 4.9099 | G15: 45440 | H15: 45440 | I15: 45440
A16: =A15+1 -> 11 | B16: =C15 -> 7/0 | C16: 8/0 | D16: Submiteed | E16: 5.0833 | F16: =E16 -> 5.0833 | G16: 45440 | H16: 45440 | I16: 45440
A17: =A16+1 -> 12 | B17: =C16 -> 8/0 | C17: 9/0 | D17: Submiteed | E17: 4.9957 | F17: =E17 -> 4.9957 | G17: 45430 | H17: 45437 | I17: 45437
A18: =A17+1 -> 13 | B18: =C17 -> 9/0 | C18: 10/0 | D18: Submiteed | E18: 4.9231 | F18: =E18 -> 4.9231 | G18: 45427 | H18: 45428 | I18: 45428
A19: =A18+1 -> 14 | B19: =C18 -> 10/0 | C19: 11/0 | D19: Submiteed | E19: 1.0051 | F19: =E19 -> 1.0051 | G19: 45427 | H19: 45428 | I19: 45428
A20: =A19+1 -> 15 | B20: =C19 -> 11/0 | C20: 12/0 | D20: Submiteed | E20: 0.2468 | F20: =E20 -> 0.2468 | G20: 45439 | H20: 45439 | I20: 45441 | J20: NATIONAL HIGHWAY NH-62
A21: =A20+1 -> 16 | B21: =C20 -> 12/0 | C21: 13/0 | D21: Submiteed | E21: 0.3292 | F21: =E21 -> 0.3292 | G21: 45439 | H21: 45439 | I21: 45441 | J21: 132KV SC LINE
A22: =A21+1 -> 17 | B22: =C21 -> 13/0 | C22: 14/0 | D22: Submiteed | E22: 0.8979 | F22: =E22 -> 0.8979 | G22: 45439 | H22: 45439 | I22: 45441
A23: =A22+1 -> 18 | B23: =C22 -> 14/0 | C23: 15/0 | E23: 0.224 | F23: =E23 -> 0.224 | G23: 45439 | H23: 45439 | I23: 45441 | J23: 400KV DC LINE
A24: =A23+1 -> 19 | B24: =C23 -> 15/0 | C24: 16/0 | D24: Submiteed | E24: 5.0201 | F24: =E24 -> 5.0201 | G24: 45439 | H24: 45439 | I24: 45441 | J24: CANAL
A25: =A24+1 -> 20 | B25: =C24 -> 16/0 | C25: 17/0 | E25: 0.3861 | F25: =E25 -> 0.3861 | G25: 45448 | H25: 45499 | I25: 45499
A26: =A25+1 -> 21 | B26: =C25 -> 17/0 | C26: 18/0 | E26: 0.4114 | F26: =E26 -> 0.4114 | G26: 45448 | H26: 45499 | I26: 45499
A27: =A26+1 -> 22 | B27: =C26 -> 18/0 | C27: 19/0 | E27: 3.0234 | F27: =E27 -> 3.0234 | G27: 45448 | H27: 45499 | I27: 45499
A28: =A27+1 -> 23 | B28: =C27 -> 19/0 | C28: 20/0 | E28: 0.2795 | F28: =E28 -> 0.2795 | G28: 45448 | H28: 45499 | I28: 45499 | J28: RAILWAY TRACK (SINGLE LINE ) ELECTRTIC
A29: =A28+1 -> 24 | B29: =C28 -> 20/0 | C29: 21/0 | E29: 2.5514 | F29: =E29 -> 2.5514 | G29: 45448 | H29: 45499 | I29: 45499
A30: =A29+1 -> 25 | B30: =C29 -> 21/0 | C30: 22/0 | E30: 2.2835 | F30: =E30 -> 2.2835 | G30: 45448 | H30: 45499 | I30: 45499
A31: =A30+1 -> 26 | B31: =C30 -> 22/0 | C31: 23/0 | E31: 0.2594 | F31: =E31 -> 0.2594 | G31: 45448 | H31: 45499 | I31: 45499 | J31: 220 KV S/C RVPN
A32: =A31+1 -> 27 | B32: =C31 -> 23/0 | C32: 24/0 | E32: 0.9285 | F32: =E32 -> 0.9285 | G32: 45455 | H32: 45499 | I32: 45499
A33: =A32+1 -> 28 | B33: =C32 -> 24/0 | C33: 25/0 | E33: 0.2521 | F33: =E33 -> 0.2521 | G33: 45455 | H33: 45499 | I33: 45499 | J33: 400 KV S/C RVPN(STP-BKN)
A34: =A33+1 -> 29 | B34: =C33 -> 25/0 | C34: 26/0 | E34: 0.2374 | F34: =E34 -> 0.2374 | G34: 45455 | H34: 45499 | I34: 45499
A35: =A34+1 -> 30 | B35: =C34 -> 26/0 | C35: 27/0 | E35: 0.204 | F35: =E35 -> 0.204 | G35: 45455 | H35: 45499 | I35: 45499 | J35: 765 KV D/C POWER GRID(BKN-MGA)
A36: =A35+1 -> 31 | B36: =C35 -> 27/0 | C36: 28/0 | E36: 2.5476 | F36: =E36 -> 2.5476 | G36: 45455 | H36: 45499 | I36: 45499
A37: =A36+1 -> 32 | B37: =C36 -> 28/0 | C37: 29/0 | E37: 0.2118 | F37: =E37 -> 0.2118 | G37: 45455 | H37: 45499 | I37: 45499 | J37: Amritsar Jamnagar Expressway
A38: =A37+1 -> 33 | B38: =C37 -> 29/0 | C38: 30/0 | E38: 4.9547 | F38: =E38 -> 4.9547 | G38: 45455 | H38: 45499 | I38: 45499
A39: =A38+1 -> 34 | B39: =C38 -> 30/0 | C39: 31/0 | E39: 4.2189 | F39: =E39 -> 4.2189 | G39: 45455 | H39: 45499 | I39: 45499
A40: =A39+1 -> 35 | B40: =C39 -> 31/0 | C40: 32/0 | E40: 4.3323 | F40: =E40 -> 4.3323 | G40: 45455 | H40: 45499 | I40: 45499
A41: =A40+1 -> 36 | B41: =C40 -> 32/0 | C41: 33/0 | E41: 4.1241 | F41: =E41 -> 4.1241 | G41: 45502 | H41: 45516 | I41: 45516 | J41: STATE HIGHWAY SH-93
A42: =A41+1 -> 37 | B42: =C41 -> 33/0 | C42: 34/0 | E42: =4049.76/1000 -> 4.04976 | F42: =E42 -> 4.04976 | G42: 45502 | H42: 45502 | I42: 45502
A43: =A42+1 -> 38 | B43: =C42 -> 34/0 | C43: 35/0 | E43: =4898.59/1000 -> 4.89859 | F43: =E43 -> 4.89859 | G43: 45502 | H43: 45502 | I43: 45502
A44: =A43+1 -> 39 | B44: =C43 -> 35/0 | C44: 36/0 | E44: =4916.35/1000 -> 4.91635 | F44: =E44 -> 4.91635 | G44: 45502 | H44: 45502 | I44: 45502
A45: =A44+1 -> 40 | B45: =C44 -> 36/0 | C45: 37/0 | E45: =1745.52/1000 -> 1.74552 | F45: =E45 -> 1.74552 | G45: 45502 | H45: 45502 | I45: 45502
A46: =A45+1 -> 41 | B46: =C45 -> 37/0 | C46: 37A/0 | E46: =2496.39/1000 -> 2.49639 | F46: =E46 -> 2.49639 | G46: 45502 | H46: 45502 | I46: 45502
A47: =A46+1 -> 42 | B47: =C46 -> 37A/0 | C47: 38/0 | E47: =2583.59/1000 -> 2.58359 | F47: =E47 -> 2.58359 | G47: 45502 | H47: 45502 | I47: 45502
A48: =A47+1 -> 43 | B48: =C47 -> 38/0 | C48: 39/0 | E48: =4163.68/1000 -> 4.16368 | F48: =E48 -> 4.16368 | G48: 45502 | H48: 45502 | I48: 45502
A49: =A48+1 -> 44 | B49: =C48 -> 39/0 | C49: 40/0 | E49: =4716.81/1000 -> 4.71681 | F49: =E49 -> 4.71681 | G49: 45502 | H49: 45502 | I49: 45502
A50: =A49+1 -> 45 | B50: =C49 -> 40/0 | C50: 40A/0 | E50: =4665.92/1000 -> 4.66592 | F50: =E50 -> 4.66592 | G50: 45502 | H50: 45502 | I50: 45502
A51: =A50+1 -> 46 | B51: =C50 -> 40A/0 | C51: 41/0 | E51: =410.607/1000 -> 0.410607 | F51: =E51 -> 0.410607 | G51: 45502 | H51: 45502 | I51: 45502
A52: =A51+1 -> 47 | B52: =C51 -> 41/0 | C52: 42/0 | E52: =823.782/1000 -> 0.823782 | F52: =E52 -> 0.823782 | G52: 45502 | H52: 45502 | I52: 45502
A53: =A52+1 -> 48 | B53: =C52 -> 42/0 | C53: 43/0 | E53: =1683.889/1000 -> 1.683889 | F53: =E53 -> 1.683889 | G53: 45502 | H53: 45502 | I53: 45502
A54: =A53+1 -> 49 | B54: =C53 -> 43/0 | C54: 44/0 | E54: =3436.41/1000 -> 3.43641 | F54: =E54 -> 3.43641 | G54: 45502 | H54: 45502 | I54: 45502
A55: =A54+1 -> 50 | B55: 44/0 | C55: 46/0 | E55: =2591.68/1000 -> 2.59168 | F55: =E55 -> 2.59168 | G55: 45708 | H55: 45708 | I55: 45708
A64: Total | E64: =SUBTOTAL(9,E6:E55) -> 117.84802 | F64: =SUBTOTAL(9,F6:F55) -> 117.84802

Sheet Check Survey 
A1: KEC International Limited
A2: =TA413_PBNTL!A3 -> Name of Line: 765 KV D/C Bikaner III - Neemrana II TL02 LOA Value: 389.96 Crore
A3: Check Survey | G3: =TA413_PBNTL!M1 -> 27.05.2026
A4: Sl.No. | B4: SPAN | D4: Section Length (Km) | E4: Submitted For Approval | F4: Approval date | G4: Remarks
B5: From Section | C5: To Section
A6: 1 | B6: ='Detailed Survey '!B6 -> Gnatry BKN -III | C6: ='Detailed Survey '!C6 -> 1/0 | D6: ='Detailed Survey '!F6 -> 0.15 | E6: 45709 | F6: 45709
A7: =A6+1 -> 2 | B7: ='Detailed Survey '!B7 -> 1/0 | C7: ='Detailed Survey '!C7 -> 2A/0 | D7: ='Detailed Survey '!F7 -> 0.29021 | E7: 45709 | F7: 45709
A8: =A7+1 -> 3 | B8: ='Detailed Survey '!B8 -> 2A/0 | C8: ='Detailed Survey '!C8 -> 3A/0 | D8: ='Detailed Survey '!F8 -> 2.836992 | E8: 45709 | F8: 45709
A9: =A8+1 -> 4 | B9: ='Detailed Survey '!B9 -> 3A/0 | C9: ='Detailed Survey '!C9 -> 3B/0 | D9: ='Detailed Survey '!F9 -> 2.691 | E9: 45709 | F9: 45709
A10: =A9+1 -> 5 | B10: 3B/0 | C10: 4/0 | D10: 1.627 | E10: 45709 | F10: 45709
A11: =A10+1 -> 6 | B11: 4/0 | C11: 4A/0 | D11: 0.709 | E11: 45492 | F11: 45492
A12: =A11+1 -> 7 | B12: 4A/0 | C12: 5/0 | D12: 2.682 | E12: 45492 | F12: 45492
A13: =A12+1 -> 8 | B13: 5/0 | C13: 5A/0 | D13: 4.418 | E13: 45503 | F13: 45503
A14: =A13+1 -> 9 | B14: ='Detailed Survey '!B14 -> 5A/0 | C14: ='Detailed Survey '!C14 -> 6/0 | D14: ='Detailed Survey '!F14 -> 0.41948 | E14: 45500 | F14: 45503
A15: =A14+1 -> 10 | B15: ='Detailed Survey '!B15 -> 6/0 | C15: ='Detailed Survey '!C15 -> 7/0 | D15: ='Detailed Survey '!F15 -> 4.9099 | E15: 45526 | F15: 45523
A16: =A15+1 -> 11 | B16: ='Detailed Survey '!B16 -> 7/0 | C16: ='Detailed Survey '!C16 -> 8/0 | D16: ='Detailed Survey '!F16 -> 5.0833 | E16: 45500 | F16: 45503
A17: =A16+1 -> 12 | B17: ='Detailed Survey '!B17 -> 8/0 | C17: ='Detailed Survey '!C17 -> 9/0 | D17: ='Detailed Survey '!F17 -> 4.9957 | E17: 45456 | F17: 45456
A18: =A17+1 -> 13 | B18: ='Detailed Survey '!B18 -> 9/0 | C18: ='Detailed Survey '!C18 -> 10/0 | D18: ='Detailed Survey '!F18 -> 4.9231 | E18: 45428 | F18: 45428
A19: =A18+1 -> 14 | B19: ='Detailed Survey '!B19 -> 10/0 | C19: ='Detailed Survey '!C19 -> 11/0 | D19: ='Detailed Survey '!F19 -> 1.0051 | E19: 45428 | F19: 45428
A20: =A19+1 -> 15 | B20: ='Detailed Survey '!B20 -> 11/0 | C20: ='Detailed Survey '!C20 -> 12/0 | D20: ='Detailed Survey '!F20 -> 0.2468 | E20: 45497 | G20: NH - 62
A21: =A20+1 -> 16 | B21: ='Detailed Survey '!B21 -> 12/0 | C21: ='Detailed Survey '!C21 -> 13/0 | D21: ='Detailed Survey '!F21 -> 0.3292 | E21: 45497 | F21: 45632 | G21: 132 KV S/C BKN-LKS T/L
A22: =A21+1 -> 17 | B22: ='Detailed Survey '!B22 -> 13/0 | C22: ='Detailed Survey '!C22 -> 14/0 | D22: ='Detailed Survey '!F22 -> 0.8979 | E22: 45682
A23: =A22+1 -> 18 | B23: ='Detailed Survey '!B23 -> 14/0 | C23: ='Detailed Survey '!C23 -> 15/0 | D23: ='Detailed Survey '!F23 -> 0.224 | E23: 45497 | F23: 45678 | G23: 400 KV D/C SUR-BKN
A24: =A23+1 -> 19 | B24: ='Detailed Survey '!B24 -> 15/0 | C24: ='Detailed Survey '!C24 -> 16/0 | D24: ='Detailed Survey '!F24 -> 5.0201 | E24: 45454 | F24: 45454
A25: =A24+1 -> 20 | B25: ='Detailed Survey '!B25 -> 16/0 | C25: ='Detailed Survey '!C25 -> 17/0 | D25: ='Detailed Survey '!F25 -> 0.3861 | E25: 45583 | F25: 45583
A26: =A25+1 -> 21 | B26: ='Detailed Survey '!B26 -> 17/0 | C26: ='Detailed Survey '!C26 -> 18/0 | D26: ='Detailed Survey '!F26 -> 0.4114 | E26: 45583 | F26: 45583
A27: =A26+1 -> 22 | B27: ='Detailed Survey '!B27 -> 18/0 | C27: ='Detailed Survey '!C27 -> 19/0 | D27: ='Detailed Survey '!F27 -> 3.0234 | E27: 45583 | F27: 45583
A28: =A27+1 -> 23 | B28: ='Detailed Survey '!B28 -> 19/0 | C28: ='Detailed Survey '!C28 -> 20/0 | D28: ='Detailed Survey '!F28 -> 0.2795 | E28: 45497 | G28: Railway Line Electrified SingleTrack
A29: =A28+1 -> 24 | B29: ='Detailed Survey '!B29 -> 20/0 | C29: ='Detailed Survey '!C29 -> 21/0 | D29: ='Detailed Survey '!F29 -> 2.5514 | E29: 45465 | F29: 45484
A30: =A29+1 -> 25 | B30: ='Detailed Survey '!B30 -> 21/0 | C30: ='Detailed Survey '!C30 -> 22/0 | D30: ='Detailed Survey '!F30 -> 2.2835 | E30: 45693
A31: =A30+1 -> 26 | B31: ='Detailed Survey '!B31 -> 22/0 | C31: ='Detailed Survey '!C31 -> 23/0 | D31: ='Detailed Survey '!F31 -> 0.2594 | E31: 45497 | F31: 45632 | G31: 220 KV S/C SUR-BKN
A32: =A31+1 -> 27 | B32: ='Detailed Survey '!B32 -> 23/0 | C32: ='Detailed Survey '!C32 -> 24/0 | D32: ='Detailed Survey '!F32 -> 0.9285 | E32: 45497 | F32: 45632
A33: =A32+1 -> 28 | B33: ='Detailed Survey '!B33 -> 24/0 | C33: ='Detailed Survey '!C33 -> 25/0 | D33: ='Detailed Survey '!F33 -> 0.2521 | E33: 45497 | F33: 45632 | G33: 400 KV S/C STP-BKN T/L
A34: =A33+1 -> 29 | B34: ='Detailed Survey '!B34 -> 25/0 | C34: ='Detailed Survey '!C34 -> 26/0 | D34: ='Detailed Survey '!F34 -> 0.2374 | E34: 45497 | F34: 45632
A35: =A34+1 -> 30 | B35: ='Detailed Survey '!B35 -> 26/0 | C35: ='Detailed Survey '!C35 -> 27/0 | D35: ='Detailed Survey '!F35 -> 0.204 | E35: 45497 | F35: 45632 | G35: 765 KV D/C BKN-MGA T/L
A36: =A35+1 -> 31 | B36: ='Detailed Survey '!B36 -> 27/0 | C36: ='Detailed Survey '!C36 -> 28/0 | D36: ='Detailed Survey '!F36 -> 2.5476 | E36: 45476 | F36: 45484
A37: =A36+1 -> 32 | B37: ='Detailed Survey '!B37 -> 28/0 | C37: ='Detailed Survey '!C37 -> 29/0 | D37: ='Detailed Survey '!F37 -> 0.2118 | E37: 45497 | G37: Expressway Crossing (NH754A)
A38: =A37+1 -> 33 | B38: ='Detailed Survey '!B38 -> 29/0 | C38: ='Detailed Survey '!C38 -> 30/0 | D38: ='Detailed Survey '!F38 -> 4.9547 | E38: 45490 | F38: 45491
A39: =A38+1 -> 34 | B39: ='Detailed Survey '!B39 -> 30/0 | C39: ='Detailed Survey '!C39 -> 31/0 | D39: ='Detailed Survey '!F39 -> 4.2189 | E39: 45490 | F39: 45490
A40: =A39+1 -> 35 | B40: ='Detailed Survey '!B40 -> 31/0 | C40: ='Detailed Survey '!C40 -> 32/0 | D40: ='Detailed Survey '!F40 -> 4.3323 | E40: 45475 | F40: 45477
A41: =A40+1 -> 36 | B41: ='Detailed Survey '!B41 -> 32/0 | C41: ='Detailed Survey '!C41 -> 33/0 | D41: ='Detailed Survey '!F41 -> 4.1241 | E41: 45516 | F41: 45516
A42: =A41+1 -> 37 | B42: ='Detailed Survey '!B42 -> 33/0 | C42: ='Detailed Survey '!C42 -> 34/0 | D42: ='Detailed Survey '!F42 -> 4.04976 | E42: 45516 | F42: 45516
A43: =A42+1 -> 38 | B43: ='Detailed Survey '!B43 -> 34/0 | C43: ='Detailed Survey '!C43 -> 35/0 | D43: ='Detailed Survey '!F43 -> 4.89859 | E43: 45516 | F43: 45516
A44: =A43+1 -> 39 | B44: ='Detailed Survey '!B44 -> 35/0 | C44: ='Detailed Survey '!C44 -> 36/0 | D44: ='Detailed Survey '!F44 -> 4.91635 | E44: 45516 | F44: 45516
A45: =A44+1 -> 40 | B45: ='Detailed Survey '!B45 -> 36/0 | C45: ='Detailed Survey '!C45 -> 37/0 | D45: ='Detailed Survey '!F45 -> 1.74552 | E45: 45516 | F45: 45516
A46: =A45+1 -> 41 | B46: ='Detailed Survey '!B46 -> 37/0 | C46: ='Detailed Survey '!C46 -> 37A/0 | D46: ='Detailed Survey '!F46 -> 2.49639 | E46: 45551 | F46: 45551
A47: =A46+1 -> 42 | B47: ='Detailed Survey '!B47 -> 37A/0 | C47: ='Detailed Survey '!C47 -> 38/0 | D47: ='Detailed Survey '!F47 -> 2.58359 | E47: 45551 | F47: 45551
A48: =A47+1 -> 43 | B48: ='Detailed Survey '!B48 -> 38/0 | C48: ='Detailed Survey '!C48 -> 39/0 | D48: ='Detailed Survey '!F48 -> 4.16368 | E48: 45583 | F48: 45583
A49: =A48+1 -> 44 | B49: ='Detailed Survey '!B49 -> 39/0 | C49: ='Detailed Survey '!C49 -> 40/0 | D49: ='Detailed Survey '!F49 -> 4.71681 | E49: 45597 | F49: 45597
... A52: =A51+1 -> 47 | B52: ='Detailed Survey '!B52 -> 41/0 | C52: ='Detailed Survey '!C52 -> 42/0 | D52: ='Detailed Survey '!F52 -> 0.823782 | E52: 45597 | F52: 45597
A53: =A52+1 -> 48 | B53: =C52 -> 42/0 | C53: 43/0 | D53: 1.683889 | E53: 45597 | F53: 45597
A54: =A53+1 -> 49 | B54: =C53 -> 43/0 | C54: 44/0 | D54: 3.43641 | E54: 45597 | F54: 45597
A55: =A54+1 -> 50 | B55: 44/0 | C55: 46/0 | D55: 2.59168 | E55: 45708 | F55: 45708
A57: Total | D57: =SUM(D6:D55) -> 117.84786

Sheet Earthing
A1: =Foundation!A1 -> KEC International Limited
A2: =Foundation!A2 -> TA413 : 765 KV D/C Bikaner III - Neemrana II TL02
A3: Details of Earthing | J3: =TA413_PBNTL!M1 -> 27.05.2026
A4: CUMM. SR.NO | B4: MONTH SR.NO. | C4: Loc. No. | D4: Type of Tower | E4: Type of Classification | F4: Start | G4: Complete | H4: Name of the Contractor | I4: Name of Supervisor | J4: Rev Month | K4: Remarks
A5: 1 | B5: =SUBTOTAL(103,$C$5:C5) -> 1 | C5: 8/10 | D5: DA+0 | E5: Sandy | F5: 45522 | G5: 45522 | H5: Sanjay Construction | I5: Reshpaul Tyagi | J5: Aug'2024 | K5: Completed
A6: 2 | B6: =SUBTOTAL(103,$C$5:C6) -> 2 | C6: 8/9 | D6: =VLOOKUP(C6,Foundation!$C$5:$D$143,2,0) -> DA+3 | E6: Sandy | F6: 45522 | G6: 45522 | H6: Sanjay Construction | I6: Reshpaul Tyagi | J6: Aug'2024 | K6: Completed
A7: 3 | B7: =SUBTOTAL(103,$C$5:C7) -> 3 | C7: 8/8 | D7: =VLOOKUP(C7,Foundation!$C$5:$D$143,2,0) -> DA+9 | E7: Sandy | F7: 45522 | G7: 45522 | H7: Sanjay Construction | I7: Reshpaul Tyagi | J7: Aug'2024 | K7: Completed
A8: 4 | B8: =SUBTOTAL(103,$C$5:C8) -> 4 | C8: 8/5 | D8: =VLOOKUP(C8,Foundation!$C$5:$D$143,2,0) -> DA+9 | E8: Sandy | F8: 45524 | G8: 45524 | H8: Sanjay Construction | I8: Reshpaul Tyagi | J8: Aug'2024 | K8: Completed
A9: 5 | B9: =SUBTOTAL(103,$C$5:C9) -> 5 | C9: 8/6 | D9: =VLOOKUP(C9,Foundation!$C$5:$D$143,2,0) -> DA+3 | E9: Sandy | F9: 45524 | G9: 45524 | H9: Sanjay Construction | I9: Reshpaul Tyagi | J9: Aug'2024 | K9: Completed
A10: 6 | B10: =SUBTOTAL(103,$C$5:C10) -> 6 | C10: 8/7 | D10: =VLOOKUP(C10,Foundation!$C$5:$D$143,2,0) -> DA+3 | E10: Sandy | F10: 45524 | G10: 45524 | H10: Sanjay Construction | I10: Reshpaul Tyagi | J10: Aug'2024 | K10: Completed
A11: 7 | B11: =SUBTOTAL(103,$C$5:C11) -> 7 | C11: 9/3 | D11: =VLOOKUP(C11,Foundation!$C$5:$D$143,2,0) -> DA+0 | E11: Sandy | F11: 45528 | G11: 45528 | H11: Sanjay Construction | I11: Reshpaul Tyagi | J11: Aug'2024 | K11: Completed
A12: 8 | B12: =SUBTOTAL(103,$C$5:C12) -> 8 | C12: 9/4 | D12: =IFERROR(VLOOKUP(C12,Foundation!$C$5:$D$143,2,0),"") -> DA+6 | E12: Sandy | F12: 45528 | G12: 45528 | H12: Sanjay Construction | I12: Reshpaul Tyagi | J12: Aug'2024 | K12: Completed
A13: 9 | B13: =SUBTOTAL(103,$C$5:C13) -> 9 | C13: 9/1 | D13: =IFERROR(VLOOKUP(C13,Foundation!$C$5:$D$143,2,0),"") -> DA+3 | E13: Sandy | F13: 45530 | G13: 45530 | H13: Sanjay Construction | I13: Reshpaul Tyagi | J13: Aug'2024 | K13: Completed
A14: 10 | B14: =SUBTOTAL(103,$C$5:C14) -> 10 | C14: 7A/2 | D14: =IFERROR(VLOOKUP(C14,Foundation!$C$5:$D$143,2,0),"") -> DA+3 | E14: Sandy | F14: 45541 | G14: 45541 | H14: Sanjay Construction | I14: Reshpaul Tyagi | J14: Sep'2024 | K14: Completed
A15: 11 | B15: =SUBTOTAL(103,$C$5:C15) -> 11 | C15: 5/8 | D15: =IFERROR(VLOOKUP(C15,Foundation!$C$5:$D$143,2,0),"") -> DA+6 | E15: Sandy | F15: 45545 | G15: 45545 | H15: Sanjay Construction | I15: Ankit Yadav | J15: Sep'2024 | K15: Completed
A16: 12 | B16: =SUBTOTAL(103,$C$5:C16) -> 12 | C16: 5/10 | D16: =IFERROR(VLOOKUP(C16,Foundation!$C$5:$D$143,2,0),"") -> DA+9 | E16: Sandy | F16: 45544 | G16: 45544 | H16: Sanjay Construction | I16: Ankit Yadav | J16: Sep'2024 | K16: Completed
A17: 13 | B17: =SUBTOTAL(103,$C$5:C17) -> 13 | C17: 6/2 | D17: =IFERROR(VLOOKUP(C17,Foundation!$C$5:$D$143,2,0),"") -> DA+6 | E17: Sandy | F17: 45545 | G17: 45545 | H17: Sanjay Construction | I17: Reshpaul Tyagi | J17: Sep'2024 | K17: Completed
A18: 14 | B18: =SUBTOTAL(103,$C$5:C18) -> 14 | C18: 6/1 | D18: =IFERROR(VLOOKUP(C18,Foundation!$C$5:$D$143,2,0),"") -> DA+9 | E18: Sandy | F18: 45545 | G18: 45545 | H18: Sanjay Construction | I18: Reshpaul Tyagi | J18: Sep'2024 | K18: Completed
A19: 15 | B19: =SUBTOTAL(103,$C$5:C19) -> 15 | C19: 6/12 | D19: =IFERROR(VLOOKUP(C19,Foundation!$C$5:$D$143,2,0),"") -> DA+1.5 | E19: Sandy | F19: 45550 | G19: 45550 | H19: Sanjay Construction | I19: Reshpaul Tyagi | J19: Sep'2024 | K19: Completed
A20: 16 | B20: =SUBTOTAL(103,$C$5:C20) -> 16 | C20: 6/11 | D20: =IFERROR(VLOOKUP(C20,Foundation!$C$5:$D$143,2,0),"") -> DA-1.5 | E20: Sandy | F20: 45550 | G20: 45550 | H20: Sanjay Construction | I20: Reshpaul Tyagi | J20: Sep'2024 | K20: Completed
A21: 17 | B21: =SUBTOTAL(103,$C$5:C21) -> 17 | C21: 7A/3 | D21: =IFERROR(VLOOKUP(C21,Foundation!$C$5:$D$143,2,0),"") -> DA+3 | E21: Sandy | F21: 45550 | G21: 45550 | H21: Sanjay Construction | I21: Reshpaul Tyagi | J21: Sep'2024 | K21: Completed
A22: 18 | B22: 18 | C22: 4A/3 | D22: =IFERROR(VLOOKUP(C22,Foundation!$C$5:$D$143,2,0),"") -> DA+9 | E22: Sandy | F22: 45551 | G22: 45551 | H22: Sanjay Construction | I22: Reshpaul Tyagi | J22: Sep'2024 | K22: Completed
A23: 19 | B23: 19 | C23: 5/6 | D23: =IFERROR(VLOOKUP(C23,Foundation!$C$5:$D$143,2,0),"") -> DA+3 | E23: Sandy | F23: 45555 | G23: 45555 | H23: Sanjay Construction | I23: Reshpaul Tyagi | J23: Sep'2024 | K23: Completed
A24: 20 | B24: 20 | C24: 5/7 | D24: =IFERROR(VLOOKUP(C24,Foundation!$C$5:$D$143,2,0),"") -> DA+9 | E24: Sandy | F24: 45555 | G24: 45555 | H24: Sanjay Construction | I24: Reshpaul Tyagi | J24: Sep'2024 | K24: Completed
A25: 21 | B25: 21 | C25: 6/3 | D25: =IFERROR(VLOOKUP(C25,Foundation!$C$5:$D$143,2,0),"") -> DA+3 | E25: Sandy | F25: 45547 | G25: =F25 -> 45547 | H25: Sanjay Construction | I25: Reshpaul Tyagi | J25: Sep'2024 | K25: Completed
A26: 22 | B26: 22 | C26: 4A/4 | D26: =IFERROR(VLOOKUP(C26,Foundation!$C$5:$D$143,2,0),"") -> DA+6 | E26: Sandy | F26: 45548 | G26: =F26 -> 45548 | H26: Sanjay Construction | I26: Reshpaul Tyagi | J26: Sep'2024 | K26: Completed
A27: 23 | B27: 23 | C27: 4A/5 | D27: =IFERROR(VLOOKUP(C27,Foundation!$C$5:$D$143,2,0),"") -> DA+9 | E27: Sandy | F27: 45547 | G27: =F27 -> 45547 | H27: Sanjay Construction | I27: Reshpaul Tyagi | J27: Sep'2024 | K27: Completed
A28: 24 | B28: 24 | C28: 7A/5 | D28: =IFERROR(VLOOKUP(C28,Foundation!$C$5:$D$143,2,0),"") -> DA+3 | E28: Sandy | F28: 45540 | G28: =F28 -> 45540 | H28: Sanjay Construction | I28: Reshpaul Tyagi | J28: Sep'2024 | K28: Completed
A29: 25 | B29: 25 | C29: 7A/4 | D29: =IFERROR(VLOOKUP(C29,Foundation!$C$5:$D$143,2,0),"") -> DA+3 | E29: Sandy | F29: 45540 | G29: =F29 -> 45540 | H29: Sanjay Construction | I29: Reshpaul Tyagi | J29: Sep'2024 | K29: Completed
A30: 26 | B30: 26 | C30: 7A/1 | D30: =IFERROR(VLOOKUP(C30,Foundation!$C$5:$D$143,2,0),"") -> DA+1.5 | E30: Sandy | F30: 45540 | G30: =F30 -> 45540 | H30: Sanjay Construction | I30: Reshpaul Tyagi | J30: Sep'2024 | K30: Completed
A31: 27 | B31: 1 | C31: 6/4 | D31: =IFERROR(VLOOKUP(C31,Foundation!$C$5:$D$143,2,0),"") -> DA+9 | E31: Sandy | F31: 45576 | G31: =F31 -> 45576 | H31: Sanjay Construction | I31: Reshpaul Tyagi | J31: Oct'2024 | K31: Completed
A32: 28 | B32: 2 | C32: 6/6 | D32: =IFERROR(VLOOKUP(C32,Foundation!$C$5:$D$143,2,0),"") -> DA-3 | E32: Sandy | F32: 45576 | G32: =F32 -> 45576 | H32: Sanjay Construction | I32: Reshpaul Tyagi | J32: Oct'2024 | K32: Completed
A33: 29 | B33: 3 | C33: 6/9 | D33: =IFERROR(VLOOKUP(C33,Foundation!$C$5:$D$143,2,0),"") -> DA+6 | E33: Sandy | F33: 45576 | G33: =F33 -> 45576 | H33: Sanjay Construction | I33: Reshpaul Tyagi | J33: Oct'2024 | K33: Completed
A34: 30 | B34: 4 | C34: 6/10 | D34: =IFERROR(VLOOKUP(C34,Foundation!$C$5:$D$143,2,0),"") -> DA+1.5 | E34: Sandy | F34: 45576 | G34: =F34 -> 45576 | H34: Sanjay Construction | I34: Reshpaul Tyagi | J34: Oct'2024 | K34: Completed
A35: 31 | B35: 5 | C35: 7/1 | D35: =IFERROR(VLOOKUP(C35,Foundation!$C$5:$D$143,2,0),"") -> DA-3 | E35: Sandy | F35: 45576 | G35: =F35 -> 45576 | H35: Sanjay Construction | I35: Reshpaul Tyagi | J35: Oct'2024 | K35: Completed
A36: 32 | B36: 6 | C36: 7/3 | D36: =IFERROR(VLOOKUP(C36,Foundation!$C$5:$D$143,2,0),"") -> DA+9 | E36: Sandy | F36: 45576 | G36: =F36 -> 45576 | H36: Sanjay Construction | I36: Reshpaul Tyagi | J36: Oct'2024 | K36: Completed
... A97: 93 | B97: 67 | C97: 34/4 | D97: =IFERROR(VLOOKUP(C97,Foundation!$C$5:$D$143,2,0),"") -> DA+6 | E97: Sandy | F97: 45591 | G97: =F97 -> 45591 | H97: Sanjay Construction | I97: Suraj Kumar | J97: Oct'2024 | K97: Completed
A98: 94 | B98: 68 | C98: 6/0 | D98: =IFERROR(VLOOKUP(C98,Foundation!$C$5:$D$143,2,0),"") -> DB1+9 | E98: Sandy | F98: 27/10/202 | G98: =F98 -> 27/10/202 | H98: Sanjay Construction | I98: Reshpaul Tyagi | J98: Oct'2024 | K98: Completed
A99: 95 | B99: 69 | C99: 5/9 | D99: =IFERROR(VLOOKUP(C99,Foundation!$C$5:$D$143,2,0),"") -> DA+6 | E99: Sandy | F99: 45592 | G99: =F99 -> 45592 | H99: Sanjay Construction | I99: Reshpaul Tyagi | J99: Oct'2024 | K99: Completed
A100: 96 | B100: 70 | C100: 4A/0 | D100: =IFERROR(VLOOKUP(C100,Foundation!$C$5:$D$143,2,0),"") -> DB1+3 | E100: Sandy | F100: 45592 | G100: =F100 -> 45592 | H100: Sanjay Construction | I100: Reshpaul Tyagi | J100: Oct'2024 | K100: Completed
A101: 97 | B101: 1 | C101: 17/0 | D101: =IFERROR(VLOOKUP(C101,Foundation!$C$5:$D$427,2,0),"") -> DC1+3 | E101: Sandy | F101: 45649 | G101: 45649 | H101: HSK Construction | I101: Reshpaul Tyagi | J101: Dec'24 | K101: Completed
A102: 98 | B102: 2 | C102: 18/1 | D102: =IFERROR(VLOOKUP(C102,Foundation!$C$5:$D$427,2,0),"") -> DA+3 | E102: Sandy | F102: 45650 | G102: 45650 | H102: HSK Construction | I102: Reshpaul Tyagi | J102: Dec'24 | K102: Completed
A103: 99 | B103: 3 | C103: 18/2 | D103: =IFERROR(VLOOKUP(C103,Foundation!$C$5:$D$427,2,0),"") -> DA+1.5 | E103: Sandy | F103: 45650 | G103: 45650 | H103: HSK Construction | I103: Reshpaul Tyagi | J103: Dec'24 | K103: Completed
A104: 100 | B104: 4 | C104: 18/3 | D104: =IFERROR(VLOOKUP(C104,Foundation!$C$5:$D$427,2,0),"") -> DA+6 | E104: Sandy | F104: 45650 | G104: 45650 | H104: HSK Construction | I104: Reshpaul Tyagi | J104: Dec'24 | K104: Completed
A105: 101 | B105: 5 | C105: 18/4 | D105: =IFERROR(VLOOKUP(C105,Foundation!$C$5:$D$427,2,0),"") -> DA-3 | E105: Sandy | F105: 45651 | G105: 45651 | H105: HSK Construction | I105: Reshpaul Tyagi | J105: Dec'24 | K105: Completed
A106: 102 | B106: 6 | C106: 18/5 | D106: =IFERROR(VLOOKUP(C106,Foundation!$C$5:$D$427,2,0),"") -> DA+0 | E106: Sandy | F106: 45651 | G106: 45651 | H106: HSK Construction | I106: Reshpaul Tyagi | J106: Dec'24 | K106: Completed
A107: 103 | B107: 7 | C107: 18/0 | D107: =IFERROR(VLOOKUP(C107,Foundation!$C$5:$D$427,2,0),"") -> DB2+6 | E107: Sandy | F107: 45651 | G107: 45651 | H107: HSK Construction | I107: Reshpaul Tyagi | J107: Dec'24 | K107: Completed
A108: 104 | B108: 8 | C108: 38/1 | D108: =IFERROR(VLOOKUP(C108,Foundation!$C$5:$D$427,2,0),"") -> DA+0 | E108: Sandy | F108: 45652 | G108: 45652 | H108: HSK Construction | I108: Jai Prakash | J108: Dec'24 | K108: Completed
A109: 105 | B109: 9 | C109: 38/2 | D109: =IFERROR(VLOOKUP(C109,Foundation!$C$5:$D$427,2,0),"") -> DA+0 | E109: Sandy | F109: 45652 | G109: 45652 | H109: HSK Construction | I109: Jai Prakash | J109: Dec'24 | K109: Completed
A110: 106 | B110: 10 | C110: 38/5 | D110: =IFERROR(VLOOKUP(C110,Foundation!$C$5:$D$427,2,0),"") -> DA+3 | E110: Sandy | F110: 45652 | G110: 45652 | H110: HSK Construction | I110: Jai Prakash | J110: Dec'24 | K110: Completed
A111: 107 | B111: 11 | C111: 38/6 | D111: =IFERROR(VLOOKUP(C111,Foundation!$C$5:$D$427,2,0),"") -> DA+6 | E111: Sandy | F111: 45652 | G111: 45652 | H111: HSK Construction | I111: Jai Prakash | J111: Dec'24 | K111: Completed
A112: 108 | B112: 12 | C112: 38/7 | D112: =IFERROR(VLOOKUP(C112,Foundation!$C$5:$D$427,2,0),"") -> DA+9 | E112: Sandy | F112: 45653 | G112: 45653 | H112: HSK Construction | I112: Jai Prakash | J112: Dec'24 | K112: Completed
... A138: 134 | B138: 10 | C138: 39/3 | D138: =IFERROR(VLOOKUP(C138,Foundation!$C$5:$D$427,2,0),"") -> DA+1.5 | E138: Sandy | F138: 45660 | G138: 45660 | H138: HSK Construction | I138: Jai Prakash | J138: Jan'25 | K138: Completed
A139: 135 | B139: 11 | C139: 40/2 | D139: =IFERROR(VLOOKUP(C139,Foundation!$C$5:$D$427,2,0),"") -> DA+6 | E139: Sandy | F139: 04.01.2025 | G139: 04.01.2025 | H139: HSK Construction | I139: Jai Prakash | J139: Jan'25 | K139: Completed
A140: 136 | B140: 12 | C140: 40/3 | D140: =IFERROR(VLOOKUP(C140,Foundation!$C$5:$D$427,2,0),"") -> DA+3 | E140: Sandy | F140: 04.01.2025 | G140: 04.01.2025 | H140: HSK Construction | I140: Jai Prakash | J140: Jan'25 | K140: Completed
A141: 137 | B141: 13 | C141: 40/4 | D141: =IFERROR(VLOOKUP(C141,Foundation!$C$5:$D$427,2,0),"") -> DA+6 | E141: Sandy | F141: 04.01.2025 | G141: 04.01.2025 | H141: HSK Construction | I141: Jai Prakash | J141: Jan'25 | K141: Completed
A142: 138 | B142: 14 | C142: 40/5 | D142: =IFERROR(VLOOKUP(C142,Foundation!$C$5:$D$427,2,0),"") -> DA+9 | E142: Sandy | F142: 04.01.2025 | G142: 04.01.2025 | H142: HSK Construction | I142: Jai Prakash | J142: Jan'25 | K142: Completed
A143: 139 | B143: 15 | C143: 40/6 | D143: =IFERROR(VLOOKUP(C143,Foundation!$C$5:$D$427,2,0),"") -> DA+9 | E143: Sandy | F143: 04.01.2025 | G143: 04.01.2025 | H143: HSK Construction | I143: Jai Prakash | J143: Jan'25 | K143: Completed
A144: 140 | B144: 16 | C144: 40/7 | D144: =IFERROR(VLOOKUP(C144,Foundation!$C$5:$D$427,2,0),"") -> DA+3 | E144: Sandy | F144: 04.01.2025 | G144: 04.01.2025 | H144: HSK Construction | I144: Jai Prakash | J144: Jan'25 | K144: Completed
A145: 141 | B145: 1 | C145: 33/5 | D145: =IFERROR(VLOOKUP(C145,Foundation!$C$5:$D$427,2,0),"") -> DA+0 | E145: Sandy | F145: 45701 | G145: 45701 | H145: HSK Construction | I145: Jai Prakash | J145: Feb'25 | K145: Completed
A146: 142 | B146: 2 | C146: 33/8 | D146: =IFERROR(VLOOKUP(C146,Foundation!$C$5:$D$427,2,0),"") -> DA+3 | E146: Sandy | F146: 45701 | G146: 45701 | H146: HSK Construction | I146: Jai Prakash | J146: Feb'25 | K146: Completed
A147: 143 | B147: 3 | C147: 33/9 | D147: =IFERROR(VLOOKUP(C147,Foundation!$C$5:$D$427,2,0),"") -> DA+1.5 | E147: Sandy | F147: 45701 | G147: 45701 | H147: HSK Construction | I147: Jai Prakash | J147: Feb'25 | K147: Completed
A148: 144 | B148: 4 | C148: 34/0 | D148: =IFERROR(VLOOKUP(C148,Foundation!$C$5:$D$427,2,0),"") -> DB1+6 | E148: Sandy | F148: 45701 | G148: 45701 | H148: HSK Construction | I148: Jai Prakash | J148: Feb'25 | K148: Completed
A149: 145 | B149: 5 | C149: 34/8 | D149: =IFERROR(VLOOKUP(C149,Foundation!$C$5:$D$427,2,0),"") -> DA+0 | E149: Sandy | F149: 45701 | G149: 45701 | H149: HSK Construction | I149: Jai Prakash | J149: Feb'25 | K149: Completed
A150: 146 | B150: 6 | C150: 35/0 | D150: =IFERROR(VLOOKUP(C150,Foundation!$C$5:$D$427,2,0),"") -> DB2+0 | E150: Sandy | F150: 45701 | G150: 45701 | H150: HSK Construction | I150: Jai Prakash | J150: Feb'25 | K150: Completed
A151: 147 | B151: 7 | C151: 35/4 | D151: =IFERROR(VLOOKUP(C151,Foundation!$C$5:$D$427,2,0),"") -> DA+9 | E151: Sandy | F151: 45702 | G151: 45702 | H151: HSK Construction | I151: Jai Prakash | J151: Feb'25 | K151: Completed
A152: 148 | B152: 8 | C152: 35/8 | D152: =IFERROR(VLOOKUP(C152,Foundation!$C$5:$D$427,2,0),"") -> DA+6 | E152: Sandy | F152: 45702 | G152: 45702 | H152: HSK Construction | I152: Jai Prakash | J152: Feb'25 | K152: Completed
A153: 149 | B153: 9 | C153: 35/9 | D153: =IFERROR(VLOOKUP(C153,Foundation!$C$5:$D$427,2,0),"") -> DA+1.5 | E153: Sandy | F153: 45702 | G153: 45702 | H153: HSK Construction | I153: Jai Prakash | J153: Feb'25 | K153: Completed
A154: 150 | B154: 10 | C154: 35/11 | D154: =IFERROR(VLOOKUP(C154,Foundation!$C$5:$D$427,2,0),"") -> DA+3 | E154: Sandy | F154: 45702 | G154: 45702 | H154: HSK Construction | I154: Jai Prakash | J154: Feb'25 | K154: Completed
A155: 151 | B155: 11 | C155: 36/0 | D155: =IFERROR(VLOOKUP(C155,Foundation!$C$5:$D$427,2,0),"") -> DB2+3 | E155: Sandy | F155: 45702 | G155: 45702 | H155: HSK Construction | I155: Jai Prakash | J155: Feb'25 | K155: Completed
A156: 152 | B156: 12 | C156: 30/0 | D156: =IFERROR(VLOOKUP(C156,Foundation!$C$5:$D$427,2,0),"") -> DB1+0 | E156: Sandy | F156: 45704 | G156: 45704 | H156: HSK Construction | I156: Jai Prakash | J156: Feb'25 | K156: Completed
... A187: 183 | B187: 6 | C187: 41/0 | D187: =IFERROR(VLOOKUP(C187,Foundation!$C$5:$D$427,2,0),"") -> DB1+9 | E187: Sandy | F187: 45750 | G187: 45750 | H187: Sanjay Construction | I187: Abul | J187: April'25 | K187: Completed
A188: 184 | B188: 7 | C188: 42/0 | D188: =IFERROR(VLOOKUP(C188,Foundation!$C$5:$D$427,2,0),"") -> DB2+0 | E188: Sandy | F188: 45751 | G188: =F188 -> 45751 | H188: Sanjay Construction | I188: Abul | J188: April'25 | K188: Completed
A189: 185 | B189: 8 | C189: 42/1 | D189: =IFERROR(VLOOKUP(C189,Foundation!$C$5:$D$427,2,0),"") -> DA+3 | E189: Sandy | F189: 45751 | G189: =F189 -> 45751 | H189: Sanjay Construction | I189: Abul | J189: April'25 | K189: Completed
A190: 186 | B190: 9 | C190: 42/2 | D190: =IFERROR(VLOOKUP(C190,Foundation!$C$5:$D$427,2,0),"") -> DA+9 | E190: Sandy | F190: 45751 | G190: =F190 -> 45751 | H190: Sanjay Construction | I190: Abul | J190: April'25 | K190: Completed
A191: 187 | B191: 10 | C191: 42/3 | D191: =IFERROR(VLOOKUP(C191,Foundation!$C$5:$D$427,2,0),"") -> DB1+9 | E191: Sandy | F191: 45751 | G191: =F191 -> 45751 | H191: Sanjay Construction | I191: Abul | J191: April'25 | K191: Completed
A192: 188 | B192: 11 | C192: 43/2 | D192: =IFERROR(VLOOKUP(C192,Foundation!$C$5:$D$427,2,0),"") -> DA+6 | E192: Sandy | F192: 45752 | G192: =F192 -> 45752 | H192: Sanjay Construction | I192: Abul | J192: April'25 | K192: Completed
A193: 189 | B193: 12 | C193: 43/3 | D193: =IFERROR(VLOOKUP(C193,Foundation!$C$5:$D$427,2,0),"") -> DA-1.5 | E193: Sandy | F193: 45752 | G193: =F193 -> 45752 | H193: Sanjay Construction | I193: Abul | J193: April'25 | K193: Completed
A194: 190 | B194: 13 | C194: 43/4 | D194: =IFERROR(VLOOKUP(C194,Foundation!$C$5:$D$427,2,0),"") -> DA+0 | E194: Sandy | F194: 45752 | G194: =F194 -> 45752 | H194: Sanjay Construction | I194: Abul | J194: April'25 | K194: Completed
A195: 191 | B195: 14 | C195: 43/6 | D195: =IFERROR(VLOOKUP(C195,Foundation!$C$5:$D$427,2,0),"") -> DA+3 | E195: Sandy | F195: 45752 | G195: =F195 -> 45752 | H195: Sanjay Construction | I195: Abul | J195: April'25 | K195: Completed
A196: 192 | B196: 15 | C196: 43/7 | D196: =IFERROR(VLOOKUP(C196,Foundation!$C$5:$D$427,2,0),"") -> DA+0 | E196: Sandy | F196: 45752 | G196: =F196 -> 45752 | H196: Sanjay Construction | I196: Abul | J196: April'25 | K196: Completed
A197: 193 | B197: 16 | C197: 43/8 | D197: =IFERROR(VLOOKUP(C197,Foundation!$C$5:$D$427,2,0),"") -> DA+9 | E197: Sandy | F197: 45752 | G197: =F197 -> 45752 | H197: Sanjay Construction | I197: Abul | J197: April'25 | K197: Completed
A198: 194 | B198: 17 | C198: 44/1 | D198: =IFERROR(VLOOKUP(C198,Foundation!$C$5:$D$427,2,0),"") -> DA+3 | E198: Sandy | F198: 45753 | G198: =F198 -> 45753 | H198: Sanjay Construction | I198: Abul | J198: April'25 | K198: Completed
A199: 195 | B199: 18 | C199: 44/2 | D199: =IFERROR(VLOOKUP(C199,Foundation!$C$5:$D$427,2,0),"") -> DA+3 | E199: Sandy | F199: 45753 | G199: =F199 -> 45753 | H199: Sanjay Construction | I199: Abul | J199: April'25 | K199: Completed
... A273: 269 | B273: 17 | C273: 4A/2 | D273: =IFERROR(VLOOKUP(C273,Foundation!$C$5:$D$427,2,0),"") -> DA+6 | E273: Sandy | F273: 45783 | G273: =F273 -> 45783 | H273: Sanjay Construction | I273: Sanjay | J273: May'25 | K273: Completed
A274: 270 | B274: 18 | C274: 4A/6 | D274: =IFERROR(VLOOKUP(C274,Foundation!$C$5:$D$427,2,0),"") -> DA+9 | E274: Sandy | F274: 45784 | G274: 45784 | H274: Sanjay Construction | I274: Sanjay | J274: May'25 | K274: Completed
A275: 271 | B275: 19 | C275: 5/0 | D275: =IFERROR(VLOOKUP(C275,Foundation!$C$5:$D$427,2,0),"") -> DB1+6 | E275: Sandy | F275: 45784 | G275: 45784 | H275: Sanjay Construction | I275: Sanjay | J275: May'25 | K275: Completed
A276: 272 | B276: 20 | C276: 5/1 | D276: =IFERROR(VLOOKUP(C276,Foundation!$C$5:$D$427,2,0),"") -> DA+6 | E276: Sandy | F276: 45784 | G276: 45784 | H276: Sanjay Construction | I276: Sanjay | J276: May'25 | K276: Completed
A277: 273 | B277: 21 | C277: 6/7 | D277: =IFERROR(VLOOKUP(C277,Foundation!$C$5:$D$427,2,0),"") -> DA+1.5 | E277: Sandy | F277: 45784 | G277: 45784 | H277: Sanjay Construction | I277: Sanjay | J277: May'25 | K277: Completed
A278: 274 | B278: 22 | C278: 7/6 | D278: =IFERROR(VLOOKUP(C278,Foundation!$C$5:$D$427,2,0),"") -> DA-1.5 | E278: Sandy | F278: 45784 | G278: 45784 | H278: Sanjay Construction | I278: Sanjay | J278: May'25 | K278: Completed
A279: 275 | B279: 23 | C279: 9/0 | D279: =IFERROR(VLOOKUP(C279,Foundation!$C$5:$D$427,2,0),"") -> DB1+12 | E279: Sandy | F279: 45785 | G279: 45785 | H279: Sanjay Construction | I279: Sanjay | J279: May'25 | K279: Completed
A280: 276 | B280: 24 | C280: 21/2 | D280: =IFERROR(VLOOKUP(C280,Foundation!$C$5:$D$427,2,0),"") -> DA+6 | E280: Sandy | F280: 45785 | G280: 45785 | H280: Sanjay Construction | I280: Sanjay | J280: May'25 | K280: Completed
A281: 277 | B281: 25 | C281: 21/3 | D281: =IFERROR(VLOOKUP(C281,Foundation!$C$5:$D$427,2,0),"") -> DA+6 | E281: Sandy | F281: 45785 | G281: 45785 | H281: Sanjay Construction | I281: Sanjay | J281: May'25 | K281: Completed
A282: 278 | B282: 1 | C282: 11/0 | D282: =IFERROR(VLOOKUP(C282,Foundation!$C$5:$D$427,2,0),"") -> DD45+0 | E282: Sandy | F282: 45839 | G282: 45839 | H282: Sanjay Construction | I282: Sanjay | J282: Jul'25 | K282: Completed
A283: 279 | B283: 2 | C283: 12/0 | D283: =IFERROR(VLOOKUP(C283,Foundation!$C$5:$D$427,2,0),"") -> DB1+9 | E283: Sandy | F283: 45839 | G283: 45839 | H283: Sanjay Construction | I283: Sanjay | J283: Jul'25 | K283: Completed
A284: 280 | B284: 3 | C284: 20/3 | D284: =IFERROR(VLOOKUP(C284,Foundation!$C$5:$D$427,2,0),"") -> DA+1.5 | E284: Sandy | F284: 45840 | G284: 45840 | H284: Sanjay Construction | I284: Sanjay | J284: Jul'25 | K284: Completed
A285: 281 | B285: 4 | C285: 20/4 | D285: =IFERROR(VLOOKUP(C285,Foundation!$C$5:$D$427,2,0),"") -> DA+3 | E285: Sandy | F285: 45840 | G285: 45840 | H285: Sanjay Construction | I285: Sanjay | J285: Jul'25 | K285: Completed
... A298: 294 | B298: 2 | C298: 41/1 | D298: =IFERROR(VLOOKUP(C298,Foundation!$C$5:$D$427,2,0),"") -> DA+9 | E298: Sandy | F298: 45967 | G298: 45967 | H298: Sanjay Construction | I298: Susheel | J298: Nov'25 | K298: Completed
A299: 295 | B299: 3 | C299: 43/5 | D299: DCT | E299: Sandy | F299: 45967 | G299: 45967 | H299: Sanjay Construction | I299: Susheel | J299: Nov'25 | K299: Completed
A300: 296 | B300: 4 | C300: 44/0 | D300: =IFERROR(VLOOKUP(C300,Foundation!$C$5:$D$427,2,0),"") -> DB1+6 | E300: Sandy | F300: 45968 | G300: 45968 | H300: Sanjay Construction | I300: Susheel | J300: Nov'25 | K300: Completed
...

Sheet Tack Welding
B1: =OPGW!B2 -> KEC International Limited
B2: =OPGW!B3 -> TA413 : 765 KV D/C Bikaner III - Neemrana II TL02
B3: Details of Tack Welding | J3: =TA413_PBNTL!M1 -> 27.05.2026
B4: CUMM. SR.NO | C4: MONTH SR.NO. | D4: Loc. No. | E4: Type of Tower | F4: Start | G4: Complete | H4: Name of the Contractor | I4: Name of Supervisor | J4: Remarks | K4: Painting
B5: 1 | C5: 1 | D5: 34/4 | E5: =VLOOKUP(D5,Erection!$C$5:$D$51,2,0) -> DA+6 | F5: 45669 | G5: 45669 | H5: MB Sharma | I5: Manoj Kumar Gupta | J5: Completed
B6: 2 | C6: 2 | D6: 34/7 | E6: =VLOOKUP(D6,Erection!$C$5:$D$51,2,0) -> DA+0 | F6: 45670 | G6: 45670 | H6: MB Sharma | I6: Manoj Kumar Gupta | J6: Completed
B7: 3 | C7: 3 | D7: 34/10 | E7: =VLOOKUP(D7,Erection!$C$5:$D$51,2,0) -> DA-3 | F7: 45671 | G7: 45671 | H7: MB Sharma | I7: Manoj Kumar Gupta | J7: Completed
B8: 4 | C8: 4 | D8: 34/3 | E8: =VLOOKUP(D8,Erection!$C$5:$D$51,2,0) -> DA+1.5 | F8: 45672 | G8: 45672 | H8: MB Sharma | I8: Manoj Kumar Gupta | J8: Completed
B9: 5 | C9: 5 | D9: 34/6 | E9: =VLOOKUP(D9,Erection!$C$5:$D$51,2,0) -> DA+3 | F9: 45673 | G9: 45673 | H9: MB Sharma | I9: Manoj Kumar Gupta | J9: Completed
B10: 6 | C10: 6 | D10: 34/5 | E10: =VLOOKUP(D10,Erection!$C$5:$D$51,2,0) -> DA+9 | F10: 45676 | G10: 45676 | H10: MB Sharma | I10: Manoj Kumar Gupta | J10: Completed
B11: 7 | C11: 7 | D11: 34/9 | E11: =VLOOKUP(D11,Erection!$C$5:$D$51,2,0) -> DA+1.5 | F11: 45678 | G11: 45678 | H11: MB Sharma | I11: Manoj Kumar Gupta | J11: Completed
B12: 8 | C12: 8 | D12: 34/12 | E12: =VLOOKUP(D12,Erection!$C$5:$D$51,2,0) -> DA+3 | F12: 45679 | G12: 45679 | H12: MB Sharma | I12: Manoj Kumar Gupta | J12: Completed
B13: 9 | C13: 9 | D13: 34/2 | E13: =VLOOKUP(D13,Erection!$C$5:$D$51,2,0) -> DA+9 | F13: 45682 | G13: 45682 | H13: MB Sharma | I13: Manoj Kumar Gupta | J13: Completed
B14: 10 | C14: 10 | D14: 34/11 | E14: =VLOOKUP(D14,Erection!$C$5:$D$51,2,0) -> DA+1.5 | F14: 45684 | G14: 45684 | H14: MB Sharma | I14: Manoj Kumar Gupta | J14: Completed
B15: 11 | C15: 11 | D15: 35/1 | E15: =VLOOKUP(D15,Erection!$C$5:$D$51,2,0) -> DA+6 | F15: 45686 | G15: 45686 | H15: MB Sharma | I15: Manoj Kumar Gupta | J15: Completed
B16: 12 | C16: 12 | D16: 35/5 | E16: =VLOOKUP(D16,Erection!$C$5:$D$51,2,0) -> DA+9 | F16: 45687 | G16: 45687 | H16: MB Sharma | I16: Manoj Kumar Gupta | J16: Completed
... B27: 23 | C27: 10 | D27: 30/1 | E27: =VLOOKUP(D27,Erection!$C$5:$D$51,2,0) -> DA+0 | F27: 45698 | G27: 45698 | H27: MB Sharma | I27: Manoj Kumar Gupta | J27: Completed
B28: 24 | C28: 11 | D28: 7A/2 | E28: =VLOOKUP(D28,Erection!$C$5:$D$750,2,0) -> DA+3 | F28: 45697 | G28: 45697 | H28: MB Sharma | I28: Gangadin Sahoo | J28: Completed
B29: 25 | C29: 12 | D29: 7A/3 | E29: =VLOOKUP(D29,Erection!$C$5:$D$750,2,0) -> DA+3 | F29: 45698 | G29: 45698 | H29: MB Sharma | I29: Gangadin Sahoo | J29: Completed
B30: 26 | C30: 13 | D30: 7/1 | E30: =VLOOKUP(D30,Erection!$C$5:$D$750,2,0) -> DA-3 | F30: 45698 | G30: 45698 | H30: MB Sharma | I30: Gangadin Sahoo | J30: Completed
B31: 27 | C31: 14 | D31: 7A/4 | E31: =VLOOKUP(D31,Erection!$C$5:$D$750,2,0) -> DA+3 | F31: 45699 | G31: 45699 | H31: MB Sharma | I31: Gangadin Sahoo | J31: Completed
B32: 28 | C32: 15 | D32: 7A/5 | E32: =VLOOKUP(D32,Erection!$C$5:$D$750,2,0) -> DA+3 | F32: 45699 | G32: 45699 | H32: MB Sharma | I32: Gangadin Sahoo | J32: Completed
B33: 29 | C33: 16 | D33: 8/1 | E33: =VLOOKUP(D33,Erection!$C$5:$D$750,2,0) -> DA-3 | F33: 45700 | G33: 45700 | H33: MB Sharma | I33: Gangadin Sahoo | J33: Completed
B34: 30 | C34: 17 | D34: 8/2 | E34: =VLOOKUP(D34,Erection!$C$5:$D$750,2,0) -> DA+6 | F34: 45701 | G34: 45701 | H34: MB Sharma | I34: Gangadin Sahoo | J34: Completed
B35: 31 | C35: 18 | D35: 8/5 | E35: =VLOOKUP(D35,Erection!$C$5:$D$750,2,0) -> DA+9 | F35: 45702 | G35: 45702 | H35: MB Sharma | I35: Gangadin Sahoo | J35: Completed
B36: 32 | C36: 19 | D36: 8/6 | E36: =VLOOKUP(D36,Erection!$C$5:$D$750,2,0) -> DA+3 | F36: 45703 | G36: 45703 | H36: MB Sharma | I36: Gangadin Sahoo | J36: Completed
B37: 33 | C37: 20 | D37: 8/7 | E37: =VLOOKUP(D37,Erection!$C$5:$D$750,2,0) -> DA+3 | F37: 45704 | G37: 45704 | H37: MB Sharma | I37: Gangadin Sahoo | J37: Completed
B38: 34 | C38: 21 | D38: 8/8 | E38: =VLOOKUP(D38,Erection!$C$5:$D$750,2,0) -> DA+9 | F38: 45705 | G38: 45705 | H38: MB Sharma | I38: Gangadin Sahoo | J38: Completed
B39: 35 | C39: 22 | D39: 8/9 | E39: =VLOOKUP(D39,Erection!$C$5:$D$750,2,0) -> DA+3 | F39: 45705 | G39: 45705 | H39: MB Sharma | I39: Gangadin Sahoo | J39: Completed
... B122: 118 | C122: 2 | D122: 5/2 | E122: =VLOOKUP(D122,Erection!$C$5:$D$750,2,0) -> DA+9 | F122: 45994 | G122: 45995 | H122: MB Sharma | I122: Sanjay Jumar | J122: Completed
B123: 119 | C123: 3 | D123: 5/3 | E123: =VLOOKUP(D123,Erection!$C$5:$D$750,2,0) -> DA+9 | F123: 46012 | G123: 46012 | H123: MB Sharma | J123: Completed
B124: 120 | C124: 4 | D124: 5/4 | E124: =VLOOKUP(D124,Erection!$C$5:$D$750,2,0) -> DA-1.5 | F124: 46014 | G124: 46014 | H124: MB Sharma | J124: Completed
B125: 121 | C125: 5 | D125: 5/5 | E125: =VLOOKUP(D125,Erection!$C$5:$D$750,2,0) -> DA+6 | F125: 46016 | G125: 46016 | H125: MB Sharma | J125: Completed
B126: 122 | C126: 6 | D126: 4A/3 | E126: =VLOOKUP(D126,Erection!$C$5:$D$750,2,0) -> DA+9 | F126: 46018 | G126: 46018 | H126: MB Sharma | J126: Completed
B127: 123 | C127: 7 | D127: 4A/2 | E127: =VLOOKUP(D127,Erection!$C$5:$D$750,2,0) -> DA+6 | F127: 46019 | G127: 46019 | H127: MB Sharma | J127: Completed
B128: 124 | C128: 8 | D128: 4A/1 | E128: =VLOOKUP(D128,Erection!$C$5:$D$750,2,0) -> DA+6 | F128: 46020 | G128: 46020 | H128: MB Sharma | J128: Completed
B129: 125 | C129: 9 | D129: 4A/4 | E129: =VLOOKUP(D129,Erection!$C$5:$D$750,2,0) -> DA+6 | F129: 46021 | G129: 46021 | H129: MB Sharma | J129: Completed
B130: 126 | C130: 10 | D130: 4A/5 | E130: =VLOOKUP(D130,Erection!$C$5:$D$750,2,0) -> DA+9 | F130: 46022 | G130: 46022 | H130: MB Sharma | J130: Completed
B131: 127 | C131: 1 | D131: 4A/6 | E131: =VLOOKUP(D131,Erection!$C$5:$D$750,2,0) -> DA+9 | F131: 46023 | G131: 46023 | H131: MB Sharma | J131: Completed
B132: 128 | C132: 2 | D132: 31/7 | E132: =VLOOKUP(D132,Erection!$C$5:$D$750,2,0) -> DA+0 | F132: 46024 | G132: 46024 | H132: MB Sharma | J132: Completed
B133: 129 | C133: 3 | D133: 31/8 | E133: =VLOOKUP(D133,Erection!$C$5:$D$750,2,0) -> DA+0 | F133: 46025 | G133: 46025 | H133: MB Sharma | J133: Completed
B134: 130 | C134: 4 | D134: 31/10 | E134: =VLOOKUP(D134,Erection!$C$5:$D$750,2,0) -> DA+4.5 | F134: 46026 | G134: 46026 | H134: MB Sharma | J134: Completed
... B145: 141 | C145: 15 | D145: 33/7 | E145: =VLOOKUP(D145,Erection!$C$5:$D$750,2,0) -> DA+6 | F145: 46044 | G145: 46044 | H145: MB Sharma | J145: Completed
B146: 142 | C146: 1 | D146: 1/0 | E146: =VLOOKUP(D146,Erection!$C$5:$D$750,2,0) -> DD60+0 | F146: 46054 | G146: 46054 | H146: MB Sharma | J146: Completed | K146: Not completed
B147: 143 | C147: 2 | D147: 2A/0 | E147: =VLOOKUP(D147,Erection!$C$5:$D$750,2,0) -> DD45+0 | F147: 46055 | G147: 46055 | H147: MB Sharma | J147: Completed | K147: Not completed
B148: 144 | C148: 3 | D148: 2A/1 | E148: =VLOOKUP(D148,Erection!$C$5:$D$750,2,0) -> DA+0 | F148: 46056 | G148: 46056 | H148: MB Sharma | J148: Completed | K148: Not completed
B149: 145 | C149: 4 | D149: 2A/2 | E149: =VLOOKUP(D149,Erection!$C$5:$D$750,2,0) -> DA+3 | F149: 46056 | G149: 46056 | H149: MB Sharma | J149: Completed | K149: Not completed
B150: 146 | C150: 5 | D150: 2A/3 | E150: =VLOOKUP(D150,Erection!$C$5:$D$750,2,0) -> DA+3 | F150: 46057 | G150: 46057 | H150: MB Sharma | J150: Completed | K150: Not completed
B151: 147 | C151: 6 | D151: 2A/4 | E151: =VLOOKUP(D151,Erection!$C$5:$D$750,2,0) -> DA+3 | F151: 46057 | G151: 46057 | H151: MB Sharma | J151: Completed | K151: Not completed
B152: 148 | C152: 7 | D152: 2A/5 | E152: =VLOOKUP(D152,Erection!$C$5:$D$750,2,0) -> DA+3 | F152: 46058 | G152: 46058 | H152: MB Sharma | J152: Completed | K152: Not completed
B153: 149 | C153: 8 | D153: 2A/6 | E153: =VLOOKUP(D153,Erection!$C$5:$D$750,2,0) -> DA+6 | F153: 46059 | G153: 46059 | H153: MB Sharma | J153: Completed | K153: Not completed
B154: 150 | C154: 9 | D154: 3A/1 | E154: =VLOOKUP(D154,Erection!$C$5:$D$750,2,0) -> DA+3 | F154: 46060 | G154: 46060 | H154: MB Sharma | J154: Completed | K154: Not completed
B155: 151 | C155: 10 | D155: 3A/2 | E155: =VLOOKUP(D155,Erection!$C$5:$D$750,2,0) -> DA+3 | F155: 46061 | G155: 46061 | H155: MB Sharma | J155: Completed | K155: Not completed
B156: 152 | C156: 11 | D156: 3A/3 | E156: =VLOOKUP(D156,Erection!$C$5:$D$750,2,0) -> DA+0 | F156: 46062 | G156: 46062 | H156: MB Sharma | J156: Completed
B157: 153 | C157: 12 | D157: 3A/4 | E157: =VLOOKUP(D157,Erection!$C$5:$D$750,2,0) -> DA+0 | F157: 46063 | G157: 46063 | H157: MB Sharma | J157: Completed
B158: 154 | C158: 13 | D158: 3A/5 | E158: =VLOOKUP(D158,Erection!$C$5:$D$750,2,0) -> DA+3 | F158: 46064 | G158: 46064 | H158: MB Sharma | J158: Completed
B159: 155 | C159: 14 | D159: 3A/6 | E159: =VLOOKUP(D159,Erection!$C$5:$D$750,2,0) -> DA+0 | F159: 46065 | G159: 46065 | H159: MB Sharma | J159: Completed
B160: 156 | C160: 15 | D160: 3B/0 | E160: =VLOOKUP(D160,Erection!$C$5:$D$750,2,0) -> DB1+9 | F160: 46066 | G160: 46066 | H160: MB Sharma | J160: Completed | K160: Not completed
B161: 157 | C161: 16 | D161: 3B/1 | E161: =VLOOKUP(D161,Erection!$C$5:$D$750,2,0) -> DA+3 | F161: 46067 | G161: 46067 | H161: MB Sharma | J161: Completed
B162: 158 | C162: 17 | D162: 3B/2 | E162: =VLOOKUP(D162,Erection!$C$5:$D$750,2,0) -> DA+9 | F162: 46068 | G162: 46068 | H162: MB Sharma | J162: Completed
B163: 159 | C163: 18 | D163: 3B/3 | E163: =VLOOKUP(D163,Erection!$C$5:$D$750,2,0) -> DA+6 | F163: 46069 | G163: 46069 | H163: MB Sharma | J163: Completed
B164: 160 | C164: 19 | D164: 4/0 | E164: =VLOOKUP(D164,Erection!$C$5:$D$750,2,0) -> DB2+9 | F164: 46070 | G164: 46070 | H164: MB Sharma | J164: Completed | K164: Not completed
B165: 161 | C165: 20 | D165: 4/5 | E165: =VLOOKUP(D165,Erection!$C$5:$D$750,2,0) -> DA+6 | F165: 46071 | G165: 46071 | H165: MB Sharma | J165: Completed | K165: Not completed
B166: 162 | C166: 21 | D166: 4A/0 | E166: =VLOOKUP(D166,Erection!$C$5:$D$750,2,0) -> DB1+3 | F166: 46072 | G166: 46072 | H166: MB Sharma | J166: Completed | K166: Not completed
B167: 163 | C167: 22 | D167: 5/0 | E167: =VLOOKUP(D167,Erection!$C$5:$D$750,2,0) -> DB1+6 | F167: 46073 | G167: 46073 | H167: MB Sharma | J167: Completed | K167: Not completed
B168: 164 | C168: 23 | D168: 5/8 | E168: =VLOOKUP(D168,Erection!$C$5:$D$750,2,0) -> DA+6 | F168: 46074 | G168: 46074 | H168: MB Sharma | J168: Completed
B169: 165 | C169: 24 | D169: 5/9 | E169: =VLOOKUP(D169,Erection!$C$5:$D$750,2,0) -> DA+6 | F169: 46075 | G169: 46075 | H169: MB Sharma | J169: Completed
B170: 166 | C170: 25 | D170: 5A/0 | E170: =VLOOKUP(D170,Erection!$C$5:$D$750,2,0) -> DB1+12 | F170: 46076 | G170: 46076 | H170: MB Sharma | J170: Completed
B171: 167 | C171: 26 | D171: 7/4 | E171: =VLOOKUP(D171,Erection!$C$5:$D$750,2,0) -> DA+6 | F171: 46077 | G171: 46077 | H171: MB Sharma | J171: Completed
B172: 168 | C172: 27 | D172: 9/0 | E172: =VLOOKUP(D172,Erection!$C$5:$D$750,2,0) -> DB1+12 | F172: 46078 | G172: 46078 | H172: MB Sharma | J172: Completed
B173: 169 | C173: 28 | D173: 15/4 | E173: =VLOOKUP(D173,Erection!$C$5:$D$750,2,0) -> DA+6 | F173: 46079 | G173: 46079 | H173: MB Sharma | J173: Completed
B174: 170 | C174: 29 | D174: 27/0 | E174: =VLOOKUP(D174,Erection!$C$5:$D$750,2,0) -> DD60+35 | F174: 46080 | G174: 46080 | H174: MB Sharma | J174: Completed | K174: Not completed
B175: 171 | C175: 30 | D175: 29/1 | E175: =VLOOKUP(D175,Erection!$C$5:$D$750,2,0) -> DA+6 | F175: 46081 | G175: 46081 | H175: MB Sharma | J175: Completed
B176: 172 | C176: 1 | D176: 30/0 | E176: =VLOOKUP(D176,Erection!$C$5:$D$750,2,0) -> DB1+0 | F176: 46082 | G176: 46082 | H176: MB Sharma | J176: Completed
B177: 173 | C177: 2 | D177: 30/2 | E177: =VLOOKUP(D177,Erection!$C$5:$D$750,2,0) -> DA+9 | F177: 46083 | G177: 46083 | H177: MB Sharma | J177: Completed | K177: Not completed
B178: 174 | C178: 3 | D178: 30/3 | E178: =VLOOKUP(D178,Erection!$C$5:$D$750,2,0) -> DA+3 | F178: 46086 | G178: 46086 | H178: MB Sharma | J178: Completed
B179: 175 | C179: 4 | D179: 30/4 | E179: =VLOOKUP(D179,Erection!$C$5:$D$750,2,0) -> DA+9 | F179: 46086 | G179: 46086 | H179: MB Sharma | J179: Completed | K179: Not completed
B180: 176 | C180: 5 | D180: 30/5 | E180: =VLOOKUP(D180,Erection!$C$5:$D$750,2,0) -> DA+0 | F180: 46086 | G180: 46086 | H180: MB Sharma | J180: Completed | K180: Not completed
B181: 177 | C181: 6 | D181: 30/6 | E181: =VLOOKUP(D181,Erection!$C$5:$D$750,2,0) -> DA+6 | F181: 46087 | G181: 46087 | H181: MB Sharma | J181: Completed | K181: Not completed
B182: 178 | C182: 7 | D182: 30/7 | E182: =VLOOKUP(D182,Erection!$C$5:$D$750,2,0) -> DA-3 | F182: 46087 | G182: 46087 | H182: MB Sharma | J182: Completed | K182: Not completed
B183: 179 | C183: 8 | D183: 30/8 | E183: =VLOOKUP(D183,Erection!$C$5:$D$750,2,0) -> DA+3 | F183: 46088 | G183: 46088 | H183: MB Sharma | J183: Completed | K183: Not completed
B184: 180 | C184: 9 | D184: 30/9 | E184: =VLOOKUP(D184,Erection!$C$5:$D$750,2,0) -> DA-3 | F184: 46088 | G184: 46088 | H184: MB Sharma | J184: Completed | K184: Not completed
B185: 181 | C185: 10 | D185: 30/10 | E185: =VLOOKUP(D185,Erection!$C$5:$D$750,2,0) -> DA+3 | F185: 46089 | G185: 46089 | H185: MB Sharma | J185: Completed | K185: Not completed
B186: 182 | C186: 11 | D186: 32/1 | E186: =VLOOKUP(D186,Erection!$C$5:$D$750,2,0) -> DA+6 | F186: 46089 | G186: 46089 | H186: MB Sharma | J186: Completed
B187: 183 | C187: 12 | D187: 32/2 | E187: =VLOOKUP(D187,Erection!$C$5:$D$750,2,0) -> DA+9 | F187: 46090 | G187: 46090 | H187: MB Sharma | J187: Completed
B188: 184 | C188: 13 | D188: 32A/1 | E188: =VLOOKUP(D188,Erection!$C$5:$D$750,2,0) -> DA+6 | F188: 46090 | G188: 46090 | H188: MB Sharma | J188: Completed
B189: 185 | C189: 14 | D189: 33/0 | E189: =VLOOKUP(D189,Erection!$C$5:$D$750,2,0) -> DB1+9 | F189: 46091 | G189: 46091 | H189: MB Sharma | J189: Completed
B190: 186 | C190: 15 | D190: 33/1 | E190: =VLOOKUP(D190,Erection!$C$5:$D$750,2,0) -> DA+9 | F190: 46091 | G190: 46091 | H190: MB Sharma | J190: Completed
B191: 187 | C191: 16 | D191: 33/4 | E191: =VLOOKUP(D191,Erection!$C$5:$D$750,2,0) -> DA+3 | F191: 46092 | G191: 46092 | H191: MB Sharma | J191: Completed
B192: 188 | C192: 17 | D192: 33/9 | E192: =VLOOKUP(D192,Erection!$C$5:$D$750,2,0) -> DA+1.5 | F192: 46092 | G192: 46092 | H192: MB Sharma | J192: Completed
B193: 189 | C193: 18 | D193: 35/4 | E193: =VLOOKUP(D193,Erection!$C$5:$D$750,2,0) -> DA+9 | F193: 46093 | G193: 46093 | H193: MB Sharma | J193: Completed
B194: 190 | C194: 19 | D194: 35/6 | E194: =VLOOKUP(D194,Erection!$C$5:$D$750,2,0) -> DA+6 | F194: 46093 | G194: 46093 | H194: MB Sharma | J194: Completed
B195: 191 | C195: 20 | D195: 35/9 | E195: =VLOOKUP(D195,Erection!$C$5:$D$750,2,0) -> DA+1.5 | F195: 46094 | G195: 46094 | H195: MB Sharma | J195: Completed
B196: 192 | C196: 21 | D196: 36A/0 | E196: =VLOOKUP(D196,Erection!$C$5:$D$750,2,0) -> DB1+9 | F196: 46094 | G196: 46094 | H196: MB Sharma | J196: Completed
B197: 193 | C197: 22 | D197: 36A/1 | E197: =VLOOKUP(D197,Erection!$C$5:$D$750,2,0) -> DA+3 | F197: 46095 | G197: 46095 | H197: MB Sharma | J197: Completed
... B199: 195 | C199: 24 | D199: 40/0 | E199: =VLOOKUP(D199,Erection!$C$5:$D$750,2,0) -> DB1+6 | F199: 46096 | G199: 46096 | H199: MB Sharma | J199: Completed
B200: 196 | C200: 25 | D200: 45/0 | E200: =VLOOKUP(D200,Erection!$C$5:$D$750,2,0) -> DB1+9 | F200: =F199 -> 46096 | G200: =F200 -> 46096 | H200: MB Sharma | J200: Completed
B201: 197 | C201: 26 | D201: 9/5 | E201: =VLOOKUP(D201,Erection!$C$5:$D$750,2,0) -> DA+3 | F201: 46097 | G201: 46097 | H201: MB Sharma | J201: Completed | K201: Not completed
B202: 198 | C202: 27 | D202: 9/6 | E202: =VLOOKUP(D202,Erection!$C$5:$D$750,2,0) -> DA+3 | F202: 46097 | G202: 46097 | H202: MB Sharma | J202: Completed | K202: Not completed
B203: 199 | C203: 28 | D203: 9/7 | E203: =VLOOKUP(D203,Erection!$C$5:$D$750,2,0) -> DA+9 | F203: 46098 | G203: 46098 | H203: MB Sharma | J203: Completed | K203: Not completed
...

Sheet  Final checking
A1: Client Name : PowerGrid Bikaner Neemrana Transmission Limited (Power Grid Corporation of India)
A2: 765 kV DC BIKANER-III NEEMRANA-II Transmission Line TA-413 | M2: =I3-J3 -> 11
D3: Bal | F3: =306-F4 -> 0 | G3: =306-G4 -> 2 | H3: =306-H4 -> 4 | I3: =302-I4 -> 47 | J3: =302-J4 -> 36 | K3: =302-K4 -> 107
A4: S. No. | B4: No of | C4: Location | D4: Type of | E4: DS Status as on | F4: =COUNTIFS(F6:F312,F165) -> 306 | G4: =COUNTIFS(G6:G312,G165) -> 304 | H4: =COUNTIFS(H6:H312,H165) -> 302 | I4: =COUNTIFS(I6:I312,"done") -> 255 | J4: =COUNTIFS(J6:J312,"done") -> 266 | K4: =COUNTIFS(K6:K312,"done") -> 195 | L4: Remarks
B5: AP | C5: Tower No. | D5: Tower | F5: Foundation | G5: Earthing | H5: Tower Erection | I5: Tack welding | J5: Final Checking | K5: Stringing
C6: Gantry | D6: Gantry
A7: =SUBTOTAL(103,$C7:C$7) -> 1 | B7: AP-1 | C7: 1/0 | D7: DD60+0 | E7: Approved | F7: Completed | G7: Completed | H7: Completed | I7: Done | J7: Done | K7: Done
A8: =SUBTOTAL(103,$C$7:C8) -> 2 | B8: AP-2A | C8: 2A/0 | D8: DD45+0 | E8: Approved | F8: Completed | G8: Completed | H8: Completed | I8: Done | J8: Done | K8: Done
A9: =SUBTOTAL(103,$C$7:C9) -> 3 | B9: AP-3 | C9: 2A/1 | D9: DA+0 | E9: Approved | F9: Completed | G9: Completed | H9: Completed | I9: Done | J9: Done | K9: Done
A10: =SUBTOTAL(103,$C$7:C10) -> 4 | C10: 2A/2 | D10: DA+3 | E10: Approved | F10: Completed | G10: Completed | H10: Completed | I10: Done | J10: Done | K10: Done
A11: =SUBTOTAL(103,$C$7:C11) -> 5 | C11: 2A/3 | D11: DA+3 | E11: Approved | F11: Completed | G11: Completed | H11: Completed | I11: Done | J11: Done | K11: Done
A12: =SUBTOTAL(103,$C$7:C12) -> 6 | C12: 2A/4 | D12: DA+3 | E12: Approved | F12: Completed | G12: Completed | H12: Completed | I12: Done | J12: Done | K12: Done
A13: =SUBTOTAL(103,$C$7:C13) -> 7 | C13: 2A/5 | D13: DA+3 | E13: Approved | F13: Completed | G13: Completed | H13: Completed | I13: Done | J13: Done | K13: Done
A14: =SUBTOTAL(103,$C$7:C14) -> 8 | C14: 2A/6 | D14: DA+6 | E14: Approved | F14: Completed | G14: Completed | H14: Completed | I14: Done | J14: Done | K14: Done
A15: =SUBTOTAL(103,$C$7:C15) -> 9 | C15: 3A/0 | D15: DD45+3 | E15: Approved | F15: Completed | G15: Completed | H15: Completed | I15: Done | J15: Done | K15: Done
A16: =SUBTOTAL(103,$C$7:C16) -> 10 | C16: 3A/1 | D16: DA+3 | E16: Approved | F16: Completed | G16: Completed | H16: Completed | I16: Done | J16: Done | K16: Done
A17: =SUBTOTAL(103,$C$7:C17) -> 11 | C17: 3A/2 | D17: DA+3 | E17: Approved | F17: Completed | G17: Completed | H17: Completed | I17: Done | J17: Done | K17: Done
A18: =SUBTOTAL(103,$C$7:C18) -> 12 | C18: 3A/3 | D18: DA+0 | E18: Approved | F18: Completed | G18: Completed | H18: Completed | I18: Done | J18: Done | K18: Done
A19: =SUBTOTAL(103,$C$7:C19) -> 13 | C19: 3A/4 | D19: DA+0 | E19: Approved | F19: Completed | G19: Completed | H19: Completed | I19: Done | J19: Done | K19: Done
A20: =SUBTOTAL(103,$C$7:C20) -> 14 | C20: 3A/5 | D20: DA+3 | E20: Approved | F20: Completed | G20: Completed | H20: Completed | I20: Done | J20: Done | K20: Done
A21: =SUBTOTAL(103,$C$7:C21) -> 15 | B21: AP-4 | C21: 3A/6 | D21: DA+0 | E21: Approved | F21: Completed | G21: Completed | H21: Completed | I21: Done | J21: Done | K21: Done
A22: =SUBTOTAL(103,$C$7:C22) -> 16 | C22: 3B/0 | D22: DB1+9 | E22: Approved | F22: Completed | G22: Completed | H22: Completed | I22: Done | J22: Done | K22: Done
A23: =SUBTOTAL(103,$C$7:C23) -> 17 | C23: 3B/1 | D23: DA+3 | E23: Approved | F23: Completed | G23: Completed | H23: Completed | I23: Done | J23: Done | K23: Done
A24: =SUBTOTAL(103,$C$7:C24) -> 18 | C24: 3B/2 | D24: DA+9 | E24: Approved | F24: Completed | G24: Completed | H24: Completed | I24: Done | J24: Done | K24: Done
A25: =SUBTOTAL(103,$C$7:C25) -> 19 | C25: 3B/3 | D25: DA+6 | E25: Approved | F25: Completed | G25: Completed | H25: Completed | I25: Done | J25: Done | K25: Done
A26: =SUBTOTAL(103,$C$7:C26) -> 20 | C26: 4/0 | D26: DB2+9 | E26: Approved | F26: Completed | G26: Completed | H26: Completed | I26: Done | J26: Done | K26: Done
A27: =SUBTOTAL(103,$C$7:C27) -> 21 | C27: 4/5 | D27: DA+6 | E27: Approved | F27: Completed | G27: Completed | H27: Completed | I27: Done | J27: Done | K27: Done
A28: =SUBTOTAL(103,$C$7:C28) -> 22 | B28: AP- 4A/0 | C28: 4A/0 | D28: DB1+3 | E28: Approved | F28: Completed | G28: Completed | H28: Completed | I28: Done | J28: Done | K28: Done
A29: =SUBTOTAL(103,$C$7:C29) -> 23 | C29: 4A/1 | D29: DA+6 | E29: Approved | F29: Completed | G29: Completed | H29: Completed | I29: Done | J29: Done | K29: Done
A30: =SUBTOTAL(103,$C$7:C30) -> 24 | C30: 4A/2 | D30: DA+6 | E30: Approved | F30: Completed | G30: Completed | H30: Completed | I30: Done | J30: Done | K30: Done
A31: =SUBTOTAL(103,$C$7:C31) -> 25 | C31: 4A/3 | D31: DA+9 | E31: Approved | F31: Completed | G31: Completed | H31: Completed | I31: Done | J31: Done | K31: Done
A32: =SUBTOTAL(103,$C$7:C32) -> 26 | C32: 4A/4 | D32: DA+6 | E32: Approved | F32: Completed | G32: Completed | H32: Completed | I32: Done | J32: Done | K32: Done
A33: =SUBTOTAL(103,$C$7:C33) -> 27 | C33: 4A/5 | D33: DA+9 | E33: Approved | F33: Completed | G33: Completed | H33: Completed | I33: Done | J33: Done | K33: Done
A34: =SUBTOTAL(103,$C$7:C34) -> 28 | C34: 4A/6 | D34: DA+9 | E34: Approved | F34: Completed | G34: Completed | H34: Completed | I34: Done | J34: Done | K34: Done
A35: =SUBTOTAL(103,$C$7:C35) -> 29 | B35: AP5 | C35: 5/0 | D35: DB1+6 | E35: Approved | F35: Completed | G35: Completed | H35: Completed | I35: Done | J35: Done | K35: Done
A36: =SUBTOTAL(103,$C$7:C36) -> 30 | C36: 5/1 | D36: DA+6 | E36: Approved | F36: Completed | G36: Completed | H36: Completed | I36: Done | J36: Done | K36: Done
A37: =SUBTOTAL(103,$C$7:C37) -> 31 | C37: 5/2 | D37: DA+9 | E37: Approved | F37: Completed | G37: Completed | H37: Completed | I37: Done | J37: Done | K37: Done
A38: =SUBTOTAL(103,$C$7:C38) -> 32 | C38: 5/3 | D38: DA+9 | E38: Approved | F38: Completed | G38: Completed | H38: Completed | I38: Done | J38: Done | K38: Done
A39: =SUBTOTAL(103,$C$7:C39) -> 33 | C39: 5/4 | D39: DA-1.5 | E39: Approved | F39: Completed | G39: Completed | H39: Completed | I39: Done | J39: Done | K39: Done
A40: =SUBTOTAL(103,$C$7:C40) -> 34 | C40: 5/5 | D40: DA+6 | E40: Approved | F40: Completed | G40: Completed | H40: Completed | I40: Done | J40: Done | K40: Done
A41: =SUBTOTAL(103,$C$7:C41) -> 35 | C41: 5/6 | D41: DA+3 | E41: Approved | F41: Completed | G41: Completed | H41: Completed | I41: Done | J41: Done | K41: Done
A42: =SUBTOTAL(103,$C$7:C42) -> 36 | C42: 5/7 | D42: DA+9 | E42: Approved | F42: Completed | G42: Completed | H42: Completed | I42: Done | J42: Done | K42: Done
A43: =SUBTOTAL(103,$C$7:C43) -> 37 | C43: 5/8 | D43: DA+6 | E43: Approved | F43: Completed | G43: Completed | H43: Completed | I43: Done | J43: Done | K43: Done
A44: =SUBTOTAL(103,$C$7:C44) -> 38 | C44: 5/9 | D44: DA+6 | E44: Approved | F44: Completed | G44: Completed | H44: Completed | I44: Done | J44: Done | K44: Done
A45: =SUBTOTAL(103,$C$7:C45) -> 39 | C45: 5/10 | D45: DA+9 | E45: Approved | F45: Completed | G45: Completed | H45: Completed | I45: Done | J45: Done | K45: Done
A46: =SUBTOTAL(103,$C$7:C46) -> 40 | B46: AP-5A | C46: 5A/0 | D46: DB1+12 | E46: Approved | F46: Completed | G46: Completed | H46: Completed | I46: Done | J46: Done | K46: Done
A47: =SUBTOTAL(103,$C$7:C47) -> 41 | B47: AP-6 | C47: 6/0 | D47: DB1+9 | E47: Approved | F47: Completed | G47: Completed | H47: Completed | I47: Done | J47: Done | K47: Done
A48: =SUBTOTAL(103,$C$7:C48) -> 42 | C48: 6/1 | D48: DA+9 | E48: Approved | F48: Completed | G48: Completed | H48: Completed | I48: Done | J48: Done | K48: Done
A49: =SUBTOTAL(103,$C$7:C49) -> 43 | C49: 6/2 | D49: DA+6 | E49: Approved | F49: Completed | G49: Completed | H49: Completed | I49: Done | J49: Done | K49: Done
A50: =SUBTOTAL(103,$C$7:C50) -> 44 | C50: 6/3 | D50: DA+3 | E50: Approved | F50: Completed | G50: Completed | H50: Completed | I50: Done | J50: Done | K50: Done
A51: =SUBTOTAL(103,$C$7:C51) -> 45 | C51: 6/4 | D51: DA+9 | E51: Approved | F51: Completed | G51: Completed | H51: Completed | I51: Done | J51: Done | K51: Done
