Workbook
Name \0: #REF!
Name \2: #REF!
Name \3: #REF!
Name \4: #REF!
Name \A: #REF!
Name \A_1: "#REF!"
Name \a1: #REF!
Name \B: #REF!
Name \C: #REF!
Name \c1: #REF!
Name \d: #N/A
Name \E: #REF!
Name \f: #REF!
Name \g: #REF!
Name \H: #REF!
Name \I: #REF!
Name \j: #REF!
Name \k: #REF!
Name \KWS123: #N/A
Name \l: #REF!
Name \M: #REF!
Name \N: #REF!
Name \P: #REF!
Name \q: #N/A
Name \R: #REF!
Name \S: #REF!
Name \t: #N/A
Name \U: #REF!
Name \V: #REF!
Name \z: #REF!
Name _: #REF!
Name _________________________________________________________dol12: #REF!
Name _________________________________________________________in18900: #REF!
Name _________________________________________________________iv19000: #REF!
Name ________________________________________________________dol12: #REF!
Name ________________________________________________________dol6: #REF!
Name ________________________________________________________in18900: #REF!
Name ________________________________________________________iv19000: #REF!
Name _______________________________________________________dol12: #REF!
Name _______________________________________________________dol6: #REF!
Name _______________________________________________________in18900: #REF!
Name _______________________________________________________iv19000: #REF!
Name ______________________________________________________dol12: #REF!
Name ______________________________________________________dol6: #REF!
Name _____________________________________________________dol12: #REF!
Name _____________________________________________________dol6: #REF!
Name _____________________________________________________in18900: #REF!
Name _____________________________________________________iv19000: #REF!
Name ____________________________________________________dol12: #REF!
Name ____________________________________________________dol6: #REF!
Name ____________________________________________________in18900: #REF!
Name ____________________________________________________iv19000: #REF!
Name ___________________________________________________dol12: #REF!
Name ___________________________________________________dol6: #REF!
Name ___________________________________________________in18900: #REF!
Name ___________________________________________________iv19000: #REF!
Name __________________________________________________dol12: #REF!
Name __________________________________________________dol6: #REF!
Name __________________________________________________in18900: #REF!
Name __________________________________________________iv19000: #REF!

Sheet TB401 DPR.....
B1: Project Code | D1: TB-401 | F1: Date | H1: =TODAY() -> 46247 | I1: LOA Start Date | L1: 45041 | M1: Business Head (T&D)- India & Sri Lanka | P1: Rajinder Gupta
B2: Project Name | D2: 765KV D/C Fategarh-III Beawar Transmission Line | I2: LOA End Date | L2: 45498 | M2: PCH | P2: Sivaraman Nataraajan
B3: Client Name | D3: Strelite Power | I3: Time Extn | L3: 45498 | M3: Regional Manager | P3: Sandeep Singh Kumar
B4: LE Value | D4: Rs 312 Cr -Supply -Rs 227.5 Cr.; Service.-Rs 84.4 Cr | I4: Planning | L4: Shah Ali Khan | M4: Project Manager | P4: Virender Gupta
A5: Activity | B5: Unit | C5: LOA Qty. | D5: LE Qty | E5: Progress till Last Month | F5: Balance | G5: L2 for Dec'23 | H5: Plan for Dec.'23 | I5: Today's Progress | J5: Month Progress | K5: WIP | L5: Gangs at Present | M5: L2 Till Month-Dec.23 | N5: Progress Till Date | O5: Balance Work | P5: Remarks
A6: Route Alignment | B6: km | C6: 215 | D6: 202 | E6: 167 | F6: =D6-E6 -> 35 | G6: 0 | H6: 35 | M6: 215 | N6: =E6+J6 -> 167 | O6: =D6-N6 -> 35 | P6: 35 Km is hold due to ROW issues
A7: Detailed Survey | B7: km | C7: 215 | D7: 202 | E7: 202 | F7: =D7-E7 -> 0 | G7: 0 | M7: 215 | N7: =E7+J7 -> 202 | O7: =D7-N7 -> 0 | P7: SPTL Approved -202/202-Kms
A8: Check Survey | B8: km | C8: 215 | D8: 202 | E8: 92.704 | F8: =D8-E8 -> 109.296 | G8: 20 | H8: 50 | J8: 17.852 | M8: 160 | N8: =E8+J8 -> 110.556 | O8: =D8-N8 -> 91.444 | P8: 1. Total 7.854 Km is under review of SPTL. 2. Total check survey completed (Field work) 167 Km. 3. Total 60 Km check survey is hold due to row issues & Other issues.
A9: Foundation | B9: Nos | C9: 534 | D9: 521 | E9: 109 | F9: =D9-E9 -> 412 | G9: 75 | H9: 30 | J9: 1 | K9: 4 | L9: 3 | M9: 399 | N9: =E9+J9 -> 110 | O9: =D9-N9 -> 411 | AA9: =65/D9 -> 0.12476008 | AC9: =(D11-C9)/C9 -> -0.024344569 | AD9: =C9*AC9 -> -13 | AE9: =366-318 -> 48 | AF9: =318-12 -> 306
A10: Earthing | B10: Nos | C10: 534 | D10: 521 | E10: 106 | F10: =D10-E10 -> 415 | G10: 75 | H10: 30 | J10: 2 | M10: 399 | N10: =E10+J10 -> 108 | O10: =D10-N10 -> 413 | AA10: =65/D10 -> 0.12476008
A11: Tower Erection | B11: Nos | C11: 534 | D11: 521 | E11: 45 | F11: =D11-E11 -> 476 | G11: 75 | H11: 40 | I11: 2 | J11: 6 | K11: 5 | L11: 5 | M11: 260 | N11: =E11+J11 -> 51 | O11: =D11-N11 -> 470 | P11: 56/2 58/15 Complete | AA11: =65/D11 -> 0.12476008
A12: Tack welding | B12: Nos | C12: 534 | D12: 521 | E12: 15 | F12: =D12-E12 -> 506 | G12: 75 | H12: 40 | I12: 1 | J12: 3 | K12: 1 | L12: 1 | M12: 260 | N12: =E12+J12 -> 18 | O12: =D12-N12 -> 503 | P12: 56/7 complete | AA12: =65/D12 -> 0.12476008
A13: Stringing | B13: Km | C13: 215 | D13: 202 | E13: 0 | F13: =D13-E13 -> 202 | G13: 20 | M13: 25 | N13: =E13+J13 -> 0 | O13: =D13-N13 -> 202 | AA13: =20.635/D13 -> 0.10215347 | AD13: =103/151 -> 0.68211921
AA14: =20.635/D14 -> #DIV/0!

Sheet Eng.
A2: Tower | B2: Tower Design | D2: Test Tower | F2: Balance Structural Drawing. | H2: Tower | I2: Stub & Template Drawings | J2: Foundation
A3: Types | D3: Structural Drawing(BTB+0) | F3: (3M/6M/9M) | H3: Testing | J3: Design/Drg
B4: Target | C4: Status | D4: Target | E4: Status | F4: Target | G4: Status | J4: Target | K4: Status
A5: DA Tower | B5: 45058 | C5: Approved | D5: 45081 | E5: Approved | F5: 45101 | G5: Approved for proto | H5: Completed | I5: Approved | J5: 15-July | K5: Approved
A6: DB Tower | B6: 45076 | C6: Approved | D6: 45137 | E6: Approved | F6: 45126 | G6: Approvedin Cat-B | H6: Completed | I6: Approved for Proto | J6: DB all Fdn. By 25 -July | K6: Approved
A8: DD Tower | B8: 45098 | C8: Approved | D8: 30-Sept. | E8: Approved in Cat -B | F8: 45158 | G8: Approved in Cat -B | H8: Completed | I8: Approved in Cat -B | J8: 45138 | K8: Approved
A9: DC Tower | B9: 45123 | C9: Approved | D9: 45207 | E9: Approved in Cat -B | F9: 45188 | G9: Approved in Cat -B | H9: Completed | I9: Approved in Cat -B | J9: 45163 | K9: Approved

Sheet Fdn (Pkg -G Section -I)
A1: KEC INTERNATIONAL LIMITED | L1: Date: | M1: =TODAY() -> 46247
A2: LILO of 765 Kv DV Fatehgarh 3 Beawar TL
A3: FOUNDATION
A4: Sl. No. | B4: Month Sl. No. | C4: JMC No. | D4: Location No. | E4: Tower Type | F4: Classification | G4: Excavation Start | H4: Dt. of Start | I4: Dt. of Concrete | J4: Name of Sub-Contractor | K4: KEC representative | L4: KEC Section In-Charge | M4: Remarks
A6: 1 | B6: 1 | D6: 32/7 | E6: DA+0 | F6: SANDY | G6: 23.10.23 | H6: 25.10.23 | I6: 28.10.23 | J6: Shakti Construction | K6: Kumar Nayak | L6: Jish C Verghese | M6: Complete
A7: 2 | B7: 2 | D7: 32/5 | E7: DA+6 | F7: SANDY | G7: 29.10.23 | H7: 31.10.23 | I7: 04.11.2023 | J7: Shakti Construction | K7: Kumar Nayak | L7: Jish C Verghese | M7: Complete
A8: 3 | B8: 3 | D8: 32/1 | E8: DA+9 | F8: SANDY | G8: 03.11.23 | H8: 06.11.23 | I8: 10.11.23 | J8: Shakti Construction | K8: Kumar Nayak | L8: Jish C Verghese | M8: Complete
A9: 4 | B9: 4 | D9: 30/2 | E9: DA+0 | F9: SANDY | G9: 13.11.23 | H9: 15.11.23 | I9: 16.11.23 | J9: Shakti Construction | K9: Kumar Nayak | L9: Jish C Verghese | M9: Complete
A10: 5 | B10: 5 | D10: 32/0 | E10: DB2+6 | F10: SANDY | G10: 18.11.23 | H10: 20.11.23 | I10: 28.11.23 | J10: Shakti Construction | K10: Dipesh | L10: Jish C Verghese | M10: Complete
B11: Dec-23
A12: 1 | B12: 6 | D12: 31/3 | E12: DA+0 | F12: SANDY | G12: 28.11.23 | H12: 30.11.23 | I12: 04.12.23 | J12: Shakti Construction | K12: Dipesh | L12: Jish C Verghese | M12: Complete

Sheet Sheet2
C2: S.No | D2: Line | E2: Activity | F2: UOM | G2: LOA Qty | H2: L2 till Sep'25 | I2: Completed till Date | J2: Balance | K2: WIP | L2: Gangs | M2: Remarks
C3: 1 | D3: Samba- Jalandhar | E3: Survey | F3: Km | G3: 144 | H3: 70 | I3: 129.36 | J3: =G3-I3 -> 14.64 | L3: 2
E4: Foundation | F4: Nos | G4: 434 | H4: 17 | I4: 2 | J4: =G4-I4 -> 432 | K4: 4 | L4: 3
C5: 2 | D5: Kishepur- Samba | E5: Survey | F5: Km | G5: 33.103 | H5: 20 | I5: 8.56 | J5: =G5-I5 -> 24.543 | K5: 0.3 | L5: 1
E6: Foundation | F6: Nos | G6: 129 | J6: =G6-I6 -> 129
C7: 3 | D7: LILO-Kisthwar | E7: Survey | F7: Km | G7: 2.18 | H7: 2.18 | I7: 2.18 | J7: =G7-I7 -> 0
E8: Foundation | F8: Nos | G8: 14 | H8: 6 | J8: =G8-I8 -> 14
D9: Total | E9: Survey | F9: Km | G9: =G7+G5+G3 -> 179.283 | H9: =H7+H5+H3 -> 92.18 | I9: =I7+I5+I3 -> 140.1 | J9: =G9-I9 -> 39.183 | K9: =K7+K5+K3 -> 0.3 | L9: =L7+L5+L3 -> 3
E10: Foundation | F10: Nos | G10: =G8+G6+G4 -> 577 | H10: =H8+H6+H4 -> 23 | I10: =I8+I6+I4 -> 2 | J10: =G10-I10 -> 575 | K10: =K8+K6+K4 -> 4 | L10: =L8+L6+L4 -> 3
P13: S.No | Q13: Loc | R13: TOT | S13: S.No | T13: Loc | U13: TOT
P14: 1 | Q14: AP156 | R14: DC+0 | S14: =10+1 -> 11 | T14: AP91 | U14: DD+25
P15: =P14+1 -> 2 | Q15: 70/2 | R15: DA+0 | S15: =S14+1 -> 12 | T15: 153/2 | U15: DA+3
P16: =P15+1 -> 3 | Q16: 153/1 | R16: DA+0
P17: =P16+1 -> 4 | Q17: AP111 | R17: DC+0
P18: =P17+1 -> 5 | Q18: 136/3 | R18: DA+0
P19: =P18+1 -> 6 | Q19: 157/1 | R19: DA+0
P20: =P19+1 -> 7 | Q20: AP150 | R20: DC+0
P21: =P20+1 -> 8 | Q21: AP70 | R21: DC+3
P22: =P21+1 -> 9 | Q22: 136/4 | R22: DA+3
P23: =P22+1 -> 10 | Q23: AP68 | R23: DB+0

Sheet Sheet3
B2: Line | C2: Activity | D2: Section | E2: L2 Oct'25 | F2: Plan Oct'25 | G2: L2 Nov'25 | H2: Plan Nov'25 | I2: L2 Dec'25 | J2: Plan Dec'25 | K2: L2 (Oct'25-Dec'25) | L2: Plan (Oct'25-Dec'25)
B3: Samba-Jalandhar | C3: FDN | D3: Jammu | E3: 25 | F3: 10 | G3: 35 | H3: 10 | I3: 40 | J3: 20 | K3: =E3+G3+I3 -> 100 | L3: =F3+H3+J3+F5+H5+J5 -> 110
C4: Gangs | F4: 3 | H4: 3 | J4: 6
C5: FDN | D5: Punjab | F5: 15 | H5: 25 | J5: 30
C6: Gangs | F6: 5 | H6: 6 | J6: 6
B7: Kishenpur-Samba | C7: FDN | D7: Jammu | E7: 2 | G7: 7 | H7: 5 | I7: 10 | J7: 8 | K7: =E7+G7+I7 -> 19 | L7: =F7+H7+J7 -> 13
C8: Gangs | H8: 3 | J8: 4
B9: LILO-Kishtwar | C9: FDN | D9: Kishtwar | E9: 2 | G9: 2 | H9: 1 | J9: 1 | K9: =E9+G9+I9 -> 4 | L9: =F9+H9+J9 -> 2
C10: Gangs | H10: 1 | J10: 1
B11: Total | C11: FDN | E11: =E9+E7+E3 -> 29 | F11: =F3+F5+F7+F9 -> 25 | G11: =G9+G7+G3 -> 44 | H11: =H3+H5+H7+H9 -> 41 | I11: =I9+I7+I3 -> 50 | J11: =J3+J5+J7+J9 -> 59 | K11: =K9+K7+K3 -> 123 | L11: =L9+L7+L3 -> 125
C12: Gangs | F12: =F6+F4+F8+F10 -> 8 | H12: =H6+H4+H8+H10 -> 13 | J12: =J6+J4+J8+J10 -> 17

Sheet Sheet4
D6: Line | E6: Portion | F6: Section | G6: Length | H6: ROW Lead | I6: ROW Team | J6: Remarks
G7: Km | I7: Currently Working
D8: Samba-Jalandhar | E8: Jammu | F8: Gantry-AP52 | G8: 47 | H8: Karmanya Pathania | I8: ROW Team-1 Akhil S ( Engineer) / Radhe Shyam (Supervisor) | J8: At site since the works are in initial phase , hence we have engaged site engineer/supervisor for ROW document collection for time being , further we can engage separate ROW team as per requirement
E9: Punjab | F9: AP52 - AP115 | G9: 47 | I9: ROW Team -2 K Govind ( Section In charge) / Kuldeep Singh ( DET)
F10: AP115 - AP187 | G10: 48 | I10: ROW Team -3 Manish Nirala (Section In charge) / Govardhan (DET)
D11: Kishenpur-Samba | F11: Gantry- AP109 | G11: 33 | I11: ROW Team -4 Mukesh ( Admin) /Yadhuveer (Supervisor) | J11: Due to heavy rains/landslides local administration blocked the roads
D12: LILO | E12: Kishtewar | F12: AP1-Tapping Point | G12: 2.1 | J12: Due to heavy rains/landslides local administration blocked the roads

Sheet Sheet5

Sheet ROW
A1: KEC INTERNATIONAL LIMITED | F1: Date | G1: 46083
A2: 400kv D/C Samba-Jalandhar T/L-Punjab Portion
D4: Submitted | E4: =COUNTIF(E7:E247,"Submitted") -> 109 | F4: =COUNTIF(F7:F247,"Submitted") -> 90
D5: File Ready | E5: =COUNTIF(E7:E247,"File Ready") -> 10 | F5: =COUNTIF(F7:F247,"File Ready") -> 8
A6: S.No | B6: Tower | C6: TOT | D6: Foundation Completion Status | E6: Crop | F6: Land | G6: Remarks
A7: 1 | B7: AP53 | C7: DC+0
A8: =A7+1 -> 2 | B8: AP54 | C8: DC+6
A9: =A8+1 -> 3 | B9: AP55 | C9: DD+3
A10: =A9+1 -> 4 | B10: 55/1 | C10: DA+6
A11: =A10+1 -> 5 | B11: AP56 | C11: DC+3
A12: =A11+1 -> 6 | B12: 56/1 | C12: DA+6
A13: =A12+1 -> 7 | B13: 56/2 | C13: DA+3
A14: =A13+1 -> 8 | B14: 56/3 | C14: DA+6 | D14: WIP
A15: =A14+1 -> 9 | B15: 56/4 | C15: DA+6
A16: =A15+1 -> 10 | B16: AP57 | C16: DD+3
A17: =A16+1 -> 11 | B17: 57/1 | C17: DA+0
A18: =A17+1 -> 12 | B18: 57/2 | C18: DA+0
A19: =A18+1 -> 13 | B19: AP58 | C19: DC+0
A20: =A19+1 -> 14 | B20: AP59 | C20: DD+6
A21: =A20+1 -> 15 | B21: 59/1 | C21: DA+3
A22: =A21+1 -> 16 | B22: AP60 | C22: DB+6
A23: =A22+1 -> 17 | B23: 60/1 | C23: DA+0
A24: =A23+1 -> 18 | B24: AP61 | C24: DC+0
A25: =A24+1 -> 19 | B25: 61/1 | C25: DA+0
A26: =A25+1 -> 20 | B26: AP62 | C26: DB+0
... A40: =A39+1 -> 34 | B40: 67/1 | C40: DA+0
A41: =A40+1 -> 35 | B41: 67/2 | C41: DA+0 | D41: WIP
A42: =A41+1 -> 36 | B42: 67/3 | C42: DA+0 | D42: C
A43: =A42+1 -> 37 | B43: AP68 | C43: DB+0 | D43: C | E43: Submitted | F43: Submitted
A44: =A43+1 -> 38 | B44: AP69 | C44: DB+0 | D44: C
A45: =A44+1 -> 39 | B45: 69/1 | C45: DA+0 | D45: C | E45: Submitted | F45: Submitted
A46: =A45+1 -> 40 | B46: 69/2 | C46: DA+0 | D46: C | E46: Submitted | F46: Submitted
A47: =A46+1 -> 41 | B47: 69/3 | C47: DA+0 | D47: C | E47: Submitted | F47: Submitted
A48: =A47+1 -> 42 | B48: AP70 | C48: DC+3 | D48: C | E48: File Ready | F48: File Ready
A49: =A48+1 -> 43 | B49: 70/1 | C49: DA+9 | D49: C | E49: File Ready
A50: =A49+1 -> 44 | B50: 70/2 | C50: DA+0 | D50: C | E50: File Ready
A51: =A50+1 -> 45 | B51: AP70/3 | C51: DD+18
A52: =A51+1 -> 46 | B52: AP71 | C52: DC+9 | D52: WIP
A53: =A52+1 -> 47 | B53: 71/1 | C53: DA+3 | E53: Submitted | F53: Submitted
A54: =A53+1 -> 48 | B54: 71/2 | C54: DA+9 | D54: C
A55: =A54+1 -> 49 | B55: 71/3 | C55: DA+6 | D55: C | E55: Submitted
A56: =A55+1 -> 50 | B56: AP72 | C56: DB+3 | D56: C | E56: Submitted | F56: Submitted
A57: =A56+1 -> 51 | B57: 72/1 | C57: DA+3 | D57: C | E57: Submitted | F57: Submitted
A58: =A57+1 -> 52 | B58: 72/2 | C58: DA+6 | D58: C | E58: Submitted
A59: =A58+1 -> 53 | B59: AP74 | C59: DB+0 | D59: C | E59: Submitted | F59: Submitted
A60: =A59+1 -> 54 | B60: AP75 | C60: DB+9 | D60: C | E60: Submitted | F60: Submitted
A61: =A60+1 -> 55 | B61: AP76 | C61: DC+9
A62: =A61+1 -> 56 | B62: 76/1 | C62: DA+0 | D62: C | E62: Submitted | F62: Submitted
A63: =A62+1 -> 57 | B63: 76/2 | C63: DA+3 | D63: C | E63: Submitted | F63: Submitted
A64: =A63+1 -> 58 | B64: 76/3 | C64: DA+3 | D64: C | E64: Submitted | F64: Submitted
A65: =A64+1 -> 59 | B65: AP77 | C65: DB+3 | D65: C | E65: Submitted | F65: Submitted
A66: =A65+1 -> 60 | B66: 77/1 | C66: DA+3 | D66: C | E66: Submitted | F66: Submitted
A67: =A66+1 -> 61 | B67: 77/2 | C67: DB+0 | D67: C | E67: Submitted | F67: Submitted
A68: =A67+1 -> 62 | B68: 77/3 | C68: DA+0
A69: =A68+1 -> 63 | B69: AP78 | C69: DB+9
A70: =A69+1 -> 64 | B70: AP79 | C70: DD+9 | D70: C | E70: Submitted | F70: Submitted
A71: =A70+1 -> 65 | B71: AP80 | C71: DD+0 | D71: C | E71: Submitted | F71: Submitted
A72: =A71+1 -> 66 | B72: 80/1 | C72: DB+3 | D72: C | E72: File Ready | G72: Court Case , Indigrid rejected to submit
A73: =A72+1 -> 67 | B73: AP81 | C73: DD+9
A74: =A73+1 -> 68 | B74: AP82 | C74: DD+3
A75: =A74+1 -> 69 | B75: 82/1 | C75: DA+0 | D75: C | E75: Submitted | F75: Submitted
A76: =A75+1 -> 70 | B76: 82/2 | C76: DA+3 | D76: C | E76: Submitted | F76: Submitted
A77: =A76+1 -> 71 | B77: AP83 | C77: DD+25
A78: =A77+1 -> 72 | B78: AP84 | C78: DD+18
A79: =A78+1 -> 73 | B79: AP85 | C79: DB+0 | D79: C | E79: Submitted | F79: Submitted
A80: =A79+1 -> 74 | B80: 85/1 | C80: DA+9 | D80: C | E80: Submitted | F80: Submitted
A81: =A80+1 -> 75 | B81: AP86 | C81: DC+0
A82: =A81+1 -> 76 | B82: 86/1 | C82: DA+3 | D82: C | E82: File Ready | F82: File Ready
A83: =A82+1 -> 77 | B83: AP87 | C83: DB+9 | D83: C
A84: =A83+1 -> 78 | B84: 87/1 | C84: DA+3
A85: =A84+1 -> 79 | B85: 87/2 | C85: DA+3 | D85: C | E85: Submitted | F85: Submitted
A86: =A85+1 -> 80 | B86: AP88 | C86: DD+18
A87: =A86+1 -> 81 | B87: AP89 | C87: DD+18
A88: =A87+1 -> 82 | B88: 89/1 | C88: DA+3 | D88: C | E88: Submitted | F88: Submitted
A89: =A88+1 -> 83 | B89: AP90 | C89: DD+0 | D89: C | E89: Submitted | F89: Submitted
A90: =A89+1 -> 84 | B90: 90/1 | C90: DA+3 | D90: C | E90: Submitted | F90: Submitted
A91: =A90+1 -> 85 | B91: 90/2 | C91: DA+0 | D91: C | E91: Submitted | F91: Submitted
A92: =A91+1 -> 86 | B92: AP91 | C92: DD+25 | D92: C | E92: File Ready
A93: =A92+1 -> 87 | B93: AP92 | C93: DD+25 | D93: C | E93: Submitted | F93: Submitted
A94: =A93+1 -> 88 | B94: 92/1 | C94: DA+3 | D94: C | E94: Submitted | F94: Submitted
A95: =A94+1 -> 89 | B95: 92/2 | C95: DA+6 | D95: C | E95: Submitted | F95: Submitted
A96: =A95+1 -> 90 | B96: 92/3 | C96: DA+0 | D96: C | E96: Submitted | F96: Submitted
A97: =A96+1 -> 91 | B97: AP93 | C97: DC+0 | D97: C | E97: Submitted | F97: Submitted
A98: =A97+1 -> 92 | B98: 93/1 | C98: DA+0 | D98: C | E98: Submitted | F98: Submitted
A99: =A98+1 -> 93 | B99: 93/2 | C99: DA+0 | D99: C | E99: Submitted | F99: Submitted
A100: =A99+1 -> 94 | B100: AP94 | C100: DB+0 | D100: C | E100: Submitted | F100: Submitted
A101: =A100+1 -> 95 | B101: AP95 | C101: DC+3 | D101: C | E101: Submitted | F101: Submitted
A102: =A101+1 -> 96 | B102: 95/1 | C102: DA+0 | D102: C | E102: Submitted | F102: Submitted
A103: =A102+1 -> 97 | B103: 95/2 | C103: DA+0 | D103: C | E103: Submitted | F103: Submitted
A104: =A103+1 -> 98 | B104: 95/3 | C104: DA+0 | D104: C | E104: Submitted | F104: Submitted
... A107: =A106+1 -> 101 | B107: AP97 | C107: DD+3 | D107: C | E107: Submitted | F107: Submitted
A108: =A107+1 -> 102 | B108: 97/1 | C108: DA+0 | D108: C | E108: Submitted | G108: Panchayat Land
A109: =A108+1 -> 103 | B109: 97/2 | C109: DA+0 | D109: C | E109: Submitted | F109: Submitted
A110: =A109+1 -> 104 | B110: 97/3 | C110: DA+3 | D110: C | E110: Submitted | F110: Submitted
A111: =A110+1 -> 105 | B111: AP98 | C111: DB+3 | D111: C | E111: Submitted | F111: Submitted
A112: =A111+1 -> 106 | B112: 98/1 | C112: DA+3 | D112: C | E112: Submitted | F112: Submitted
A113: =A112+1 -> 107 | B113: AP99 | C113: DB+0 | D113: C | E113: Submitted | F113: Submitted
A114: =A113+1 -> 108 | B114: 99/1 | C114: DA+9 | D114: C | E114: Submitted | F114: Submitted
A115: =A114+1 -> 109 | B115: AP100 | C115: DC+3 | D115: C | E115: File Ready | F115: File Ready
A116: =A115+1 -> 110 | B116: AP101 | C116: DC+0
...

Sheet Sheet13 (2)
C2: Paticulars | D2: Plain Terrain | E2: Hilly Terrain
C3: Line Length (KM) | D3: 137 KM | E3: 36 KM
D4: =137/173 -> 0.79190751 | E4: =36/173 -> 0.20809249

Sheet TB-605
B1: Project Code | C1: TB-605 | D1: Date | E1: 46246 | H1: President-T & D | I1: Ganesh Srinivasan
B2: Project Name | C2: Transmission Line Portion for “Transmission scheme for evacuation of power from Ratle HEP (850 MW) & Kiru HEP (624 MW): Part-A” | F2: LOA Start Date | G2: 45793 | H2: SBU Head- T&D | I2: Rajinder Gupta
B3: Client Name | C3: Ratle Kiru Power Transmission Ltd | F3: LOA End Date | G3: 46461 | H3: PCH | I3: NK Gupta
B4: Revised End Date | F4: Planning | G4: Aditya.M | H4: Project Manager | I4: Mithu Dutta
A5: Progress Summary - Ratle Kiru Power Transmission Ltd
A6: Activity | B6: Final Estimated Qty | C6: Cumulative L2 till Last Month | D6: Cumulative Progress till Last Month | E6: L2 for present Month (Revised) | F6: Plan for the Month | G6: Today's Progress | H6: Progress till Date for the Month | I6: L2 till Current Month | J6: Completed till Date | K6: Balance Work | L6: Under Progress | M6: Gangs at Present | N6: Remarks | P6: Gap with respect to revised L2 - Cummilative till Aug-26 | Q6: Gap with respect to monthly plan for the month Aug-26
A7: Check Survey | B7: =B17+B26+B35+B44 -> 175.719 | C7: =C17+C26+C35+C44 -> 179.103 | D7: =D17+D26+D35+D44 -> 175.719 | E7: =E17+E26+E35+E44 -> 0 | F7: =F17+F26+F35+F44 -> 0 | G7: =G17+G26+G35+G44 -> 0 | H7: =H17+H26+H35+H44 -> 0 | I7: =+C7+E7 -> 179.103 | J7: =+H7+D7 -> 175.719 | L7: =L17+L26+L35+L44 -> 0
A8: Foundation | B8: =B18+B27+B36+B45 -> 523 | C8: =C18+C27+C36+C45 -> 510 | D8: =D18+D27+D36+D45 -> 431 | E8: =E18+E27+E36+E45 -> 24 | F8: =F18+F27+F36+F45 -> 26 | G8: =G18+G27+G36+G45 -> 0 | H8: =H18+H27+H36+H45 -> 3 | I8: =+C8+E8 -> 534 | J8: =+H8+D8 -> 434 | K8: =+B8-J8 -> 89 | L8: =L18+L27+L36+L45 -> 28 | M8: =M18+M27+M36+M45 -> 22 | P8: =P18+P27+P36+P45 -> 100 | Q8: =Q18+Q27+Q36+Q45 -> 23
A9: Earthing | B9: =B19+B28+B37+B46 -> 523 | C9: =C19+C28+C37+C46 -> 506 | D9: =D19+D28+D37+D46 -> 379 | E9: =E19+E28+E37+E46 -> 24 | F9: =F19+F28+F37+F46 -> 26 | G9: =G19+G28+G37+G46 -> 0 | H9: =H19+H28+H37+H46 -> 0 | I9: =+C9+E9 -> 530 | J9: =+H9+D9 -> 379 | K9: =+B9-J9 -> 144 | L9: =L19+L28+L37+L46 -> 0 | M9: =M19+M28+M37+M46 -> 0 | P9: =P19+P28+P37+P46 -> 151 | Q9: =Q19+Q28+Q37+Q46 -> 26
A10: Tower Erection | B10: =B20+B29+B38+B47 -> 523 | C10: =C20+C29+C38+C47 -> 410 | D10: =D20+D29+D38+D47 -> 273 | E10: =E20+E29+E38+E47 -> 56 | F10: =F20+F29+F38+F47 -> 32 | G10: =G20+G29+G38+G47 -> 1 | H10: =H20+H29+H38+H47 -> 9 | I10: =+C10+E10 -> 466 | J10: =+H10+D10 -> 282 | K10: =+B10-J10 -> 241 | L10: =L20+L29+L38+L47 -> 13 | M10: =M20+M29+M38+M47 -> 13 | P10: =P20+P29+P38+P47 -> 184 | Q10: =Q20+Q29+Q38+Q47 -> 23
A11: Tack welding | B11: =B21+B30+B39+B48 -> 523 | C11: =C21+C30+C39+C48 -> 410 | D11: =D21+D30+D39+D48 -> 0 | E11: =E21+E30+E39+E48 -> 56 | F11: =F21+F30+F39+F48 -> 32 | G11: =G21+G30+G39+G48 -> 0 | H11: =H21+H30+H39+H48 -> 0 | I11: =+C11+E11 -> 466 | J11: =+H11+D11 -> 0 | K11: =+B11-J11 -> 523 | L11: =L21+L30+L39+L48 -> 0 | M11: =M21+M30+M39+M48 -> 0 | P11: =P21+P30+P39+P48 -> 466 | Q11: =Q21+Q30+Q39+Q48 -> 32
A12: Stringing-P/O-R/S | B12: =B22+B31+B40+B49 -> 175.719 | C12: =C22+C31+C40+C49 -> 48 | D12: =D22+D31+D40+D49 -> 5.655 | E12: =E22+E31+E40+E49 -> 22 | F12: =F22+F31+F40+F49 -> 11 | G12: =G22+G31+G40+G49 -> 0 | H12: =H22+H31+H40+H49 -> 0 | I12: =+C12+E12 -> 70 | J12: =+H12+D12 -> 5.655 | K12: =+B12-J12 -> 170.064 | L12: =L22 -> 4.79 | M12: 6 | N12: 4 Stringing + 1 Hotline+1 Drone Team | P12: =P22+P31+P40+P49 -> 64.345 | Q12: =Q22+Q31+Q40+Q49 -> 11
A13: Stringing-F/S | B13: =B23+B32+B41+B50 -> 175.719 | C13: =C23+C32+C41+C50 -> 48 | D13: =D23+D32+D41+D50 -> 4.715 | E13: =E23+E32+E41+E50 -> 22 | F13: =F23+F32+F41+F50 -> 11 | G13: =G23+G32+G41+G50 -> 0 | H13: =H23+H32+H41+H50 -> 0.952 | I13: =+C13+E13 -> 70 | J13: =+H13+D13 -> 5.667 | K13: =+B13-J13 -> 170.052 | L13: =L23 -> 0 | P13: =P23+P32+P41+P50 -> 60.333 | Q13: =Q23+Q32+Q41+Q50 -> 10.048
A14: Line Wise Progress
A15: 400 kV Samba- Jalandhar D/C Line(Quad) - Wind Zone - 5-Jammu Portion
A16: Activity | B16: Final Estimated Qty | C16: Cumulative L2 till Last Month | D16: Cumulative Progress till Last Month | E16: L2 for present Month (Revised) | F16: Plan for the Month | G16: Today's Progress | H16: Progress till Date for the Month | I16: L2 till Current Month | J16: Completed till Date | K16: Balance Work | L16: Under Progress | M16: Gangs at Present | N16: Remarks | P16: Gap with respect to revised L2 - Cummilative till Jun-26 | Q16: Gap with respect to monthly plan for the month June-26
A17: Check Survey | B17: 46.92 | C17: 49 | D17: 46.92 | I17: =+C17+E17 -> 49 | J17: =+H17+D17 -> 46.92 | K17: =+B17-J17 -> 0
A18: Foundation | B18: 126 | C18: 141 | D18: 119 | F18: 3 | I18: =+C18+E18 -> 141 | J18: =+H18+D18 -> 119 | K18: =+B18-J18 -> 7 | L18: 2 | M18: 2 | P18: =I18-J18 -> 22 | Q18: =F18-H18 -> 3
A19: Earthing | B19: 126 | C19: 141 | D19: 99 | F19: 3 | I19: =+C19+E19 -> 141 | J19: =+H19+D19 -> 99 | K19: =+B19-J19 -> 27 | P19: =I19-J19 -> 42 | Q19: =F19-H19 -> 3
A20: Tower Erection | B20: 126 | C20: 118 | D20: 103 | E20: 14 | F20: 4 | H20: 1 | I20: =+C20+E20 -> 132 | J20: =+H20+D20 -> 104 | K20: =+B20-J20 -> 22 | L20: 2 | M20: 2 | N20: Final Checking-41 Towers done | P20: =I20-J20 -> 28 | Q20: =F20-H20 -> 3
A21: Tack welding | B21: 126 | C21: 118 | D21: 0 | E21: 14 | F21: 4 | I21: =+C21+E21 -> 132 | J21: =+H21+D21 -> 0 | K21: =+B21-J21 -> 126 | L21: 0 | M21: 0 | P21: =I21-J21 -> 132 | Q21: =F21-H21 -> 4
A22: Stringing-P/O-R/S | B22: 46.92 | C22: 23 | D22: 5.655 | E22: 5 | F22: 10 | I22: =+C22+E22 -> 28 | J22: =+H22+D22 -> 5.655 | K22: =+B22-J22 -> 41.265 | L22: 4.79 | M22: 5 | N22: 4 Stringing + 1 Hotline | P22: =I22-J22 -> 22.345 | Q22: =F22-H22 -> 10
A23: Stringing- F/S | B23: 46.92 | C23: 23 | D23: 4.715 | E23: 5 | F23: 10 | H23: =0.466+0.486 -> 0.952 | I23: =+C23+E23 -> 28 | J23: =+H23+D23 -> 5.667 | K23: =+B23-J23 -> 41.253 | P23: =I23-J23 -> 22.333 | Q23: =F23-H23 -> 9.048 | S23: =4.72-3.64 -> 1.08
A24: 400 kV Samba- Jalandhar D/C Line(Quad) - Wind Zone - 5-Punjab Portion
A25: Activity | B25: Final Estimated Qty | C25: Cumulative L2 till Last Month | D25: Cumulative Progress till Last Month | E25: L2 for present Month (Revised) | F25: Plan for the Month | G25: Today's Progress | H25: Progress till Date for the Month | I25: L2 till Current Month | J25: Completed till Date | K25: Balance Work | L25: Under Progress | M25: Gangs at Present | N25: Remarks | P25: Gap with respect to revised L2 - Cummilative till Jun-26 | Q25: Gap with respect to monthly plan for the month June-26
A26: Check Survey | B26: 92.281 | C26: 95 | D26: 92.281 | I26: =+C26+E26 -> 95 | J26: =+H26+D26 -> 92.281 | K26: =+B26-J26 -> 0
A27: Foundation | B27: 263 | C27: 267 | D27: 237 | E27: 12 | F27: 2 | I27: =+C27+E27 -> 279 | J27: =+H27+D27 -> 237 | K27: =+B27-J27 -> 26 | L27: 2 | M27: 2 | N27: 1FDN+1PILE | P27: =I27-J27 -> 42 | Q27: =F27-H27 -> 2
A28: Earthing | B28: 263 | C28: 267 | D28: 227 | E28: 12 | F28: 2 | I28: =+C28+E28 -> 279 | J28: =+H28+D28 -> 227 | K28: =+B28-J28 -> 36 | L28: 0 | P28: =I28-J28 -> 52 | Q28: =F28-H28 -> 2
A29: Tower Erection | B29: 263 | C29: 227 | D29: 154 | E29: 20 | F29: 2 | H29: 1 | I29: =+C29+E29 -> 247 | J29: =+H29+D29 -> 155 | K29: =+B29-J29 -> 108 | L29: 1 | M29: 1 | N29: Final Checking- 44 Towers done | P29: =I29-J29 -> 92 | Q29: =F29-H29 -> 1
A30: Tack welding | B30: 263 | C30: 227 | D30: 0 | E30: 20 | F30: 2 | I30: =+C30+E30 -> 247 | J30: =+H30+D30 -> 0 | K30: =+B30-J30 -> 263 | L30: 0 | M30: 0 | P30: =I30-J30 -> 247 | Q30: =F30-H30 -> 2
A31: Stringing-P/O-R/S | B31: 92.281 | C31: 25 | D31: 0 | E31: 13 | I31: =+C31+E31 -> 38 | J31: =+H31+D31 -> 0 | K31: =+B31-J31 -> 92.281 | L31: 0 | P31: =I31-J31 -> 38 | Q31: =F31-H31 -> 0
A32: Stringing-F/S | B32: 92.281 | C32: 25 | E32: 13 | I32: =+C32+E32 -> 38 | K32: =+B32-J32 -> 92.281 | P32: =I32-J32 -> 38 | Q32: =F32-H32 -> 0
A33: 400 kV Kishenpur-Samba D/C Line (Quad) - Wind Zone-5
A34: Activity | B34: Final Estimated Qty | C34: Cumulative L2 till Last Month | D34: Cumulative Progress till Last Month | E34: L2 for present Month (Revised) | F34: Plan for the Month | G34: Today's Progress | H34: Progress till Date for the Month | I34: L2 till Current Month | J34: Completed till Date | K34: Balance Work | L34: Under Progress | M34: Gangs at Present | N34: Remarks | P34: Gap with respect to revised L2 - Cummilative till Jun-26 | Q34: Gap with respect to monthly plan for the month June-26
A35: Check Survey | B35: 33.103 | C35: 33.103 | D35: 33.103 | I35: =+C35+E35 -> 33.103 | J35: =+H35+D35 -> 33.103 | K35: =+B35-J35 -> 0
A36: Foundation | B36: 116 | C36: 97 | D36: 70 | E36: 10 | F36: 16 | H36: 1 | I36: =+C36+E36 -> 107 | J36: =+H36+D36 -> 71 | K36: =+B36-J36 -> 45 | L36: 18 | M36: 13 | P36: =I36-J36 -> 36 | Q36: =F36-H36 -> 15
A37: Earthing | B37: 116 | C37: 97 | D37: 53 | E37: 10 | F37: 16 | I37: =+C37+E37 -> 107 | J37: =+H37+D37 -> 53 | K37: =+B37-J37 -> 63 | L37: 0 | P37: =I37-J37 -> 54 | Q37: =F37-H37 -> 16
A38: Tower Erection | B38: 116 | C38: 65 | D38: 16 | E38: 20 | F38: 26 | G38: 1 | H38: 7 | I38: =+C38+E38 -> 85 | J38: =+H38+D38 -> 23 | K38: =+B38-J38 -> 93 | L38: 10 | M38: 10 | P38: =I38-J38 -> 62 | Q38: =F38-H38 -> 19
A39: Tack welding | B39: 116 | C39: 65 | D39: 0 | E39: 20 | F39: 26 | I39: =+C39+E39 -> 85 | J39: =+H39+D39 -> 0 | K39: =+B39-J39 -> 116 | L39: 0 | M39: 0 | P39: =I39-J39 -> 85 | Q39: =F39-H39 -> 26
A40: Stringing-P/O-R/S | B40: 33.103 | C40: 0 | D40: 0 | E40: 4 | F40: 1 | I40: =+C40+E40 -> 4 | J40: =+H40+D40 -> 0 | K40: =+B40-J40 -> 33.103 | M40: 1 | N40: 1 Drone Team | P40: =I40-J40 -> 4 | Q40: =F40-H40 -> 1
A41: Stringing-F/S | B41: 33.103 | E41: 4 | F41: 1 | K41: =+B41-J41 -> 33.103 | P41: =I41-J41 -> 0 | Q41: =F41-H41 -> 1
A42: 400kV DC LILO at Kistwar(Twin) Line - Wind Zone-2
A43: Activity | B43: Final Estimated Qty | C43: Cumulative L2 till Last Month | D43: Cumulative Progress till Last Month | E43: L2 for present Month (Revised) | F43: Plan for the Month | G43: Today's Progress | H43: Progress till Date for the Month | I43: L2 till Current Month | J43: Completed till Date | K43: Balance Work | L43: Under Progress | M43: Gangs at Present | N43: Remarks | P43: Gap with respect to revised L2 - Cummilative till Jun-26 | Q43: Gap with respect to monthly plan for the month June-26
A44: Check Survey | B44: 3.415 | C44: 2 | D44: 3.415 | I44: =+C44+F44 -> 2 | J44: =+H44+D44 -> 3.415 | K44: =+B44-J44 -> 0
A45: Foundation | B45: 18 | C45: 5 | D45: 5 | E45: 2 | F45: 5 | H45: 2 | I45: =+C45+E45 -> 7 | J45: =+H45+D45 -> 7 | K45: =+B45-J45 -> 11 | L45: 6 | M45: 5 | P45: =I45-J45 -> 0 | Q45: =F45-H45 -> 3
A46: Earthing | B46: 18 | C46: 1 | D46: 0 | E46: 2 | F46: 5 | I46: =+C46+E46 -> 3 | J46: =+H46+D46 -> 0 | K46: =+B46-J46 -> 18 | L46: 0 | P46: =I46-J46 -> 3 | Q46: =F46-H46 -> 5
A47: Tower Erection | B47: 18 | C47: 0 | D47: 0 | E47: 2 | I47: =+C47+E47 -> 2 | J47: =+H47+D47 -> 0 | K47: =+B47-J47 -> 18 | L47: 0 | M47: 0 | P47: =I47-J47 -> 2 | Q47: =F47-H47 -> 0
A48: Tack welding | B48: 18 | C48: 0 | D48: 0 | E48: 2 | I48: =+C48+E48 -> 2 | J48: =+H48+D48 -> 0 | K48: =+B48-J48 -> 18 | L48: 0 | M48: 0 | P48: =I48-J48 -> 2 | Q48: =F48-H48 -> 0
A49: Stringing-P/O-R/S | B49: 3.415 | C49: 0 | D49: 0 | I49: =+C49+E49 -> 0 | J49: =+H49+D49 -> 0 | K49: =+B49-J49 -> 3.415 | L49: 0 | M49: 0 | P49: =I49-J49 -> 0
A50: Stringing-F/S | B50: 3.415 | K50: =+B50-J50 -> 3.415 | P50: =I50-J50 -> 0 | U50: =599+300 -> 899
A51: Supply Status | U51: =U50+300 -> 1199
A52: Line | B52: Description | C52: Final Estimated Qty | D52: L2 till Aug-26 | E52: Qty Supplied till Aug-26 | F52: Remarks
A53: Samba-Jalandhar | B53: Stubs | C53: =262+127 -> 389 | D53: =100+120+150+64 -> 434 | E53: 387
B54: Towers | C54: 389 | D54: =101+115+107 -> 323 | E54: 361 | P54: =P58-P55 -> 0 | Q54: New Received | S54: Quadian | T54: Samba
B55: 120 KN Ins | C55: 3016 | D55: =870+870+434 -> 2174 | E55: 900 | P55: =E57+E64+E72 -> 4254.241 | Q55: DPR | S55: 200 | T55: 810 | U55: =S55+T55 -> 1010
B56: 160 KN Ins | C56: 9132 | D56: =2998+2998+1500 -> 7496 | E56: =1700+400+100 -> 2200 | P56: =4254.241-P57 -> 1679.626 | Q56: Samba | S56: 300 | T56: 1200 | U56: =S56+T56 -> 1500
B57: Conductor | C57: =(47+93)*24*1.01 -> 3393.6 | D57: 3489 | E57: =3394+393.481+226.76 -> 4014.241 | P57: 2574.615 | Q57: Quadian
B58: OPGW | C58: 1 | D58: 1 | P58: =P56+P57 -> 4254.241 | Q58: Total Received Conductor
B59: HWF | C59: 1 | D59: 1 | E59: =(40+5)% -> 0.45
A60: Samba-Kishenpur | B60: Stubs | C60: 116 | D60: 129 | E60: 111
B61: Towers | C61: 116 | D61: 129 | E61: 111
B62: 120 KN Ins | C62: 295 | D62: =174+174 -> 348
B63: 160 KN Ins | C63: 5606 | D63: =2940+2940 -> 5880
B64: Conductor | C64: =33.4*24*1.01 -> 809.616 | D64: =286+516 -> 802 | E64: 224
B65: OPGW | C65: 1 | D65: 1
B66: GS E/W | C66: 1 | D66: 1 | E66: 1
B67: HWF | C67: 1 | D67: 1
A68: LILO at Kishtwar | B68: Stubs | C68: 18 | D68: 18 | E68: 15
B69: Towers | C69: 18 | D69: 18
B70: 120 KN Ins | C70: 117 | D70: 90
B71: 160 KN Ins | C71: 453 | D71: 252
B72: Conductor | C72: =3.43*12*1.01 -> 41.5716 | D72: 14 | E72: 16
B73: OPGW | C73: 1 | D73: 1
B74: GS E/W | C74: 1 | D74: 1
B75: HWF | C75: 1 | D75: 1

Sheet Sheet16
C2: S.No | D2: Gang | E2: Line | F2: Remarks
C3: 1 | D3: Pawan Kumar Sharma | E3: J-S (Jammu) | F3: Gang idle since 4-4-26 at Loc: 40/3 due to ROW
C4: =C3+1 -> 2 | D4: Md. Ikrar | E4: J-S(Punjab) | F4: Loc: 144/4 completed on 5-4-2026 and no work front available due to crop harvesting
C5: =C4+1 -> 3 | D5: Ms. Hussain | E5: J-S(Punjab) | F5: Loc: 144/3 will be completed on 6-4-2026 and no work front availabl due to crop harvesting
C6: =C5+1 -> 4

Sheet Sheet14
B1: S.No | C1: Month | D1: Concreting | F1: Cement | G1: TMT
D2: M10 | E2: M20
D3: M3 | E3: M3 | F3: Bags | G3: MT
B4: 1 | C4: 45901 | D4: 14.664 | E4: 135.088 | F4: =ROUND((D4*4.4)+(E4*8),0) -> 1145 | G4: 8.44
B5: =B4+1 -> 2 | C5: 45931 | D5: 76.132 | E5: 667.004 | F5: =ROUND((D5*4.4)+(E5*8),0) -> 5671 | G5: 47.8
B6: =B5+1 -> 3 | C6: 45962 | D6: 283.933 | E6: 2687.36 | F6: =ROUND((D6*4.4)+(E6*8),0) -> 22748 | G6: 176.38
B7: =B6+1 -> 4 | C7: 45992 | D7: 415.90302 | E7: 3983.996 | F7: =ROUND((D7*4.4)+(E7*8),0) -> 33702 | G7: 264.63 | L7: Concreting (M3) | M7: Tower Erection(MT)
B8: =B7+1 -> 5 | C8: 46023 | D8: 411.1974 | E8: 4750.4 | F8: =ROUND((D8*4.4)+(E8*8),0) -> 39812 | G8: 164.07 | L8: 21381 | M8: 2332
B9: =B8+1 -> 6 | C9: 46054 | D9: 411.1974 | E9: 4300.4 | F9: =ROUND((D9*4.4)+(E9*8),0) -> 36212 | G9: 264.45
B10: =B9+1 -> 7 | C10: 46082 | D10: 296.343 | E10: 2947.484 | F10: =ROUND((D10*4.4)+(E10*8),0) -> 24884 | G10: 199.54
B11: Total | D11: =SUM(D4:D10) -> 1909.3698 | E11: =SUM(E4:E10) -> 19471.732 | F11: =SUM(F4:F10) -> 164174 | G11: =SUM(G4:G10) -> 1125.31

Sheet Sheet12
C1: Supply Portion
C2: S.No | D2: Material | E2: UOM | F2: BOQ Qty | G2: Final Estimated Qty | H2: L2 till Mar'26 | I2: Supplied Qty | J2: Balance to Supply
C3: 1 | D3: Stubs | E3: EA | F3: 434 | G3: 389 | H3: 434 | I3: 353 | J3: =G3-I3 -> 36
C4: 2 | D4: Towers | E4: EA | F4: 434 | G4: 389 | H4: 216 | I4: 314 | J4: =G4-I4 -> 75
C7: S.No | D7: Activity | E7: UOM | F7: BOQ Qty | G7: Final Estimated Qty | H7: L2 till Feb'26 | I7: Completed till Feb'26 | J7: L2 Mar'26 | K7: Progress in Mar'26 | L7: Cumm L2 till Mar'26 | M7: Cumm. Progress till Mar'26 | N7: Balance | O7: Remarks
C8: 400 kV D/C Samba - Jalandhar TL
C9: 1 | D9: Survey | E9: Km | F9: 143 | G9: 137 | H9: 143 | I9: 136 | L9: =H9+J9 -> 143 | M9: =I9+K9 -> 136 | N9: =G9-M9 -> 1
C10: 2 | D10: Foundation | E10: EA | F10: 434 | G10: 389 | H10: 207 | I10: 202 | J10: 45 | K10: 28 | L10: =H10+J10 -> 252 | M10: =I10+K10 -> 230 | N10: =G10-M10 -> 159 | O10: 19 Gangs
C11: 3 | D11: Tower Erection | E11: EA | F11: 434 | G11: 389 | H11: 125 | I11: 55 | J11: 45 | K11: 48 | L11: =H11+J11 -> 170 | M11: =I11+K11 -> 103 | N11: =G11-M11 -> 286 | O11: 10 Gangs
C12: 4 | D12: Stringing | E12: Km | F12: 143 | G12: 137 | N12: =G12-M12 -> 137
C13: 400kV D/C Samba -Kishenpur TL
C14: 1 | D14: Survey | E14: Km | F14: 33 | G14: 33 | H14: 33 | I14: 33 | L14: =H14+J14 -> 33 | M14: =I14+K14 -> 33
C15: 2 | D15: Foundation | E15: EA | F15: 129 | G15: 116 | H15: 39 | I15: 37 | J15: 11 | K15: 7 | L15: =H15+J15 -> 50 | M15: =I15+K15 -> 44 | N15: =G15-M15 -> 72 | O15: 6 Gangs
C16: 3 | D16: Tower Erection | E16: EA | F16: 129 | G16: 116 | J16: 5 | K16: 2 | L16: =H16+J16 -> 5 | M16: =I16+K16 -> 2 | N16: =G16-M16 -> 114 | O16: 1 Gang
C17: 4 | D17: Stringing | E17: Km | F17: 33 | G17: 33 | N17: =G17-M17 -> 33
C18: LILO-Kisthwar
C19: 1 | D19: Survey | E19: Km | F19: 2 | G19: 3.4 | H19: 2 | I19: 3.4 | L19: =H19+J19 -> 2 | M19: =I19+K19 -> 3.4
C20: 2 | D20: Foundation | E20: EA | F20: 14 | G20: 18 | H20: 14 | L20: =H20+J20 -> 14 | N20: =G20-M20 -> 18 | O20: 3 Gangs
C21: 3 | D21: Tower Erection | E21: EA | F21: 14 | G21: 18 | J21: 2 | L21: =H21+J21 -> 2 | N21: =G21-M21 -> 18
C22: 4 | D22: Stringing | E22: Km | F22: 2 | G22: 3.4 | N22: =G22-M22 -> 3.4
C27: Supply Portion
C28: S.No | D28: Material | E28: UOM | F28: BOQ Qty | G28: Final Estimated Qty | H28: L2 till Mar'26 | I28: Supplied Qty | J28: Balance to Supply
C29: 1 | D29: Stubs | E29: EA | F29: 129 | G29: 116 | H29: 129 | I29: 64 | J29: =G29-I29 -> 52
C30: 2 | D30: Towers | E30: EA | F30: 129 | G30: 116 | H30: 129 | I30: 41 | J30: =G30-I30 -> 75
C32: Service Portion
C33: S.No | D33: Activity | E33: UOM | F33: BOQ Qty | G33: Final Estimated Qty | H33: L2 till Feb'26 | I33: Completed till Feb'26 | J33: L2 Mar'26 | K33: Progress in Mar'26 | L33: Cumm L2 till Mar'26 | M33: Cumm. Progress till Mar'26 | N33: Balance | O33: Remarks
C39: Supply Portion
C40: S.No | D40: Material | E40: UOM | F40: BOQ Qty | G40: Final Estimated Qty | H40: L2 till Mar'26 | I40: Supplied Qty | J40: Balance to Supply
C41: 1 | D41: Stubs | E41: EA | F41: 14 | G41: 18 | H41: 14 | I41: 10 | J41: =G41-I41 -> 8
C42: 2 | D42: Towers | E42: EA | F42: 14 | G42: 18 | H42: 14 | J42: =G42-I42 -> 18
C45: S.No | D45: Activity | E45: UOM | F45: BOQ Qty | G45: Final Estimated Qty | H45: L2 till Feb'26 | I45: Completed till Feb'26 | J45: L2 Mar'26 | K45: Progress in Mar'26 | L45: Cumm L2 till Mar'26 | M45: Cumm. Progress till Mar'26 | N45: Balance | O45: Remarks

Sheet Sheet13
C2: Paticulars | D2: Jammu Portion | E2: Punjab Portion
C3: Line Length (KM) | D3: 83 KM | E3: 90 KM
D4: =83/173 -> 0.47976879 | E4: =90/173 -> 0.52023121

Sheet Sheet15
C2: Supply Portion
C3: S.No | D3: Line | E3: LOA Cr | F3: Billed till date Cr | G3: Balance Cr
C4: 1 | D4: 400 kV Samba- Jalandhar D/C line (Quad) | E4: 155.09 | F4: 88.06 | G4: =E4-F4 -> 67.03
C5: 2 | D5: 400 kV Kishenpur-Samba D/C line (Quad) | E5: 67.47 | F5: =176387266/10^7 -> 17.638727 | G5: =E5-F5 -> 49.831273
C6: 3 | D6: LILO of 400 kV Kishenpur- Dulhasti line (Twin) at Kishtwar S/s | E6: 6.43 | F6: =1439185/10^7 -> 0.1439185 | G6: =E6-F6 -> 6.2860815
C7: Total | E7: =SUM(E4:E6) -> 228.99 | F7: =SUM(F4:F6) -> 105.84265 | G7: =SUM(G4:G6) -> 123.14735
C9: Service Portion
C10: S.No | D10: Line | E10: LOA Cr | F10: Billed till date Cr | G10: Balance Cr
C11: 1 | D11: 400 kV Samba- Jalandhar D/C line (Quad) | E11: 119.32273 | F11: =305299128/10^7 -> 30.529913 | G11: =E11-F11 -> 88.792813
C12: =C11+1 -> 2 | D12: 400 kV Kishenpur-Samba D/C line (Quad) | E12: 50.13038 | F12: =46321408/10^7 -> 4.6321408 | G12: =E12-F12 -> 45.498239 | J12: =88.06+17.64+0.14 -> 105.84
C13: =C12+1 -> 3 | D13: LILO of 400 kV Kishenpur- Dulhasti line (Twin) at Kishtwar S/s | E13: 4.4045142 | G13: =E13-F13 -> 4.4045142
C14: =C13+1 -> 4 | D14: Unit Rate Schedule for Services | E14: 6.4654119 | G14: =E14-F14 -> 6.4654119
C15: =C14+1 -> 5 | D15: ROW Schedule | E15: 5.9322034 | G15: =E15-F15 -> 5.9322034
C16: Total | E16: =SUM(E11:E15) -> 186.25524 | F16: =SUM(F11:F15) -> 35.162054 | G16: =SUM(G11:G15) -> 151.09318
F17: 1.5

Sheet TB401 DPR
A1: Project Progress for TB-401/408,Section-II
A2: 765KV D/C Fategarh-III Beawar Transmission Line | D2: TB-401 | G2: LOA Date | I2: Pkg-G -26.04.23 | L2: Completion Period | N2: 45747 | Q2: Date: | R2: =TODAY() -> 46247
D3: TB-408 | I3: Pkg-F - 11.09.23 | L3: Completion Period | N3: 45747
A4: .
A5: Activity | B5: Qty as per LOA | C5: Qty Received | D5: L2 | F5: Overall Progress | H5: Mar'25 | J5: Balance | K5: Apr'25 | O5: Plan | Q5: Remarks
D6: 45656 | E6: Till Mar-25 | F6: As on date | G6: Till Mar-25 | H6: Plan | I6: Actual | J6: As on date | K6: Plan | L6: WIP | M6: Today comp | N6: Actual | O6: 45536 | P6: 45474
A7: Details Survey | B7: 215 | C7: =C8+C9 -> 189.53 | E7: =E8+E9 -> 203 | F7: =F8+F9 -> 199.841 | G7: =G8+G9 -> 199.841
A8: Pkg-G (Section-II) | C8: 101.1 | E8: =215/2 -> 107.5 | F8: 101.1 | G8: 101.1
A9: Pkg-F (Section-II) | C9: 88.43 | E9: =(65+65+41+20)/2 -> 95.5 | F9: 98.741 | G9: 98.741
A10: Check Survey | B10: 215 | C10: =C11+C12 -> 189.53 | D10: =D11+D12 -> 0 | E10: =E11+E12 -> 203 | F10: =F11+F12 -> 189.526 | G10: =G11+G12 -> 184.552 | H10: =H11+H12 -> 14.88 | I10: =I11+I12 -> 6.08 | J10: =J11+J12 -> 0.004 | ... L10: =L11+L12 -> 0 | N10: =N11+N12 -> 4.974 | O10: =O11+O12 -> 0
A11: Pkg-G (Section-II) | C11: 101.1 | E11: =215/2 -> 107.5 | F11: =G11+N11 -> 101.096 | G11: 101.096 | H11: 6.08 | I11: 6.08 | J11: =C11-G11-N11 -> 0.004
A12: Pkg-F (Section-II) | C12: 88.43 | E12: =(65+65+41+20)/2 -> 95.5 | F12: =G12+N12 -> 88.43 | G12: =79.653+3.803 -> 83.456 | H12: 8.8 | J12: =C12-G12-N12 -> 0 | N12: 4.974
A13: Foundation | B13: 534 | C13: =C14+C15 -> 488 | D13: =D14+D15 -> 0 | E13: =E14+E15 -> 488 | F13: =F14+F15 -> 485 | G13: =G14+G15 -> 485 | H13: =H14+H15 -> 9 | I13: =I14+I15 -> 6 | J13: =J14+J15 -> 3 | ... L13: =L14+L15 -> 3 | N13: =N14+N15 -> 0 | O13: =O14+O15 -> 0 | P13: =P14+P15 -> 0
A14: Pkg-G (Section-II) | C14: 265 | E14: 265 | F14: =G14+N14 -> 265 | G14: 265 | H14: 5 | I14: 5 | J14: =C14-G14-N14 -> 0 | S14: 9649905358 | T14: D S Jangid
A15: Pkg-F (Section-II) | C15: 223 | E15: 223 | F15: =G15+N15 -> 220 | G15: 220 | H15: 4 | I15: 1 | J15: =C15-G15-N15 -> 3 | L15: 3 | S15: 7014675307 | T15: jangid
A16: Gang / Worker | K16: 10/180 | L16: 02/55
A17: Erection | B17: 534 | C17: =C18+C19 -> 488 | D17: =D18+D19 -> 0 | E17: =E18+E19 -> 488 | F17: =F18+F19 -> 367 | G17: =G18+G19 -> 365 | H17: =H18+H19 -> 36 | I17: =I18+I19 -> 24 | J17: =J18+J19 -> 121 | ... P17: =P18+P19 -> 0
A18: Pkg-G (Section-II) | C18: 265 | E18: 265 | F18: =G18+N18 -> 201 | G18: 201 | H18: 20 | I18: 11 | J18: =C18-G18-N18 -> 64 | L18: 0
A19: Pkg-F (Section-II) | C19: 223 | E19: 223 | F19: =G19+N19 -> 166 | G19: 164 | H19: 16 | I19: 13 | J19: =C19-G19-N19 -> 57 | L19: 4 | M19: 1 | N19: 2 | Q19: 70/10 Complete
A20: Gang / Worker | K20: 7/240 | L20: 4/241
A21: Stringing Payout | B21: 215 | C21: =C22+C23 -> 189.53 | D21: =D22+D23 -> 0 | E21: =E22+E23 -> 189.53 | F21: =F22+F23 -> 94.743 | G21: =G22+G23 -> 94.743 | H21: =H22+H23 -> 0 | I21: =I22+I23 -> 9.18 | J21: =J22+J23 -> 94.787 | ... O21: =O22+O23 -> 0 | P21: 15
A22: Pkg-G (Section-II) | C22: 101.1 | E22: 101.1 | F22: =G22+N22 -> 52.284 | G22: 52.284 | J22: =C22-G22-N22 -> 48.816
A23: Pkg-F (Section-II) | C23: 88.43 | E23: 88.43 | F23: =G23+N23 -> 42.459 | G23: 42.459 | I23: 9.18 | J23: =C23-G23-N23 -> 45.971 | L23: 1.881
A24: Gang / Worker | L24: 2/154
A25: Stringing Final sag | B25: 215 | C25: =C26+C27 -> 189.53 | D25: =D26+D27 -> 0 | E25: =E26+E27 -> 189.53 | F25: =F26+F27 -> 88.935 | G25: =G26+G27 -> 88.935 | H25: =H26+H27 -> 0 | I25: =I26+I27 -> 14.161 | J25: =J26+J27 -> 100.595 | ... O25: =O26+O27 -> 0 | P25: 15
A26: Pkg-G (Section-II) | C26: 101.1 | E26: 101.1 | F26: =G26+N26 -> 49.703 | G26: 49.703 | I26: 4.981 | J26: =C26-G26-N26 -> 51.397 | L26: =7.562-4.981 -> 2.581
A27: Pkg-F (Section-II) | C27: 88.43 | E27: 88.43 | F27: =G27+N27 -> 39.232 | G27: 39.232 | I27: 9.18 | J27: =C27-G27-N27 -> 49.198 | L27: 3.227
A28: Gang / Worker | L28: 2/154

Sheet Survey-Summary
B1: PROJECT NAME | C1: INDIGRID - 400kV D/C QUAD WZ-5 SAMBA-JALANDHAR & KISHENPUR-SAMBA TL | Z1: COMP | AA1: APPROVED
B2: START DATE (NOA DATE) | C2: 16-MAY-2025 | Z2: PENDING | AA2: UNDER REVIEW
B3: KEC PROJECT | C3: TB-605 | AA3: PENDING
B4: NAME OF CLIENT | C4: RATLE KIRU POWER TRANSMISSION LIMITED
B5: TITLE | C5: SITE SURVEY STATUS
B7: TEAM FORMATION | H7: CHECK SURVEY SUMMARY (KM)
B8: Portion | C8: SURVEY LEAD | D8: TEAM MEMBERS | E8: MACHINE | F8: LINE NAME | G8: SECTION LENGTH | H8: COMPLETED | I8: BALANCE | J8: SUBMITTED | K8: APPROVED | L8: APPROVAL PENDING | M8: REMARK
B9: Jammu | C9: 1)BIPPAN SHARMA | D9: 2) Shiv Kumar( Asst Surveyor) | E9: DGPS-1 TS-02 | F9: 400kV D/C Jalandar - Samba T/L (GANTRY TO AP 52) | G9: 46.915 | H9: =45.61+0.83 -> 46.44 | I9: =G9-H9 -> 0.475 | J9: =39.202+4.505+2.346 -> 46.053 | K9: 46.053 | L9: =J9-K9 -> 0 | M9: 0.48 km is from Sambha Gantyry to AP 4
D10: 3) Sahil Raj(Asst Surveyor) | F10: 400kV D/C Samba - Kishenpur T/L | G10: 33 | H10: =7.63+0.34+0.29+0.3+0.83+2.257+0.79+0.849+1.044+0.76+0.7+0.4+0.3+0.964+0.684+2+3+4 -> 27.138 | I10: =G10-H10 -> 5.862 | J10: 19.6 | K10: 19.6 | L10: =J10-K10 -> 0 | M10: AP4-AP14, AP24-AP55, AP55-AP70, AP70-AP86,AP95-AP109 C/S Completed AP15-AP24 - Re-routing required due to landsliding (Hold) AP86-AP95 - Hold due to under powerline crossing
D11: 4) Sunil (Survey Helper) | F11: LILO at Kistwar | G11: 2.18 | H11: 2.18 | I11: =G11-H11 -> 0 | J11: 2.18 | K11: 2.18 | L11: =J11-K11 -> 0 | M11: Contour completed 12 Locations out of 13 location AP 11 conturing not done due to ROW since 29th Jul'25
D12: 5) Sanjhi Ram((Survey Helper) | I12: =G12-H12 -> 0 | L12: =J12-K12 -> 0
B13: Punjab | C13: 1)RAJ KAMAL GHOSH | D13: 2) Anupam Basak (Survayor DET) | E13: TS-01 | F13: 400kV D/C Jalandar - Samba T/L ( AP 52-115) | G13: 47.25 | H13: 46.474 | I13: =G13-H13 -> 0.776 | J13: 45.892 | K13: =13.05+32.842 -> 45.892 | L13: =J13-K13 -> 0
D14: 3) Kuldeep singh (supervisor DET) | I14: =G14-H14 -> 0 | L14: =J14-K14 -> 0
D15: 4) Vickey Ghosh (Survey DET) | I15: =G15-H15 -> 0 | L15: =J15-K15 -> 0
D16: 5) Rupak Kumar (Survey Helper) | L16: =J16-K16 -> 0
B17: Punjab | C17: 1)SAGAR MAJHI | D17: 2) Surajit Majhi(Asst Surveyor) | E17: TS-01 | F17: 400kV D/C Jalandar - Samba T/L ( AP 115-187) | G17: 47.805 | H17: =34.985+1.456+2.013+2.516 -> 40.97 | I17: =G17-H17 -> 6.835 | J17: 47.81 | K17: 23.519 | L17: =J17-K17 -> 24.291
D18: 3) Rudra Madhav (supervisor DET) | I18: =G18-H18 -> 0 | L18: =J18-K18 -> 0
D19: 4)Gordhan Ram (supervisor DET) | I19: =G19-H19 -> 0 | L19: =J19-K19 -> 0
I20: =G20-H20 -> 0 | L20: =J20-K20 -> 0
B21: TOTAL (KM) | G21: =SUM(G9:G20) -> 177.15 | H21: =SUM(H9:H20) -> 163.202 | I21: =SUM(I9:I20) -> 13.948 | J21: =SUM(J9:J20) -> 161.535 | K21: =SUM(K9:K20) -> 137.244 | L21: =SUM(L9:L20) -> 24.291 | M21: =SUM(M9:M20) -> 0
G26: 400kV D/C Samba-Jalandhar C/S -Details
G27: S.No | H27: Section | I27: Section | J27: Length | K27: Submitted | L27: Approval Date | M27: Remarks
J28: Km | K28: Date
G29: 1 | H29: AP20-AP30 | I29: Jammu | J29: 10.43 | K29: 45846 | L29: 45854
G30: 2 | H30: AP30-AP41 | I30: Jammu | J30: 13.72 | K30: 45857 | L30: 45862
G31: 3 | H31: AP41-AP51 | I31: Jammu | J31: 15.05 | K31: 45868 | L31: 45873
G32: 4 | H32: AP15-AP20 | I32: Jammu | J32: 4.51 | K32: 45908 | L32: 45909
G33: 5 | H33: AP5-AP15 | I33: Jammu | J33: 2.346 | K33: 45918 | L33: 45930
G34: 5 | H34: AP53-AP66 | I34: Punjab | J34: 11.37 | K34: 45875 | L34: 45894
G35: 6 | H35: AP70-AP84 | I35: Punjab | J35: 11.41 | K35: 45885 | L35: 45900
G36: 7 | H36: AP84-AP96 | I36: Punjab | J36: 10.07 | K36: 45890 | L36: 45894
G37: 8 | H37: AP115-AP123 | I37: Punjab | J37: 6.93 | K37: 45888 | L37: 45904
G38: 9 | H38: AP131-AP140 | I38: Punjab | J38: 10.3 | K38: 45888 | L38: 45904
G39: 10 | H39: AP145-AP153 | I39: Punjab | J39: 6.29 | K39: 45892 | L39: 45904
G40: 11 | H40: AP96-AP115 | I40: Punjab | J40: 9.626 | K40: 45913 | L40: 45961
G41: 12 | H41: AP66-AP70 | I41: Punjab | J41: 3.42 | K41: 45919 | L41: 45961
G42: 13 | H42: AP153-AP175 | I42: Punjab | J42: 12.083 | K42: 45922 | M42: Route diversion in between 168-175 to be finalized
G43: Total | J43: =SUM(J29:J42) -> 127.555
G45: 400kV D/C Kishenpur-Samba C/S -Details
G46: S.No | H46: Section | I46: Section | J46: Length | K46: Submitted | L46: Approval Date | M46: Remarks
J47: Km | K47: Date
G48: 1 | H48: AP95-AP109 | I48: Jammu | J48: 3.13 | K48: 45908 | L48: 45909
G49: =G48+1 -> 2 | H49: AP78-AP86 | I49: Jammu | J49: 1.945 | K49: 45927 | L49: 45930
G50: =G49+1 -> 3 | H50: AP24-AP39 | I50: Jammu | J50: 5.5 | K50: 16-10-2025 30-10-2025 | L50: 45962
G51: =G50+1 -> 4 | H51: AP39-AP55 | I51: Jammu | J51: 5.463 | K51: 45985 | L51: 45994
G52: =G51+1 -> 5 | H52: AP4-AP14 | I52: Jammu | J52: 3.597 | K52: 45994 | L52: 45994
G53: Total | J53: =SUM(J48:J52) -> 19.635
G55: LILO-Kisthewar C/S -Details
G56: S.No | H56: Section | I56: Section | J56: Length | K56: Submitted | L56: Approval Date | M56: Remarks
J57: Km | K57: Date
G58: 1 | H58: TP-Gantry | I58: Kishtwar | J58: 2.18 | K58: 30-08-2025 08-09-2025 27-09-2025 | L58: 45930
G59: Total | J59: =SUM(J58:J58) -> 2.18

Sheet Sheet6
D2: Survey
D3: Line | E3: Portion | F3: Scope | G3: Completed | H3: Submitted | I3: Approved
D4: S-J | E4: Jammu | F4: 46.92 | G4: 46.44 | H4: 46.44 | I4: 46.44
D5: S-J | E5: Punjab | F5: 95.06 | G5: 95.06 | H5: 84.936 | I5: 72.85
D6: K-S | F6: 33.103 | G6: 23.393 | H6: 16.04 | I6: 10.6
D7: LILO | F7: 2.18 | G7: 2.18 | H7: 2.18 | I7: 2.18
D8: Total | F8: =SUM(F4:F7) -> 177.263 | G8: =SUM(G4:G7) -> 167.073 | H8: =SUM(H4:H7) -> 149.596 | I8: =SUM(I4:I7) -> 132.07
F10: 16.04 | J10: 10.58
F11: 45.892 | J11: 45.892
F12: 46.06 | J12: 46.06
F13: 20.674 | G13: 18.37 | J13: 20.674
F14: 12.08
F15: 2.18
J16: =66.566+6.29 -> 72.856

Sheet Approved Survey
A1: KEC INTERNATIONAL LIMITED
A2: 400 kV Samba- Jalandhar D/C Line(Quad) - Wind Zone - 5 | H2: 400 kV Samba- Kishenpur D/C Line(Quad) - Wind Zone - 5
A3: Approved Check Survey Sections | H3: Approved Check Survey Sections
A4: S.No | B4: Portion | C4: Section | D4: Length Km | H4: S.No | I4: Section | J4: Length Km
A5: 1 | B5: Jammu | C5: AP5-AP6 | D5: =119.059/1000 -> 0.119059 | H5: 1 | I5: AP78-AP86 | J5: 1.945
A6: =A5+1 -> 2 | B6: Jammu | C6: AP6-AP7 | D6: =92.496/1000 -> 0.092496 | H6: 2 | I6: AP95-AP109 | J6: 3.13
A7: =A6+1 -> 3 | B7: Jammu | C7: AP7-AP8 | D7: =134.988/1000 -> 0.134988 | H7: 3 | I7: AP24-AP39 | J7: 5.5
A8: =A7+1 -> 4 | B8: Jammu | C8: AP8-AP9 | D8: =365.176/1000 -> 0.365176 | H8: Total | J8: =SUM(J5:J7) -> 10.575
A9: =A8+1 -> 5 | B9: Jammu | C9: AP9-AP10 | D9: =236.697/1000 -> 0.236697
A10: =A9+1 -> 6 | B10: Jammu | C10: AP10-AP11 | D10: =213.152/1000 -> 0.213152 | H10: LILO-Kishtwar
A11: =A10+1 -> 7 | B11: Jammu | C11: AP11-AP12 | D11: =206.593/1000 -> 0.206593 | H11: Approved Check Survey Sections
A12: =A11+1 -> 8 | B12: Jammu | C12: AP12-AP13 | D12: =289.862/1000 -> 0.289862 | H12: S.No | I12: Section | J12: Length Km
A13: =A12+1 -> 9 | B13: Jammu | C13: AP13-AP14 | D13: =402.938/1000 -> 0.402938 | H13: 1 | I13: AP1-TP | J13: 2.18
A14: =A13+1 -> 10 | B14: Jammu | C14: AP14-AP15 | D14: =284.883/1000 -> 0.284883
A15: =A14+1 -> 11 | B15: Jammu | C15: AP15-AP16 | D15: =1673.439/1000 -> 1.673439
A16: =A15+1 -> 12 | B16: Jammu | C16: AP16-AP17 | D16: =285.948/1000 -> 0.285948
A17: =A16+1 -> 13 | B17: Jammu | C17: AP17-AP18 | D17: =401.159/1000 -> 0.401159
A18: =A17+1 -> 14 | B18: Jammu | C18: AP18-AP19 | D18: =1055.218/1000 -> 1.055218
A19: =A18+1 -> 15 | B19: Jammu | C19: AP19-AP20 | D19: =1088.747/1000 -> 1.088747
A20: =A19+1 -> 16 | B20: Jammu | C20: AP20-AP21 | D20: =485.93/1000 -> 0.48593
A21: =A20+1 -> 17 | B21: Jammu | C21: AP21-AP22 | D21: =712.337/1000 -> 0.712337
A22: =A21+1 -> 18 | B22: Jammu | C22: AP22-AP23 | D22: =1177.079/1000 -> 1.177079
A23: =A22+1 -> 19 | B23: Jammu | C23: AP23-AP24 | D23: =2454.951/1000 -> 2.454951
A24: =A23+1 -> 20 | B24: Jammu | C24: AP24-AP25 | D24: =366.044/1000 -> 0.366044
A25: =A24+1 -> 21 | B25: Jammu | C25: AP25-AP26 | D25: =1028.029/1000 -> 1.028029
A26: =A25+1 -> 22 | B26: Jammu | C26: AP26-AP27 | D26: =442.371/1000 -> 0.442371
A27: =A26+1 -> 23 | B27: Jammu | C27: AP27-AP28 | D27: =739.739/1000 -> 0.739739
A28: =A27+1 -> 24 | B28: Jammu | C28: AP28-AP29 | D28: =445.991/1000 -> 0.445991
A29: =A28+1 -> 25 | B29: Jammu | C29: AP29-AP30 | D29: =2573.629/1000 -> 2.573629
A30: =A29+1 -> 26 | B30: Jammu | C30: AP30-AP31 | D30: =2514.73/1000 -> 2.51473
A31: =A30+1 -> 27 | B31: Jammu | C31: AP31-AP32 | D31: =2374.48/1000 -> 2.37448
A32: =A31+1 -> 28 | B32: Jammu | C32: AP32-AP33 | D32: =836.984/1000 -> 0.836984
A33: =A32+1 -> 29 | B33: Jammu | C33: AP33-AP34 | D33: =967.8/1000 -> 0.9678
A34: =A33+1 -> 30 | B34: Jammu | C34: AP34-AP35 | D34: =819.907/1000 -> 0.819907
A35: =A34+1 -> 31 | B35: Jammu | C35: AP35-AP36 | D35: =820.234/1000 -> 0.820234
A36: =A35+1 -> 32 | B36: Jammu | C36: AP36-AP37 | D36: =439.8/1000 -> 0.4398
A37: =A36+1 -> 33 | B37: Jammu | C37: AP37-AP38 | D37: =1203.4/1000 -> 1.2034
A38: =A37+1 -> 34 | B38: Jammu | C38: AP38-AP39 | D38: =775.272/1000 -> 0.775272
A39: =A38+1 -> 35 | B39: Jammu | C39: AP39-AP40 | D39: =1209.893/1000 -> 1.209893
A40: =A39+1 -> 36 | B40: Jammu | C40: AP40-AP41 | D40: =1760.473/1000 -> 1.760473
A41: =A40+1 -> 37 | B41: Jammu | C41: AP41-AP42 | D41: =212.44/1000 -> 0.21244
A42: =A41+1 -> 38 | B42: Jammu | C42: AP42-AP43 | D42: =1361.04/1000 -> 1.36104
A43: =A42+1 -> 39 | B43: Jammu | C43: AP43-AP44 | D43: =1911.9/1000 -> 1.9119
A44: =A43+1 -> 40 | B44: Jammu | C44: AP44-AP45 | D44: =1474.69/1000 -> 1.47469
A45: =A44+1 -> 41 | B45: Jammu | C45: AP45-AP46 | D45: =1079.5/1000 -> 1.0795
A46: =A45+1 -> 42 | B46: Jammu | C46: AP46-AP47 | D46: =2216.45/1000 -> 2.21645
A47: =A46+1 -> 43 | B47: Jammu | C47: AP47-AP48 | D47: =1360.36/1000 -> 1.36036
A48: =A47+1 -> 44 | B48: Jammu | C48: AP48-AP49 | D48: =371.5/1000 -> 0.3715
A49: =A48+1 -> 45 | B49: Jammu | C49: AP49-AP50 | D49: =203.3/1000 -> 0.2033
A50: =A49+1 -> 46 | B50: Jammu | C50: AP50-AP50A | D50: =409.91/1000 -> 0.40991
A51: =A50+1 -> 47 | B51: Jammu | C51: AP50A-AP51 | D51: =4450.9/1000 -> 4.4509
A52: =A51+1 -> 48 | B52: Punjab | C52: AP53-AP54 | D52: =416.66/1000 -> 0.41666
A53: =A52+1 -> 49 | B53: Punjab | C53: AP54-AP55 | D53: =389.29/1000 -> 0.38929
A54: =A53+1 -> 50 | B54: Punjab | C54: AP55-AP56 | D54: =793.45/1000 -> 0.79345
A55: =A54+1 -> 51 | B55: Punjab | C55: AP56-AP57 | D55: =1906.1/1000 -> 1.9061
A56: =A55+1 -> 52 | B56: Punjab | C56: AP57-AP58 | D56: =982.37/1000 -> 0.98237
A57: =A56+1 -> 53 | B57: Punjab | C57: AP58-AP59 | D57: =406.44/1000 -> 0.40644
A58: =A57+1 -> 54 | B58: Punjab | C58: AP59-AP60 | D58: =788.04/1000 -> 0.78804
A59: =A58+1 -> 55 | B59: Punjab | C59: AP60-AP61 | D59: =757.58/1000 -> 0.75758
A60: =A59+1 -> 56 | B60: Punjab | C60: AP61-AP62 | D60: =563.92/1000 -> 0.56392
A61: =A60+1 -> 57 | B61: Punjab | C61: AP62-AP63 | D61: =1081.23/1000 -> 1.08123
A62: =A61+1 -> 58 | B62: Punjab | C62: AP63-AP64 | D62: =450.86/1000 -> 0.45086
A63: =A62+1 -> 59 | B63: Punjab | C63: AP64-AP65 | D63: =602.84/1000 -> 0.60284
A64: =A63+1 -> 60 | B64: Punjab | C64: AP65-AP66 | D64: =2228.49/1000 -> 2.22849
A65: =A64+1 -> 61 | B65: Punjab | C65: AP70-AP71 | D65: =1598.955/1000 -> 1.598955
A66: =A65+1 -> 62 | B66: Punjab | C66: AP71-AP72 | D66: =1666.222/1000 -> 1.666222
A67: =A66+1 -> 63 | B67: Punjab | C67: AP72-AP73 | D67: =809.571/1000 -> 0.809571
A68: =A67+1 -> 64 | B68: Punjab | C68: AP73-AP74 | D68: =406.688/1000 -> 0.406688
A69: =A68+1 -> 65 | B69: Punjab | C69: AP74-AP75 | D69: =316.253/1000 -> 0.316253
A70: =A69+1 -> 66 | B70: Punjab | C70: AP75-AP76 | D70: =248.423/1000 -> 0.248423
A71: =A70+1 -> 67 | B71: Punjab | C71: AP76-AP77 | D71: =1681.454/1000 -> 1.681454
A72: =A71+1 -> 68 | B72: Punjab | C72: AP77-AP78 | D72: =1630.396/1000 -> 1.630396
A73: =A72+1 -> 69 | B73: Punjab | C73: AP78-AP79 | D73: =320.743/1000 -> 0.320743
A74: =A73+1 -> 70 | B74: Punjab | C74: AP79-AP80 | D74: =242.225/1000 -> 0.242225
A75: =A74+1 -> 71 | B75: Punjab | C75: AP80-AP81 | D75: =839.249/1000 -> 0.839249
A76: =A75+1 -> 72 | B76: Punjab | C76: AP81-AP82 | D76: =242.663/1000 -> 0.242663
A77: =A76+1 -> 73 | B77: Punjab | C77: AP82-AP83 | D77: =1149.152/1000 -> 1.149152
A78: =A77+1 -> 74 | B78: Punjab | C78: AP83-AP84 | D78: =251.516/1000 -> 0.251516
A79: =A78+1 -> 75 | B79: Punjab | C79: AP84-AP85 | D79: =445.126/1000 -> 0.445126
A80: =A79+1 -> 76 | B80: Punjab | C80: AP85-AP86 | D80: =838.553/1000 -> 0.838553
A81: =A80+1 -> 77 | B81: Punjab | C81: AP86-AP87 | D81: =836.764/1000 -> 0.836764
A82: =A81+1 -> 78 | B82: Punjab | C82: AP87-AP88 | D82: =1185.42/1000 -> 1.18542
A83: =A82+1 -> 79 | B83: Punjab | C83: AP88-AP89 | D83: =211.063/1000 -> 0.211063
A84: =A83+1 -> 80 | B84: Punjab | C84: AP89-AP90 | D84: =618.229/1000 -> 0.618229
A85: =A84+1 -> 81 | B85: Punjab | C85: AP90-AP91 | D85: =1181.01/1000 -> 1.18101
A86: =A85+1 -> 82 | B86: Punjab | C86: AP91-AP92 | D86: =247.685/1000 -> 0.247685
A87: =A86+1 -> 83 | B87: Punjab | C87: AP92-AP93 | D87: =1455.156/1000 -> 1.455156
A88: =A87+1 -> 84 | B88: Punjab | C88: AP93-AP94 | D88: =889.075/1000 -> 0.889075
A89: =A88+1 -> 85 | B89: Punjab | C89: AP94-AP95 | D89: =411.542/1000 -> 0.411542
A90: =A89+1 -> 86 | B90: Punjab | C90: AP95-AP96 | D90: =1751.019/1000 -> 1.751019
A91: =A90+1 -> 87 | B91: Punjab | C91: AP115-AP116 | D91: =751.41/1000 -> 0.75141
A92: =A91+1 -> 88 | B92: Punjab | C92: AP116-AP117 | D92: =515.47/1000 -> 0.51547
A93: =A92+1 -> 89 | B93: Punjab | C93: AP117-AP118 | D93: =1409.68/1000 -> 1.40968
A94: =A93+1 -> 90 | B94: Punjab | C94: AP118-AP119 | D94: =634.36/1000 -> 0.63436
A95: =A94+1 -> 91 | B95: Punjab | C95: AP119-AP120 | D95: =518.18/1000 -> 0.51818
A96: =A95+1 -> 92 | B96: Punjab | C96: AP120-AP121 | D96: =1212.37/1000 -> 1.21237
A97: =A96+1 -> 93 | B97: Punjab | C97: AP121-AP122 | D97: =1136.859/1000 -> 1.136859
A98: =A97+1 -> 94 | B98: Punjab | C98: AP122-AP123 | D98: =753.546/1000 -> 0.753546
A99: =A98+1 -> 95 | B99: Punjab | C99: AP131-AP132 | D99: =2841.988/1000 -> 2.841988
A100: =A99+1 -> 96 | B100: Punjab | C100: AP132-AP133 | D100: =816.077/1000 -> 0.816077
...

Sheet Approved CS J-S Line
A1: Line: 400 kV D/C Quad Jalandhar-Samba TL
A2: Approved Check Survey Tower Schedule
A3: AS PER DETAIL SURVEY | J3: AS PER CHECK SURVEY
A4: Sr. No. | B4: Tower No. | C4: Type of Tower | D4: Span Length (m) | E4: Section Length (m) | F4: Angle of Deviation | G4: UTM Coordinates | J4: Sr. No. | K4: Tower No. | L4: Type of Tower | M4: Raised Chimney | Q4: Leg Extension | U4: Span Length (m) | V4: Section Length (m) | W4: Reduced Level | X4: Angle of Deviation | Y4: UTM Coordinates | AA4: Crossing/Remarks
G5: Easting | H5: Northing | M5: LEG A | N5: LEG B | O5: LEG C | P5: LEG D | Q5: LEG A | R5: LEG B | S5: LEG C | T5: LEG D | Y5: Easting | Z5: Northing
A6: 1 | B6: AP 5/0 | C6: DD+18 | E6: 0 | F6: 47°01'57"L | G6: 516661.84 | H6: 3596578.1 | J6: 1 | K6: AP 5/0 | L6: DD+0 | M6: 0 | N6: 0 | O6: 0 | P6: 0 | Q6: 0 | R6: 0 | S6: 0 | T6: 0 | V6: 0 | W6: 384.3 | X6: 47°01'59"LT | Y6: 516472.78 | Z6: 3598642.7
D7: 119.059 | U7: 119.059 | AA7: 2 nos 11 KV,Road Crossing
A8: =A6+1 -> 2 | B8: AP 6/0 | C8: DA+0 | E8: =E6+D7 -> 119.059 | F8: 40°54'41"R | G8: 516805.33 | H8: 3596183.2 | J8: =J6+1 -> 2 | K8: AP 6/0 | L8: DD+9 | M8: 0 | N8: 0 | O8: 0 | P8: 0 | Q8: 0 | R8: 0 | S8: 0 | T8: 0 | V8: =U7 -> 119.059 | W8: 384.202 | X8: 40°54'42"RT | Y8: 516557.85 | Z8: 3598559.4
D9: 92.496 | U9: 92.496
A10: =A8+1 -> 3 | B10: AP 7/0 | C10: DA+0 | E10: =E8+D9 -> 211.555 | F10: 47°08'48"L | G10: 516948.8 | H10: 3595788.3 | J10: =J8+1 -> 3 | K10: AP 7/0 | L10: DD+25 | M10: 0 | N10: 0 | O10: 0 | P10: 0 | Q10: 0 | R10: 0 | S10: 0 | T10: 0 | V10: =V8+U9 -> 211.555 | W10: 382.166 | X10: 47°08'48"LT | Y10: 516565.42 | Z10: 3598467.2
D11: 134.989 | U11: 134.988 | AA11: 400 KV(JAL-SAM) line Crossing
A12: =A10+1 -> 4 | B12: AP 8/0 | C12: DA+6 | E12: =E10+D11 -> 346.544 | F12: 41°15'08"R | G12: 517087.16 | H12: 3595407.5 | J12: =J10+1 -> 4 | K12: AP 8/0 | L12: DD+25 | M12: 0 | N12: 0 | O12: 0 | P12: 0 | Q12: 0 | R12: 0 | S12: 0 | T12: 0 | V12: =V10+U11 -> 346.543 | W12: 377.89 | X12: 41°15'08"RT | Y12: 516671.56 | Z12: 3598383.8
D13: 365.175 | U13: 365.176 | AA13: Nalla Crossing
A14: =A12+1 -> 5 | B14: AP 9/0 | C14: DC+6 | E14: =E12+D13 -> 711.719 | F14: 37°05'47"R | G14: 517233.3 | H14: 3595005.3 | J14: =J12+1 -> 5 | K14: AP 9/0 | L14: DD+9 | M14: 0 | N14: 0 | O14: 0 | P14: 0 | Q14: 0 | R14: 0 | S14: 0 | T14: 0 | V14: =V12+U13 -> 711.719 | W14: 373.28 | X14: 37°05'47"RT | Y14: 516738.65 | Z14: 3598024.8
D15: 236.697 | U15: 236.697 | AA15: 2 nos 25KV,Railway Crossing
A16: =A14+1 -> 6 | B16: AP 10/0 | C16: DC+3 | E16: =E14+D15 -> 948.416 | F16: 20°40'31"L | G16: 517425.65 | H16: 3594793.7 | J16: =J14+1 -> 6 | K16: AP 10/0 | L16: DD+9 | M16: 0 | N16: 0 | O16: 0 | P16: 0 | Q16: 0 | R16: 0 | S16: 0 | T16: 0 | V16: =V14+U15 -> 948.416 | W16: 364.063 | X16: 20°40'31"LT | Y16: 516633 | Z16: 3597813
D17: 213.252 | U17: 213.252
A18: =A16+1 -> 7 | B18: AP 11/0 | C18: DC+3 | E18: =E16+D17 -> 1161.668 | F18: 51°34'01"R | G18: 517777.57 | H18: 3594601.2 | J18: =J16+1 -> 7 | K18: AP 11/0 | L18: DD+25 | M18: 0 | N18: 0 | O18: 0 | P18: 0 | Q18: 0 | R18: 0 | S18: 0 | T18: 0 | V18: =V16+U17 -> 1161.668 | W18: 361.99 | X18: 51°34'02"RT | Y18: 516611.32 | Z18: 3597600.9
D19: 206.592 | U19: 206.593 | AA19: Cannal,11 KV,Road,400 kv(JAL-SAM) Line Crossing
A20: =A18+1 -> 8 | B20: AP 12/0 | C20: DA+0 | E20: =E18+D19 -> 1368.26 | F20: 47°50'12"L | G20: 517986.28 | H20: 3594326.4 | J20: =J18+1 -> 8 | K20: AP 12/0 | L20: DD+30 | M20: 0 | N20: 0 | O20: 0 | P20: 0 | Q20: 0 | R20: 0 | S20: 0 | T20: 0 | V20: =V18+U19 -> 1368.261 | W20: 353.883 | X20: 47°50'13"LT | Y20: 516437.27 | Z20: 3597489.6
D21: 289.862 | U21: 289.862 | AA21: 220 kv(HRN-SAM) Line Crossing
A22: =A20+1 -> 9 | B22: AP 13/0 | C22: DA+0 | E22: =E20+D21 -> 1658.122 | F22: 39°08'44"L | G22: 518204.06 | H22: 3594039.8 | J22: =J20+1 -> 9 | K22: AP 13/0 | L22: DD+25 | M22: 0 | N22: 0 | O22: 0 | P22: 0 | Q22: 1.5 | R22: 1.5 | S22: 0 | T22: 0 | V22: =V20+U21 -> 1658.123 | W22: 348.38 | X22: 39°08'44"LT | Y22: 516389.11 | Z22: 3597203.7
D23: 402.938 | U23: 402.938 | AA23: Cannal,Cart Track Crossing
A24: =A22+1 -> 10 | B24: AP 14/0 | C24: DC+0 | E24: =E22+D23 -> 2061.06 | F24: 14°33'47"R | G24: 518415.92 | H24: 3593760.9 | J24: =J22+1 -> 10 | K24: AP 14/0 | L24: DB+9 | M24: 0 | N24: 0 | O24: 0 | P24: 0 | Q24: 0 | R24: 0 | S24: 2 | T24: 0 | V24: =V22+U23 -> 2061.061 | W24: 345.17 | X24: 14°33'47"RT | Y24: 516588.02 | Z24: 3596853.3
D25: 284.883 | U25: 284.883 | AA25: River,220 KV(BAR-HRN)Line Crossing
A26: =A24+1 -> 11 | B26: AP 15/0 | C26: DA+0 | E26: =E24+D25 -> 2345.943 | F26: 4°57'01"L | G26: 518741.12 | H26: 3593584.5 | J26: =J24+1 -> 11 | K26: AP 15/0 | L26: DD+18 | M26: 0 | N26: 0 | O26: 0 | P26: 0 | Q26: 1.5 | R26: 0 | S26: 0 | T26: 0 | V26: =V24+U25 -> 2345.944 | W26: 341.282 | X26: 4°57'01"LT | Y26: 516661.84 | Z26: 3596578.1
D27: 420.199 | U27: 412.199 | AA27: Canal crosssing
A28: =A26+1 -> 12 | B28: 15/1 | C28: DA+0 | G28: 516805.33 | H28: 3596183.2 | J28: =J26+1 -> 12 | K28: 15/1 | L28: DA+0 | M28: 0 | N28: 0 | O28: 0 | P28: 0 | Q28: 0 | R28: 0 | S28: 0 | T28: 0 | W28: 337.118 | Y28: 516802.6 | Z28: 3596190.7
D29: 420.127 | U29: 428.128
A30: =A28+1 -> 13 | B30: 15/2 | C30: DA+0 | G30: 516948.8 | H30: 3595788.3 | J30: =J28+1 -> 13 | K30: 15/2 | L30: DA+0 | M30: 0 | N30: 0 | O30: 0 | P30: 0 | Q30: 0 | R30: 0 | S30: 0 | T30: 0 | W30: 331.591 | Y30: 516948.8 | Z30: 3595788.3
D31: 405.152 | U31: 405.152 | AA31: Road and LT Line crossing
A32: =A30+1 -> 14 | B32: 15/3 | C32: DA+6 | G32: 517087.16 | H32: 3595407.5 | J32: =J30+1 -> 14 | K32: 15/3 | L32: DA+9 | M32: 0 | N32: 0 | O32: 0 | P32: 0 | Q32: 0 | R32: 0 | S32: 0 | T32: 0 | W32: 327.063 | Y32: 517087.16 | Z32: 3595407.5
D33: 427.96 | U33: 427.96
A34: =A32+1 -> 15 | B34: AP 16/0 | C34: DC+6 | E34: =D27+D29+D31+D33 -> 1673.438 | F34: 22°18'18"LT | G34: 517233.3 | H34: 3595005.3 | J34: =J32+1 -> 15 | K34: AP 16/0 | L34: DC+0 | M34: 0 | N34: 0 | O34: 0 | P34: 0 | Q34: 0 | R34: 0 | S34: 0 | T34: 0 | V34: =U27+U29+U31+U33 -> 1673.439 | W34: 320.406 | X34: 22°18'18"LT | Y34: 517233.3 | Z34: 3595005.3
D35: 285.948 | U35: 285.948 | AA35: 11 KV,Road,LTLine Crossing
A36: =A34+1 -> 16 | B36: AP 17/0 | C36: DC+3 | E36: =D35 -> 285.948 | F36: 19°02'28"LT | G36: 517425.65 | H36: 3594793.7 | J36: =J34+1 -> 16 | K36: AP 17/0 | L36: DC+3 | M36: 0 | N36: 0 | O36: 0 | P36: 0 | Q36: 0 | R36: 0 | S36: 0 | T36: 0 | V36: =U35 -> 285.948 | W36: 317.232 | X36: 19°02'28"LT | Y36: 517425.65 | Z36: 3594793.7 | AA36: LTLine to be shifted
D37: 401.159 | U37: 401.159 | AA37: 11KV,66KV,Road,LTLine Crossing
A38: =A36+1 -> 17 | B38: AP 18/0 | C38: DC+3 | E38: =D37 -> 401.159 | F38: 24°05'21"RT | G38: 517777.57 | H38: 3594601.2 | J38: =J36+1 -> 17 | K38: AP 18/0 | L38: DC+0 | M38: 0 | N38: 0 | O38: 0 | P38: 0 | Q38: 0 | R38: 0 | S38: 0 | T38: 0 | V38: =U37 -> 401.159 | W38: 315.046 | X38: 24°05'21"RT | Y38: 517777.57 | Z38: 3594601.2
D39: 345 | U39: 345 | AA39: LTLine Crossing
A40: =A38+1 -> 18 | B40: 18/1 | C40: DA+0 | G40: 517986.28 | H40: 3594326.4 | J40: =J38+1 -> 18 | K40: 18/1 | L40: DA+0 | M40: 0 | N40: 0 | O40: 0 | P40: 0 | Q40: 0 | R40: 0 | S40: 0 | T40: 0 | W40: 316.217 | Y40: 517986.28 | Z40: 3594326.4
D41: 360 | U41: 360.001
A42: =A40+1 -> 19 | B42: 18/2 | C42: DA+0 | G42: 518204.06 | H42: 3594039.8 | J42: =J40+1 -> 19 | K42: 18/2 | L42: DA+0 | M42: 0 | N42: 0 | O42: 0 | P42: 0 | Q42: 0 | R42: 0 | S42: 0 | T42: 0 | W42: 317.215 | Y42: 518204.06 | Z42: 3594039.8
D43: 350.217 | U43: 350.217 | AA43: Canal crosssing
A44: =A42+1 -> 20 | B44: AP 19/0 | C44: DC+0 | E44: =D39+D41+D43 -> 1055.217 | F44: 24°17'20"LT | G44: 518415.92 | H44: 3593760.9 | J44: =J42+1 -> 20 | K44: AP 19/0 | L44: DC+0 | M44: 0 | N44: 0 | O44: 0 | P44: 0 | Q44: 0 | R44: 0 | S44: 0 | T44: 0 | V44: =U39+U41+U43 -> 1055.218 | W44: 317.08 | X44: 24°17'20"LT | Y44: 518415.92 | Z44: 3593760.9
D45: 370 | U45: 369.999 | AA45: LTLine,Road Crossing
A46: =A44+1 -> 21 | B46: 19/1 | C46: DA+0 | G46: 518741.12 | H46: 3593584.5 | J46: =J44+1 -> 21 | K46: 19/1 | L46: DA+0 | M46: 0 | N46: 0 | O46: 0 | P46: 0 | Q46: 0 | R46: 0 | S46: 0 | T46: 0 | W46: 318.753 | Y46: 518741.12 | Z46: 3593584.5
D47: 360 | U47: 360 | AA47: Canal,nalla crosssing
A48: =A46+1 -> 22 | B48: 19/2 | C48: DA+0 | G48: 519057.54 | H48: 3593412.7 | J48: =J46+1 -> 22 | K48: 19/2 | L48: DA+0 | M48: 0 | N48: 0 | O48: 0 | P48: 0 | Q48: 0 | R48: 0 | S48: 0 | T48: 0 | W48: 318.952 | Y48: 519057.54 | Z48: 3593412.7
D49: 358.747 | U49: 358.748 | AA49: Road and LT Line crossing
A50: =A48+1 -> 23 | B50: 20/0 | C50: DB+6 | E50: 0 | G50: 519372.85 | H50: AP24-AP39 | J50: =J48+1 -> 23 | K50: 20/0 | L50: DB+6 | M50: Comments by RKPTL , need to be rectified by M/s. KEC | N50: 1.5 | O50: 1.5 | P50: 1.5 | V50: 0 | W50: 320.649 | Y50: 519372.85 | Z50: 3593241.6
D51: 485.93 | U51: 485.93 | AA51: River Crossing
A52: =A50+1 -> 24 | B52: 21/0 | C52: DD+6 | E52: =D51 -> 485.93 | F52: 39° 17' 49"RT | G52: 519776.1 | H52: 3592970.5 | J52: =J50+1 -> 24 | K52: 21/0 | L52: DD+6 | M52: 1.5 | N52: 1.5 | O52: 1.5 | P52: 1.5 | V52: =U51 -> 485.93 | W52: 319.74 | X52: 39°17'49" RT | Y52: 519776.1 | Z52: 3592970.5
D53: 325 | U53: 325 | AA53: 2 nos LT Line,Cart Track
A54: =A52+1 -> 25 | B54: 21/1 | C54: DA+0 | G54: 519869.96 | H54: 3592659.3 | J54: =J52+1 -> 25 | K54: 21/1 | L54: DA+0 | M54: 0 | N54: 0 | O54: 0 | P54: 0 | W54: 316.858 | Y54: 519869.96 | Z54: 3592659.3 | AA54: LT Line to be shifted
D55: 387.337 | U55: 387.337 | AA55: 11 kv Line Crossing
A56: =A54+1 -> 26 | B56: 22/0 | C56: DC+3 | E56: =D53+D55 -> 712.337 | F56: 15°58'43"LT | G56: 519981.82 | H56: 3592288.5 | J56: =J54+1 -> 26 | K56: 22/0 | L56: DC+3 | M56: 0 | N56: 0 | O56: 0 | P56: 0 | V56: =U53+U55 -> 712.337 | W56: 312.93 | X56: 15°58'43"LT | Y56: 519981.82 | Z56: 3592288.5
D57: 390 | U57: 390 | AA57: 3nos LT Line,Road,11 KV Crossing
A58: =A56+1 -> 27 | B58: 22/1 | C58: DA+3 | G58: 520192.88 | H58: 3591960.6 | J58: =J56+1 -> 27 | K58: 22/1 | L58: DA+3 | M58: 0 | N58: 0 | O58: 0 | P58: 0 | W58: 310.637 | Y58: 520192.88 | Z58: 3591960.6
D59: 388.629 | U59: 388.629 | AA59: LT Line crosiing
A60: =A58+1 -> 28 | B60: 22/2 | C60: DA+3 | G60: 520403.2 | H60: 3591633.8 | J60: =J58+1 -> 28 | K60: 22/2 | L60: DA+3 | M60: 0 | N60: 0 | O60: 0 | P60: 0 | W60: 306.671 | Y60: 520403.2 | Z60: 3591633.8
D61: 398.45 | U61: 398.45 | AA61: 2 nos LT Line Crossing
A62: =A60+1 -> 29 | B62: 23/0 | C62: DB+0 | E62: =D57+D59+D61 -> 1177.079 | F62: 9°30'47"LT | G62: 520618.83 | H62: 3591298.7 | J62: =J60+1 -> 29 | K62: 23/0 | L62: DB+0 | M62: 0 | N62: 0 | O62: 0 | P62: 0 | V62: =U57+U59+U61 -> 1177.079 | W62: 303.472 | X62: 9°30'47"LT | Y62: 520618.83 | Z62: 3591298.7
D63: 419.999 | U63: 435.999 | AA63: Road and LT Line Crossing
A64: =A62+1 -> 30 | B64: 23/1 | C64: DA+6 | G64: 520901.38 | H64: 3590987.9 | J64: =J62+1 -> 30 | K64: 23/1 | L64: DA+6 | M64: 0 | N64: 0 | O64: 0 | P64: 0 | W64: 299.951 | Y64: 520912.14 | Z64: 3590976.1
D65: 400 | U65: 384 | AA65: Road,LT Line,11 KV Line Crossing
A66: =A64+1 -> 31 | B66: 23/2 | C66: DA+3 | G66: 521170.46 | H66: 3590692 | J66: =J64+1 -> 31 | K66: 23/2 | L66: DA+3 | M66: 0 | N66: 0 | O66: 0 | P66: 0 | W66: 296.476 | Y66: 521170.46 | Z66: 3590692
D67: 420 | U67: 420 | AA67: LT Line Crossing
A68: =A66+1 -> 32 | B68: 23/3 | C68: DA+3 | G68: 521453.01 | H68: 3590381.2 | J68: =J66+1 -> 32 | K68: 23/3 | L68: DA+3 | M68: 0 | N68: 0 | O68: 0 | P68: 0 | W68: 293.587 | Y68: 521453.01 | Z68: 3590381.2
D69: 410 | U69: 410 | AA69: 2 nos LT Line Crossing
A70: =A68+1 -> 33 | B70: 23/4 | C70: DA+3 | G70: 521728.82 | H70: 3590077.9 | J70: =J68+1 -> 33 | K70: 23/4 | L70: DA+3 | M70: 0 | N70: 0 | O70: 0 | P70: 0 | W70: 290.264 | Y70: 521728.82 | Z70: 3590077.9
D71: 407.25 | U71: 407.25 | AA71: 2 LT Line,Nalla Crossing
A72: =A70+1 -> 34 | B72: 23/5 | C72: DA+3 | G72: 522002.79 | H72: 3589776.6 | J72: =J70+1 -> 34 | K72: 23/5 | L72: DA+3 | M72: 0 | N72: 0 | O72: 0 | P72: 0 | W72: 286.229 | Y72: 522002.79 | Z72: 3589776.6
D73: 397.702 | U73: 397.702 | AA73: 11 KV,Nalla,Road Crossing
A74: =A72+1 -> 35 | B74: 24/0 | C74: DC+0 | E74: =D63+D65+D67+D69+D71+D73 -> 2454.951 | F74: 26° 06' 39"RT | G74: 522270.33 | H74: 3589482.3 | J74: =J72+1 -> 35 | K74: 24/0 | L74: DC+3 | M74: 0 | N74: 0 | O74: 0 | P74: 0 | V74: =U63+U65+U67+U69+U71+U73 -> 2454.951 | W74: 284.901 | X74: 26°6'39"RT | Y74: 522270.33 | Z74: 3589482.3
D75: 310.147 | U75: 366.004 | AA75: 2 nos LT Line, Road Crossing
A76: =A74+1 -> 36 | B76: 25/0 | C76: DD+0 | E76: =D75 -> 310.147 | F76: 35° 11' 52"LT | G76: 522356.69 | H76: 3589184.4 | J76: =J74+1 -> 36 | K76: 25/0 | L76: DD+0 | M76: 0 | N76: 0 | O76: 0 | P76: 0 | V76: =U75 -> 366.004 | W76: 282.934 | X76: 36°50'56"LT | Y76: 522372.24 | Z76: 3589130.8
D77: 374.999 | U77: 372.4 | AA77: Nalla Crossing
A78: =A76+1 -> 37 | B78: 25/1 | C78: DA+0 | G78: 522649.61 | H78: 3588950.3 | J78: =J76+1 -> 37 | K78: 25/1 | L78: DA+0 | M78: 0 | N78: 0 | O78: 0 | P78: 0 | W78: 282.874 | Y78: 522669.71 | Z78: 3588906.7
D79: 330 | U79: 311.866 | AA79: Drain, 2nos LT Line,Road Crossing,
A80: =A78+1 -> 38 | B80: 25/2 | C80: DA+0 | G80: 522907.39 | H80: 3588744.2 | J80: =J78+1 -> 38 | K80: 25/2 | L80: DA+0 | M80: 0 | N80: 0 | O80: 0 | P80: 0 | W80: 283.88 | Y80: 522918.83 | Z80: 3588719.1
D81: 366.046 | U81: 343.763 | AA81: LT Line Crossing
A82: =A80+1 -> 39 | B82: 26/0 | C82: DD+0 | E82: =D77+D79+D81 -> 1071.045 | F82: 49° 51' 22"RT | G82: 523193.32 | H82: 3588515.7 | J82: =J80+1 -> 39 | K82: 26/0 | L82: DD+0 | M82: 0 | N82: 0 | O82: 0 | P82: 0 | V82: =U77+U79+U81 -> 1028.029 | W82: 284.271 | X82: 51°30'37"RT | Y82: 523193.43 | Z82: 3588512.3
D83: 445.757 | U83: 442.371 | AA83: River Crossing
A84: =A82+1 -> 40 | B84: 27/0 | C84: DB+0 | E84: =D83 -> 445.757 | F84: 10° 41' 31"RT | G84: 523205.05 | H84: 3588070.1 | J84: =J82+1 -> 40 | K84: 27/0 | L84: DB+0 | M84: 0 | N84: 0 | O84: 0 | P84: 0 | V84: =U83 -> 442.371 | W84: 299.465 | X84: 10°41'20"RT | Y84: 523205.05 | Z84: 3588070.1
D85: 320 | U85: 360 | AA85: LT Line Crossing
A86: =A84+1 -> 41 | B86: 27/1 | C86: DA+3 | G86: 523153.98 | H86: 3587754.2 | J86: =J84+1 -> 41 | K86: 27/1 | L86: DA+3 | M86: 1 | N86: 1 | O86: 1 | P86: 1 | W86: 295.54 | Y86: 523147.59 | Z86: 3587714.7 | AA86: Contouring Required
D87: 419.739 | U87: 379.739 | AA87: Road Crossing
A88: =A86+1 -> 42 | B88: 28/0 | C88: DC+6 | E88: =D85+D87 -> 739.739 | F88: 27° 47' 33"LT | G88: 523086.98 | H88: 3587339.8 | J88: =J86+1 -> 42 | K88: 28/0 | L88: DC+6 | M88: 2 | N88: 2 | O88: 2 | P88: 2 | V88: =U85+U87 -> 739.739 | W88: 299.027 | X88: 27°47'33"LT | Y88: 523086.98 | Z88: 3587339.8 | AA88: Contouring Required
D89: 445.991 | U89: 445.991 | AA89: 11 KV Line,Road Crossing
A90: =A88+1 -> 43 | B90: 29/0 | C90: DC+9 | E90: =D89 -> 445.991 | F90: 22° 59' 55"LT | G90: 523229.3 | H90: 3586917.2 | J90: =J88+1 -> 43 | K90: 29/0 | L90: DC+9 | M90: 2 | N90: 2 | O90: 2 | P90: 2 | V90: =U89 -> 445.991 | W90: 297.021 | X90: 22°59'55"LT | Y90: 523229.3 | Z90: 3586917.2 | AA90: Contouring Required
D91: 378 | U91: 373 | AA91: LT Line Crossing
A92: =A90+1 -> 44 | B92: 29/1 | C92: DA+0 | G92: 523480.3 | H92: 3586634.5 | J92: =J90+1 -> 44 | K92: 29/1 | L92: DA+0 | M92: 0 | N92: 0 | O92: 0 | P92: 0 | W92: 295.767 | Y92: 523476.98 | Z92: 3586638.3 | AA92: LT Line to be shifted,Contouring Required
D93: 361 | U93: 374
A94: =A92+1 -> 45 | B94: 29/2 | C94: DA+3 | G94: 523720.01 | H94: 3586364.6 | J94: =J92+1 -> 45 | K94: 29/2 | L94: DA+3 | M94: 1 | N94: 1 | O94: 1 | P94: 1 | W94: 287.94 | Y94: 523725.33 | Z94: 3586358.6
D95: 356 | U95: 352
A96: =A94+1 -> 46 | B96: 29/3 | C96: DA+0 | G96: 523956.41 | H96: 3586098.4 | J96: =J94+1 -> 46 | K96: 29/3 | L96: DA+0 | M96: 0 | N96: 0 | O96: 0 | P96: 0 | W96: 296.014 | Y96: 523959.06 | Z96: 3586095.4 | AA96: Conturing Required
D97: 410 | U97: 406
A98: =A96+1 -> 47 | B98: 29/4 | C98: DA+0 | G98: 524228.65 | H98: 3585791.8 | J98: =J96+1 -> 47 | K98: 29/4 | L98: DA+0 | M98: 0 | N98: 0 | O98: 0 | P98: 0 | W98: 298.58 | Y98: 524228.65 | Z98: 3585791.8 | AA98: Conturing Required
D99: 358 | U99: 352 | AA99: 11 KV Line Crossing
A100: =A98+1 -> 48 | B100: 29/5 | C100: DA+0 | G100: 524466.37 | H100: 3585524.2 | J100: =J98+1 -> 48 | K100: 29/5 | L100: DA+0 | M100: 0 | N100: 0 | O100: 0 | P100: 0 | W100: 296.73 | Y100: 524462.39 | Z100: 3585528.6
...

Sheet Approved CS K-S Line
A1: Line: 400 kV D/C Quad Kishenpur-Samba TL
A2: Approved Check Survey Tower Schedule
A3: AS PER DETAIL SURVEY | J3: AS PER CHECK SURVEY
A4: Sr. No. | B4: Tower No. | C4: Type of Tower | D4: Span Length (m) | E4: Section Length (m) | F4: Angle of Deviation | G4: UTM Coordinates | J4: Sr. No. | K4: Tower No. | L4: Type of Tower | M4: Raised Chimney | Q4: Leg Extension | U4: Span Length (m) | V4: Section Length (m) | W4: Reduced Level | X4: Angle of Deviation | Y4: UTM Coordinates | AA4: Crossing/Remarks
G5: Easting | H5: Northing | M5: LEG A | N5: LEG B | O5: LEG C | P5: LEG D | Q5: LEG A | R5: LEG B | S5: LEG C | T5: LEG D | Y5: Easting | Z5: Northing
A6: 1 | B6: AP 78/0 | C6: DC+9 | E6: 0 | F6: 28°55'39"L | G6: 515334.47 | H6: 3621567.2 | J6: 1 | K6: AP 78/0 | L6: DC+9 | M6: 0 | N6: 0 | O6: 0 | P6: 0 | Q6: 1 | R6: 0 | S6: 3 | T6: 3 | V6: 0 | W6: 524.77 | X6: 29°55'53"L | Y6: 515334.47 | Z6: 3621567.1
D7: 361.044 | U7: 340.277
A8: 2 | B8: AP 79/0 | C8: DD+9 | E8: =E6+D7 -> 361.044 | F8: 31°39'03"R | G8: 515034.27 | H8: 3621767.7 | J8: 2 | K8: AP 79/0 | L8: DD+9 | M8: 0 | N8: 0 | O8: 0 | P8: 0 | Q8: 0 | R8: 1 | S8: 0 | T8: 0 | V8: =V6+U7 -> 340.277 | W8: 524.982 | X8: 30°11'47"R | Y8: 515048.27 | Z8: 3621751.2 | AA8: LT LINE TO BE SHIFTED
D9: 374.114 | U9: 392.251 | AA9: NALLA CROSSING
A10: 3 | B10: AP 80/0 | C10: DD+3 | E10: =E8+D9 -> 735.158 | F10: 36°56'25"L | G10: 514878.54 | H10: 3622107.9 | J10: 3 | K10: AP 80/0 | L10: DD+3 | M10: 0 | N10: -1.5 | O10: 0 | P10: 0 | Q10: 0 | R10: 0 | S10: 0 | T10: 1 | V10: =V8+U9 -> 732.528 | W10: 532.688 | X10: 30°16'26"L | Y10: 514869.85 | Z10: 3622100.5
D11: 148.51 | U11: 144.77
A12: 4 | B12: AP 81/0 | C12: DD+18 | E12: =E10+D11 -> 883.668 | F12: 49°18'55"L | G12: 514747.98 | H12: 3622178.7 | J12: 4 | K12: AP 81/0 | L12: DD+18 | M12: 0 | N12: 0 | O12: 0 | P12: 0 | Q12: 0 | R12: 0 | S12: 0 | T12: 2 | V12: =V10+U11 -> 877.298 | W12: 535.86 | X12: 53°31'26"L | Y12: 514747.98 | Z12: 3622178.7
D13: 195.926 | U13: 195.926 | AA13: 220 KV S/C CROSSING(KSN-SRN)
A14: 5 | B14: AP 82/0 | C14: DD+18 | E14: =E12+D13 -> 1079.594 | F14: 5°38'12"R | G14: 514564.89 | H14: 3622108.9 | J14: 5 | K14: AP 82/0 | L14: DD+18 | M14: 0 | N14: 0 | O14: 0 | P14: 0 | Q14: 1 | R14: 3 | S14: 4 | T14: 4 | V14: =V12+U13 -> 1073.224 | W14: 532.66 | X14: 5°38'20"R | Y14: 514564.89 | Z14: 3622108.9
D15: 194.627 | U15: 194.623 | AA15: 220 D/C CROSSING(KSN-SRN)
A16: 6 | B16: AP 83/0 | C16: DD+25 | E16: =E14+D15 -> 1274.221 | F16: 46°40'30"R | G16: 514377.09 | H16: 3622057.8 | J16: 6 | K16: AP 83/0 | L16: DD+25 | M16: 0 | N16: 0 | O16: 0 | P16: 0 | Q16: 0 | R16: 0 | S16: 3 | T16: 0 | V16: =V14+U15 -> 1267.847 | W16: 522.13 | X16: 46°40'25"R | Y16: 514377.09 | Z16: 3622057.9
D17: 123.478 | U17: 123.478
A18: 7 | B18: AP 84/0 | C18: DC+9 | E18: =E16+D17 -> 1397.699 | F18: 26°50'39"R | G18: 514271.76 | H18: 3622122.3 | J18: 7 | K18: AP 84/0 | L18: DC+9 | M18: 0 | N18: 0 | O18: 0 | P18: 0 | Q18: 3 | R18: 3 | S18: 3 | T18: 3 | V18: =V16+U17 -> 1391.325 | W18: 525.46 | X18: 26°50'39"R | Y18: 514271.76 | Z18: 3622122.3 | AA18: CONTOUR NOT REQUIRED
D19: 358.138 | U19: 358.134
A20: 8 | B20: AP 85/0 | C20: DC+0 | E20: =E18+D19 -> 1755.837 | F20: 18°33'39"R | G20: 514083.58 | H20: 3622427 | J20: 8 | K20: AP 85/0 | L20: DC+0 | M20: 0 | N20: -1.5 | O20: 0 | P20: 1 | Q20: 0 | R20: 0 | S20: 0 | T20: 0 | V20: =V18+U19 -> 1749.459 | W20: 513.5 | X20: 18°33'34"R | Y20: 514083.58 | Z20: 3622427
D21: 195.995 | U21: 195.99 | AA21: LT LINE,2 NOS 11 KV CROSSING
A22: 9 | B22: AP 86/0 | C22: DD+0 | E22: =E20+D21 -> 1951.832 | F22: 37°33'24"L | G22: 514039.03 | H22: 3622617.9 | J22: 9 | K22: AP 86/0 | L22: DD+0 | M22: 0 | N22: 0 | O22: 1.5 | P22: 0 | Q22: 0 | R22: 0 | S22: 0 | T22: 0 | V22: =V20+U21 -> 1945.449 | W22: 519.05 | Y22: 514039.03 | Z22: 3622617.9
U23: 402.938 | AA23: Cannal,Cart Track Crossing
A25: =A22+1 -> 10 | B25: AP 95/0 | C25: DD+0 | E25: 0 | F25: 49° 37' 37"RT | G25: 511950.67 | H25: 3623917.5 | J25: =J22+1 -> 10 | K25: AP 95/0 | L25: DD+0 | M25: 0 | N25: -1.5 | O25: 0 | P25: 1.5 | Q25: 0 | R25: 0 | S25: 0 | T25: 0 | V25: 0 | W25: 483.848 | X25: 47° 47' 09"RT | Y25: 511953.99 | Z25: 3623920
D26: 216.941 | U26: 215.857 | AA26: LT Line,2 NOS 11KV Line Crossing
A27: =A25+1 -> 11 | B27: AP 96/0 | C27: DC+0 | E27: =E25+D26 -> 216.941 | F27: 23° 11' 17"RT | G27: 511872.02 | H27: 3624119.7 | J27: =J25+1 -> 11 | K27: AP 96/0 | L27: DC-3 | M27: 0 | N27: 0 | O27: 0 | P27: 3 | Q27: 0 | R27: 0 | S27: 1 | T27: 0 | V27: =V25+U26 -> 215.857 | W27: 480.277 | X27: 24° 15' 00"RT | Y27: 511872.02 | Z27: 3624119.7
D28: 166.009 | U28: 166.009 | AA28: LT Line Crossing
A29: =A27+1 -> 12 | B29: AP 97/0 | C29: DC+0 | E29: =E27+D28 -> 382.95 | F29: 25° 05' 24"LT | G29: 511877.62 | H29: 3624285.6 | J29: =J27+1 -> 12 | K29: AP 97/0 | L29: DC-3 | M29: 0 | N29: 0 | O29: 0 | P29: 0 | Q29: 0 | R29: 0 | S29: 0 | T29: 0 | V29: =V27+U28 -> 381.866 | W29: 485.367 | X29: 25° 09' 02"LT | Y29: 511877.62 | Z29: 3624285.6 | AA29: Contour Not Required
D30: 242.696 | U30: 242.696 | AA30: Nalla and LT Line crossing
A31: =A29+1 -> 13 | B31: AP 98/0 | C31: DD+9 | E31: =E29+D30 -> 625.646 | F31: 48° 10' 12"LT | G31: 511782.17 | H31: 3624508.8 | J31: =J29+1 -> 13 | K31: AP 98/0 | L31: DD+9 | M31: 0 | N31: 0 | O31: 0 | P31: 0 | Q31: 2 | R31: 2 | S31: 3 | T31: 2 | V31: =V29+U30 -> 624.562 | W31: 486.733 | X31: 48° 10' 19"LT | Y31: 511782.17 | Z31: 3624508.8
D32: 202.992 | U32: 202.992 | AA32: 132 KV S/C Line Crossing
A33: =A31+1 -> 14 | B33: AP 99/0 | C33: DD+18 | E33: =E31+D32 -> 828.638 | F33: 58° 23' 34"RT | G33: 511589.86 | H33: 3624573.7 | J33: =J31+1 -> 14 | K33: AP 99/0 | L33: DD+18 | M33: 0 | N33: 0 | O33: 0 | P33: 0 | Q33: 0 | R33: 0 | S33: 0 | T33: 0 | V33: =V31+U32 -> 827.554 | W33: 468.882 | X33: 58° 23' 34"RT | Y33: 511589.86 | Z33: 3624573.7 | AA33: Contour Not Required
D34: 155.699 | U34: 155.699
A35: =A33+1 -> 15 | B35: AP 100/0 | C35: DD+9 | E35: =E33+D34 -> 984.337 | F35: 45° 03' 40"RT | G35: 511554.99 | H35: 3624725.5 | J35: =J33+1 -> 15 | K35: AP 100/0 | L35: DD+9 | M35: 0 | N35: 0 | O35: 0 | P35: 0 | Q35: 0 | R35: 0 | S35: 0 | T35: 0 | V35: =V33+U34 -> 983.253 | W35: 468.116 | X35: 45° 03' 40"RT | Y35: 511554.99 | Z35: 3624725.5
D36: 491.503 | U36: 491.503 | AA36: Nalla and LT Line crossing
A37: =A35+1 -> 16 | B37: AP 101/0 | C37: DD+9 | E37: =E35+D36 -> 1475.84 | F37: 34° 37' 48"LT | G37: 511816.34 | H37: 3625141.7 | J37: =J35+1 -> 16 | K37: AP 101/0 | L37: DD+9 | M37: 0 | N37: 0 | O37: 0 | P37: 0 | Q37: 0 | R37: 0 | S37: 0 | T37: 0 | V37: =V35+U36 -> 1474.756 | W37: 482.052 | X37: 34° 37' 48"LT | Y37: 511816.34 | Z37: 3625141.7 | AA37: Contour Not Required
D38: 136.501 | U38: 136.501
A39: =A37+1 -> 17 | B39: AP 102/0 | C39: DD+0 | E39: =E37+D38 -> 1612.341 | F39: 49° 54' 56"LT | G39: 511810.37 | H39: 3625278.1 | J39: =J37+1 -> 17 | K39: AP 102/0 | L39: DD+0 | M39: 0 | N39: 0 | O39: 0 | P39: 0 | Q39: 0 | R39: 1 | S39: 0 | T39: 0 | V39: =V37+U38 -> 1611.257 | W39: 479.213 | X39: 49° 54' 56"LT | Y39: 511810.37 | Z39: 3625278.1
D40: 122.195 | U40: 122.195 | AA40: 11 kv Line Crossing
A41: =A39+1 -> 18 | B41: AP 103/0 | C41: DD+6 | E41: =E39+D40 -> 1734.536 | F41: 37° 03' 00"RT | G41: 511713.53 | H41: 3625352.6 | J41: =J39+1 -> 18 | K41: AP 103/0 | L41: DD+6 | M41: 0 | N41: 0 | O41: 0 | P41: 0 | Q41: 1 | R41: 0 | S41: 0 | T41: 1 | V41: =V39+U40 -> 1733.452 | W41: 476.5 | X41: 37° 03' 00"RT | Y41: 511713.53 | Z41: 3625352.6
D42: 185.672 | U42: 185.672 | AA42: Electrified Railway crossing,11 KV Crossing
A43: =A41+1 -> 19 | B43: AP 104/0 | C43: DD+9 | E43: =E41+D42 -> 1920.208 | F43: 24° 32' 24"LT | G43: 511664.34 | H43: 3625531.7 | J43: =J41+1 -> 19 | K43: AP 104/0 | L43: DD+9 | M43: 0 | N43: 0 | O43: 0 | P43: 0 | Q43: 0 | R43: 0 | S43: 0 | T43: 0 | V43: =V41+U42 -> 1919.124 | W43: 475.575 | X43: 24° 32' 24"LT | Y43: 511664.34 | Z43: 3625531.7 | AA43: Contour Not Required
D44: 303.562 | U44: 303.562
A45: =A43+1 -> 20 | B45: AP 105/0 | C45: DD+0 | E45: =E43+D44 -> 2223.77 | F45: 55° 28' 40"RT | G45: 511469.59 | H45: 3625764.5 | J45: =J43+1 -> 20 | K45: AP 105/0 | L45: DD+0 | M45: 0 | N45: 0 | O45: 0 | P45: 0 | Q45: 0 | R45: 0 | S45: 1 | T45: 0 | V45: =V43+U44 -> 2222.686 | W45: 475.007 | X45: 55° 28' 40"RT | Y45: 511469.59 | Z45: 3625764.5
D46: 287.716 | U46: 287.716 | AA46: 2nos 11KV Line Crossing
A47: =A45+1 -> 21 | B47: AP 106/0 | C47: DB+0 | E47: =E45+D46 -> 2511.486 | F47: 13° 39' 57"RT | G47: 511546.81 | H47: 3626041.7 | J47: =J45+1 -> 21 | K47: AP 106/0 | L47: DB+0 | M47: 0 | N47: 0 | O47: 0 | P47: 0 | Q47: 0 | R47: 0 | S47: 0 | T47: 0 | V47: =V45+U46 -> 2510.402 | W47: 469.175 | X47: 13° 39' 57"RT | Y47: 511546.81 | Z47: 3626041.7 | AA47: Contour Not Required
D48: 425.991 | U48: 425.991
A49: =A47+1 -> 22 | B49: AP 107/0 | C49: DC+0 | E49: =E47+D48 -> 2937.477 | F49: 27° 39' 10"RT | G49: 511754.88 | H49: 3626413.4 | J49: =J47+1 -> 22 | K49: AP 107/0 | L49: DC+0 | M49: -1.5 | N49: -1.5 | O49: 0 | P49: 0 | Q49: 0 | R49: 0 | S49: 0 | T49: 0 | V49: =V47+U48 -> 2936.393 | W49: 457.977 | X49: 27° 39' 10"RT | Y49: 511754.88 | Z49: 3626413.4 | AA49: 2nos LTLine crossing
D50: 141.744 | H50: AP24-AP39 | U50: 141.744
A51: =A49+1 -> 23 | B51: AP 108/0 | C51: DC+0 | E51: =E49+D50 -> 3079.221 | F51: 16° 58' 12"LT | G51: 511873.6 | H51: 3626490.8 | J51: =J49+1 -> 23 | K51: AP 108/0 | L51: DC+0 | M51: 0 | N51: 0 | O51: 0 | P51: 0 | Q51: 0 | R51: 0 | S51: 0 | T51: 0 | V51: =V49+U50 -> 3078.137 | W51: 458.784 | X51: 16° 58' 12"LT | Y51: 511873.6 | Z51: 3626490.8 | AA51: Contour Not Required
D52: 52.346 | U52: 52.346
A53: =A51+1 -> 24 | B53: AP 109/0 | C53: DD+0 | E53: =E51+D52 -> 3131.567 | G53: 511907.19 | H53: 3626531 | J53: =J51+1 -> 24 | K53: AP 109/0 | L53: DD+0 | M53: 0 | N53: 0 | O53: 0 | P53: 0 | Q53: 0 | R53: 0 | S53: 0 | T53: 0 | V53: =V51+U52 -> 3130.483 | W53: 458.578 | Y53: 511907.19 | Z53: 3626531 | AA53: Contour Not Required

Sheet Foundation JS-Line -Jammu
A1: KEC INTERNATIONAL LIMITED | O1: Date: | P1: ='TB-605'!E1 -> 46246
A2: 400 kV Samba- Jalandhar D/C Line(Quad) - Wind Zone - 5-Jammu Portion
A3: FOUNDATION
A5: S.No | B5: Loc No. | C5: Tower Type | D5: Classification | E5: Conc Volume | F5: Start Date | G5: Foundation | M5: Earthing | N5: FDN Status | O5: Gang Name | P5: Gang Strength | Q5: Remark
G6: Excavation | H6: Stub Setting | I6: PCC | J6: Rebar Placing | K6: RCC | L6: Completion Date
A7: 1 | B7: 29/5 | C7: DA+0 | D7: WET | E7: 34.389 | F7: 45866 | G7: 45876 | H7: 45879 | I7: 45879 | J7: 45879 | K7: 45880 | L7: 45880 | M7: 45994 | N7: Completed | O7: Rakesh | P7: 8
A8: =A7+1 -> 2 | B8: 29/4 | C8: DA+0 | D8: DRY | E8: 21.318 | F8: 45880 | G8: 45890 | H8: 45890 | I8: 45891 | J8: 45891 | K8: 45906 | L8: 45906 | M8: 45994 | N8: Completed | O8: Rakesh | P8: 5
A9: =A8+1 -> 3 | B9: 29/3 | C9: DA+0 | D9: DRY | E9: 21.318 | F9: 45900 | G9: 45921 | H9: 45921 | I9: 45922 | J9: 45922 | K9: 45924 | L9: 45924 | N9: Completed | O9: Adishiv | P9: 12 | Q9: Completed & 1 leg 1.5 M RC pending
A10: =A9+1 -> 4 | B10: 27/0 | C10: DB+0 | D10: WET | E10: =65.112+6.59 -> 71.702 | F10: 45907 | G10: 45916 | H10: 45918 | I10: 45918 | J10: 45919 | K10: 45920 | L10: 45920 | M10: 46032 | N10: Completed | O10: Adishiv | P10: 12
A11: =A10+1 -> 5 | B11: 17/0 | C11: DC+3 | D11: FS | E11: 142.45 | F11: 45910 | G11: 45982 | H11: 45983 | I11: 45983 | J11: 45983 | K11: 45984 | L11: 45984 | M11: 45998 | N11: Completed | O11: Md.Farooq | P11: 12 | Q11: Benching work completed on 21.9.25 Pit B- Casting completed. Work on hold since 12th Oct'25 & restart from 07th Nov'25 & completed on 23rd Nov'25
A12: =A11+1 -> 6 | B12: 18/0 | C12: DC+0 | D12: FS | E12: =122.268+12.044 -> 134.312 | F12: 45911 | G12: 45944 | H12: 45944 | I12: 45944 | J12: 45944 | K12: 45946 | L12: 45946 | M12: 45948 | N12: Completed | O12: Md. Sharif | P12: 20
A13: =A12+1 -> 7 | B13: 29/6 | C13: DA+3 | D13: WET | F13: 45940 | G13: 45944 | H13: 45944 | I13: 45945 | J13: 45945 | K13: 45946 | L13: 45946 | M13: 45948 | N13: Completed | O13: Adishiv | P13: 12 | Q13: Intially work started on 26.9.25 but due to high water table work was hold till 3.10.25 and as advised by RKPTL team loc shifted about 60 mtrs and work resumed from 10.10.25 & completed on 16.10.25
A14: =A13+1 -> 8 | B14: 30/3 | C14: DA+6 | D14: PS | F14: 45960 | G14: 45983 | H14: 45984 | I14: 45984 | J14: 45985 | K14: 45985 | L14: 45985 | M14: 45987 | N14: Completed | O14: Kewal Krishan | P14: 9
A15: =A14+1 -> 9 | B15: 23/1 | C15: DA+6 | D15: WET | F15: 45925 | G15: 45965 | H15: 45968 | I15: 45968 | J15: 45969 | K15: 45971 | L15: 45971 | M15: 45997 | N15: Completed | O15: Vishal | P15: 8
A16: =A15+1 -> 10 | B16: 29/1 | C16: DA+0 | D16: WET | F16: 45933 | G16: 45937 | H16: 45939 | I16: 45939 | J16: 45939 | K16: 45940 | L16: 45940 | M16: 45959 | N16: Completed | O16: Adishiv | P16: 12 | Q16: RC Casting done by Anil Sharma on 11.02.2026
A17: 11 | B17: 22/1 | C17: DA+3 | D17: WET | F17: 45940 | G17: 45957 | H17: 45957 | I17: 45957 | J17: 45957 | K17: 45958 | L17: 45958 | M17: 45981 | N17: Completed | O17: ANB Construction | P17: 5
A18: 12 | B18: 15/2 | C18: DA+0 | D18: FS | F18: 45948 | G18: 45970 | H18: 45979 | I18: 45980 | J18: 45980 | K18: 45980 | L18: 45980 | M18: 45998 | N18: Completed | O18: Balwanth Singh | P18: 21
A19: 13 | B19: 31/1 | C19: DA+3 | D19: PS | F19: 45947 | G19: 45957 | H19: 45958 | I19: 45958 | J19: 45959 | K19: 45960 | L19: 45960 | M19: 45981 | N19: Completed | O19: Md. Sharif | P19: 24
A20: 14 | B20: 22/0 | C20: DC+3 | D20: WET | F20: 45948 | G20: 45960 | H20: 45961 | I20: 45961 | J20: 45961 | K20: 45961 | L20: 45961 | M20: 45980 | N20: Completed | O20: Surjeet | P20: 10
A21: 15 | B21: 21/1 | C21: DA+0 | D21: WET | F21: 45958 | G21: 45960 | H21: 45961 | I21: 45961 | J21: 45961 | K21: 45961 | L21: 45961 | M21: 45970 | N21: Completed | O21: Surjeet | P21: 19
A22: =A21+1 -> 16 | B22: 31/3 | C22: DA+0 | D22: PS | F22: 45960 | G22: 45968 | H22: 45970 | I22: 45970 | J22: 45971 | K22: 45972 | L22: 45972 | M22: 45972 | N22: Completed | O22: Md. Sharif | P22: 12
A23: =A22+1 -> 17 | B23: 22/2 | C23: DA+3 | D23: WET | F23: 45959 | G23: 45971 | H23: 45973 | I23: 45973 | J23: 45973 | K23: 45974 | L23: 45974 | M23: 45981 | N23: Completed | O23: ANB Construction | P23: 8
A24: =A23+1 -> 18 | B24: 15/1 | C24: DA+0 | D24: PS | F24: 45967 | G24: 45974 | H24: 45978 | I24: 45978 | J24: 45978 | K24: 45978 | L24: 45978 | M24: 45993 | N24: Completed | O24: Balwanth Singh | P24: 21
A25: =A24+1 -> 19 | B25: 40/0 | C25: DC+3 | D25: PS | F25: 45970 | G25: 45991 | H25: 45993 | I25: 45993 | J25: 45994 | K25: 45994 | L25: 45994 | M25: 46006 | N25: Completed | O25: Pawan Kumar Shama | P25: 15
A26: =A25+1 -> 20 | B26: 20/0 | C26: DB+6 | D26: WET | F26: 45973 | G26: 45986 | H26: 45989 | I26: 45989 | J26: 45990 | K26: 45991 | L26: 45991 | M26: 45995 | N26: Completed | O26: Surjeet | P26: 8
A27: =A26+1 -> 21 | B27: 27/1 | C27: DA+3 | D27: WET | F27: 45975 | G27: 45978 | H27: 45983 | I27: 45983 | J27: 45984 | K27: 45984 | L27: 45984 | M27: 45998 | N27: Completed | O27: Md.Sharif | P27: 40 | Q27: RC Casting Pending
A28: =A27+1 -> 22 | B28: AP32 | C28: DB+0 | D28: FS | F28: 45973 | G28: 45982 | H28: 45983 | I28: 45984 | J28: 45984 | K28: 45987 | L28: 45987 | M28: 45993 | N28: Completed | O28: Md.Sharif
A29: =A28+1 -> 23 | B29: 23/0 | C29: DB+0 | D29: FS | F29: 45976 | G29: 45997 | H29: 45998 | I29: 45998 | J29: 45999 | K29: 111743 | L29: 46000 | M29: 46002 | N29: Completed | O29: ANB Construction | P29: 9
A30: =A29+1 -> 24 | B30: 30/5 | C30: DA+9 | D30: PS | F30: 45977 | G30: 45989 | H30: 45990 | I30: 45990 | J30: 45990 | K30: 45990 | L30: 45990 | M30: 45996 | N30: Completed | O30: Akram | P30: 15
A31: =A30+1 -> 25 | B31: 40/1 | C31: DA+3 | D31: WET | F31: 45977 | G31: 45990 | H31: 45991 | I31: 45991 | J31: 45991 | K31: 45991 | L31: 45991 | M31: 45997 | N31: Completed | O31: Thakur Cosnt | P31: 7
A32: =A31+1 -> 26 | B32: 19/2 | C32: DA+0 | D32: FS | F32: 45984 | G32: 46002 | H32: 46002 | I32: 46004 | J32: 46004 | K32: 46004 | L32: 46004 | M32: 46007 | N32: Completed | O32: Balwanth Singh | P32: 9
A33: =A32+1 -> 27 | B33: 18/1 | C33: DA+0 | D33: PS | F33: 45986 | G33: 45996 | H33: 45997 | I33: 45997 | J33: 45997 | K33: 45997 | L33: 45997 | M33: 45998 | N33: Completed | O33: Md.Farooq | P33: 12
A34: =A33+1 -> 28 | B34: AP28 | C34: DC+6 | D34: WET | F34: 45988 | G34: 45989 | H34: 45992 | I34: 45992 | J34: 45992 | K34: 45995 | L34: 45995 | M34: 45994 | N34: Completed | O34: Md. Sharif | P34: 35
A35: =A34+1 -> 29 | B35: 30/2 | C35: DA+0 | D35: PS | F35: 45988 | G35: 46000 | H35: 46001 | I35: 46001 | J35: 46001 | K35: 46003 | L35: 46003 | M35: 46007 | N35: Completed | O35: Kewal Krishan | P35: 8
A36: =A35+1 -> 30 | B36: 23/4 | C36: DA+3 | D36: FS | F36: 45991 | G36: 46019 | H36: 46021 | I36: 46022 | J36: 46022 | K36: 46022 | L36: 46022 | M36: 46029 | N36: Completed | O36: Anil Sharma | P36: 7 | Q36: Pit B, C, D- Casting Completed Pit A- Prop Setting/PCC
A37: =A36+1 -> 31 | B37: 29/0 | C37: DC+9 | D37: WET | F37: 45994 | G37: 45997 | H37: 45998 | I37: 45999 | J37: 46000 | K37: 46001 | L37: 46001 | M37: 46003 | N37: Completed | O37: Md. Sharif | P37: 28
A38: =A37+1 -> 32 | B38: 23/5 | C38: DA+3 | D38: FS | F38: 45994 | G38: 46011 | H38: 46012 | I38: 46012 | J38: 46012 | K38: 46012 | L38: 46012 | M38: 46105 | N38: Completed | O38: Balwanth Singh | P38: 20
A39: =A38+1 -> 33 | B39: 39/2 | C39: DA+0 | D39: FS | F39: 45996 | G39: 46003 | H39: 46003 | I39: 46004 | J39: 46004 | K39: 46004 | L39: 46004 | M39: 46006 | N39: Completed | O39: Pawan Kumar Shama | P39: 17
A40: =A39+1 -> 34 | B40: 30/4 | C40: DA+0 | D40: FS | F40: 45996 | G40: 46009 | H40: 46010 | I40: 46010 | J40: 46010 | K40: 46010 | L40: 46010 | M40: 46014 | N40: Completed | O40: Akram | P40: 15
A41: =A40+1 -> 35 | B41: AP33 | C41: DC+0 | D41: FS | F41: 46000 | G41: 46019 | H41: 46022 | I41: 46022 | J41: 46022 | K41: 46022 | L41: 46022 | M41: 46007 | N41: Completed | O41: Adishiv | P41: 8 | Q41: Pit A,D,C - Casting Completed Pit B- Excavation Completed
A42: =A41+1 -> 36 | B42: AP19 | C42: DC+0 | D42: FS | F42: 46001 | G42: 46013 | H42: 46014 | I42: 46014 | J42: 46014 | K42: 46015 | L42: 46015 | M42: 46012 | N42: Completed | O42: Md.Farooq | P42: 12
A43: =A42+1 -> 37 | B43: AP43 | C43: DD+3 | D43: WET | F43: 46002 | G43: 46011 | H43: 46012 | I43: 46014 | J43: 46014 | K43: 46016 | L43: 46016 | M43: 46025 | N43: Completed | O43: Thakur Cosnt | P43: 16
A44: =A43+1 -> 38 | B44: AP45 | C44: DB+0 | D44: WET | F44: 46003 | G44: 46011 | H44: 46013 | I44: 46013 | J44: 46014 | K44: 46014 | L44: 46014 | M44: 46016 | N44: Completed | O44: Md. Sharif | P44: 28
A45: =A44+1 -> 39 | B45: 31/2 | C45: DA+0 | D45: FS | F45: 46007 | G45: 46015 | H45: 46016 | I45: 46016 | J45: 46018 | K45: 46018 | L45: 46018 | M45: 46041 | N45: Completed | O45: Gulam | P45: 12
A46: =A45+1 -> 40 | B46: 46/1 | C46: DA+0 | D46: PS | F46: 46008 | G46: 46015 | H46: 46015 | I46: 46016 | J46: 46016 | K46: 46016 | L46: 46016 | M46: 46024 | N46: Completed | O46: Pawan Kumar Shama | P46: 17
A47: =A46+1 -> 41 | B47: AP31 | C47: DB+0 | D47: FS | F47: 46010 | G47: 46033 | H47: 46038 | I47: 46038 | J47: 46038 | K47: 46040 | L47: 46040 | M47: 46024 | N47: Completed | O47: Akram | P47: 15
A48: =A47+1 -> 42 | B48: AP16 | C48: DC+0 | D48: FS | F48: 46026 | G48: 46043 | H48: 46046 | I48: 46046 | J48: 46047 | K48: 46047 | L48: 46047 | N48: Completed | O48: Balwanth Singh | P48: 20 | Q48: Pit B,C,D - Casting Completed
A49: =A48+1 -> 43 | B49: 18/2 | C49: DA+6 | D49: FS | F49: 46016 | G49: 46028 | H49: 46029 | I49: 46029 | J49: 46029 | K49: 46030 | L49: 46030 | M49: 46044 | N49: Completed | O49: Md.Farooq | P49: 12
A50: =A49+1 -> 44 | B50: AP26 | C50: DD+0 | D50: FS | F50: 46015 | G50: 46026 | H50: 46027 | I50: 46029 | J50: 46029 | K50: 46030 | L50: 46030 | M50: 46099 | N50: Completed | O50: Balwanth Singh | P50: 20
A51: =A50+1 -> 45 | B51: 43/1 | C51: DA+6 | D51: FS | F51: 46018 | G51: 46024 | H51: 46024 | I51: 46024 | J51: 46025 | K51: 46026 | L51: 46026 | M51: 46044 | N51: Completed | O51: Thakur Cosnt | P51: 16
A52: =A51+1 -> 46 | B52: 31/4 | C52: DA+3 | D52: FS | F52: 46020 | G52: 46029 | H52: 46030 | I52: 46030 | J52: 46030 | K52: 46031 | L52: 46031 | M52: 46032 | N52: Completed | O52: Gulam | P52: 12
A53: =A52+1 -> 47 | B53: 46/3 | C53: DA+0 | D53: FS | F53: 46020 | G53: 46029 | H53: 46031 | I53: 46031 | J53: 46031 | K53: 46031 | L53: 46031 | M53: 46032 | N53: Completed | O53: Pawan Kumar Shama | P53: 17
A54: =A53+1 -> 48 | B54: AP30 | C54: DB+0 | D54: FS | F54: 46026 | G54: 46043 | H54: 46051 | I54: 46051 | J54: 46051 | K54: 46053 | L54: 46053 | M54: 46111 | N54: Completed | O54: Akram | P54: 18
A55: =A54+1 -> 49 | B55: 43/2 | C55: DA+0 | D55: FS | F55: 46029 | G55: 46033 | H55: 46034 | I55: 46034 | J55: 46034 | K55: 46034 | L55: 46034 | M55: 46043 | N55: Completed | O55: Thakur Cosnt | P55: 16
A56: =A55+1 -> 50 | B56: 32/1 | C56: DA+6 | D56: FS | F56: 46030 | G56: 46051 | H56: 46052 | I56: 46052 | J56: 46052 | K56: 46052 | L56: 46052 | M56: 46055 | N56: Completed | O56: Anil Sharma | P56: 7
A57: =A56+1 -> 51 | B57: 33/1 | C57: DA+0 | D57: FS/FS(SD) | F57: 46031 | G57: 46148 | H57: 46149 | I57: 46149 | J57: 46149 | K57: 46149 | L57: 46149 | M57: 46151 | N57: Completed | O57: Adishiv/Thakur Const-1 | P57: 10
A58: =A57+1 -> 52 | B58: 25/2 | C58: DA+0 | D58: FS | F58: 46033 | G58: 46042 | H58: 46043 | I58: 46043 | J58: 46043 | K58: 46043 | L58: 46043 | M58: 46054 | N58: Completed | O58: Balwanth Singh | P58: 20
A59: =A58+1 -> 53 | B59: 45/2 | C59: DA+0 | D59: PS | F59: 46034 | G59: 46042 | H59: 46043 | I59: 46043 | J59: 46043 | K59: 46043 | L59: 46043 | M59: 46061 | N59: Completed | O59: Pawan Kumar Shama | P59: 12
A60: =A59+1 -> 54 | B60: 19/1 | C60: DA+0 | D60: FS | F60: 46034 | G60: 46041 | H60: 46042 | I60: 46042 | J60: 46042 | K60: 46042 | L60: 46042 | M60: 46044 | N60: Completed | O60: Md.Farooq | P60: 10
A61: =A60+1 -> 55 | B61: 31/5 | C61: DA+3 | D61: FS | F61: 46036 | G61: 46044 | H61: 46044 | I61: 46044 | J61: 46044 | K61: 46044 | L61: 46044 | M61: 46044 | N61: Completed | O61: Gulam | P61: 10
A62: =A61+1 -> 56 | B62: 50A/7 | C62: DA+6 | D62: PS | F62: 46053 | G62: 46066 | H62: 46066 | I62: 46066 | J62: 46066 | K62: 46067 | L62: 46067 | M62: 46076 | O62: Wani Const | P62: 8
A63: =A62+1 -> 57 | B63: 44/3 | C63: DA+0 | D63: FS | F63: 46038 | G63: 46042 | H63: 46043 | I63: 46043 | J63: 46043 | K63: 46043 | L63: 46043 | M63: 46077 | N63: Completed | O63: Thakur Cosnt | P63: 16
A64: =A63+1 -> 58 | B64: 44/2 | C64: DA+0 | D64: FS | F64: 46051 | G64: 46059 | H64: 46059 | I64: 46059 | J64: 46060 | K64: 46060 | L64: 46060 | M64: 46078 | N64: Completed | O64: Thakur Cosnt | P64: 16
A65: =A64+1 -> 59 | B65: AP21 | C65: DD+6 | D65: WET | F65: 46051 | G65: 46079 | H65: 46080 | I65: 46080 | J65: 46080 | K65: 46080 | L65: 46080 | N65: Completed | O65: Akram | P65: 18
A66: =A65+1 -> 60 | B66: 45/1 | C66: DA+3 | D66: PS | F66: 46051 | G66: 46057 | H66: 46058 | I66: 46058 | J66: 46058 | K66: 46058 | L66: 46058 | M66: 46078 | N66: Completed | O66: Pawan Kumar Shama | P66: 12
A67: =A66+1 -> 61 | B67: AP15 | C67: DD+18 | D67: WET | F67: 46053 | G67: 46059 | H67: 46059 | I67: 46059 | J67: 46059 | K67: 46061 | L67: 46061 | M67: 46106 | N67: Completed | O67: Balwanth Singh | P67: 20
A68: =A67+1 -> 62 | B68: AP12 | C68: DD+30 | D68: WET /PS | F68: 46056 | G68: 46070 | H68: 46071 | I68: 46071 | J68: 46071 | K68: 46073 | L68: 46073 | N68: Completed | O68: Gulam | P68: 10
A69: =A68+1 -> 63 | B69: 25/1 | C69: DA+0 | D69: FS | F69: 46058 | G69: 46065 | H69: 46065 | I69: 46065 | J69: 46065 | K69: 46066 | L69: 46066 | M69: 46079 | N69: Completed | O69: Balwanth Singh | P69: 20
A70: =A69+1 -> 64 | B70: AP35 | C70: DD+0 | D70: FS | F70: 46058 | G70: 46153 | H70: 46163 | I70: 46163 | J70: 46174 | K70: 46176 | L70: 46176 | M70: 46176 | N70: Completed | O70: Adishiv | P70: 5
A71: =A70+1 -> 65 | B71: AP46 | C71: DB+0 | D71: FS | F71: 46063 | G71: 46073 | H71: 46073 | I71: 46073 | J71: 46073 | K71: 46073 | L71: 46073 | M71: 46147 | N71: Completed | O71: Pawan Kumar Shama | P71: 12
A72: =A71+1 -> 66 | B72: AP44 | C72: DB+0 | D72: PS | F72: 46064 | G72: 46073 | H72: 46073 | I72: 46073 | J72: 46073 | K72: 46073 | L72: 46073 | M72: 46098 | N72: Completed | O72: Thakur Cosnt | P72: 16
A73: =A72+1 -> 67 | B73: AP25 | C73: DD+0 | D73: FS | F73: 46068 | G73: 46078 | H73: 46078 | I73: 46078 | J73: 46078 | K73: 46078 | L73: 46078 | M73: 46099 | N73: Completed | O73: Balwanth Singh | P73: 20
A74: =A73+1 -> 68 | B74: 29/2 | C74: DA+3 | D74: PS (SD) | F74: 46066 | G74: 46086 | H74: 46088 | I74: 46088 | J74: 46088 | K74: 46088 | L74: 46088 | M74: 46094 | N74: Completed | O74: Anil Sharma | P74: 8
A75: =A74+1 -> 69 | B75: 50A/8 | C75: DA+0 | D75: PS | F75: 46070 | G75: 46078 | H75: 46078 | I75: 46078 | J75: 46078 | K75: 46078 | L75: 46078 | M75: 46094 | N75: Completed | O75: Wani Const | P75: 8
A76: =A75+1 -> 70 | B76: 44/1 | C76: DA+0 | D76: PS | F76: 46076 | G76: 46079 | H76: 46080 | I76: 46080 | J76: 46080 | K76: 46080 | L76: 46080 | M76: 46082 | N76: Completed | O76: Thakur Cosnt | P76: 16
A77: =A76+1 -> 71 | B77: 33/2 | C77: DA+0 | D77: PS | F77: 46076 | G77: 46089 | H77: 46090 | I77: 46090 | J77: 46090 | K77: 46090 | L77: 46090 | N77: Completed | O77: Gulam | P77: 10
A78: =A77+1 -> 72 | B78: 46/5 | C78: DA+6 | D78: FS | F78: 46076 | G78: 46086 | H78: 46086 | I78: 46086 | J78: 46086 | K78: 46086 | L78: 46086 | M78: 46099 | N78: Completed | O78: Pawan Kumar Shama | P78: 12
A79: =A78+1 -> 73 | B79: 50A/3 | C79: DA+3 | D79: PS (SD) | F79: 46082 | G79: 46086 | H79: 46087 | I79: 46087 | J79: 46087 | K79: 46087 | L79: 46087 | M79: 46099 | N79: Completed | O79: Wani Const | P79: 8
A80: =A79+1 -> 74 | B80: AP14 | C80: DB+9 | D80: DFR | F80: 46082 | G80: 46086 | H80: 46089 | I80: 46089 | J80: 46089 | K80: 46089 | L80: 46089 | M80: 46105 | N80: Completed | O80: Balwanth Singh | P80: 20
A81: =A80+1 -> 75 | B81: AP24 | C81: DC+3 | D81: PS | F81: 46082 | G81: 46095 | H81: 46095 | I81: 46095 | J81: 46095 | K81: 46096 | L81: 46096 | M81: 46105 | N81: Completed | O81: Balwanth Singh | P81: 20
A82: =A81+1 -> 76 | B82: 43/3 | C82: DA+3 | D82: PS | F82: 46086 | G82: 46088 | H82: 46089 | I82: 46089 | J82: 46089 | K82: 46089 | L82: 46089 | M82: 46100 | N82: Completed | O82: Thakur Cosnt | P82: 16
A83: =A82+1 -> 77 | B83: 43/4 | C83: DA+0 | D83: PS(SD) | F83: 46089 | G83: 46101 | H83: 46102 | I83: 46102 | J83: 46102 | K83: 46102 | L83: 46102 | M83: 46104 | N83: Completed | O83: Thakur Cosnt | P83: 16
A84: =A83+1 -> 78 | B84: 46/4 | C84: DA+0 | D84: FS | F84: 46089 | G84: 46092 | H84: 46092 | I84: 46092 | J84: 46092 | K84: 46092 | L84: 46092 | M84: 46100 | N84: Completed | O84: Pawan Kumar Shama | P84: 12
A85: =A84+1 -> 79 | B85: AP34 | C85: DB+0 | D85: FS | F85: 46111 | G85: 46134 | H85: 46136 | I85: 46137 | J85: 46137 | K85: 46137 | L85: 46137 | M85: 46143 | N85: Completed | O85: Gulam | P85: 10
A86: =A85+1 -> 80 | B86: 46/2 | C86: DA+0 | D86: PS(SD) | F86: 46094 | G86: 46108 | H86: 46109 | I86: 46109 | J86: 46109 | K86: 46109 | L86: 46109 | M86: 46111 | N86: Completed | O86: Pawan Kumar Shama | P86: 12
A87: =A86+1 -> 81 | B87: 15/3 | C87: DA+9 | D87: FS | F87: 46094 | G87: 46110 | H87: 46111 | I87: 46111 | J87: 46111 | K87: 46111 | L87: 46111 | M87: 46144 | N87: Completed | O87: Anil Sharma | P87: 10
A88: =A87+1 -> 82 | B88: 38/1 | C88: DA+3 | D88: FS | F88: 46103 | G88: 46110 | H88: 46111 | I88: 46111 | J88: 46111 | K88: 46111 | L88: 46111 | M88: 46120 | N88: Completed | O88: Pawan Kumar Shama-2 | P88: 8
A89: =A88+1 -> 83 | B89: 42/3 | C89: DA+0 | D89: PS | F89: 46106 | G89: 46111 | H89: 46112 | I89: 46112 | J89: 46112 | K89: 46112 | L89: 46112 | M89: 46120 | N89: Completed | O89: Thakur Cosnt | P89: 16
... A92: =A91+1 -> 86 | B92: 40/2 | C92: DA+3 | D92: PS | F92: 46112 | G92: 46124 | H92: 46125 | I92: 46125 | J92: 46125 | K92: 46125 | L92: 46125 | M92: 46147 | N92: Completed | O92: Pawan Sharma-2 | P92: 10
A93: =A92+1 -> 87 | B93: AP7 | C93: DD+30 | D93: WET | F93: 46113 | G93: 46128 | H93: 46133 | I93: 46137 | J93: 46141 | K93: 46141 | L93: 46141 | N93: Completed | O93: Anil Sharma | P93: 10
A94: =A93+1 -> 88 | B94: 42/2 | C94: DA+0 | D94: FS | F94: 46123 | G94: 46127 | H94: 46128 | I94: 46128 | J94: 46128 | K94: 46128 | L94: 46128 | M94: 46143 | N94: Completed | O94: Thakur Cosnt | P94: 14
A95: =A94+1 -> 89 | B95: AP1 | C95: DD+0 | D95: DFR | F95: 46121 | G95: 46129 | H95: 46130 | I95: 46130 | J95: 46130 | K95: 46130 | L95: 46130 | M95: 46143 | N95: Completed | O95: Pawan Sharma-1 | P95: 12
A96: =A95+1 -> 90 | B96: AP6 | C96: DD+9 | D96: WET | F96: 46123 | G96: 46141 | H96: 46142 | I96: 46142 | J96: 46142 | K96: 46142 | L96: 46142 | N96: Completed | O96: Balwanth Singh | P96: 10
A97: =A96+1 -> 91 | B97: AP41 | C97: DD+30 | D97: PS | F97: 46130 | G97: 46141 | H97: 46142 | I97: 46142 | J97: 46142 | K97: 46142 | L97: 46142 | M97: 46148 | N97: Completed | O97: Pawan Sharma-2 | P97: 10
A98: =A97+1 -> 92 | B98: 37/1 | C98: DA+3 | D98: FS | F98: 46136 | G98: 46140 | H98: 46141 | I98: 46141 | J98: 46141 | K98: 46141 | L98: 46141 | M98: 46145 | N98: Completed | O98: Pawan Sharma-1 | P98: 12
A99: =A98+1 -> 93 | B99: AP38 | C99: DB+0 | D99: PS | F99: 46145 | G99: 46155 | H99: 46156 | I99: 46156 | J99: 46156 | K99: 46156 | L99: 46156 | M99: 46158 | N99: Completed | O99: Pawan Sharma-1 | P99: 12
A100: =A99+1 -> 94 | B100: 40/3 | C100: DB+3 | D100: FS | F100: 46147 | G100: 46157 | H100: 46158 | I100: 46158 | J100: 46158 | K100: 46158 | L100: 46158 | M100: 46160 | N100: Completed | O100: Pawan Sharma-2 | P100: 10
A101: =A100+1 -> 95 | B101: 23/2 | C101: DA+3 | D101: FS(SD) | F101: 46147 | G101: 46159 | H101: 46160 | I101: 46160 | J101: 46160 | K101: 46161 | L101: 46161 | N101: Completed | O101: Balwanth Singh | P101: 10
A102: =A101+1 -> 96 | B102: 50A/2 | C102: DA+3 | D102: PS(SD) | F102: 46153 | G102: 46158 | H102: 46159 | I102: 46159 | J102: 46159 | K102: 46159 | L102: 46159 | N102: Completed | O102: Samsad | P102: 21
A103: =A102+1 -> 97 | B103: AP42 | C103: DD+30 | D103: PS | F103: 46151 | G103: 46165 | H103: 46167 | I103: 46167 | J103: 46167 | K103: 46168 | L103: 46168 | N103: Completed | O103: Thakur Cosnt | P103: 14
...

Sheet Erection -Jammu
A1: KEC INTERNATIONAL LIMITED | I1: Date: | J1: ='TB-605'!E1 -> 46246
A2: 400 kV Samba- Jalandhar D/C Line(Quad) - Wind Zone - 5-Jammu Portion
A3: TOWER ERECTION
A5: S.No | B5: Loc No. | C5: Tower Type | D5: Weight MT | E5: Conc Volume | F5: Starting Date | G5: Completion Date | H5: Status | I5: Gang Name | J5: Gang Strength | K5: Final Checking Status | L5: Remark
A7: 1 | B7: 29/5 | C7: DA+0 | D7: 18.339 | E7: 34.389 | F7: 45988 | G7: 45994 | H7: Completed | I7: Raj Labour Suppliers | J7: 23 | K7: Completed
A8: =A7+1 -> 2 | B8: 29/4 | C8: DA+0 | D8: 18.339 | E8: 21.318 | F8: 45996 | G8: 46001 | H8: Completed | I8: Raj Labour Suppliers | J8: 23 | K8: Completed
A9: =A8+1 -> 3 | B9: 27/0 | C9: DB+0 | D9: 27.92 | E9: 21.318 | F9: 46002 | G9: 45982 | H9: Completed | I9: Raj Labour Suppliers | J9: 23 | K9: Completed
A10: 4 | B10: 29/6 | C10: DA+3 | D10: 19.44 | F10: 46013 | G10: 46020 | H10: Completed | I10: Raj Labour Suppliers | J10: 20 | K10: Completed
A11: =A10+1 -> 5 | B11: 15/1 | C11: DA+0 | D11: 18.339 | F11: 46016 | G11: 46027 | H11: Completed | I11: Anbi Construction | J11: 15
A12: =A11+1 -> 6 | B12: 30/3 | C12: DA+6 | D12: 22.68 | F12: 46020 | G12: 46030 | H12: Completed | I12: Raj Labour Suppliers | J12: 20
A13: =A12+1 -> 7 | B13: 15/2 | C13: DA+0 | D13: 18.339 | F13: 46029 | G13: 46038 | H13: Completed | I13: Anbi Construction | J13: 15
A14: =A13+1 -> 8 | B14: 30/5 | C14: DA+9 | D14: 24.149 | F14: 46031 | G14: 46040 | H14: Completed | I14: Raj Labour Suppliers | J14: 20
A15: =A14+1 -> 9 | B15: AP18 | C15: DC+0 | D15: 32.22 | F15: 46040 | G15: 46053 | H15: Completed | I15: Anbi Construction | J15: 21 | K15: Completed
A16: =A15+1 -> 10 | B16: 30/4 | C16: DA+0 | D16: 18.339 | F16: 46040 | G16: 46044 | H16: Completed | I16: Raj Labour Suppliers | J16: 22
A17: =A16+1 -> 11 | B17: 31/1 | C17: DA+3 | D17: 19.44 | F17: 46047 | G17: 46054 | H17: Completed | I17: Raj Labour Suppliers | J17: 22 | K17: Completed
A18: =A17+1 -> 12 | B18: 31/2 | C18: DA+0 | D18: 18.339 | F18: 46054 | G18: 46059 | H18: Completed | I18: Raj Labour Suppliers | J18: 22 | K18: Completed
A19: =A18+1 -> 13 | B19: 19/2 | C19: DA+0 | D19: 18.339 | F19: 46054 | G19: 46060 | H19: Completed | I19: Anbi Construction | J19: 21
A20: =A19+1 -> 14 | B20: 23/1 | C20: DA+0 | D20: 18.339 | F20: 46058 | G20: 46063 | H20: Completed | I20: Kushboo Devi | J20: 21 | L20: Due to row gang idle for 2 days 07-02-2026 to 08-02-2026
A21: =A20+1 -> 15 | B21: 31/3 | C21: DA+0 | D21: 18.339 | F21: 46059 | G21: 46061 | H21: Completed | I21: Raj Labour Suppliers | J21: 22 | K21: Completed
A22: =A21+1 -> 16 | B22: 19/1 | C22: DA+0 | D22: 18.339 | F22: 46061 | G22: 46066 | H22: Completed | I22: Anvi Construction | J22: 21
A23: =A22+1 -> 17 | B23: 31/4 | C23: DA+3 | D23: 19.44 | F23: 46062 | G23: 46066 | H23: Completed | I23: Raj Labour Suppliers | J23: 22 | K23: Completed
A24: =A23+1 -> 18 | B24: AP23 | C24: DB+0 | D24: 27.92 | F24: 46064 | G24: 46068 | H24: Completed | I24: Kushboo Devi | J24: 21
A25: =A24+1 -> 19 | B25: AP32 | C25: DB+0 | D25: =27.921 -> 27.921 | F25: 46066 | G25: 46073 | H25: Completed | I25: Raj Labour Suppliers | J25: 22 | K25: Completed
A26: =A25+1 -> 20 | B26: AP19 | C26: DC+0 | D26: 32.222 | F26: 46066 | G26: 46077 | H26: Completed | I26: Anvi Construction | J26: 21 | K26: Completed
A27: =A26+1 -> 21 | B27: 23/5 | C27: DA+3 | D27: 19.44 | F27: 46068 | G27: 46072 | H27: Completed | I27: Kushboo Devi | J27: 21
A28: =A27+1 -> 22 | B28: 40/1 | C28: DA+3 | D28: 19.44 | F28: 46069 | G28: 46076 | H28: Completed | I28: ASC Infra Pvt Ltd | J28: 26
A29: =A28+1 -> 23 | B29: 45/2 | C29: DA+0 | D29: 18.339 | F29: 46070 | G29: 46078 | H29: Completed | I29: Raju Kumar | J29: =18+5 -> 23
A30: =A29+1 -> 24 | B30: 32/1 | C30: DA+6 | D30: 22.68 | F30: 46073 | G30: 46078 | H30: Completed | I30: Raj Labour Suppliers | J30: 22
A31: =A30+1 -> 25 | B31: 23/4 | C31: DA+3 | D31: 19.44 | F31: 46073 | G31: 46075 | H31: Completed | I31: Kushboo Devi | J31: 21
A32: =A31+1 -> 26 | B32: AP26 | C32: DD+0 | D32: 42.226 | F32: 46075 | G32: 46084 | H32: Completed | I32: Kushboo Devi | J32: 21 | K32: Completed
A33: =A32+1 -> 27 | B33: 39/2 | C33: DA+0 | D33: 18.339 | F33: 46077 | G33: 46081 | H33: Completed | I33: ASC Infra Pvt Ltd | J33: 26
A34: =A33+1 -> 28 | B34: 18/2 | C34: DA+6 | D34: 22.68 | F34: 46077 | G34: 46085 | H34: Completed | I34: Anvi Construction | J34: 21 | K34: Completed
A35: =A34+1 -> 29 | B35: 31/5 | C35: DA+3 | D35: 19.44 | F35: 46088 | G35: 46091 | H35: Completed | I35: Niva Sarkar Mandal | J35: 20 | K35: Completed
A36: =A35+1 -> 30 | B36: AP40 | C36: DC+3 | D36: 33.53 | F36: 46081 | G36: 46089 | H36: Completed | I36: ASC Infra Pvt Ltd | J36: 26
A37: =A36+1 -> 31 | B37: 18/1 | C37: DA+0 | D37: 18.339 | F37: 46086 | G37: 46093 | H37: Completed | I37: Anvi Construction | J37: 21 | K37: Completed
A38: =A37+1 -> 32 | B38: 25/2 | C38: DA+0 | D38: 18.339 | F38: 46086 | G38: 46093 | H38: Completed | I38: Kushboo Devi | J38: 20 | K38: Completed
A39: =A38+1 -> 33 | B39: 44/3 | C39: DA+0 | D39: 18.339 | F39: 46089 | G39: 46093 | H39: Completed | I39: ASC Infra Pvt Ltd | J39: 26
A40: =A39+1 -> 34 | B40: 29/1 | C40: DA+0 | D40: 18.339 | F40: 46090 | G40: 46104 | H40: Completed | I40: Century Engineering | J40: 18
A41: =A40+1 -> 35 | B41: 44/2 | C41: DA+0 | D41: 18.339 | F41: 46093 | G41: 46097 | H41: Completed | I41: ASC Infra Pvt Ltd | J41: 26
A42: =A41+1 -> 36 | B42: 25/1 | C42: DA+0 | D42: 18.339 | F42: 46093 | G42: 46098 | H42: Completed | I42: Kushboo Devi | J42: 20 | K42: Completed
A43: =A42+1 -> 37 | B43: AP33 | C43: DC+0 | D43: 32.22 | F43: 46093 | G43: 46105 | H43: Completed | I43: Niva Sarkar Mandal | J43: 20
A44: =A43+1 -> 38 | B44: AP25 | C44: DD+0 | D44: 42.23 | F44: 46097 | G44: 46106 | H44: Completed | I44: Kushboo Devi | J44: 20 | K44: Completed
A45: =A44+1 -> 39 | B45: 45/1 | C45: DA+3 | D45: 19.44 | F45: 46097 | G45: 46102 | H45: Completed | I45: ASC Infra Pvt Ltd | J45: 20
A46: =A45+1 -> 40 | B46: 44/1 | C46: DA+0 | D46: 18.34 | F46: 46097 | G46: 46105 | H46: Completed | I46: ASC Infra Pvt Ltd | J46: 20
A47: =A46+1 -> 41 | B47: 46/1 | C47: DA+0 | D47: 18.34 | F47: 46104 | G47: 46111 | H47: Completed | I47: Century Engineering | J47: 18
A48: =A47+1 -> 42 | B48: AP44 | C48: DB+0 | D48: 27.92 | F48: 46105 | G48: 46111 | H48: Completed | I48: ASC Infra Pvt Ltd | J48: 20
A49: =A48+1 -> 43 | B49: 33/2 | C49: DA+0 | D49: 18.34 | F49: 46105 | G49: 46110 | H49: Completed | I49: Niva Sarkar Mandal | J49: 20
A50: =A49+1 -> 44 | B50: AP24 | C50: DC+3 | D50: 33.53 | F50: 46106 | G50: 46118 | H50: Completed | I50: Kushboo Devi | J50: 20 | K50: Completed
A51: =A50+1 -> 45 | B51: AP31 | C51: DB+0 | D51: 27.921 | F51: 46110 | G51: 46116 | H51: Completed | I51: Niva Sarkar Mandal | J51: 25 | K51: Completed
A52: =A51+1 -> 46 | B52: 46/4 | C52: DA+0 | D52: 18.339 | F52: 46111 | G52: 46117 | H52: Completed | I52: Century Engineering | J52: 21
A53: =A52+1 -> 47 | B53: 43/3 | C53: DA+3 | D53: 19.442 | F53: 46111 | G53: 46114 | H53: Completed | I53: ASC Infra Pvt Ltd | J53: 24
A54: =A53+1 -> 48 | B54: 43/2 | C54: DA+0 | D54: 18.34 | F54: 46114 | G54: 46118 | H54: Completed | I54: ASC Infra Pvt Ltd | J54: 24
A55: =A54+1 -> 49 | B55: AP17 | C55: DC+3 | D55: 33.53 | F55: 46116 | G55: 46122 | H55: Completed | I55: Kushboo Devi-2 | J55: 15
A56: =A55+1 -> 50 | B56: AP30 | C56: DB+0 | D56: 27.92 | F56: 46116 | G56: 46124 | H56: Completed | I56: Niva Sarkar Mandal | J56: 25 | K56: Completed
A57: =A56+1 -> 51 | B57: 46/5 | C57: DA+6 | D57: 22.68 | F57: 46117 | G57: 46122 | H57: Completed | I57: Century Engineering | J57: 21
A58: =A57+1 -> 52 | B58: 43/1 | C58: DA+6 | D58: 22.68 | F58: 46118 | G58: 46122 | H58: Completed | I58: ASC Infra Pvt Ltd | J58: 24
A59: =A58+1 -> 53 | B59: AP20 | C59: DB+6 | D59: 34.578 | F59: 46118 | G59: 46127 | H59: Completed | I59: Kushboo Devi | J59: 20
A60: =A59+1 -> 54 | B60: 43/4 | C60: DA+0 | D60: 18.34 | F60: 46122 | G60: 46126 | H60: Completed | I60: ASC Infra Pvt Ltd | J60: 24
A61: =A60+1 -> 55 | B61: 15/3 | C61: DA+9 | D61: 24.149 | F61: 46124 | G61: 46131 | H61: Completed | I61: Kushboo Devi-2 | J61: 15
A62: =A61+1 -> 56 | B62: 46/2 | C62: DA+0 | D62: 18.34 | F62: 46126 | G62: 46130 | H62: Completed | I62: ASC Infra Pvt Ltd | J62: 24
A63: =A62+1 -> 57 | B63: AP16 | C63: DC+0 | D63: 32.22 | F63: 46127 | G63: 46132 | H63: Completed | I63: Kushboo Devi | J63: 20
A64: =A63+1 -> 58 | B64: 46/3 | C64: DA+0 | D64: 18.34 | F64: 46130 | G64: 46133 | H64: Completed | I64: ASC Infra Pvt Ltd | J64: 24
A65: =A64+1 -> 59 | B65: 29/2 | C65: DA+3 | D65: 19.44 | F65: 46131 | G65: 46135 | H65: Completed | I65: Kushboo Devi-2 | J65: 15
A66: =A65+1 -> 60 | B66: 50A/7 | C66: DA+6 | D66: 22.68 | F66: 46132 | G66: 46138 | H66: Completed | I66: Kushboo Devi | J66: 20
A67: =A66+1 -> 61 | B67: AP43 | C67: DD+3 | D67: 44.071 | F67: 46133 | G67: 46142 | H67: Completed | I67: ASC Infra Pvt Ltd | J67: 24
A68: =A67+1 -> 62 | B68: 47/1 | C68: DA+0 | D68: 18.34 | F68: 46136 | G68: 46140 | H68: Completed | I68: Kushboo Devi-2 | J68: 22
... A109: =A108+1 -> 103 | B109: AP13 | C109: DD+25 | D109: 79.47435 | F109: 46222 | G109: 46234 | H109: Completed | I109: Kajal Const | J109: 35
A110: =A109+1 -> 104 | B110: AP51 | C110: DD+30 | D110: 94.55548 | F110: 46223 | H110: 5th Section | I110: Vijay B-1 | J110: 25
A111: =A110+1 -> 105 | B111: 50A/6 | C111: DA+3 | D111: 19.442 | F111: 46233 | G111: 46240 | H111: Completed | I111: Vijay B-2 | J111: 24
A112: =A111+1 -> 106 | B112: 50A/5 | C112: DA+0 | D112: 18.34345 | F112: 46240 | H112: 2nd Section | I112: Vijay B-2 | J112: 24 | L112: No Work Due to ROW

Sheet Vertical Chart -JS Line Jammu 
A1: KEC INTERNATIONAL LIMITED
A2: 400 kV Samba- Jalandhar D/C Line(Quad) - Wind Zone - 5-Jammu Portion
A3: Vertical Chart
J4: Complete | L4: =COUNTIF($L$8:$L$256,"Clear") -> 95 | M4: =COUNTIF($M$8:$M$256,"C") -> 83 | N4: =COUNTIF($N$8:$N$256,"C") -> 73 | O4: =COUNTIF($O$8:$O$256,"C") -> 59 | P4: =COUNTIF($P$8:$P$256,"C") -> 0
J5: WIP | M5: =COUNTIF($M$8:$M$256,"WIP") -> 9 | N5: =COUNTIF($N$8:$N$256,"WIP") -> 0 | O5: =COUNTIF($O$8:$O$256,"WIP") -> 3 | P5: =COUNTIF($P$8:$P$256,"WIP") -> 0
A6: S.No | B6: Tower | C6: TOT | D6: Angle of Deviation | E6: Raised Chimney | I6: FDN Classification | J6: Span Length (Mtr) | K6: Section Length (m) | L6: ROW | M6: Foundation | N6: Earthing | O6: Tower Erection | P6: Tack Welding | Q6: Stringing | R6: Remarks
E7: LEG A | F7: LEG B | G7: LEG C | H7: LEG D
A8: 1 | B8: AP5 | C8: DD+0 | D8: 47°01'59"LT | E8: 0 | F8: 0 | G8: 0 | H8: 0 | K8: 0
J9: 119.059
A10: =A8+1 -> 2 | B10: AP6 | C10: DD+9 | D10: 40°54'42"RT | E10: 0 | F10: 0 | G10: 0 | H10: 0 | K10: =J9 -> 119.059 | L10: Clear | M10: WIP
J11: 92.496
A12: =A10+1 -> 3 | B12: AP7 | C12: DD+30 | D12: 47°08'48"LT | E12: 4 | F12: 5 | G12: 4 | H12: 3 | I12: WET | K12: =J11 -> 92.496 | L12: Clear | M12: WIP
J13: 134.988 | R13: 400 KV D/C Line Jalandhar to Samba
A14: =A12+1 -> 4 | B14: AP8 | C14: DD+30 | D14: 41°15'08"RT | E14: 4 | F14: 5 | G14: 4 | H14: 3 | K14: =J13 -> 134.988
J15: 365.176
A16: =A14+1 -> 5 | B16: AP9 | C16: DD+9 | D16: 37°05'47"RT | E16: 0 | F16: 0 | G16: 0 | H16: 0 | K16: =J15 -> 365.176
J17: 236.697 | R17: Railway Crossing Electrified (Jammu/Delhi)
A18: =A16+1 -> 6 | B18: AP10 | C18: DD+9 | D18: 20°40'31"LT | E18: 0 | F18: 0 | G18: 0 | H18: 0 | K18: =J17 -> 236.697
J19: 213.252
A20: =A18+1 -> 7 | B20: AP11 | C20: DD+25 | D20: 51°34'02"RT | E20: 0 | F20: 0 | G20: 0 | H20: 0 | K20: =J19 -> 213.252
J21: 206.593 | R21: 400 KV D/C Line Jalandhar to Samba
A22: =A20+1 -> 8 | B22: AP12 | C22: DD+30 | D22: 47°50'13"LT | E22: 0 | F22: 0 | G22: 0 | H22: 0 | I22: WET/PS | K22: =J21 -> 206.593 | L22: Clear | M22: C
J23: 289.862 | R23: 220 KV D/C Line Samba To Hiranagar
A24: =A22+1 -> 9 | B24: AP13 | C24: DD+25 | D24: 39°08'44"LT | E24: 1.5 | F24: 1.5 | G24: 0 | H24: 0 | K24: =J23 -> 289.862
J25: 402.938
A26: =A24+1 -> 10 | B26: AP14 | C26: DB+9 | D26: 14°33'47"RT | E26: 0 | F26: 0 | G26: 2 | H26: 0 | I26: DFR | K26: =J25 -> 402.938 | L26: Clear | M26: C | N26: C
J27: 284.883 | R27: 220 KV D/C Line Bishnah-Hiranagar
A28: =A26+1 -> 11 | B28: AP15 | C28: DD+18 | D28: 4°57'01"LT | E28: 1.5 | F28: 0 | G28: 0 | H28: 0 | I28: WET | K28: =J27 -> 284.883 | L28: Clear | M28: C | N28: C
J29: 412.199
A30: =A28+1 -> 12 | B30: 15/1 | C30: DA+0 | E30: 0 | F30: 0 | G30: 0 | H30: 0 | I30: PS | L30: Clear | M30: C | N30: C | O30: C
J31: 428.128
A32: =A30+1 -> 13 | B32: 15/2 | C32: DA+0 | E32: 0 | F32: 0 | G32: 0 | H32: 0 | I32: FS | L32: Clear | M32: C | N32: C | O32: C
J33: 405.152
A34: =A32+1 -> 14 | B34: 15/3 | C34: DA+9 | E34: 0 | F34: 0 | G34: 0 | H34: 0 | I34: FS | L34: Clear | M34: C | O34: C
J35: 427.96
A36: =A34+1 -> 15 | B36: AP16 | C36: DC+0 | D36: 22°18'18"LT | E36: 0 | F36: 0 | G36: 0 | H36: 0 | I36: FS | K36: =J29+J31+J33+J35 -> 1673.439 | L36: Clear | M36: C | O36: C
J37: 285.948
A38: =A36+1 -> 16 | B38: AP17 | C38: DC+3 | D38: 19°02'28"LT | E38: 0 | F38: 0 | G38: 0 | H38: 0 | I38: FS | K38: =J37 -> 285.948 | L38: Clear | M38: C | N38: C | O38: C
J39: 401.159 | R39: 66 KV H Pole (Sandhi) Ghagwal To Rajpura
A40: =A38+1 -> 17 | B40: AP18 | C40: DC+0 | D40: 24°05'21"RT | E40: 0 | F40: 0 | G40: 0 | H40: 0 | I40: FS | K40: =J39 -> 401.159 | L40: Clear | M40: C | N40: C | O40: C
J41: 345
A42: =A40+1 -> 18 | B42: 18/1 | C42: DA+0 | E42: 0 | F42: 0 | G42: 0 | H42: 0 | I42: PS | L42: Clear | M42: C | N42: C | O42: C
J43: 360.001
A44: =A42+1 -> 19 | B44: 18/2 | C44: DA+6 | E44: 0 | F44: 0 | G44: 0 | H44: 0 | I44: FS | L44: Clear | M44: C | N44: C | O44: C
J45: 350.217
A46: =A44+1 -> 20 | B46: AP19 | C46: DC+0 | D46: 24°17'20"LT | E46: 0 | F46: 0 | G46: 0 | H46: 0 | I46: FS | K46: =J41+J43+J45 -> 1055.218 | L46: Clear | M46: C | N46: C | O46: C
J47: 369.999
A48: =A46+1 -> 21 | B48: 19/1 | C48: DA+0 | E48: 0 | F48: 0 | G48: 0 | H48: 0 | I48: PS | L48: Clear | M48: C | N48: C | O48: C
J49: 360
A50: =A48+1 -> 22 | B50: 19/2 | C50: DA+0 | E50: 0 | F50: 0 | G50: 0 | H50: 0 | I50: FS | L50: Clear | M50: C | N50: C | O50: C
J51: 358.748
A52: =A50+1 -> 23 | B52: AP20 | C52: DB+6 | D52: 5°25'51"RT | E52: 1.5 | F52: 1.5 | G52: 1.5 | H52: 1.5 | I52: WET | K52: =J47+J49+J51 -> 1088.747 | L52: Clear | M52: C | N52: C | O52: C
J53: 485.93
A54: =A52+1 -> 24 | B54: AP21 | C54: DD+6 | D54: 39°17'49" RT | E54: 1.5 | F54: 1.5 | G54: 1.5 | H54: 1.5 | I54: WET | K54: =J53 -> 485.93 | L54: Clear | M54: C
J55: 325
A56: =A54+1 -> 25 | B56: 21/1 | C56: DA+0 | E56: 0 | F56: 0 | G56: 0 | H56: 0 | I56: WET | L56: Clear | M56: C | N56: C
J57: 387.337
A58: =A56+1 -> 26 | B58: AP22 | C58: DC+3 | D58: 15°58'43"LT | E58: 0 | F58: 0 | G58: 0 | H58: 0 | I58: WET | K58: =J55+J57 -> 712.337 | L58: Clear | M58: C | N58: C
J59: 390
A60: =A58+1 -> 27 | B60: 22/1 | C60: DA+3 | E60: 0 | F60: 0 | G60: 0 | H60: 0 | I60: WET | L60: Clear | M60: C | N60: C
J61: 388.629
A62: 28 | B62: 22/2 | C62: DA+3 | E62: 0 | F62: 0 | G62: 0 | H62: 0 | I62: WET | L62: Clear | M62: C | N62: C
J63: 398.45
A64: 29 | B64: AP23 | C64: DB+0 | D64: 9°30'47"LT | E64: 0 | F64: 0 | G64: 0 | H64: 0 | I64: FS | K64: =J59+J61+J63 -> 1177.079 | L64: Clear | M64: C | N64: C | O64: C
J65: 435.999
A66: 30 | B66: 23/1 | C66: DA+6 | E66: 0 | F66: 0 | G66: 0 | H66: 0 | I66: WET | L66: Clear | M66: C | N66: C | O66: C
J67: 384
A68: 31 | B68: 23/2 | C68: DA+3 | E68: 0 | F68: 0 | G68: 0 | H68: 0 | L68: Clear | M68: WIP
J69: 420
A70: 32 | B70: 23/3 | C70: DA+3 | E70: 0 | F70: 0 | G70: 0 | H70: 0 | L70: Clear
J71: 410
A72: 33 | B72: 23/4 | C72: DA+3 | E72: 0 | F72: 0 | G72: 0 | H72: 0 | I72: FS | L72: Clear | M72: C | N72: C | O72: C
J73: 407.25
A74: 34 | B74: 23/5 | C74: DA+3 | E74: 0 | F74: 0 | G74: 0 | H74: 0 | I74: FS | L74: Clear | M74: C | N74: C | O74: C
J75: 397.702
A76: 35 | B76: AP24 | C76: DC+3 | D76: 26°6'39"RT | E76: 0 | F76: 0 | G76: 0 | H76: 0 | I76: PS | K76: =J65+J67+J69+J71+J73+J75 -> 2454.951 | L76: Clear | M76: C | N76: C | O76: C
J77: 366.004
A78: 36 | B78: AP25 | C78: DD+0 | D78: 36°50'56"LT | E78: 0 | F78: 0 | G78: 0 | H78: 0 | I78: FS | K78: =J77 -> 366.004 | L78: Clear | M78: C | N78: C | O78: C
J79: 372.4
A80: 37 | B80: 25/1 | C80: DA+0 | E80: 0 | F80: 0 | G80: 0 | H80: 0 | I80: PS | L80: Clear | M80: C | N80: C | O80: C
J81: 311.866
A82: 38 | B82: 25/2 | C82: DA+0 | E82: 0 | F82: 0 | G82: 0 | H82: 0 | I82: FS | L82: Clear | M82: C | N82: C | O82: C
J83: 343.763
A84: 39 | B84: AP26 | C84: DD+0 | D84: 51°30'37"RT | E84: 0 | F84: 0 | G84: 0 | H84: 0 | I84: FS | K84: =J79+J81+J83 -> 1028.029 | L84: Clear | M84: C | N84: C | O84: C
J85: 442.371
A86: 40 | B86: AP27 | C86: DB+0 | D86: 10°41'20"RT | E86: 0 | F86: 0 | G86: 0 | H86: 0 | I86: WET | K86: =J85 -> 442.371 | L86: Clear | M86: C | N86: C | O86: C
J87: 360
A88: 41 | B88: 27/1 | C88: DA+3 | E88: 1.5 | G88: 1.5 | H88: 2.5 | I88: WET | L88: Clear | M88: C | N88: C
J89: 379.739
A90: 42 | B90: AP28 | C90: DC+6 | D90: 27°47'33"LT | E90: 1.5 | F90: 2.5 | G90: 1.5 | H90: 1.5 | I90: WET | K90: =J87+J89 -> 739.739 | L90: Clear | M90: C | N90: C
J91: 445.991
A92: 43 | B92: AP29 | C92: DC+9 | D92: 22°59'55"LT | E92: 1.5 | F92: 3 | G92: 3 | H92: 1.5 | I92: WET | K92: =J91 -> 445.991 | L92: Clear | M92: C | N92: C
J93: 373
A94: 44 | B94: 29/1 | C94: DA+0 | E94: 1.5 | F94: 1.5 | G94: 0 | H94: 0 | I94: WET | L94: Clear | M94: C | N94: C | O94: C
J95: 374
A96: 45 | B96: 29/2 | C96: DA+3 | E96: 1 | F96: 1 | G96: 1 | H96: 1 | I96: PS(SD) | L96: Clear | M96: C | N96: C | O96: WIP
J97: 352
A98: 46 | B98: 29/3 | C98: DA+0 | E98: 1.5 | F98: 0 | G98: 0 | H98: 0 | I98: DRY | L98: Clear | M98: C
J99: 406
A100: 47 | B100: 29/4 | C100: DA+0 | E100: 0 | F100: 0 | G100: 0 | H100: 0 | I100: DRY | L100: Clear | M100: C | N100: C | O100: C
...

Sheet Sheet17
B2: S.No | C2: Line | D2: Portion | E2: Line Qty | F2: Foundation Completed | G2: Tower Erection Completed | H2: Tower Erection WIP | I2: Gap between Foundation & Erection | J2: Tower Erection Gangs Available at Site | K2: Remarks
B3: 1 | C3: Samba-Jalandhar | D3: Jammu | E3: 137 | F3: 81 | G3: 51 | H3: 4 | I3: =F3-G3-H3 -> 26 | J3: 5 | K3: 10 locations ROW clear - Work front for 5 gangs i.e; 2 loc per gang 2 Locations -supply of DD18/25/30 Extensions required 5 locations -Crop harvesting required 4 locations under ROW
B4: =B3+1 -> 2 | C4: Samba-Jalandhar | D4: Punjab | E4: 262 | F4: 154 | G4: 66 | H4: 6 | I4: =F4-G4-H4 -> 82 | J4: 7 | K4: 4 locations - ROW Clear 9 Locations - Supply of DD 18/25/30 extensions required 1 locations - Transposition tower supply required Due to standing crop (wheat) at maximum locations farmers are not allowing for tower erection work . Expected for crop harvesting in next 1 week time
B5: =B4+1 -> 3 | C5: Samba-Kishenpur | E5: 116 | F5: 44 | G5: 2 | H5: 1 | I5: =F5-G5-H5 -> 41 | J5: 1 | K5: 8 locations - ROW Clear 27 locations - supply of unequal leg extensions required / DD18/25/30 M extension required 5 locations under ROW

Sheet Stringing JS-Jammu
B1: KEC INTERNATIONAL LIMITED
B2: 400 kV Samba- Jalandhar D/C Line(Quad) - Wind Zone - 5-Jammu Portion
B3: Stringing
B5: S.No | C5: Section | D5: Length Km | E5: TSE/Manual | F5: Insulator Hoisting | H5: Paying Out | J5: Rough Sag | L5: Final Sag | N5: Remarks | O5: Gang | P5: Manpower
F6: Start Date | G6: End Date | H6: Start Date | I6: End Date | J6: Start Date | K6: End Date | L6: Start Date | M6: End Date
B7: 1 | C7: AP25-AP26 | D7: 1.028 | E7: TSE | F7: 46183 | G7: 46185 | H7: 46190 | I7: 46194 | J7: 46190 | K7: 46194 | L7: 46196 | M7: 46197 | N7: F/S Completed | O7: Tariq | P7: 32
B8: =B7+1 -> 2 | C8: AP26-AP27 | D8: 0.442 | E8: Manual | F8: 46187 | G8: 46187 | H8: 46187 | I8: 46189 | J8: 46187 | K8: 46189 | L8: 46190 | M8: 46195 | N8: F/S Completed | O8: Tariq
B9: =B8+1 -> 3 | C9: AP18-AP19 | D9: 1.06 | E9: TSE | F9: 46193 | G9: 46201 | H9: 46210 | I9: 46215 | J9: 46211 | K9: 46215 | L9: 46219 | M9: 46223 | N9: F/S Completed | O9: Janual Sheik | P9: 25
B10: =B9+1 -> 4 | C10: AP24-AP25 | D10: 0.366 | E10: Manual | F10: 46198 | G10: 46199 | H10: 46199 | I10: 46208 | J10: 46200 | K10: 46208 | L10: 46207 | M10: 46209 | N10: F/S Completed | O10: Tariq | P10: 35
B11: =B10+1 -> 5 | C11: AP20-AP21 | D11: 0.486 | E11: Manual | F11: 46203 | G11: 46204 | H11: 46204 | I11: 46205 | J11: 46206 | K11: 46208 | L11: 46237 | M11: 46239 | N11: F/S Completed | O11: Janual Sheik | P11: 25
B12: =B11+1 -> 6 | C12: AP27-AP28 | D12: 0.739 | E12: Manual | F12: 46210 | G12: 46213 | H12: 46214 | I12: 46217 | J12: 46215 | K12: 46217 | L12: 46220 | M12: 46221 | N12: F/S Completed | O12: Tariq | P12: 35
B13: =B12+1 -> 7 | C13: AP19-AP20 | D13: 1.089 | E13: TSE | F13: 46211 | G13: 46213 | H13: 46218 | I13: 46222 | J13: 46219 | K13: 46222 | L13: 46226 | M13: 46228 | N13: F/S Completed | O13: Janual Sheik | P13: 25
B14: =B13+1 -> 8 | C14: AP28-AP29 | D14: 0.446 | E14: Manual | F14: 46218 | G14: 46219 | H14: 46218 | I14: 46219 | J14: 46220 | K14: 46232 | L14: 46234 | M14: 46236 | N14: F/S Completed | O14: Tariq | P14: 35
B15: =B14+1 -> 9 | C15: AP46-AP47 | D15: 2.216 | E15: TSE | F15: 46220 | G15: 46236 | N15: Top Phase Paying Out | O15: Musludin | P15: 80
B16: =B15+1 -> 10 | C16: AP29-AP30 | D16: 2.57 | E16: TSE | F16: 46229 | G16: 46238 | N16: Conductor Payingout and Rough Sag Completed of top RHS | O16: Tariq | P16: 35
B17: =B16+1 -> 11 | C17: AP17-AP18 | D17: =401.159/1000 -> 0.401159 | E17: Manual | F17: 46244 | N17: Back Stay WIP | O17: Gopal Associates (Hot Line Gang) | P17: 20

Sheet Foundation -KS Line
A1: KEC INTERNATIONAL LIMITED | O1: Date: | P1: ='TB-605'!E1 -> 46246
A2: 400 kV Kishenpur -Samba T/L
A3: FOUNDATION
A5: S.No | B5: Loc No. | C5: Tower Type | D5: Classification | E5: Forest/Non Forest | F5: Start Date | G5: Foundation | L5: Completion Date | M5: Status | N5: Earthing | O5: Gang Name | P5: Gang Strength | Q5: Remark
G6: Excavation | H6: Stub Setting | I6: PCC | J6: Rebar Placing | K6: RCC
A7: 1 | B7: 85/0 | C7: DC+0 | D7: DFR | E7: Non Forest | F7: 45931 | G7: 45945 | H7: 45953 | I7: 45953 | J7: 45954 | K7: 45956 | L7: 45956 | M7: Completed | N7: 45970 | O7: Ankush Sharma | P7: 8
A8: 2 | B8: 86/0 | C8: DD+0 | D8: DFR | E8: Non Forest | F8: 45954 | G8: 45967 | H8: 45968 | I8: 45970 | J8: 45970 | K8: 45971 | L8: 45971 | M8: Completed | N8: 45972 | O8: Ankush Sharma | P8: 13
A9: 3 | B9: 106/0 | C9: DB+0 | D9: DFR | E9: Non Forest | F9: 45944 | G9: 45953 | H9: 45960 | I9: 45960 | J9: 45961 | K9: 45961 | L9: 45961 | M9: Completed | N9: 45981 | O9: Naresh | P9: 8
A10: 4 | B10: 28/0 | C10: DC+3 | D10: DFR | E10: Non Forest | F10: 45954 | G10: 45960 | H10: 45967 | I10: 45967 | J10: 45968 | K10: 45969 | L10: 45969 | M10: Completed | N10: 45975 | O10: Asish Gupta | P10: 9
A11: 5 | B11: 27/0 | C11: DB+3 | D11: DFR | E11: Non Forest | F11: 45968 | G11: 45990 | H11: 45991 | I11: 45991 | J11: 45991 | K11: 45991 | L11: 45991 | M11: Completed | N11: 45995 | O11: Asish Gupta | P11: 10
A12: 6 | B12: 25/0 | C12: DB+0 | D12: DFR | E12: Non Forest | F12: 45975 | G12: 45979 | H12: 45981 | I12: 45982 | J12: 22-11-205 | K12: 45983 | L12: 45983 | M12: Completed | N12: 45995
A13: 7 | B13: 97/0 | C13: DC-3 | D13: DFR | E13: Non Forest | F13: 45958 | G13: 45965 | H13: 45988 | I13: 45989 | J13: 45990 | K13: 45990 | L13: 45990 | M13: Completed | N13: 45995 | O13: BS Const | P13: 10
A14: 8 | B14: AP107 | C14: DC+0 | D14: DFR | E14: Non Forest | F14: 45963 | G14: 45979 | H14: 45981 | I14: 45982 | J14: 22-11-205 | K14: 45983 | L14: 45983 | M14: Completed | N14: 45994 | O14: Naresh | P14: 12
A15: 9 | B15: AP79 | C15: DD+9 | D15: DFR | E15: Non Forest | F15: 45971 | G15: 45988 | H15: 45988 | I15: 45988 | J15: 45988 | K15: 45988 | L15: 45988 | M15: Completed | N15: 45999 | O15: Ankush Sharma | P15: 13
A16: 10 | B16: AP33 | C16: DB+6 | D16: DFR | E16: Non Forest | F16: 45975 | G16: 45979 | H16: 45989 | I16: 45989 | J16: 45990 | K16: 45990 | L16: 45990 | M16: Completed | N16: 45994 | O16: Akthar | P16: 10
A17: =A16+1 -> 11 | B17: AP29 | C17: DD-3 | D17: WET | E17: Non Forest | F17: 45984 | G17: 45997 | H17: 45997 | I17: 45997 | J17: 45998 | K17: 45999 | L17: 45999 | M17: Completed | N17: 46024 | O17: Asish Gupta | P17: 10
A18: =A17+1 -> 12 | B18: AP32 | C18: DC-3 | D18: WET | E18: Non Forest | F18: 45987 | G18: 46008 | H18: 46009 | I18: 46009 | J18: 46009 | K18: 46010 | L18: 46010 | M18: Completed | N18: 46012 | O18: Akthar | P18: 10
A19: =A18+1 -> 13 | B19: AP80 | C19: DD+3 | D19: DFR | E19: Non Forest | F19: 45989 | G19: 46009 | H19: 46010 | I19: 46011 | J19: 46012 | K19: 46012 | L19: 46012 | M19: Completed | N19: 46014 | O19: Ankush Sharma | P19: 13
A20: =A19+1 -> 14 | B20: AP105 | C20: DD+0 | D20: DFR | E20: Non Forest | F20: 45993 | G20: 46000 | H20: 46006 | I20: 46006 | J20: 46007 | K20: 46008 | L20: 46008 | M20: Completed | N20: 46009 | O20: Naresh | P20: 12
A21: =A20+1 -> 15 | B21: AP96 | C21: DC-3 | D21: DFR | E21: Non Forest | F21: 45994 | G21: 46009 | H21: 46009 | I21: 46009 | J21: 46012 | K21: 46012 | L21: 46012 | M21: Completed | N21: 46017 | O21: BS Const | P21: 10
A22: =A21+1 -> 16 | B22: 30/1 | C22: DA+0 | D22: WET | E22: Non Forest | F22: 45999 | G22: 46007 | H22: 46007 | I22: 46007 | J22: 46007 | K22: 46008 | L22: 46008 | M22: Completed | N22: 46025 | O22: Asish Gupta | P22: 10
A23: =A22+1 -> 17 | B23: AP43 | C23: DC-3 | D23: DFR | E23: Non Forest | F23: 46012 | G23: 46019 | H23: 46021 | I23: 46022 | J23: 46022 | K23: 46022 | L23: 46022 | M23: Completed | N23: 46024 | O23: Akthar | P23: 10
A24: =A23+1 -> 18 | B24: AP31 | C24: DB+9 | D24: WET | E24: Non Forest | F24: 46012 | G24: 46016 | H24: 46017 | I24: 46017 | J24: 46018 | K24: 46019 | L24: 46019 | M24: Completed | N24: 46032 | O24: Asish Gupta | P24: 10
A25: =A24+1 -> 19 | B25: AP51 | C25: DB+0 | D25: DFR | E25: Non Forest | F25: 46016 | G25: 46019 | H25: 46025 | I25: 46026 | J25: 46026 | K25: 46027 | L25: 46027 | M25: Completed | N25: 46030 | O25: BS Const | P25: 10
A26: =A25+1 -> 20 | B26: AP52 | C26: DC-3 | D26: DFR | E26: Non Forest | F26: 46016 | G26: 46019 | H26: 46021 | I26: 46021 | J26: 46021 | K26: 46025 | L26: 46025 | M26: Completed | N26: 46026 | O26: Naresh | P26: 12
A27: =A26+1 -> 21 | B27: AP54 | C27: DD+9 | D27: DFR | E27: Non Forest | F27: 46016 | G27: 46022 | H27: 46025 | I27: 46026 | J27: 46027 | K27: 46029 | L27: 46029 | M27: Completed | N27: 46034 | O27: Ankush Sharma | P27: 13
A28: =A27+1 -> 22 | B28: AP30 | C28: DD+0 | D28: WET | E28: Non Forest | F28: 46019 | G28: 46031 | H28: 46033 | I28: 46033 | J28: 46033 | K28: 46034 | L28: 46034 | M28: Completed | N28: Completed | O28: Asish Gupta | P28: 10
A29: =A28+1 -> 23 | B29: AP44 | C29: DD-3 | D29: DFR | E29: Non Forest | F29: 46020 | G29: 46034 | H29: 46038 | I29: 46039 | J29: 46039 | K29: 46041 | L29: 46041 | M29: Completed | N29: 46043 | O29: Akthar | P29: 10
A30: =A29+1 -> 24 | B30: AP26 | C30: DB-3 | D30: DFR | E30: Non Forest | F30: 46033 | G30: 46041 | H30: 46041 | I30: 46042 | J30: 46042 | K30: 46043 | L30: 46043 | M30: Completed | N30: 46044 | O30: Asish Gupta | P30: 10
A31: =A30+1 -> 25 | B31: AP81 | C31: DD+18 | D31: WET | E31: Non Forest | F31: 46034 | G31: 46076 | H31: 46078 | I31: 46079 | J31: 46079 | K31: 46079 | L31: 46079 | M31: Completed | N31: Completed | O31: Ankush Sharma | P31: 13
A32: =A31+1 -> 26 | B32: AP8 | C32: DD+0 | D32: DRY | E32: Non Forest | F32: 46037 | G32: 46056 | H32: 46060 | I32: 46060 | J32: 46060 | K32: 46063 | L32: 46063 | M32: Completed | N32: 46064 | O32: Kulbhushan | P32: 6
A33: =A32+1 -> 27 | B33: AP108 | C33: DC+0 | D33: DFR | E33: Non Forest | F33: 46039 | G33: 46053 | H33: 46053 | I33: 46053 | J33: 46053 | K33: 46053 | L33: 46053 | M33: Completed | N33: Completed | O33: Naresh | P33: 12
A34: =A33+1 -> 28 | B34: AP27A | C34: DB+6 | D34: FS | E34: Non Forest | F34: 46040 | G34: 46053 | H34: 46053 | I34: 46053 | J34: 46053 | K34: 46053 | L34: 46053 | M34: Completed | N34: Completed | O34: Asish Gupta | P34: 10
A35: =A34+1 -> 29 | B35: 8/2 | C35: DB+3 | D35: DFR | E35: Non Forest | F35: 46044 | G35: 46053 | H35: 46053 | I35: 46053 | J35: 46053 | K35: 46053 | L35: 46053 | M35: Completed | N35: Completed | O35: Md. Farooq | P35: 6
A36: =A35+1 -> 30 | B36: AP9 | C36: DB+9 | D36: DFR | E36: Non Forest | F36: 46056 | G36: 46079 | H36: 46080 | I36: 46080 | J36: 46080 | K36: 46080 | L36: 46080 | M36: Completed | N36: Completed | O36: Asish Gupta | P36: 10
A37: =A36+1 -> 31 | B37: AP11 | C37: DD+18 | D37: DFR | E37: Non Forest | F37: 46056 | G37: 46076 | H37: 46077 | I37: 46077 | J37: 46077 | K37: 46077 | L37: 46077 | M37: Completed | N37: Completed | O37: Akthar | P37: 10
A38: =A37+1 -> 32 | B38: 8/1 | C38: DB+3 | D38: DFR | E38: Non Forest | F38: 46058 | G38: 46071 | H38: 46071 | I38: 46071 | J38: 46071 | K38: 46071 | L38: 46071 | M38: Completed | N38: Completed | O38: Kulbhushan | P38: 6
A39: =A38+1 -> 33 | B39: 26/1 | C39: DB | D39: DFR | E39: Non Forest | F39: 46060 | G39: 46077 | H39: 46080 | I39: 46080 | J39: 46080 | K39: 46080 | L39: 46080 | M39: Completed | N39: Completed | O39: Asish Gupta | P39: 10
A40: =A39+1 -> 34 | B40: 9/1 | C40: DD+18 | D40: DFR | E40: Non Forest | F40: 46063 | G40: 46079 | H40: 46081 | I40: 46081 | J40: 46081 | K40: 46081 | L40: 46081 | M40: Completed | N40: Completed | O40: Asish Gupta | P40: 10
A41: =A40+1 -> 35 | B41: AP53 | C41: DC+3 | D41: DFR | E41: Non Forest | F41: 46064 | G41: 46072 | H41: 46077 | I41: 46077 | J41: 46079 | K41: 46079 | L41: 46079 | M41: Completed | N41: Completed | O41: BS Const | P41: 10
A42: =A41+1 -> 36 | B42: AP84 | C42: DC+9 | D42: DFR | E42: Non Forest | F42: 46071 | G42: 46076 | H42: 46077 | I42: 46080 | J42: 46080 | K42: 46081 | L42: 46081 | M42: Completed | N42: Completed | O42: Naresh | P42: 10
A43: =A42+1 -> 37 | B43: AP83 | C43: DD+25 | D43: DFR | E43: Non Forest | F43: 46071 | G43: 46105 | H43: 46106 | I43: 46107 | J43: 46107 | K43: 46107 | L43: 46107 | M43: Completed | N43: Completed | O43: Ankush Sharma | P43: 10
A44: =A43+1 -> 38 | B44: AP7 | C44: DC+9 | D44: DFR | E44: Non Forest | F44: 46073 | G44: 46079 | H44: 46080 | I44: 46080 | J44: 46080 | K44: 46080 | L44: 46080 | M44: Completed | N44: Completed | O44: Kulbhushan | P44: 12
... A57: =A56+1 -> 51 | B57: AP104 | C57: DD+9 | D57: DFR | E57: Non Forest | F57: 46131 | G57: 46146 | H57: 46147 | I57: 46147 | J57: 46147 | K57: 46149 | L57: 46149 | M57: Completed | N57: Completed | O57: Naresh | P57: 13
A58: =A57+1 -> 52 | B58: AP45 | C58: DD+9 | D58: DFR | E58: Non Forest | F58: 46131 | G58: 46158 | H58: 46159 | I58: 46171 | J58: 46171 | K58: 46171 | L58: 46171 | M58: Completed | O58: Ganesh | P58: 10
A59: =A58+1 -> 53 | B59: AP49 | C59: DC+9 | D59: DFR | E59: Non Forest | F59: 46133 | G59: 46158 | H59: 46159 | I59: 46162 | J59: 46162 | K59: 46163 | L59: 46163 | M59: Completed | O59: Rumal Singh | P59: 7
A60: =A59+1 -> 54 | B60: AP88A | C60: DD+0 | D60: WET | E60: Non Forest | F60: 46142 | G60: 46159 | H60: 46162 | I60: 46162 | J60: 46162 | K60: 46163 | L60: 46163 | M60: Completed | N60: Completed | O60: Ankush Sharma | P60: 10
A61: =A60+1 -> 55 | B61: AP90 | C61: DD+0 | D61: WET | E61: Non Forest | F61: 46147 | G61: 46167 | H61: 46167 | I61: 46167 | J61: 46168 | K61: 46171 | L61: 46171 | M61: Completed | O61: BS Const | P61: 10
A62: =A61+1 -> 56 | B62: AP103 | C62: DD+6 | D62: WET | E62: Non Forest | F62: 46147 | G62: 46161 | H62: 46164 | I62: 46166 | J62: 46166 | K62: 46173 | L62: 46173 | M62: Completed | O62: Naresh | P62: 13
A63: =A62+1 -> 57 | B63: AP1 | C63: DD+0 | D63: DFR | E63: Non Forest | F63: 46152 | G63: 46171 | H63: 46171 | I63: 46171 | J63: 46173 | K63: 46173 | L63: 46173 | M63: Completed | N63: Completed | O63: Kulbhushan | P63: 10
A64: =A63+1 -> 58 | B64: AP39 | C64: DB+0 | D64: DFR | E64: Forest | F64: 46157 | G64: 46161 | H64: 46162 | I64: 46162 | J64: 46163 | K64: 46164 | L64: 46164 | M64: Completed | O64: Ganesh | P64: 10 | R64: Forest
A65: =A64+1 -> 59 | B65: AP35 | C65: DC+9 | D65: DFR | E65: Forest | F65: 46158 | G65: 46192 | H65: 46194 | I65: 46194 | J65: 46194 | K65: 46196 | L65: 46196 | M65: Completed | O65: RK Singh | P65: 14
A66: =A65+1 -> 60 | B66: AP88B | C66: DD+0 | D66: WET | E66: Non Forest | F66: 46165 | G66: 46178 | H66: 46181 | I66: 46181 | J66: 46181 | K66: 46182 | L66: 46182 | M66: Completed | O66: Ankush Sharma | P66: 11
A67: =A66+1 -> 61 | B67: AP50 | C67: DD+3 | D67: DFR | E67: Forest | F67: 46165 | G67: 46199 | H67: 46200 | I67: 46200 | J67: 46200 | K67: 46202 | L67: 46202 | M67: Completed | O67: Rumal Singh | P67: 7
A68: =A67+1 -> 62 | B68: AP102 | C68: DD+0 | D68: DFR | E68: Non Forest | F68: 46167 | G68: 46178 | H68: 46179 | I68: 46179 | J68: 46182 | K68: 46198 | L68: 46198 | M68: Completed | O68: Naresh | P68: 13
A69: =A68+1 -> 63 | B69: AP89 | C69: DD+9 | D69: WET | E69: Non Forest | F69: 46175 | G69: 46185 | H69: 46185 | I69: 46186 | J69: 46187 | K69: 46190 | L69: 46190 | M69: Completed | O69: BS Const | P69: 11
A70: =A69+1 -> 64 | B70: AP36 | C70: DB+0 | D70: DFR | E70: Forest | F70: 46184 | G70: 46203 | H70: 46210 | I70: 46210 | J70: 46212 | K70: 46214 | L70: 46214 | M70: Completed | O70: RK Singh | P70: 14
A71: =A70+1 -> 65 | B71: AP78 | C71: DC+9 | D71: DFR | E71: Non Forest | F71: 46194 | G71: 46221 | M71: WIP | O71: Naresh | P71: 13 | Q71: Pit D - Casting upto frustrum Pit B,C- Excavation Completed Pit A - Steel Binding
A72: =A71+1 -> 66 | B72: AP70 | C72: DD+9 | D72: DFR | E72: Forest | F72: 46189 | G72: 46202 | H72: 46231 | I72: 46231 | J72: 46232 | K72: 46233 | L72: 46233 | M72: Completed | O72: Ankush Sharma | P72: 13
A73: =A72+1 -> 67 | B73: AP12 | C73: DB+0 | D73: DFR | E73: Forest | F73: 46193 | G73: 46230 | H73: 46231 | I73: 46231 | J73: 46232 | K73: 46233 | L73: 46233 | M73: Completed | O73: Kalbhushan | P73: 13
A74: =A73+1 -> 68 | B74: AP13 | C74: DB+9 | D74: DFR | E74: Forest | F74: 46193 | G74: 46201 | H74: 46201 | I74: 46202 | J74: 46202 | K74: 46203 | L74: 46203 | M74: Completed | O74: Ganesh | P74: 10
A75: =A74+1 -> 69 | B75: AP2 | C75: DD+30 | D75: DFR | E75: Non Forest | F75: 46189 | M75: WIP | O75: Kalbhushan | P75: 10 | Q75: Pit C- Casting upto 1st part chimney Pit B- Casting Completed Pit D- Prop Setting
A76: =A75+1 -> 70 | B76: AP23 | C76: DB-3 | D76: DFR | E76: Forest | F76: 46201 | G76: 46232 | H76: 46236 | I76: 46237 | J76: 46238 | K76: 46243 | L76: 46243 | M76: Completed | O76: Anil Sharma | P76: 10 | Q76: Pit A,B,C-Casting Completed Pit D- Casting upto Pyramid
A77: =A76+1 -> 71 | B77: AP19 | C77: DB+6 | D77: WET | E77: Forest | F77: 46192 | G77: 46217 | H77: 46218 | I77: 46218 | J77: 46219 | K77: 46220 | L77: 46220 | M77: Completed | O77: Balwanth Singh | P77: 13
A78: =A77+1 -> 72 | B78: AP34 | C78: DD+3 | D78: DFR | E78: Forest | F78: 46199 | G78: 46218 | H78: 46219 | I78: 46221 | J78: 46222 | K78: 46230 | L78: 46230 | M78: Completed | O78: RK Singh | P78: 14
A79: =A78+1 -> 73 | B79: AP77 | C79: DD+18 | D79: DFR | E79: Non Forest | F79: 46201 | M79: WIP | O79: BS Const | Q79: Pit B,C - Excavation (Dewatering) Work on hold due to rains and approach road issue
A80: =A79+1 -> 74 | B80: AP41 | C80: DC+6 | D80: DFR | E80: Forest | F80: 46202 | M80: WIP | O80: Darshan | P80: 10 | Q80: Pit A-Casting upto Pyramid Pit B,C,D - Excavation WIP
A81: =A80+1 -> 75 | B81: AP56 | C81: DC+0 | D81: DFR | E81: Forest | F81: 46205 | G81: 46218 | H81: 46220 | I81: 46222 | J81: 46223 | K81: 46230 | L81: 46230 | M81: Completed | O81: KDR Engineering | P81: 8
A82: =A81+1 -> 76 | B82: AP14 | C82: DB-3 | D82: DFR | E82: Forest | F82: 46208 | G82: 46241 | M82: WIP | O82: Ganesh | P82: 10 | Q82: Pit A,B- Casting Completd Pit D-Casting upto Pyramid Pit C- Excavation
A83: =A82+1 -> 77 | B83: AP60 | C83: DB+0 | D83: DFR | E83: Forest | F83: 46208 | M83: WIP | O83: Rumal Singh | P83: 12 | Q83: Pit A, B, D -Excavation WIP Material Shifting WIP
A84: =A83+1 -> 78 | B84: AP48 | C84: DC-3 | D84: DFR | E84: Forest | F84: 46215 | M84: WIP | O84: Darshan | P84: 8 | Q84: Pit C,D - Excavation WIP -Manually Pit A- Prop Setting Pit B- PCC Done Material Shifting WIP
A85: =A84+1 -> 79 | B85: AP20 | C85: DB+0 | D85: DFR | E85: Forest | F85: 46227 | G85: 46238 | H85: 46239 | I85: 46240 | J85: 46241 | M85: WIP | O85: Balwanth Singh | P85: 11 | Q85: Pit A,B- Casting Completed Pit C,D- Casting upto frustrum
A86: =A85+1 -> 80 | B86: AP57 | C86: DC+9 | D86: DFR | E86: Forest | F86: 46233 | M86: WIP | O86: Harsh | P86: 8 | Q86: Pit D- Excavation Completed Pit A - Steel Binding WIP
A87: =A86+1 -> 81 | B87: AP59 | C87: DC-3 | D87: DFR | E87: Forest | F87: 46235 | M87: WIP | O87: Yogesh | P87: 5 | Q87: Pit B,C- Excavation WIP
A88: =A87+1 -> 82 | B88: AP66 | C88: DD+9 | D88: DFR | E88: Forest | M88: WIP | O88: Naresh | Q88: Approach Road Making WIP
A89: =A88+1 -> 83 | B89: AP61 | C89: DC+0 | D89: DFR | E89: Forest | F89: 46240 | M89: WIP | O89: Rumal Singh | Q89: Pit A, D, C - Excavation WIP
A90: =A89+1 -> 84 | B90: AP55 | C90: DC-3 | D90: DFR | E90: Forest | F90: 46237 | M90: WIP | O90: KDR Engineering | P90: 8 | Q90: Pit A, B, - Excavation WIP Material Shifting WIP
A91: =A90+1 -> 85 | B91: AP22 | C91: DC+0 | D91: DFR | E91: Forest | M91: WIP | O91: Anil Sharma | Q91: Approach Road Work WIP
A92: =A91+1 -> 86 | B92: AP18 | C92: DB+6 | D92: DFR | E92: Forest | M92: WIP | O92: Balwanth Singh | P92: 7 | Q92: Marking WIP
A93: =A92+1 -> 87 | B93: AP71 | C93: DD-3 | D93: DFR | E93: Forest | F93: 46240 | M93: WIP | O93: Ankush Sharma | P93: 13 | Q93: Pit A, C - Excavation Completed
A94: =A93+1 -> 88 | B94: AP67 | C94: DC+9 | D94: DFR | E94: Forest | M94: WIP | O94: BS Const | P94: 10 | Q94: Approach Road Making WIP
A95: =A94+1 -> 89 | B95: AP64 | C95: DC-3 | D95: DFR | E95: Forest | F95: 46242 | M95: WIP | O95: Naresh | Q95: Pit A, B - Excavation WIP
A96: =A95+1 -> 90 | B96: AP65 | C96: DC-3 | D96: DFR | E96: Forest | F96: 46244 | M96: WIP | O96: Naresh | Q96: Pit A- Excavation WIP

Sheet Erection -SK
A1: KEC INTERNATIONAL LIMITED | H1: Date: | I1: ='TB-605'!E1 -> 46246
A2: 400kV D/C Samba -Kishenpur TL
A3: TOWER ERECTION
A5: S.No | B5: Loc No. | C5: Tower Type | D5: Weight MT | E5: Starting Date | F5: Completion Date | G5: Status | H5: Gang Name | I5: Gang Strength | J5: Remark
A7: 1 | B7: 30/1 | C7: DA+0 | D7: 18.34 | E7: 46099 | F7: 46105 | G7: Completed | H7: Anvi Construction | I7: 18
A8: =A7+1 -> 2 | B8: AP27A | C8: DB+6 | D8: 34.578 | E8: 46105 | F8: 46112 | G8: Completed | H8: Anvi Construction | I8: 23
A9: =A8+1 -> 3 | B9: AP31 | C9: DB+9 | D9: 36.354 | E9: 46121 | F9: 46163 | G9: Completed | H9: Anvi Construction | I9: 18 | J9: Work restart from 16-05-2026
A10: =A9+1 -> 4 | B10: AP30 | C10: DD+0 | D10: 42.226 | E10: 46163 | F10: 46176 | G10: Completed | H10: Anvi Construction | I10: 18
A11: =A10+1 -> 5 | B11: AP29 | C11: DD-3 | D11: 38.988424 | E11: 46176 | F11: 46186 | G11: Completed | H11: Anvi Construction | I11: 18
A12: =A11+1 -> 6 | B12: AP27 | C12: DB+3 | D12: 29.31 | E12: 46094 | F12: 46200 | G12: Completed | H12: Anvi Construction | I12: 18
A13: =A12+1 -> 7 | B13: 26/1 | C13: DB+9 | D13: 30.035 | E13: 46200 | F13: 46215 | G13: Completed | H13: Anvi Construction | I13: 20
A14: =A13+1 -> 8 | B14: AP43 | C14: DC-3 | D14: 29.865 | E14: 46201 | F14: 46210 | G14: Completed | H14: Kushboo Devi | I14: 22
A15: =A14+1 -> 9 | B15: AP54 | C15: DD+9 | D15: 56.157 | E15: 46202 | F15: 46212 | G15: Completed | H15: Saritha Devi | I15: 24
A16: =A15+1 -> 10 | B16: AP87 | C16: DC+9 | D16: 41.525 | E16: 46208 | F16: 46234 | G16: Completed | H16: Neelkant | I16: 20
A17: =A16+1 -> 11 | B17: AP89 | C17: DD+9 | D17: 56.157 | E17: 46208 | F17: 46220 | G17: Completed | H17: Prem Latha-1 | I17: 30
A18: =A17+1 -> 12 | B18: AP39 | C18: DB+0 | D18: 27.922 | E18: 46208 | F18: 46218 | G18: Completed | H18: Splice Net | I18: 22
A19: =A18+1 -> 13 | B19: AP90 | C19: DD+0 | D19: 41.912 | E19: 46212 | F19: 46227 | G19: Completed | H19: Prem Latha-2 | I19: 25
A20: =A19+1 -> 14 | B20: AP44 | C20: DD-3 | D20: 39.296 | E20: 46210 | F20: 46221 | G20: Completed | H20: Kushboo Devi | I20: 28
A21: =A20+1 -> 15 | B21: AP26 | C21: DB-3 | D21: 26.709 | E21: 46215 | F21: 46230 | G21: Completed | H21: Anvi Construction | I21: 20
... A24: =A23+1 -> 18 | B24: AP33 | C24: DB+6 | D24: 34.634 | E24: 46229 | F24: 46243 | G24: Completed | H24: Kushboo Devi | I24: 28
A25: =A24+1 -> 19 | B25: AP53 | C25: DC+3 | D25: 33.4 | E25: 46230 | G25: Cage 1 | H25: Kauleshwar Mahato | I25: 18
A26: =A25+1 -> 20 | B26: AP85 | C26: DC+0 | D26: 32.066 | E26: 46229 | F26: 46237 | G26: Completed | H26: Prem Latha-2 | I26: 25
A27: =A26+1 -> 21 | B27: 9/1 | C27: DD+18 | D27: 71.31 | E27: 46229 | G27: Cage 2 | H27: Jirwa Devi | I27: 25
A28: =A27+1 -> 22 | B28: AP25 | C28: DB+0 | D28: 27.922 | E28: 46230 | F28: 46244 | G28: Completed | H28: Anvi Construction | I28: 20
A29: =A28+1 -> 23 | B29: AP11 | C29: DD+18 | D29: 71.31 | E29: 46231 | G29: Cage 2 | H29: Jwala Singh | I29: 25
A30: =A29+1 -> 24 | B30: AP88A | C30: DD+0 | D30: 42.254 | E30: 46232 | F30: 46238 | G30: Completed | H30: Prem Latha-1 | I30: 30
A31: =A30+1 -> 25 | B31: AP86 | C31: DD+0 | D31: 42.43 | E31: 46234 | G31: 2nd section | H31: Neelkant | I31: 20
A32: =A31+1 -> 26 | B32: AP10 | C32: DB+9 | D32: 36.355 | E32: 46234 | F32: 46241 | G32: Completed | H32: Kajal Const | I32: 35
A33: =A32+1 -> 27 | B33: AP88B | C33: DD+0 | D33: 42.744 | E33: 46237 | F33: 46246 | G33: Completed | H33: Prem Latha-2 | I33: 25
A34: =A33+1 -> 28 | B34: AP80 | C34: DD+3 | D34: 43.7922 | E34: 46239 | G34: 1st section | H34: Prem Latha-1 | I34: 30
A35: =A34+1 -> 29 | B35: AP35 | C35: DC+9 | D35: 41.283 | E35: 46241 | G35: 1st section | H35: Splice Net | I35: 25
A36: =A35+1 -> 30 | B36: AP13 | C36: DB+9 | D36: 36.355 | E36: 46241 | G36: 3rd section | H36: Kajal Const | I36: 35
A37: =A36+1 -> 31 | B37: AP42 | C37: DB+3 | D37: 29.492 | E37: 46243 | G37: Material Shifting | H37: Kushboo Devi | I37: 28
A38: =A37+1 -> 32 | B38: AP79 | C38: DD+9 | D38: 52.690538 | E38: 46246 | G38: Material Shifting | H38: Prem Latha-2 | I38: 25
A39: =A38+1 -> 33 | B39: AP56 | C39: DC+0 | D39: 31.99 | E39: 46246 | G39: Material Shifting | H39: MD Zalil | I39: 12

Sheet Sheet7
B3: S.No | C3: Loc | D3: TOT | E3: RC | F3: RC | G3: RC | H3: RC
B4: 1 | C4: AP144 | D4: DB+0
B5: =B4+1 -> 2
B6: =B5+1 -> 3
B7: =B6+1 -> 4 | E7: 1 | F7: 1 | G7: 1 | H7: 1
B8: =B7+1 -> 5
B9: =B8+1 -> 6 | C9: AP145 | D9: DB+0 | E9: 2 | F9: 2 | G9: 2 | H9: 2
B10: =B9+1 -> 7
B11: =B10+1 -> 8
B12: =B11+1 -> 9
B13: =B12+1 -> 10
B14: =B13+1 -> 11
B15: =B14+1 -> 12 | I15: Hussain
B16: =B15+1 -> 13 | I16: Hussain
B17: =B16+1 -> 14 | I17: Hussain
B18: =B17+1 -> 15 | I18: Hussain
B19: =B18+1 -> 16
B20: =B19+1 -> 17
B21: =B20+1 -> 18
B22: =B21+1 -> 19 | E22: 1 | F22: 1 | G22: 1 | H22: 1
B23: =B22+1 -> 20
B24: =B23+1 -> 21
B25: =B24+1 -> 22
B26: =B25+1 -> 23
B27: =B26+1 -> 24
B28: =B27+1 -> 25
B29: =B28+1 -> 26
B30: =B29+1 -> 27
B31: =B30+1 -> 28
B32: =B31+1 -> 29
B33: =B32+1 -> 30
B34: =B33+1 -> 31
... B48: =B47+1 -> 45
B49: =B48+1 -> 46 | C49: AP66 | D49: DC+0
B50: =B49+1 -> 47 | C50: AP67 | D50: DD+0
B51: =B50+1 -> 48 | C51: 67/1 | D51: DA+0
B52: =B51+1 -> 49 | C52: 67/2 | D52: DA+0
B53: =B52+1 -> 50 | C53: 67/3 | D53: DA+0
B54: =B53+1 -> 51 | C54: AP68 | D54: DB+0
B55: =B54+1 -> 52
B56: =B55+1 -> 53
B57: =B56+1 -> 54
B58: =B57+1 -> 55 | C58: 69/3 | D58: DA+0
B59: =B58+1 -> 56 | C59: AP70 | D59: DC+3

Sheet Sheet8
C2: Tower | D2: Structure | E2: Supplied Qty till date | F2: Material DI received and will dispatch in 1 week | G2: Total | I2: Tower | J2: Supplied Qty | K2: Material Under Transit | L2: Total
C3: DA | D3: Basic Tower Body | E3: =34+39+12+2 -> 87 | G3: =E3+F3 -> 87 | I3: DA+0 | J3: 34 | L3: =J3+K3 -> 34
D4: +0MBE | E4: =34+12+2 -> 48 | G4: =E4+F4 -> 48 | I4: DA+3 | J4: 39 | L4: =J4+K4 -> 39
D5: +3MBE | E5: 39 | G5: =E5+F5 -> 39 | I5: DA+6 | J5: 12 | L5: =J5+K5 -> 12
D6: +6MBE | E6: 12 | G6: =E6+F6 -> 12 | I6: DA+9 | J6: 2 | L6: =J6+K6 -> 2
D7: +9MBE | E7: 2 | G7: =E7+F7 -> 2 | L7: =J7+K7 -> 0
C9: DB | D9: Basic Tower Body | E9: =10+2+1 -> 13 | F9: 16 | G9: =E9+F9 -> 29 | I9: DB+0 | J9: 10 | K9: 14 | L9: =J9+K9 -> 24
D10: +0MBE | E10: 11 | F10: 16 | G10: =E10+F10 -> 27 | I10: DB+3 | J10: 2 | L10: =J10+K10 -> 2
D11: +3MBE | E11: 2 | G11: =E11+F11 -> 2 | I11: DB+6 | J11: 1 | L11: =J11+K11 -> 1
D12: +6MBE | E12: 1 | G12: =E12+F12 -> 1 | I12: DB+9 | K12: 2 | L12: =J12+K12 -> 2
D13: +9MBE | F13: 2 | G13: =E13+F13 -> 2 | L13: =J13+K13 -> 0
C15: DC | D15: Basic Tower Body | E15: 5 | G15: =E15+F15 -> 5 | I15: DC+0 | L15: =J15+K15 -> 0
D16: +0MBE | E16: 2 | G16: =E16+F16 -> 2 | I16: DC+3 | J16: 3 | L16: =J16+K16 -> 3
D17: +3MBE | E17: 3 | G17: =E17+F17 -> 3 | I17: DC+6 | J17: 2 | L17: =J17+K17 -> 2
D18: +6MBE | E18: 2 | G18: =E18+F18 -> 2 | I18: DC+9 | L18: =J18+K18 -> 0
D19: +9MBE | L19: =J19+K19 -> 0
C21: DD | D21: Basic Tower Body | E21: 5 | F21: =20-1 -> 19 | G21: =E21+F21 -> 24 | I21: DD+0 | K21: 13 | L21: =J21+K21 -> 13
D22: +0MBE | E22: 2 | F22: 18 | G22: =E22+F22 -> 20 | I22: DD+3 | J22: 3 | K22: 1 | L22: =J22+K22 -> 4
D23: +3MBE | E23: 3 | F23: 1 | G23: =E23+F23 -> 4 | I23: DD+6 | J23: 2 | L23: =J23+K23 -> 2
D24: +6MBE | E24: 2 | G24: =E24+F24 -> 2 | I24: DD+9 | K24: 5 | L24: =J24+K24 -> 5
D25: +9MBE | F25: 5 | G25: =E25+F25 -> 5 | L25: =J25+K25 -> 0
D26: +18MBE | L26: =J26+K26 -> 0
D27: +25MBE | L27: =J27+K27 -> 0
D28: +30MBE | L28: =J28+K28 -> 0
C29: Total | E29: =E21+E15+E9+E3 -> 110 | F29: =F21+F15+F9+F3 -> 35 | G29: =G21+G15+G9+G3 -> 145 | I29: Total | J29: =SUM(J3:J28) -> 110 | K29: =SUM(K3:K28) -> 35 | L29: =SUM(L3:L28) -> 145

Sheet Material Status SK
A1: 400 kV Kishenpur-Samba D/C line(Quad) - Wind Zone - 5-Jammu Portion
A2: Tower Erection Plan- Aug-26 | H2: Material Shifting from Store in % | I2: Material Shifting from Site to Loc in % | J2: Material Headloading Mode | K2: Status | N2: At 04:00 PM | O2: Date :- 12.08.2026
A3: S.No | B3: Loc | C3: Tower | D3: MT | E3: Gang | F3: Start Date | G3: End Date | M3: Dispatched | N3: Balance
A4: 1 | B4: AP25 | C4: DB+0 | D4: 27.92172 | E4: Anvi Const | F4: 46235 | G4: =F4+10 -> 46245 | H4: 100 | I4: 100 | J4: Tractor / Manual | K4: Completed
A5: =A4+1 -> 2 | B5: AP33 | C5: DB+6 | D5: 34.63 | E5: Kushboo Devi | F5: 46233 | G5: =F5+10 -> 46243 | H5: 100 | I5: 100 | J5: Tractor / Manual | K5: Completed
A6: =A5+1 -> 3 | B6: AP42 | C6: DB+3 | D6: 29.492056 | F6: 46244 | G6: =F6+9 -> 46253 | H6: 60 | I6: 30 | J6: Tractor / Manual | K6: Material Shifting | M6: 3 | N6: 2
A7: =A6+1 -> 4 | B7: AP32 | C7: DC-3 | D7: 29.865 | F7: 46254 | G7: =F7+9 -> 46263 | H7: 25 | J7: Tractor | K7: Material Shifting
A8: =A7+1 -> 5 | B8: AP36 | C8: DB+0 | D8: 27.91 | E8: Splice Net | F8: 46230 | G8: =F8+10 -> 46240 | H8: 100 | I8: 100 | J8: Tractor / Manual | K8: Completed
A9: =A8+1 -> 6 | B9: AP35 | C9: DC+9 | D9: 41.283 | F9: 46242 | G9: =F9+9 -> 46251 | H9: 100 | I9: 100 | J9: Tractor / Manual | K9: ='Erection -SK'!G35 -> 1st section
A10: =A9+1 -> 7 | B10: AP34 | C10: DD+3 | D10: 43.198092 | F10: 46253 | G10: =F10+9 -> 46262 | H10: 100 | I10: 20 | J10: Tractor / Manual
A11: =A10+1 -> 8 | B11: AP88A | C11: DD+0 | D11: 42.253864 | E11: Prem Latha-1 | F11: 46233 | G11: =F11+10 -> 46243 | H11: 100 | I11: 100 | J11: Tractor | K11: Completed
A12: =A11+1 -> 9 | B12: AP88B | C12: DD+0 | D12: 42.74411 | F12: 46244 | G12: =F12+9 -> 46253 | H12: 100 | I12: 100 | J12: Manual | K12: Completed
A13: =A12+1 -> 10 | B13: AP49 | C13: DC+9 | D13: 41.525 | F13: 46254 | G13: =F13+9 -> 46263 | J13: Tractor / Manual
A14: =A13+1 -> 11 | B14: AP85 | C14: DC+0 | D14: 32.07 | E14: Prem Latha-2 | F14: 46233 | G14: =F14+10 -> 46243 | H14: 100 | I14: 100 | J14: Tractor | K14: Completed
A15: =A14+1 -> 12 | B15: AP81 | C15: DD+18 | D15: 71.310346 | F15: 46249 | G15: 46257 | H15: 10 | J15: Tractor / Manual | K15: Material Shifting | M15: 1 | N15: 7
A16: =A15+1 -> 13 | B16: AP50 | C16: DD+3 | D16: 43.338 | F16: 46244 | G16: =F16+10 -> 46254 | J16: Tractor / Manual
A17: =A16+1 -> 14 | B17: AP86 | C17: DD+0 | D17: 42.429764 | E17: Neelkant | F17: 46242 | G17: =F17+12 -> 46254 | H17: 100 | I17: 100 | J17: Tractor | K17: ='Erection -SK'!G31 -> 2nd section
A18: =A17+1 -> 15 | B18: AP79 | C18: DD+9 | D18: 52.690538 | E18: Prem Latha-2 | F18: 46235 | G18: =F18+10 -> 46245 | H18: 70 | I18: 50 | J18: Tractor | K18: ='Erection -SK'!G38 -> Material Shifting | M18: 5 | N18: 2
A19: =A18+1 -> 16 | B19: AP80 | C19: DD+3 | D19: 43.79171 | E19: Prem Latha-1 | F19: 46247 | G19: =F19+10 -> 46257 | H19: 100 | I19: 0 | J19: Tractor | K19: ='Erection -SK'!G34 -> 1st section
A20: =A19+1 -> 17 | B20: 9/1 | C20: DD+18 | D20: 71.310346 | E20: Jirwa Devi | F20: 46233 | G20: =F20+15 -> 46248 | H20: 100 | I20: 60 | J20: Tractor | K20: ='Erection -SK'!G27 -> Cage 2
A21: =A20+1 -> 18 | B21: AP28 | C21: DC+3 | D21: 33.547229 | F21: 46246 | G21: =F21+9 -> 46255 | J21: Tractor / Manual
A22: =A21+1 -> 19 | B22: AP23 | C22: DB-3 | D22: 27.935496 | F22: 46256 | G22: =F22+9 -> 46265 | J22: Tractor / Manual
A23: =A22+1 -> 20 | B23: AP19 | C23: DB+6 | D23: 35.48 | F23: 46250 | G23: =F23+10 -> 46260 | J23: Tractor / Manual
A24: =A23+1 -> 21 | B24: AP53 | C24: DC+3 | D24: 33.405018 | E24: Kauleshwar | F24: 46235 | G24: =F24+10 -> 46245 | H24: 100 | I24: 100 | J24: Tractor / Manual | K24: ='Erection -SK'!G25 -> Cage 1
A25: =A24+1 -> 22 | B25: AP52 | C25: DC-3 | D25: 30.932993 | F25: 46247 | G25: =F25+10 -> 46257 | J25: Tractor / Manual
A26: =A25+1 -> 23 | B26: AP11 | C26: DD+18 | D26: 71.310346 | E26: Jwala Singh | F26: 46235 | G26: =F26+15 -> 46250 | H26: 100 | I26: 100 | J26: Dumper/ Tractor | K26: ='Erection -SK'!G29 -> Cage 2
A27: =A26+1 -> 24 | B27: AP12 | C27: DB+0 | D27: 27.921 | F27: 46251 | G27: =F27+10 -> 46261 | J27: Dumper/ Tractor
A28: =A27+1 -> 25 | B28: AP10 | C28: DB+9 | D28: 36.355072 | E28: Kajal Const | F28: 46237 | G28: =F28+9 -> 46246 | H28: 100 | I28: 100 | J28: Dumper/ Tractor | K28: Completed
A29: =A28+1 -> 26 | B29: AP13 | C29: DB+9 | D29: 36.355 | F29: 46239 | G29: =F29+10 -> 46249 | H29: 100 | I29: 40 | J29: Dumper/ Tractor

Sheet Stringing SK
B1: KEC INTERNATIONAL LIMITED
B2: 400 kV Samba- Kishenpur D/C Line(Quad) - Wind Zone - 5
B3: Stringing
B5: S.No | C5: Section | D5: Length Km | E5: TSE/Manual | F5: Insulator Hoisting | H5: Paying Out | J5: Rough Sag | L5: Final Sag | N5: Remarks | O5: Gang | P5: Manpower
F6: Start Date | G6: End Date | H6: Start Date | I6: End Date | J6: Start Date | K6: End Date | L6: Start Date | M6: End Date
B7: 1 | C7: AP25-AP27 | D7: =1081.815/1000 -> 1.081815 | E7: Manual | F7: 46244 | O7: Nogyo Tec (Drawn) | P7: 32

Sheet LILO
A1: KEC INTERNATIONAL LIMITED | O1: Date: | P1: ='TB-605'!E1 -> 46246
A2: LILO Kishtwar - Wind Zone - 2
A3: FOUNDATION
A5: S.No | B5: Loc No. | C5: Tower Type | D5: Classification | E5: Conc Volume | F5: Start Date | G5: Foundation | L5: Completion Date | M5: Status | N5: Earthing | O5: Gang Name | P5: Gang Strength | Q5: Remark
G6: Excavation | H6: Stub Setting | I6: PCC | J6: Rebar Placing | K6: RCC
A7: 1 | B7: AP7 | C7: DDM+E0+0 | D7: DFR | E7: =31.932+4.177 -> 36.109 | F7: 46121 | G7: 46162 | H7: 46163 | I7: 46164 | J7: 46164 | K7: 46166 | L7: 46166 | M7: Completed | O7: Zaffar | P7: 12 | Q7: Pit A- RR Wall Completed on 7-8-2026
A8: =A7+1 -> 2 | B8: AP8 | C8: DDM+E6+3 | D8: DFR | E8: =31.932+4.177 -> 36.109 | F8: 46109 | G8: 46198 | H8: 46199 | I8: 46199 | J8: 46200 | K8: 46200 | L8: 46200 | M8: Completed | O8: Bittu | P8: 8 | Q8: Pit A- RC WIP
A9: =A8+1 -> 3 | B9: AP9 | C9: DDM+E0+0 | D9: DFR | E9: =31.932+4.177 -> 36.109 | F9: 46110 | G9: 46233 | H9: 46233 | I9: 46244 | J9: 46245 | K9: 46245 | L9: 46245 | M9: Completed | O9: Bhat Const. | P9: 12 | Q9: RC Pending
A10: =A9+1 -> 4 | B10: AP10 | C10: DDM+E6+3 | D10: DFR | E10: =31.932+4.177 -> 36.109 | F10: 46140 | M10: WIP | O10: Bhat Const. | Q10: Pit A,B,D- Excavation WIP
A11: =A10+1 -> 5 | B11: 8/1 | C11: DDM+E6+3 | D11: DFR | E11: =31.932+4.177 -> 36.109 | F11: 46160 | G11: 46193 | H11: 46194 | I11: 46194 | J11: 46195 | K11: 46195 | L11: 46195 | M11: Completed | O11: Bittu | P11: 5 | Q11: RC Pending
A12: =A11+1 -> 6 | B12: AP6 | C12: DDM+E0+0 | D12: DFR | E12: =31.932+4.177 -> 36.109 | F12: 46150 | G12: 46192 | H12: 46196 | I12: 46196 | J12: 46197 | K12: 46197 | L12: 46197 | M12: Completed | O12: Zaffar | P12: 12 | Q12: RC Pending
A13: =A12+1 -> 7 | B13: AP5 | C13: DDM+E0+0 | D13: DFR | E13: =31.932+4.177 -> 36.109 | F13: 46179 | G13: 46188 | H13: 46202 | I13: 46202 | J13: 46202 | K13: 46203 | L13: 46203 | M13: Completed | N13: 46205 | O13: TR Kotwal | P13: 12
A14: =A13+1 -> 8 | B14: AP2 | C14: DDM+E6+3 | D14: DFR | E14: =31.932+4.177 -> 36.109 | F14: 46187 | M14: WIP | O14: Zaffar | P14: 12 | Q14: Pit C- Casting upto step box Pit D- Bar Binding WIP
A15: =A14+1 -> 9 | B15: AP11 | C15: DDM+E6+3 | D15: DFR | E15: =31.932+4.177 -> 36.109 | F15: 46193 | G15: 46243 | M15: WIP | O15: Abdul Jabbar | P15: 14 | Q15: Pit A- Casting Completed Pit C- Casting 1st part chimney Pit B - Excavation Completed Pit D - Casting 1st part chimney
A16: =A15+1 -> 10 | B16: AP12 | C16: DDM+E40+0 | D16: DFR | E16: =31.932+4.177 -> 36.109 | F16: 46201 | G16: 46233 | M16: WIP | O16: Abdul Jabbar | Q16: Pit A,B,C,D- Excavation Completed
A17: =A16+1 -> 11 | B17: AP4 | C17: DDM+E6+3 | D17: DFR | E17: =31.932+4.177 -> 36.109 | F17: 46202 | G17: 46208 | H17: 46243 | I17: 46244 | J17: 46245 | K17: 46245 | L17: 46245 | M17: Completed | O17: TR Kotwal | P17: 16 | Q17: RC Pending
A18: =A17+1 -> 12 | B18: AP3 | C18: DDM+E6+3 | D18: DFR | E18: =31.932+4.177 -> 36.109 | F18: 46206 | M18: WIP | O18: TR Kotwal | Q18: Pit B,D - Excavation Completed
A19: =A18+1 -> 13 | B19: AP13 | C19: DDM+40+0 | D19: DFR | E19: =31.932+4.177 -> 36.109 | F19: 46233 | M19: WIP | O19: Abdul Jabbar | P19: 5 | Q19: Pit A- Excavation WIP

Sheet Erection-Punjab
A1: KEC INTERNATIONAL LIMITED | I1: Date: | J1: ='TB-605'!E1 -> 46246
A2: 400 kV Samba- Jalandhar D/C Line(Quad) - Wind Zone - 5- Punjab Portion
A3: TOWER ERECTION
A5: S.No | B5: Loc No. | C5: Tower Type | D5: Weight MT | E5: Conc Volume | F5: Starting Date | G5: Completion Date | H5: Status | I5: Gang Name | J5: Gang Strength | K5: Final Checking Status | L5: Remark
A7: 1 | B7: 89/1 | C7: DA+3 | D7: 19.44 | E7: 34.389 | F7: 46055 | G7: 46059 | H7: Completed | I7: Saritha Devi | J7: 30
A8: =A7+1 -> 2 | B8: 117/3 | C8: DA+0 | D8: 18.339 | F8: 46056 | G8: 46060 | H8: Completed | I8: Poonam Kumari | J8: 34
A9: =A8+1 -> 3 | B9: 95/3 | C9: DA+0 | D9: 18.339 | F9: 46059 | G9: 46061 | H9: Completed | I9: Saritha Devi | J9: 30 | K9: Completed
A10: =A9+1 -> 4 | B10: 97/2 | C10: DA+0 | D10: 18.339 | F10: 46058 | G10: 46062 | H10: Completed | I10: Jwala Singh | J10: 22
A11: =A10+1 -> 5 | B11: 92/2 | C11: DA+6 | D11: 22.68 | E11: 21.318 | F11: 46055 | G11: 46063 | H11: Completed | I11: Dhruv Strategic | J11: 32
A12: =A11+1 -> 6 | B12: 117/1 | C12: DA+0 | D12: 18.339 | F12: 46060 | G12: 46064 | H12: Completed | I12: Poonam Kumari | J12: 34
A13: =A12+1 -> 7 | B13: 95/2 | C13: DA+0 | D13: 18.339 | F13: 46061 | G13: 46064 | H13: Completed | I13: Saritha Devi | J13: 30 | K13: Completed
A14: =A13+1 -> 8 | B14: 97/1 | C14: DA+0 | D14: 18.339 | F14: 46062 | G14: 46065 | H14: Completed | I14: Jwala Singh | J14: 22
A15: =A14+1 -> 9 | B15: 95/4 | C15: DA+0 | D15: 18.339 | F15: 46064 | G15: 46066 | H15: Completed | I15: Saritha Devi | J15: 30 | K15: Completed
A16: =A15+1 -> 10 | B16: 117/2 | C16: DA+3 | D16: 19.44 | F16: 46064 | G16: 46069 | H16: Completed | I16: Poonam Kumari-1 | J16: 34
A17: =A16+1 -> 11 | B17: 92/3 | C17: DA+0 | D17: 18.339 | F17: 46065 | G17: 46069 | H17: Completed | I17: Poonam Kumari-2 | J17: 30
A18: =A17+1 -> 12 | B18: 131/4 | C18: DA+0 | D18: 18.339 | F18: 46065 | G18: 46070 | H18: Completed | I18: ZR Construction | J18: 30
A19: =A18+1 -> 13 | B19: 97/3 | C19: DA+3 | D19: 19.44 | F19: 46065 | G19: 46070 | H19: Completed | I19: Jwala Singh | J19: 22
A20: =A19+1 -> 14 | B20: AP96 | C20: DC+0 | D20: 32.222 | F20: 46066 | G20: 46070 | H20: Completed | I20: Saritha Devi | J20: 30 | K20: Completed
A21: =A20+1 -> 15 | B21: 93/2 | C21: DA+0 | D21: 18.339 | F21: 46070 | G21: 46073 | H21: Completed | I21: Poonam Kumari-2 | J21: 30 | K21: Completed
A22: =A21+1 -> 16 | B22: AP115 | C22: DB+0 | D22: 27.92 | F22: 46069 | G22: 46073 | H22: Completed | I22: Poonam Kumari-1 | J22: 34 | K22: Completed
A23: =A22+1 -> 17 | B23: 98/1 | C23: DA+3 | D23: 19.44 | F23: 46070 | G23: 46073 | H23: Completed | I23: Jwala Singh | J23: 22
A24: =A23+1 -> 18 | B24: 76/1 | C24: DA+0 | D24: 18.339 | F24: 46070 | G24: 46075 | H24: Completed | I24: Rakesh | J24: 23 | K24: Completed
A25: =A24+1 -> 19 | B25: AP94 | C25: DB+0 | D25: 27.92 | F25: 46070 | G25: 46074 | H25: Completed | I25: Saritha Devi | J25: 30 | K25: Completed
A26: =A25+1 -> 20 | B26: 131/5 | C26: DA+3 | D26: 19.44 | F26: 46070 | G26: 46075 | H26: Completed | I26: ZR Construction | J26: 30
A27: =A26+1 -> 21 | B27: 118/1 | C27: DA+0 | D27: 18.339 | F27: 46074 | G27: 46076 | H27: Completed | I27: Poonam Kumari-1 | J27: 34
A28: =A27+1 -> 22 | B28: AP98 | C28: DB+3 | D28: 29.492 | F28: 46075 | G28: 46079 | H28: Completed | I28: Jwala Singh | J28: 22
A29: =A28+1 -> 23 | B29: AP93 | C29: DC+0 | D29: 32.222 | F29: 46073 | G29: 46078 | H29: Completed | I29: Poonam Kumari-2 | J29: 30 | K29: Completed
A30: =A29+1 -> 24 | B30: AP95 | C30: DC+3 | D30: 33.53 | F30: 46074 | G30: 46078 | H30: Completed | I30: Saritha Devi | J30: 30 | K30: Completed
A31: =A30+1 -> 25 | B31: 76/2 | C31: DA+3 | D31: 19.44 | F31: 46075 | G31: 46080 | H31: Completed | I31: Rakesh | J31: 23 | K31: Completed
A32: =A31+1 -> 26 | B32: 131/3 | C32: DA+3 | D32: 19.44 | F32: 46076 | G32: 46080 | H32: Completed | I32: ZR Construction | J32: 30
A33: =A32+1 -> 27 | B33: AP117 | C33: DB+0 | D33: 27.92 | F33: 46077 | G33: 46081 | H33: Completed | I33: Poonam Kumari-2 | J33: 30 | K33: Completed
A34: =A33+1 -> 28 | B34: 87/2 | C34: DA+3 | D34: 19.44 | F34: 46078 | G34: 46081 | H34: Completed | I34: Saritha Devi | J34: 30
A35: =A34+1 -> 29 | B35: 92/1 | C35: DA+3 | D35: 19.44 | F35: 46078 | G35: 46081 | H35: Completed | I35: Poonam Kumari-2 | J35: 30
A36: =A35+1 -> 30 | B36: AP99 | C36: DB+0 | D36: 27.92 | F36: 46079 | G36: 46083 | H36: Completed | I36: Jwala Singh | J36: 22
A37: =A36+1 -> 31 | B37: 71/2 | C37: DA+9 | D37: 24.149 | F37: 46080 | G37: 46086 | H37: Completed | I37: Rakesh | J37: 23 | K37: Completed
A38: =A37+1 -> 32 | B38: 131/1 | C38: DA+3 | D38: 19.44 | F38: 46080 | G38: 46083 | H38: Completed | I38: ZR Construction | J38: 30
A39: =A38+1 -> 33 | B39: AP97 | C39: DD+3 | D39: 44.071 | F39: 46082 | G39: 46090 | H39: Completed | I39: Saritha Devi | J39: 30 | K39: Completed
A40: =A39+1 -> 34 | B40: AP106 | C40: DD+6 | D40: 52.663 | F40: 46082 | G40: 46094 | H40: Completed | I40: Poonam Kumari | J40: 30
A41: =A40+1 -> 35 | B41: 103/1 | C41: DA+0 | D41: 18.339 | F41: 46083 | G41: 46088 | H41: Completed | I41: Jwala Singh | J41: 22
A42: =A41+1 -> 36 | B42: 132/1 | C42: DA+3 | D42: 19.442 | F42: 46083 | G42: 46089 | H42: Completed | I42: ZR Construction | J42: 30
A43: =A42+1 -> 37 | B43: 76/3 | C43: DA+3 | D43: 19.442 | F43: 46086 | G43: 46091 | H43: Completed | I43: Rakesh | J43: 23 | K43: Completed
A44: =A43+1 -> 38 | B44: 116/1 | C44: DA+0 | D44: 18.34 | F44: 46088 | G44: 46090 | H44: Completed | I44: Jwala Singh | J44: 22
A45: =A44+1 -> 39 | B45: 156/4 | C45: DA+0 | D45: 18.34 | F45: 46088 | G45: 46094 | H45: Completed | I45: Vijay Bhagat | J45: 25
A46: =A45+1 -> 40 | B46: 130/2 | C46: DA+0 | D46: 18.34 | F46: 46089 | G46: 46094 | H46: Completed | I46: ZR Construction | J46: 30 | L46: Due to ROW work hampered on 09-03-2026
A47: =A46+1 -> 41 | B47: 90/2 | C47: DA+0 | D47: 18.34 | F47: 46090 | G47: 46093 | H47: Completed | I47: Saritha Devi | J47: 30
A48: =A47+1 -> 42 | B48: AP102 | C48: DB+0 | D48: 27.92 | F48: 46092 | G48: 46095 | H48: Completed | I48: Jwala Singh | J48: 22
A49: =A48+1 -> 43 | B49: AP77 | C49: DB+3 | D49: 29.492 | F49: 46092 | G49: 46098 | H49: Completed | I49: Rakesh | J49: 23 | K49: Completed
A50: =A49+1 -> 44 | B50: 95/1 | C50: DA+0 | D50: 18.34 | F50: 46093 | G50: 46096 | H50: Completed | I50: Saritha Devi | J50: 30 | K50: Completed
A51: =A50+1 -> 45 | B51: 131/6 | C51: DA+9 | D51: 24.149 | F51: 46094 | G51: 46100 | H51: Completed | I51: ZR Construction | J51: 30
A52: =A51+1 -> 46 | B52: AP157 | C52: DB+0 | D52: 27.92 | F52: 46094 | G52: 46102 | H52: Completed | I52: Vijay Bhagat | J52: 25
A53: =A52+1 -> 47 | B53: AP111 | C53: DC+0 | D53: 32.222 | F53: 46094 | G53: 46103 | H53: Completed | I53: Poonam Kumari | J53: 30
A54: =A53+1 -> 48 | B54: AP100 | C54: DC+3 | D54: 33.53 | F54: 46095 | G54: 46100 | H54: Completed | I54: Jwala Singh | J54: 22
A55: =A54+1 -> 49 | B55: 69/3 | C55: DA+0 | D55: 18.34 | F55: 46098 | G55: 46102 | H55: Completed | I55: Saritha Devi | J55: 30
A56: =A55+1 -> 50 | B56: 77/1 | C56: DA+3 | D56: 19.44 | F56: 46098 | G56: 46103 | H56: Completed | I56: Rakesh | J56: 23 | K56: Completed
A57: =A56+1 -> 51 | B57: 136/1 | C57: DA+3 | D57: 19.44 | F57: 46102 | G57: 46112 | H57: Completed | I57: ZR Construction | J57: 30
A58: =A57+1 -> 52 | B58: AP104 | C58: DB+0 | D58: 27.92 | F58: 46101 | G58: 46104 | H58: Completed | I58: Jwala Singh | J58: 22
A59: =A58+1 -> 53 | B59: 69/2 | C59: DA+0 | D59: 18.34 | F59: 46102 | G59: 46105 | H59: Completed | I59: Saritha Devi | J59: 30
A60: =A59+1 -> 54 | B60: AP156 | C60: DC+0 | D60: 32.22 | F60: 46102 | G60: 46110 | H60: Completed | I60: Vijay Bhagat | J60: 25
A61: =A60+1 -> 55 | B61: 77/2 | C61: DB+0 | D61: 27.92 | F61: 46103 | G61: 46109 | H61: Completed | I61: Rakesh | J61: 23 | K61: Completed
A62: =A61+1 -> 56 | B62: 104/1 | C62: DA+3 | D62: 19.44 | F62: 46104 | G62: 46106 | H62: Completed | I62: Jwala Singh | J62: 22
A63: =A62+1 -> 57 | B63: 115/1 | C63: DA+6 | D63: 22.68 | F63: 46107 | G63: 46112 | H63: Completed | I63: Vijay Bhagat-2 | J63: 18
A64: =A63+1 -> 58 | B64: AP68 | C64: DB+0 | D64: 27.92 | F64: 46105 | G64: 46110 | H64: Completed | I64: Saritha Devi | J64: 30
A65: =A64+1 -> 59 | B65: AP103 | C65: DD+0 | D65: 42.226 | F65: 46107 | G65: 46112 | H65: Completed | I65: Jwala Singh | J65: 22
A66: =A65+1 -> 60 | B66: AP80 | C66: DD+0 | D66: 42.226 | F66: 46109 | G66: 46117 | H66: Completed | I66: Rakesh | J66: 23 | K66: Completed
A67: =A66+1 -> 61 | B67: 69/1 | C67: DA+0 | D67: 18.34 | F67: 46110 | G67: 46112 | H67: Completed | I67: Saritha Devi | J67: 30
A68: =A67+1 -> 62 | B68: 157/1 | C68: DA+0 | D68: 18.34 | F68: 46110 | G68: 46115 | H68: Completed | I68: Vijay Bhagat | J68: 20
A69: =A68+1 -> 63 | B69: AP85 | C69: DB+0 | D69: 27.92 | F69: 46116 | G69: 46124 | H69: Completed | I69: Vijay Bhagat-2 | J69: 20
A70: =A69+1 -> 64 | B70: 145/1 | C70: DA+0 | D70: 18.34 | F70: 46112 | G70: 46116 | H70: Completed | I70: Jwala Singh | J70: 25
A71: =A70+1 -> 65 | B71: AP70 | C71: DC+3 | D71: 33.53 | F71: 46112 | G71: 46119 | H71: Completed | I71: Saritha Devi | J71: 24
A72: =A71+1 -> 66 | B72: 135/1 | C72: DA+6 | D72: 22.68 | F72: 46116 | G72: 46125 | H72: Completed | I72: ZR Construction | J72: 20
A73: =A72+1 -> 67 | B73: AP146 | C73: DC+0 | D73: 32.22 | F73: 46116 | G73: 46122 | H73: Completed | I73: Jwala Singh | J73: 25
A74: =A73+1 -> 68 | B74: 156/2 | C74: DA+0 | D74: 18.34 | F74: 46116 | G74: 46121 | H74: Completed | I74: Vijay Bhagat-1 | J74: 25
A75: =A74+1 -> 69 | B75: AP79 | C75: DD+9 | D75: 56.129 | F75: 46118 | G75: 46129 | H75: Completed | I75: Rakesh | J75: 20 | K75: Completed
A76: =A75+1 -> 70 | B76: 151/1 | C76: DA+0 | D76: 18.34 | F76: 46122 | G76: 46124 | H76: Completed | I76: Jwala Singh | J76: 25
A77: =A76+1 -> 71 | B77: 156/3 | C77: DA+0 | D77: 18.34 | F77: 46122 | G77: 46126 | H77: Completed | I77: Vijay Bhagat-1 | J77: 25
A78: =A77+1 -> 72 | B78: 67/1 | C78: DA+0 | D78: 18.34 | F78: 46123 | G78: 46125 | H78: Completed | I78: Saritha Devi | J78: 24
A79: =A78+1 -> 73 | B79: AP114 | C79: DB+0 | D79: 27.92 | F79: 46124 | G79: 46131 | H79: Completed | I79: Vijay Bhagat-2 | J79: 20
A80: =A79+1 -> 74 | B80: 150/2 | C80: DA+0 | D80: 18.34 | F80: 46124 | G80: 46128 | H80: Completed | I80: Jwala Singh | J80: 25
A81: =A80+1 -> 75 | B81: 70/2 | C81: DA+0 | D81: 18.34 | F81: 46125 | G81: 46129 | H81: Completed | I81: Saritha Devi | J81: 24
A82: =A81+1 -> 76 | B82: 136/2 | C82: DA+3 | D82: 19.44 | F82: 46125 | G82: 46129 | H82: Completed | I82: ZR Construction | J82: 20
A83: =A82+1 -> 77 | B83: 155/1 | C83: DA+0 | D83: 18.34 | F83: 46126 | G83: 46129 | H83: Completed | I83: Vijay Bhagat-1 | J83: 25
A84: =A83+1 -> 78 | B84: 152/1 | C84: DA+3 | D84: 19.44 | F84: 46128 | G84: 46131 | H84: Completed | I84: Jwala Singh | J84: 25
A85: =A84+1 -> 79 | B85: AP69 | C85: DB+0 | D85: 27.92 | F85: 46129 | G85: 46133 | H85: Completed | I85: Saritha Devi | J85: 24
A86: =A85+1 -> 80 | B86: 82/1 | C86: DA+0 | D86: 18.34 | F86: 46129 | G86: 46133 | H86: Completed | I86: Rakesh | J86: 20 | K86: Completed
A87: =A86+1 -> 81 | B87: AP135 | C87: DB+3 | D87: 29.492 | F87: 46130 | G87: 46137 | H87: Completed | I87: ZR Construction | J87: 20
A88: =A87+1 -> 82 | B88: 155/2 | C88: DA+0 | D88: 18.34 | F88: 46130 | G88: 46134 | H88: Completed | I88: Vijay Bhagat-1 | J88: 25
A89: =A88+1 -> 83 | B89: 99/1 | C89: DA+9 | D89: 24.149 | F89: 46131 | G89: 46139 | H89: Completed | I89: Vijay Bhagat-2 | J89: 20
A90: =A89+1 -> 84 | B90: 145/2 | C90: DA+3 | D90: 19.44 | F90: 46131 | G90: 46134 | H90: Completed | I90: Jwala Singh | J90: 25
A91: =A90+1 -> 85 | B91: 72/1 | C91: DA+3 | D91: 19.44 | F91: 46133 | G91: 46137 | H91: Completed | I91: Saritha Devi | J91: 24
A92: =A91+1 -> 86 | B92: AP75 | C92: DB+9 | D92: 36.354 | F92: 46133 | G92: 46140 | H92: Completed | I92: Rakesh | J92: 20 | K92: Completed
A93: =A92+1 -> 87 | B93: 155/3 | C93: DA+0 | D93: 18.34 | F93: 46134 | G93: 46139 | H93: Completed | I93: Vijay Bhagat-1 | J93: 25
A94: =A93+1 -> 88 | B94: 150/1 | C94: DA+0 | D94: 18.34 | F94: 46134 | G94: 46138 | H94: Completed | I94: Jwala Singh | J94: 25
A95: =A94+1 -> 89 | B95: 136/3 | C95: DA+0 | D95: 18.34 | F95: 46137 | G95: 46142 | H95: Completed | I95: ZR Construction | J95: 20
A96: =A95+1 -> 90 | B96: 72/2 | C96: DA+6 | D96: 22.68 | F96: 46137 | G96: 46142 | H96: Completed | I96: Saritha Devi | J96: 24
A97: =A96+1 -> 91 | B97: AP147 | C97: DB+0 | D97: 27.92 | F97: 46138 | G97: 46142 | H97: Completed | I97: Jwala Singh | J97: 25
A98: =A97+1 -> 92 | B98: 156/1 | C98: DA+6 | D98: 22.68 | F98: 46139 | G98: 46146 | H98: Completed | I98: Vijay Bhagat-1 | J98: 25
A99: =A98+1 -> 93 | B99: AP118 | C99: DC+0 | D99: 32.22 | F99: 46139 | G99: 46147 | H99: Completed | I99: Vijay Bhagat-2 | J99: 20
A100: =A99+1 -> 94 | B100: AP74 | C100: DB+0 | D100: 27.92 | F100: 46140 | G100: 46145 | H100: Completed | I100: Rakesh | J100: 20 | K100: Completed
A101: =A100+1 -> 95 | B101: AP72 | C101: DB+3 | D101: 29.492 | F101: 46142 | G101: 46147 | H101: Completed | I101: Saritha Devi | J101: 24
A102: =A101+1 -> 96 | B102: 131/2 | C102: DA+3 | D102: 19.442 | F102: 46142 | G102: 46147 | H102: Completed | I102: ZR Construction | J102: 20
...

Sheet Vertical Chart -JS Line Punjab
A1: KEC INTERNATIONAL LIMITED
A2: 400 kV Samba- Jalandhar D/C Line(Quad) - Wind Zone - 5-Punjab Portion
A3: Vertical Chart
J4: Complete | L4: =COUNTIF($L$8:$L$488,"Clear") -> 226 | M4: =COUNTIF($M$8:$M$488,"C") -> 222 | N4: =COUNTIF($N$8:$N$488,"C") -> 176 | O4: =COUNTIF($O$8:$O$594,"C") -> 137 | P4: =COUNTIF($P$8:$P$417,"C") -> 0
J5: WIP | M5: =COUNTIF($M$8:$M$488,"WIP") -> 3 | N5: =COUNTIF($N$8:$N$417,"WIP") -> 0 | O5: =COUNTIF($O$8:$O$553,"WIP") -> 4 | P5: =COUNTIF($P$8:$P$417,"WIP") -> 0
A6: S.No | B6: Tower | C6: TOT | D6: Angle of Deviation | E6: Raised Chimney | I6: FDN Classification | J6: Span Length (Mtr) | K6: Section Length (m) | L6: ROW | M6: Foundation | N6: Earthing | O6: Tower Erection | P6: Tack Welding | Q6: Stringing | R6: Remarks
E7: LEG A | F7: LEG B | G7: LEG C | H7: LEG D
A8: 1 | B8: AP53 | C8: DC+0 | D8: 29°2'38"RT | I8: PS (SD) | K8: 0 | L8: Clear | M8: C
J9: 416.658
A10: =A8+1 -> 2 | B10: AP54 | C10: DD+6 | D10: 15°23'08"RT | I10: PS (SD) | K10: =J9 -> 416.658 | L10: Clear | M10: C
J11: 389.277
A12: =A10+1 -> 3 | B12: AP55 | C12: DD+3 | D12: 38°18'51"RT | I12: PS | K12: =J11 -> 389.277 | L12: Clear | M12: C
J13: 384.151
A14: =A12+1 -> 4 | B14: 55/1 | C14: DA+6 | I14: PS (SD) | K14: =J13 -> 384.151 | L14: Clear | M14: C | N14: C
J15: 409.3
A16: =A14+1 -> 5 | B16: AP56 | C16: DC+3 | D16: 25°53'58"RT | I16: PS (SD) | K16: =J15 -> 409.3 | L16: Clear | M16: C
J17: 409.72
A18: =A16+1 -> 6 | B18: 56/1 | C18: DA+6 | K18: =J17 -> 409.72
J19: 406.732
A20: =A18+1 -> 7 | B20: 56/2 | C20: DA+3 | I20: FS(PD) | K20: =J19 -> 406.732 | L20: Clear | M20: C
J21: 404.913
A22: =A20+1 -> 8 | B22: 56/3 | C22: DA+6 | I22: PS (SD) | K22: =J21 -> 404.913 | L22: Clear | M22: C | N22: C
J23: 285.563
A24: =A22+1 -> 9 | B24: 56/4 | C24: DA+6 | I24: PS (SD) | K24: =J23 -> 285.563 | L24: Clear | M24: C
J25: 399.174
A26: =A24+1 -> 10 | B26: AP57 | C26: DD+3 | D26: 39°39'47"LT | I26: PS(SD) | K26: =J25 -> 399.174 | L26: Clear | M26: C
J27: 343.784
A28: =A26+1 -> 11 | B28: 57/1 | C28: DA+0 | I28: PS(SD) | K28: =J27 -> 343.784 | L28: Clear | M28: C
J29: 313.063
A30: =A28+1 -> 12 | B30: 57/2 | C30: DA+0 | I30: PS(SD) | L30: Clear | M30: C
J31: 325.525
A32: =A30+1 -> 13 | B32: AP58 | C32: DC+0 | D32: 24°19'0"RT | I32: WET | L32: Clear | M32: C
J33: 406.443
A34: =A32+1 -> 14 | B34: AP59 | C34: DD+6 | D34: 47°09'41"LT | I34: PS(SD) | L34: Clear | M34: C
J35: 423.081
A36: =A34+1 -> 15 | B36: 59/1 | C36: DA+3 | I36: FS(PD) | K36: =J29+J31+J33+J35 -> 1468.112 | L36: Clear | M36: C | O36: WIP
J37: 364.958
A38: =A36+1 -> 16 | B38: AP60 | C38: DB+6 | D38: 8°29'30"LT | I38: PS(SD) | K38: =J37 -> 364.958 | L38: Clear | M38: C | N38: C | O38: C
J39: 380.949
A40: =A38+1 -> 17 | B40: 60/1 | C40: DA+0 | I40: PS(SD) | K40: =J39 -> 380.949 | L40: Clear | M40: C | N40: C
J41: 376.626
A42: =A40+1 -> 18 | B42: AP61 | C42: DC+0 | D42: 21°54'40"RT | I42: PS(SD) | L42: Clear | M42: C | N42: C
J43: 299.077
A44: =A42+1 -> 19 | B44: 61/1 | C44: DA+0 | I44: PS(SD) | L44: Clear | M44: C | N44: C
J45: 264.842
A46: =A44+1 -> 20 | B46: AP62 | C46: DB+0 | D46: 4°52'18"RT | I46: PS(SD) | L46: Clear | M46: WIP
J47: 364.064
A48: =A46+1 -> 21 | B48: 62/1 | C48: DA+0 | I48: PS(SD) | L48: Clear | M48: C
J49: 319.184
A50: =A48+1 -> 22 | B50: 62/2 | C50: DA+0 | I50: PS(SD) | L50: Clear | M50: C | N50: C
J51: 397.985
A52: =A50+1 -> 23 | B52: AP63 | C52: DB+9 | D52: 12°25'23"LT | I52: PS(SD) | K52: =J47+J49+J51 -> 1081.233 | L52: Clear | M52: C | N52: C
J53: 450.859
A54: =A52+1 -> 24 | B54: AP64 | C54: DC+9 | D54: 17°10'17"RT | I54: PS(SD) | L54: Clear | M54: C | N54: C
J55: 326.477
A56: =A54+1 -> 25 | B56: 64/1 | C56: DA+0 | I56: PS(SD) | L56: Clear | M56: C | N56: C | O56: C
J57: 276.363
A58: =A56+1 -> 26 | B58: AP65 | C58: DB+0 | D58: 12°37'37"RT | I58: PS(SD) | K58: =J55+J57 -> 602.84 | L58: Clear | M58: C | O58: C
J59: 307.216
A60: =A58+1 -> 27 | B60: 65/1 | C60: DA+0 | I60: PS(SD) | L60: Clear | M60: C | O60: C
J61: 389.397
A62: =A60+1 -> 28 | B62: 65/2 | C62: DA+6 | I62: PS(SD) | L62: Clear | M62: C | N62: C
J63: 368.792
A64: =A62+1 -> 29 | B64: 65/3 | C64: DA+0 | I64: PS(SD) | L64: Clear | M64: C
J65: 404.386
A66: =A64+1 -> 30 | B66: 65/4 | C66: DA+3 | I66: PS(SD) | L66: Clear | M66: C | O66: C
J67: 378.135
A68: =A66+1 -> 31 | B68: 65/5 | C68: DA+3 | I68: PS(SD) | L68: Clear | M68: C
J69: 370.482
A70: =A68+1 -> 32 | B70: AP66 | C70: DC+0 | D70: 26°31'54"RT | I70: WET | L70: Clear | M70: C | N70: C | O70: C
J71: 199.386
A72: =A70+1 -> 33 | B72: AP67 | C72: DD+0 | D72: 42°51'4"LT | I72: PS (SD) | L72: Clear | M72: C | N72: C | O72: C
J73: 294.009
A74: =A72+1 -> 34 | B74: 67/1 | C74: DA+0 | I74: PS (SD) | L74: Clear | M74: C | N74: C | O74: C
J75: 312.708
A76: =A74+1 -> 35 | B76: 67/2 | C76: DA+0 | I76: PS (SD) | K76: =J65+J67+J69+J71+J73+J75 -> 1959.106 | L76: Clear | M76: C | N76: C
J77: 321.893 | R77: 66 KV H Pole Gurdaspur To Gahlari T/L
A78: =A76+1 -> 36 | B78: 67/3 | C78: DA+0 | I78: PS (SD) | K78: =J77 -> 321.893 | L78: Clear | M78: C | N78: C | O78: C
J79: 382.475
A80: =A78+1 -> 37 | B80: AP68 | C80: DB+0 | D80: 12°54'1"LT | I80: PS (SD) | L80: Clear | M80: C | N80: C | O80: C
J81: 388.11
A82: =A80+1 -> 38 | B82: AP69 | C82: DB+0 | D82: 5°21'56"RT | I82: PS (SD) | L82: Clear | M82: C | N82: C | O82: C
J83: 382.675
A84: =A82+1 -> 39 | B84: 69/1 | C84: DA+0 | I84: FS | K84: =J79+J81+J83 -> 1153.26 | L84: Clear | M84: C | N84: C | O84: C
J85: 390.446
A86: =A84+1 -> 40 | B86: 69/2 | C86: DA+0 | I86: FS | K86: =J85 -> 390.446 | L86: Clear | M86: C | N86: C | O86: C
J87: 361.751
A88: =A86+1 -> 41 | B88: 69/3 | C88: DA+0 | I88: WET | L88: Clear | M88: C | N88: C | O88: C
J89: 396.035
A90: =A88+1 -> 42 | B90: AP70 | C90: DC+3 | D90: 28°33'28"RT | I90: PS (SD) | L90: Clear | M90: C | N90: C | O90: C
J91: 435.862
A92: =A90+1 -> 43 | B92: 70/1 | C92: DA+9 | I92: PS (SD) | K92: =J91 -> 435.862 | L92: Clear | M92: C | N92: C
J93: 333.945
A94: =A92+1 -> 44 | B94: 70/2 | C94: DA+0 | I94: PS (SD) | L94: Clear | M94: C | N94: C | O94: C
J95: 502.836
A96: =A94+1 -> 45 | B96: AP70/3 | C96: DD+18 | D96: 2°59'27"LT | E96: 1 | F96: 1 | G96: 1 | H96: 1 | I96: PS (SD) | L96: Clear | M96: C | O96: WIP
J97: 326.311
A98: =A96+1 -> 46 | B98: AP71 | C98: DC+9 | D98: 17°25'49"LT | I98: PS (SD) | L98: Clear | M98: C | N98: C
J99: 415.29
A100: =A98+1 -> 47 | B100: 71/1 | C100: DA+3 | I100: PS (SD) | L100: Clear | M100: C | O100: C
...

Sheet Sheet9
D2: S.No | E2: Loc | F2: TOT | G2: Classification | H2: Start Date | I2: End Darte | J2: JMC
D3: 1 | E3: 153/0 | F3: DC+0 | G3: WET | H3: 46039 | I3: 46058 | J3: 105 | K3: OK
D4: =D3+1 -> 2 | E4: AP139 | F4: DB+0 | G4: WET | H4: 46042 | I4: 46059 | J4: =J3+1 -> 106 | K4: OK
D5: =D4+1 -> 3 | E5: 151/2 | F5: DA+3 | G5: WET | H5: 46056 | I5: 46060 | J5: =J4+1 -> 107 | K5: OK
D6: =D5+1 -> 4 | E6: AP97 | F6: DD+3 | G6: WET | H6: 46051 | I6: 46061 | J6: =J5+1 -> 108 | K6: OK
D7: =D6+1 -> 5 | E7: AP155 | F7: DD+0 | G7: WET | H7: 46053 | I7: 46062 | J7: =J6+1 -> 109 | K7: OK
D8: =D7+1 -> 6 | E8: 136/2 | F8: DA+3 | G8: WET | H8: 46044 | I8: 46064 | J8: =J7+1 -> 110 | K8: OK
D9: =D8+1 -> 7 | E9: AP130 | F9: DD+18 | G9: PS | H9: 46040 | I9: 46065 | J9: =J8+1 -> 111 | K9: OK
D10: =D9+1 -> 8 | E10: 152/4 | F10: DA+0 | G10: WET | H10: 46057 | I10: 46065 | J10: =J9+1 -> 112 | K10: OK
D11: =D10+1 -> 9 | E11: AP92 | F11: DD+25 | G11: PS | H11: 46043 | I11: 46066 | J11: =J10+1 -> 113 | K11: OK | P11: =8+30+40+26 -> 104
D12: =D11+1 -> 10 | E12: 153/1 | F12: DA+0 | G12: WET | H12: 46059 | I12: 46066 | J12: =J11+1 -> 114 | K12: OK
D13: =D12+1 -> 11 | E13: AP156 | F13: DC+0 | G13: WET | H13: 46058 | I13: 46067 | J13: =J12+1 -> 115 | K13: OK
D14: =D13+1 -> 12 | E14: 136/3 | F14: DA+0 | G14: WET | H14: 46062 | I14: 46068 | J14: =J13+1 -> 116 | K14: OK
D15: =D14+1 -> 13 | E15: 157/1 | F15: DA+0 | G15: WET | H15: 46062 | I15: 46068 | J15: =J14+1 -> 117 | K15: OK
D16: =D15+1 -> 14 | E16: 72/1 | F16: DA+3 | G16: WET | H16: 46067 | I16: 46070 | J16: =J15+1 -> 118 | K16: OK
D17: =D16+1 -> 15 | E17: AP150 | F17: DC+0 | G17: WET | H17: 46062 | I17: 46071 | J17: =J16+1 -> 119 | K17: OK
D18: =D17+1 -> 16 | E18: AP70 | F18: DC+3 | G18: PS(SD) | H18: 46063 | I18: 46071 | J18: =J17+1 -> 120 | K18: OK
D19: =D18+1 -> 17 | E19: 153/2 | F19: DA+3 | G19: WET | H19: 46066 | I19: 46071 | J19: =J18+1 -> 121 | K19: OK
D20: =D19+1 -> 18 | E20: AP111 | F20: DC+0 | G20: WET | H20: 46059 | I20: 46072 | J20: =J19+1 -> 122 | K20: OK
D21: =D20+1 -> 19 | E21: 136/4 | F21: DA+3 | G21: WET | H21: 46065 | I21: 46073 | J21: =J20+1 -> 123 | K21: OK
D22: =D21+1 -> 20 | E22: 70/2 | F22: DA+0 | G22: PS(SD) | H22: 46058 | I22: 46074 | J22: =J21+1 -> 124 | K22: OK
D23: =D22+1 -> 21 | E23: AP68 | F23: DB+0 | G23: PS(SD) | H23: 46063 | I23: 46074 | J23: =J22+1 -> 125 | K23: OK
... D32: =D31+1 -> 30 | E32: AP114 | F32: DB+0 | G32: WET | H32: 46074 | I32: 46081 | J32: =J31+1 -> 134 | K32: OK
D33: =D32+1 -> 31 | E33: 71/2 | F33: DA+9 | G33: WET | J33: 135 | K33: OK
D34: =D33+1 -> 32 | E34: 69/0 | H34: 46077 | I34: 46082 | J34: 136 | K34: OK
D37: S.No | E37: Loc | F37: TOT | G37: Classification | H37: Start Date | I37: End Darte | J37: JMC
D38: 1 | E38: AP148 | F38: DD+25 2MRC | G38: PS | H38: 46072 | I38: 46097 | J38: 140
D39: =D38+1 -> 2 | E39: AP149 | F39: DD+25 | G39: PS | H39: 46074 | I39: 46091 | J39: 137
D40: =D39+1 -> 3 | E40: 67/2 | F40: DA+0 | G40: PS (SD) | H40: 46085 | I40: 46094 | J40: 138 | K40: OK
D41: =D40+1 -> 4 | E41: AP71 | F41: DC+9 | G41: PS (SD) | H41: 46084 | I41: 46104 | J41: 143 | K41: OK
D42: =D41+1 -> 5 | E42: AP152 | F42: DD+0 | G42: WET | H42: 46081 | I42: 46107 | J42: 145
D43: =D42+1 -> 6 | E43: AP127 | F43: DD+30 2MRC | G43: PS | H43: 46082 | I43: 46096 | J43: 139
D44: =D43+1 -> 7 | E44: AP145 | F44: DB+0 | G44: PS (SD) | H44: 46082 | I44: 46106 | J44: 144
D45: =D44+1 -> 8 | E45: AP136 | F45: DC+3 | G45: WET | H45: 46083 | I45: 46099 | J45: 141
D46: =D45+1 -> 9 | E46: 67/1 | F46: DA+0 | G46: PS(SD) | H46: 46094 | I46: 46100 | J46: 142 | K46: OK
D47: =D46+1 -> 10 | E47: AP108 | F47: DD+25 | G47: PS | H47: 46082 | I47: 46109 | J47: 146 | K47: OK

Sheet ROW Front vs Progress
B2: S.No | C2: Line | D2: ROW Clearence Work Front | E2: Completed | F2: WIP | G2: Balance
B3: 1 | C3: Samba-Jalandhar (Jammu Portion) | D3: 95 | E3: 84 | F3: 7 | G3: =D3-E3-F3 -> 4
B4: =B3+1 -> 2 | C4: Samba-Jalandhar (Punjab Portion) | D4: 181 | E4: 158 | F4: 10 | G4: =D4-E4-F4 -> 13
B5: =B4+1 -> 3 | C5: Samba-Kishenpur | D5: 56 | E5: 46 | F5: 7 | G5: =D5-E5-F5 -> 3
B6: =B5+1 -> 4 | C6: LILO-Kishtwar | D6: 4 | F6: 3 | G6: =D6-E6-F6 -> 1
B7: Total | D7: =SUM(D3:D6) -> 336 | E7: =SUM(E3:E6) -> 288 | F7: =SUM(F3:F6) -> 27 | G7: =SUM(G3:G6) -> 21
D38: 46098 | E38: 3

Sheet Foundation -JS Line- Punjab
A1: KEC International Ltd | O1: Date: | P1: ='TB-605'!E1 -> 46246
A2: 400 kV Samba- Jalandhar D/C Line(Quad) - Wind Zone - 5-Punjab Portion
A3: FOUNDATION
A5: S.No | B5: Loc No. | C5: Tower Type | D5: Classification | E5: Conc Volume | F5: Start Date | G5: Foundation | L5: Completion Date | M5: FDN Status | N5: Earthing | O5: Gang Name | P5: Gang Strength | Q5: Remark
G6: Excavation | H6: Stub Setting | I6: PCC | J6: Rebar Placing | K6: RCC
A7: 1 | B7: 90/1 | C7: DA+3 | D7: WET | E7: =31.932+4.177 -> 36.109 | F7: 45925 | G7: 46033 | H7: 46033 | I7: 46033 | J7: 46033 | K7: 46033 | L7: 46033 | M7: Completed | O7: Anchal Singh | P7: 25 | Q7: 3 pits casting completed on 24.10.25. After clearence of ROW on 09.01.26, Work resumed since 10.01.26 in the 4th pit and work completed on 11.01.26
A8: =A7+1 -> 2 | B8: 117/1 | C8: DA+0 | D8: WET | F8: 45943 | G8: 45948 | H8: 45948 | I8: 45949 | J8: 45949 | K8: 45950 | L8: 45950 | M8: Completed | O8: Sakrala Material | P8: 10
A9: =A8+1 -> 3 | B9: 92/3 | C9: DA+0 | D9: WET | F9: 45946 | G9: 45955 | H9: 45955 | I9: 45955 | J9: 45956 | K9: 45957 | L9: 45957 | M9: Completed | O9: MS Constructions | P9: 9
A10: =A9+1 -> 4 | B10: 92/2 | C10: DA+6 | D10: WET | F10: 45949 | G10: 45955 | H10: 45957 | I10: 45957 | J10: 45958 | K10: 45958 | L10: 45958 | M10: Completed | O10: MS Constructions | P10: 10
A11: =A10+1 -> 5 | B11: 71/3 | C11: DA+6 | D11: WET | F11: 45947 | G11: 45949 | H11: 45950 | I11: 45950 | J11: 45951 | K11: 45953 | L11: 45953 | M11: Completed | O11: Ramesh | P11: 12
A12: =A11+1 -> 6 | B12: 72/2 | C12: DA+6 | D12: WET | F12: 45953 | G12: 45954 | H12: 45955 | I12: 45955 | J12: 45956 | K12: 45958 | L12: 45958 | M12: Completed | O12: Ramesh | P12: 12
A13: =A12+1 -> 7 | B13: 117/3 | C13: DA+0 | D13: WET | F13: 45953 | G13: 45955 | H13: 45956 | I13: 45957 | J13: 45959 | K13: 45959 | L13: 45959 | M13: Completed | N13: 45965 | O13: Sakrala Material | P13: 10
A14: =A13+1 -> 8 | B14: 74/0 | C14: DB+0 | D14: WET | F14: 45955 | G14: 45957 | H14: 45961 | I14: 45961 | J14: 45962 | K14: 45967 | L14: 45967 | M14: Completed | N14: 45973 | O14: Ramesh | P14: 16
A15: =A14+1 -> 9 | B15: 72/0 | C15: DB+3 | D15: WET | F15: 45962 | G15: 45963 | H15: 45964 | I15: 45965 | J15: 45966 | K15: 45970 | L15: 45970 | M15: Completed | N15: 45973 | O15: Ramesh
A16: =A15+1 -> 10 | B16: 89/1 | C16: DA+3 | D16: WET | F16: 45956 | G16: 45960 | H16: 45961 | I16: 45961 | J16: 45961 | K16: 45961 | L16: 45961 | M16: Completed | N16: 45968 | O16: Anchal Singh | P16: =8+15 -> 23
A17: =A16+1 -> 11 | B17: 93/1 | C17: DA+0 | D17: WET | F17: 45957 | G17: 45958 | H17: 45960 | I17: 45960 | J17: 45960 | K17: 45961 | L17: 45961 | M17: Completed | N17: 45970 | O17: MS Constructions | P17: 19
A18: =A17+1 -> 12 | B18: 117/2 | C18: DA+3 | D18: WET | F18: 45956 | G18: 45958 | H18: 45962 | I18: 45962 | J18: 45963 | K18: 45965 | L18: 45965 | M18: Completed | N18: 45967 | O18: Sakrala Material | P18: 20
A19: =A18+1 -> 13 | B19: 118/1 | C19: DA+0 | D19: WET | F19: 45963 | G19: 45964 | H19: 45965 | I19: 45965 | J19: 45965 | K19: 45967 | L19: 45967 | M19: Completed | N19: 45969 | O19: Sakrala Material
A20: =A19+1 -> 14 | B20: 95/2 | C20: DA+0 | D20: WET | F20: 45959 | G20: 45965 | H20: 45966 | I20: 45967 | J20: 45967 | K20: 45969 | L20: 45969 | M20: Completed | N20: 45970 | O20: Ikrar/MS Hussain | P20: 13
A21: =A20+1 -> 15 | B21: 95/3 | C21: DA+0 | D21: WET | F21: 45961 | G21: 45969 | H21: 45970 | I21: 45970 | J21: 45970 | K21: 45971 | L21: 45971 | M21: Completed | N21: 45972 | O21: Ikrar/MS Hussain
A22: =A21+1 -> 16 | B22: 93/2 | C22: DA+0 | D22: WET | F22: 45959 | G22: 45960 | H22: 45963 | I22: 45963 | J22: 45963 | K22: 45965 | L22: 45965 | M22: Completed | O22: MS Constructions | P22: 19
A23: =A22+1 -> 17 | B23: 92/1 | C23: DA+3 | D23: WET | F23: 45964 | G23: 45968 | H23: 45970 | I23: 45970 | J23: 45971 | K23: 45971 | L23: 45971 | M23: Completed | N23: 45975 | O23: MS Constructions
A24: =A23+1 -> 18 | B24: 97/2 | C24: DA+0 | D24: WET | F24: 45960 | G24: 45963 | H24: 45969 | I24: 45970 | J24: 45971 | K24: 45973 | L24: 45973 | M24: Completed | N24: 45977 | O24: Md. Latif | P24: 25
A25: =A24+1 -> 19 | B25: 97/1 | C25: DA+0 | D25: WET | F25: 45963 | G25: 45967 | H25: 45971 | I25: 45972 | J25: 45972 | K25: 45974 | L25: 45974 | M25: Completed | N25: 45977 | O25: Md. Latif
A26: =A25+1 -> 20 | B26: AP90 | C26: DD+0 | D26: WET | F26: 45962 | G26: 45978 | H26: 45979 | I26: 45979 | J26: 45981 | K26: 45983 | L26: 45983 | M26: Completed | N26: 45980 | O26: Anchal Singh | P26: 25
A27: =A26+1 -> 21 | B27: AP118 | C27: DC+0 | D27: WET | F27: 45968 | G27: 45973 | H27: 45974 | I27: 45974 | J27: 45974 | K27: 45977 | L27: 45977 | M27: Completed | N27: 45980 | O27: Sakrala Material | P27: 20
A28: =A27+1 -> 22 | B28: 131/1 | C28: DA+3 | D28: WET | F28: 45967 | G28: 46003 | H28: 46003 | I28: 45975 | J28: 45975 | K28: 45976 | L28: 45976 | M28: Completed | N28: 45982 | O28: TCC Construction | P28: 16
A29: =A28+1 -> 23 | B29: 95/1 | C29: DA+0 | D29: WET | F29: 45970 | G29: 45974 | H29: 45975 | I29: 45975 | J29: 45975 | K29: 45976 | L29: 45976 | M29: Completed | N29: 45977 | O29: Ikrar/MS Hussain | P29: 20
A30: =A29+1 -> 24 | B30: AP93 | C30: DC+0 | D30: WET | F30: 45971 | G30: 45978 | H30: 45979 | I30: 45979 | J30: 45979 | K30: 45980 | L30: 45980 | M30: Completed | N30: 45992 | O30: MS Constructions | P30: 19
A31: =A30+1 -> 25 | B31: 76/2 | C31: DA+3 | D31: WET | F31: 45972 | G31: 45973 | H31: 45974 | I31: 45974 | J31: 45974 | K31: 45975 | L31: 45975 | M31: Completed | N31: 45976 | O31: Ramesh | P31: 16
A32: =A31+1 -> 26 | B32: 97/3 | C32: DA+3 | D32: WET | F32: 45972 | G32: 45973 | H32: 45976 | I32: 45979 | J32: 45979 | K32: 45981 | L32: 45981 | M32: Completed | N32: 45982 | O32: Md. Latif | P32: 25
A33: =A32+1 -> 27 | B33: AP98 | C33: DB+3 | D33: WET | F33: 45973 | G33: 45980 | H33: 45982 | I33: 45982 | J33: 45984 | K33: 45985 | L33: 45985 | M33: Completed | N33: 45992 | O33: Md. Latif
A34: =A33+1 -> 28 | B34: 95/4 | C34: DA+0 | D34: WET | F34: 45974 | G34: 45979 | H34: 45980 | I34: 45980 | J34: 45981 | K34: 45981 | L34: 45981 | M34: Completed | N34: 45982 | O34: Ikrar | P34: 11
A35: =A34+1 -> 29 | B35: 76/1 | C35: DA+0 | D35: WET | F35: 45975 | G35: 45976 | H35: 45976 | I35: 45977 | J35: 45977 | K35: 45979 | L35: 45979 | M35: Completed | N35: 45980 | O35: Ramesh | P35: 16
A36: =A35+1 -> 30 | B36: 131/3 | C36: DA+3 | D36: WET | F36: 45976 | G36: 45977 | H36: 45979 | I36: 45979 | J36: 45980 | K36: 45980 | L36: 45980 | M36: Completed | N36: 45982 | O36: TCC Construction | P36: 16
A37: =A36+1 -> 31 | B37: AP116 | C37: DCT+0 | D37: FS | F37: 45977 | G37: 45988 | H37: 45989 | I37: 45989 | J37: 45989 | K37: 45991 | L37: 45991 | M37: Completed | N37: 45992 | O37: Sakrala Material | P37: 20
A38: =A37+1 -> 32 | B38: AP96 | C38: DC+0 | D38: WET | F38: 45978 | G38: 45988 | H38: 45988 | I38: 45988 | J38: 45989 | K38: 45990 | L38: 45990 | M38: Completed | N38: 45992 | O38: MS Hussain | P38: 12
A39: =A38+1 -> 33 | B39: AP77 | C39: DB+3 | D39: WET | F39: 45979 | G39: 46001 | H39: 46002 | I39: 46002 | J39: 46002 | K39: 46004 | L39: 46004 | M39: Completed | N39: 46005 | O39: Ramesh | P39: 16 | Q39: 2 pits casting completed on 22.11.2025 Balance 2 pits under ROW till 08.12.2025 Work resumed from 09.12.2025 & Completed on 13.12.25
A40: =A39+1 -> 34 | B40: 131/2 | C40: DA+3 | D40: WET | F40: 45980 | G40: 45982 | H40: 45983 | I40: 45984 | J40: 45984 | K40: 45985 | L40: 45985 | M40: Completed | N40: 45987 | O40: TCC Construction | P40: 16
A41: =A40+1 -> 35 | B41: AP94 | C41: DB+0 | D41: WET | F41: 45981 | G41: 45985 | H41: 45986 | I41: 45986 | J41: 45987 | K41: 45988 | L41: 45988 | M41: Completed | N41: 45996 | O41: MS Constructions | P41: 19
A42: =A41+1 -> 36 | B42: 98/1 | C42: DA+3 | D42: WET | F42: 45981 | G42: 45984 | H42: 45986 | I42: 45986 | J42: 45987 | K42: 45987 | L42: 45987 | M42: Completed | N42: 45987 | O42: Md. Latif | P42: 12
A43: =A42+1 -> 37 | B43: 103/1 | C43: DA+0 | D43: WET | F43: 45983 | G43: 45987 | H43: 45988 | I43: 45988 | J43: 45989 | K43: 45989 | L43: 45989 | M43: Completed | N43: 45989 | O43: Ikrar | P43: 11
A44: =A43+1 -> 38 | B44: 131/4 | C44: DA+0 | D44: WET | F44: 45983 | G44: 45988 | H44: 45989 | I44: 45989 | J44: 45990 | K44: 45991 | L44: 45991 | M44: Completed | N44: 45992 | O44: TCC Construction | P44: 16
A45: =A44+1 -> 39 | B45: AP87 | C45: DB+9 | D45: PS | F45: 45982 | G45: 45988 | H45: 45990 | I45: 45990 | J45: 45990 | K45: 45991 | L45: 45991 | M45: Completed | N45: 45994 | O45: Anchal Singh | P45: 25
A46: =A45+1 -> 40 | B46: AP99 | C46: DB+0 | D46: WET | F46: 45984 | G46: 45987 | H46: 45988 | I46: 45989 | J46: 45989 | K46: 45991 | L46: 45991 | M46: Completed | N46: 46001 | O46: Md. Latif | P46: 15
A47: =A46+1 -> 41 | B47: AP75 | C47: DB+9 | D47: FS | F47: 45986 | G47: 45989 | H47: 45990 | I47: 45990 | J47: 45990 | K47: 45992 | L47: 45992 | M47: Completed | N47: 45992 | O47: Ramesh | P47: 16
A48: =A47+1 -> 42 | B48: 82/2 | C48: DA+3 | D48: WET | F48: 45987 | G48: 45993 | H48: 45994 | I48: 45994 | J48: 45995 | K48: 45996 | L48: 45996 | M48: Completed | N48: 45999 | O48: Anchal Singh | P48: 25
A49: =A48+1 -> 43 | B49: AP100 | C49: DC+3 | D49: WET | F49: 45987 | G49: 45994 | H49: 45996 | I49: 45996 | J49: 45997 | K49: 45998 | L49: 45998 | M49: Completed | N49: 46001 | O49: Md. Latif | P49: 13
A50: =A49+1 -> 44 | B50: AP117 | C50: DB+0 | D50: WET | F50: 45990 | G50: 45995 | H50: 45996 | I50: 45997 | J50: 45997 | K50: 111743 | L50: 46000 | M50: Completed | N50: 46000 | O50: Sakrala Material | P50: 20
A51: =A50+1 -> 45 | B51: AP95 | C51: DC+3 | D51: WET | F51: 45990 | G51: 45996 | H51: 45996 | I51: 45997 | J51: 45997 | K51: 45998 | L51: 45998 | M51: Completed | N51: 45998 | O51: MS Constructions | P51: 19
... A53: =A52+1 -> 47 | B53: AP103 | C53: DD+0 | D53: WET | F53: 45993 | G53: 46006 | H53: 46007 | I53: 46007 | J53: 46008 | K53: 46009 | L53: 46009 | M53: Completed | N53: 46003 | O53: Ikrar | P53: 11
A54: =A53+1 -> 48 | B54: 99/1 | C54: DA+9 | D54: WET | F54: 45992 | G54: 45994 | H54: 45996 | I54: 05-12-205 | J54: 45996 | K54: 45997 | L54: 45997 | M54: Completed | N54: 46002 | O54: Md. Latif | P54: 12
A55: =A54+1 -> 49 | B55: 82/1 | C55: DA+0 | D55: WET | F55: 45994 | G55: 45996 | H55: 45999 | I55: 46000 | J55: 46000 | K55: 46001 | L55: 46001 | M55: Completed | N55: 46002 | O55: Anchal Singh | P55: 25
A56: =A55+1 -> 50 | B56: 76/3 | C56: DA+3 | D56: WET | F56: 45994 | G56: 45994 | H56: 45994 | I56: 45994 | J56: 45995 | K56: 45997 | L56: 45997 | M56: Completed | N56: 45998 | O56: Ramesh | P56: 16
A57: =A56+1 -> 51 | B57: 77/2 | C57: DB+0 | D57: WET | F57: 45996 | G57: 45996 | H57: 45996 | I57: 45997 | J57: 45998 | K57: 46001 | L57: 46001 | M57: Completed | N57: 46003 | O57: Ramesh | P57: 16
A58: =A57+1 -> 52 | B58: AP106 | C58: DD+6 | D58: WET | F58: 45996 | G58: 46002 | H58: 46003 | I58: 46003 | J58: 46004 | K58: 46006 | L58: 46006 | M58: Completed | N58: 46008 | O58: Md. Latif | P58: 25
A59: =A58+1 -> 53 | B59: AP104 | C59: DB+0 | D59: WET | F59: 45996 | G59: 46002 | H59: 46002 | I59: 46003 | J59: 46003 | K59: 46004 | L59: 46004 | M59: Completed | N59: 46006 | O59: MS Hussain | P59: 12
A60: =A59+1 -> 54 | B60: AP135 | C60: DB+3 | D60: WET | F60: 45996 | G60: 45998 | H60: 46000 | I60: 46000 | J60: 46003 | K60: 46007 | L60: 46007 | M60: Completed | N60: 46011 | O60: Ram Sadotra | P60: 40
A61: =A60+1 -> 55 | B61: 135/1 | C61: DA+6 | D61: WET | F61: 45998 | G61: 46000 | H61: 46002 | I61: 46003 | J61: 46005 | K61: 46020 | L61: 46020 | M61: Completed | N61: 46025 | O61: Ram Sadotra | P61: 40 | Q61: Since farmers left water in the field work hampered since 14.12.25. Work restarted from 28.12.25 and completed on 29.12.25
A62: =A61+1 -> 56 | B62: 85/1 | C62: DA+9 | D62: WET | F62: 45997 | G62: 46003 | H62: 46005 | I62: 46005 | J62: 46006 | K62: 46007 | L62: 46007 | M62: Completed | N62: 46012 | O62: Anchal Singh | P62: 25
A63: =A62+1 -> 57 | B63: 106/1 | C63: DA+0 | D63: WET | F63: 46001 | G63: 46005 | H63: 46007 | I63: 46007 | J63: 46007 | K63: 46008 | L63: 46008 | M63: Completed | N63: 46013 | O63: Md. Latif | P63: 25
A64: =A63+1 -> 58 | B64: 136/1 | C64: DA+3 | D64: WET | F64: 46002 | G64: 46003 | H64: 46006 | I64: 46006 | J64: 46008 | K64: 46010 | L64: 46010 | M64: Completed | N64: 46015 | O64: Ram Sadotra | P64: 40
A65: =A64+1 -> 59 | B65: 130/2 | C65: DA+0 | D65: WET | F65: 46003 | G65: 46006 | H65: 46006 | I65: 46006 | J65: 46006 | K65: 46008 | L65: 46008 | M65: Completed | N65: 46011 | O65: MS Constructions | P65: 20
A66: =A65+1 -> 60 | B66: AP85 | C66: DB+0 | D66: WET | F66: 46003 | G66: 46009 | H66: 46011 | I66: 46011 | J66: 46014 | K66: 46015 | L66: 46015 | M66: Completed | N66: 46017 | O66: Anchal Singh | P66: 25
A67: =A66+1 -> 61 | B67: 135/2 | C67: DA+3 | D67: WET | F67: 46004 | G67: 46005 | H67: 46007 | I67: 46008 | J67: 46009 | K67: 46012 | L67: 46012 | M67: Completed | N67: 46016 | O67: Ram Sadotra | P67: 40
A68: =A67+1 -> 62 | B68: 77/1 | C68: DA+3 | D68: WET | F68: 46004 | G68: 46005 | H68: 46005 | I68: 46005 | J68: 46006 | K68: 46007 | L68: 46007 | M68: Completed | N68: 46009 | O68: Ramesh | P68: 16
A69: =A68+1 -> 63 | B69: 102/1 | C69: DA+6 | D69: WET | F69: 46005 | G69: 46008 | H69: 46008 | I69: 46008 | J69: 46008 | K69: 46009 | L69: 46009 | M69: Completed | N69: 46009 | O69: MS Hussain | P69: 12
A70: =A69+1 -> 64 | B70: 130/1 | C70: DA+0 | D70: WET | F70: 46007 | G70: 46008 | H70: 46009 | I70: 46010 | J70: 46010 | K70: 46011 | L70: 46011 | M70: Completed | N70: 46011 | O70: MS Constructions | P70: 20
A71: =A70+1 -> 65 | B71: AP80 | C71: DD+0 | D71: PS | F71: 46007 | G71: 46012 | H71: 46013 | I71: 46013 | J71: 46014 | K71: 46016 | L71: 46016 | M71: Completed | N71: 46017 | O71: Ramesh | P71: 16
A72: =A71+1 -> 66 | B72: 116/1 | C72: DA+0 | D72: WET | F72: 46008 | G72: 46009 | H72: 46010 | I72: 46010 | J72: 46010 | K72: 46011 | L72: 46011 | M72: Completed | N72: 46012 | O72: Md. Latif | P72: 25
A73: =A72+1 -> 67 | B73: 156/4 | C73: DA+0 | D73: WET | F73: 46009 | G73: 46012 | H73: 46012 | I73: 46016 | J73: 46016 | K73: 46017 | L73: 46017 | M73: Completed | N73: 46025 | O73: Md. Latif | P73: 25
... A108: =A107+1 -> 102 | B108: AP92 | C108: DD+25 | D108: PS | F108: 46043 | G108: 46061 | H108: 46062 | I108: 46062 | J108: 46063 | K108: 46066 | L108: 46066 | M108: Completed | N108: 46070 | O108: Anchal Singh | P108: 20
A109: =A108+1 -> 103 | B109: 71/2 | C109: DA+6 DA+9 | D109: WET | F109: 46040 | G109: 46042 | H109: 46042 | I109: 46042 | J109: 46042 | K109: 46043 | L109: 46043 | M109: Completed | N109: 46044 | O109: Ramesh | P109: 16 | Q109: Loc: 71/2 -recasted with DA+9 Started : 11-2-26 & Completed : 12-2-26
A110: =A109+1 -> 104 | B110: 151/1 | C110: DA+0 | D110: WET | F110: 46040 | G110: 46044 | H110: 46052 | I110: 46052 | J110: 46053 | K110: 46053 | L110: 46053 | M110: Completed | N110: 46054 | O110: Ms. Hussain | P110: 13
A111: =A110+1 -> 105 | B111: 69/1 | C111: DA+0 | D111: FS | F111: 46040 | G111: 46044 | H111: 46044 | I111: 46044 | J111: 46044 | K111: 46049 | L111: 46049 | M111: Completed | N111: 46072 | O111: Sufiyan Ali | P111: 25
A112: =A111+1 -> 106 | B112: AP139 | C112: DB+0 | D112: WET | F112: 46042 | G112: 46057 | H112: 46058 | I112: 46058 | J112: 46058 | K112: 46059 | L112: 46059 | M112: Completed | N112: 46061 | O112: Ram Sadotra | P112: 40
A113: =A112+1 -> 107 | B113: 155/2 | C113: DA+0 | D113: WET | F113: 46042 | G113: 46051 | H113: 46051 | I113: 46051 | J113: 46052 | K113: 46052 | L113: 46052 | M113: Completed | N113: 46052 | O113: Md. Latif | P113: 25
A114: =A113+1 -> 108 | B114: 115/1 | C114: DA+6 | D114: WET | F114: 46043 | G114: 46052 | H114: 46052 | I114: 46052 | J114: 46053 | K114: 46053 | L114: 46053 | M114: Completed | N114: 46055 | O114: Sakrala Material | P114: 20
A115: =A114+1 -> 109 | B115: 136/2 | C115: DA+3 | D115: WET | F115: 46044 | G115: 46059 | H115: 46060 | I115: 46060 | J115: 46063 | K115: 46064 | L115: 46064 | M115: Completed | N115: 46068 | O115: Ram Sadotra | P115: 40
A116: =A115+1 -> 110 | B116: 155/3 | C116: DA+0 | D116: WET | F116: 46045 | G116: 46052 | H116: 46053 | I116: 46053 | J116: 46053 | K116: 46053 | L116: 46053 | M116: Completed | N116: 46058 | O116: Md. Latif | P116: 25
A117: =A116+1 -> 111 | B117: AP97 | C117: DD+3 | D117: WET | F117: 46051 | G117: 46059 | H117: 46059 | I117: 46059 | J117: 46060 | K117: 46061 | L117: 46061 | M117: Completed | N117: 46060 | O117: Sufiyan Ali | P117: 20
A118: =A117+1 -> 112 | B118: AP155 | C118: DD+0 | D118: WET | F118: 46053 | G118: 46059 | H118: 46060 | I118: 46060 | J118: 46062 | K118: 46062 | L118: 46062 | M118: Completed | N118: 46063 | O118: Md. Latif | P118: 25
A119: =A118+1 -> 113 | B119: 151/2 | C119: DA+3 | D119: WET | F119: 46056 | G119: 46059 | H119: 46059 | I119: 46059 | J119: 46059 | K119: 46060 | L119: 46060 | M119: Completed | N119: 46060 | O119: Ms. Hussain | P119: 13
A120: =A119+1 -> 114 | B120: 152/4 | C120: DA+0 | D120: WET | F120: 46057 | G120: 45327 | H120: 46063 | I120: 46063 | J120: 46064 | K120: 46065 | L120: 46065 | M120: Completed | N120: 46067 | O120: Ram Sadotra | P120: 40
A121: =A120+1 -> 115 | B121: AP156 | C121: DC+0 | D121: WET | F121: 46058 | G121: 46066 | H121: 46066 | I121: 46066 | J121: 46067 | K121: 46067 | L121: 46067 | M121: Completed | N121: 46068 | O121: Md. Latif | P121: 25
... A162: =A161+1 -> 156 | B162: 65/2 | C162: DA+6 | D162: PS(SD) | F162: 46111 | G162: 46116 | H162: 46118 | I162: 46118 | J162: 46118 | K162: 46119 | L162: 46119 | M162: Completed | N162: 46122 | O162: Sufiyan Ai | P162: 10
A163: =A162+1 -> 157 | B163: AP59 | C163: DD+6 | D163: PS(SD) | F163: 46123 | G163: 46133 | H163: 46133 | I163: 46137 | J163: 46137 | K163: 46139 | L163: 46139 | M163: Completed | O163: Sufiyan Ai | P163: 13
A164: =A163+1 -> 158 | B164: AP165 | C164: DB+6 1MRC | D164: FS | F164: 46116 | G164: 46129 | H164: 46130 | I164: 46130 | J164: 46131 | K164: 46134 | L164: 46134 | M164: Completed | N164: 46146 | O164: Ram Sadotra | P164: 15
A165: =A164+1 -> 159 | B165: 55/1 | C165: DA+6 | D165: PS(SD) | F165: 46123 | G165: 46138 | H165: 46138 | I165: 46138 | J165: 46138 | K165: 46140 | L165: 46140 | M165: Completed | N165: 46143 | O165: Wani Const | P165: 8
A166: =A165+1 -> 160 | B166: AP61 | C166: DC+0 | D166: PS(SD) | F166: 46120 | G166: 46127 | H166: 46130 | I166: 46130 | J166: 46130 | K166: 46133 | L166: 46133 | M166: Completed | N166: 46149 | O166: Sufiyan Ali | P166: 12
A167: =A166+1 -> 161 | B167: AP126 | C167: DB+0 | D167: WET | F167: 46118 | G167: 46124 | H167: 46125 | I167: 46125 | J167: 46126 | K167: 46127 | L167: 46127 | M167: Completed | N167: 46127 | O167: MS Constructions | P167: 16
A168: =A167+1 -> 162 | B168: AP142 | C168: DD+0 | D168: PS(SD) | F168: 46123 | G168: 46136 | H168: 46137 | I168: 46137 | J168: 46139 | K168: 46141 | L168: 46141 | M168: Completed | N168: 46143 | O168: MS Hussain | P168: 12
A169: =A168+1 -> 163 | B169: AP166 | C169: DB+6 2MRC | D169: FS | F169: 46130 | G169: 46137 | H169: 46138 | I169: 46138 | J169: 46141 | K169: 46142 | L169: 46142 | M169: Completed | N169: 46146 | O169: Ram Sadotra | P169: 12
A170: =A169+1 -> 164 | B170: AP123 | C170: DC+0 | D170: WET | F170: 46126 | G170: 46135 | H170: 46136 | I170: 46136 | J170: 46137 | K170: 46138 | L170: 46138 | M170: Completed | N170: 46138 | O170: MS Constructions | P170: 16
